Workbook

Sheet Assumptions
A1: SPACEX MODEL — ASSUMPTIONS
A2: All inputs blue text. One source of truth.
A4: ═══ ALLOCATOR IN ═══
A6: Section I — From Central Allocator Module | B6: Placeholders pending live links. | C6: All values blue text.
A7: Parameter | B7: 2025 | C7: 2026 | D7: 2027 | E7: 2028 | F7: 2029 | G7: 2030 | H7: 2031 | I7: 2032 | J7: 2033 | K7: 2034 | L7: 2035 | M7: 2036 | N7: 2037 | O7: 2038 | P7: 2039 | Q7: 2040 | R7: 2041 | S7: 2042 | T7: 2043 | U7: 2044 | V7: 2045 | W7: 2046 | X7: 2047 | Y7: 2048 | Z7: 2049 | AA7: 2050
A8: Total Starlink Allocation ($mm) | B8: 10360 | C8: 15000 | D8: 15000 | E8: 20000 | F8: 60000 | G8: 75000 | H8: 90000 | I8: 105000 | J8: 120000 | K8: 120000 | L8: 120000 | M8: 120000 | N8: 120000 | O8: 120000 | P8: 120000 | Q8: 120000 | R8: 120000 | S8: 120000 | T8: 120000 | U8: 120000 | V8: 120000 | W8: 120000 | X8: 120000 | Y8: 120000 | Z8: 120000 | AA8: 120000
D11: 2025 | E11: 2026 | F11: 2027 | G11: 2028 | H11: 2029 | I11: 2030 | J11: 2031 | K11: 2032 | L11: 2033 | M11: 2034 | N11: 2035 | O11: 2036 | P11: 2037 | Q11: 2038 | R11: 2039 | S11: 2040 | T11: 2041 | U11: 2042 | V11: 2043 | W11: 2044 | X11: 2045 | Y11: 2046 | Z11: 2047 | AA11: 2048 | AB11: 2049 | AC11: 2050
C12: 2026 | D12: 2027 | E12: 2028 | F12: 2029 | G12: 2030 | H12: 2031 | I12: 2032 | J12: 2033 | K12: 2034 | L12: 2035 | M12: 2036 | N12: 2037 | O12: 2038 | P12: 2039 | Q12: 2040 | R12: 2041 | S12: 2042 | T12: 2043 | U12: 2044 | V12: 2045 | W12: 2046 | X12: 2047 | Y12: 2048 | Z12: 2049 | AA12: 2050
C13: =Starlink!E212 -> 5 | D13: =Starlink!F212 -> 5 | E13: =Starlink!G212 -> 5 | F13: =Starlink!H212 -> 5 | G13: =Starlink!I212 -> 5 | H13: =Starlink!J212 -> 5 | I13: =Starlink!K212 -> 5 | J13: =Starlink!L212 -> 5 | ... AA13: =Starlink!AC212 -> 5
C14: =Starlink!E213 -> 83.452381 | D14: =Starlink!F213 -> 78.90365 | E14: =Starlink!G213 -> 72.854036 | F14: =Starlink!H213 -> 63.267853 | G14: =Starlink!I213 -> 47.22347 | H14: =Starlink!J213 -> 45.7846 | I14: =Starlink!K213 -> 41.693873 | J14: =Starlink!L213 -> 41.979841 | ... AA14: =Starlink!AC213 -> 137.71368
C15: =Starlink!E214 -> 0 | D15: =Starlink!F214 -> 0 | E15: =Starlink!G214 -> 0 | F15: =Starlink!H214 -> 0 | G15: =Starlink!I214 -> 0 | H15: =Starlink!J214 -> 0 | I15: =Starlink!K214 -> 0 | J15: =Starlink!L214 -> 0 | ... AA15: =Starlink!AC214 -> 0
C16: =Starlink!E215 -> 1.7854563 | D16: =Starlink!F215 -> 1.9222834 | E16: =Starlink!G215 -> 2.0657765 | F16: =Starlink!H215 -> -1 | G16: =Starlink!I215 -> -1 | H16: =Starlink!J215 -> -1 | I16: =Starlink!K215 -> -1 | J16: =Starlink!L215 -> -1 | ... AA16: =Starlink!AC215 -> -1
C17: =Starlink!E209 -> 1409.7394 | D17: =Starlink!F209 -> 1212.4176 | E17: =Starlink!G209 -> 1166.8041 | F17: =Starlink!H209 -> 1135.9029 | G17: =Starlink!I209 -> 1112.0746 | H17: =Starlink!J209 -> 1098.9828 | I17: =Starlink!K209 -> 1102.9602 | J17: =Starlink!L209 -> 1115.1582 | ... AA17: =Starlink!AC209 -> 9856.3689
C18: =Starlink!E210 -> 1404.3658 | D18: =Starlink!F210 -> 1264.8119 | E18: =Starlink!G210 -> 1239.6847 | F18: =Starlink!H210 -> 1158.8573 | G18: =Starlink!I210 -> 1128.4935 | H18: =Starlink!J210 -> 1110.0588 | I18: =Starlink!K210 -> 1105.6945 | J18: =Starlink!L210 -> 1110.3056 | ... AA18: =Starlink!AC210 -> 9856.3689
C19: =Starlink!E211 -> 10000000 | D19: =Starlink!F211 -> 10000000 | E19: =Starlink!G211 -> 10000000 | F19: =Starlink!H211 -> 10000000 | G19: =Starlink!I211 -> 10000000 | H19: =Starlink!J211 -> 10000000 | I19: =Starlink!K211 -> 10000000 | J19: =Starlink!L211 -> 10000000 | ... AA19: =Starlink!AC211 -> 10000000
C20: =Starlink!E203 -> 8644.6203 | D20: =Starlink!F203 -> 8679.9282 | E20: =Starlink!G203 -> 9262.2478 | F20: =Starlink!H203 -> 10062.166 | G20: =Starlink!I203 -> 9215.8283 | H20: =Starlink!J203 -> 9410.2408 | I20: =Starlink!K203 -> 9736.0823 | J20: =Starlink!L203 -> 10103.842 | ... AA20: =Starlink!AC203 -> 51648.21
C21: =Starlink!E204 -> 0.78919331 | D21: =Starlink!F204 -> 0.76745194 | E21: =Starlink!G204 -> 0.7683031 | F21: =Starlink!H204 -> 0.78034255 | G21: =Starlink!I204 -> 0.84908134 | H21: =Starlink!J204 -> 0.81061709 | I21: =Starlink!K204 -> 0.81526255 | J21: =Starlink!L204 -> 0.81793572 | ... AA21: =Starlink!AC204 -> 0.86749494
A23: ═══ MODULE ASSUMPTIONS ═══
A24: Section B — Satellite Specifications
A25: Parameter | B25: Base Case | C25: Min | D25: Max | E25: Note
A26: V2 Mini Mass (kg) | B26: 575 | C26: 575 | D26: 575 | E26: Fixed — no meaningful variance. Source: SpaceX 2024 Progress Report
A27: V3 Mass (kg) | B27: 2000 | C27: 1800 | D27: 2200 | E27: Source: SpaceX 2024 Progress Report
A28: V2 Mini Bandwidth per Sat — BB (Gbps) | B28: 96 | C28: 96 | D28: 96 | E28: Fixed V2 Mini broadband bandwidth. Source: SpaceX 2024 Progress Report
A29: V2 Mini Bandwidth per Sat — DTC (Gbps) | B29: 0.2 | C29: 2 | D29: 4.5 | E29: From DTC Coverage Gap model — constrained by smartphone radio link budget
A30: V3 Bandwidth per Sat — BB base year (Gbps) | B30: 1000 | C30: 1000 | D30: 1000 | E30: Base year 2025; improves via Wright's Law. Source: SpaceX 2024 Progress Report
A31: V3 Bandwidth per Sat — DTC (Gbps) | B31: 2.75 | C31: 1 | D31: 5 | E31: Placeholder — update from DTC Coverage Gap model when V3 DTC specs available
A32: Satellite Useful Life — V2 Mini (Years) | B32: 5 | C32: 4 | D32: 6 | E32: Source: SpaceX constellation operations data
A33: Satellite Useful Life — V3 (Years) | B33: 5 | C33: 4 | D33: 7 | E33: V3 may have longer life — upper range extended
A34: Capex Lag (Years) | B34: 1 | C34: 1 | D34: 1 | E34: Budget deployed in Year N activates satellites in Year N+1. Fixed at 1 year.
A36: Section C — Wright's Law Parameters
A37: Parameter | B37: Base Case | C37: Min | D37: Max | E37: Note
A38: Satellite Cost per kg — base year ($/kg) | B38: 650 | C38: 600 | D38: 750 | E38: SpaceX 2024 baseline
A39: Satellite Cost per kg — learning rate | B39: 0.05 | C39: 0.07 | D39: 0.17 | E39: 12% reduction per cumulative doubling
A40: V3 Bandwidth per Sat — learning rate | B40: 0.05 | C40: 0.07 | D40: 0.17 | E40: 12% improvement per cumulative doubling
A41: Cumulative sats at base year | B41: 7486 | C41: 7486 | D41: 7486 | E41: From historical constellation data
A42: Satellite Cost floor ($/kg) | B42: 400 | C42: 300 | D42: 500
A43: V3 Bandwidth cap (Gbps) | B43: 5000 | C43: 3000 | D43: 7000
A44: V2 Mini Cost per kg — base year ($/kg) | B44: 650 | C44: 600 | D44: 750 | E44: Same baseline as V3. Source: SpaceX 2024
A45: V2 Mini Cost per kg — learning rate | B45: 0.05 | C45: 0.03 | D45: 0.1 | E45: Shared manufacturing learning curve with V3
A46: V2 Mini Cost floor ($/kg) | B46: 400 | C46: 300 | D46: 500 | E46: Same floor as V3
A47: V2 Mini and V3 share the same cumulative production base (Cumulative sats at base year row above) as they are produced in the same manufacturing pipeline.
A49: Section D — Revenue Parameters
A50: Parameter | B50: Base Case | C50: Min | D50: Max | E50: Note
A51: Starshield Reserved % — start | B51: 0.0257 | C51: 0.015 | D51: 0.04
A52: Starshield Reserved % — floor | B52: 0.0001 | C52: 0.005 | D52: 0.02
A53: Starshield Reserved % — decay rate | B53: 1 | C53: 0.15 | D53: 0.4
A54: Starshield Rev per Gbps — base year ($/Gbps) | B54: 167421 | C54: 120000 | D54: 220000
A55: Starshield Rev per Gbps — decay rate | B55: 0.05 | C55: 0.03 | D55: 0.1
A56: TAM Inflation Rate (annual) | B56: 0.025 | C56: 0.01 | D56: 0.05 | E56: Annual price uplift on satellite bandwidth pricing (reflects inflation in end-user willingness to pay)
A57: GNI per Capita Growth Rate (annual) | B57: 0.03 | C57: 0.01 | D57: 0.06 | E57: Proxy for rising global purchasing power — expands accessible TAM over time
A59: Section E — Operating Expenses
A60: Parameter | B60: Base Case | C60: Min | D60: Max | E60: Note
A61: R&D % of Revenue — start | B61: 0.159 | C61: 0.12 | D61: 0.2 | E61: 2025 rate. Source: SpaceX_Valuation_Model_Q4_25_CLEANUP.xlsx row 172
A62: R&D % of Revenue — floor | B62: 0.05 | C62: 0.03 | D62: 0.08 | E62: Reached by 2030 and held flat. Source: old model
A63: R&D % of Revenue — decay rate | B63: 0.206 | C63: 0.15 | D63: 0.3 | E63: Annual proportional decay: rate × (1 − 0.206) each year. Reaches floor ~2030. Source: old model CAGR
A64: SG&A % of Revenue — 2025 start | B64: 0.102 | C64: 0.08 | D64: 0.13 | E64: Source: old model row 176
A65: SG&A % of Revenue — ceiling | B65: 0.115 | C65: 0.1 | D65: 0.14 | E65: Reached by 2030 and held flat. Source: old model
A66: SG&A % of Revenue — growth rate | B66: 0.024 | C66: 0.01 | D66: 0.04 | E66: Annual proportional growth: rate × (1 + 0.024) each year until ceiling. Source: old model CAGR
A68: Section F — CapEx Parameters
A69: Parameter | B69: Base Case | C69: Min | D69: Max | E69: Note
A70: Satellite Dep per kg — base year ($/kg/yr) | B70: 128.8 | C70: 110 | D70: 150
A71: Satellite Dep per kg — annual decay rate | B71: 0.01 | C71: 0.005 | D71: 0.02
A72: Constellation Depreciation in COGS (%) | B72: 1 | C72: 1 | D72: 1 | E72: 100% of satellite depreciation treated as COGS not below-EBITDA. Adjust if partial treatment required.
A73: Facility CapEx per satellite — base year ($) | B73: 90650 | C73: 70000 | D73: 120000 | E73: Extracted from 2025 model data
A74: Facility CapEx — learning rate | B74: 0.1 | C74: 0.05 | D74: 0.15
A76: Section J — BB/DTC Allocation Engine Parameters | B76: Controls the sigmoid-based internal split of capex budget between Broadband and DTC satellites.
A77: Parameter | B77: Base Case | C77: Min | D77: Max | E77: Note
A78: Allocation Floor (min share per segment) | B78: 0.15 | C78: 0.1 | D78: 0.25 | E78: Neither BB nor DTC can receive less than this share of the satellite deployment budget regardless of IRR differential.
A79: Allocation Ceiling (max share per segment) | B79: 0.85 | C79: 0.75 | D79: 0.9 | E79: Neither BB nor DTC can receive more than this share regardless of IRR differential.
A80: Sigmoid Steepness (k) | B80: 3 | C80: 1 | D80: 10 | E80: Controls how sharply the allocation responds to IRR differential. Higher k = more aggressive tilt toward higher-IRR segment.
A81: Forward IRR Look-ahead (Years) | B81: 2 | C81: 1 | D81: 3 | E81: Number of years ahead used to compute forward IRR for trajectory signal.
A82: Forward IRR Weight in Allocation | B82: 0.7 | C82: 0.1 | D82: 0.5 | E82: Weight given to forward IRR vs spot IRR when computing the blended IRR used in sigmoid allocation. Remainder weight goes to spot IRR.
A84: ═══ CONSTELLATION STATE ═══
A86: Section K — Constellation Opening Balances and Deorbit Parameters
A87: Hardcoded from Mach33 Starlink tracking data (SpaceX_BFM_11_24_-_Starlink_Data.csv) and old integrated model. Opening balances represent end-2025 actuals. Model is budget-driven from 2026 onward.
A89: K1: End-2025 Actuals (opening balance for 2026)
A90: Parameter | B90: Value | C90: Note
A91: V2 Mini BB Active Sats — end 2025 | B91: 5246 | C91: Source: Mach33 Starlink tracking data Dec 2025
A92: V2 Mini DTC Active Sats — end 2025 | B92: 650 | C92: Source: Mach33 Starlink tracking data Dec 2025
A93: V2 Mini BB Bandwidth — end 2025 (Gbps) | B93: 503616 | C93: 5,246 sats × 96 Gbps/sat
A94: V2 Mini DTC Bandwidth — end 2025 (Gbps) | B94: 1936 | C94: 650 sats × 2.978 Gbps/sat
A95: Legacy V1/V1.5 Bandwidth — end 2025 (Gbps) | B95: 71888 | C95: Residual bandwidth from pre-V2 Mini constellation. Declines to zero by end-2028 as legacy sats deorbit. Source: 577,440 total minus V2 Mini derived
A96: V2 Mini BB Sats Launched in 2025 | B96: 2987 | C96: Source: Mach33 Starlink tracking data — annual total from monthly data
A97: V2 Mini DTC Sats Launched in 2025 | B97: 182 | C97: Source: Mach33 Starlink tracking data — annual total from monthly data
A98: V3 BB Sats Launched in 2025 | B98: 0 | C98: Starship not yet operational for Starlink in 2025
A99: V3 DTC Sats Launched in 2025 | B99: 0 | C99: Starship not yet operational for Starlink in 2025
A101: K2: Legacy Bandwidth Runoff Schedule
A102: Parameter | B102: 2025 | C102: 2026 | D102: 2027 | E102: 2028 | F102: 2029 | G102: 2030 | H102: 2031 | I102: 2032 | J102: 2033 | K102: 2034 | L102: 2035 | M102: 2036 | N102: 2037 | O102: 2038 | P102: 2039 | Q102: 2040
A103: Legacy V1/V1.5 Active Bandwidth (Gbps) | B103: 71888 | C103: 53916 | D103: 35944 | E103: 17972 | F103: 0 | G103: 0 | H103: 0 | I103: 0 | J103: 0 | K103: 0 | L103: 0 | M103: 0 | N103: 0 | O103: 0 | P103: 0 | Q103: 0
A104: Straight-line runoff of legacy V1/V1.5 bandwidth over 4 years. Hardcoded — not formula-driven. Update if actual deorbit schedule differs.
A106: K3: Deorbit Mechanic Parameters
A107: Parameter | B107: Base Case | C107: Min | D107: Max | E107: Note
A108: V2 Mini BB Deorbit Lag (Years) | B108: 5 | C108: 4 | D108: 6 | E108: Sats launched in Year N deorbit in Year N + useful life. Must match Satellite Useful Life — V2 Mini
A109: V3 BB Deorbit Lag (Years) | B109: 5 | C109: 4 | D109: 7 | E109: Must match Satellite Useful Life — V3
A110: V2 Mini DTC Deorbit Lag (Years) | B110: 5 | C110: 4 | D110: 6 | E110: Must match V2 Mini useful life
A111: V3 DTC Deorbit Lag (Years) | B111: 5 | C111: 4 | D111: 7 | E111: Must match V3 useful life
A112: Bandwidth Removed per Deorbited V2 Mini BB Sat (Gbps) | B112: 96 | C112: 96 | D112: 96 | E112: Fixed — same as launch bandwidth. V2 Mini BB bandwidth does not improve over time
A113: Bandwidth Removed per Deorbited V2 Mini DTC Sat (Gbps) | B113: 2.978 | C113: 2.978 | D113: 2.978 | E113: Fixed
A114: Bandwidth Removed per Deorbited V3 BB Sat (Gbps) | B114: 1000 | C114: 1000 | D114: 1000 | E114: Use launch-year bandwidth, not current-year. Base case uses 2025 base year figure — Phase 4 wiring will use INDEX/MATCH lookback
A115: Bandwidth Removed per Deorbited V3 DTC Sat (Gbps) | B115: 5 | C115: 5 | D115: 5 | E115: Use launch-year bandwidth
...

Sheet Allocator
A1: CENTRAL ALLOCATOR
A2: Three-layer engine: capital / Starship capacity / cash sweep
A4: Year | D4: 2025 | E4: 2026 | F4: 2027 | G4: 2028 | H4: 2029 | I4: 2030 | J4: 2031 | K4: 2032 | L4: 2033 | M4: 2034 | N4: 2035 | O4: 2036 | P4: 2037 | Q4: 2038 | R4: 2039 | S4: 2040 | T4: 2041 | U4: 2042 | V4: 2043 | W4: 2044 | X4: 2045 | Y4: 2046 | Z4: 2047 | AA4: 2048 | AB4: 2049 | AC4: 2050
A6: LAYER 1 — CAPITAL ALLOCATION
A8: [Legacy R8 — was hardcoded capital pool ramp; superseded by R117 BoY tracker]
A10: ▸ Outputs: Capital allocation per module ($mm)
A11: Launch | D11: =MIN(D128,D$117*D161) -> 240 | E11: =MIN(E128,E$117*E161) -> 236.45318 | F11: =MIN(F128,F$117*F161) -> 238.63025 | G11: =MIN(G128,G$117*G161) -> 208.55973 | H11: =MIN(H128,H$117*H161) -> 178.41674 | I11: =MIN(I128,I$117*I161) -> 148.88105 | J11: =MIN(J128,J$117*J161) -> 119.11335 | K11: =MIN(K128,K$117*K161) -> 89.619636 | ... AC11: =MIN(AC128,AC$117*AC161) -> 0.12138466
A12: Starlink | C12: V9 baseline hardcode — Total Starlink Allocation from Assumptions!B8:J8, held flat 2034+. Replaced by live Allocator output in Sprint 7. | D12: =MIN(D129,D$117*D162) -> 5060.5888 | E12: =MIN(E129,E$117*E162) -> 5517.4058 | F12: =MIN(F129,F$117*F162) -> 28516.757 | G12: =MIN(G129,G$117*G162) -> 28614.113 | H12: =MIN(H129,H$117*H162) -> 30063.004 | I12: =MIN(I129,I$117*I162) -> 27275.694 | J12: =MIN(J129,J$117*J162) -> 29960.392 | K12: =MIN(K129,K$117*K162) -> 31175.135 | ... AC12: =MIN(AC129,AC$117*AC162) -> 100000
A13: ODC | D13: =MIN(D130,D$117*D163) -> 0 | E13: =MIN(E130,E$117*E163) -> 0 | F13: =MIN(F130,F$117*F163) -> 0 | G13: =MIN(G130,G$117*G163) -> 0 | H13: =MIN(H130,H$117*H163) -> 0 | I13: =MIN(I130,I$117*I163) -> 0 | J13: =MIN(J130,J$117*J163) -> 0 | K13: =MIN(K130,K$117*K163) -> 0 | ... AC13: =MIN(AC130,AC$117*AC163) -> 0
A14: AI Stack | D14: =MIN(D131,D$117*D164) -> 0 | E14: =MIN(E131,E$117*E164) -> 0 | F14: =MIN(F131,F$117*F164) -> 0 | G14: =MIN(G131,G$117*G164) -> 0 | H14: =MIN(H131,H$117*H164) -> 0 | I14: =MIN(I131,I$117*I164) -> 0 | J14: =MIN(J131,J$117*J164) -> 0 | K14: =MIN(K131,K$117*K164) -> 0 | ... AC14: =MIN(AC131,AC$117*AC164) -> 0
A15: Lunar / Mars | D15: 0 | E15: 0 | F15: 0 | G15: 0 | H15: 0 | I15: 0 | J15: 0 | K15: 0 | L15: 0 | M15: 0 | N15: 0 | O15: 0 | P15: 0 | Q15: 0 | R15: 0 | S15: 0 | T15: 0 | U15: 0 | V15: 0 | W15: 0 | X15: 0 | Y15: 0 | Z15: 0 | AA15: 0 | AB15: 0 | AC15: 0
A16: Total allocated | D16: =SUM(D11:D15) -> 5300.5888 | E16: =SUM(E11:E15) -> 5753.859 | F16: =SUM(F11:F15) -> 28755.387 | G16: =SUM(G11:G15) -> 28822.673 | H16: =SUM(H11:H15) -> 30241.421 | I16: =SUM(I11:I15) -> 27424.575 | J16: =SUM(J11:J15) -> 30079.505 | K16: =SUM(K11:K15) -> 31264.755 | ... AC16: =SUM(AC11:AC15) -> 100000.12
A17: [Spec 09: sigmoid bounds queue at gate by construction; residual diagnostic only — Patch L second-term retired] | D17: =MAX(0, D117 - D16) -> 585.59866 | E17: =MAX(0, E117 - E16) -> 642.8614 | F17: =MAX(0, F117 - F16) -> 10843.263 | G17: =MAX(0, G117 - G16) -> 17403.54 | H17: =MAX(0, H117 - H16) -> 25142.047 | I17: =MAX(0, I117 - I16) -> 38345.228 | J17: =MAX(0, J117 - J16) -> 45646.356 | K17: =MAX(0, K117 - K16) -> 55002.324 | ... AC17: =MAX(0, AC117 - AC16) -> 220286.84
A19: ▸ Helper: Floor allocations ($mm) — Pass 1
A20: Launch floor
A21: Starlink floor
A22: ODC floor
A23: AI Stack floor
A24: Total floor allocated
A25: Remainder pool ($mm)
A26: Floor pro-rate scalar (≤1; <1 if floors > pool)
A27: ▸ Helper: Effective IRR for sigmoid (prior-year, floored at 0, masked)
A28: Launch effective IRR
A29: Starlink effective IRR
A30: ODC effective IRR
... A39: ▸ Inputs read: per-module Blended IRR
A40: Launch Blended IRR | D40: =INDEX('Customer Launch'!D:D,MATCH("Blended IRR",'Customer Launch'!$A:$A,0)) -> 2.2846788 | E40: =INDEX('Customer Launch'!E:E,MATCH("Blended IRR",'Customer Launch'!$A:$A,0)) -> 2.5252453 | F40: =INDEX('Customer Launch'!F:F,MATCH("Blended IRR",'Customer Launch'!$A:$A,0)) -> 4.1886093 | G40: =INDEX('Customer Launch'!G:G,MATCH("Blended IRR",'Customer Launch'!$A:$A,0)) -> 5.5958579 | H40: =INDEX('Customer Launch'!H:H,MATCH("Blended IRR",'Customer Launch'!$A:$A,0)) -> 6.9897191 | I40: =INDEX('Customer Launch'!I:I,MATCH("Blended IRR",'Customer Launch'!$A:$A,0)) -> 9.5937922 | J40: =INDEX('Customer Launch'!J:J,MATCH("Blended IRR",'Customer Launch'!$A:$A,0)) -> 10.603868 | K40: =INDEX('Customer Launch'!K:K,MATCH("Blended IRR",'Customer Launch'!$A:$A,0)) -> 12.082096 | L40: =INDEX('Customer Launch'!L:L,MATCH("Blended IRR",'Customer Launch'!$A:$A,0)) -> 13.037917 | M40: =INDEX('Customer Launch'!M:M,MATCH("Blended IRR",'Customer Launch'!$A:$A,0)) -> 13.10238 | N40: =INDEX('Customer Launch'!N:N,MATCH("Blended IRR",'Customer Launch'!$A:$A,0)) -> 13.151414 | O40: =INDEX('Customer Launch'!O:O,MATCH("Blended IRR",'Customer Launch'!$A:$A,0)) -> 12.75675 | P40: =INDEX('Customer Launch'!P:P,MATCH("Blended IRR",'Customer Launch'!$A:$A,0)) -> 12.297593 | Q40: =INDEX('Customer Launch'!Q:Q,MATCH("Blended IRR",'Customer Launch'!$A:$A,0)) -> 11.793723 | R40: =INDEX('Customer Launch'!R:R,MATCH("Blended IRR",'Customer Launch'!$A:$A,0)) -> 11.261072 | S40: =INDEX('Customer Launch'!S:S,MATCH("Blended IRR",'Customer Launch'!$A:$A,0)) -> 10.712369 | T40: =INDEX('Customer Launch'!T:T,MATCH("Blended IRR",'Customer Launch'!$A:$A,0)) -> 10.157698 | U40: =INDEX('Customer Launch'!U:U,MATCH("Blended IRR",'Customer Launch'!$A:$A,0)) -> 9.6049632 | V40: =INDEX('Customer Launch'!V:V,MATCH("Blended IRR",'Customer Launch'!$A:$A,0)) -> 9.0602807 | W40: =INDEX('Customer Launch'!W:W,MATCH("Blended IRR",'Customer Launch'!$A:$A,0)) -> 8.5283083 | X40: =INDEX('Customer Launch'!X:X,MATCH("Blended IRR",'Customer Launch'!$A:$A,0)) -> 8.0125157 | Y40: =INDEX('Customer Launch'!Y:Y,MATCH("Blended IRR",'Customer Launch'!$A:$A,0)) -> 7.5154103 | Z40: =INDEX('Customer Launch'!Z:Z,MATCH("Blended IRR",'Customer Launch'!$A:$A,0)) -> 7.0387224 | AA40: =INDEX('Customer Launch'!AA:AA,MATCH("Blended IRR",'Customer Launch'!$A:$A,0)) -> 6.5835594 | AB40: =INDEX('Customer Launch'!AB:AB,MATCH("Blended IRR",'Customer Launch'!$A:$A,0)) -> 2.0261287 | AC40: =INDEX('Customer Launch'!AC:AC,MATCH("Blended IRR",'Customer Launch'!$A:$A,0)) -> 1.8934966
A41: Starlink Blended IRR | D41: =INDEX(Starlink!D:D,MATCH("Aggregate Blended IRR for Allocator (market-mix-weighted vehicle-level)",Starlink!$A:$A,0)) -> 5.656414 | E41: =INDEX(Starlink!E:E,MATCH("Aggregate Blended IRR for Allocator (market-mix-weighted vehicle-level)",Starlink!$A:$A,0)) -> 6.3255587 | F41: =INDEX(Starlink!F:F,MATCH("Aggregate Blended IRR for Allocator (market-mix-weighted vehicle-level)",Starlink!$A:$A,0)) -> 6.7191285 | G41: =INDEX(Starlink!G:G,MATCH("Aggregate Blended IRR for Allocator (market-mix-weighted vehicle-level)",Starlink!$A:$A,0)) -> 7.1326555 | H41: =INDEX(Starlink!H:H,MATCH("Aggregate Blended IRR for Allocator (market-mix-weighted vehicle-level)",Starlink!$A:$A,0)) -> 7.6162306 | I41: =INDEX(Starlink!I:I,MATCH("Aggregate Blended IRR for Allocator (market-mix-weighted vehicle-level)",Starlink!$A:$A,0)) -> 8.0757167 | J41: =INDEX(Starlink!J:J,MATCH("Aggregate Blended IRR for Allocator (market-mix-weighted vehicle-level)",Starlink!$A:$A,0)) -> 8.5796406 | K41: =INDEX(Starlink!K:K,MATCH("Aggregate Blended IRR for Allocator (market-mix-weighted vehicle-level)",Starlink!$A:$A,0)) -> 9.0887138 | L41: =INDEX(Starlink!L:L,MATCH("Aggregate Blended IRR for Allocator (market-mix-weighted vehicle-level)",Starlink!$A:$A,0)) -> 9.62441 | M41: =INDEX(Starlink!M:M,MATCH("Aggregate Blended IRR for Allocator (market-mix-weighted vehicle-level)",Starlink!$A:$A,0)) -> 10.188468 | N41: =INDEX(Starlink!N:N,MATCH("Aggregate Blended IRR for Allocator (market-mix-weighted vehicle-level)",Starlink!$A:$A,0)) -> 10.782793 | O41: =INDEX(Starlink!O:O,MATCH("Aggregate Blended IRR for Allocator (market-mix-weighted vehicle-level)",Starlink!$A:$A,0)) -> 11.409169 | P41: =INDEX(Starlink!P:P,MATCH("Aggregate Blended IRR for Allocator (market-mix-weighted vehicle-level)",Starlink!$A:$A,0)) -> 11.991885 | Q41: =INDEX(Starlink!Q:Q,MATCH("Aggregate Blended IRR for Allocator (market-mix-weighted vehicle-level)",Starlink!$A:$A,0)) -> 12.684043 | R41: =INDEX(Starlink!R:R,MATCH("Aggregate Blended IRR for Allocator (market-mix-weighted vehicle-level)",Starlink!$A:$A,0)) -> 13.380837 | S41: =INDEX(Starlink!S:S,MATCH("Aggregate Blended IRR for Allocator (market-mix-weighted vehicle-level)",Starlink!$A:$A,0)) -> 14.148853 | T41: =INDEX(Starlink!T:T,MATCH("Aggregate Blended IRR for Allocator (market-mix-weighted vehicle-level)",Starlink!$A:$A,0)) -> 11.308869 | U41: =INDEX(Starlink!U:U,MATCH("Aggregate Blended IRR for Allocator (market-mix-weighted vehicle-level)",Starlink!$A:$A,0)) -> 15.815296 | V41: =INDEX(Starlink!V:V,MATCH("Aggregate Blended IRR for Allocator (market-mix-weighted vehicle-level)",Starlink!$A:$A,0)) -> 16.719556 | W41: =INDEX(Starlink!W:W,MATCH("Aggregate Blended IRR for Allocator (market-mix-weighted vehicle-level)",Starlink!$A:$A,0)) -> 17.674224 | X41: =INDEX(Starlink!X:X,MATCH("Aggregate Blended IRR for Allocator (market-mix-weighted vehicle-level)",Starlink!$A:$A,0)) -> 17.577168 | Y41: =INDEX(Starlink!Y:Y,MATCH("Aggregate Blended IRR for Allocator (market-mix-weighted vehicle-level)",Starlink!$A:$A,0)) -> 18.578387 | Z41: =INDEX(Starlink!Z:Z,MATCH("Aggregate Blended IRR for Allocator (market-mix-weighted vehicle-level)",Starlink!$A:$A,0)) -> 19.160798 | AA41: =INDEX(Starlink!AA:AA,MATCH("Aggregate Blended IRR for Allocator (market-mix-weighted vehicle-level)",Starlink!$A:$A,0)) -> 20.249816 | AB41: =INDEX(Starlink!AB:AB,MATCH("Aggregate Blended IRR for Allocator (market-mix-weighted vehicle-level)",Starlink!$A:$A,0)) -> 5.2449687 | AC41: =INDEX(Starlink!AC:AC,MATCH("Aggregate Blended IRR for Allocator (market-mix-weighted vehicle-level)",Starlink!$A:$A,0)) -> 5.5819986
A42: ODC Blended IRR | D42: =INDEX(ODC!D:D, MATCH("Blended IRR", ODC!$A:$A, 0)) -> 0 | E42: =INDEX(ODC!E:E, MATCH("Blended IRR", ODC!$A:$A, 0)) -> 0 | F42: =INDEX(ODC!F:F, MATCH("Blended IRR", ODC!$A:$A, 0)) -> 0 | G42: =INDEX(ODC!G:G, MATCH("Blended IRR", ODC!$A:$A, 0)) -> 0 | H42: =INDEX(ODC!H:H, MATCH("Blended IRR", ODC!$A:$A, 0)) -> 0 | I42: =INDEX(ODC!I:I, MATCH("Blended IRR", ODC!$A:$A, 0)) -> 0 | J42: =INDEX(ODC!J:J, MATCH("Blended IRR", ODC!$A:$A, 0)) -> 0 | K42: =INDEX(ODC!K:K, MATCH("Blended IRR", ODC!$A:$A, 0)) -> 0 | L42: =INDEX(ODC!L:L, MATCH("Blended IRR", ODC!$A:$A, 0)) -> 0 | M42: =INDEX(ODC!M:M, MATCH("Blended IRR", ODC!$A:$A, 0)) -> 0 | N42: =INDEX(ODC!N:N, MATCH("Blended IRR", ODC!$A:$A, 0)) -> 0 | O42: =INDEX(ODC!O:O, MATCH("Blended IRR", ODC!$A:$A, 0)) -> 0 | P42: =INDEX(ODC!P:P, MATCH("Blended IRR", ODC!$A:$A, 0)) -> 0 | Q42: =INDEX(ODC!Q:Q, MATCH("Blended IRR", ODC!$A:$A, 0)) -> 0 | R42: =INDEX(ODC!R:R, MATCH("Blended IRR", ODC!$A:$A, 0)) -> 0 | S42: =INDEX(ODC!S:S, MATCH("Blended IRR", ODC!$A:$A, 0)) -> 0 | T42: =INDEX(ODC!T:T, MATCH("Blended IRR", ODC!$A:$A, 0)) -> 0 | U42: =INDEX(ODC!U:U, MATCH("Blended IRR", ODC!$A:$A, 0)) -> 0 | V42: =INDEX(ODC!V:V, MATCH("Blended IRR", ODC!$A:$A, 0)) -> 0 | W42: =INDEX(ODC!W:W, MATCH("Blended IRR", ODC!$A:$A, 0)) -> 0 | X42: =INDEX(ODC!X:X, MATCH("Blended IRR", ODC!$A:$A, 0)) -> 0 | Y42: =INDEX(ODC!Y:Y, MATCH("Blended IRR", ODC!$A:$A, 0)) -> 0 | Z42: =INDEX(ODC!Z:Z, MATCH("Blended IRR", ODC!$A:$A, 0)) -> 0 | AA42: =INDEX(ODC!AA:AA, MATCH("Blended IRR", ODC!$A:$A, 0)) -> 0 | AB42: =INDEX(ODC!AB:AB, MATCH("Blended IRR", ODC!$A:$A, 0)) -> 0 | AC42: =INDEX(ODC!AC:AC, MATCH("Blended IRR", ODC!$A:$A, 0)) -> 0
A43: AI Stack Blended IRR | D43: =INDEX('AI Stack'!D:D, MATCH("Blended IRR", 'AI Stack'!$A:$A, 0)) -> 0 | E43: =INDEX('AI Stack'!E:E, MATCH("Blended IRR", 'AI Stack'!$A:$A, 0)) -> 0 | F43: =INDEX('AI Stack'!F:F, MATCH("Blended IRR", 'AI Stack'!$A:$A, 0)) -> 0 | G43: =INDEX('AI Stack'!G:G, MATCH("Blended IRR", 'AI Stack'!$A:$A, 0)) -> 0 | H43: =INDEX('AI Stack'!H:H, MATCH("Blended IRR", 'AI Stack'!$A:$A, 0)) -> 0 | I43: =INDEX('AI Stack'!I:I, MATCH("Blended IRR", 'AI Stack'!$A:$A, 0)) -> 0 | J43: =INDEX('AI Stack'!J:J, MATCH("Blended IRR", 'AI Stack'!$A:$A, 0)) -> 0 | K43: =INDEX('AI Stack'!K:K, MATCH("Blended IRR", 'AI Stack'!$A:$A, 0)) -> 0 | L43: =INDEX('AI Stack'!L:L, MATCH("Blended IRR", 'AI Stack'!$A:$A, 0)) -> 0 | M43: =INDEX('AI Stack'!M:M, MATCH("Blended IRR", 'AI Stack'!$A:$A, 0)) -> 0 | N43: =INDEX('AI Stack'!N:N, MATCH("Blended IRR", 'AI Stack'!$A:$A, 0)) -> 0 | O43: =INDEX('AI Stack'!O:O, MATCH("Blended IRR", 'AI Stack'!$A:$A, 0)) -> 0 | P43: =INDEX('AI Stack'!P:P, MATCH("Blended IRR", 'AI Stack'!$A:$A, 0)) -> 0 | Q43: =INDEX('AI Stack'!Q:Q, MATCH("Blended IRR", 'AI Stack'!$A:$A, 0)) -> 0 | R43: =INDEX('AI Stack'!R:R, MATCH("Blended IRR", 'AI Stack'!$A:$A, 0)) -> 0 | S43: =INDEX('AI Stack'!S:S, MATCH("Blended IRR", 'AI Stack'!$A:$A, 0)) -> 0 | T43: =INDEX('AI Stack'!T:T, MATCH("Blended IRR", 'AI Stack'!$A:$A, 0)) -> 0 | U43: =INDEX('AI Stack'!U:U, MATCH("Blended IRR", 'AI Stack'!$A:$A, 0)) -> 0 | V43: =INDEX('AI Stack'!V:V, MATCH("Blended IRR", 'AI Stack'!$A:$A, 0)) -> 0 | W43: =INDEX('AI Stack'!W:W, MATCH("Blended IRR", 'AI Stack'!$A:$A, 0)) -> 0 | X43: =INDEX('AI Stack'!X:X, MATCH("Blended IRR", 'AI Stack'!$A:$A, 0)) -> 0 | Y43: =INDEX('AI Stack'!Y:Y, MATCH("Blended IRR", 'AI Stack'!$A:$A, 0)) -> 0 | Z43: =INDEX('AI Stack'!Z:Z, MATCH("Blended IRR", 'AI Stack'!$A:$A, 0)) -> 0 | AA43: =INDEX('AI Stack'!AA:AA, MATCH("Blended IRR", 'AI Stack'!$A:$A, 0)) -> 0 | AB43: =INDEX('AI Stack'!AB:AB, MATCH("Blended IRR", 'AI Stack'!$A:$A, 0)) -> 0 | AC43: =INDEX('AI Stack'!AC:AC, MATCH("Blended IRR", 'AI Stack'!$A:$A, 0)) -> 0
A44: Lunar / Mars Blended IRR | D44: =INDEX('Lunar Mars'!D:D, MATCH("Blended IRR", 'Lunar Mars'!$A:$A, 0)) -> 0 | E44: =INDEX('Lunar Mars'!E:E, MATCH("Blended IRR", 'Lunar Mars'!$A:$A, 0)) -> 0 | F44: =INDEX('Lunar Mars'!F:F, MATCH("Blended IRR", 'Lunar Mars'!$A:$A, 0)) -> 0 | G44: =INDEX('Lunar Mars'!G:G, MATCH("Blended IRR", 'Lunar Mars'!$A:$A, 0)) -> 0 | H44: =INDEX('Lunar Mars'!H:H, MATCH("Blended IRR", 'Lunar Mars'!$A:$A, 0)) -> 0 | I44: =INDEX('Lunar Mars'!I:I, MATCH("Blended IRR", 'Lunar Mars'!$A:$A, 0)) -> 0 | J44: =INDEX('Lunar Mars'!J:J, MATCH("Blended IRR", 'Lunar Mars'!$A:$A, 0)) -> 0 | K44: =INDEX('Lunar Mars'!K:K, MATCH("Blended IRR", 'Lunar Mars'!$A:$A, 0)) -> 0 | L44: =INDEX('Lunar Mars'!L:L, MATCH("Blended IRR", 'Lunar Mars'!$A:$A, 0)) -> 0 | M44: =INDEX('Lunar Mars'!M:M, MATCH("Blended IRR", 'Lunar Mars'!$A:$A, 0)) -> 0 | N44: =INDEX('Lunar Mars'!N:N, MATCH("Blended IRR", 'Lunar Mars'!$A:$A, 0)) -> 0 | O44: =INDEX('Lunar Mars'!O:O, MATCH("Blended IRR", 'Lunar Mars'!$A:$A, 0)) -> 0 | P44: =INDEX('Lunar Mars'!P:P, MATCH("Blended IRR", 'Lunar Mars'!$A:$A, 0)) -> 0 | Q44: =INDEX('Lunar Mars'!Q:Q, MATCH("Blended IRR", 'Lunar Mars'!$A:$A, 0)) -> 0 | R44: =INDEX('Lunar Mars'!R:R, MATCH("Blended IRR", 'Lunar Mars'!$A:$A, 0)) -> 0 | S44: =INDEX('Lunar Mars'!S:S, MATCH("Blended IRR", 'Lunar Mars'!$A:$A, 0)) -> 0 | T44: =INDEX('Lunar Mars'!T:T, MATCH("Blended IRR", 'Lunar Mars'!$A:$A, 0)) -> 0 | U44: =INDEX('Lunar Mars'!U:U, MATCH("Blended IRR", 'Lunar Mars'!$A:$A, 0)) -> 0 | V44: =INDEX('Lunar Mars'!V:V, MATCH("Blended IRR", 'Lunar Mars'!$A:$A, 0)) -> 0 | W44: =INDEX('Lunar Mars'!W:W, MATCH("Blended IRR", 'Lunar Mars'!$A:$A, 0)) -> 0 | X44: =INDEX('Lunar Mars'!X:X, MATCH("Blended IRR", 'Lunar Mars'!$A:$A, 0)) -> 0 | Y44: =INDEX('Lunar Mars'!Y:Y, MATCH("Blended IRR", 'Lunar Mars'!$A:$A, 0)) -> 0 | Z44: =INDEX('Lunar Mars'!Z:Z, MATCH("Blended IRR", 'Lunar Mars'!$A:$A, 0)) -> 0 | AA44: =INDEX('Lunar Mars'!AA:AA, MATCH("Blended IRR", 'Lunar Mars'!$A:$A, 0)) -> 0 | AB44: =INDEX('Lunar Mars'!AB:AB, MATCH("Blended IRR", 'Lunar Mars'!$A:$A, 0)) -> 0 | AC44: =INDEX('Lunar Mars'!AC:AC, MATCH("Blended IRR", 'Lunar Mars'!$A:$A, 0)) -> 0
A46: ▸ Inputs read: per-module Strategic Priority Weight
A47: Launch | D47: =INDEX('Customer Launch'!D:D, MATCH("Strategic Priority Weight (1–5)", 'Customer Launch'!$A:$A, 0)) -> 2 | E47: =INDEX('Customer Launch'!E:E, MATCH("Strategic Priority Weight (1–5)", 'Customer Launch'!$A:$A, 0)) -> 2 | F47: =INDEX('Customer Launch'!F:F, MATCH("Strategic Priority Weight (1–5)", 'Customer Launch'!$A:$A, 0)) -> 2 | G47: =INDEX('Customer Launch'!G:G, MATCH("Strategic Priority Weight (1–5)", 'Customer Launch'!$A:$A, 0)) -> 2 | H47: =INDEX('Customer Launch'!H:H, MATCH("Strategic Priority Weight (1–5)", 'Customer Launch'!$A:$A, 0)) -> 2 | I47: =INDEX('Customer Launch'!I:I, MATCH("Strategic Priority Weight (1–5)", 'Customer Launch'!$A:$A, 0)) -> 2 | J47: =INDEX('Customer Launch'!J:J, MATCH("Strategic Priority Weight (1–5)", 'Customer Launch'!$A:$A, 0)) -> 2 | K47: =INDEX('Customer Launch'!K:K, MATCH("Strategic Priority Weight (1–5)", 'Customer Launch'!$A:$A, 0)) -> 2 | L47: =INDEX('Customer Launch'!L:L, MATCH("Strategic Priority Weight (1–5)", 'Customer Launch'!$A:$A, 0)) -> 2 | M47: =INDEX('Customer Launch'!M:M, MATCH("Strategic Priority Weight (1–5)", 'Customer Launch'!$A:$A, 0)) -> 2 | N47: =INDEX('Customer Launch'!N:N, MATCH("Strategic Priority Weight (1–5)", 'Customer Launch'!$A:$A, 0)) -> 2 | O47: =INDEX('Customer Launch'!O:O, MATCH("Strategic Priority Weight (1–5)", 'Customer Launch'!$A:$A, 0)) -> 2 | P47: =INDEX('Customer Launch'!P:P, MATCH("Strategic Priority Weight (1–5)", 'Customer Launch'!$A:$A, 0)) -> 2 | Q47: =INDEX('Customer Launch'!Q:Q, MATCH("Strategic Priority Weight (1–5)", 'Customer Launch'!$A:$A, 0)) -> 2 | R47: =INDEX('Customer Launch'!R:R, MATCH("Strategic Priority Weight (1–5)", 'Customer Launch'!$A:$A, 0)) -> 2 | S47: =INDEX('Customer Launch'!S:S, MATCH("Strategic Priority Weight (1–5)", 'Customer Launch'!$A:$A, 0)) -> 2 | T47: =INDEX('Customer Launch'!T:T, MATCH("Strategic Priority Weight (1–5)", 'Customer Launch'!$A:$A, 0)) -> 2 | U47: =INDEX('Customer Launch'!U:U, MATCH("Strategic Priority Weight (1–5)", 'Customer Launch'!$A:$A, 0)) -> 2 | V47: =INDEX('Customer Launch'!V:V, MATCH("Strategic Priority Weight (1–5)", 'Customer Launch'!$A:$A, 0)) -> 2 | W47: =INDEX('Customer Launch'!W:W, MATCH("Strategic Priority Weight (1–5)", 'Customer Launch'!$A:$A, 0)) -> 2 | X47: =INDEX('Customer Launch'!X:X, MATCH("Strategic Priority Weight (1–5)", 'Customer Launch'!$A:$A, 0)) -> 2 | Y47: =INDEX('Customer Launch'!Y:Y, MATCH("Strategic Priority Weight (1–5)", 'Customer Launch'!$A:$A, 0)) -> 2 | Z47: =INDEX('Customer Launch'!Z:Z, MATCH("Strategic Priority Weight (1–5)", 'Customer Launch'!$A:$A, 0)) -> 2 | AA47: =INDEX('Customer Launch'!AA:AA, MATCH("Strategic Priority Weight (1–5)", 'Customer Launch'!$A:$A, 0)) -> 2 | AB47: =INDEX('Customer Launch'!AB:AB, MATCH("Strategic Priority Weight (1–5)", 'Customer Launch'!$A:$A, 0)) -> 2 | AC47: =INDEX('Customer Launch'!AC:AC, MATCH("Strategic Priority Weight (1–5)", 'Customer Launch'!$A:$A, 0)) -> 2
A48: Starlink | D48: =INDEX(Starlink!D:D, MATCH("Strategic Priority Weight (1–5)", Starlink!$A:$A, 0)) -> 5 | E48: =INDEX(Starlink!E:E, MATCH("Strategic Priority Weight (1–5)", Starlink!$A:$A, 0)) -> 5 | F48: =INDEX(Starlink!F:F, MATCH("Strategic Priority Weight (1–5)", Starlink!$A:$A, 0)) -> 5 | G48: =INDEX(Starlink!G:G, MATCH("Strategic Priority Weight (1–5)", Starlink!$A:$A, 0)) -> 5 | H48: =INDEX(Starlink!H:H, MATCH("Strategic Priority Weight (1–5)", Starlink!$A:$A, 0)) -> 5 | I48: =INDEX(Starlink!I:I, MATCH("Strategic Priority Weight (1–5)", Starlink!$A:$A, 0)) -> 5 | J48: =INDEX(Starlink!J:J, MATCH("Strategic Priority Weight (1–5)", Starlink!$A:$A, 0)) -> 5 | K48: =INDEX(Starlink!K:K, MATCH("Strategic Priority Weight (1–5)", Starlink!$A:$A, 0)) -> 5 | L48: =INDEX(Starlink!L:L, MATCH("Strategic Priority Weight (1–5)", Starlink!$A:$A, 0)) -> 5 | M48: =INDEX(Starlink!M:M, MATCH("Strategic Priority Weight (1–5)", Starlink!$A:$A, 0)) -> 5 | N48: =INDEX(Starlink!N:N, MATCH("Strategic Priority Weight (1–5)", Starlink!$A:$A, 0)) -> 5 | O48: =INDEX(Starlink!O:O, MATCH("Strategic Priority Weight (1–5)", Starlink!$A:$A, 0)) -> 5 | P48: =INDEX(Starlink!P:P, MATCH("Strategic Priority Weight (1–5)", Starlink!$A:$A, 0)) -> 5 | Q48: =INDEX(Starlink!Q:Q, MATCH("Strategic Priority Weight (1–5)", Starlink!$A:$A, 0)) -> 5 | R48: =INDEX(Starlink!R:R, MATCH("Strategic Priority Weight (1–5)", Starlink!$A:$A, 0)) -> 5 | S48: =INDEX(Starlink!S:S, MATCH("Strategic Priority Weight (1–5)", Starlink!$A:$A, 0)) -> 5 | T48: =INDEX(Starlink!T:T, MATCH("Strategic Priority Weight (1–5)", Starlink!$A:$A, 0)) -> 5 | U48: =INDEX(Starlink!U:U, MATCH("Strategic Priority Weight (1–5)", Starlink!$A:$A, 0)) -> 5 | V48: =INDEX(Starlink!V:V, MATCH("Strategic Priority Weight (1–5)", Starlink!$A:$A, 0)) -> 5 | W48: =INDEX(Starlink!W:W, MATCH("Strategic Priority Weight (1–5)", Starlink!$A:$A, 0)) -> 5 | X48: =INDEX(Starlink!X:X, MATCH("Strategic Priority Weight (1–5)", Starlink!$A:$A, 0)) -> 5 | Y48: =INDEX(Starlink!Y:Y, MATCH("Strategic Priority Weight (1–5)", Starlink!$A:$A, 0)) -> 5 | Z48: =INDEX(Starlink!Z:Z, MATCH("Strategic Priority Weight (1–5)", Starlink!$A:$A, 0)) -> 5 | AA48: =INDEX(Starlink!AA:AA, MATCH("Strategic Priority Weight (1–5)", Starlink!$A:$A, 0)) -> 5 | AB48: =INDEX(Starlink!AB:AB, MATCH("Strategic Priority Weight (1–5)", Starlink!$A:$A, 0)) -> 5 | AC48: =INDEX(Starlink!AC:AC, MATCH("Strategic Priority Weight (1–5)", Starlink!$A:$A, 0)) -> 5
A49: ODC | D49: =INDEX(ODC!D:D, MATCH("Strategic Priority Weight (1–5)", ODC!$A:$A, 0)) -> 4 | E49: =INDEX(ODC!E:E, MATCH("Strategic Priority Weight (1–5)", ODC!$A:$A, 0)) -> 4 | F49: =INDEX(ODC!F:F, MATCH("Strategic Priority Weight (1–5)", ODC!$A:$A, 0)) -> 4 | G49: =INDEX(ODC!G:G, MATCH("Strategic Priority Weight (1–5)", ODC!$A:$A, 0)) -> 4 | H49: =INDEX(ODC!H:H, MATCH("Strategic Priority Weight (1–5)", ODC!$A:$A, 0)) -> 4 | I49: =INDEX(ODC!I:I, MATCH("Strategic Priority Weight (1–5)", ODC!$A:$A, 0)) -> 4 | J49: =INDEX(ODC!J:J, MATCH("Strategic Priority Weight (1–5)", ODC!$A:$A, 0)) -> 4 | K49: =INDEX(ODC!K:K, MATCH("Strategic Priority Weight (1–5)", ODC!$A:$A, 0)) -> 4 | L49: =INDEX(ODC!L:L, MATCH("Strategic Priority Weight (1–5)", ODC!$A:$A, 0)) -> 4 | M49: =INDEX(ODC!M:M, MATCH("Strategic Priority Weight (1–5)", ODC!$A:$A, 0)) -> 4 | N49: =INDEX(ODC!N:N, MATCH("Strategic Priority Weight (1–5)", ODC!$A:$A, 0)) -> 4 | O49: =INDEX(ODC!O:O, MATCH("Strategic Priority Weight (1–5)", ODC!$A:$A, 0)) -> 4 | P49: =INDEX(ODC!P:P, MATCH("Strategic Priority Weight (1–5)", ODC!$A:$A, 0)) -> 4 | Q49: =INDEX(ODC!Q:Q, MATCH("Strategic Priority Weight (1–5)", ODC!$A:$A, 0)) -> 4 | R49: =INDEX(ODC!R:R, MATCH("Strategic Priority Weight (1–5)", ODC!$A:$A, 0)) -> 4 | S49: =INDEX(ODC!S:S, MATCH("Strategic Priority Weight (1–5)", ODC!$A:$A, 0)) -> 4 | T49: =INDEX(ODC!T:T, MATCH("Strategic Priority Weight (1–5)", ODC!$A:$A, 0)) -> 4 | U49: =INDEX(ODC!U:U, MATCH("Strategic Priority Weight (1–5)", ODC!$A:$A, 0)) -> 4 | V49: =INDEX(ODC!V:V, MATCH("Strategic Priority Weight (1–5)", ODC!$A:$A, 0)) -> 4 | W49: =INDEX(ODC!W:W, MATCH("Strategic Priority Weight (1–5)", ODC!$A:$A, 0)) -> 4 | X49: =INDEX(ODC!X:X, MATCH("Strategic Priority Weight (1–5)", ODC!$A:$A, 0)) -> 4 | Y49: =INDEX(ODC!Y:Y, MATCH("Strategic Priority Weight (1–5)", ODC!$A:$A, 0)) -> 4 | Z49: =INDEX(ODC!Z:Z, MATCH("Strategic Priority Weight (1–5)", ODC!$A:$A, 0)) -> 4 | AA49: =INDEX(ODC!AA:AA, MATCH("Strategic Priority Weight (1–5)", ODC!$A:$A, 0)) -> 4 | AB49: =INDEX(ODC!AB:AB, MATCH("Strategic Priority Weight (1–5)", ODC!$A:$A, 0)) -> 4 | AC49: =INDEX(ODC!AC:AC, MATCH("Strategic Priority Weight (1–5)", ODC!$A:$A, 0)) -> 4
A50: AI Stack | D50: =INDEX('AI Stack'!D:D, MATCH("Strategic Priority Weight (1–5)", 'AI Stack'!$A:$A, 0)) -> 4 | E50: =INDEX('AI Stack'!E:E, MATCH("Strategic Priority Weight (1–5)", 'AI Stack'!$A:$A, 0)) -> 4 | F50: =INDEX('AI Stack'!F:F, MATCH("Strategic Priority Weight (1–5)", 'AI Stack'!$A:$A, 0)) -> 4 | G50: =INDEX('AI Stack'!G:G, MATCH("Strategic Priority Weight (1–5)", 'AI Stack'!$A:$A, 0)) -> 4 | H50: =INDEX('AI Stack'!H:H, MATCH("Strategic Priority Weight (1–5)", 'AI Stack'!$A:$A, 0)) -> 4 | I50: =INDEX('AI Stack'!I:I, MATCH("Strategic Priority Weight (1–5)", 'AI Stack'!$A:$A, 0)) -> 4 | J50: =INDEX('AI Stack'!J:J, MATCH("Strategic Priority Weight (1–5)", 'AI Stack'!$A:$A, 0)) -> 4 | K50: =INDEX('AI Stack'!K:K, MATCH("Strategic Priority Weight (1–5)", 'AI Stack'!$A:$A, 0)) -> 4 | L50: =INDEX('AI Stack'!L:L, MATCH("Strategic Priority Weight (1–5)", 'AI Stack'!$A:$A, 0)) -> 4 | M50: =INDEX('AI Stack'!M:M, MATCH("Strategic Priority Weight (1–5)", 'AI Stack'!$A:$A, 0)) -> 4 | N50: =INDEX('AI Stack'!N:N, MATCH("Strategic Priority Weight (1–5)", 'AI Stack'!$A:$A, 0)) -> 4 | O50: =INDEX('AI Stack'!O:O, MATCH("Strategic Priority Weight (1–5)", 'AI Stack'!$A:$A, 0)) -> 4 | P50: =INDEX('AI Stack'!P:P, MATCH("Strategic Priority Weight (1–5)", 'AI Stack'!$A:$A, 0)) -> 4 | Q50: =INDEX('AI Stack'!Q:Q, MATCH("Strategic Priority Weight (1–5)", 'AI Stack'!$A:$A, 0)) -> 4 | R50: =INDEX('AI Stack'!R:R, MATCH("Strategic Priority Weight (1–5)", 'AI Stack'!$A:$A, 0)) -> 4 | S50: =INDEX('AI Stack'!S:S, MATCH("Strategic Priority Weight (1–5)", 'AI Stack'!$A:$A, 0)) -> 4 | T50: =INDEX('AI Stack'!T:T, MATCH("Strategic Priority Weight (1–5)", 'AI Stack'!$A:$A, 0)) -> 4 | U50: =INDEX('AI Stack'!U:U, MATCH("Strategic Priority Weight (1–5)", 'AI Stack'!$A:$A, 0)) -> 4 | V50: =INDEX('AI Stack'!V:V, MATCH("Strategic Priority Weight (1–5)", 'AI Stack'!$A:$A, 0)) -> 4 | W50: =INDEX('AI Stack'!W:W, MATCH("Strategic Priority Weight (1–5)", 'AI Stack'!$A:$A, 0)) -> 4 | X50: =INDEX('AI Stack'!X:X, MATCH("Strategic Priority Weight (1–5)", 'AI Stack'!$A:$A, 0)) -> 4 | Y50: =INDEX('AI Stack'!Y:Y, MATCH("Strategic Priority Weight (1–5)", 'AI Stack'!$A:$A, 0)) -> 4 | Z50: =INDEX('AI Stack'!Z:Z, MATCH("Strategic Priority Weight (1–5)", 'AI Stack'!$A:$A, 0)) -> 4 | AA50: =INDEX('AI Stack'!AA:AA, MATCH("Strategic Priority Weight (1–5)", 'AI Stack'!$A:$A, 0)) -> 4 | AB50: =INDEX('AI Stack'!AB:AB, MATCH("Strategic Priority Weight (1–5)", 'AI Stack'!$A:$A, 0)) -> 4 | AC50: =INDEX('AI Stack'!AC:AC, MATCH("Strategic Priority Weight (1–5)", 'AI Stack'!$A:$A, 0)) -> 4
A51: Lunar / Mars | D51: =INDEX('Lunar Mars'!D:D, MATCH("Strategic Priority Weight (1–5)", 'Lunar Mars'!$A:$A, 0)) -> 3 | E51: =INDEX('Lunar Mars'!E:E, MATCH("Strategic Priority Weight (1–5)", 'Lunar Mars'!$A:$A, 0)) -> 3 | F51: =INDEX('Lunar Mars'!F:F, MATCH("Strategic Priority Weight (1–5)", 'Lunar Mars'!$A:$A, 0)) -> 3 | G51: =INDEX('Lunar Mars'!G:G, MATCH("Strategic Priority Weight (1–5)", 'Lunar Mars'!$A:$A, 0)) -> 3 | H51: =INDEX('Lunar Mars'!H:H, MATCH("Strategic Priority Weight (1–5)", 'Lunar Mars'!$A:$A, 0)) -> 3 | I51: =INDEX('Lunar Mars'!I:I, MATCH("Strategic Priority Weight (1–5)", 'Lunar Mars'!$A:$A, 0)) -> 3 | J51: =INDEX('Lunar Mars'!J:J, MATCH("Strategic Priority Weight (1–5)", 'Lunar Mars'!$A:$A, 0)) -> 3 | K51: =INDEX('Lunar Mars'!K:K, MATCH("Strategic Priority Weight (1–5)", 'Lunar Mars'!$A:$A, 0)) -> 3 | L51: =INDEX('Lunar Mars'!L:L, MATCH("Strategic Priority Weight (1–5)", 'Lunar Mars'!$A:$A, 0)) -> 3 | M51: =INDEX('Lunar Mars'!M:M, MATCH("Strategic Priority Weight (1–5)", 'Lunar Mars'!$A:$A, 0)) -> 3 | N51: =INDEX('Lunar Mars'!N:N, MATCH("Strategic Priority Weight (1–5)", 'Lunar Mars'!$A:$A, 0)) -> 3 | O51: =INDEX('Lunar Mars'!O:O, MATCH("Strategic Priority Weight (1–5)", 'Lunar Mars'!$A:$A, 0)) -> 3 | P51: =INDEX('Lunar Mars'!P:P, MATCH("Strategic Priority Weight (1–5)", 'Lunar Mars'!$A:$A, 0)) -> 3 | Q51: =INDEX('Lunar Mars'!Q:Q, MATCH("Strategic Priority Weight (1–5)", 'Lunar Mars'!$A:$A, 0)) -> 3 | R51: =INDEX('Lunar Mars'!R:R, MATCH("Strategic Priority Weight (1–5)", 'Lunar Mars'!$A:$A, 0)) -> 3 | S51: =INDEX('Lunar Mars'!S:S, MATCH("Strategic Priority Weight (1–5)", 'Lunar Mars'!$A:$A, 0)) -> 3 | T51: =INDEX('Lunar Mars'!T:T, MATCH("Strategic Priority Weight (1–5)", 'Lunar Mars'!$A:$A, 0)) -> 3 | U51: =INDEX('Lunar Mars'!U:U, MATCH("Strategic Priority Weight (1–5)", 'Lunar Mars'!$A:$A, 0)) -> 3 | V51: =INDEX('Lunar Mars'!V:V, MATCH("Strategic Priority Weight (1–5)", 'Lunar Mars'!$A:$A, 0)) -> 3 | W51: =INDEX('Lunar Mars'!W:W, MATCH("Strategic Priority Weight (1–5)", 'Lunar Mars'!$A:$A, 0)) -> 3 | X51: =INDEX('Lunar Mars'!X:X, MATCH("Strategic Priority Weight (1–5)", 'Lunar Mars'!$A:$A, 0)) -> 3 | Y51: =INDEX('Lunar Mars'!Y:Y, MATCH("Strategic Priority Weight (1–5)", 'Lunar Mars'!$A:$A, 0)) -> 3 | Z51: =INDEX('Lunar Mars'!Z:Z, MATCH("Strategic Priority Weight (1–5)", 'Lunar Mars'!$A:$A, 0)) -> 3 | AA51: =INDEX('Lunar Mars'!AA:AA, MATCH("Strategic Priority Weight (1–5)", 'Lunar Mars'!$A:$A, 0)) -> 3 | AB51: =INDEX('Lunar Mars'!AB:AB, MATCH("Strategic Priority Weight (1–5)", 'Lunar Mars'!$A:$A, 0)) -> 3 | AC51: =INDEX('Lunar Mars'!AC:AC, MATCH("Strategic Priority Weight (1–5)", 'Lunar Mars'!$A:$A, 0)) -> 3
A53: LAYER 2 — STARSHIP CAPACITY ALLOCATION
A55: Total Starship annual capacity (kg) | D55: ='Launch Capacity'!D23 -> 150000 | E55: ='Launch Capacity'!E23 -> 145833.33 | F55: ='Launch Capacity'!F23 -> 166224.03 | G55: ='Launch Capacity'!G23 -> 179613.66 | H55: ='Launch Capacity'!H23 -> 178825.75 | I55: ='Launch Capacity'!I23 -> 175551.24 | J55: ='Launch Capacity'!J23 -> 179180.09 | K55: ='Launch Capacity'!K23 -> 179343.62 | ... AC55: ='Launch Capacity'!AC23 -> 247339.5
A57: ▸ Dedicated reservations — off the top (per Sprint 4)
A58: Lunar slots reserved (kg) | D58: =Assumptions!$D$287*Assumptions!$B$278 -> 0 | E58: =Assumptions!$D$287*Assumptions!$B$278 -> 0 | F58: =Assumptions!$D$287*Assumptions!$B$278 -> 0 | G58: =Assumptions!$D$287*Assumptions!$B$278 -> 0 | H58: =Assumptions!$D$287*Assumptions!$B$278 -> 0 | I58: =Assumptions!$D$287*Assumptions!$B$278 -> 0 | J58: =Assumptions!$D$287*Assumptions!$B$278 -> 0 | K58: =Assumptions!$D$287*Assumptions!$B$278 -> 0 | ... AC58: =Assumptions!$D$287*Assumptions!$B$278 -> 0
A59: Mars slots reserved (kg) | D59: =Assumptions!$D$288*Assumptions!$B$283 -> 0 | E59: =Assumptions!$D$288*Assumptions!$B$283 -> 0 | F59: =Assumptions!$D$288*Assumptions!$B$283 -> 0 | G59: =Assumptions!$D$288*Assumptions!$B$283 -> 0 | H59: =Assumptions!$D$288*Assumptions!$B$283 -> 0 | I59: =Assumptions!$D$288*Assumptions!$B$283 -> 0 | J59: =Assumptions!$D$288*Assumptions!$B$283 -> 0 | K59: =Assumptions!$D$288*Assumptions!$B$283 -> 0 | ... AC59: =Assumptions!$D$288*Assumptions!$B$283 -> 0
A60: Total dedicated reserved (kg) | D60: =D58+D59 -> 0 | E60: =E58+E59 -> 0 | F60: =F58+F59 -> 0 | G60: =G58+G59 -> 0 | H60: =H58+H59 -> 0 | I60: =I58+I59 -> 0 | J60: =J58+J59 -> 0 | K60: =K58+K59 -> 0 | ... AC60: =AC58+AC59 -> 0
A61: Capacity available for priority queue (kg) | D61: =MAX(0,D55-D60) -> 150000 | E61: =MAX(0,E55-E60) -> 145833.33 | F61: =MAX(0,F55-F60) -> 166224.03 | G61: =MAX(0,G55-G60) -> 179613.66 | H61: =MAX(0,H55-H60) -> 178825.75 | I61: =MAX(0,I55-I60) -> 175551.24 | J61: =MAX(0,J55-J60) -> 179180.09 | K61: =MAX(0,K55-K60) -> 179343.62 | ... AC61: =MAX(0,AC55-AC60) -> 247339.5
A63: ▸ Inputs read: per-module Capacity Demand (kg-to-LEO)
A64: Launch uncapped demand | D64: =INDEX('Customer Launch'!D:D, MATCH("Capacity Demand (kg-to-LEO)", 'Customer Launch'!$A:$A, 0)) -> 0 | E64: =INDEX('Customer Launch'!E:E, MATCH("Capacity Demand (kg-to-LEO)", 'Customer Launch'!$A:$A, 0)) -> 0 | F64: =INDEX('Customer Launch'!F:F, MATCH("Capacity Demand (kg-to-LEO)", 'Customer Launch'!$A:$A, 0)) -> 15849684 | G64: =INDEX('Customer Launch'!G:G, MATCH("Capacity Demand (kg-to-LEO)", 'Customer Launch'!$A:$A, 0)) -> 18474100 | H64: =INDEX('Customer Launch'!H:H, MATCH("Capacity Demand (kg-to-LEO)", 'Customer Launch'!$A:$A, 0)) -> 21541489 | I64: =INDEX('Customer Launch'!I:I, MATCH("Capacity Demand (kg-to-LEO)", 'Customer Launch'!$A:$A, 0)) -> 25127845 | J64: =INDEX('Customer Launch'!J:J, MATCH("Capacity Demand (kg-to-LEO)", 'Customer Launch'!$A:$A, 0)) -> 29322367 | K64: =INDEX('Customer Launch'!K:K, MATCH("Capacity Demand (kg-to-LEO)", 'Customer Launch'!$A:$A, 0)) -> 34229786 | L64: =INDEX('Customer Launch'!L:L, MATCH("Capacity Demand (kg-to-LEO)", 'Customer Launch'!$A:$A, 0)) -> 39973090 | M64: =INDEX('Customer Launch'!M:M, MATCH("Capacity Demand (kg-to-LEO)", 'Customer Launch'!$A:$A, 0)) -> 46696738 | N64: =INDEX('Customer Launch'!N:N, MATCH("Capacity Demand (kg-to-LEO)", 'Customer Launch'!$A:$A, 0)) -> 54570447 | O64: =INDEX('Customer Launch'!O:O, MATCH("Capacity Demand (kg-to-LEO)", 'Customer Launch'!$A:$A, 0)) -> 63793642 | P64: =INDEX('Customer Launch'!P:P, MATCH("Capacity Demand (kg-to-LEO)", 'Customer Launch'!$A:$A, 0)) -> 74600706 | Q64: =INDEX('Customer Launch'!Q:Q, MATCH("Capacity Demand (kg-to-LEO)", 'Customer Launch'!$A:$A, 0)) -> 87267152 | R64: =INDEX('Customer Launch'!R:R, MATCH("Capacity Demand (kg-to-LEO)", 'Customer Launch'!$A:$A, 0)) -> 1.021169e+08 | S64: =INDEX('Customer Launch'!S:S, MATCH("Capacity Demand (kg-to-LEO)", 'Customer Launch'!$A:$A, 0)) -> 1.1953085e+08 | T64: =INDEX('Customer Launch'!T:T, MATCH("Capacity Demand (kg-to-LEO)", 'Customer Launch'!$A:$A, 0)) -> 1.3935683e+08 | U64: =INDEX('Customer Launch'!U:U, MATCH("Capacity Demand (kg-to-LEO)", 'Customer Launch'!$A:$A, 0)) -> 1.6249488e+08 | V64: =INDEX('Customer Launch'!V:V, MATCH("Capacity Demand (kg-to-LEO)", 'Customer Launch'!$A:$A, 0)) -> 1.8950178e+08 | W64: =INDEX('Customer Launch'!W:W, MATCH("Capacity Demand (kg-to-LEO)", 'Customer Launch'!$A:$A, 0)) -> 2.2102848e+08 | X64: =INDEX('Customer Launch'!X:X, MATCH("Capacity Demand (kg-to-LEO)", 'Customer Launch'!$A:$A, 0)) -> 2.57836e+08 | Y64: =INDEX('Customer Launch'!Y:Y, MATCH("Capacity Demand (kg-to-LEO)", 'Customer Launch'!$A:$A, 0)) -> 3.0081419e+08 | Z64: =INDEX('Customer Launch'!Z:Z, MATCH("Capacity Demand (kg-to-LEO)", 'Customer Launch'!$A:$A, 0)) -> 3.5100361e+08 | AA64: =INDEX('Customer Launch'!AA:AA, MATCH("Capacity Demand (kg-to-LEO)", 'Customer Launch'!$A:$A, 0)) -> 4.096212e+08 | AB64: =INDEX('Customer Launch'!AB:AB, MATCH("Capacity Demand (kg-to-LEO)", 'Customer Launch'!$A:$A, 0)) -> 4.7809028e+08 | AC64: =INDEX('Customer Launch'!AC:AC, MATCH("Capacity Demand (kg-to-LEO)", 'Customer Launch'!$A:$A, 0)) -> 5.580757e+08
A65: Starlink uncapped demand | D65: =INDEX(Starlink!D:D, MATCH("Capacity Demand (kg-to-LEO)", Starlink!$A:$A, 0)) -> 10000000 | E65: =INDEX(Starlink!E:E, MATCH("Capacity Demand (kg-to-LEO)", Starlink!$A:$A, 0)) -> 10000000 | F65: =INDEX(Starlink!F:F, MATCH("Capacity Demand (kg-to-LEO)", Starlink!$A:$A, 0)) -> 10000000 | G65: =INDEX(Starlink!G:G, MATCH("Capacity Demand (kg-to-LEO)", Starlink!$A:$A, 0)) -> 10000000 | H65: =INDEX(Starlink!H:H, MATCH("Capacity Demand (kg-to-LEO)", Starlink!$A:$A, 0)) -> 10000000 | I65: =INDEX(Starlink!I:I, MATCH("Capacity Demand (kg-to-LEO)", Starlink!$A:$A, 0)) -> 10000000 | J65: =INDEX(Starlink!J:J, MATCH("Capacity Demand (kg-to-LEO)", Starlink!$A:$A, 0)) -> 10000000 | K65: =INDEX(Starlink!K:K, MATCH("Capacity Demand (kg-to-LEO)", Starlink!$A:$A, 0)) -> 10000000 | L65: =INDEX(Starlink!L:L, MATCH("Capacity Demand (kg-to-LEO)", Starlink!$A:$A, 0)) -> 10000000 | M65: =INDEX(Starlink!M:M, MATCH("Capacity Demand (kg-to-LEO)", Starlink!$A:$A, 0)) -> 10000000 | N65: =INDEX(Starlink!N:N, MATCH("Capacity Demand (kg-to-LEO)", Starlink!$A:$A, 0)) -> 10000000 | O65: =INDEX(Starlink!O:O, MATCH("Capacity Demand (kg-to-LEO)", Starlink!$A:$A, 0)) -> 10000000 | P65: =INDEX(Starlink!P:P, MATCH("Capacity Demand (kg-to-LEO)", Starlink!$A:$A, 0)) -> 10000000 | Q65: =INDEX(Starlink!Q:Q, MATCH("Capacity Demand (kg-to-LEO)", Starlink!$A:$A, 0)) -> 10000000 | R65: =INDEX(Starlink!R:R, MATCH("Capacity Demand (kg-to-LEO)", Starlink!$A:$A, 0)) -> 10000000 | S65: =INDEX(Starlink!S:S, MATCH("Capacity Demand (kg-to-LEO)", Starlink!$A:$A, 0)) -> 10000000 | T65: =INDEX(Starlink!T:T, MATCH("Capacity Demand (kg-to-LEO)", Starlink!$A:$A, 0)) -> 10000000 | U65: =INDEX(Starlink!U:U, MATCH("Capacity Demand (kg-to-LEO)", Starlink!$A:$A, 0)) -> 10000000 | V65: =INDEX(Starlink!V:V, MATCH("Capacity Demand (kg-to-LEO)", Starlink!$A:$A, 0)) -> 10000000 | W65: =INDEX(Starlink!W:W, MATCH("Capacity Demand (kg-to-LEO)", Starlink!$A:$A, 0)) -> 10000000 | X65: =INDEX(Starlink!X:X, MATCH("Capacity Demand (kg-to-LEO)", Starlink!$A:$A, 0)) -> 10000000 | Y65: =INDEX(Starlink!Y:Y, MATCH("Capacity Demand (kg-to-LEO)", Starlink!$A:$A, 0)) -> 10000000 | Z65: =INDEX(Starlink!Z:Z, MATCH("Capacity Demand (kg-to-LEO)", Starlink!$A:$A, 0)) -> 10000000 | AA65: =INDEX(Starlink!AA:AA, MATCH("Capacity Demand (kg-to-LEO)", Starlink!$A:$A, 0)) -> 10000000 | AB65: =INDEX(Starlink!AB:AB, MATCH("Capacity Demand (kg-to-LEO)", Starlink!$A:$A, 0)) -> 10000000 | AC65: =INDEX(Starlink!AC:AC, MATCH("Capacity Demand (kg-to-LEO)", Starlink!$A:$A, 0)) -> 10000000
A66: ODC uncapped demand | D66: =INDEX(ODC!D:D, MATCH("Capacity Demand (kg-to-LEO)", ODC!$A:$A, 0)) -> 0 | E66: =INDEX(ODC!E:E, MATCH("Capacity Demand (kg-to-LEO)", ODC!$A:$A, 0)) -> 140000 | F66: =INDEX(ODC!F:F, MATCH("Capacity Demand (kg-to-LEO)", ODC!$A:$A, 0)) -> 840000 | G66: =INDEX(ODC!G:G, MATCH("Capacity Demand (kg-to-LEO)", ODC!$A:$A, 0)) -> 2800000 | H66: =INDEX(ODC!H:H, MATCH("Capacity Demand (kg-to-LEO)", ODC!$A:$A, 0)) -> 4900000 | I66: =INDEX(ODC!I:I, MATCH("Capacity Demand (kg-to-LEO)", ODC!$A:$A, 0)) -> 5320000 | J66: =INDEX(ODC!J:J, MATCH("Capacity Demand (kg-to-LEO)", ODC!$A:$A, 0)) -> 2800000 | K66: =INDEX(ODC!K:K, MATCH("Capacity Demand (kg-to-LEO)", ODC!$A:$A, 0)) -> 2800000 | L66: =INDEX(ODC!L:L, MATCH("Capacity Demand (kg-to-LEO)", ODC!$A:$A, 0)) -> 2800000 | M66: =INDEX(ODC!M:M, MATCH("Capacity Demand (kg-to-LEO)", ODC!$A:$A, 0)) -> 2800000 | N66: =INDEX(ODC!N:N, MATCH("Capacity Demand (kg-to-LEO)", ODC!$A:$A, 0)) -> 2800000 | O66: =INDEX(ODC!O:O, MATCH("Capacity Demand (kg-to-LEO)", ODC!$A:$A, 0)) -> 2800000 | P66: =INDEX(ODC!P:P, MATCH("Capacity Demand (kg-to-LEO)", ODC!$A:$A, 0)) -> 2800000 | Q66: =INDEX(ODC!Q:Q, MATCH("Capacity Demand (kg-to-LEO)", ODC!$A:$A, 0)) -> 2800000 | R66: =INDEX(ODC!R:R, MATCH("Capacity Demand (kg-to-LEO)", ODC!$A:$A, 0)) -> 2800000 | S66: =INDEX(ODC!S:S, MATCH("Capacity Demand (kg-to-LEO)", ODC!$A:$A, 0)) -> 2800000 | T66: =INDEX(ODC!T:T, MATCH("Capacity Demand (kg-to-LEO)", ODC!$A:$A, 0)) -> 2800000 | U66: =INDEX(ODC!U:U, MATCH("Capacity Demand (kg-to-LEO)", ODC!$A:$A, 0)) -> 2800000 | V66: =INDEX(ODC!V:V, MATCH("Capacity Demand (kg-to-LEO)", ODC!$A:$A, 0)) -> 2800000 | W66: =INDEX(ODC!W:W, MATCH("Capacity Demand (kg-to-LEO)", ODC!$A:$A, 0)) -> 2800000 | X66: =INDEX(ODC!X:X, MATCH("Capacity Demand (kg-to-LEO)", ODC!$A:$A, 0)) -> 2800000 | Y66: =INDEX(ODC!Y:Y, MATCH("Capacity Demand (kg-to-LEO)", ODC!$A:$A, 0)) -> 2800000 | Z66: =INDEX(ODC!Z:Z, MATCH("Capacity Demand (kg-to-LEO)", ODC!$A:$A, 0)) -> 2800000 | AA66: =INDEX(ODC!AA:AA, MATCH("Capacity Demand (kg-to-LEO)", ODC!$A:$A, 0)) -> 2800000 | AB66: =INDEX(ODC!AB:AB, MATCH("Capacity Demand (kg-to-LEO)", ODC!$A:$A, 0)) -> 2800000 | AC66: =INDEX(ODC!AC:AC, MATCH("Capacity Demand (kg-to-LEO)", ODC!$A:$A, 0)) -> 2800000
A67: AI Stack uncapped demand | D67: =INDEX('AI Stack'!D:D, MATCH("Capacity Demand (kg-to-LEO)", 'AI Stack'!$A:$A, 0)) -> 0 | E67: =INDEX('AI Stack'!E:E, MATCH("Capacity Demand (kg-to-LEO)", 'AI Stack'!$A:$A, 0)) -> 0 | F67: =INDEX('AI Stack'!F:F, MATCH("Capacity Demand (kg-to-LEO)", 'AI Stack'!$A:$A, 0)) -> 0 | G67: =INDEX('AI Stack'!G:G, MATCH("Capacity Demand (kg-to-LEO)", 'AI Stack'!$A:$A, 0)) -> 0 | H67: =INDEX('AI Stack'!H:H, MATCH("Capacity Demand (kg-to-LEO)", 'AI Stack'!$A:$A, 0)) -> 0 | I67: =INDEX('AI Stack'!I:I, MATCH("Capacity Demand (kg-to-LEO)", 'AI Stack'!$A:$A, 0)) -> 0 | J67: =INDEX('AI Stack'!J:J, MATCH("Capacity Demand (kg-to-LEO)", 'AI Stack'!$A:$A, 0)) -> 0 | K67: =INDEX('AI Stack'!K:K, MATCH("Capacity Demand (kg-to-LEO)", 'AI Stack'!$A:$A, 0)) -> 0 | L67: =INDEX('AI Stack'!L:L, MATCH("Capacity Demand (kg-to-LEO)", 'AI Stack'!$A:$A, 0)) -> 0 | M67: =INDEX('AI Stack'!M:M, MATCH("Capacity Demand (kg-to-LEO)", 'AI Stack'!$A:$A, 0)) -> 0 | N67: =INDEX('AI Stack'!N:N, MATCH("Capacity Demand (kg-to-LEO)", 'AI Stack'!$A:$A, 0)) -> 0 | O67: =INDEX('AI Stack'!O:O, MATCH("Capacity Demand (kg-to-LEO)", 'AI Stack'!$A:$A, 0)) -> 0 | P67: =INDEX('AI Stack'!P:P, MATCH("Capacity Demand (kg-to-LEO)", 'AI Stack'!$A:$A, 0)) -> 0 | Q67: =INDEX('AI Stack'!Q:Q, MATCH("Capacity Demand (kg-to-LEO)", 'AI Stack'!$A:$A, 0)) -> 0 | R67: =INDEX('AI Stack'!R:R, MATCH("Capacity Demand (kg-to-LEO)", 'AI Stack'!$A:$A, 0)) -> 0 | S67: =INDEX('AI Stack'!S:S, MATCH("Capacity Demand (kg-to-LEO)", 'AI Stack'!$A:$A, 0)) -> 0 | T67: =INDEX('AI Stack'!T:T, MATCH("Capacity Demand (kg-to-LEO)", 'AI Stack'!$A:$A, 0)) -> 0 | U67: =INDEX('AI Stack'!U:U, MATCH("Capacity Demand (kg-to-LEO)", 'AI Stack'!$A:$A, 0)) -> 0 | V67: =INDEX('AI Stack'!V:V, MATCH("Capacity Demand (kg-to-LEO)", 'AI Stack'!$A:$A, 0)) -> 0 | W67: =INDEX('AI Stack'!W:W, MATCH("Capacity Demand (kg-to-LEO)", 'AI Stack'!$A:$A, 0)) -> 0 | X67: =INDEX('AI Stack'!X:X, MATCH("Capacity Demand (kg-to-LEO)", 'AI Stack'!$A:$A, 0)) -> 0 | Y67: =INDEX('AI Stack'!Y:Y, MATCH("Capacity Demand (kg-to-LEO)", 'AI Stack'!$A:$A, 0)) -> 0 | Z67: =INDEX('AI Stack'!Z:Z, MATCH("Capacity Demand (kg-to-LEO)", 'AI Stack'!$A:$A, 0)) -> 0 | AA67: =INDEX('AI Stack'!AA:AA, MATCH("Capacity Demand (kg-to-LEO)", 'AI Stack'!$A:$A, 0)) -> 0 | AB67: =INDEX('AI Stack'!AB:AB, MATCH("Capacity Demand (kg-to-LEO)", 'AI Stack'!$A:$A, 0)) -> 0 | AC67: =INDEX('AI Stack'!AC:AC, MATCH("Capacity Demand (kg-to-LEO)", 'AI Stack'!$A:$A, 0)) -> 0
A68: Lunar / Mars uncapped demand (diagnostic only — NOT read by queue) | D68: =INDEX('Lunar Mars'!D:D, MATCH("Capacity Demand (kg-to-LEO)", 'Lunar Mars'!$A:$A, 0)) -> 0 | E68: =INDEX('Lunar Mars'!E:E, MATCH("Capacity Demand (kg-to-LEO)", 'Lunar Mars'!$A:$A, 0)) -> 0 | F68: =INDEX('Lunar Mars'!F:F, MATCH("Capacity Demand (kg-to-LEO)", 'Lunar Mars'!$A:$A, 0)) -> 283333.33 | G68: =INDEX('Lunar Mars'!G:G, MATCH("Capacity Demand (kg-to-LEO)", 'Lunar Mars'!$A:$A, 0)) -> 1237500 | H68: =INDEX('Lunar Mars'!H:H, MATCH("Capacity Demand (kg-to-LEO)", 'Lunar Mars'!$A:$A, 0)) -> 757500 | I68: =INDEX('Lunar Mars'!I:I, MATCH("Capacity Demand (kg-to-LEO)", 'Lunar Mars'!$A:$A, 0)) -> 4600000 | J68: =INDEX('Lunar Mars'!J:J, MATCH("Capacity Demand (kg-to-LEO)", 'Lunar Mars'!$A:$A, 0)) -> 1540000 | K68: =INDEX('Lunar Mars'!K:K, MATCH("Capacity Demand (kg-to-LEO)", 'Lunar Mars'!$A:$A, 0)) -> 10290000 | L68: =INDEX('Lunar Mars'!L:L, MATCH("Capacity Demand (kg-to-LEO)", 'Lunar Mars'!$A:$A, 0)) -> 2291666.7 | M68: =INDEX('Lunar Mars'!M:M, MATCH("Capacity Demand (kg-to-LEO)", 'Lunar Mars'!$A:$A, 0)) -> 23353333 | N68: =INDEX('Lunar Mars'!N:N, MATCH("Capacity Demand (kg-to-LEO)", 'Lunar Mars'!$A:$A, 0)) -> 3075000 | O68: =INDEX('Lunar Mars'!O:O, MATCH("Capacity Demand (kg-to-LEO)", 'Lunar Mars'!$A:$A, 0)) -> 54940000 | P68: =INDEX('Lunar Mars'!P:P, MATCH("Capacity Demand (kg-to-LEO)", 'Lunar Mars'!$A:$A, 0)) -> 4305000 | Q68: =INDEX('Lunar Mars'!Q:Q, MATCH("Capacity Demand (kg-to-LEO)", 'Lunar Mars'!$A:$A, 0)) -> 107420000 | R68: =INDEX('Lunar Mars'!R:R, MATCH("Capacity Demand (kg-to-LEO)", 'Lunar Mars'!$A:$A, 0)) -> 5535000 | S68: =INDEX('Lunar Mars'!S:S, MATCH("Capacity Demand (kg-to-LEO)", 'Lunar Mars'!$A:$A, 0)) -> 211150000 | T68: =INDEX('Lunar Mars'!T:T, MATCH("Capacity Demand (kg-to-LEO)", 'Lunar Mars'!$A:$A, 0)) -> 6560000 | U68: =INDEX('Lunar Mars'!U:U, MATCH("Capacity Demand (kg-to-LEO)", 'Lunar Mars'!$A:$A, 0)) -> 416970000 | V68: =INDEX('Lunar Mars'!V:V, MATCH("Capacity Demand (kg-to-LEO)", 'Lunar Mars'!$A:$A, 0)) -> 7380000 | W68: =INDEX('Lunar Mars'!W:W, MATCH("Capacity Demand (kg-to-LEO)", 'Lunar Mars'!$A:$A, 0)) -> 827790000 | X68: =INDEX('Lunar Mars'!X:X, MATCH("Capacity Demand (kg-to-LEO)", 'Lunar Mars'!$A:$A, 0)) -> 8200000 | Y68: =INDEX('Lunar Mars'!Y:Y, MATCH("Capacity Demand (kg-to-LEO)", 'Lunar Mars'!$A:$A, 0)) -> 1238610000 | Z68: =INDEX('Lunar Mars'!Z:Z, MATCH("Capacity Demand (kg-to-LEO)", 'Lunar Mars'!$A:$A, 0)) -> 9020000 | AA68: =INDEX('Lunar Mars'!AA:AA, MATCH("Capacity Demand (kg-to-LEO)", 'Lunar Mars'!$A:$A, 0)) -> 1649430000 | AB68: =INDEX('Lunar Mars'!AB:AB, MATCH("Capacity Demand (kg-to-LEO)", 'Lunar Mars'!$A:$A, 0)) -> 9840000 | AC68: =INDEX('Lunar Mars'!AC:AC, MATCH("Capacity Demand (kg-to-LEO)", 'Lunar Mars'!$A:$A, 0)) -> 2060250000
A70: ▸ Waterfall — priority queue
A71: 1. Starlink allocation (kg) | D71: =MIN(D65,D$61*D173) -> 128960.95 | E71: =MIN(E65,E$61*E173) -> 125786.6 | F71: =MIN(F65,F$61*F173) -> 119705.35 | G71: =MIN(G65,G$61*G173) -> 111181.19 | H71: =MIN(H65,H$61*H173) -> 97069.384 | I71: =MIN(I65,I$61*I173) -> 72803.654 | J71: =MIN(J65,J$61*J173) -> 70891.314 | K71: =MIN(K65,K$61*K173) -> 64811.071 | ... AC71: =MIN(AC65,AC$61*AC173) -> 221815.88
A72: Capacity slack after IRR queue (kg) | D72: =MAX(0, D61 - D71 - D78 - D79 - D80) -> 21039.051 | E72: =MAX(0, E61 - E71 - E78 - E79 - E80) -> 20046.738 | F72: =MAX(0, F61 - F71 - F78 - F79 - F80) -> 0 | G72: =MAX(0, G61 - G71 - G78 - G79 - G80) -> 0 | H72: =MAX(0, H61 - H71 - H78 - H79 - H80) -> 0 | I72: =MAX(0, I61 - I71 - I78 - I79 - I80) -> 0 | J72: =MAX(0, J61 - J71 - J78 - J79 - J80) -> 1.5133992e-09 | K72: =MAX(0, K61 - K71 - K78 - K79 - K80) -> 1.4551915e-11 | ... AC72: =MAX(0, AC61 - AC71 - AC78 - AC79 - AC80) -> 1.1801603e-08
A73: Memo: ODC + AI Stack combined masked kg demand (diagnostic) | D73: =D143+D144 -> 0 | E73: =E143+E144 -> 0 | F73: =F143+F144 -> 0 | G73: =G143+G144 -> 0 | H73: =H143+H144 -> 0 | I73: =I143+I144 -> 0 | J73: =J143+J144 -> 0 | K73: =K143+K144 -> 0 | ... AC73: =AC143+AC144 -> 0
A74: [Legacy — compute-tier combined; superseded by R143/R144 individual ranks]
A75: Memo: Available after queue (alias of R72) | D75: =D72 -> 21039.051 | E75: =E72 -> 20046.738 | F75: =F72 -> 0 | G75: =G72 -> 0 | H75: =H72 -> 0 | I75: =I72 -> 0 | J75: =J72 -> 1.5133992e-09 | K75: =K72 -> 1.4551915e-11 | ... AC75: =AC72 -> 1.1801603e-08
A76: [Legacy — ODC pro-rata weight; superseded by R134-R137 ranks] | D76: [Legacy — ODC pro-rata weight; superseded by R134-R137 ranks]
A77: [Legacy — AI Stack pro-rata weight; superseded by R134-R137 ranks] | D77: [Legacy — AI Stack pro-rata weight; superseded by R134-R137 ranks]
A78: ODC allocation (kg) | D78: =MIN(D66,D$61*D174) -> 0 | E78: =MIN(E66,E$61*E174) -> 0 | F78: =MIN(F66,F$61*F174) -> 0 | G78: =MIN(G66,G$61*G174) -> 0 | H78: =MIN(H66,H$61*H174) -> 0 | I78: =MIN(I66,I$61*I174) -> 0 | J78: =MIN(J66,J$61*J174) -> 0 | K78: =MIN(K66,K$61*K174) -> 0 | ... AC78: =MIN(AC66,AC$61*AC174) -> 0
A79: AI Stack allocation (kg) | D79: =MIN(D67,D$61*D175) -> 0 | E79: =MIN(E67,E$61*E175) -> 0 | F79: =MIN(F67,F$61*F175) -> 0 | G79: =MIN(G67,G$61*G175) -> 0 | H79: =MIN(H67,H$61*H175) -> 0 | I79: =MIN(I67,I$61*I175) -> 0 | J79: =MIN(J67,J$61*J175) -> 0 | K79: =MIN(K67,K$61*K175) -> 0 | ... AC79: =MIN(AC67,AC$61*AC175) -> 0
A80: 3. Launch allocation (kg) | D80: =MIN(D64,D$61*D172) -> 0 | E80: =MIN(E64,E$61*E172) -> 0 | F80: =MIN(F64,F$61*F172) -> 46518.68 | G80: =MIN(G64,G$61*G172) -> 68432.465 | H80: =MIN(H64,H$61*H172) -> 81756.361 | I80: =MIN(I64,I$61*I172) -> 102747.59 | J80: =MIN(J64,J$61*J172) -> 108288.78 | K80: =MIN(K64,K$61*K172) -> 114532.55 | ... AC80: =MIN(AC64,AC$61*AC172) -> 25523.618
A82: [Legacy] LAYER 3 — STARLINK CASH SWEEP (retired per Spec 07)
A83: [Legacy] Maintenance threshold (Blended IRR floor)
A84: [Legacy] Sweep active flag (1/0)
A85: [Legacy] Maintenance FCF floor ($mm)
A86: [Legacy] ODC sweep contribution ($mm)
A87: [Legacy] AI Stack sweep contribution ($mm)
A88: [Legacy] Total swept (conservation check)
A90: ▸ Layer 2 diagnostics
A91: Total kg allocated (queue + reservations) | D91: =D60+D71+D78+D79+D80 -> 128960.95 | E91: =E60+E71+E78+E79+E80 -> 125786.6 | F91: =F60+F71+F78+F79+F80 -> 166224.03 | G91: =G60+G71+G78+G79+G80 -> 179613.66 | H91: =H60+H71+H78+H79+H80 -> 178825.75 | I91: =I60+I71+I78+I79+I80 -> 175551.24 | J91: =J60+J71+J78+J79+J80 -> 179180.09 | K91: =K60+K71+K78+K79+K80 -> 179343.62 | ... AC91: =AC60+AC71+AC78+AC79+AC80 -> 247339.5
A92: Slack capacity (kg) | D92: =D55-D91 -> 21039.051 | E92: =E55-E91 -> 20046.738 | F92: =F55-F91 -> 0 | G92: =G55-G91 -> 0 | H92: =H55-H91 -> 0 | I92: =I55-I91 -> 0 | J92: =J55-J91 -> 0 | K92: =K55-K91 -> 0 | ... AC92: =AC55-AC91 -> 0
A93: Capacity utilised % | D93: =IFERROR(D91/D55,0) -> 0.85973966 | E93: =IFERROR(E91/E55,0) -> 0.86253666 | F93: =IFERROR(F91/F55,0) -> 1 | G93: =IFERROR(G91/G55,0) -> 1 | H93: =IFERROR(H91/H55,0) -> 1 | I93: =IFERROR(I91/I55,0) -> 1 | J93: =IFERROR(J91/J55,0) -> 1 | K93: =IFERROR(K91/K55,0) -> 1 | ... AC93: =IFERROR(AC91/AC55,0) -> 1
A94: Conservation check (allocated ≤ Starship total) | D94: =IF(D91<=D55+0.5,"OK","FAIL") -> OK | E94: =IF(E91<=E55+0.5,"OK","FAIL") -> OK | F94: =IF(F91<=F55+0.5,"OK","FAIL") -> OK | G94: =IF(G91<=G55+0.5,"OK","FAIL") -> OK | H94: =IF(H91<=H55+0.5,"OK","FAIL") -> OK | I94: =IF(I91<=I55+0.5,"OK","FAIL") -> OK | J94: =IF(J91<=J55+0.5,"OK","FAIL") -> OK | K94: =IF(K91<=K55+0.5,"OK","FAIL") -> OK | ... AC94: =IF(AC91<=AC55+0.5,"OK","FAIL") -> OK
A95: [Legacy] ▸ Layer 3 helpers (retired per Spec 07)
A96: [Legacy] Total sweep pool ($mm)
A97: [Legacy] Pool A — Starlink FCF overflow ($mm)
A98: [Legacy] Pool B — Idle capital reflow ($mm)
A99: [Legacy] ODC sweep share
A100: [Legacy] AI Stack sweep share
A101: [Legacy] Launch idle ($mm)
A102: [Legacy] Starlink idle ($mm)
A103: [Legacy] ODC idle ($mm)
A104: [Legacy] AI Stack idle ($mm)
A110: ═══ NEW CASH POOL TRACKER (Spec 07) ═══
A111: Starting cash EoY 2024 ($mm) | D111: =Assumptions!$B$466 -> 20000
A112: IPO injection this year ($mm) | D112: =IF(D$4=Assumptions!$B$468, Assumptions!$B$467, 0) -> 0 | E112: =IF(E$4=Assumptions!$B$468, Assumptions!$B$467, 0) -> 0 | F112: =IF(F$4=Assumptions!$B$468, Assumptions!$B$467, 0) -> 30000 | G112: =IF(G$4=Assumptions!$B$468, Assumptions!$B$467, 0) -> 0 | H112: =IF(H$4=Assumptions!$B$468, Assumptions!$B$467, 0) -> 0 | I112: =IF(I$4=Assumptions!$B$468, Assumptions!$B$467, 0) -> 0 | J112: =IF(J$4=Assumptions!$B$468, Assumptions!$B$467, 0) -> 0 | K112: =IF(K$4=Assumptions!$B$468, Assumptions!$B$467, 0) -> 0 | ... AC112: =IF(AC$4=Assumptions!$B$468, Assumptions!$B$467, 0) -> 0
A113: Group P&L FCF this year ($mm) | D113: {=INDEX('Group P&L'!$D$69:$AC$69, 1, D$4-2024)} -> 3112.5216 | E113: {=INDEX('Group P&L'!$D$69:$AC$69, 1, E$4-2024)} -> 232.93662 | F113: {=INDEX('Group P&L'!$D$69:$AC$69, 1, F$4-2024)} -> 3853.9284 | G113: {=INDEX('Group P&L'!$D$69:$AC$69, 1, G$4-2024)} -> 7609.3956 | H113: {=INDEX('Group P&L'!$D$69:$AC$69, 1, H$4-2024)} -> 10524.042 | I113: {=INDEX('Group P&L'!$D$69:$AC$69, 1, I$4-2024)} -> 10072.924 | J113: {=INDEX('Group P&L'!$D$69:$AC$69, 1, J$4-2024)} -> 10867.087 | K113: {=INDEX('Group P&L'!$D$69:$AC$69, 1, K$4-2024)} -> 10676.419 | ... AC113: {=INDEX('Group P&L'!$D$69:$AC$69, 1, AC$4-2024)} -> -37238.844
A114: Mars/Moon strategic earmark this year ($mm) — queue-side reservation, NOT a separate cash event | D114: =Assumptions!$B$471 -> 1000 | E114: {=MAX(Assumptions!$B$471, INDEX('Group P&L'!$D$69:$AC$69, 1, E$4-2025) * Assumptions!$B$470)} -> 1000 | F114: {=MAX(Assumptions!$B$471, INDEX('Group P&L'!$D$69:$AC$69, 1, F$4-2025) * Assumptions!$B$470)} -> 1000 | G114: {=MAX(Assumptions!$B$471, INDEX('Group P&L'!$D$69:$AC$69, 1, G$4-2025) * Assumptions!$B$470)} -> 1000 | H114: {=MAX(Assumptions!$B$471, INDEX('Group P&L'!$D$69:$AC$69, 1, H$4-2025) * Assumptions!$B$470)} -> 1141.4093 | I114: {=MAX(Assumptions!$B$471, INDEX('Group P&L'!$D$69:$AC$69, 1, I$4-2025) * Assumptions!$B$470)} -> 1578.6063 | J114: {=MAX(Assumptions!$B$471, INDEX('Group P&L'!$D$69:$AC$69, 1, J$4-2025) * Assumptions!$B$470)} -> 1510.9386 | K114: {=MAX(Assumptions!$B$471, INDEX('Group P&L'!$D$69:$AC$69, 1, K$4-2025) * Assumptions!$B$470)} -> 1630.063 | L114: {=MAX(Assumptions!$B$471, INDEX('Group P&L'!$D$69:$AC$69, 1, L$4-2025) * Assumptions!$B$470)} -> 1601.4629 | ... AC114: {=MAX(Assumptions!$B$471, INDEX('Group P&L'!$D$69:$AC$69, 1, AC$4-2025) * Assumptions!$B$470)} -> 6963.8725
A115: Non-module cash claims this year ($mm) = OpEx + Corp CapEx + Spectrum CapEx + Taxes | D115: {=INDEX('Group P&L'!$D$54:$AC$54,1,D$4-2024)+INDEX(CapEx!$D$21:$AC$21,1,D$4-2024)+INDEX(CapEx!$D$65:$AC$65,1,D$4-2024)+INDEX('Group P&L'!$D$64:$AC$64,1,D$4-2024)+IF(Assumptions!$B$497=1,D187,0)} -> 13113.813 | E115: {=INDEX('Group P&L'!$D$54:$AC$54,1,E$4-2024)+INDEX(CapEx!$D$21:$AC$21,1,E$4-2024)+INDEX(CapEx!$D$65:$AC$65,1,E$4-2024)+INDEX('Group P&L'!$D$64:$AC$64,1,E$4-2024)+IF(Assumptions!$B$497=1,E187,0)} -> 15715.801 | F115: {=INDEX('Group P&L'!$D$54:$AC$54,1,F$4-2024)+INDEX(CapEx!$D$21:$AC$21,1,F$4-2024)+INDEX(CapEx!$D$65:$AC$65,1,F$4-2024)+INDEX('Group P&L'!$D$64:$AC$64,1,F$4-2024)+IF(Assumptions!$B$497=1,F187,0)} -> 12746.808 | G115: {=INDEX('Group P&L'!$D$54:$AC$54,1,G$4-2024)+INDEX(CapEx!$D$21:$AC$21,1,G$4-2024)+INDEX(CapEx!$D$65:$AC$65,1,G$4-2024)+INDEX('Group P&L'!$D$64:$AC$64,1,G$4-2024)+IF(Assumptions!$B$497=1,G187,0)} -> 9973.1739 | H115: {=INDEX('Group P&L'!$D$54:$AC$54,1,H$4-2024)+INDEX(CapEx!$D$21:$AC$21,1,H$4-2024)+INDEX(CapEx!$D$65:$AC$65,1,H$4-2024)+INDEX('Group P&L'!$D$64:$AC$64,1,H$4-2024)+IF(Assumptions!$B$497=1,H187,0)} -> 8283.9052 | I115: {=INDEX('Group P&L'!$D$54:$AC$54,1,I$4-2024)+INDEX(CapEx!$D$21:$AC$21,1,I$4-2024)+INDEX(CapEx!$D$65:$AC$65,1,I$4-2024)+INDEX('Group P&L'!$D$64:$AC$64,1,I$4-2024)+IF(Assumptions!$B$497=1,I187,0)} -> 7984.4148 | J115: {=INDEX('Group P&L'!$D$54:$AC$54,1,J$4-2024)+INDEX(CapEx!$D$21:$AC$21,1,J$4-2024)+INDEX(CapEx!$D$65:$AC$65,1,J$4-2024)+INDEX('Group P&L'!$D$64:$AC$64,1,J$4-2024)+IF(Assumptions!$B$497=1,J187,0)} -> 8168.9476 | K115: {=INDEX('Group P&L'!$D$54:$AC$54,1,K$4-2024)+INDEX(CapEx!$D$21:$AC$21,1,K$4-2024)+INDEX(CapEx!$D$65:$AC$65,1,K$4-2024)+INDEX('Group P&L'!$D$64:$AC$64,1,K$4-2024)+IF(Assumptions!$B$497=1,K187,0)} -> 8375.6929 | ... AC115: {=INDEX('Group P&L'!$D$54:$AC$54,1,AC$4-2024)+INDEX(CapEx!$D$21:$AC$21,1,AC$4-2024)+INDEX(CapEx!$D$65:$AC$65,1,AC$4-2024)+INDEX('Group P&L'!$D$64:$AC$64,1,AC$4-2024)+IF(Assumptions!$B$497=1,AC187,0)} -> 12513.375
A116: Cash BoY ($mm) — year-chained (Rule 23 exception, intentional) | D116: =Assumptions!$B$466+D112 -> 20000 | E116: =D116+D113+E112 -> 23112.522 | F116: =E116+E113+F112 -> 53345.458 | G116: =F116+F113+G112 -> 57199.387 | H116: =G116+G113+H112 -> 64808.782 | I116: =H116+H113+I112 -> 75332.824 | J116: =I116+I113+J112 -> 85405.748 | K116: =J116+J113+K112 -> 96272.835 | L116: =K116+K113+L112 -> 106949.25 | ... AC116: =AB116+AB113+AC112 -> 339764.21
A117: Available cash for IRR queue this year ($mm) = Cash BoY − Mars earmark − non-module claims | D117: =MAX(0, D116-D114-D115) -> 5886.1874 | E117: =MAX(0, E116-E114-E115) -> 6396.7204 | F117: =MAX(0, F116-F114-F115) -> 39598.65 | G117: =MAX(0, G116-G114-G115) -> 46226.213 | H117: =MAX(0, H116-H114-H115) -> 55383.468 | I117: =MAX(0, I116-I114-I115) -> 65769.803 | J117: =MAX(0, J116-J114-J115) -> 75725.862 | K117: =MAX(0, K116-K114-K115) -> 86267.079 | ... AC117: =MAX(0, AC116-AC114-AC115) -> 320286.96
A118: Cash EoY ($mm) — diagnostic; chains to next-year BoY | D118: =D116+D113 -> 23112.522 | E118: =E116+E113 -> 23345.458 | F118: =F116+F113 -> 57199.387 | G118: =G116+G113 -> 64808.782 | H118: =H116+H113 -> 75332.824 | I118: =I116+I113 -> 85405.748 | J118: =J116+J113 -> 96272.835 | K118: =K116+K113 -> 106949.25 | ... AC118: =AC116+AC113 -> 302525.37
A119: Memo: Mars earmark vs Lunar Mars actual CapEx divergence ($mm) | D119: =D114-'Lunar Mars'!D101 -> 1000 | E119: =E114-'Lunar Mars'!E101 -> 1000 | F119: =F114-'Lunar Mars'!F101 -> 959.875 | G119: =G114-'Lunar Mars'!G101 -> 861.58333 | H119: =H114-'Lunar Mars'!H101 -> 1035.2843 | I119: =I114-'Lunar Mars'!I101 -> 1083.6063 | J119: =J114-'Lunar Mars'!J101 -> 1297.4386 | K119: =K114-'Lunar Mars'!K101 -> 631.39636 | ... AC119: =AC114-'Lunar Mars'!AC101 -> -76994.461
A120: Memo: Non-module claims (iteration diagnostic) | D120: =D115 -> 13113.813 | E120: =E115 -> 15715.801 | F120: =F115 -> 12746.808 | G120: =G115 -> 9973.1739 | H120: =H115 -> 8283.9052 | I120: =I115 -> 7984.4148 | J120: =J115 -> 8168.9476 | K120: =K115 -> 8375.6929 | ... AC120: =AC115 -> 12513.375
A121: ▸ Uncapped cash demand per module ($mm) — Spec 07 Patch E
A122: Launch uncapped cash demand | D122: =INDEX('Customer Launch'!D:D, MATCH("Cash Demand ($mm)", 'Customer Launch'!$A:$A, 0)) -> 240 | E122: =INDEX('Customer Launch'!E:E, MATCH("Cash Demand ($mm)", 'Customer Launch'!$A:$A, 0)) -> 236.45318 | F122: =INDEX('Customer Launch'!F:F, MATCH("Cash Demand ($mm)", 'Customer Launch'!$A:$A, 0)) -> 238.63025 | G122: =INDEX('Customer Launch'!G:G, MATCH("Cash Demand ($mm)", 'Customer Launch'!$A:$A, 0)) -> 208.55973 | H122: =INDEX('Customer Launch'!H:H, MATCH("Cash Demand ($mm)", 'Customer Launch'!$A:$A, 0)) -> 178.41674 | I122: =INDEX('Customer Launch'!I:I, MATCH("Cash Demand ($mm)", 'Customer Launch'!$A:$A, 0)) -> 148.88105 | J122: =INDEX('Customer Launch'!J:J, MATCH("Cash Demand ($mm)", 'Customer Launch'!$A:$A, 0)) -> 119.11335 | K122: =INDEX('Customer Launch'!K:K, MATCH("Cash Demand ($mm)", 'Customer Launch'!$A:$A, 0)) -> 89.619636 | L122: =INDEX('Customer Launch'!L:L, MATCH("Cash Demand ($mm)", 'Customer Launch'!$A:$A, 0)) -> 60.282317 | M122: =INDEX('Customer Launch'!M:M, MATCH("Cash Demand ($mm)", 'Customer Launch'!$A:$A, 0)) -> 30.935047 | N122: =INDEX('Customer Launch'!N:N, MATCH("Cash Demand ($mm)", 'Customer Launch'!$A:$A, 0)) -> 1.6666034 | O122: =INDEX('Customer Launch'!O:O, MATCH("Cash Demand ($mm)", 'Customer Launch'!$A:$A, 0)) -> 1.4196354 | P122: =INDEX('Customer Launch'!P:P, MATCH("Cash Demand ($mm)", 'Customer Launch'!$A:$A, 0)) -> 1.2076407 | Q122: =INDEX('Customer Launch'!Q:Q, MATCH("Cash Demand ($mm)", 'Customer Launch'!$A:$A, 0)) -> 1.0135881 | R122: =INDEX('Customer Launch'!R:R, MATCH("Cash Demand ($mm)", 'Customer Launch'!$A:$A, 0)) -> 0.8454509 | S122: =INDEX('Customer Launch'!S:S, MATCH("Cash Demand ($mm)", 'Customer Launch'!$A:$A, 0)) -> 0.69630649 | T122: =INDEX('Customer Launch'!T:T, MATCH("Cash Demand ($mm)", 'Customer Launch'!$A:$A, 0)) -> 0.80294205 | U122: =INDEX('Customer Launch'!U:U, MATCH("Cash Demand ($mm)", 'Customer Launch'!$A:$A, 0)) -> 0.45755257 | V122: =INDEX('Customer Launch'!V:V, MATCH("Cash Demand ($mm)", 'Customer Launch'!$A:$A, 0)) -> 0.36514772 | W122: =INDEX('Customer Launch'!W:W, MATCH("Cash Demand ($mm)", 'Customer Launch'!$A:$A, 0)) -> 0.28861473 | X122: =INDEX('Customer Launch'!X:X, MATCH("Cash Demand ($mm)", 'Customer Launch'!$A:$A, 0)) -> 0.25041193 | Y122: =INDEX('Customer Launch'!Y:Y, MATCH("Cash Demand ($mm)", 'Customer Launch'!$A:$A, 0)) -> 0.19539409 | Z122: =INDEX('Customer Launch'!Z:Z, MATCH("Cash Demand ($mm)", 'Customer Launch'!$A:$A, 0)) -> 0.15803987 | AA122: =INDEX('Customer Launch'!AA:AA, MATCH("Cash Demand ($mm)", 'Customer Launch'!$A:$A, 0)) -> 0.12178499 | AB122: =INDEX('Customer Launch'!AB:AB, MATCH("Cash Demand ($mm)", 'Customer Launch'!$A:$A, 0)) -> 0.15882759 | AC122: =INDEX('Customer Launch'!AC:AC, MATCH("Cash Demand ($mm)", 'Customer Launch'!$A:$A, 0)) -> 0.12138466
A123: Starlink uncapped cash demand | D123: =INDEX(Starlink!D:D, MATCH("Cash Demand ($mm)", Starlink!$A:$A, 0)) -> 100000 | E123: =INDEX(Starlink!E:E, MATCH("Cash Demand ($mm)", Starlink!$A:$A, 0)) -> 100000 | F123: =INDEX(Starlink!F:F, MATCH("Cash Demand ($mm)", Starlink!$A:$A, 0)) -> 100000 | G123: =INDEX(Starlink!G:G, MATCH("Cash Demand ($mm)", Starlink!$A:$A, 0)) -> 100000 | H123: =INDEX(Starlink!H:H, MATCH("Cash Demand ($mm)", Starlink!$A:$A, 0)) -> 100000 | I123: =INDEX(Starlink!I:I, MATCH("Cash Demand ($mm)", Starlink!$A:$A, 0)) -> 100000 | J123: =INDEX(Starlink!J:J, MATCH("Cash Demand ($mm)", Starlink!$A:$A, 0)) -> 100000 | K123: =INDEX(Starlink!K:K, MATCH("Cash Demand ($mm)", Starlink!$A:$A, 0)) -> 100000 | L123: =INDEX(Starlink!L:L, MATCH("Cash Demand ($mm)", Starlink!$A:$A, 0)) -> 100000 | M123: =INDEX(Starlink!M:M, MATCH("Cash Demand ($mm)", Starlink!$A:$A, 0)) -> 100000 | N123: =INDEX(Starlink!N:N, MATCH("Cash Demand ($mm)", Starlink!$A:$A, 0)) -> 100000 | O123: =INDEX(Starlink!O:O, MATCH("Cash Demand ($mm)", Starlink!$A:$A, 0)) -> 100000 | P123: =INDEX(Starlink!P:P, MATCH("Cash Demand ($mm)", Starlink!$A:$A, 0)) -> 100000 | Q123: =INDEX(Starlink!Q:Q, MATCH("Cash Demand ($mm)", Starlink!$A:$A, 0)) -> 100000 | R123: =INDEX(Starlink!R:R, MATCH("Cash Demand ($mm)", Starlink!$A:$A, 0)) -> 100000 | S123: =INDEX(Starlink!S:S, MATCH("Cash Demand ($mm)", Starlink!$A:$A, 0)) -> 100000 | T123: =INDEX(Starlink!T:T, MATCH("Cash Demand ($mm)", Starlink!$A:$A, 0)) -> 100000 | U123: =INDEX(Starlink!U:U, MATCH("Cash Demand ($mm)", Starlink!$A:$A, 0)) -> 100000 | V123: =INDEX(Starlink!V:V, MATCH("Cash Demand ($mm)", Starlink!$A:$A, 0)) -> 100000 | W123: =INDEX(Starlink!W:W, MATCH("Cash Demand ($mm)", Starlink!$A:$A, 0)) -> 100000 | X123: =INDEX(Starlink!X:X, MATCH("Cash Demand ($mm)", Starlink!$A:$A, 0)) -> 100000 | Y123: =INDEX(Starlink!Y:Y, MATCH("Cash Demand ($mm)", Starlink!$A:$A, 0)) -> 100000 | Z123: =INDEX(Starlink!Z:Z, MATCH("Cash Demand ($mm)", Starlink!$A:$A, 0)) -> 100000 | AA123: =INDEX(Starlink!AA:AA, MATCH("Cash Demand ($mm)", Starlink!$A:$A, 0)) -> 100000 | AB123: =INDEX(Starlink!AB:AB, MATCH("Cash Demand ($mm)", Starlink!$A:$A, 0)) -> 100000 | AC123: =INDEX(Starlink!AC:AC, MATCH("Cash Demand ($mm)", Starlink!$A:$A, 0)) -> 100000
A124: ODC uncapped cash demand | D124: =INDEX(ODC!D:D, MATCH("Cash Demand ($mm)", ODC!$A:$A, 0)) -> 0 | E124: =INDEX(ODC!E:E, MATCH("Cash Demand ($mm)", ODC!$A:$A, 0)) -> 956.77744 | F124: =INDEX(ODC!F:F, MATCH("Cash Demand ($mm)", ODC!$A:$A, 0)) -> 4543.9705 | G124: =INDEX(ODC!G:G, MATCH("Cash Demand ($mm)", ODC!$A:$A, 0)) -> 9705.3231 | H124: =INDEX(ODC!H:H, MATCH("Cash Demand ($mm)", ODC!$A:$A, 0)) -> 15727.4 | I124: =INDEX(ODC!I:I, MATCH("Cash Demand ($mm)", ODC!$A:$A, 0)) -> 15820.731 | J124: =INDEX(ODC!J:J, MATCH("Cash Demand ($mm)", ODC!$A:$A, 0)) -> 7778.3652 | K124: =INDEX(ODC!K:K, MATCH("Cash Demand ($mm)", ODC!$A:$A, 0)) -> 7711.6245 | L124: =INDEX(ODC!L:L, MATCH("Cash Demand ($mm)", ODC!$A:$A, 0)) -> 7690.1742 | M124: =INDEX(ODC!M:M, MATCH("Cash Demand ($mm)", ODC!$A:$A, 0)) -> 7671.2465 | N124: =INDEX(ODC!N:N, MATCH("Cash Demand ($mm)", ODC!$A:$A, 0)) -> 7654.0359 | O124: =INDEX(ODC!O:O, MATCH("Cash Demand ($mm)", ODC!$A:$A, 0)) -> 7647.758 | P124: =INDEX(ODC!P:P, MATCH("Cash Demand ($mm)", ODC!$A:$A, 0)) -> 7642.5861 | Q124: =INDEX(ODC!Q:Q, MATCH("Cash Demand ($mm)", ODC!$A:$A, 0)) -> 7638.2588 | R124: =INDEX(ODC!R:R, MATCH("Cash Demand ($mm)", ODC!$A:$A, 0)) -> 7634.5901 | S124: =INDEX(ODC!S:S, MATCH("Cash Demand ($mm)", ODC!$A:$A, 0)) -> 7631.4442 | T124: =INDEX(ODC!T:T, MATCH("Cash Demand ($mm)", ODC!$A:$A, 0)) -> 7628.7199 | U124: =INDEX(ODC!U:U, MATCH("Cash Demand ($mm)", ODC!$A:$A, 0)) -> 7626.3401 | V124: =INDEX(ODC!V:V, MATCH("Cash Demand ($mm)", ODC!$A:$A, 0)) -> 7624.2453 | W124: =INDEX(ODC!W:W, MATCH("Cash Demand ($mm)", ODC!$A:$A, 0)) -> 7622.3887 | X124: =INDEX(ODC!X:X, MATCH("Cash Demand ($mm)", ODC!$A:$A, 0)) -> 7620.7331 | Y124: =INDEX(ODC!Y:Y, MATCH("Cash Demand ($mm)", ODC!$A:$A, 0)) -> 7619.2486 | Z124: =INDEX(ODC!Z:Z, MATCH("Cash Demand ($mm)", ODC!$A:$A, 0)) -> 7617.9107 | AA124: =INDEX(ODC!AA:AA, MATCH("Cash Demand ($mm)", ODC!$A:$A, 0)) -> 7616.6994 | AB124: =INDEX(ODC!AB:AB, MATCH("Cash Demand ($mm)", ODC!$A:$A, 0)) -> 7615.5982 | AC124: =INDEX(ODC!AC:AC, MATCH("Cash Demand ($mm)", ODC!$A:$A, 0)) -> 7614.5932
A125: AI Stack uncapped cash demand | D125: =INDEX('AI Stack'!D:D, MATCH("Cash Demand ($mm)", 'AI Stack'!$A:$A, 0)) -> 0 | E125: =INDEX('AI Stack'!E:E, MATCH("Cash Demand ($mm)", 'AI Stack'!$A:$A, 0)) -> 0 | F125: =INDEX('AI Stack'!F:F, MATCH("Cash Demand ($mm)", 'AI Stack'!$A:$A, 0)) -> 0 | G125: =INDEX('AI Stack'!G:G, MATCH("Cash Demand ($mm)", 'AI Stack'!$A:$A, 0)) -> 0 | H125: =INDEX('AI Stack'!H:H, MATCH("Cash Demand ($mm)", 'AI Stack'!$A:$A, 0)) -> 0 | I125: =INDEX('AI Stack'!I:I, MATCH("Cash Demand ($mm)", 'AI Stack'!$A:$A, 0)) -> 0 | J125: =INDEX('AI Stack'!J:J, MATCH("Cash Demand ($mm)", 'AI Stack'!$A:$A, 0)) -> 0 | K125: =INDEX('AI Stack'!K:K, MATCH("Cash Demand ($mm)", 'AI Stack'!$A:$A, 0)) -> 0 | L125: =INDEX('AI Stack'!L:L, MATCH("Cash Demand ($mm)", 'AI Stack'!$A:$A, 0)) -> 0 | M125: =INDEX('AI Stack'!M:M, MATCH("Cash Demand ($mm)", 'AI Stack'!$A:$A, 0)) -> 0 | N125: =INDEX('AI Stack'!N:N, MATCH("Cash Demand ($mm)", 'AI Stack'!$A:$A, 0)) -> 0 | O125: =INDEX('AI Stack'!O:O, MATCH("Cash Demand ($mm)", 'AI Stack'!$A:$A, 0)) -> 0 | P125: =INDEX('AI Stack'!P:P, MATCH("Cash Demand ($mm)", 'AI Stack'!$A:$A, 0)) -> 0 | Q125: =INDEX('AI Stack'!Q:Q, MATCH("Cash Demand ($mm)", 'AI Stack'!$A:$A, 0)) -> 0 | R125: =INDEX('AI Stack'!R:R, MATCH("Cash Demand ($mm)", 'AI Stack'!$A:$A, 0)) -> 0 | S125: =INDEX('AI Stack'!S:S, MATCH("Cash Demand ($mm)", 'AI Stack'!$A:$A, 0)) -> 0 | T125: =INDEX('AI Stack'!T:T, MATCH("Cash Demand ($mm)", 'AI Stack'!$A:$A, 0)) -> 0 | U125: =INDEX('AI Stack'!U:U, MATCH("Cash Demand ($mm)", 'AI Stack'!$A:$A, 0)) -> 0 | V125: =INDEX('AI Stack'!V:V, MATCH("Cash Demand ($mm)", 'AI Stack'!$A:$A, 0)) -> 0 | W125: =INDEX('AI Stack'!W:W, MATCH("Cash Demand ($mm)", 'AI Stack'!$A:$A, 0)) -> 0 | X125: =INDEX('AI Stack'!X:X, MATCH("Cash Demand ($mm)", 'AI Stack'!$A:$A, 0)) -> 0 | Y125: =INDEX('AI Stack'!Y:Y, MATCH("Cash Demand ($mm)", 'AI Stack'!$A:$A, 0)) -> 0 | Z125: =INDEX('AI Stack'!Z:Z, MATCH("Cash Demand ($mm)", 'AI Stack'!$A:$A, 0)) -> 0 | AA125: =INDEX('AI Stack'!AA:AA, MATCH("Cash Demand ($mm)", 'AI Stack'!$A:$A, 0)) -> 0 | AB125: =INDEX('AI Stack'!AB:AB, MATCH("Cash Demand ($mm)", 'AI Stack'!$A:$A, 0)) -> 0 | AC125: =INDEX('AI Stack'!AC:AC, MATCH("Cash Demand ($mm)", 'AI Stack'!$A:$A, 0)) -> 0
A127: ▸ IRR-masked cash demand ($mm) — negative IRR → zero
...

Sheet Launch Capacity
A1: LAUNCH CAPACITY
A2: Starship + Falcon 9 — fleet × cadence × payload, with cost curves
A4: Year | D4: 2025 | E4: 2026 | F4: 2027 | G4: 2028 | H4: 2029 | I4: 2030 | J4: 2031 | K4: 2032 | L4: 2033 | M4: 2034 | N4: 2035 | O4: 2036 | P4: 2037 | Q4: 2038 | R4: 2039 | S4: 2040 | T4: 2041 | U4: 2042 | V4: 2043 | W4: 2044 | X4: 2045 | Y4: 2046 | Z4: 2047 | AA4: 2048 | AB4: 2049 | AC4: 2050
A6: OUTPUTS — FALCON 9 (feeds Launch module)
A7: Total F9 launches available | D7: =D72 -> 336 | E7: =E72 -> 432 | F7: =F72 -> 528 | G7: =G72 -> 618 | H7: =H72 -> 696 | I7: =I72 -> 762 | J7: =J72 -> 816 | K7: =K72 -> 858 | ... AC7: =AC72 -> 912
A8: F9 cost per launch ($mm, blended) | D8: =D68 -> 17.75 | E8: =E68 -> 17.727832 | F8: =F68 -> 17.72 | G8: =G68 -> 17.714179 | H8: =H68 -> 17.709767 | I8: =I68 -> 17.706419 | J8: =J68 -> 17.703923 | K8: =K68 -> 17.702146 | ... AC8: =AC68 -> 17.700443
A9: F9 annual capacity (kg-to-LEO) | D9: =D73 -> 7660800 | E9: =E73 -> 9849600 | F9: =F73 -> 12038400 | G9: =G73 -> 14090400 | H9: =H73 -> 15868800 | I9: =I73 -> 17373600 | J9: =J73 -> 18604800 | K9: =K73 -> 19562400 | ... AC9: =AC73 -> 20793600
A11: OUTPUTS — STARSHIP (feeds Allocator Layer 2 at D23)
A23: Total Annual Capacity (kg-to-LEO) ← EXTERNAL REF: Allocator!D38, Dashboard!D46 | D23: =D144 -> 150000 | E23: =E144 -> 145833.33 | F23: =F144 -> 166224.03 | G23: =G144 -> 179613.66 | H23: =H144 -> 178825.75 | I23: =I144 -> 175551.24 | J23: =J144 -> 179180.09 | K23: =K144 -> 179343.62 | ... AC23: =AC144 -> 247339.5
A24: Total Annual Launches | D24: =D143 -> 1 | E24: =E143 -> 1 | F24: =F143 -> 1.1733461 | G24: =G143 -> 1.3062812 | H24: =H143 -> 1.4164415 | I24: =I143 -> 1.5265325 | J24: =J143 -> 1.6289099 | K24: =K143 -> 1.7080345 | ... AC24: =AC143 -> 2.4130683
A25: Average $/kg | D25: =D146 -> 390 | E25: =E146 -> 267.696 | F25: =F146 -> 216.27445 | G25: =G146 -> 185.47253 | H25: =H146 -> 146.22114 | I25: =I146 -> 105.01218 | J25: =J146 -> 81.201868 | K25: =K146 -> 57.3659 | ... AC25: =AC146 -> 22.71187
A27: OUTPUTS — COMBINED FLEET
A28: Combined fleet blended $/kg | D28: =(D8*D7+D141*D143)/(D7+D143) -> 17.87092 | E28: =IFERROR((E8*E7+E141*E143)/(E7+E143),0) -> 17.77705 | F28: =IFERROR((F8*F7+F141*F143)/(F7+F143),0) -> 17.748645 | G28: =IFERROR((G8*G7+G141*G143)/(G7+G143),0) -> 17.730607 | H28: =IFERROR((H8*H7+H141*H143)/(H7+H143),0) -> 17.711292 | I28: =IFERROR((I8*I7+I141*I143)/(I7+I143),0) -> 17.695163 | J28: =IFERROR((J8*J7+J141*J143)/(J7+J143),0) -> 17.686448 | K28: =IFERROR((K8*K7+K141*K143)/(K7+K143),0) -> 17.678943 | L28: =IFERROR((L8*L7+L141*L143)/(L7+L143),0) -> 17.675916 | ... AC28: =IFERROR((AC8*AC7+AC141*AC143)/(AC7+AC143),0) -> 17.659876
A30: ══════════ FALCON 9 ══════════
A32: SECTION F1 — INPUTS FROM ASSUMPTIONS
A33: F9 booster (1st stage) mfg cost ($mm) | B33: =Assumptions!B170 -> 30
A34: F9 2nd stage mfg cost ($mm, expendable) | B34: =Assumptions!B171 -> 10
A35: F9 fairing cost ($mm, net of 75% recovery) | B35: =Assumptions!B172 -> 1.25
A36: F9 per-launch ops cost ($mm) | B36: =Assumptions!B173 -> 5
A37: F9 booster refurb % of mfg | B37: =Assumptions!B174 -> 0.03
A38: F9 payload to LEO (kg) | B38: =Assumptions!B175 -> 22800
A39: F9 lifetime reuses per booster | B39: =Assumptions!B176 -> 50
A40: F9 Wright's Law mfg learning rate | B40: =Assumptions!B177 -> 0.02
A41: F9 cadence per booster (flights/yr, flat) | B41: =Assumptions!B178 -> 12
A42: F9 base booster build rate (boosters/year) | B42: =Assumptions!B179 -> 8
A43: V3 Starlink launch trigger year | B43: =Assumptions!B180 -> 2027
A44: F9 build-rate decay window (years) | B44: =Assumptions!B181 -> 8
A45: F9 seed fleet (boosters at start of 2025) | B45: =Assumptions!B185 -> 24
A50: SECTION F2 — FLEET BUILD (build rate decays once V3 Starship trigger fires)
A51: Boosters in fleet (start of year) | D51: =$B$45 -> 24 | E51: =D54 -> 32 | F51: =E54 -> 40 | G51: =F54 -> 48 | H51: =G54 -> 55 | I51: =H54 -> 61 | J51: =I54 -> 66 | K51: =J54 -> 70 | L51: =K54 -> 73 | ... AC51: =AB54 -> 76
A52: Boosters built this year | D52: =IF(D$4<$B$43,$B$42,MAX(0,$B$42*(1-(D$4-$B$43)/$B$44))) -> 8 | E52: =IF(E$4<$B$43,$B$42,MAX(0,$B$42*(1-(E$4-$B$43)/$B$44))) -> 8 | F52: =IF(F$4<$B$43,$B$42,MAX(0,$B$42*(1-(F$4-$B$43)/$B$44))) -> 8 | G52: =IF(G$4<$B$43,$B$42,MAX(0,$B$42*(1-(G$4-$B$43)/$B$44))) -> 7 | H52: =IF(H$4<$B$43,$B$42,MAX(0,$B$42*(1-(H$4-$B$43)/$B$44))) -> 6 | I52: =IF(I$4<$B$43,$B$42,MAX(0,$B$42*(1-(I$4-$B$43)/$B$44))) -> 5 | J52: =IF(J$4<$B$43,$B$42,MAX(0,$B$42*(1-(J$4-$B$43)/$B$44))) -> 4 | K52: =IF(K$4<$B$43,$B$42,MAX(0,$B$42*(1-(K$4-$B$43)/$B$44))) -> 3 | ... AC52: =IF(AC$4<$B$43,$B$42,MAX(0,$B$42*(1-(AC$4-$B$43)/$B$44))) -> 0
A53: Boosters retired this year (80% of lifetime cap) | D53: =IFERROR(MAX(0,(D51+D52)*MIN(1,MAX(0,(D55-0.8*$B$39)/(0.2*$B$39)))),0) -> 0 | E53: =IFERROR(MIN(E51+E52,(E51+E52)*E$57/$B$39),0) -> 0 | F53: =IFERROR(MIN(F51+F52,(F51+F52)*F$57/$B$39),0) -> 0 | G53: =IFERROR(MIN(G51+G52,(G51+G52)*G$57/$B$39),0) -> 0 | H53: =IFERROR(MIN(H51+H52,(H51+H52)*H$57/$B$39),0) -> 0 | I53: =IFERROR(MIN(I51+I52,(I51+I52)*I$57/$B$39),0) -> 0 | J53: =IFERROR(MIN(J51+J52,(J51+J52)*J$57/$B$39),0) -> 0 | K53: =IFERROR(MIN(K51+K52,(K51+K52)*K$57/$B$39),0) -> 0 | L53: =IFERROR(MIN(L51+L52,(L51+L52)*L$57/$B$39),0) -> 0 | ... AC53: =IFERROR(MIN(AC51+AC52,(AC51+AC52)*AC$57/$B$39),0) -> 0
A54: Boosters in fleet (end of year) | D54: =MAX(0,D51+D52-D53) -> 32 | E54: =MAX(0,E51+E52-E53) -> 40 | F54: =MAX(0,F51+F52-F53) -> 48 | G54: =MAX(0,G51+G52-G53) -> 55 | H54: =MAX(0,H51+H52-H53) -> 61 | I54: =MAX(0,I51+I52-I53) -> 66 | J54: =MAX(0,J51+J52-J53) -> 70 | K54: =MAX(0,K51+K52-K53) -> 73 | ... AC54: =MAX(0,AC51+AC52-AC53) -> 76
A55: Avg cum flights per booster (lifetime usage) | D55: =IFERROR(D58/((D51+D54)/2),0) -> 12 | E55: =IFERROR(IF(E54=0,0,(D55*D54+E58)/MAX(1,(D54+E52))),0) -> 20.4 | F55: =IFERROR(IF(F54=0,0,(E55*E54+F58)/MAX(1,(E54+F52))),0) -> 28 | G55: =IFERROR(IF(G54=0,0,(F55*F54+G58)/MAX(1,(F54+G52))),0) -> 35.672727 | H55: =IFERROR(IF(H54=0,0,(G55*G54+H58)/MAX(1,(G54+H52))),0) -> 43.57377 | I55: =IFERROR(IF(I54=0,0,(H55*H54+I58)/MAX(1,(H54+I52))),0) -> 51.818182 | J55: =IFERROR(IF(J54=0,0,(I55*I54+J58)/MAX(1,(I54+J52))),0) -> 60.514286 | K55: =IFERROR(IF(K54=0,0,(J55*J54+K58)/MAX(1,(J54+K52))),0) -> 69.780822 | L55: =IFERROR(IF(L54=0,0,(K55*K54+L58)/MAX(1,(K54+L52))),0) -> 79.76 | ... AC55: =IFERROR(IF(AC54=0,0,(AB55*AB54+AC58)/MAX(1,(AB54+AC52))),0) -> 282.63158
A56: Cumulative F9 boosters ever built (running total) | D56: =D51+D52 -> 32 | E56: =D56+E52 -> 40 | F56: =E56+F52 -> 48 | G56: =F56+G52 -> 55 | H56: =G56+H52 -> 61 | I56: =H56+I52 -> 66 | J56: =I56+J52 -> 70 | K56: =J56+K52 -> 73 | L56: =K56+L52 -> 75 | ... AC56: =AB56+AC52 -> 76
A57: SECTION F3 — CADENCE & ANNUAL LAUNCHES
A58: Total F9 launches this year (avg fleet × cadence) | D58: =((D51+D54)/2)*$B$41 -> 336 | E58: =((E51+E54)/2)*$B$41 -> 432 | F58: =((F51+F54)/2)*$B$41 -> 528 | G58: =((G51+G54)/2)*$B$41 -> 618 | H58: =((H51+H54)/2)*$B$41 -> 696 | I58: =((I51+I54)/2)*$B$41 -> 762 | J58: =((J51+J54)/2)*$B$41 -> 816 | K58: =((K51+K54)/2)*$B$41 -> 858 | ... AC58: =((AC51+AC54)/2)*$B$41 -> 912
A59: Cumulative F9 booster flights (running total) | D59: =D58 -> 336 | E59: =D59+E58 -> 768 | F59: =E59+F58 -> 1296 | G59: =F59+G58 -> 1914 | H59: =G59+H58 -> 2610 | I59: =H59+I58 -> 3372 | J59: =I59+J58 -> 4188 | K59: =J59+K58 -> 5046 | L59: =K59+L58 -> 5934 | ... AC59: =AB59+AC58 -> 21432
A61: SECTION F4 — PER-LAUNCH COST BUILD
A62: Booster mfg cost this year (Wright's Law @ 2%) | D62: =$B$33 -> 30 | E62: =$B$33*(1-$B$40)^IFERROR(LOG(E56/$B$45,2),0) -> 29.556648 | F62: =$B$33*(1-$B$40)^IFERROR(LOG(F56/$B$45,2),0) -> 29.4 | G62: =$B$33*(1-$B$40)^IFERROR(LOG(G56/$B$45,2),0) -> 29.283579 | H62: =$B$33*(1-$B$40)^IFERROR(LOG(H56/$B$45,2),0) -> 29.195339 | I62: =$B$33*(1-$B$40)^IFERROR(LOG(I56/$B$45,2),0) -> 29.128379 | J62: =$B$33*(1-$B$40)^IFERROR(LOG(J56/$B$45,2),0) -> 29.078467 | K62: =$B$33*(1-$B$40)^IFERROR(LOG(K56/$B$45,2),0) -> 29.042923 | L62: =$B$33*(1-$B$40)^IFERROR(LOG(L56/$B$45,2),0) -> 29.020052 | ... AC62: =$B$33*(1-$B$40)^IFERROR(LOG(AC56/$B$45,2),0) -> 29.008851
A63: Amortized booster cost per launch ($mm) | D63: =D62/$B$39 -> 0.6 | E63: =IFERROR(E62/$B$39,0) -> 0.59113295 | F63: =IFERROR(F62/$B$39,0) -> 0.588 | G63: =IFERROR(G62/$B$39,0) -> 0.58567158 | H63: =IFERROR(H62/$B$39,0) -> 0.58390679 | I63: =IFERROR(I62/$B$39,0) -> 0.58256757 | J63: =IFERROR(J62/$B$39,0) -> 0.58156934 | K63: =IFERROR(K62/$B$39,0) -> 0.58085845 | L63: =IFERROR(L62/$B$39,0) -> 0.58040104 | ... AC63: =IFERROR(AC62/$B$39,0) -> 0.58017702
A64: Booster refurb per flight ($mm) | D64: =D62*$B$37 -> 0.9 | E64: =$B$36 -> 5 | F64: =$B$36 -> 5 | G64: =$B$36 -> 5 | H64: =$B$36 -> 5 | I64: =$B$36 -> 5 | J64: =$B$36 -> 5 | K64: =$B$36 -> 5 | L64: =$B$36 -> 5 | ... AC64: =$B$36 -> 5
A65: 2nd stage cost per launch ($mm, expendable) | D65: =$B$34 -> 10 | E65: =$B$34 -> 10 | F65: =$B$34 -> 10 | G65: =$B$34 -> 10 | H65: =$B$34 -> 10 | I65: =$B$34 -> 10 | J65: =$B$34 -> 10 | K65: =$B$34 -> 10 | ... AC65: =$B$34 -> 10
A66: Fairing net cost per launch ($mm) | D66: =$B$35 -> 1.25 | E66: =$B$35 -> 1.25 | F66: =$B$35 -> 1.25 | G66: =$B$35 -> 1.25 | H66: =$B$35 -> 1.25 | I66: =$B$35 -> 1.25 | J66: =$B$35 -> 1.25 | K66: =$B$35 -> 1.25 | ... AC66: =$B$35 -> 1.25
A67: Operations cost per launch ($mm) | D67: =$B$36 -> 5 | E67: =E62*$B$37 -> 0.88669943 | F67: =F62*$B$37 -> 0.882 | G67: =G62*$B$37 -> 0.87850737 | H67: =H62*$B$37 -> 0.87586018 | I67: =I62*$B$37 -> 0.87385136 | J67: =J62*$B$37 -> 0.872354 | K67: =K62*$B$37 -> 0.87128768 | L67: =L62*$B$37 -> 0.87060156 | ... AC67: =AC62*$B$37 -> 0.87026553
A68: Total F9 cost per launch ($mm) | D68: =D63+D64+D65+D66+D67 -> 17.75 | E68: =E63+E64+E65+E66+E67 -> 17.727832 | F68: =F63+F64+F65+F66+F67 -> 17.72 | G68: =G63+G64+G65+G66+G67 -> 17.714179 | H68: =H63+H64+H65+H66+H67 -> 17.709767 | I68: =I63+I64+I65+I66+I67 -> 17.706419 | J68: =J63+J64+J65+J66+J67 -> 17.703923 | K68: =K63+K64+K65+K66+K67 -> 17.702146 | ... AC68: =AC63+AC64+AC65+AC66+AC67 -> 17.700443
A69: F9 $/kg | D69: =IFERROR(D68*1000000/$B$38,0) -> 778.50877 | E69: =IFERROR(E68*1000000/$B$38,0) -> 777.53651 | F69: =IFERROR(F68*1000000/$B$38,0) -> 777.19298 | G69: =IFERROR(G68*1000000/$B$38,0) -> 776.93767 | H69: =IFERROR(H68*1000000/$B$38,0) -> 776.74417 | I69: =IFERROR(I68*1000000/$B$38,0) -> 776.59732 | J69: =IFERROR(J68*1000000/$B$38,0) -> 776.48787 | K69: =IFERROR(K68*1000000/$B$38,0) -> 776.40992 | ... AC69: =IFERROR(AC68*1000000/$B$38,0) -> 776.3352
A71: SECTION F5 — F9 OUTPUTS
A72: Total F9 launches available this year | D72: =D58 -> 336 | E72: =E58 -> 432 | F72: =F58 -> 528 | G72: =G58 -> 618 | H72: =H58 -> 696 | I72: =I58 -> 762 | J72: =J58 -> 816 | K72: =K58 -> 858 | ... AC72: =AC58 -> 912
A73: F9 kg-to-LEO capacity | D73: =D72*$B$38 -> 7660800 | E73: =E72*$B$38 -> 9849600 | F73: =F72*$B$38 -> 12038400 | G73: =G72*$B$38 -> 14090400 | H73: =H72*$B$38 -> 15868800 | I73: =I72*$B$38 -> 17373600 | J73: =J72*$B$38 -> 18604800 | K73: =K72*$B$38 -> 19562400 | ... AC73: =AC72*$B$38 -> 20793600
A74: Total F9 launch cost ($mm/year) | D74: =D72*D68 -> 5964 | E74: =E68*E72 -> 7658.4236 | F74: =F68*F72 -> 9356.16 | G74: =G68*G72 -> 10947.363 | H74: =H68*H72 -> 12325.998 | I74: =I68*I72 -> 13492.291 | J74: =J68*J72 -> 14446.401 | K74: =K68*K72 -> 15188.441 | L74: =L68*L72 -> 15718.49 | ... AC74: =AC68*AC72 -> 16142.804
A75: F9 fleet book value ($mm, mfg × fleet) | D75: =D54*D62 -> 960 | E75: =E62*E52 -> 236.45318 | F75: =F62*F52 -> 235.2 | G75: =G62*G52 -> 204.98505 | H75: =H62*H52 -> 175.17204 | I75: =I62*I52 -> 145.64189 | J75: =J62*J52 -> 116.31387 | K75: =K62*K52 -> 87.128768 | L75: =L62*L52 -> 58.040104 | ... AC75: =AC62*AC52 -> 0
A77: ═════ STARSHIP SECTIONS ═════
A79: SECTION S1 — INPUTS FROM ASSUMPTIONS
A80: Super Heavy manufacturing cost ($mm/unit, base) | B80: =Assumptions!B144 -> 35.1
A81: Starship 2nd-stage manufacturing cost ($mm/unit, base) | B81: =Assumptions!B145 -> 23.4
A82: Per-launch operations cost ($mm) | B82: =Assumptions!B146 -> 0
A83: Booster refurb % of manufacturing | B83: =Assumptions!B147 -> 0
A84: Ship refurb % of manufacturing | B84: =Assumptions!B148 -> 0.02
A85: Payload — booster-only mode (kg) | B85: =Assumptions!B149 -> 150000
A86: Payload — fully reusable mode (kg) | B86: =Assumptions!B150 -> 100000
A87: Lifetime reuses per ship (cap) | B87: =Assumptions!B151 -> 30
A88: Manufacturing learning rate | B88: =Assumptions!B152 -> 0.1
A89: Base turnaround time per booster (years/flight) | B89: =Assumptions!B153 -> 1
A90: WL learning rate — turnaround vs cum upmass | B90: =Assumptions!B154 -> 0.145
A91: Anchor year for cum-upmass Wright's Law | B91: =Assumptions!B155 -> 2025
... A93: Max annual production growth rate (multiplier) | B93: =Assumptions!B157 -> 2
A94: Variant mix (% fully reusable, year-row) | D94: =Assumptions!D160 -> 0 | E94: =Assumptions!E160 -> 0.083333333 | F94: =Assumptions!F160 -> 0.16666667 | G94: =Assumptions!G160 -> 0.25 | H94: =Assumptions!H160 -> 0.475 | I94: =Assumptions!I160 -> 0.7 | J94: =Assumptions!J160 -> 0.8 | K94: =Assumptions!K160 -> 0.9 | ... AC94: =Assumptions!AC160 -> 0.95
A95: Lifetime reuses per booster (year cap) | D95: =Assumptions!D163 -> 5 | E95: =Assumptions!E163 -> 10 | F95: =Assumptions!F163 -> 15 | G95: =Assumptions!G163 -> 20 | H95: =Assumptions!H163 -> 25 | I95: =Assumptions!I163 -> 30 | J95: =Assumptions!J163 -> 34 | K95: =Assumptions!K163 -> 38 | ... AC95: =Assumptions!AC163 -> 100
A96: Boosters built per year (Assumptions stub) | D96: =IF(Assumptions!$B$323=0,Assumptions!D161,FLOOR(MAX(0,Allocator!D186)*Assumptions!$B$325,1)) -> 0 | E96: =IF(Assumptions!$B$323=0,Assumptions!E161,FLOOR(MAX(0,Allocator!E186)*Assumptions!$B$325,1)) -> 0 | F96: =IF(Assumptions!$B$323=0,Assumptions!F161,FLOOR(MAX(0,Allocator!F186)*Assumptions!$B$325,1)) -> 0 | G96: =IF(Assumptions!$B$323=0,Assumptions!G161,FLOOR(MAX(0,Allocator!G186)*Assumptions!$B$325,1)) -> 0 | H96: =IF(Assumptions!$B$323=0,Assumptions!H161,FLOOR(MAX(0,Allocator!H186)*Assumptions!$B$325,1)) -> 0 | I96: =IF(Assumptions!$B$323=0,Assumptions!I161,FLOOR(MAX(0,Allocator!I186)*Assumptions!$B$325,1)) -> 0 | J96: =IF(Assumptions!$B$323=0,Assumptions!J161,FLOOR(MAX(0,Allocator!J186)*Assumptions!$B$325,1)) -> 0 | K96: =IF(Assumptions!$B$323=0,Assumptions!K161,FLOOR(MAX(0,Allocator!K186)*Assumptions!$B$325,1)) -> 0 | ... AC96: =IF(Assumptions!$B$323=0,Assumptions!AC161,FLOOR(MAX(0,Allocator!AC186)*Assumptions!$B$325,1)) -> 0
A97: Ships built per year (Assumptions stub) | D97: =IF(Assumptions!$B$323=0,Assumptions!D162,FLOOR(MAX(0,Allocator!D186)*(1-Assumptions!$B$325),1)) -> 0 | E97: =IF(Assumptions!$B$323=0,Assumptions!E162,FLOOR(MAX(0,Allocator!E186)*(1-Assumptions!$B$325),1)) -> 0 | F97: =IF(Assumptions!$B$323=0,Assumptions!F162,FLOOR(MAX(0,Allocator!F186)*(1-Assumptions!$B$325),1)) -> 0 | G97: =IF(Assumptions!$B$323=0,Assumptions!G162,FLOOR(MAX(0,Allocator!G186)*(1-Assumptions!$B$325),1)) -> 0 | H97: =IF(Assumptions!$B$323=0,Assumptions!H162,FLOOR(MAX(0,Allocator!H186)*(1-Assumptions!$B$325),1)) -> 0 | I97: =IF(Assumptions!$B$323=0,Assumptions!I162,FLOOR(MAX(0,Allocator!I186)*(1-Assumptions!$B$325),1)) -> 0 | J97: =IF(Assumptions!$B$323=0,Assumptions!J162,FLOOR(MAX(0,Allocator!J186)*(1-Assumptions!$B$325),1)) -> 0 | K97: =IF(Assumptions!$B$323=0,Assumptions!K162,FLOOR(MAX(0,Allocator!K186)*(1-Assumptions!$B$325),1)) -> 0 | ... AC97: =IF(Assumptions!$B$323=0,Assumptions!AC162,FLOOR(MAX(0,Allocator!AC186)*(1-Assumptions!$B$325),1)) -> 0
A99: SECTION S2 — FLEET BUILD
A100: Boosters in fleet (start of year) | D100: 1 | E100: =D103 -> 1 | F100: =E103 -> 1 | G100: =F103 -> 1 | H100: =G103 -> 1 | I100: =H103 -> 1 | J100: =I103 -> 1 | K100: =J103 -> 1 | L100: =K103 -> 1 | ... AC100: =AB103 -> 1
A101: Boosters built this year | D101: =D96 -> 0 | E101: =E96 -> 0 | F101: =F96 -> 0 | G101: =G96 -> 0 | H101: =H96 -> 0 | I101: =I96 -> 0 | J101: =J96 -> 0 | K101: =K96 -> 0 | ... AC101: =AC96 -> 0
A102: Boosters retired this year (gate at 80% lifetime) | D102: =IFERROR(MAX(0,(D100+D101)*MIN(1,MAX(0,(D110-0.8*D95)/(0.2*D95)))),0) -> 0 | E102: =IFERROR(MAX(0,(E100+E101)*MIN(1,MAX(0,(E124/(E100+E101)-0.8*E95)/(0.2*E95)))),0) -> 0 | F102: =IFERROR(MAX(0,(F100+F101)*MIN(1,MAX(0,(F124/(F100+F101)-0.8*F95)/(0.2*F95)))),0) -> 0 | G102: =IFERROR(MAX(0,(G100+G101)*MIN(1,MAX(0,(G124/(G100+G101)-0.8*G95)/(0.2*G95)))),0) -> 0 | H102: =IFERROR(MAX(0,(H100+H101)*MIN(1,MAX(0,(H124/(H100+H101)-0.8*H95)/(0.2*H95)))),0) -> 0 | I102: =IFERROR(MAX(0,(I100+I101)*MIN(1,MAX(0,(I124/(I100+I101)-0.8*I95)/(0.2*I95)))),0) -> 0 | J102: =IFERROR(MAX(0,(J100+J101)*MIN(1,MAX(0,(J124/(J100+J101)-0.8*J95)/(0.2*J95)))),0) -> 0 | K102: =IFERROR(MAX(0,(K100+K101)*MIN(1,MAX(0,(K124/(K100+K101)-0.8*K95)/(0.2*K95)))),0) -> 0 | L102: =IFERROR(MAX(0,(L100+L101)*MIN(1,MAX(0,(L124/(L100+L101)-0.8*L95)/(0.2*L95)))),0) -> 0 | ... AC102: =IFERROR(MAX(0,(AC100+AC101)*MIN(1,MAX(0,(AC124/(AC100+AC101)-0.8*AC95)/(0.2*AC95)))),0) -> 0
A103: Boosters in fleet (end of year) | D103: =MAX(0,D100+D101-D102) -> 1 | E103: =MAX(0,E100+E101-E102) -> 1 | F103: =MAX(0,F100+F101-F102) -> 1 | G103: =MAX(0,G100+G101-G102) -> 1 | H103: =MAX(0,H100+H101-H102) -> 1 | I103: =MAX(0,I100+I101-I102) -> 1 | J103: =MAX(0,J100+J101-J102) -> 1 | K103: =MAX(0,K100+K101-K102) -> 1 | ... AC103: =MAX(0,AC100+AC101-AC102) -> 1
A104: Cumulative boosters built (running total) | D104: =D100+D101 -> 1 | E104: =D104+E101 -> 1 | F104: =E104+F101 -> 1 | G104: =F104+G101 -> 1 | H104: =G104+H101 -> 1 | I104: =H104+I101 -> 1 | J104: =I104+J101 -> 1 | K104: =J104+K101 -> 1 | L104: =K104+L101 -> 1 | ... AC104: =AB104+AC101 -> 1
A105: Ships in fleet (start of year) | D105: 1 | E105: =D108 -> 1 | F105: =E108 -> 0.99722222 | G105: =F108 -> 0.99070363 | H105: =G108 -> 0.97981796 | I105: =H108 -> 0.95739097 | J105: =I108 -> 0.92177187 | K105: =J108 -> 0.87833427 | L105: =K108 -> 0.82709324 | ... AC105: =AB108 -> 0
A106: Ships entering fleet this year (reusable) | D106: =D97*D94 -> 0 | E106: =E97*E94 -> 0 | F106: =F97*F94 -> 0 | G106: =G97*G94 -> 0 | H106: =H97*H94 -> 0 | I106: =I97*I94 -> 0 | J106: =J97*J94 -> 0 | K106: =K97*K94 -> 0 | ... AC106: =AC97*AC94 -> 0
A107: Ships retired (reusable wear-out, year cap) | D107: =IFERROR(D115/$B$87,0) -> 0 | E107: =IFERROR(E115/$B$87,0) -> 0.0027777778 | F107: =IFERROR(F115/$B$87,0) -> 0.0065185895 | G107: =IFERROR(G115/$B$87,0) -> 0.010885676 | H107: =IFERROR(H115/$B$87,0) -> 0.022426991 | I107: =IFERROR(I115/$B$87,0) -> 0.035619093 | J107: =IFERROR(J115/$B$87,0) -> 0.043437599 | K107: =IFERROR(K115/$B$87,0) -> 0.051241036 | ... AC107: =IFERROR(AC115/$B$87,0) -> 0.07641383
A108: Ships in fleet (end of year) | D108: =MAX(0,D105+D106-D107) -> 1 | E108: =MAX(0,E105+E106-E107) -> 0.99722222 | F108: =MAX(0,F105+F106-F107) -> 0.99070363 | G108: =MAX(0,G105+G106-G107) -> 0.97981796 | H108: =MAX(0,H105+H106-H107) -> 0.95739097 | I108: =MAX(0,I105+I106-I107) -> 0.92177187 | J108: =MAX(0,J105+J106-J107) -> 0.87833427 | K108: =MAX(0,K105+K106-K107) -> 0.82709324 | ... AC108: =MAX(0,AC105+AC106-AC107) -> 0
A109: Cumulative ships ever in reusable service | D109: =D106 -> 0 | E109: =D109+E106 -> 0 | F109: =E109+F106 -> 0 | G109: =F109+G106 -> 0 | H109: =G109+H106 -> 0 | I109: =H109+I106 -> 0 | J109: =I109+J106 -> 0 | K109: =J109+K106 -> 0 | L109: =K109+L106 -> 0 | ... AC109: =AB109+AC106 -> 0
A111: SECTION S3 — CADENCE & ANNUAL LAUNCHES
A112: Turnaround time per booster (years/flight, Wright's Law on cum upmass) | D112: =$B$89 -> 1 | E112: =MAX($B$89*(1-$B$90)^IFERROR(LOG(MAX(1,D118)/($B$85*(1-D94)+$B$86*D94),2),0),1/$B$92) -> 1 | F112: =MAX($B$89*(1-$B$90)^IFERROR(LOG(MAX(1,E118)/($B$85*(1-E94)+$B$86*E94),2),0),1/$B$92) -> 0.85226345 | G112: =MAX($B$89*(1-$B$90)^IFERROR(LOG(MAX(1,F118)/($B$85*(1-F94)+$B$86*F94),2),0),1/$B$92) -> 0.76553197 | H112: =MAX($B$89*(1-$B$90)^IFERROR(LOG(MAX(1,G118)/($B$85*(1-G94)+$B$86*G94),2),0),1/$B$92) -> 0.70599454 | I112: =MAX($B$89*(1-$B$90)^IFERROR(LOG(MAX(1,H118)/($B$85*(1-H94)+$B$86*H94),2),0),1/$B$92) -> 0.65507938 | J112: =MAX($B$89*(1-$B$90)^IFERROR(LOG(MAX(1,I118)/($B$85*(1-I94)+$B$86*I94),2),0),1/$B$92) -> 0.61390748 | K112: =MAX($B$89*(1-$B$90)^IFERROR(LOG(MAX(1,J118)/($B$85*(1-J94)+$B$86*J94),2),0),1/$B$92) -> 0.58546826 | L112: =MAX($B$89*(1-$B$90)^IFERROR(LOG(MAX(1,K118)/($B$85*(1-K94)+$B$86*K94),2),0),1/$B$92) -> 0.56104468 | ... AC112: =MAX($B$89*(1-$B$90)^IFERROR(LOG(MAX(1,AB118)/($B$85*(1-AB94)+$B$86*AB94),2),0),1/$B$92) -> 0.41441015
A113: Cadence per booster (flights/year, derived, capped) | D113: =MIN(1/D112,$B$92) -> 1 | E113: =MIN(1/E112,$B$92) -> 1 | F113: =MIN(1/F112,$B$92) -> 1.1733461 | G113: =MIN(1/G112,$B$92) -> 1.3062812 | H113: =MIN(1/H112,$B$92) -> 1.4164415 | I113: =MIN(1/I112,$B$92) -> 1.5265325 | J113: =MIN(1/J112,$B$92) -> 1.6289099 | K113: =MIN(1/K112,$B$92) -> 1.7080345 | ... AC113: =MIN(1/AC112,$B$92) -> 2.4130683
A114: Total annual booster launches | D114: =((D100+D103)/2)*D113 -> 1 | E114: =((E100+E103)/2)*E113 -> 1 | F114: =((F100+F103)/2)*F113 -> 1.1733461 | G114: =((G100+G103)/2)*G113 -> 1.3062812 | H114: =((H100+H103)/2)*H113 -> 1.4164415 | I114: =((I100+I103)/2)*I113 -> 1.5265325 | J114: =((J100+J103)/2)*J113 -> 1.6289099 | K114: =((K100+K103)/2)*K113 -> 1.7080345 | ... AC114: =((AC100+AC103)/2)*AC113 -> 2.4130683
A115: of which: fully-reusable flights | D115: =D114*D94 -> 0 | E115: =E114*E94 -> 0.083333333 | F115: =F114*F94 -> 0.19555768 | G115: =G114*G94 -> 0.32657029 | H115: =H114*H94 -> 0.67280974 | I115: =I114*I94 -> 1.0685728 | J115: =J114*J94 -> 1.303128 | K115: =K114*K94 -> 1.5372311 | ... AC115: =AC114*AC94 -> 2.2924149
A116: of which: booster-only flights | D116: =D114*(1-D94) -> 1 | E116: =E114*(1-E94) -> 0.91666667 | F116: =F114*(1-F94) -> 0.97778842 | G116: =G114*(1-G94) -> 0.97971087 | H116: =H114*(1-H94) -> 0.74363181 | I116: =I114*(1-I94) -> 0.45795976 | J116: =J114*(1-J94) -> 0.32578199 | K116: =K114*(1-K94) -> 0.17080345 | ... AC116: =AC114*(1-AC94) -> 0.12065342
A117: Annual upmass (kg, all-fleet) | D117: =D114*($B$85*(1-D94)+$B$86*D94) -> 150000 | E117: =E114*($B$85*(1-E94)+$B$86*E94) -> 145833.33 | F117: =F114*($B$85*(1-F94)+$B$86*F94) -> 166224.03 | G117: =G114*($B$85*(1-G94)+$B$86*G94) -> 179613.66 | H117: =H114*($B$85*(1-H94)+$B$86*H94) -> 178825.75 | I117: =I114*($B$85*(1-I94)+$B$86*I94) -> 175551.24 | J117: =J114*($B$85*(1-J94)+$B$86*J94) -> 179180.09 | K117: =K114*($B$85*(1-K94)+$B$86*K94) -> 179343.62 | ... AC117: =AC114*($B$85*(1-AC94)+$B$86*AC94) -> 247339.5
A118: Cumulative upmass (kg, all-fleet) | D118: =D117 -> 150000 | E118: =D118+E117 -> 295833.33 | F118: =E118+F117 -> 462057.37 | G118: =F118+G117 -> 641671.03 | H118: =G118+H117 -> 820496.77 | I118: =H118+I117 -> 996048.01 | J118: =I118+J117 -> 1175228.1 | K118: =J118+K117 -> 1354571.7 | L118: =K118+L117 -> 1540237.3 | ... AC118: =AB118+AC117 -> 5299559.6
A120: SECTION S4 — PER-LAUNCH COST BUILD
A121: Super Heavy mfg cost this year ($mm, Wright's Law) | D121: =$B$80 -> 35.1 | E121: =$B$80*(1-$B$88)^IFERROR(LOG(MAX(1,E104)/MAX(1,D104),2)+LOG(MAX(1,D104),2),0) -> 35.1 | F121: =$B$80*(1-$B$88)^IFERROR(LOG(MAX(1,F104)/MAX(1,E104),2)+LOG(MAX(1,E104),2),0) -> 35.1 | G121: =$B$80*(1-$B$88)^IFERROR(LOG(MAX(1,G104)/MAX(1,F104),2)+LOG(MAX(1,F104),2),0) -> 35.1 | H121: =$B$80*(1-$B$88)^IFERROR(LOG(MAX(1,H104)/MAX(1,G104),2)+LOG(MAX(1,G104),2),0) -> 35.1 | I121: =$B$80*(1-$B$88)^IFERROR(LOG(MAX(1,I104)/MAX(1,H104),2)+LOG(MAX(1,H104),2),0) -> 35.1 | J121: =$B$80*(1-$B$88)^IFERROR(LOG(MAX(1,J104)/MAX(1,I104),2)+LOG(MAX(1,I104),2),0) -> 35.1 | K121: =$B$80*(1-$B$88)^IFERROR(LOG(MAX(1,K104)/MAX(1,J104),2)+LOG(MAX(1,J104),2),0) -> 35.1 | L121: =$B$80*(1-$B$88)^IFERROR(LOG(MAX(1,L104)/MAX(1,K104),2)+LOG(MAX(1,K104),2),0) -> 35.1 | ... AC121: =$B$80*(1-$B$88)^IFERROR(LOG(MAX(1,AC104)/MAX(1,AB104),2)+LOG(MAX(1,AB104),2),0) -> 35.1
A122: Starship 2nd-stage mfg cost this year ($mm, Wright's Law) | D122: =$B$81 -> 23.4 | E122: =$B$81*(1-$B$88)^IFERROR(LOG(MAX(1,E109)/MAX(1,D109+0.0001),2)+LOG(MAX(1,D109+0.0001),2),0) -> 23.4 | F122: =$B$81*(1-$B$88)^IFERROR(LOG(MAX(1,F109)/MAX(1,E109+0.0001),2)+LOG(MAX(1,E109+0.0001),2),0) -> 23.4 | G122: =$B$81*(1-$B$88)^IFERROR(LOG(MAX(1,G109)/MAX(1,F109+0.0001),2)+LOG(MAX(1,F109+0.0001),2),0) -> 23.4 | H122: =$B$81*(1-$B$88)^IFERROR(LOG(MAX(1,H109)/MAX(1,G109+0.0001),2)+LOG(MAX(1,G109+0.0001),2),0) -> 23.4 | I122: =$B$81*(1-$B$88)^IFERROR(LOG(MAX(1,I109)/MAX(1,H109+0.0001),2)+LOG(MAX(1,H109+0.0001),2),0) -> 23.4 | J122: =$B$81*(1-$B$88)^IFERROR(LOG(MAX(1,J109)/MAX(1,I109+0.0001),2)+LOG(MAX(1,I109+0.0001),2),0) -> 23.4 | K122: =$B$81*(1-$B$88)^IFERROR(LOG(MAX(1,K109)/MAX(1,J109+0.0001),2)+LOG(MAX(1,J109+0.0001),2),0) -> 23.4 | L122: =$B$81*(1-$B$88)^IFERROR(LOG(MAX(1,L109)/MAX(1,K109+0.0001),2)+LOG(MAX(1,K109+0.0001),2),0) -> 23.4 | ... AC122: =$B$81*(1-$B$88)^IFERROR(LOG(MAX(1,AC109)/MAX(1,AB109+0.0001),2)+LOG(MAX(1,AB109+0.0001),2),0) -> 23.4
A123: Cumulative booster flights (all-fleet) | D123: =D114 -> 1 | E123: =D123+E114 -> 2 | F123: =E123+F114 -> 3.1733461 | G123: =F123+G114 -> 4.4796273 | H123: =G123+H114 -> 5.8960688 | I123: =H123+I114 -> 7.4226014 | J123: =I123+J114 -> 9.0515113 | K123: =J123+K114 -> 10.759546 | L123: =K123+L114 -> 12.541935 | ... AC123: =AB123+AC114 -> 49.203306
A124: Cum flights per booster (avg) | D124: =IFERROR(D123/D104,0) -> 1 | E124: =IFERROR(E123/E104,0) -> 2 | F124: =IFERROR(F123/F104,0) -> 3.1733461 | G124: =IFERROR(G123/G104,0) -> 4.4796273 | H124: =IFERROR(H123/H104,0) -> 5.8960688 | I124: =IFERROR(I123/I104,0) -> 7.4226014 | J124: =IFERROR(J123/J104,0) -> 9.0515113 | K124: =IFERROR(K123/K104,0) -> 10.759546 | ... AC124: =IFERROR(AC123/AC104,0) -> 49.203306
A125: Cumulative fully-reusable flights | D125: =D115 -> 0 | E125: =D125+E115 -> 0.083333333 | F125: =E125+F115 -> 0.27889102 | G125: =F125+G115 -> 0.60546131 | H125: =G125+H115 -> 1.278271 | I125: =H125+I115 -> 2.3468438 | J125: =I125+J115 -> 3.6499718 | K125: =J125+K115 -> 5.1872029 | L125: =K125+L115 -> 6.8210597 | ... AC125: =AB125+AC115 -> 41.618726
A126: Cum flights per reusable ship (avg) | D126: =IFERROR(D125/D109,0) -> 0 | E126: =IFERROR(E125/E109,0) -> 0 | F126: =IFERROR(F125/F109,0) -> 0 | G126: =IFERROR(G125/G109,0) -> 0 | H126: =IFERROR(H125/H109,0) -> 0 | I126: =IFERROR(I125/I109,0) -> 0 | J126: =IFERROR(J125/J109,0) -> 0 | K126: =IFERROR(K125/K109,0) -> 0 | ... AC126: =IFERROR(AC125/AC109,0) -> 0
A128: ▸ Booster-only mode
A129: Variable cost per flight ($mm) | D129: =$B$82+D122+$B$83*D121 -> 23.4 | E129: =$B$82+E122+$B$83*E121 -> 23.4 | F129: =$B$82+F122+$B$83*F121 -> 23.4 | G129: =$B$82+G122+$B$83*G121 -> 23.4 | H129: =$B$82+H122+$B$83*H121 -> 23.4 | I129: =$B$82+I122+$B$83*I121 -> 23.4 | J129: =$B$82+J122+$B$83*J121 -> 23.4 | K129: =$B$82+K122+$B$83*K121 -> 23.4 | ... AC129: =$B$82+AC122+$B$83*AC121 -> 23.4
A130: Amortized SH mfg cost per flight ($mm) | D130: =IFERROR(D121/D124,0) -> 35.1 | E130: =IFERROR(E121/E124,0) -> 17.55 | F130: =IFERROR(F121/F124,0) -> 11.06088 | G130: =IFERROR(G121/G124,0) -> 7.8354733 | H130: =IFERROR(H121/H124,0) -> 5.9531191 | I130: =IFERROR(I121/I124,0) -> 4.7288004 | J130: =IFERROR(J121/J124,0) -> 3.8778055 | K130: =IFERROR(K121/K124,0) -> 3.2622195 | ... AC130: =IFERROR(AC121/AC124,0) -> 0.7133667
...

Sheet Starlink Capacity
A1: STARLINK CAPACITY
A2: Aggregates Starlink constellation capacity (BB + DTC). Allocates bandwidth to ODC (and AI Stack when active) as internal claims on both pools. Remainder = available for external Starlink revenue (BB and DTC separately). At-cost proportional cost allocation per pool.
A4: Year | D4: 2025 | E4: 2026 | F4: 2027 | G4: 2028 | H4: 2029 | I4: 2030 | J4: 2031 | K4: 2032 | L4: 2033 | M4: 2034 | N4: 2035 | O4: 2036 | P4: 2037 | Q4: 2038 | R4: 2039 | S4: 2040 | T4: 2041 | U4: 2042 | V4: 2043 | W4: 2044 | X4: 2045 | Y4: 2046 | Z4: 2047 | AA4: 2048 | AB4: 2049 | AC4: 2050
A5: Year offset | D5: 0 | E5: 1 | F5: 2 | G5: 3 | H5: 4 | I5: 5 | J5: 6 | K5: 7 | L5: 8 | M5: 9 | N5: 10 | O5: 11 | P5: 12 | Q5: 13 | R5: 14 | S5: 15 | T5: 16 | U5: 17 | V5: 18 | W5: 19 | X5: 20 | Y5: 21 | Z5: 22 | AA5: 23 | AB5: 24 | AC5: 25
A7: SECTION A — CONSTELLATION SUMMARY (from Starlink tab)
A8: Total Active BB Satellites | D8: =INDEX(Starlink!D:D, MATCH("Total Active BB Satellites", Starlink!$A:$A, 0)) -> 4196.8 | E8: =INDEX(Starlink!E:E, MATCH("Total Active BB Satellites", Starlink!$A:$A, 0)) -> 3201.0593 | F8: =INDEX(Starlink!F:F, MATCH("Total Active BB Satellites", Starlink!$A:$A, 0)) -> 2202.7341 | G8: =INDEX(Starlink!G:G, MATCH("Total Active BB Satellites", Starlink!$A:$A, 0)) -> 1200.7861 | H8: =INDEX(Starlink!H:H, MATCH("Total Active BB Satellites", Starlink!$A:$A, 0)) -> 192.84057 | I8: =INDEX(Starlink!I:I, MATCH("Total Active BB Satellites", Starlink!$A:$A, 0)) -> 223.78213 | J8: =INDEX(Starlink!J:J, MATCH("Total Active BB Satellites", Starlink!$A:$A, 0)) -> 200.45163 | K8: =INDEX(Starlink!K:K, MATCH("Total Active BB Satellites", Starlink!$A:$A, 0)) -> 177.12156 | L8: =INDEX(Starlink!L:L, MATCH("Total Active BB Satellites", Starlink!$A:$A, 0)) -> 157.70168 | M8: =INDEX(Starlink!M:M, MATCH("Total Active BB Satellites", Starlink!$A:$A, 0)) -> 146.86681 | N8: =INDEX(Starlink!N:N, MATCH("Total Active BB Satellites", Starlink!$A:$A, 0)) -> 149.033 | O8: =INDEX(Starlink!O:O, MATCH("Total Active BB Satellites", Starlink!$A:$A, 0)) -> 156.46247 | P8: =INDEX(Starlink!P:P, MATCH("Total Active BB Satellites", Starlink!$A:$A, 0)) -> 171.03659 | Q8: =INDEX(Starlink!Q:Q, MATCH("Total Active BB Satellites", Starlink!$A:$A, 0)) -> 190.51761 | R8: =INDEX(Starlink!R:R, MATCH("Total Active BB Satellites", Starlink!$A:$A, 0)) -> 212.74692 | S8: =INDEX(Starlink!S:S, MATCH("Total Active BB Satellites", Starlink!$A:$A, 0)) -> 237.85284 | T8: =INDEX(Starlink!T:T, MATCH("Total Active BB Satellites", Starlink!$A:$A, 0)) -> 230.62516 | U8: =INDEX(Starlink!U:U, MATCH("Total Active BB Satellites", Starlink!$A:$A, 0)) -> 257.67218 | V8: =INDEX(Starlink!V:V, MATCH("Total Active BB Satellites", Starlink!$A:$A, 0)) -> 284.67329 | W8: =INDEX(Starlink!W:W, MATCH("Total Active BB Satellites", Starlink!$A:$A, 0)) -> 311.1473 | X8: =INDEX(Starlink!X:X, MATCH("Total Active BB Satellites", Starlink!$A:$A, 0)) -> 334.82386 | Y8: =INDEX(Starlink!Y:Y, MATCH("Total Active BB Satellites", Starlink!$A:$A, 0)) -> 420.95411 | Z8: =INDEX(Starlink!Z:Z, MATCH("Total Active BB Satellites", Starlink!$A:$A, 0)) -> 510.38749 | AA8: =INDEX(Starlink!AA:AA, MATCH("Total Active BB Satellites", Starlink!$A:$A, 0)) -> 603.30773 | AB8: =INDEX(Starlink!AB:AB, MATCH("Total Active BB Satellites", Starlink!$A:$A, 0)) -> 693.7572 | AC8: =INDEX(Starlink!AC:AC, MATCH("Total Active BB Satellites", Starlink!$A:$A, 0)) -> 788.02895
A9: Total Active DTC Satellites | D9: =INDEX(Starlink!D:D, MATCH("Total Active DTC Satellites", Starlink!$A:$A, 0)) -> 520 | E9: =INDEX(Starlink!E:E, MATCH("Total Active DTC Satellites", Starlink!$A:$A, 0)) -> 399.43399 | F9: =INDEX(Starlink!F:F, MATCH("Total Active DTC Satellites", Starlink!$A:$A, 0)) -> 278.4119 | G9: =INDEX(Starlink!G:G, MATCH("Total Active DTC Satellites", Starlink!$A:$A, 0)) -> 156.75049 | H9: =INDEX(Starlink!H:H, MATCH("Total Active DTC Satellites", Starlink!$A:$A, 0)) -> 34.03069 | I9: =INDEX(Starlink!I:I, MATCH("Total Active DTC Satellites", Starlink!$A:$A, 0)) -> 39.490964 | J9: =INDEX(Starlink!J:J, MATCH("Total Active DTC Satellites", Starlink!$A:$A, 0)) -> 35.373817 | K9: =INDEX(Starlink!K:K, MATCH("Total Active DTC Satellites", Starlink!$A:$A, 0)) -> 31.256746 | L9: =INDEX(Starlink!L:L, MATCH("Total Active DTC Satellites", Starlink!$A:$A, 0)) -> 27.829708 | M9: =INDEX(Starlink!M:M, MATCH("Total Active DTC Satellites", Starlink!$A:$A, 0)) -> 25.917673 | N9: =INDEX(Starlink!N:N, MATCH("Total Active DTC Satellites", Starlink!$A:$A, 0)) -> 26.299942 | O9: =INDEX(Starlink!O:O, MATCH("Total Active DTC Satellites", Starlink!$A:$A, 0)) -> 27.611024 | P9: =INDEX(Starlink!P:P, MATCH("Total Active DTC Satellites", Starlink!$A:$A, 0)) -> 30.182928 | Q9: =INDEX(Starlink!Q:Q, MATCH("Total Active DTC Satellites", Starlink!$A:$A, 0)) -> 33.620755 | R9: =INDEX(Starlink!R:R, MATCH("Total Active DTC Satellites", Starlink!$A:$A, 0)) -> 37.543574 | S9: =INDEX(Starlink!S:S, MATCH("Total Active DTC Satellites", Starlink!$A:$A, 0)) -> 41.97403 | T9: =INDEX(Starlink!T:T, MATCH("Total Active DTC Satellites", Starlink!$A:$A, 0)) -> 65.676695 | U9: =INDEX(Starlink!U:U, MATCH("Total Active DTC Satellites", Starlink!$A:$A, 0)) -> 70.449699 | V9: =INDEX(Starlink!V:V, MATCH("Total Active DTC Satellites", Starlink!$A:$A, 0)) -> 75.2146 | W9: =INDEX(Starlink!W:W, MATCH("Total Active DTC Satellites", Starlink!$A:$A, 0)) -> 79.886484 | X9: =INDEX(Starlink!X:X, MATCH("Total Active DTC Satellites", Starlink!$A:$A, 0)) -> 84.0647 | Y9: =INDEX(Starlink!Y:Y, MATCH("Total Active DTC Satellites", Starlink!$A:$A, 0)) -> 99.264157 | Z9: =INDEX(Starlink!Z:Z, MATCH("Total Active DTC Satellites", Starlink!$A:$A, 0)) -> 115.04652 | AA9: =INDEX(Starlink!AA:AA, MATCH("Total Active DTC Satellites", Starlink!$A:$A, 0)) -> 131.44421 | AB9: =INDEX(Starlink!AB:AB, MATCH("Total Active DTC Satellites", Starlink!$A:$A, 0)) -> 147.40588 | AC9: =INDEX(Starlink!AC:AC, MATCH("Total Active DTC Satellites", Starlink!$A:$A, 0)) -> 164.04207
A10: Total Active Satellites (All) | D10: =D8+D9 -> 4716.8 | E10: =E8+E9 -> 3600.4933 | F10: =F8+F9 -> 2481.146 | G10: =G8+G9 -> 1357.5366 | H10: =H8+H9 -> 226.87126 | I10: =I8+I9 -> 263.27309 | J10: =J8+J9 -> 235.82545 | K10: =K8+K9 -> 208.37831 | ... AC10: =AC8+AC9 -> 952.07102
A12: Total Active BB Bandwidth (Gbps) | D12: =INDEX(Starlink!D:D, MATCH("Total Active BB Bandwidth (Gbps)", Starlink!$A:$A, 0)) -> 575504 | E12: =INDEX(Starlink!E:E, MATCH("Total Active BB Bandwidth (Gbps)", Starlink!$A:$A, 0)) -> 613339.36 | F12: =INDEX(Starlink!F:F, MATCH("Total Active BB Bandwidth (Gbps)", Starlink!$A:$A, 0)) -> 648495.11 | G12: =INDEX(Starlink!G:G, MATCH("Total Active BB Bandwidth (Gbps)", Starlink!$A:$A, 0)) -> 679883.88 | H12: =INDEX(Starlink!H:H, MATCH("Total Active BB Bandwidth (Gbps)", Starlink!$A:$A, 0)) -> 705020.58 | I12: =INDEX(Starlink!I:I, MATCH("Total Active BB Bandwidth (Gbps)", Starlink!$A:$A, 0)) -> 520497.37 | J12: =INDEX(Starlink!J:J, MATCH("Total Active BB Bandwidth (Gbps)", Starlink!$A:$A, 0)) -> 496187.52 | K12: =INDEX(Starlink!K:K, MATCH("Total Active BB Bandwidth (Gbps)", Starlink!$A:$A, 0)) -> 471861.32 | L12: =INDEX(Starlink!L:L, MATCH("Total Active BB Bandwidth (Gbps)", Starlink!$A:$A, 0)) -> 451607.73 | M12: =INDEX(Starlink!M:M, MATCH("Total Active BB Bandwidth (Gbps)", Starlink!$A:$A, 0)) -> 440317.87 | N12: =INDEX(Starlink!N:N, MATCH("Total Active BB Bandwidth (Gbps)", Starlink!$A:$A, 0)) -> 442614.34 | O12: =INDEX(Starlink!O:O, MATCH("Total Active BB Bandwidth (Gbps)", Starlink!$A:$A, 0)) -> 450418.43 | P12: =INDEX(Starlink!P:P, MATCH("Total Active BB Bandwidth (Gbps)", Starlink!$A:$A, 0)) -> 465701.14 | Q12: =INDEX(Starlink!Q:Q, MATCH("Total Active BB Bandwidth (Gbps)", Starlink!$A:$A, 0)) -> 486127.99 | R12: =INDEX(Starlink!R:R, MATCH("Total Active BB Bandwidth (Gbps)", Starlink!$A:$A, 0)) -> 509445.74 | S12: =INDEX(Starlink!S:S, MATCH("Total Active BB Bandwidth (Gbps)", Starlink!$A:$A, 0)) -> 535792.67 | T12: =INDEX(Starlink!T:T, MATCH("Total Active BB Bandwidth (Gbps)", Starlink!$A:$A, 0)) -> 745140.62 | U12: =INDEX(Starlink!U:U, MATCH("Total Active BB Bandwidth (Gbps)", Starlink!$A:$A, 0)) -> 773563.13 | V12: =INDEX(Starlink!V:V, MATCH("Total Active BB Bandwidth (Gbps)", Starlink!$A:$A, 0)) -> 801965.99 | W12: =INDEX(Starlink!W:W, MATCH("Total Active BB Bandwidth (Gbps)", Starlink!$A:$A, 0)) -> 829847 | X12: =INDEX(Starlink!X:X, MATCH("Total Active BB Bandwidth (Gbps)", Starlink!$A:$A, 0)) -> 854825.05 | Y12: =INDEX(Starlink!Y:Y, MATCH("Total Active BB Bandwidth (Gbps)", Starlink!$A:$A, 0)) -> 945282.73 | Z12: =INDEX(Starlink!Z:Z, MATCH("Total Active BB Bandwidth (Gbps)", Starlink!$A:$A, 0)) -> 1039257.8 | AA12: =INDEX(Starlink!AA:AA, MATCH("Total Active BB Bandwidth (Gbps)", Starlink!$A:$A, 0)) -> 1136948.7 | AB12: =INDEX(Starlink!AB:AB, MATCH("Total Active BB Bandwidth (Gbps)", Starlink!$A:$A, 0)) -> 1232094 | AC12: =INDEX(Starlink!AC:AC, MATCH("Total Active BB Bandwidth (Gbps)", Starlink!$A:$A, 0)) -> 1331312.5
A13: Total Active DTC Bandwidth (Gbps) | D13: =INDEX(Starlink!D:D, MATCH("Total Active DTC Bandwidth (Gbps)", Starlink!$A:$A, 0)) -> 1936 | E13: =INDEX(Starlink!E:E, MATCH("Total Active DTC Bandwidth (Gbps)", Starlink!$A:$A, 0)) -> 1961.9435 | F13: =INDEX(Starlink!F:F, MATCH("Total Active DTC Bandwidth (Gbps)", Starlink!$A:$A, 0)) -> 1986.6327 | G13: =INDEX(Starlink!G:G, MATCH("Total Active DTC Bandwidth (Gbps)", Starlink!$A:$A, 0)) -> 2009.5638 | H13: =INDEX(Starlink!H:H, MATCH("Total Active DTC Bandwidth (Gbps)", Starlink!$A:$A, 0)) -> 2029.5844 | I13: =INDEX(Starlink!I:I, MATCH("Total Active DTC Bandwidth (Gbps)", Starlink!$A:$A, 0)) -> 2044.6001 | J13: =INDEX(Starlink!J:J, MATCH("Total Active DTC Bandwidth (Gbps)", Starlink!$A:$A, 0)) -> 2033.278 | K13: =INDEX(Starlink!K:K, MATCH("Total Active DTC Bandwidth (Gbps)", Starlink!$A:$A, 0)) -> 2021.9561 | L13: =INDEX(Starlink!L:L, MATCH("Total Active DTC Bandwidth (Gbps)", Starlink!$A:$A, 0)) -> 2012.5317 | M13: =INDEX(Starlink!M:M, MATCH("Total Active DTC Bandwidth (Gbps)", Starlink!$A:$A, 0)) -> 2007.2736 | N13: =INDEX(Starlink!N:N, MATCH("Total Active DTC Bandwidth (Gbps)", Starlink!$A:$A, 0)) -> 2008.3248 | O13: =INDEX(Starlink!O:O, MATCH("Total Active DTC Bandwidth (Gbps)", Starlink!$A:$A, 0)) -> 2011.9303 | P13: =INDEX(Starlink!P:P, MATCH("Total Active DTC Bandwidth (Gbps)", Starlink!$A:$A, 0)) -> 2019.0031 | Q13: =INDEX(Starlink!Q:Q, MATCH("Total Active DTC Bandwidth (Gbps)", Starlink!$A:$A, 0)) -> 2028.4571 | R13: =INDEX(Starlink!R:R, MATCH("Total Active DTC Bandwidth (Gbps)", Starlink!$A:$A, 0)) -> 2039.2448 | S13: =INDEX(Starlink!S:S, MATCH("Total Active DTC Bandwidth (Gbps)", Starlink!$A:$A, 0)) -> 2051.4286 | T13: =INDEX(Starlink!T:T, MATCH("Total Active DTC Bandwidth (Gbps)", Starlink!$A:$A, 0)) -> 2116.6109 | U13: =INDEX(Starlink!U:U, MATCH("Total Active DTC Bandwidth (Gbps)", Starlink!$A:$A, 0)) -> 2129.7367 | V13: =INDEX(Starlink!V:V, MATCH("Total Active DTC Bandwidth (Gbps)", Starlink!$A:$A, 0)) -> 2142.8401 | W13: =INDEX(Starlink!W:W, MATCH("Total Active DTC Bandwidth (Gbps)", Starlink!$A:$A, 0)) -> 2155.6878 | X13: =INDEX(Starlink!X:X, MATCH("Total Active DTC Bandwidth (Gbps)", Starlink!$A:$A, 0)) -> 2167.1779 | Y13: =INDEX(Starlink!Y:Y, MATCH("Total Active DTC Bandwidth (Gbps)", Starlink!$A:$A, 0)) -> 2208.9764 | Z13: =INDEX(Starlink!Z:Z, MATCH("Total Active DTC Bandwidth (Gbps)", Starlink!$A:$A, 0)) -> 2252.3779 | AA13: =INDEX(Starlink!AA:AA, MATCH("Total Active DTC Bandwidth (Gbps)", Starlink!$A:$A, 0)) -> 2297.4716 | AB13: =INDEX(Starlink!AB:AB, MATCH("Total Active DTC Bandwidth (Gbps)", Starlink!$A:$A, 0)) -> 2341.3662 | AC13: =INDEX(Starlink!AC:AC, MATCH("Total Active DTC Bandwidth (Gbps)", Starlink!$A:$A, 0)) -> 2387.1157
A14: Starshield Reserved Bandwidth (Gbps) | D14: =INDEX(Starlink!D:D, MATCH("Starshield Reserved Bandwidth (Gbps)", Starlink!$A:$A, 0)) -> 14790.453 | E14: =INDEX(Starlink!E:E, MATCH("Starshield Reserved Bandwidth (Gbps)", Starlink!$A:$A, 0)) -> 5837.5885 | F14: =INDEX(Starlink!F:F, MATCH("Starshield Reserved Bandwidth (Gbps)", Starlink!$A:$A, 0)) -> 2311.6148 | G14: =INDEX(Starlink!G:G, MATCH("Starshield Reserved Bandwidth (Gbps)", Starlink!$A:$A, 0)) -> 934.53368 | H14: =INDEX(Starlink!H:H, MATCH("Starshield Reserved Bandwidth (Gbps)", Starlink!$A:$A, 0)) -> 70.502058 | I14: =INDEX(Starlink!I:I, MATCH("Starshield Reserved Bandwidth (Gbps)", Starlink!$A:$A, 0)) -> 52.049737 | J14: =INDEX(Starlink!J:J, MATCH("Starshield Reserved Bandwidth (Gbps)", Starlink!$A:$A, 0)) -> 49.618752 | K14: =INDEX(Starlink!K:K, MATCH("Starshield Reserved Bandwidth (Gbps)", Starlink!$A:$A, 0)) -> 47.186132 | L14: =INDEX(Starlink!L:L, MATCH("Starshield Reserved Bandwidth (Gbps)", Starlink!$A:$A, 0)) -> 45.160773 | M14: =INDEX(Starlink!M:M, MATCH("Starshield Reserved Bandwidth (Gbps)", Starlink!$A:$A, 0)) -> 44.031787 | N14: =INDEX(Starlink!N:N, MATCH("Starshield Reserved Bandwidth (Gbps)", Starlink!$A:$A, 0)) -> 44.261434 | O14: =INDEX(Starlink!O:O, MATCH("Starshield Reserved Bandwidth (Gbps)", Starlink!$A:$A, 0)) -> 45.041843 | P14: =INDEX(Starlink!P:P, MATCH("Starshield Reserved Bandwidth (Gbps)", Starlink!$A:$A, 0)) -> 46.570114 | Q14: =INDEX(Starlink!Q:Q, MATCH("Starshield Reserved Bandwidth (Gbps)", Starlink!$A:$A, 0)) -> 48.612799 | R14: =INDEX(Starlink!R:R, MATCH("Starshield Reserved Bandwidth (Gbps)", Starlink!$A:$A, 0)) -> 50.944574 | S14: =INDEX(Starlink!S:S, MATCH("Starshield Reserved Bandwidth (Gbps)", Starlink!$A:$A, 0)) -> 53.579267 | T14: =INDEX(Starlink!T:T, MATCH("Starshield Reserved Bandwidth (Gbps)", Starlink!$A:$A, 0)) -> 74.514062 | U14: =INDEX(Starlink!U:U, MATCH("Starshield Reserved Bandwidth (Gbps)", Starlink!$A:$A, 0)) -> 77.356313 | V14: =INDEX(Starlink!V:V, MATCH("Starshield Reserved Bandwidth (Gbps)", Starlink!$A:$A, 0)) -> 80.196599 | W14: =INDEX(Starlink!W:W, MATCH("Starshield Reserved Bandwidth (Gbps)", Starlink!$A:$A, 0)) -> 82.9847 | X14: =INDEX(Starlink!X:X, MATCH("Starshield Reserved Bandwidth (Gbps)", Starlink!$A:$A, 0)) -> 85.482505 | Y14: =INDEX(Starlink!Y:Y, MATCH("Starshield Reserved Bandwidth (Gbps)", Starlink!$A:$A, 0)) -> 94.528273 | Z14: =INDEX(Starlink!Z:Z, MATCH("Starshield Reserved Bandwidth (Gbps)", Starlink!$A:$A, 0)) -> 103.92578 | AA14: =INDEX(Starlink!AA:AA, MATCH("Starshield Reserved Bandwidth (Gbps)", Starlink!$A:$A, 0)) -> 113.69487 | AB14: =INDEX(Starlink!AB:AB, MATCH("Starshield Reserved Bandwidth (Gbps)", Starlink!$A:$A, 0)) -> 123.2094 | AC14: =INDEX(Starlink!AC:AC, MATCH("Starshield Reserved Bandwidth (Gbps)", Starlink!$A:$A, 0)) -> 133.13125
A15: Commercial BB Bandwidth (pre-internal-claim) (Gbps) | D15: =INDEX(Starlink!D:D, MATCH("Commercial BB Bandwidth (Gbps)", Starlink!$A:$A, 0)) -> 560713.55 | E15: =INDEX(Starlink!E:E, MATCH("Commercial BB Bandwidth (Gbps)", Starlink!$A:$A, 0)) -> 607501.78 | F15: =INDEX(Starlink!F:F, MATCH("Commercial BB Bandwidth (Gbps)", Starlink!$A:$A, 0)) -> 646183.5 | G15: =INDEX(Starlink!G:G, MATCH("Commercial BB Bandwidth (Gbps)", Starlink!$A:$A, 0)) -> 678949.35 | H15: =INDEX(Starlink!H:H, MATCH("Commercial BB Bandwidth (Gbps)", Starlink!$A:$A, 0)) -> 704950.07 | I15: =INDEX(Starlink!I:I, MATCH("Commercial BB Bandwidth (Gbps)", Starlink!$A:$A, 0)) -> 520445.32 | J15: =INDEX(Starlink!J:J, MATCH("Commercial BB Bandwidth (Gbps)", Starlink!$A:$A, 0)) -> 496137.9 | K15: =INDEX(Starlink!K:K, MATCH("Commercial BB Bandwidth (Gbps)", Starlink!$A:$A, 0)) -> 471814.13 | L15: =INDEX(Starlink!L:L, MATCH("Commercial BB Bandwidth (Gbps)", Starlink!$A:$A, 0)) -> 451562.57 | M15: =INDEX(Starlink!M:M, MATCH("Commercial BB Bandwidth (Gbps)", Starlink!$A:$A, 0)) -> 440273.83 | N15: =INDEX(Starlink!N:N, MATCH("Commercial BB Bandwidth (Gbps)", Starlink!$A:$A, 0)) -> 442570.08 | O15: =INDEX(Starlink!O:O, MATCH("Commercial BB Bandwidth (Gbps)", Starlink!$A:$A, 0)) -> 450373.39 | P15: =INDEX(Starlink!P:P, MATCH("Commercial BB Bandwidth (Gbps)", Starlink!$A:$A, 0)) -> 465654.57 | Q15: =INDEX(Starlink!Q:Q, MATCH("Commercial BB Bandwidth (Gbps)", Starlink!$A:$A, 0)) -> 486079.38 | R15: =INDEX(Starlink!R:R, MATCH("Commercial BB Bandwidth (Gbps)", Starlink!$A:$A, 0)) -> 509394.79 | S15: =INDEX(Starlink!S:S, MATCH("Commercial BB Bandwidth (Gbps)", Starlink!$A:$A, 0)) -> 535739.09 | T15: =INDEX(Starlink!T:T, MATCH("Commercial BB Bandwidth (Gbps)", Starlink!$A:$A, 0)) -> 745066.11 | U15: =INDEX(Starlink!U:U, MATCH("Commercial BB Bandwidth (Gbps)", Starlink!$A:$A, 0)) -> 773485.78 | V15: =INDEX(Starlink!V:V, MATCH("Commercial BB Bandwidth (Gbps)", Starlink!$A:$A, 0)) -> 801885.79 | W15: =INDEX(Starlink!W:W, MATCH("Commercial BB Bandwidth (Gbps)", Starlink!$A:$A, 0)) -> 829764.01 | X15: =INDEX(Starlink!X:X, MATCH("Commercial BB Bandwidth (Gbps)", Starlink!$A:$A, 0)) -> 854739.57 | Y15: =INDEX(Starlink!Y:Y, MATCH("Commercial BB Bandwidth (Gbps)", Starlink!$A:$A, 0)) -> 945188.2 | Z15: =INDEX(Starlink!Z:Z, MATCH("Commercial BB Bandwidth (Gbps)", Starlink!$A:$A, 0)) -> 1039153.9 | AA15: =INDEX(Starlink!AA:AA, MATCH("Commercial BB Bandwidth (Gbps)", Starlink!$A:$A, 0)) -> 1136835 | AB15: =INDEX(Starlink!AB:AB, MATCH("Commercial BB Bandwidth (Gbps)", Starlink!$A:$A, 0)) -> 1231970.8 | AC15: =INDEX(Starlink!AC:AC, MATCH("Commercial BB Bandwidth (Gbps)", Starlink!$A:$A, 0)) -> 1331179.4
A16: Total Active Gbps (BB + DTC, memo) | D16: =D12+D13 -> 577440 | E16: =E12+E13 -> 615301.31 | F16: =F12+F13 -> 650481.74 | G16: =G12+G13 -> 681893.45 | H16: =H12+H13 -> 707050.16 | I16: =I12+I13 -> 522541.97 | J16: =J12+J13 -> 498220.8 | K16: =K12+K13 -> 473883.28 | ... AC16: =AC12+AC13 -> 1333699.6
A18: SECTION B — INTERNAL BANDWIDTH CLAIMS
A19: ODC Fleet GW (nameplate, from ODC tab) | D19: =INDEX(ODC!D:D, MATCH("Fleet GW (compute power)", ODC!$A:$A, 0)) -> 0 | E19: =INDEX(ODC!E:E, MATCH("Fleet GW (compute power)", ODC!$A:$A, 0)) -> 0 | F19: =INDEX(ODC!F:F, MATCH("Fleet GW (compute power)", ODC!$A:$A, 0)) -> 0 | G19: =INDEX(ODC!G:G, MATCH("Fleet GW (compute power)", ODC!$A:$A, 0)) -> 0 | H19: =INDEX(ODC!H:H, MATCH("Fleet GW (compute power)", ODC!$A:$A, 0)) -> 0 | I19: =INDEX(ODC!I:I, MATCH("Fleet GW (compute power)", ODC!$A:$A, 0)) -> 0 | J19: =INDEX(ODC!J:J, MATCH("Fleet GW (compute power)", ODC!$A:$A, 0)) -> 0 | K19: =INDEX(ODC!K:K, MATCH("Fleet GW (compute power)", ODC!$A:$A, 0)) -> 0 | L19: =INDEX(ODC!L:L, MATCH("Fleet GW (compute power)", ODC!$A:$A, 0)) -> 0 | M19: =INDEX(ODC!M:M, MATCH("Fleet GW (compute power)", ODC!$A:$A, 0)) -> 0 | N19: =INDEX(ODC!N:N, MATCH("Fleet GW (compute power)", ODC!$A:$A, 0)) -> 0 | O19: =INDEX(ODC!O:O, MATCH("Fleet GW (compute power)", ODC!$A:$A, 0)) -> 0 | P19: =INDEX(ODC!P:P, MATCH("Fleet GW (compute power)", ODC!$A:$A, 0)) -> 0 | Q19: =INDEX(ODC!Q:Q, MATCH("Fleet GW (compute power)", ODC!$A:$A, 0)) -> 0 | R19: =INDEX(ODC!R:R, MATCH("Fleet GW (compute power)", ODC!$A:$A, 0)) -> 0 | S19: =INDEX(ODC!S:S, MATCH("Fleet GW (compute power)", ODC!$A:$A, 0)) -> 0 | T19: =INDEX(ODC!T:T, MATCH("Fleet GW (compute power)", ODC!$A:$A, 0)) -> 0 | U19: =INDEX(ODC!U:U, MATCH("Fleet GW (compute power)", ODC!$A:$A, 0)) -> 0 | V19: =INDEX(ODC!V:V, MATCH("Fleet GW (compute power)", ODC!$A:$A, 0)) -> 0 | W19: =INDEX(ODC!W:W, MATCH("Fleet GW (compute power)", ODC!$A:$A, 0)) -> 0 | X19: =INDEX(ODC!X:X, MATCH("Fleet GW (compute power)", ODC!$A:$A, 0)) -> 0 | Y19: =INDEX(ODC!Y:Y, MATCH("Fleet GW (compute power)", ODC!$A:$A, 0)) -> 0 | Z19: =INDEX(ODC!Z:Z, MATCH("Fleet GW (compute power)", ODC!$A:$A, 0)) -> 0 | AA19: =INDEX(ODC!AA:AA, MATCH("Fleet GW (compute power)", ODC!$A:$A, 0)) -> 0 | AB19: =INDEX(ODC!AB:AB, MATCH("Fleet GW (compute power)", ODC!$A:$A, 0)) -> 0 | AC19: =INDEX(ODC!AC:AC, MATCH("Fleet GW (compute power)", ODC!$A:$A, 0)) -> 0
A20: ODC Utilization % | D20: =INDEX(ODC!D:D, MATCH("Utilization %", ODC!$A:$A, 0)) -> 0.4 | E20: =INDEX(ODC!E:E, MATCH("Utilization %", ODC!$A:$A, 0)) -> 0.4 | F20: =INDEX(ODC!F:F, MATCH("Utilization %", ODC!$A:$A, 0)) -> 0.55 | G20: =INDEX(ODC!G:G, MATCH("Utilization %", ODC!$A:$A, 0)) -> 0.7 | H20: =INDEX(ODC!H:H, MATCH("Utilization %", ODC!$A:$A, 0)) -> 0.85 | I20: =INDEX(ODC!I:I, MATCH("Utilization %", ODC!$A:$A, 0)) -> 0.85 | J20: =INDEX(ODC!J:J, MATCH("Utilization %", ODC!$A:$A, 0)) -> 0.85 | K20: =INDEX(ODC!K:K, MATCH("Utilization %", ODC!$A:$A, 0)) -> 0.85 | L20: =INDEX(ODC!L:L, MATCH("Utilization %", ODC!$A:$A, 0)) -> 0.85 | M20: =INDEX(ODC!M:M, MATCH("Utilization %", ODC!$A:$A, 0)) -> 0.85 | N20: =INDEX(ODC!N:N, MATCH("Utilization %", ODC!$A:$A, 0)) -> 0.85 | O20: =INDEX(ODC!O:O, MATCH("Utilization %", ODC!$A:$A, 0)) -> 0.85 | P20: =INDEX(ODC!P:P, MATCH("Utilization %", ODC!$A:$A, 0)) -> 0.85 | Q20: =INDEX(ODC!Q:Q, MATCH("Utilization %", ODC!$A:$A, 0)) -> 0.85 | R20: =INDEX(ODC!R:R, MATCH("Utilization %", ODC!$A:$A, 0)) -> 0.85 | S20: =INDEX(ODC!S:S, MATCH("Utilization %", ODC!$A:$A, 0)) -> 0.85 | T20: =INDEX(ODC!T:T, MATCH("Utilization %", ODC!$A:$A, 0)) -> 0.85 | U20: =INDEX(ODC!U:U, MATCH("Utilization %", ODC!$A:$A, 0)) -> 0.85 | V20: =INDEX(ODC!V:V, MATCH("Utilization %", ODC!$A:$A, 0)) -> 0.85 | W20: =INDEX(ODC!W:W, MATCH("Utilization %", ODC!$A:$A, 0)) -> 0.85 | X20: =INDEX(ODC!X:X, MATCH("Utilization %", ODC!$A:$A, 0)) -> 0.85 | Y20: =INDEX(ODC!Y:Y, MATCH("Utilization %", ODC!$A:$A, 0)) -> 0.85 | Z20: =INDEX(ODC!Z:Z, MATCH("Utilization %", ODC!$A:$A, 0)) -> 0.85 | AA20: =INDEX(ODC!AA:AA, MATCH("Utilization %", ODC!$A:$A, 0)) -> 0.85 | AB20: =INDEX(ODC!AB:AB, MATCH("Utilization %", ODC!$A:$A, 0)) -> 0.85 | AC20: =INDEX(ODC!AC:AC, MATCH("Utilization %", ODC!$A:$A, 0)) -> 0.85
A21: ODC compute energy delivered (GWh/yr) = D19 × 8760 × D20 | D21: =D19*8760*D20 -> 0 | E21: =E19*8760*E20 -> 0 | F21: =F19*8760*F20 -> 0 | G21: =G19*8760*G20 -> 0 | H21: =H19*8760*H20 -> 0 | I21: =I19*8760*I20 -> 0 | J21: =J19*8760*J20 -> 0 | K21: =K19*8760*K20 -> 0 | ... AC21: =AC19*8760*AC20 -> 0
A22: Conversion factor (Gbps per GWh/yr) — PLACEHOLDER, pending research | D22: =Assumptions!$B$458 -> 0.05 | E22: =Assumptions!$B$458 -> 0.05 | F22: =Assumptions!$B$458 -> 0.05 | G22: =Assumptions!$B$458 -> 0.05 | H22: =Assumptions!$B$458 -> 0.05 | I22: =Assumptions!$B$458 -> 0.05 | J22: =Assumptions!$B$458 -> 0.05 | K22: =Assumptions!$B$458 -> 0.05 | ... AC22: =Assumptions!$B$458 -> 0.05
A23: ODC total bandwidth claim (Gbps) — derived = D21 × D22 | D23: =D21*D22 -> 0 | E23: =E21*E22 -> 0 | F23: =F21*F22 -> 0 | G23: =G21*G22 -> 0 | H23: =H21*H22 -> 0 | I23: =I21*I22 -> 0 | J23: =J21*J22 -> 0 | K23: =K21*K22 -> 0 | ... AC23: =AC21*AC22 -> 0
A24: BB-share of ODC bandwidth (%) — PLACEHOLDER, pending research | D24: =Assumptions!$B$459 -> 0.5 | E24: =Assumptions!$B$459 -> 0.5 | F24: =Assumptions!$B$459 -> 0.5 | G24: =Assumptions!$B$459 -> 0.5 | H24: =Assumptions!$B$459 -> 0.5 | I24: =Assumptions!$B$459 -> 0.5 | J24: =Assumptions!$B$459 -> 0.5 | K24: =Assumptions!$B$459 -> 0.5 | ... AC24: =Assumptions!$B$459 -> 0.5
A25: ODC BB bandwidth claim (Gbps) = D23 × D24 | D25: =D23*D24 -> 0 | E25: =E23*E24 -> 0 | F25: =F23*F24 -> 0 | G25: =G23*G24 -> 0 | H25: =H23*H24 -> 0 | I25: =I23*I24 -> 0 | J25: =J23*J24 -> 0 | K25: =K23*K24 -> 0 | ... AC25: =AC23*AC24 -> 0
A26: ODC DTC bandwidth claim (Gbps) = D23 × (1 − D24) | D26: =D23*(1-D24) -> 0 | E26: =E23*(1-E24) -> 0 | F26: =F23*(1-F24) -> 0 | G26: =G23*(1-G24) -> 0 | H26: =H23*(1-H24) -> 0 | I26: =I23*(1-I24) -> 0 | J26: =J23*(1-J24) -> 0 | K26: =K23*(1-K24) -> 0 | ... AC26: =AC23*(1-AC24) -> 0
A27: AI Stack BW BB claim (Gbps) — scaffold, locked at zero | D27: 0 | E27: 0 | F27: 0 | G27: 0 | H27: 0 | I27: 0 | J27: 0 | K27: 0 | L27: 0 | M27: 0 | N27: 0 | O27: 0 | P27: 0 | Q27: 0 | R27: 0 | S27: 0 | T27: 0 | U27: 0 | V27: 0 | W27: 0 | X27: 0 | Y27: 0 | Z27: 0 | AA27: 0 | AB27: 0 | AC27: 0
A28: AI Stack BW DTC claim (Gbps) — scaffold, locked at zero | D28: 0 | E28: 0 | F28: 0 | G28: 0 | H28: 0 | I28: 0 | J28: 0 | K28: 0 | L28: 0 | M28: 0 | N28: 0 | O28: 0 | P28: 0 | Q28: 0 | R28: 0 | S28: 0 | T28: 0 | U28: 0 | V28: 0 | W28: 0 | X28: 0 | Y28: 0 | Z28: 0 | AA28: 0 | AB28: 0 | AC28: 0
A29: Total internal BB bandwidth claim (Gbps) | D29: =D25+D27 -> 0 | E29: =E25+E27 -> 0 | F29: =F25+F27 -> 0 | G29: =G25+G27 -> 0 | H29: =H25+H27 -> 0 | I29: =I25+I27 -> 0 | J29: =J25+J27 -> 0 | K29: =K25+K27 -> 0 | ... AC29: =AC25+AC27 -> 0
A30: Total internal DTC bandwidth claim (Gbps) | D30: =D26+D28 -> 0 | E30: =E26+E28 -> 0 | F30: =F26+F28 -> 0 | G30: =G26+G28 -> 0 | H30: =H26+H28 -> 0 | I30: =I26+I28 -> 0 | J30: =J26+J28 -> 0 | K30: =K26+K28 -> 0 | ... AC30: =AC26+AC28 -> 0
A31: Memo: ODC BB claim as % of Total Active BB Gbps | D31: =IFERROR(D29/D12, 0) -> 0 | E31: =IFERROR(E29/E12, 0) -> 0 | F31: =IFERROR(F29/F12, 0) -> 0 | G31: =IFERROR(G29/G12, 0) -> 0 | H31: =IFERROR(H29/H12, 0) -> 0 | I31: =IFERROR(I29/I12, 0) -> 0 | J31: =IFERROR(J29/J12, 0) -> 0 | K31: =IFERROR(K29/K12, 0) -> 0 | ... AC31: =IFERROR(AC29/AC12, 0) -> 0
A32: Memo: ODC DTC claim as % of Total Active DTC Gbps | D32: =IFERROR(D30/D13, 0) -> 0 | E32: =IFERROR(E30/E13, 0) -> 0 | F32: =IFERROR(F30/F13, 0) -> 0 | G32: =IFERROR(G30/G13, 0) -> 0 | H32: =IFERROR(H30/H13, 0) -> 0 | I32: =IFERROR(I30/I13, 0) -> 0 | J32: =IFERROR(J30/J13, 0) -> 0 | K32: =IFERROR(K30/K13, 0) -> 0 | ... AC32: =IFERROR(AC30/AC13, 0) -> 0
A35: SECTION C — AVAILABLE BANDWIDTH (EXTERNAL REVENUE BASE)
A36: Available Commercial BB Gbps (post-internal-claim) ← EXTERNAL REF: Starlink!D109 BB Revenue | D36: =MAX(0, D15-D29) -> 560713.55 | E36: =MAX(0, E15-E29) -> 607501.78 | F36: =MAX(0, F15-F29) -> 646183.5 | G36: =MAX(0, G15-G29) -> 678949.35 | H36: =MAX(0, H15-H29) -> 704950.07 | I36: =MAX(0, I15-I29) -> 520445.32 | J36: =MAX(0, J15-J29) -> 496137.9 | K36: =MAX(0, K15-K29) -> 471814.13 | ... AC36: =MAX(0, AC15-AC29) -> 1331179.4
A37: Available DTC Gbps (post-internal-claim) ← EXTERNAL REF: Starlink!D110 DTC Demand input | D37: =MAX(0, D13-D30) -> 1936 | E37: =MAX(0, E13-E30) -> 1961.9435 | F37: =MAX(0, F13-F30) -> 1986.6327 | G37: =MAX(0, G13-G30) -> 2009.5638 | H37: =MAX(0, H13-H30) -> 2029.5844 | I37: =MAX(0, I13-I30) -> 2044.6001 | J37: =MAX(0, J13-J30) -> 2033.278 | K37: =MAX(0, K13-K30) -> 2021.9561 | ... AC37: =MAX(0, AC13-AC30) -> 2387.1157
A38: Memo: % of Commercial BB consumed internally | D38: =IFERROR(D29/D15, 0) -> 0 | E38: =IFERROR(E29/E15, 0) -> 0 | F38: =IFERROR(F29/F15, 0) -> 0 | G38: =IFERROR(G29/G15, 0) -> 0 | H38: =IFERROR(H29/H15, 0) -> 0 | I38: =IFERROR(I29/I15, 0) -> 0 | J38: =IFERROR(J29/J15, 0) -> 0 | K38: =IFERROR(K29/K15, 0) -> 0 | ... AC38: =IFERROR(AC29/AC15, 0) -> 0
A39: Memo: % of DTC consumed internally | D39: =IFERROR(D30/D13, 0) -> 0 | E39: =IFERROR(E30/E13, 0) -> 0 | F39: =IFERROR(F30/F13, 0) -> 0 | G39: =IFERROR(G30/G13, 0) -> 0 | H39: =IFERROR(H30/H13, 0) -> 0 | I39: =IFERROR(I30/I13, 0) -> 0 | J39: =IFERROR(J30/J13, 0) -> 0 | K39: =IFERROR(K30/K13, 0) -> 0 | ... AC39: =IFERROR(AC30/AC13, 0) -> 0
A42: SECTION D — INTERNAL TRANSFER PRICING (AT-COST, PROPORTIONAL, PER POOL)
A43: Memo: BB share of Total Active Gbps = D12/D16 | D43: =IFERROR(D12/D16, 0) -> 0.99664727 | E43: =IFERROR(E12/E16, 0) -> 0.99681141 | F43: =IFERROR(F12/F16, 0) -> 0.99694591 | G43: =IFERROR(G12/G16, 0) -> 0.99705297 | H43: =IFERROR(H12/H16, 0) -> 0.9971295 | I43: =IFERROR(I12/I16, 0) -> 0.9960872 | J43: =IFERROR(J12/J16, 0) -> 0.99591892 | K43: =IFERROR(K12/K16, 0) -> 0.99573322 | ... AC43: =IFERROR(AC12/AC16, 0) -> 0.99821015
A44: Memo: DTC share of Total Active Gbps = D13/D16 | D44: =IFERROR(D13/D16, 0) -> 0.0033527293 | E44: =IFERROR(E13/E16, 0) -> 0.0031885898 | F44: =IFERROR(F13/F16, 0) -> 0.0030540945 | G44: =IFERROR(G13/G16, 0) -> 0.002947035 | H44: =IFERROR(H13/H16, 0) -> 0.0028704956 | I44: =IFERROR(I13/I16, 0) -> 0.0039127961 | J44: =IFERROR(J13/J16, 0) -> 0.0040810781 | K44: =IFERROR(K13/K16, 0) -> 0.0042667808 | ... AC44: =IFERROR(AC13/AC16, 0) -> 0.001789845
A45: BB cost basis ($mm) = Gbps-weighted Constellation D&A + Ground ops + Spectrum amort | D45: =INDEX(Starlink!D:D,MATCH("Constellation Depreciation ($mm)",Starlink!$A:$A,0))*D43+(INDEX(Starlink!D:D,MATCH("Broadband Revenue ($mm)",Starlink!$A:$A,0))+INDEX(Starlink!D:D,MATCH("DTC Revenue ($mm)",Starlink!$A:$A,0))+INDEX(Starlink!D:D,MATCH("Starshield Revenue ($mm)",Starlink!$A:$A,0))+INDEX(Starlink!D:D,MATCH("Hardware Revenue (Terminals) ($mm)",Starlink!$A:$A,0)))*Assumptions!$B$367*D43+INDEX(Starlink!D:D,MATCH("Spectrum amortization ($mm)",Starlink!$A:$A,0)) -> 909.44663 | E45: =INDEX(Starlink!E:E,MATCH("Constellation Depreciation ($mm)",Starlink!$A:$A,0))*E43+(INDEX(Starlink!E:E,MATCH("Broadband Revenue ($mm)",Starlink!$A:$A,0))+INDEX(Starlink!E:E,MATCH("DTC Revenue ($mm)",Starlink!$A:$A,0))+INDEX(Starlink!E:E,MATCH("Starshield Revenue ($mm)",Starlink!$A:$A,0))+INDEX(Starlink!E:E,MATCH("Hardware Revenue (Terminals) ($mm)",Starlink!$A:$A,0)))*Assumptions!$B$367*E43+INDEX(Starlink!E:E,MATCH("Spectrum amortization ($mm)",Starlink!$A:$A,0)) -> 1359.5788 | F45: =INDEX(Starlink!F:F,MATCH("Constellation Depreciation ($mm)",Starlink!$A:$A,0))*F43+(INDEX(Starlink!F:F,MATCH("Broadband Revenue ($mm)",Starlink!$A:$A,0))+INDEX(Starlink!F:F,MATCH("DTC Revenue ($mm)",Starlink!$A:$A,0))+INDEX(Starlink!F:F,MATCH("Starshield Revenue ($mm)",Starlink!$A:$A,0))+INDEX(Starlink!F:F,MATCH("Hardware Revenue (Terminals) ($mm)",Starlink!$A:$A,0)))*Assumptions!$B$367*F43+INDEX(Starlink!F:F,MATCH("Spectrum amortization ($mm)",Starlink!$A:$A,0)) -> 1627.0704 | G45: =INDEX(Starlink!G:G,MATCH("Constellation Depreciation ($mm)",Starlink!$A:$A,0))*G43+(INDEX(Starlink!G:G,MATCH("Broadband Revenue ($mm)",Starlink!$A:$A,0))+INDEX(Starlink!G:G,MATCH("DTC Revenue ($mm)",Starlink!$A:$A,0))+INDEX(Starlink!G:G,MATCH("Starshield Revenue ($mm)",Starlink!$A:$A,0))+INDEX(Starlink!G:G,MATCH("Hardware Revenue (Terminals) ($mm)",Starlink!$A:$A,0)))*Assumptions!$B$367*G43+INDEX(Starlink!G:G,MATCH("Spectrum amortization ($mm)",Starlink!$A:$A,0)) -> 1702.6637 | H45: =INDEX(Starlink!H:H,MATCH("Constellation Depreciation ($mm)",Starlink!$A:$A,0))*H43+(INDEX(Starlink!H:H,MATCH("Broadband Revenue ($mm)",Starlink!$A:$A,0))+INDEX(Starlink!H:H,MATCH("DTC Revenue ($mm)",Starlink!$A:$A,0))+INDEX(Starlink!H:H,MATCH("Starshield Revenue ($mm)",Starlink!$A:$A,0))+INDEX(Starlink!H:H,MATCH("Hardware Revenue (Terminals) ($mm)",Starlink!$A:$A,0)))*Assumptions!$B$367*H43+INDEX(Starlink!H:H,MATCH("Spectrum amortization ($mm)",Starlink!$A:$A,0)) -> 1646.4621 | I45: =INDEX(Starlink!I:I,MATCH("Constellation Depreciation ($mm)",Starlink!$A:$A,0))*I43+(INDEX(Starlink!I:I,MATCH("Broadband Revenue ($mm)",Starlink!$A:$A,0))+INDEX(Starlink!I:I,MATCH("DTC Revenue ($mm)",Starlink!$A:$A,0))+INDEX(Starlink!I:I,MATCH("Starshield Revenue ($mm)",Starlink!$A:$A,0))+INDEX(Starlink!I:I,MATCH("Hardware Revenue (Terminals) ($mm)",Starlink!$A:$A,0)))*Assumptions!$B$367*I43+INDEX(Starlink!I:I,MATCH("Spectrum amortization ($mm)",Starlink!$A:$A,0)) -> 1613.8046 | J45: =INDEX(Starlink!J:J,MATCH("Constellation Depreciation ($mm)",Starlink!$A:$A,0))*J43+(INDEX(Starlink!J:J,MATCH("Broadband Revenue ($mm)",Starlink!$A:$A,0))+INDEX(Starlink!J:J,MATCH("DTC Revenue ($mm)",Starlink!$A:$A,0))+INDEX(Starlink!J:J,MATCH("Starshield Revenue ($mm)",Starlink!$A:$A,0))+INDEX(Starlink!J:J,MATCH("Hardware Revenue (Terminals) ($mm)",Starlink!$A:$A,0)))*Assumptions!$B$367*J43+INDEX(Starlink!J:J,MATCH("Spectrum amortization ($mm)",Starlink!$A:$A,0)) -> 1621.5208 | K45: =INDEX(Starlink!K:K,MATCH("Constellation Depreciation ($mm)",Starlink!$A:$A,0))*K43+(INDEX(Starlink!K:K,MATCH("Broadband Revenue ($mm)",Starlink!$A:$A,0))+INDEX(Starlink!K:K,MATCH("DTC Revenue ($mm)",Starlink!$A:$A,0))+INDEX(Starlink!K:K,MATCH("Starshield Revenue ($mm)",Starlink!$A:$A,0))+INDEX(Starlink!K:K,MATCH("Hardware Revenue (Terminals) ($mm)",Starlink!$A:$A,0)))*Assumptions!$B$367*K43+INDEX(Starlink!K:K,MATCH("Spectrum amortization ($mm)",Starlink!$A:$A,0)) -> 1620.9777 | L45: =INDEX(Starlink!L:L,MATCH("Constellation Depreciation ($mm)",Starlink!$A:$A,0))*L43+(INDEX(Starlink!L:L,MATCH("Broadband Revenue ($mm)",Starlink!$A:$A,0))+INDEX(Starlink!L:L,MATCH("DTC Revenue ($mm)",Starlink!$A:$A,0))+INDEX(Starlink!L:L,MATCH("Starshield Revenue ($mm)",Starlink!$A:$A,0))+INDEX(Starlink!L:L,MATCH("Hardware Revenue (Terminals) ($mm)",Starlink!$A:$A,0)))*Assumptions!$B$367*L43+INDEX(Starlink!L:L,MATCH("Spectrum amortization ($mm)",Starlink!$A:$A,0)) -> 1623.1993 | M45: =INDEX(Starlink!M:M,MATCH("Constellation Depreciation ($mm)",Starlink!$A:$A,0))*M43+(INDEX(Starlink!M:M,MATCH("Broadband Revenue ($mm)",Starlink!$A:$A,0))+INDEX(Starlink!M:M,MATCH("DTC Revenue ($mm)",Starlink!$A:$A,0))+INDEX(Starlink!M:M,MATCH("Starshield Revenue ($mm)",Starlink!$A:$A,0))+INDEX(Starlink!M:M,MATCH("Hardware Revenue (Terminals) ($mm)",Starlink!$A:$A,0)))*Assumptions!$B$367*M43+INDEX(Starlink!M:M,MATCH("Spectrum amortization ($mm)",Starlink!$A:$A,0)) -> 1631.1001 | N45: =INDEX(Starlink!N:N,MATCH("Constellation Depreciation ($mm)",Starlink!$A:$A,0))*N43+(INDEX(Starlink!N:N,MATCH("Broadband Revenue ($mm)",Starlink!$A:$A,0))+INDEX(Starlink!N:N,MATCH("DTC Revenue ($mm)",Starlink!$A:$A,0))+INDEX(Starlink!N:N,MATCH("Starshield Revenue ($mm)",Starlink!$A:$A,0))+INDEX(Starlink!N:N,MATCH("Hardware Revenue (Terminals) ($mm)",Starlink!$A:$A,0)))*Assumptions!$B$367*N43+INDEX(Starlink!N:N,MATCH("Spectrum amortization ($mm)",Starlink!$A:$A,0)) -> 1647.6348 | O45: =INDEX(Starlink!O:O,MATCH("Constellation Depreciation ($mm)",Starlink!$A:$A,0))*O43+(INDEX(Starlink!O:O,MATCH("Broadband Revenue ($mm)",Starlink!$A:$A,0))+INDEX(Starlink!O:O,MATCH("DTC Revenue ($mm)",Starlink!$A:$A,0))+INDEX(Starlink!O:O,MATCH("Starshield Revenue ($mm)",Starlink!$A:$A,0))+INDEX(Starlink!O:O,MATCH("Hardware Revenue (Terminals) ($mm)",Starlink!$A:$A,0)))*Assumptions!$B$367*O43+INDEX(Starlink!O:O,MATCH("Spectrum amortization ($mm)",Starlink!$A:$A,0)) -> 1667.3525 | P45: =INDEX(Starlink!P:P,MATCH("Constellation Depreciation ($mm)",Starlink!$A:$A,0))*P43+(INDEX(Starlink!P:P,MATCH("Broadband Revenue ($mm)",Starlink!$A:$A,0))+INDEX(Starlink!P:P,MATCH("DTC Revenue ($mm)",Starlink!$A:$A,0))+INDEX(Starlink!P:P,MATCH("Starshield Revenue ($mm)",Starlink!$A:$A,0))+INDEX(Starlink!P:P,MATCH("Hardware Revenue (Terminals) ($mm)",Starlink!$A:$A,0)))*Assumptions!$B$367*P43+INDEX(Starlink!P:P,MATCH("Spectrum amortization ($mm)",Starlink!$A:$A,0)) -> 1692.8055 | Q45: =INDEX(Starlink!Q:Q,MATCH("Constellation Depreciation ($mm)",Starlink!$A:$A,0))*Q43+(INDEX(Starlink!Q:Q,MATCH("Broadband Revenue ($mm)",Starlink!$A:$A,0))+INDEX(Starlink!Q:Q,MATCH("DTC Revenue ($mm)",Starlink!$A:$A,0))+INDEX(Starlink!Q:Q,MATCH("Starshield Revenue ($mm)",Starlink!$A:$A,0))+INDEX(Starlink!Q:Q,MATCH("Hardware Revenue (Terminals) ($mm)",Starlink!$A:$A,0)))*Assumptions!$B$367*Q43+INDEX(Starlink!Q:Q,MATCH("Spectrum amortization ($mm)",Starlink!$A:$A,0)) -> 1722.4844 | R45: =INDEX(Starlink!R:R,MATCH("Constellation Depreciation ($mm)",Starlink!$A:$A,0))*R43+(INDEX(Starlink!R:R,MATCH("Broadband Revenue ($mm)",Starlink!$A:$A,0))+INDEX(Starlink!R:R,MATCH("DTC Revenue ($mm)",Starlink!$A:$A,0))+INDEX(Starlink!R:R,MATCH("Starshield Revenue ($mm)",Starlink!$A:$A,0))+INDEX(Starlink!R:R,MATCH("Hardware Revenue (Terminals) ($mm)",Starlink!$A:$A,0)))*Assumptions!$B$367*R43+INDEX(Starlink!R:R,MATCH("Spectrum amortization ($mm)",Starlink!$A:$A,0)) -> 1755.276 | S45: =INDEX(Starlink!S:S,MATCH("Constellation Depreciation ($mm)",Starlink!$A:$A,0))*S43+(INDEX(Starlink!S:S,MATCH("Broadband Revenue ($mm)",Starlink!$A:$A,0))+INDEX(Starlink!S:S,MATCH("DTC Revenue ($mm)",Starlink!$A:$A,0))+INDEX(Starlink!S:S,MATCH("Starshield Revenue ($mm)",Starlink!$A:$A,0))+INDEX(Starlink!S:S,MATCH("Hardware Revenue (Terminals) ($mm)",Starlink!$A:$A,0)))*Assumptions!$B$367*S43+INDEX(Starlink!S:S,MATCH("Spectrum amortization ($mm)",Starlink!$A:$A,0)) -> 1791.8115 | T45: =INDEX(Starlink!T:T,MATCH("Constellation Depreciation ($mm)",Starlink!$A:$A,0))*T43+(INDEX(Starlink!T:T,MATCH("Broadband Revenue ($mm)",Starlink!$A:$A,0))+INDEX(Starlink!T:T,MATCH("DTC Revenue ($mm)",Starlink!$A:$A,0))+INDEX(Starlink!T:T,MATCH("Starshield Revenue ($mm)",Starlink!$A:$A,0))+INDEX(Starlink!T:T,MATCH("Hardware Revenue (Terminals) ($mm)",Starlink!$A:$A,0)))*Assumptions!$B$367*T43+INDEX(Starlink!T:T,MATCH("Spectrum amortization ($mm)",Starlink!$A:$A,0)) -> 1927.1302 | U45: =INDEX(Starlink!U:U,MATCH("Constellation Depreciation ($mm)",Starlink!$A:$A,0))*U43+(INDEX(Starlink!U:U,MATCH("Broadband Revenue ($mm)",Starlink!$A:$A,0))+INDEX(Starlink!U:U,MATCH("DTC Revenue ($mm)",Starlink!$A:$A,0))+INDEX(Starlink!U:U,MATCH("Starshield Revenue ($mm)",Starlink!$A:$A,0))+INDEX(Starlink!U:U,MATCH("Hardware Revenue (Terminals) ($mm)",Starlink!$A:$A,0)))*Assumptions!$B$367*U43+INDEX(Starlink!U:U,MATCH("Spectrum amortization ($mm)",Starlink!$A:$A,0)) -> 1945.0153 | V45: =INDEX(Starlink!V:V,MATCH("Constellation Depreciation ($mm)",Starlink!$A:$A,0))*V43+(INDEX(Starlink!V:V,MATCH("Broadband Revenue ($mm)",Starlink!$A:$A,0))+INDEX(Starlink!V:V,MATCH("DTC Revenue ($mm)",Starlink!$A:$A,0))+INDEX(Starlink!V:V,MATCH("Starshield Revenue ($mm)",Starlink!$A:$A,0))+INDEX(Starlink!V:V,MATCH("Hardware Revenue (Terminals) ($mm)",Starlink!$A:$A,0)))*Assumptions!$B$367*V43+INDEX(Starlink!V:V,MATCH("Spectrum amortization ($mm)",Starlink!$A:$A,0)) -> 1993.4878 | W45: =INDEX(Starlink!W:W,MATCH("Constellation Depreciation ($mm)",Starlink!$A:$A,0))*W43+(INDEX(Starlink!W:W,MATCH("Broadband Revenue ($mm)",Starlink!$A:$A,0))+INDEX(Starlink!W:W,MATCH("DTC Revenue ($mm)",Starlink!$A:$A,0))+INDEX(Starlink!W:W,MATCH("Starshield Revenue ($mm)",Starlink!$A:$A,0))+INDEX(Starlink!W:W,MATCH("Hardware Revenue (Terminals) ($mm)",Starlink!$A:$A,0)))*Assumptions!$B$367*W43+INDEX(Starlink!W:W,MATCH("Spectrum amortization ($mm)",Starlink!$A:$A,0)) -> 2044.387 | X45: =INDEX(Starlink!X:X,MATCH("Constellation Depreciation ($mm)",Starlink!$A:$A,0))*X43+(INDEX(Starlink!X:X,MATCH("Broadband Revenue ($mm)",Starlink!$A:$A,0))+INDEX(Starlink!X:X,MATCH("DTC Revenue ($mm)",Starlink!$A:$A,0))+INDEX(Starlink!X:X,MATCH("Starshield Revenue ($mm)",Starlink!$A:$A,0))+INDEX(Starlink!X:X,MATCH("Hardware Revenue (Terminals) ($mm)",Starlink!$A:$A,0)))*Assumptions!$B$367*X43+INDEX(Starlink!X:X,MATCH("Spectrum amortization ($mm)",Starlink!$A:$A,0)) -> 2095.7668 | Y45: =INDEX(Starlink!Y:Y,MATCH("Constellation Depreciation ($mm)",Starlink!$A:$A,0))*Y43+(INDEX(Starlink!Y:Y,MATCH("Broadband Revenue ($mm)",Starlink!$A:$A,0))+INDEX(Starlink!Y:Y,MATCH("DTC Revenue ($mm)",Starlink!$A:$A,0))+INDEX(Starlink!Y:Y,MATCH("Starshield Revenue ($mm)",Starlink!$A:$A,0))+INDEX(Starlink!Y:Y,MATCH("Hardware Revenue (Terminals) ($mm)",Starlink!$A:$A,0)))*Assumptions!$B$367*Y43+INDEX(Starlink!Y:Y,MATCH("Spectrum amortization ($mm)",Starlink!$A:$A,0)) -> 2213.5603 | Z45: =INDEX(Starlink!Z:Z,MATCH("Constellation Depreciation ($mm)",Starlink!$A:$A,0))*Z43+(INDEX(Starlink!Z:Z,MATCH("Broadband Revenue ($mm)",Starlink!$A:$A,0))+INDEX(Starlink!Z:Z,MATCH("DTC Revenue ($mm)",Starlink!$A:$A,0))+INDEX(Starlink!Z:Z,MATCH("Starshield Revenue ($mm)",Starlink!$A:$A,0))+INDEX(Starlink!Z:Z,MATCH("Hardware Revenue (Terminals) ($mm)",Starlink!$A:$A,0)))*Assumptions!$B$367*Z43+INDEX(Starlink!Z:Z,MATCH("Spectrum amortization ($mm)",Starlink!$A:$A,0)) -> 2326.6931 | AA45: =INDEX(Starlink!AA:AA,MATCH("Constellation Depreciation ($mm)",Starlink!$A:$A,0))*AA43+(INDEX(Starlink!AA:AA,MATCH("Broadband Revenue ($mm)",Starlink!$A:$A,0))+INDEX(Starlink!AA:AA,MATCH("DTC Revenue ($mm)",Starlink!$A:$A,0))+INDEX(Starlink!AA:AA,MATCH("Starshield Revenue ($mm)",Starlink!$A:$A,0))+INDEX(Starlink!AA:AA,MATCH("Hardware Revenue (Terminals) ($mm)",Starlink!$A:$A,0)))*Assumptions!$B$367*AA43+INDEX(Starlink!AA:AA,MATCH("Spectrum amortization ($mm)",Starlink!$A:$A,0)) -> 2447.1134 | AB45: =INDEX(Starlink!AB:AB,MATCH("Constellation Depreciation ($mm)",Starlink!$A:$A,0))*AB43+(INDEX(Starlink!AB:AB,MATCH("Broadband Revenue ($mm)",Starlink!$A:$A,0))+INDEX(Starlink!AB:AB,MATCH("DTC Revenue ($mm)",Starlink!$A:$A,0))+INDEX(Starlink!AB:AB,MATCH("Starshield Revenue ($mm)",Starlink!$A:$A,0))+INDEX(Starlink!AB:AB,MATCH("Hardware Revenue (Terminals) ($mm)",Starlink!$A:$A,0)))*Assumptions!$B$367*AB43+INDEX(Starlink!AB:AB,MATCH("Spectrum amortization ($mm)",Starlink!$A:$A,0)) -> 2573.1627 | AC45: =INDEX(Starlink!AC:AC,MATCH("Constellation Depreciation ($mm)",Starlink!$A:$A,0))*AC43+(INDEX(Starlink!AC:AC,MATCH("Broadband Revenue ($mm)",Starlink!$A:$A,0))+INDEX(Starlink!AC:AC,MATCH("DTC Revenue ($mm)",Starlink!$A:$A,0))+INDEX(Starlink!AC:AC,MATCH("Starshield Revenue ($mm)",Starlink!$A:$A,0))+INDEX(Starlink!AC:AC,MATCH("Hardware Revenue (Terminals) ($mm)",Starlink!$A:$A,0)))*Assumptions!$B$367*AC43+INDEX(Starlink!AC:AC,MATCH("Spectrum amortization ($mm)",Starlink!$A:$A,0)) -> 2712.3678
A46: DTC cost basis ($mm) = Gbps-weighted Constellation D&A + Ground ops (no spectrum) | D46: =INDEX(Starlink!D:D,MATCH("Constellation Depreciation ($mm)",Starlink!$A:$A,0))*D44+(INDEX(Starlink!D:D,MATCH("Broadband Revenue ($mm)",Starlink!$A:$A,0))+INDEX(Starlink!D:D,MATCH("DTC Revenue ($mm)",Starlink!$A:$A,0))+INDEX(Starlink!D:D,MATCH("Starshield Revenue ($mm)",Starlink!$A:$A,0))+INDEX(Starlink!D:D,MATCH("Hardware Revenue (Terminals) ($mm)",Starlink!$A:$A,0)))*Assumptions!$B$367*D44 -> 1.9380497 | E46: =INDEX(Starlink!E:E,MATCH("Constellation Depreciation ($mm)",Starlink!$A:$A,0))*E44+(INDEX(Starlink!E:E,MATCH("Broadband Revenue ($mm)",Starlink!$A:$A,0))+INDEX(Starlink!E:E,MATCH("DTC Revenue ($mm)",Starlink!$A:$A,0))+INDEX(Starlink!E:E,MATCH("Starshield Revenue ($mm)",Starlink!$A:$A,0))+INDEX(Starlink!E:E,MATCH("Hardware Revenue (Terminals) ($mm)",Starlink!$A:$A,0)))*Assumptions!$B$367*E44 -> 1.5767221 | F46: =INDEX(Starlink!F:F,MATCH("Constellation Depreciation ($mm)",Starlink!$A:$A,0))*F44+(INDEX(Starlink!F:F,MATCH("Broadband Revenue ($mm)",Starlink!$A:$A,0))+INDEX(Starlink!F:F,MATCH("DTC Revenue ($mm)",Starlink!$A:$A,0))+INDEX(Starlink!F:F,MATCH("Starshield Revenue ($mm)",Starlink!$A:$A,0))+INDEX(Starlink!F:F,MATCH("Hardware Revenue (Terminals) ($mm)",Starlink!$A:$A,0)))*Assumptions!$B$367*F44 -> 1.3083089 | G46: =INDEX(Starlink!G:G,MATCH("Constellation Depreciation ($mm)",Starlink!$A:$A,0))*G44+(INDEX(Starlink!G:G,MATCH("Broadband Revenue ($mm)",Starlink!$A:$A,0))+INDEX(Starlink!G:G,MATCH("DTC Revenue ($mm)",Starlink!$A:$A,0))+INDEX(Starlink!G:G,MATCH("Starshield Revenue ($mm)",Starlink!$A:$A,0))+INDEX(Starlink!G:G,MATCH("Hardware Revenue (Terminals) ($mm)",Starlink!$A:$A,0)))*Assumptions!$B$367*G44 -> 1.0916465 | H46: =INDEX(Starlink!H:H,MATCH("Constellation Depreciation ($mm)",Starlink!$A:$A,0))*H44+(INDEX(Starlink!H:H,MATCH("Broadband Revenue ($mm)",Starlink!$A:$A,0))+INDEX(Starlink!H:H,MATCH("DTC Revenue ($mm)",Starlink!$A:$A,0))+INDEX(Starlink!H:H,MATCH("Starshield Revenue ($mm)",Starlink!$A:$A,0))+INDEX(Starlink!H:H,MATCH("Hardware Revenue (Terminals) ($mm)",Starlink!$A:$A,0)))*Assumptions!$B$367*H44 -> 0.90142228 | I46: =INDEX(Starlink!I:I,MATCH("Constellation Depreciation ($mm)",Starlink!$A:$A,0))*I44+(INDEX(Starlink!I:I,MATCH("Broadband Revenue ($mm)",Starlink!$A:$A,0))+INDEX(Starlink!I:I,MATCH("DTC Revenue ($mm)",Starlink!$A:$A,0))+INDEX(Starlink!I:I,MATCH("Starshield Revenue ($mm)",Starlink!$A:$A,0))+INDEX(Starlink!I:I,MATCH("Hardware Revenue (Terminals) ($mm)",Starlink!$A:$A,0)))*Assumptions!$B$367*I44 -> 1.1017376 | J46: =INDEX(Starlink!J:J,MATCH("Constellation Depreciation ($mm)",Starlink!$A:$A,0))*J44+(INDEX(Starlink!J:J,MATCH("Broadband Revenue ($mm)",Starlink!$A:$A,0))+INDEX(Starlink!J:J,MATCH("DTC Revenue ($mm)",Starlink!$A:$A,0))+INDEX(Starlink!J:J,MATCH("Starshield Revenue ($mm)",Starlink!$A:$A,0))+INDEX(Starlink!J:J,MATCH("Hardware Revenue (Terminals) ($mm)",Starlink!$A:$A,0)))*Assumptions!$B$367*J44 -> 1.180935 | K46: =INDEX(Starlink!K:K,MATCH("Constellation Depreciation ($mm)",Starlink!$A:$A,0))*K44+(INDEX(Starlink!K:K,MATCH("Broadband Revenue ($mm)",Starlink!$A:$A,0))+INDEX(Starlink!K:K,MATCH("DTC Revenue ($mm)",Starlink!$A:$A,0))+INDEX(Starlink!K:K,MATCH("Starshield Revenue ($mm)",Starlink!$A:$A,0))+INDEX(Starlink!K:K,MATCH("Hardware Revenue (Terminals) ($mm)",Starlink!$A:$A,0)))*Assumptions!$B$367*K44 -> 1.2325747 | L46: =INDEX(Starlink!L:L,MATCH("Constellation Depreciation ($mm)",Starlink!$A:$A,0))*L44+(INDEX(Starlink!L:L,MATCH("Broadband Revenue ($mm)",Starlink!$A:$A,0))+INDEX(Starlink!L:L,MATCH("DTC Revenue ($mm)",Starlink!$A:$A,0))+INDEX(Starlink!L:L,MATCH("Starshield Revenue ($mm)",Starlink!$A:$A,0))+INDEX(Starlink!L:L,MATCH("Hardware Revenue (Terminals) ($mm)",Starlink!$A:$A,0)))*Assumptions!$B$367*L44 -> 1.2917505 | M46: =INDEX(Starlink!M:M,MATCH("Constellation Depreciation ($mm)",Starlink!$A:$A,0))*M44+(INDEX(Starlink!M:M,MATCH("Broadband Revenue ($mm)",Starlink!$A:$A,0))+INDEX(Starlink!M:M,MATCH("DTC Revenue ($mm)",Starlink!$A:$A,0))+INDEX(Starlink!M:M,MATCH("Starshield Revenue ($mm)",Starlink!$A:$A,0))+INDEX(Starlink!M:M,MATCH("Hardware Revenue (Terminals) ($mm)",Starlink!$A:$A,0)))*Assumptions!$B$367*M44 -> 1.3574269 | N46: =INDEX(Starlink!N:N,MATCH("Constellation Depreciation ($mm)",Starlink!$A:$A,0))*N44+(INDEX(Starlink!N:N,MATCH("Broadband Revenue ($mm)",Starlink!$A:$A,0))+INDEX(Starlink!N:N,MATCH("DTC Revenue ($mm)",Starlink!$A:$A,0))+INDEX(Starlink!N:N,MATCH("Starshield Revenue ($mm)",Starlink!$A:$A,0))+INDEX(Starlink!N:N,MATCH("Hardware Revenue (Terminals) ($mm)",Starlink!$A:$A,0)))*Assumptions!$B$367*N44 -> 1.4261159 | O46: =INDEX(Starlink!O:O,MATCH("Constellation Depreciation ($mm)",Starlink!$A:$A,0))*O44+(INDEX(Starlink!O:O,MATCH("Broadband Revenue ($mm)",Starlink!$A:$A,0))+INDEX(Starlink!O:O,MATCH("DTC Revenue ($mm)",Starlink!$A:$A,0))+INDEX(Starlink!O:O,MATCH("Starshield Revenue ($mm)",Starlink!$A:$A,0))+INDEX(Starlink!O:O,MATCH("Hardware Revenue (Terminals) ($mm)",Starlink!$A:$A,0)))*Assumptions!$B$367*O44 -> 1.4919978 | P46: =INDEX(Starlink!P:P,MATCH("Constellation Depreciation ($mm)",Starlink!$A:$A,0))*P44+(INDEX(Starlink!P:P,MATCH("Broadband Revenue ($mm)",Starlink!$A:$A,0))+INDEX(Starlink!P:P,MATCH("DTC Revenue ($mm)",Starlink!$A:$A,0))+INDEX(Starlink!P:P,MATCH("Starshield Revenue ($mm)",Starlink!$A:$A,0))+INDEX(Starlink!P:P,MATCH("Hardware Revenue (Terminals) ($mm)",Starlink!$A:$A,0)))*Assumptions!$B$367*P44 -> 1.5584574 | Q46: =INDEX(Starlink!Q:Q,MATCH("Constellation Depreciation ($mm)",Starlink!$A:$A,0))*Q44+(INDEX(Starlink!Q:Q,MATCH("Broadband Revenue ($mm)",Starlink!$A:$A,0))+INDEX(Starlink!Q:Q,MATCH("DTC Revenue ($mm)",Starlink!$A:$A,0))+INDEX(Starlink!Q:Q,MATCH("Starshield Revenue ($mm)",Starlink!$A:$A,0))+INDEX(Starlink!Q:Q,MATCH("Hardware Revenue (Terminals) ($mm)",Starlink!$A:$A,0)))*Assumptions!$B$367*Q44 -> 1.6238031 | R46: =INDEX(Starlink!R:R,MATCH("Constellation Depreciation ($mm)",Starlink!$A:$A,0))*R44+(INDEX(Starlink!R:R,MATCH("Broadband Revenue ($mm)",Starlink!$A:$A,0))+INDEX(Starlink!R:R,MATCH("DTC Revenue ($mm)",Starlink!$A:$A,0))+INDEX(Starlink!R:R,MATCH("Starshield Revenue ($mm)",Starlink!$A:$A,0))+INDEX(Starlink!R:R,MATCH("Hardware Revenue (Terminals) ($mm)",Starlink!$A:$A,0)))*Assumptions!$B$367*R44 -> 1.6889814 | S46: =INDEX(Starlink!S:S,MATCH("Constellation Depreciation ($mm)",Starlink!$A:$A,0))*S44+(INDEX(Starlink!S:S,MATCH("Broadband Revenue ($mm)",Starlink!$A:$A,0))+INDEX(Starlink!S:S,MATCH("DTC Revenue ($mm)",Starlink!$A:$A,0))+INDEX(Starlink!S:S,MATCH("Starshield Revenue ($mm)",Starlink!$A:$A,0))+INDEX(Starlink!S:S,MATCH("Hardware Revenue (Terminals) ($mm)",Starlink!$A:$A,0)))*Assumptions!$B$367*S44 -> 1.7554089 | T46: =INDEX(Starlink!T:T,MATCH("Constellation Depreciation ($mm)",Starlink!$A:$A,0))*T44+(INDEX(Starlink!T:T,MATCH("Broadband Revenue ($mm)",Starlink!$A:$A,0))+INDEX(Starlink!T:T,MATCH("DTC Revenue ($mm)",Starlink!$A:$A,0))+INDEX(Starlink!T:T,MATCH("Starshield Revenue ($mm)",Starlink!$A:$A,0))+INDEX(Starlink!T:T,MATCH("Hardware Revenue (Terminals) ($mm)",Starlink!$A:$A,0)))*Assumptions!$B$367*T44 -> 1.686711 | U46: =INDEX(Starlink!U:U,MATCH("Constellation Depreciation ($mm)",Starlink!$A:$A,0))*U44+(INDEX(Starlink!U:U,MATCH("Broadband Revenue ($mm)",Starlink!$A:$A,0))+INDEX(Starlink!U:U,MATCH("DTC Revenue ($mm)",Starlink!$A:$A,0))+INDEX(Starlink!U:U,MATCH("Starshield Revenue ($mm)",Starlink!$A:$A,0))+INDEX(Starlink!U:U,MATCH("Hardware Revenue (Terminals) ($mm)",Starlink!$A:$A,0)))*Assumptions!$B$367*U44 -> 1.6840531 | V46: =INDEX(Starlink!V:V,MATCH("Constellation Depreciation ($mm)",Starlink!$A:$A,0))*V44+(INDEX(Starlink!V:V,MATCH("Broadband Revenue ($mm)",Starlink!$A:$A,0))+INDEX(Starlink!V:V,MATCH("DTC Revenue ($mm)",Starlink!$A:$A,0))+INDEX(Starlink!V:V,MATCH("Starshield Revenue ($mm)",Starlink!$A:$A,0))+INDEX(Starlink!V:V,MATCH("Hardware Revenue (Terminals) ($mm)",Starlink!$A:$A,0)))*Assumptions!$B$367*V44 -> 1.763922 | W46: =INDEX(Starlink!W:W,MATCH("Constellation Depreciation ($mm)",Starlink!$A:$A,0))*W44+(INDEX(Starlink!W:W,MATCH("Broadband Revenue ($mm)",Starlink!$A:$A,0))+INDEX(Starlink!W:W,MATCH("DTC Revenue ($mm)",Starlink!$A:$A,0))+INDEX(Starlink!W:W,MATCH("Starshield Revenue ($mm)",Starlink!$A:$A,0))+INDEX(Starlink!W:W,MATCH("Hardware Revenue (Terminals) ($mm)",Starlink!$A:$A,0)))*Assumptions!$B$367*W44 -> 1.8470992 | X46: =INDEX(Starlink!X:X,MATCH("Constellation Depreciation ($mm)",Starlink!$A:$A,0))*X44+(INDEX(Starlink!X:X,MATCH("Broadband Revenue ($mm)",Starlink!$A:$A,0))+INDEX(Starlink!X:X,MATCH("DTC Revenue ($mm)",Starlink!$A:$A,0))+INDEX(Starlink!X:X,MATCH("Starshield Revenue ($mm)",Starlink!$A:$A,0))+INDEX(Starlink!X:X,MATCH("Hardware Revenue (Terminals) ($mm)",Starlink!$A:$A,0)))*Assumptions!$B$367*X44 -> 1.932944 | Y46: =INDEX(Starlink!Y:Y,MATCH("Constellation Depreciation ($mm)",Starlink!$A:$A,0))*Y44+(INDEX(Starlink!Y:Y,MATCH("Broadband Revenue ($mm)",Starlink!$A:$A,0))+INDEX(Starlink!Y:Y,MATCH("DTC Revenue ($mm)",Starlink!$A:$A,0))+INDEX(Starlink!Y:Y,MATCH("Starshield Revenue ($mm)",Starlink!$A:$A,0))+INDEX(Starlink!Y:Y,MATCH("Hardware Revenue (Terminals) ($mm)",Starlink!$A:$A,0)))*Assumptions!$B$367*Y44 -> 2.0569515 | Z46: =INDEX(Starlink!Z:Z,MATCH("Constellation Depreciation ($mm)",Starlink!$A:$A,0))*Z44+(INDEX(Starlink!Z:Z,MATCH("Broadband Revenue ($mm)",Starlink!$A:$A,0))+INDEX(Starlink!Z:Z,MATCH("DTC Revenue ($mm)",Starlink!$A:$A,0))+INDEX(Starlink!Z:Z,MATCH("Starshield Revenue ($mm)",Starlink!$A:$A,0))+INDEX(Starlink!Z:Z,MATCH("Hardware Revenue (Terminals) ($mm)",Starlink!$A:$A,0)))*Assumptions!$B$367*Z44 -> 2.1529034 | AA46: =INDEX(Starlink!AA:AA,MATCH("Constellation Depreciation ($mm)",Starlink!$A:$A,0))*AA44+(INDEX(Starlink!AA:AA,MATCH("Broadband Revenue ($mm)",Starlink!$A:$A,0))+INDEX(Starlink!AA:AA,MATCH("DTC Revenue ($mm)",Starlink!$A:$A,0))+INDEX(Starlink!AA:AA,MATCH("Starshield Revenue ($mm)",Starlink!$A:$A,0))+INDEX(Starlink!AA:AA,MATCH("Hardware Revenue (Terminals) ($mm)",Starlink!$A:$A,0)))*Assumptions!$B$367*AA44 -> 2.2506539 | AB46: =INDEX(Starlink!AB:AB,MATCH("Constellation Depreciation ($mm)",Starlink!$A:$A,0))*AB44+(INDEX(Starlink!AB:AB,MATCH("Broadband Revenue ($mm)",Starlink!$A:$A,0))+INDEX(Starlink!AB:AB,MATCH("DTC Revenue ($mm)",Starlink!$A:$A,0))+INDEX(Starlink!AB:AB,MATCH("Starshield Revenue ($mm)",Starlink!$A:$A,0))+INDEX(Starlink!AB:AB,MATCH("Hardware Revenue (Terminals) ($mm)",Starlink!$A:$A,0)))*Assumptions!$B$367*AB44 -> 2.3560658 | AC46: =INDEX(Starlink!AC:AC,MATCH("Constellation Depreciation ($mm)",Starlink!$A:$A,0))*AC44+(INDEX(Starlink!AC:AC,MATCH("Broadband Revenue ($mm)",Starlink!$A:$A,0))+INDEX(Starlink!AC:AC,MATCH("DTC Revenue ($mm)",Starlink!$A:$A,0))+INDEX(Starlink!AC:AC,MATCH("Starshield Revenue ($mm)",Starlink!$A:$A,0))+INDEX(Starlink!AC:AC,MATCH("Hardware Revenue (Terminals) ($mm)",Starlink!$A:$A,0)))*Assumptions!$B$367*AC44 -> 2.4726838
A47: Marginal BB cost per Gbps/yr ($) = D45 × 1e6 / D12 | D47: =IFERROR(D45*1000000/D12, 0) -> 1580.2612 | E47: =IFERROR(E45*1000000/E12, 0) -> 2216.6828 | F47: =IFERROR(F45*1000000/F12, 0) -> 2508.994 | G47: =IFERROR(G45*1000000/G12, 0) -> 2504.3448 | H47: =IFERROR(H45*1000000/H12, 0) -> 2335.3391 | I47: =IFERROR(I45*1000000/I12, 0) -> 3100.5048 | J47: =IFERROR(J45*1000000/J12, 0) -> 3267.9596 | K47: =IFERROR(K45*1000000/K12, 0) -> 3435.2842 | ... AC47: =IFERROR(AC45*1000000/AC12, 0) -> 2037.3637
A48: Marginal DTC cost per Gbps/yr ($) = D46 × 1e6 / D13 | D48: =IFERROR(D46*1000000/D13, 0) -> 1001.0587 | E48: =IFERROR(E46*1000000/E13, 0) -> 803.65319 | F48: =IFERROR(F46*1000000/F13, 0) -> 658.55601 | G48: =IFERROR(G46*1000000/G13, 0) -> 543.22561 | H48: =IFERROR(H46*1000000/H13, 0) -> 444.14131 | I48: =IFERROR(I46*1000000/I13, 0) -> 538.85235 | J48: =IFERROR(J46*1000000/J13, 0) -> 580.8035 | K48: =IFERROR(K46*1000000/K13, 0) -> 609.59518 | ... AC48: =IFERROR(AC46*1000000/AC13, 0) -> 1035.8458
A49: [Note: Rule 23 exception — both rates are year-by-year derived, not deterministic ramps]
A50: ODC pays Starlink for BB ($mm) = D25 × D47 / 1e6 | D50: =IFERROR(D25*D47/1000000, 0) -> 0 | E50: =IFERROR(E25*E47/1000000, 0) -> 0 | F50: =IFERROR(F25*F47/1000000, 0) -> 0 | G50: =IFERROR(G25*G47/1000000, 0) -> 0 | H50: =IFERROR(H25*H47/1000000, 0) -> 0 | I50: =IFERROR(I25*I47/1000000, 0) -> 0 | J50: =IFERROR(J25*J47/1000000, 0) -> 0 | K50: =IFERROR(K25*K47/1000000, 0) -> 0 | ... AC50: =IFERROR(AC25*AC47/1000000, 0) -> 0
A51: ODC pays Starlink for DTC ($mm) = D26 × D48 / 1e6 | D51: =IFERROR(D26*D48/1000000, 0) -> 0 | E51: =IFERROR(E26*E48/1000000, 0) -> 0 | F51: =IFERROR(F26*F48/1000000, 0) -> 0 | G51: =IFERROR(G26*G48/1000000, 0) -> 0 | H51: =IFERROR(H26*H48/1000000, 0) -> 0 | I51: =IFERROR(I26*I48/1000000, 0) -> 0 | J51: =IFERROR(J26*J48/1000000, 0) -> 0 | K51: =IFERROR(K26*K48/1000000, 0) -> 0 | ... AC51: =IFERROR(AC26*AC48/1000000, 0) -> 0
A52: AI Stack pays Starlink BB ($mm) — scaffold, locked at zero | D52: 0 | E52: 0 | F52: 0 | G52: 0 | H52: 0 | I52: 0 | J52: 0 | K52: 0 | L52: 0 | M52: 0 | N52: 0 | O52: 0 | P52: 0 | Q52: 0 | R52: 0 | S52: 0 | T52: 0 | U52: 0 | V52: 0 | W52: 0 | X52: 0 | Y52: 0 | Z52: 0 | AA52: 0 | AB52: 0 | AC52: 0
A53: AI Stack pays Starlink DTC ($mm) — scaffold, locked at zero | D53: 0 | E53: 0 | F53: 0 | G53: 0 | H53: 0 | I53: 0 | J53: 0 | K53: 0 | L53: 0 | M53: 0 | N53: 0 | O53: 0 | P53: 0 | Q53: 0 | R53: 0 | S53: 0 | T53: 0 | U53: 0 | V53: 0 | W53: 0 | X53: 0 | Y53: 0 | Z53: 0 | AA53: 0 | AB53: 0 | AC53: 0
A54: Total internal bandwidth revenue ($mm) = D50 + D51 + D52 + D53 ← BOOKED ON Starlink R116 | D54: =D50+D51+D52+D53 -> 0 | E54: =E50+E51+E52+E53 -> 0 | F54: =F50+F51+F52+F53 -> 0 | G54: =G50+G51+G52+G53 -> 0 | H54: =H50+H51+H52+H53 -> 0 | I54: =I50+I51+I52+I53 -> 0 | J54: =J50+J51+J52+J53 -> 0 | K54: =K50+K51+K52+K53 -> 0 | ... AC54: =AC50+AC51+AC52+AC53 -> 0

Sheet Customer Launch
A1: LAUNCH
A2: SpaceX Modular Valuation Model — $mm unless noted
A4: INPUTS FROM CENTRAL ALLOCATOR
A6: Capital Allocation ($mm) | D6: =Allocator!D11 -> 240 | E6: =Allocator!E11 -> 236.45318 | F6: =Allocator!F11 -> 238.63025 | G6: =Allocator!G11 -> 208.55973 | H6: =Allocator!H11 -> 178.41674 | I6: =Allocator!I11 -> 148.88105 | J6: =Allocator!J11 -> 119.11335 | K6: =Allocator!K11 -> 89.619636 | ... AC6: =Allocator!AC11 -> 0.12138466
A7: Starship Capacity Allocation (kg-to-LEO) | D7: =Allocator!D80 -> 0 | E7: =Allocator!E80 -> 0 | F7: =Allocator!F80 -> 46518.68 | G7: =Allocator!G80 -> 68432.465 | H7: =Allocator!H80 -> 81756.361 | I7: =Allocator!I80 -> 102747.59 | J7: =Allocator!J80 -> 108288.78 | K7: =Allocator!K80 -> 114532.55 | ... AC7: =Allocator!AC80 -> 25523.618
A8: Cash Sweep Contribution ($mm) | D8: =0 -> 0 | E8: =0 -> 0 | F8: =0 -> 0 | G8: =0 -> 0 | H8: =0 -> 0 | I8: =0 -> 0 | J8: =0 -> 0 | K8: =0 -> 0 | ... AC8: =0 -> 0
A9: Total Capital Available ($mm) | D9: =D6+D8 -> 240 | E9: =E6+E8 -> 236.45318 | F9: =F6+F8 -> 238.63025 | G9: =G6+G8 -> 208.55973 | H9: =H6+H8 -> 178.41674 | I9: =I6+I8 -> 148.88105 | J9: =J6+J8 -> 119.11335 | K9: =K6+K8 -> 89.619636 | ... AC9: =AC6+AC8 -> 0.12138466
A11: Year | D11: 2025 | E11: 2026 | F11: 2027 | G11: 2028 | H11: 2029 | I11: 2030 | J11: 2031 | K11: 2032 | L11: 2033 | M11: 2034 | N11: 2035 | O11: 2036 | P11: 2037 | Q11: 2038 | R11: 2039 | S11: 2040 | T11: 2041 | U11: 2042 | V11: 2043 | W11: 2044 | X11: 2045 | Y11: 2046 | Z11: 2047 | AA11: 2048 | AB11: 2049 | AC11: 2050
A13: MODULE LOGIC
A15: 1. Inputs from Launch Capacity
A16: F9 launches available | D16: ='Launch Capacity'!D7 -> 336 | E16: ='Launch Capacity'!E7 -> 432 | F16: ='Launch Capacity'!F7 -> 528 | G16: ='Launch Capacity'!G7 -> 618 | H16: ='Launch Capacity'!H7 -> 696 | I16: ='Launch Capacity'!I7 -> 762 | J16: ='Launch Capacity'!J7 -> 816 | K16: ='Launch Capacity'!K7 -> 858 | ... AC16: ='Launch Capacity'!AC7 -> 912
A17: F9 cost per launch ($mm) | D17: ='Launch Capacity'!D8 -> 17.75 | E17: ='Launch Capacity'!E8 -> 17.727832 | F17: ='Launch Capacity'!F8 -> 17.72 | G17: ='Launch Capacity'!G8 -> 17.714179 | H17: ='Launch Capacity'!H8 -> 17.709767 | I17: ='Launch Capacity'!I8 -> 17.706419 | J17: ='Launch Capacity'!J8 -> 17.703923 | K17: ='Launch Capacity'!K8 -> 17.702146 | ... AC17: ='Launch Capacity'!AC8 -> 17.700443
A18: Starship cost per launch ($mm) | D18: ='Launch Capacity'!D141 -> 58.5 | E18: ='Launch Capacity'!E141 -> 39.039 | F18: ='Launch Capacity'!F141 -> 30.63888 | G18: ='Launch Capacity'!G141 -> 25.502473 | H18: ='Launch Capacity'!H141 -> 18.460419 | I18: ='Launch Capacity'!I141 -> 12.0764 | J18: ='Launch Capacity'!J141 -> 8.9322055 | K18: ='Launch Capacity'!K141 -> 6.0234195 | ... AC18: ='Launch Capacity'!AC141 -> 2.3279667
A19: Starship customer slots (kg from Allocator) | D19: =D7 -> 0 | E19: =E7 -> 0 | F19: =F7 -> 46518.68 | G19: =G7 -> 68432.465 | H19: =H7 -> 81756.361 | I19: =I7 -> 102747.59 | J19: =J7 -> 108288.78 | K19: =K7 -> 114532.55 | ... AC19: =AC7 -> 25523.618
A21: 2. Market sizing
A22: Commercial launch market ($mm) | D22: =Assumptions!D191 -> 8000 | E22: =Assumptions!E191 -> 8640 | F22: =Assumptions!F191 -> 9331.2 | G22: =Assumptions!G191 -> 10077.696 | H22: =Assumptions!H191 -> 10883.912 | I22: =Assumptions!I191 -> 11754.625 | J22: =Assumptions!J191 -> 12694.995 | K22: =Assumptions!K191 -> 13710.594 | ... AC22: =Assumptions!AC191 -> 54787.802
A23: Government launch market ($mm) | D23: =Assumptions!D192 -> 4000 | E23: =Assumptions!E192 -> 4200 | F23: =Assumptions!F192 -> 4410 | G23: =Assumptions!G192 -> 4630.5 | H23: =Assumptions!H192 -> 4862.025 | I23: =Assumptions!I192 -> 5105.1263 | J23: =Assumptions!J192 -> 5360.3826 | K23: =Assumptions!K192 -> 5628.4017 | ... AC23: =Assumptions!AC192 -> 13545.42
A25: 3. SpaceX market share
A26: Commercial market share % | D26: =Assumptions!D193 -> 0.7 | E26: =Assumptions!E193 -> 0.70666667 | F26: =Assumptions!F193 -> 0.71333333 | G26: =Assumptions!G193 -> 0.72 | H26: =Assumptions!H193 -> 0.72666667 | I26: =Assumptions!I193 -> 0.73333333 | J26: =Assumptions!J193 -> 0.74 | K26: =Assumptions!K193 -> 0.74666667 | ... AC26: =Assumptions!AC193 -> 0.8
A27: Government market share % | D27: =Assumptions!D194 -> 0.9 | E27: =Assumptions!E194 -> 0.89333333 | F27: =Assumptions!F194 -> 0.88666667 | G27: =Assumptions!G194 -> 0.88 | H27: =Assumptions!H194 -> 0.87333333 | I27: =Assumptions!I194 -> 0.86666667 | J27: =Assumptions!J194 -> 0.86 | K27: =Assumptions!K194 -> 0.85333333 | ... AC27: =Assumptions!AC194 -> 0.8
A28: SpaceX commercial $ addressable ($mm) | D28: =D22*D26 -> 5600 | E28: =E22*E26 -> 6105.6 | F28: =F22*F26 -> 6656.256 | G28: =G22*G26 -> 7255.9411 | H28: =H22*H26 -> 7908.9758 | I28: =I22*I26 -> 8620.0581 | J28: =J22*J26 -> 9394.296 | K28: =K22*K26 -> 10237.244 | ... AC28: =AC22*AC26 -> 43830.241
A29: SpaceX government $ addressable ($mm) | D29: =D23*D27 -> 3600 | E29: =E23*E27 -> 3752 | F29: =F23*F27 -> 3910.2 | G29: =G23*G27 -> 4074.84 | H29: =H23*H27 -> 4246.1685 | I29: =I23*I27 -> 4424.4428 | J29: =J23*J27 -> 4609.929 | K29: =K23*K27 -> 4802.9028 | ... AC29: =AC23*AC27 -> 10836.336
A31: 4. Customer pricing
A32: F9 customer price ($mm/launch) | D32: =Assumptions!D195 -> 67 | E32: =Assumptions!E195 -> 64.99 | F32: =Assumptions!F195 -> 63.0403 | G32: =Assumptions!G195 -> 61.149091 | H32: =Assumptions!H195 -> 59.314618 | I32: =Assumptions!I195 -> 57.53518 | J32: =Assumptions!J195 -> 55.809124 | K32: =Assumptions!K195 -> 54.134851 | ... AC32: =Assumptions!AC195 -> 31.287305
A33: Starship customer price ($mm/launch) | D33: =Assumptions!D196 -> 0 | E33: =Assumptions!E196 -> 0 | F33: =Assumptions!F196 -> 100 | G33: =Assumptions!G196 -> 92 | H33: =Assumptions!H196 -> 84.64 | I33: =Assumptions!I196 -> 77.8688 | J33: =Assumptions!J196 -> 71.639296 | K33: =Assumptions!K196 -> 65.908152 | ... AC33: =Assumptions!AC196 -> 14.693323
A35: 5. Revenue build
A36: F9 commercial launches | D36: =IFERROR(MIN(D16, D28/D32), 0) -> 83.58209 | E36: =IFERROR(MIN(E16, E28/E32), 0) -> 93.946761 | F36: =IFERROR(MIN(F16, F28/F32), 0) -> 105.58731 | G36: =IFERROR(MIN(G16, G28/G32), 0) -> 118.65984 | H36: =IFERROR(MIN(H16, H28/H32), 0) -> 133.3394 | I36: =IFERROR(MIN(I16, I28/I32), 0) -> 149.82239 | J36: =IFERROR(MIN(J16, J28/J32), 0) -> 168.32903 | K36: =IFERROR(MIN(K16, K28/K32), 0) -> 189.10634 | ... AC36: =IFERROR(MIN(AC16, AC28/AC32), 0) -> 912
A37: F9 government launches | D37: =IFERROR(MIN(MAX(0,D16-D36), D29/D32), 0) -> 53.731343 | E37: =IFERROR(MIN(MAX(0,E16-E36), E29/E32), 0) -> 57.731959 | F37: =IFERROR(MIN(MAX(0,F16-F36), F29/F32), 0) -> 62.026989 | G37: =IFERROR(MIN(MAX(0,G16-G36), G29/G32), 0) -> 66.637785 | H37: =IFERROR(MIN(MAX(0,H16-H36), H29/H32), 0) -> 71.587218 | I37: =IFERROR(MIN(MAX(0,I16-I36), I29/I32), 0) -> 76.899782 | J37: =IFERROR(MIN(MAX(0,J16-J36), J29/J32), 0) -> 82.601708 | K37: =IFERROR(MIN(MAX(0,K16-K36), K29/K32), 0) -> 88.721087 | ... AC37: =IFERROR(MIN(MAX(0,AC16-AC36), AC29/AC32), 0) -> 0
A38: F9 total launches sold | D38: =D36+D37 -> 137.31343 | E38: =E36+E37 -> 151.67872 | F38: =F36+F37 -> 167.6143 | G38: =G36+G37 -> 185.29762 | H38: =H36+H37 -> 204.92662 | I38: =I36+I37 -> 226.72217 | J38: =J36+J37 -> 250.93074 | K38: =K36+K37 -> 277.82743 | ... AC38: =AC36+AC37 -> 912
A39: Starship customer launches (from Allocator) | D39: =IFERROR(D19/Assumptions!$B$202, 0) -> 0 | E39: =IFERROR(E19/Assumptions!$B$202, 0) -> 0 | F39: =IFERROR(F19/Assumptions!$B$202, 0) -> 0.31012453 | G39: =IFERROR(G19/Assumptions!$B$202, 0) -> 0.45621644 | H39: =IFERROR(H19/Assumptions!$B$202, 0) -> 0.54504241 | I39: =IFERROR(I19/Assumptions!$B$202, 0) -> 0.68498393 | J39: =IFERROR(J19/Assumptions!$B$202, 0) -> 0.7219252 | K39: =IFERROR(K19/Assumptions!$B$202, 0) -> 0.76355036 | ... AC39: =IFERROR(AC19/Assumptions!$B$202, 0) -> 0.17015746
A40: Starship customer commercial launches | D40: =D39*IFERROR(D28/(D28+D29),0.7) -> 0 | E40: =E39*IFERROR(E28/(E28+E29),0.7) -> 0 | F40: =F39*IFERROR(F28/(F28+F29),0.7) -> 0.19536052 | G40: =G39*IFERROR(G28/(G28+G29),0.7) -> 0.29214928 | H40: =H39*IFERROR(H28/(H28+H29),0.7) -> 0.35464221 | I40: =I39*IFERROR(I28/(I28+I29),0.7) -> 0.45265061 | J40: =J39*IFERROR(J28/(J28+J29),0.7) -> 0.48428092 | K40: =K39*IFERROR(K28/(K28+K29),0.7) -> 0.51971908 | ... AC40: =AC39*IFERROR(AC28/(AC28+AC29),0.7) -> 0.13642783
A41: Starship customer government launches | D41: =D39-D40 -> 0 | E41: =E39-E40 -> 0 | F41: =F39-F40 -> 0.11476402 | G41: =G39-G40 -> 0.16406715 | H41: =H39-H40 -> 0.1904002 | I41: =I39-I40 -> 0.23233332 | J41: =J39-J40 -> 0.23764428 | K41: =K39-K40 -> 0.24383128 | ... AC41: =AC39-AC40 -> 0.033729629
A42: F9 commercial revenue ($mm) | D42: =D36*D32 -> 5600 | E42: =E36*E32 -> 6105.6 | F42: =F36*F32 -> 6656.256 | G42: =G36*G32 -> 7255.9411 | H42: =H36*H32 -> 7908.9758 | I42: =I36*I32 -> 8620.0581 | J42: =J36*J32 -> 9394.296 | K42: =K36*K32 -> 10237.244 | ... AC42: =AC36*AC32 -> 28534.022
A43: F9 government revenue ($mm) | D43: =D37*D32 -> 3600 | E43: =E37*E32 -> 3752 | F43: =F37*F32 -> 3910.2 | G43: =G37*G32 -> 4074.84 | H43: =H37*H32 -> 4246.1685 | I43: =I37*I32 -> 4424.4428 | J43: =J37*J32 -> 4609.929 | K43: =K37*K32 -> 4802.9028 | ... AC43: =AC37*AC32 -> 0
A44: Starship commercial revenue ($mm) | D44: =D40*D33 -> 0 | E44: =E40*E33 -> 0 | F44: =F40*F33 -> 19.536052 | G44: =G40*G33 -> 26.877734 | H44: =H40*H33 -> 30.016917 | I44: =I40*I33 -> 35.24736 | J44: =J40*J33 -> 34.693544 | K44: =K40*K33 -> 34.253724 | ... AC44: =AC40*AC33 -> 2.0045782
A45: Starship government revenue ($mm) | D45: =D41*D33 -> 0 | E45: =E41*E33 -> 0 | F45: =F41*F33 -> 11.476402 | G45: =G41*G33 -> 15.094178 | H45: =H41*H33 -> 16.115473 | I45: =I41*I33 -> 18.091517 | J45: =J41*J33 -> 17.024669 | K45: =K41*K33 -> 16.070469 | ... AC45: =AC41*AC33 -> 0.49560033
A46: P2P revenue (placeholder — deferred) | D46: 0 | E46: 0 | F46: 0 | G46: 0 | H46: 0 | I46: 0 | J46: 0 | K46: 0 | L46: 0 | M46: 0 | N46: 0 | O46: 0 | P46: 0 | Q46: 0 | R46: 0 | S46: 0 | T46: 0 | U46: 0 | V46: 0 | W46: 0 | X46: 0 | Y46: 0 | Z46: 0 | AA46: 0 | AB46: 0 | AC46: 0
A47: Total Revenue ($mm) | D47: =D42+D43+D44+D45+D46 -> 9200 | E47: =E42+E43+E44+E45+E46 -> 9857.6 | F47: =F42+F43+F44+F45+F46 -> 10597.468 | G47: =G42+G43+G44+G45+G46 -> 11372.753 | H47: =H42+H43+H44+H45+H46 -> 12201.277 | I47: =I42+I43+I44+I45+I46 -> 13097.84 | J47: =J42+J43+J44+J45+J46 -> 14055.943 | K47: =K42+K43+K44+K45+K46 -> 15090.471 | ... AC47: =AC42+AC43+AC44+AC45+AC46 -> 28536.523
A49: COST OF GOODS SOLD (vending-machine framework) | B49: (consolidated D&A view → CapEx tab)
A50: F9 launch variable cost ($mm) | D50: =D38*D17 -> 2437.3134 | E50: =E38*E17 -> 2688.9349 | F50: =F38*F17 -> 2970.1255 | G50: =G38*G17 -> 3282.3952 | H50: =H38*H17 -> 3629.2027 | I50: =I38*I17 -> 4014.4377 | J50: =J38*J17 -> 4442.4586 | K50: =K38*K17 -> 4918.1418 | ... AC50: =AC38*AC17 -> 16142.804
A51: Starship launch variable cost ($mm) | D51: =(D39+D101)*D18 -> 50.29477 | E51: =(E39+E101)*E18 -> 32.737219 | F51: =(F39+F101)*F18 -> 33.952788 | G51: =(G39+G101)*G18 -> 30.537284 | H51: =(H39+H101)*H18 -> 22.007988 | I51: =(I39+I101)*I18 -> 14.133514 | J51: =(J39+J101)*J18 -> 10.669823 | K51: =(K39+K101)*K18 -> 7.2017459 | ... AC51: =(AC39+AC101)*AC18 -> 3.8386542
A52: Insurance — external launches ($mm) | D52: =D59*Assumptions!$B$375 -> 460 | E52: =E59*Assumptions!$B$375 -> 492.88 | F52: =F59*Assumptions!$B$375 -> 529.87342 | G52: =G59*Assumptions!$B$375 -> 568.63765 | H52: =H59*Assumptions!$B$375 -> 610.06384 | I52: =I59*Assumptions!$B$375 -> 654.89198 | J52: =J59*Assumptions!$B$375 -> 702.79716 | K52: =K59*Assumptions!$B$375 -> 754.52353 | ... AC52: =AC59*Assumptions!$B$375 -> 1426.8261
A53: Other COGS — external launches ($mm) | D53: =D59*Assumptions!$B$376 -> 184 | E53: =E59*Assumptions!$B$376 -> 197.152 | F53: =F59*Assumptions!$B$376 -> 211.94937 | G53: =G59*Assumptions!$B$376 -> 227.45506 | H53: =H59*Assumptions!$B$376 -> 244.02553 | I53: =I59*Assumptions!$B$376 -> 261.95679 | J53: =J59*Assumptions!$B$376 -> 281.11886 | K53: =K59*Assumptions!$B$376 -> 301.80941 | ... AC53: =AC59*Assumptions!$B$376 -> 570.73045
A54: F9 fleet D&A ($mm) | D54: {=SUMPRODUCT((COLUMN($D$52:D$52)>=COLUMN($D$52))*(COLUMN($D$52:D$52)<=COLUMN(D$52))*('Launch Capacity'!$D$52:D$52),'Launch Capacity'!$D$62:D$62)/Assumptions!$B$199} -> 48 | E54: {=SUMPRODUCT((COLUMN($D$52:E$52)>=COLUMN($D$52))*(COLUMN($D$52:E$52)<=COLUMN(E$52))*('Launch Capacity'!$D$52:E$52),'Launch Capacity'!$D$62:E$62)/Assumptions!$B$199} -> 95.290636 | F54: {=SUMPRODUCT((COLUMN($D$52:F$52)>=COLUMN($D$52))*(COLUMN($D$52:F$52)<=COLUMN(F$52))*('Launch Capacity'!$D$52:F$52),'Launch Capacity'!$D$62:F$62)/Assumptions!$B$199} -> 142.33064 | G54: {=SUMPRODUCT((COLUMN($D$52:G$52)>=COLUMN($D$52))*(COLUMN($D$52:G$52)<=COLUMN(G$52))*('Launch Capacity'!$D$52:G$52),'Launch Capacity'!$D$62:G$62)/Assumptions!$B$199} -> 183.32765 | H54: {=SUMPRODUCT((COLUMN($D$52:H$52)>=COLUMN($D$52))*(COLUMN($D$52:H$52)<=COLUMN(H$52))*('Launch Capacity'!$D$52:H$52),'Launch Capacity'!$D$62:H$62)/Assumptions!$B$199} -> 218.36205 | I54: {=SUMPRODUCT((COLUMN($D$52:I$52)>=COLUMN($D$52))*(COLUMN($D$52:I$52)<=COLUMN(I$52))*('Launch Capacity'!$D$52:I$52),'Launch Capacity'!$D$62:I$62)/Assumptions!$B$199} -> 247.49043 | J54: {=SUMPRODUCT((COLUMN($D$52:J$52)>=COLUMN($D$52))*(COLUMN($D$52:J$52)<=COLUMN(J$52))*('Launch Capacity'!$D$52:J$52),'Launch Capacity'!$D$62:J$62)/Assumptions!$B$199} -> 270.75321 | K54: {=SUMPRODUCT((COLUMN($D$52:K$52)>=COLUMN($D$52))*(COLUMN($D$52:K$52)<=COLUMN(K$52))*('Launch Capacity'!$D$52:K$52),'Launch Capacity'!$D$62:K$62)/Assumptions!$B$199} -> 288.17896 | ... AC54: {=SUMPRODUCT((COLUMN($D$52:AC$52)>=COLUMN($D$52))*(COLUMN($D$52:AC$52)<=COLUMN(AC$52))*('Launch Capacity'!$D$52:AC$52),'Launch Capacity'!$D$62:AC$62)/Assumptions!$B$199} -> 305.58875
A55: Starship fleet D&A — total fleet ($mm) | D55: =(D39+D101)*'Launch Capacity'!D136/Assumptions!$B$199 -> 6.0353724 | E55: =(E39+E101)*'Launch Capacity'!E136/Assumptions!$B$199 -> 2.9434063 | F55: =(F39+F101)*'Launch Capacity'!F136/Assumptions!$B$199 -> 2.4514454 | G55: =(G39+G101)*'Launch Capacity'!G136/Assumptions!$B$199 -> 1.8764774 | H55: =(H39+H101)*'Launch Capacity'!H136/Assumptions!$B$199 -> 1.419428 | I55: =(I39+I101)*'Launch Capacity'!I136/Assumptions!$B$199 -> 1.1068624 | J55: =(J39+J101)*'Launch Capacity'!J136/Assumptions!$B$199 -> 0.92643406 | K55: =(K39+K101)*'Launch Capacity'!K136/Assumptions!$B$199 -> 0.78007769 | ... AC55: =(AC39+AC101)*'Launch Capacity'!AC136/Assumptions!$B$199 -> 0.23525835
A56: Total fleet D&A ($mm) | D56: =D54+D55 -> 54.035372 | E56: =E54+E55 -> 98.234043 | F56: =F54+F55 -> 144.78208 | G56: =G54+G55 -> 185.20412 | H56: =H54+H55 -> 219.78148 | I56: =I54+I55 -> 248.5973 | J56: =J54+J55 -> 271.67964 | K56: =K54+K55 -> 288.95904 | ... AC56: =AC54+AC55 -> 305.82401
A57: Total COGS ($mm) | D57: =SUM(D50:D53)+D56 -> 3185.6436 | E57: =SUM(E50:E53)+E56 -> 3509.9382 | F57: =SUM(F50:F53)+F56 -> 3890.6831 | G57: =SUM(G50:G53)+G56 -> 4294.2293 | H57: =SUM(H50:H53)+H56 -> 4725.0816 | I57: =SUM(I50:I53)+I56 -> 5194.0173 | J57: =SUM(J50:J53)+J56 -> 5708.7241 | K57: =SUM(K50:K53)+K56 -> 6270.6355 | ... AC57: =SUM(AC50:AC53)+AC56 -> 18450.023
A58: ─── Revenue split (external vs internal) ───
A59: External revenue ($mm) — market price | D59: =D42+D43+D44+D45+D46 -> 9200 | E59: =E42+E43+E44+E45+E46 -> 9857.6 | F59: =F42+F43+F44+F45+F46 -> 10597.468 | G59: =G42+G43+G44+G45+G46 -> 11372.753 | H59: =H42+H43+H44+H45+H46 -> 12201.277 | I59: =I42+I43+I44+I45+I46 -> 13097.84 | J59: =J42+J43+J44+J45+J46 -> 14055.943 | K59: =K42+K43+K44+K45+K46 -> 15090.471 | ... AC59: =AC42+AC43+AC44+AC45+AC46 -> 28536.523
A60: Internal transfer revenue ($mm) — at-cost | D60: =SUM('Customer Launch'!D106:D108) -> 56.330142 | E60: =SUM('Customer Launch'!E106:E108) -> 35.680626 | F60: =SUM('Customer Launch'!F106:F108) -> 26.216315 | G60: =SUM('Customer Launch'!G106:G108) -> 20.064179 | H60: =SUM('Customer Launch'!H106:H108) -> 12.716764 | I60: =SUM('Customer Launch'!I106:I108) -> 6.3204057 | J60: =SUM('Customer Launch'!J106:J108) -> 4.5879755 | K60: =SUM('Customer Launch'!K106:K108) -> 2.8844657 | ... AC60: =SUM('Customer Launch'!AC106:AC108) -> 3.6535147
A61: Total Revenue ($mm) | D61: =D59+D60 -> 9256.3301 | E61: =E59+E60 -> 9893.2806 | F61: =F59+F60 -> 10623.685 | G61: =G59+G60 -> 11392.817 | H61: =H59+H60 -> 12213.993 | I61: =I59+I60 -> 13104.16 | J61: =J59+J60 -> 14060.531 | K61: =K59+K60 -> 15093.355 | ... AC61: =AC59+AC60 -> 28540.176
A62: Gross Profit ($mm) | D62: =D61-D57 -> 6070.6866 | E62: =E61-E57 -> 6383.3424 | F62: =F61-F57 -> 6733.0016 | G62: =G61-G57 -> 7098.5879 | H62: =H61-H57 -> 7488.9119 | I62: =I61-I57 -> 7910.1428 | J62: =J61-J57 -> 8351.8071 | K62: =K61-K57 -> 8822.7196 | ... AC62: =AC61-AC57 -> 10090.153
A63: Gross Margin % | D63: =IFERROR(D62/D61,0) -> 0.65584162 | E63: =IFERROR(E62/E61,0) -> 0.64521999 | F63: =IFERROR(F62/F61,0) -> 0.63377272 | G63: =IFERROR(G62/G61,0) -> 0.62307573 | H63: =IFERROR(H62/H61,0) -> 0.61314196 | I63: =IFERROR(I62/I61,0) -> 0.603636 | J63: =IFERROR(J62/J61,0) -> 0.59398944 | K63: =IFERROR(K62/K61,0) -> 0.5845433 | ... AC63: =IFERROR(AC62/AC61,0) -> 0.35354208
A64: External Gross Margin % (memo) | D64: =IFERROR((D59-(D50+D51*IFERROR(D39/(D39+D101),0)+D52+D53+D54+D55*IFERROR(D39/(D39+D101),0)))/D59,0) -> 0.65985724 | E64: =IFERROR((E59-(E50+E51*IFERROR(E39/(E39+E101),0)+E52+E53+E54+E55*IFERROR(E39/(E39+E101),0)))/E59,0) -> 0.64755543 | F64: =IFERROR((F59-(F50+F51*IFERROR(F39/(F39+F101),0)+F52+F53+F54+F55*IFERROR(F39/(F39+F101),0)))/F59,0) -> 0.63534057 | G64: =IFERROR((G59-(G50+G51*IFERROR(G39/(G39+G101),0)+G52+G53+G54+G55*IFERROR(G39/(G39+G101),0)))/G59,0) -> 0.62417498 | H64: =IFERROR((H59-(H50+H51*IFERROR(H39/(H39+H101),0)+H52+H53+H54+H55*IFERROR(H39/(H39+H101),0)))/H59,0) -> 0.61378101 | I64: =IFERROR((I59-(I50+I51*IFERROR(I39/(I39+I101),0)+I52+I53+I54+I55*IFERROR(I39/(I39+I101),0)))/I59,0) -> 0.60392729 | J64: =IFERROR((J59-(J50+J51*IFERROR(J39/(J39+J101),0)+J52+J53+J54+J55*IFERROR(J39/(J39+J101),0)))/J59,0) -> 0.59418332 | K64: =IFERROR((K59-(K50+K51*IFERROR(K39/(K39+K101),0)+K52+K53+K54+K55*IFERROR(K39/(K39+K101),0)))/K59,0) -> 0.58465503 | ... AC64: =IFERROR((AC59-(AC50+AC51*IFERROR(AC39/(AC39+AC101),0)+AC52+AC53+AC54+AC55*IFERROR(AC39/(AC39+AC101),0)))/AC59,0) -> 0.35358734
A65: ─── Module FCF build (pre-tax, pre-corp-overhead) ───
A66: Module EBITDA ($mm) = Gross Profit | D66: =D62 -> 6070.6866 | E66: =E62 -> 6383.3424 | F66: =F62 -> 6733.0016 | G66: =G62 -> 7098.5879 | H66: =H62 -> 7488.9119 | I66: =I62 -> 7910.1428 | J66: =J62 -> 8351.8071 | K66: =K62 -> 8822.7196 | ... AC66: =AC62 -> 10090.153
A67: + Total D&A add-back ($mm) | D67: =D56 -> 54.035372 | E67: =E56 -> 98.234043 | F67: =F56 -> 144.78208 | G67: =G56 -> 185.20412 | H67: =H56 -> 219.78148 | I67: =I56 -> 248.5973 | J67: =J56 -> 271.67964 | K67: =K56 -> 288.95904 | ... AC67: =AC56 -> 305.82401
A68: − Module CapEx ($mm) | D68: ='Launch Capacity'!D62*'Launch Capacity'!D52+D39*'Launch Capacity'!D136 -> 240 | E68: ='Launch Capacity'!E62*'Launch Capacity'!E52+E39*'Launch Capacity'!E136 -> 236.45318 | F68: ='Launch Capacity'!F62*'Launch Capacity'!F52+F39*'Launch Capacity'!F136 -> 238.63025 | G68: ='Launch Capacity'!G62*'Launch Capacity'!G52+G39*'Launch Capacity'!G136 -> 208.55973 | H68: ='Launch Capacity'!H62*'Launch Capacity'!H52+H39*'Launch Capacity'!H136 -> 178.41674 | I68: ='Launch Capacity'!I62*'Launch Capacity'!I52+I39*'Launch Capacity'!I136 -> 148.88105 | J68: ='Launch Capacity'!J62*'Launch Capacity'!J52+J39*'Launch Capacity'!J136 -> 119.11335 | K68: ='Launch Capacity'!K62*'Launch Capacity'!K52+K39*'Launch Capacity'!K136 -> 89.619636 | ... AC68: ='Launch Capacity'!AC62*'Launch Capacity'!AC52+AC39*'Launch Capacity'!AC136 -> 0.12138466
A69: Module FCF ($mm) | D69: =D66+D67-D68 -> 5884.7219 | E69: =E66+E67-E68 -> 6245.1233 | F69: =F66+F67-F68 -> 6639.1535 | G69: =G66+G67-G68 -> 7075.2323 | H69: =H66+H67-H68 -> 7530.2767 | I69: =I66+I67-I68 -> 8009.859 | J69: =J66+J67-J68 -> 8504.3734 | K69: =K66+K67-K68 -> 9022.059 | ... AC69: =AC66+AC67-AC68 -> 10395.856
A71: 8. IRR engine — DEPRECATED Sprint 5.5 (see row 79+ for MFW-IRR)
A72: Cumulative CapEx ($mm) | D72: =SUM($D$68:D68) -> 240 | E72: =SUM($D$68:E68) -> 476.45318 | F72: =SUM($D$68:F68) -> 715.08343 | G72: =SUM($D$68:G68) -> 923.64316 | H72: =SUM($D$68:H68) -> 1102.0599 | I72: =SUM($D$68:I68) -> 1250.9409 | J72: =SUM($D$68:J68) -> 1370.0543 | K72: =SUM($D$68:K68) -> 1459.6739 | ... AC72: =SUM($D$68:AC68) -> 1560.6606
A73: Cumulative FCF ($mm) | D73: =SUM($D$69:D69) -> 5884.7219 | E73: =SUM($D$69:E69) -> 12129.845 | F73: =SUM($D$69:F69) -> 18768.999 | G73: =SUM($D$69:G69) -> 25844.231 | H73: =SUM($D$69:H69) -> 33374.508 | I73: =SUM($D$69:I69) -> 41384.367 | J73: =SUM($D$69:J69) -> 49888.74 | K73: =SUM($D$69:K69) -> 58910.799 | ... AC73: =SUM($D$69:AC69) -> 288247.03
A74: Spot IRR (FCF/CapEx ratio proxy) | D74: =IFERROR(D69/D68,0) -> 24.519675 | E74: =IFERROR(E69/E68,0) -> 26.41167 | F74: =IFERROR(F69/F68,0) -> 27.821927 | G74: =IFERROR(G69/G68,0) -> 33.92425 | H74: =IFERROR(H69/H68,0) -> 42.206111 | I74: =IFERROR(I69/I68,0) -> 53.800395 | J74: =IFERROR(J69/J68,0) -> 71.397313 | K74: =IFERROR(K69/K68,0) -> 100.67056 | ... AC74: =IFERROR(AC69/AC68,0) -> 85643.899
A75: Forward IRR (Y+2 FCF / current CapEx) | D75: {=IFERROR(IFERROR(INDEX($D69:$AC69,COLUMN(D69)-COLUMN($D69)+1+2)/D68,0),0)} -> 27.663139 | E75: {=IFERROR(IFERROR(INDEX($D69:$AC69,COLUMN(E69)-COLUMN($D69)+1+2)/E68,0),0)} -> 29.922339 | F75: {=IFERROR(IFERROR(INDEX($D69:$AC69,COLUMN(F69)-COLUMN($D69)+1+2)/F68,0),0)} -> 31.556253 | G75: {=IFERROR(IFERROR(INDEX($D69:$AC69,COLUMN(G69)-COLUMN($D69)+1+2)/G68,0),0)} -> 38.405589 | H75: {=IFERROR(IFERROR(INDEX($D69:$AC69,COLUMN(H69)-COLUMN($D69)+1+2)/H68,0),0)} -> 47.665782 | I75: {=IFERROR(IFERROR(INDEX($D69:$AC69,COLUMN(I69)-COLUMN($D69)+1+2)/I68,0),0)} -> 60.599111 | J75: {=IFERROR(IFERROR(INDEX($D69:$AC69,COLUMN(J69)-COLUMN($D69)+1+2)/J68,0),0)} -> 80.272618 | K75: {=IFERROR(IFERROR(INDEX($D69:$AC69,COLUMN(K69)-COLUMN($D69)+1+2)/K68,0),0)} -> 112.9501 | ... AC75: {=IFERROR(IFERROR(INDEX($D69:$AC69,COLUMN(AC69)-COLUMN($D69)+1+2)/AC68,0),0)} -> 0
A76: Blended IRR (50/50) | D76: =0.5*D74+0.5*D75 -> 26.091407 | E76: =0.5*E74+0.5*E75 -> 28.167004 | F76: =0.5*F74+0.5*F75 -> 29.68909 | G76: =0.5*G74+0.5*G75 -> 36.164919 | H76: =0.5*H74+0.5*H75 -> 44.935946 | I76: =0.5*I74+0.5*I75 -> 57.199753 | J76: =0.5*J74+0.5*J75 -> 75.834966 | K76: =0.5*K74+0.5*K75 -> 106.81033 | ... AC76: =0.5*AC74+0.5*AC75 -> 42821.95
A77: [Corp overhead moved to Group P&L — Refine Spec 01]
A79: Marginal CapEx economic life (yrs, endogenous) | D79: =MAX(Assumptions!$B$305,MIN(Assumptions!$B$306,ROUND(Assumptions!$B$176/Assumptions!$B$178,0))) -> 4 | E79: =MAX(Assumptions!$B$305,MIN(Assumptions!$B$306,ROUND(Assumptions!$B$176/Assumptions!$B$178,0))) -> 4 | F79: =MAX(Assumptions!$B$305,MIN(Assumptions!$B$306,ROUND(Assumptions!$B$176/Assumptions!$B$178,0))) -> 4 | G79: =MAX(Assumptions!$B$305,MIN(Assumptions!$B$306,ROUND(Assumptions!$B$176/Assumptions!$B$178,0))) -> 4 | H79: =MAX(Assumptions!$B$305,MIN(Assumptions!$B$306,ROUND(Assumptions!$B$176/Assumptions!$B$178,0))) -> 4 | I79: =MAX(Assumptions!$B$305,MIN(Assumptions!$B$306,ROUND(Assumptions!$B$176/Assumptions!$B$178,0))) -> 4 | J79: =MAX(Assumptions!$B$305,MIN(Assumptions!$B$306,ROUND(Assumptions!$B$176/Assumptions!$B$178,0))) -> 4 | K79: =MAX(Assumptions!$B$305,MIN(Assumptions!$B$306,ROUND(Assumptions!$B$176/Assumptions!$B$178,0))) -> 4 | ... AC79: =MAX(Assumptions!$B$305,MIN(Assumptions!$B$306,ROUND(Assumptions!$B$176/Assumptions!$B$178,0))) -> 4
A80: CF t=0 ($mm) | D80: =-D96 -> -9169.3134 | E80: =-E96 -> -3022.4242 | F80: =-F96 -> -15715.083 | G80: =-G96 -> -15923.643 | H80: =-H96 -> -16102.06 | I80: =-I96 -> -16250.941 | J80: =-J96 -> -16370.054 | K80: =-K96 -> -16459.674 | ... AC80: =-AC96 -> -16560.661
A81: CF t=1 ($mm) | D81: {=IFERROR(INDEX($D$69:$AC$69,COLUMN(D80)-COLUMN($D$80)+1+1),0)} -> 6245.1233 | E81: {=IFERROR(INDEX($D$69:$AC$69,COLUMN(E80)-COLUMN($D$80)+1+1),0)} -> 6639.1535 | F81: {=IFERROR(INDEX($D$69:$AC$69,COLUMN(F80)-COLUMN($D$80)+1+1),0)} -> 7075.2323 | G81: {=IFERROR(INDEX($D$69:$AC$69,COLUMN(G80)-COLUMN($D$80)+1+1),0)} -> 7530.2767 | H81: {=IFERROR(INDEX($D$69:$AC$69,COLUMN(H80)-COLUMN($D$80)+1+1),0)} -> 8009.859 | I81: {=IFERROR(INDEX($D$69:$AC$69,COLUMN(I80)-COLUMN($D$80)+1+1),0)} -> 8504.3734 | J81: {=IFERROR(INDEX($D$69:$AC$69,COLUMN(J80)-COLUMN($D$80)+1+1),0)} -> 9022.059 | K81: {=IFERROR(INDEX($D$69:$AC$69,COLUMN(K80)-COLUMN($D$80)+1+1),0)} -> 9561.5407 | ... AC81: {=IFERROR(INDEX($D$69:$AC$69,COLUMN(AC80)-COLUMN($D$80)+1+1),0)} -> 0
A82: CF t=2 ($mm) | D82: {=IFERROR(INDEX($D$69:$AC$69,COLUMN(D80)-COLUMN($D$80)+1+2),0)} -> 6639.1535 | E82: {=IFERROR(INDEX($D$69:$AC$69,COLUMN(E80)-COLUMN($D$80)+1+2),0)} -> 7075.2323 | F82: {=IFERROR(INDEX($D$69:$AC$69,COLUMN(F80)-COLUMN($D$80)+1+2),0)} -> 7530.2767 | G82: {=IFERROR(INDEX($D$69:$AC$69,COLUMN(G80)-COLUMN($D$80)+1+2),0)} -> 8009.859 | H82: {=IFERROR(INDEX($D$69:$AC$69,COLUMN(H80)-COLUMN($D$80)+1+2),0)} -> 8504.3734 | I82: {=IFERROR(INDEX($D$69:$AC$69,COLUMN(I80)-COLUMN($D$80)+1+2),0)} -> 9022.059 | J82: {=IFERROR(INDEX($D$69:$AC$69,COLUMN(J80)-COLUMN($D$80)+1+2),0)} -> 9561.5407 | K82: {=IFERROR(INDEX($D$69:$AC$69,COLUMN(K80)-COLUMN($D$80)+1+2),0)} -> 10122.547 | ... AC82: {=IFERROR(INDEX($D$69:$AC$69,COLUMN(AC80)-COLUMN($D$80)+1+2),0)} -> 0
A83: CF t=3 ($mm) | D83: {=IFERROR(INDEX($D$69:$AC$69,COLUMN(D80)-COLUMN($D$80)+1+3),0)} -> 7075.2323 | E83: {=IFERROR(INDEX($D$69:$AC$69,COLUMN(E80)-COLUMN($D$80)+1+3),0)} -> 7530.2767 | F83: {=IFERROR(INDEX($D$69:$AC$69,COLUMN(F80)-COLUMN($D$80)+1+3),0)} -> 8009.859 | G83: {=IFERROR(INDEX($D$69:$AC$69,COLUMN(G80)-COLUMN($D$80)+1+3),0)} -> 8504.3734 | H83: {=IFERROR(INDEX($D$69:$AC$69,COLUMN(H80)-COLUMN($D$80)+1+3),0)} -> 9022.059 | I83: {=IFERROR(INDEX($D$69:$AC$69,COLUMN(I80)-COLUMN($D$80)+1+3),0)} -> 9561.5407 | J83: {=IFERROR(INDEX($D$69:$AC$69,COLUMN(J80)-COLUMN($D$80)+1+3),0)} -> 10122.547 | K83: {=IFERROR(INDEX($D$69:$AC$69,COLUMN(K80)-COLUMN($D$80)+1+3),0)} -> 10707.604 | ... AC83: {=IFERROR(INDEX($D$69:$AC$69,COLUMN(AC80)-COLUMN($D$80)+1+3),0)} -> 0
A84: CF t=4 ($mm) | D84: {=IFERROR(INDEX($D$69:$AC$69,COLUMN(D80)-COLUMN($D$80)+1+4),0)} -> 7530.2767 | E84: {=IFERROR(INDEX($D$69:$AC$69,COLUMN(E80)-COLUMN($D$80)+1+4),0)} -> 8009.859 | F84: {=IFERROR(INDEX($D$69:$AC$69,COLUMN(F80)-COLUMN($D$80)+1+4),0)} -> 8504.3734 | G84: {=IFERROR(INDEX($D$69:$AC$69,COLUMN(G80)-COLUMN($D$80)+1+4),0)} -> 9022.059 | H84: {=IFERROR(INDEX($D$69:$AC$69,COLUMN(H80)-COLUMN($D$80)+1+4),0)} -> 9561.5407 | I84: {=IFERROR(INDEX($D$69:$AC$69,COLUMN(I80)-COLUMN($D$80)+1+4),0)} -> 10122.547 | J84: {=IFERROR(INDEX($D$69:$AC$69,COLUMN(J80)-COLUMN($D$80)+1+4),0)} -> 10707.604 | K84: {=IFERROR(INDEX($D$69:$AC$69,COLUMN(K80)-COLUMN($D$80)+1+4),0)} -> 11287.032 | ... AC84: {=IFERROR(INDEX($D$69:$AC$69,COLUMN(AC80)-COLUMN($D$80)+1+4),0)} -> 0
A85: CF t=5 ($mm) | D85: {=IFERROR(INDEX($D$69:$AC$69,COLUMN(D80)-COLUMN($D$80)+1+5),0)} -> 8009.859 | E85: {=IFERROR(INDEX($D$69:$AC$69,COLUMN(E80)-COLUMN($D$80)+1+5),0)} -> 8504.3734 | F85: {=IFERROR(INDEX($D$69:$AC$69,COLUMN(F80)-COLUMN($D$80)+1+5),0)} -> 9022.059 | G85: {=IFERROR(INDEX($D$69:$AC$69,COLUMN(G80)-COLUMN($D$80)+1+5),0)} -> 9561.5407 | H85: {=IFERROR(INDEX($D$69:$AC$69,COLUMN(H80)-COLUMN($D$80)+1+5),0)} -> 10122.547 | I85: {=IFERROR(INDEX($D$69:$AC$69,COLUMN(I80)-COLUMN($D$80)+1+5),0)} -> 10707.604 | J85: {=IFERROR(INDEX($D$69:$AC$69,COLUMN(J80)-COLUMN($D$80)+1+5),0)} -> 11287.032 | K85: {=IFERROR(INDEX($D$69:$AC$69,COLUMN(K80)-COLUMN($D$80)+1+5),0)} -> 11890.48 | ... AC85: {=IFERROR(INDEX($D$69:$AC$69,COLUMN(AC80)-COLUMN($D$80)+1+5),0)} -> 0
A86: CF t=6 ($mm) | D86: {=IFERROR(INDEX($D$69:$AC$69,COLUMN(D80)-COLUMN($D$80)+1+6),0)} -> 8504.3734 | E86: {=IFERROR(INDEX($D$69:$AC$69,COLUMN(E80)-COLUMN($D$80)+1+6),0)} -> 9022.059 | F86: {=IFERROR(INDEX($D$69:$AC$69,COLUMN(F80)-COLUMN($D$80)+1+6),0)} -> 9561.5407 | G86: {=IFERROR(INDEX($D$69:$AC$69,COLUMN(G80)-COLUMN($D$80)+1+6),0)} -> 10122.547 | H86: {=IFERROR(INDEX($D$69:$AC$69,COLUMN(H80)-COLUMN($D$80)+1+6),0)} -> 10707.604 | I86: {=IFERROR(INDEX($D$69:$AC$69,COLUMN(I80)-COLUMN($D$80)+1+6),0)} -> 11287.032 | J86: {=IFERROR(INDEX($D$69:$AC$69,COLUMN(J80)-COLUMN($D$80)+1+6),0)} -> 11890.48 | K86: {=IFERROR(INDEX($D$69:$AC$69,COLUMN(K80)-COLUMN($D$80)+1+6),0)} -> 12517.191 | ... AC86: {=IFERROR(INDEX($D$69:$AC$69,COLUMN(AC80)-COLUMN($D$80)+1+6),0)} -> 0
A87: CF t=7 ($mm) | D87: {=IFERROR(INDEX($D$69:$AC$69,COLUMN(D80)-COLUMN($D$80)+1+7),0)} -> 9022.059 | E87: {=IFERROR(INDEX($D$69:$AC$69,COLUMN(E80)-COLUMN($D$80)+1+7),0)} -> 9561.5407 | F87: {=IFERROR(INDEX($D$69:$AC$69,COLUMN(F80)-COLUMN($D$80)+1+7),0)} -> 10122.547 | G87: {=IFERROR(INDEX($D$69:$AC$69,COLUMN(G80)-COLUMN($D$80)+1+7),0)} -> 10707.604 | H87: {=IFERROR(INDEX($D$69:$AC$69,COLUMN(H80)-COLUMN($D$80)+1+7),0)} -> 11287.032 | I87: {=IFERROR(INDEX($D$69:$AC$69,COLUMN(I80)-COLUMN($D$80)+1+7),0)} -> 11890.48 | J87: {=IFERROR(INDEX($D$69:$AC$69,COLUMN(J80)-COLUMN($D$80)+1+7),0)} -> 12517.191 | K87: {=IFERROR(INDEX($D$69:$AC$69,COLUMN(K80)-COLUMN($D$80)+1+7),0)} -> 13166.503 | ... AC87: {=IFERROR(INDEX($D$69:$AC$69,COLUMN(AC80)-COLUMN($D$80)+1+7),0)} -> 0
A88: CF t=8 ($mm) | D88: {=IFERROR(INDEX($D$69:$AC$69,COLUMN(D80)-COLUMN($D$80)+1+8),0)} -> 9561.5407 | E88: {=IFERROR(INDEX($D$69:$AC$69,COLUMN(E80)-COLUMN($D$80)+1+8),0)} -> 10122.547 | F88: {=IFERROR(INDEX($D$69:$AC$69,COLUMN(F80)-COLUMN($D$80)+1+8),0)} -> 10707.604 | G88: {=IFERROR(INDEX($D$69:$AC$69,COLUMN(G80)-COLUMN($D$80)+1+8),0)} -> 11287.032 | H88: {=IFERROR(INDEX($D$69:$AC$69,COLUMN(H80)-COLUMN($D$80)+1+8),0)} -> 11890.48 | I88: {=IFERROR(INDEX($D$69:$AC$69,COLUMN(I80)-COLUMN($D$80)+1+8),0)} -> 12517.191 | J88: {=IFERROR(INDEX($D$69:$AC$69,COLUMN(J80)-COLUMN($D$80)+1+8),0)} -> 13166.503 | K88: {=IFERROR(INDEX($D$69:$AC$69,COLUMN(K80)-COLUMN($D$80)+1+8),0)} -> 13836.999 | ... AC88: {=IFERROR(INDEX($D$69:$AC$69,COLUMN(AC80)-COLUMN($D$80)+1+8),0)} -> 0
A89: CF t=9 ($mm) | D89: {=IFERROR(INDEX($D$69:$AC$69,COLUMN(D80)-COLUMN($D$80)+1+9),0)} -> 10122.547 | E89: {=IFERROR(INDEX($D$69:$AC$69,COLUMN(E80)-COLUMN($D$80)+1+9),0)} -> 10707.604 | F89: {=IFERROR(INDEX($D$69:$AC$69,COLUMN(F80)-COLUMN($D$80)+1+9),0)} -> 11287.032 | G89: {=IFERROR(INDEX($D$69:$AC$69,COLUMN(G80)-COLUMN($D$80)+1+9),0)} -> 11890.48 | H89: {=IFERROR(INDEX($D$69:$AC$69,COLUMN(H80)-COLUMN($D$80)+1+9),0)} -> 12517.191 | I89: {=IFERROR(INDEX($D$69:$AC$69,COLUMN(I80)-COLUMN($D$80)+1+9),0)} -> 13166.503 | J89: {=IFERROR(INDEX($D$69:$AC$69,COLUMN(J80)-COLUMN($D$80)+1+9),0)} -> 13836.999 | K89: {=IFERROR(INDEX($D$69:$AC$69,COLUMN(K80)-COLUMN($D$80)+1+9),0)} -> 14469.374 | ... AC89: {=IFERROR(INDEX($D$69:$AC$69,COLUMN(AC80)-COLUMN($D$80)+1+9),0)} -> 0
A90: CF t=10 ($mm) | D90: {=IFERROR(INDEX($D$69:$AC$69,COLUMN(D80)-COLUMN($D$80)+1+10),0)} -> 10707.604 | E90: {=IFERROR(INDEX($D$69:$AC$69,COLUMN(E80)-COLUMN($D$80)+1+10),0)} -> 11287.032 | F90: {=IFERROR(INDEX($D$69:$AC$69,COLUMN(F80)-COLUMN($D$80)+1+10),0)} -> 11890.48 | G90: {=IFERROR(INDEX($D$69:$AC$69,COLUMN(G80)-COLUMN($D$80)+1+10),0)} -> 12517.191 | H90: {=IFERROR(INDEX($D$69:$AC$69,COLUMN(H80)-COLUMN($D$80)+1+10),0)} -> 13166.503 | I90: {=IFERROR(INDEX($D$69:$AC$69,COLUMN(I80)-COLUMN($D$80)+1+10),0)} -> 13836.999 | J90: {=IFERROR(INDEX($D$69:$AC$69,COLUMN(J80)-COLUMN($D$80)+1+10),0)} -> 14469.374 | K90: {=IFERROR(INDEX($D$69:$AC$69,COLUMN(K80)-COLUMN($D$80)+1+10),0)} -> 15101.219 | ... AC90: {=IFERROR(INDEX($D$69:$AC$69,COLUMN(AC80)-COLUMN($D$80)+1+10),0)} -> 0
A91: Spot IRR (MFW-IRR) | D91: =IFERROR(IRR(INDEX(D$80:D$90,1):INDEX(D$80:D$90,D$79+1)),IFERROR(C91,0)) -> 0.61761102 | E91: =IFERROR(IRR(INDEX(E$80:E$90,1):INDEX(E$80:E$90,E$79+1)),IFERROR(D91,0)) -> 2.2361108 | F91: =IFERROR(IRR(INDEX(F$80:F$90,1):INDEX(F$80:F$90,F$79+1)),IFERROR(E91,0)) -> 0.32939963 | G91: =IFERROR(IRR(INDEX(G$80:G$90,1):INDEX(G$80:G$90,G$79+1)),IFERROR(F91,0)) -> 0.35852195 | H91: =IFERROR(IRR(INDEX(H$80:H$90,1):INDEX(H$80:H$90,H$79+1)),IFERROR(G91,0)) -> 0.38931519 | I91: =IFERROR(IRR(INDEX(I$80:I$90,1):INDEX(I$80:I$90,I$79+1)),IFERROR(H91,0)) -> 0.42168708 | J91: =IFERROR(IRR(INDEX(J$80:J$90,1):INDEX(J$80:J$90,J$79+1)),IFERROR(I91,0)) -> 0.45594836 | K91: =IFERROR(IRR(INDEX(K$80:K$90,1):INDEX(K$80:K$90,K$79+1)),IFERROR(J91,0)) -> 0.4919053 | ... AC91: =IFERROR(IRR(INDEX(AC$80:AC$90,1):INDEX(AC$80:AC$90,AC$79+1)),IFERROR(AB91,0)) -> -0.37225137
A92: Forward IRR Y+2 (MFW-IRR) | D92: =IFERROR(IRR(INDEX(F$80:F$90,1):INDEX(F$80:F$90,D$79+1)),IFERROR(C92,0)) -> 0.32939963 | E92: =IFERROR(IRR(INDEX(G$80:G$90,1):INDEX(G$80:G$90,E$79+1)),IFERROR(D92,0)) -> 0.35852195 | F92: =IFERROR(IRR(INDEX(H$80:H$90,1):INDEX(H$80:H$90,F$79+1)),IFERROR(E92,0)) -> 0.38931519 | G92: =IFERROR(IRR(INDEX(I$80:I$90,1):INDEX(I$80:I$90,G$79+1)),IFERROR(F92,0)) -> 0.42168708 | H92: =IFERROR(IRR(INDEX(J$80:J$90,1):INDEX(J$80:J$90,H$79+1)),IFERROR(G92,0)) -> 0.45594836 | I92: =IFERROR(IRR(INDEX(K$80:K$90,1):INDEX(K$80:K$90,I$79+1)),IFERROR(H92,0)) -> 0.4919053 | J92: =IFERROR(IRR(INDEX(L$80:L$90,1):INDEX(L$80:L$90,J$79+1)),IFERROR(I92,0)) -> 0.52961703 | K92: =IFERROR(IRR(INDEX(M$80:M$90,1):INDEX(M$80:M$90,K$79+1)),IFERROR(J92,0)) -> 0.56911333 | ... AC92: =IFERROR(IRR(INDEX(AE$80:AE$90,1):INDEX(AE$80:AE$90,AC$79+1)),IFERROR(AB92,0)) -> -0.37225137
A93: Memo: Fleet-level Blended IRR (MFW-IRR, historical) | D93: =(1-Assumptions!$B$307)*D91+Assumptions!$B$307*D92 -> 0.41586305 | E93: =(1-Assumptions!$B$307)*E91+Assumptions!$B$307*E92 -> 0.9217986 | F93: =(1-Assumptions!$B$307)*F91+Assumptions!$B$307*F92 -> 0.37134052 | G93: =(1-Assumptions!$B$307)*G91+Assumptions!$B$307*G92 -> 0.40273754 | H93: =(1-Assumptions!$B$307)*H91+Assumptions!$B$307*H92 -> 0.4359584 | I93: =(1-Assumptions!$B$307)*I91+Assumptions!$B$307*I92 -> 0.47083984 | J93: =(1-Assumptions!$B$307)*J91+Assumptions!$B$307*J92 -> 0.50751643 | K93: =(1-Assumptions!$B$307)*K91+Assumptions!$B$307*K92 -> 0.54595092 | ... AC93: =(1-Assumptions!$B$307)*AC91+Assumptions!$B$307*AC92 -> -0.37225137
A94: Cumulative CapEx ($mm) — incl historical base | D94: =Assumptions!$B$317+SUM($D$68:D68) -> 15240 | E94: =Assumptions!$B$317+SUM($D$68:E68) -> 15476.453 | F94: =Assumptions!$B$317+SUM($D$68:F68) -> 15715.083 | G94: =Assumptions!$B$317+SUM($D$68:G68) -> 15923.643 | H94: =Assumptions!$B$317+SUM($D$68:H68) -> 16102.06 | I94: =Assumptions!$B$317+SUM($D$68:I68) -> 16250.941 | J94: =Assumptions!$B$317+SUM($D$68:J68) -> 16370.054 | K94: =Assumptions!$B$317+SUM($D$68:K68) -> 16459.674 | ... AC94: =Assumptions!$B$317+SUM($D$68:AC68) -> 16560.661
A95: Cumulative D&A ($mm) | D95: =SUM($D$62:D62) -> 6070.6866 | E95: =SUM($D$62:E62) -> 12454.029 | F95: =SUM($D$62:F62) -> 19187.031 | G95: =SUM($D$62:G62) -> 26285.619 | H95: =SUM($D$62:H62) -> 33774.53 | I95: =SUM($D$62:I62) -> 41684.673 | J95: =SUM($D$62:J62) -> 50036.48 | K95: =SUM($D$62:K62) -> 58859.2 | ... AC95: =SUM($D$62:AC62) -> 282794.64
A96: Net Invested Capital ($mm) | D96: =IF(D94-D95>0, D94-D95, D94) -> 9169.3134 | E96: =IF(E94-E95>0, E94-E95, E94) -> 3022.4242 | F96: =IF(F94-F95>0, F94-F95, F94) -> 15715.083 | G96: =IF(G94-G95>0, G94-G95, G94) -> 15923.643 | H96: =IF(H94-H95>0, H94-H95, H94) -> 16102.06 | I96: =IF(I94-I95>0, I94-I95, I94) -> 16250.941 | J96: =IF(J94-J95>0, J94-J95, J94) -> 16370.054 | K96: =IF(K94-K95>0, K94-K95, K94) -> 16459.674 | ... AC96: =IF(AC94-AC95>0, AC94-AC95, AC94) -> 16560.661
A97: ─── Inter-module launch flow (at-cost transfer pricing) ───
A98: Starlink internal Starship launches | D98: =IFERROR(Allocator!D71/Assumptions!$B$202,0) -> 0.85973966 | E98: =IFERROR(Allocator!E71/Assumptions!$B$202,0) -> 0.8385773 | F98: =IFERROR(Allocator!F71/Assumptions!$B$202,0) -> 0.79803568 | G98: =IFERROR(Allocator!G71/Assumptions!$B$202,0) -> 0.74120797 | H98: =IFERROR(Allocator!H71/Assumptions!$B$202,0) -> 0.64712923 | I98: =IFERROR(Allocator!I71/Assumptions!$B$202,0) -> 0.48535769 | J98: =IFERROR(Allocator!J71/Assumptions!$B$202,0) -> 0.47260876 | K98: =IFERROR(Allocator!K71/Assumptions!$B$202,0) -> 0.43207381 | ... AC98: =IFERROR(Allocator!AC71/Assumptions!$B$202,0) -> 1.4787726
A99: ODC internal Starship launches | D99: =IFERROR(Allocator!D78/Assumptions!$B$202,0) -> 0 | E99: =IFERROR(Allocator!E78/Assumptions!$B$202,0) -> 0 | F99: =IFERROR(Allocator!F78/Assumptions!$B$202,0) -> 0 | G99: =IFERROR(Allocator!G78/Assumptions!$B$202,0) -> 0 | H99: =IFERROR(Allocator!H78/Assumptions!$B$202,0) -> 0 | I99: =IFERROR(Allocator!I78/Assumptions!$B$202,0) -> 0 | J99: =IFERROR(Allocator!J78/Assumptions!$B$202,0) -> 0 | K99: =IFERROR(Allocator!K78/Assumptions!$B$202,0) -> 0 | ... AC99: =IFERROR(Allocator!AC78/Assumptions!$B$202,0) -> 0
A100: Lunar/Mars internal Starship launches | D100: =IFERROR(Allocator!D60/Assumptions!$B$202,0) -> 0 | E100: =IFERROR(Allocator!E60/Assumptions!$B$202,0) -> 0 | F100: =IFERROR(Allocator!F60/Assumptions!$B$202,0) -> 0 | G100: =IFERROR(Allocator!G60/Assumptions!$B$202,0) -> 0 | H100: =IFERROR(Allocator!H60/Assumptions!$B$202,0) -> 0 | I100: =IFERROR(Allocator!I60/Assumptions!$B$202,0) -> 0 | J100: =IFERROR(Allocator!J60/Assumptions!$B$202,0) -> 0 | K100: =IFERROR(Allocator!K60/Assumptions!$B$202,0) -> 0 | ... AC100: =IFERROR(Allocator!AC60/Assumptions!$B$202,0) -> 0
A101: Total internal launches | D101: =D98+D99+D100 -> 0.85973966 | E101: =E98+E99+E100 -> 0.8385773 | F101: =F98+F99+F100 -> 0.79803568 | G101: =G98+G99+G100 -> 0.74120797 | H101: =H98+H99+H100 -> 0.64712923 | I101: =I98+I99+I100 -> 0.48535769 | J101: =J98+J99+J100 -> 0.47260876 | K101: =K98+K99+K100 -> 0.43207381 | ... AC101: =AC98+AC99+AC100 -> 1.4787726
A102: Total launches (internal + external Starship + F9) | D102: =D38+D39+D101 -> 138.17317 | E102: =E38+E39+E101 -> 152.5173 | F102: =F38+F39+F101 -> 168.72246 | G102: =G38+G39+G101 -> 186.49505 | H102: =H38+H39+H101 -> 206.11879 | I102: =I38+I39+I101 -> 227.89251 | J102: =J38+J39+J101 -> 252.12528 | K102: =K38+K39+K101 -> 279.02305 | ... AC102: =AC38+AC39+AC101 -> 913.64893
A103: Variable cost per Starship launch ($mm) | D103: =D18 -> 58.5 | E103: =E18 -> 39.039 | F103: =F18 -> 30.63888 | G103: =G18 -> 25.502473 | H103: =H18 -> 18.460419 | I103: =I18 -> 12.0764 | J103: =J18 -> 8.9322055 | K103: =K18 -> 6.0234195 | ... AC103: =AC18 -> 2.3279667
A104: Total Starship fleet D&A / total Starship launches ($mm/launch) | D104: =IFERROR(D55/(D39+D101),0) -> 7.02 | E104: =IFERROR(E55/(E39+E101),0) -> 3.51 | F104: =IFERROR(F55/(F39+F101),0) -> 2.212176 | G104: =IFERROR(G55/(G39+G101),0) -> 1.5670947 | H104: =IFERROR(H55/(H39+H101),0) -> 1.1906238 | I104: =IFERROR(I55/(I39+I101),0) -> 0.94576007 | J104: =IFERROR(J55/(J39+J101),0) -> 0.77556109 | K104: =IFERROR(K55/(K39+K101),0) -> 0.6524439 | ... AC104: =IFERROR(AC55/(AC39+AC101),0) -> 0.14267334
A105: Fully-loaded $/Starship launch (var + D&A share) | D105: =D103+D104 -> 65.52 | E105: =E103+E104 -> 42.549 | F105: =F103+F104 -> 32.851056 | G105: =G103+G104 -> 27.069568 | H105: =H103+H104 -> 19.651043 | I105: =I103+I104 -> 13.02216 | J105: =J103+J104 -> 9.7077666 | K105: =K103+K104 -> 6.6758634 | ... AC105: =AC103+AC104 -> 2.47064
