Workbook

Sheet Assumptions
D1: 2025 | E1: 2026 | F1: 2027 | G1: 2028 | H1: 2029 | I1: 2030 | J1: 2031 | K1: 2032 | L1: 2033 | M1: 2034 | N1: 2035 | O1: 2036 | P1: 2037 | Q1: 2038 | R1: 2039 | S1: 2040 | T1: 2041 | U1: 2042 | V1: 2043 | W1: 2044 | X1: 2045 | Y1: 2046 | Z1: 2047 | AA1: 2048 | AB1: 2049 | AC1: 2050
A2: GLOBAL | D2: 0 | E2: 1 | F2: 2 | G2: 3 | H2: 4 | I2: 5 | J2: 6 | K2: 7 | L2: 8 | M2: 9 | N2: 10 | O2: 11 | P2: 12 | Q2: 13 | R2: 14 | S2: 15 | T2: 16 | U2: 17 | V2: 18 | W2: 19 | X2: 20 | Y2: 21 | Z2: 22 | AA2: 23 | AB2: 24 | AC2: 25
A3: Tax rate (corporate, US federal + state blended) | B3: 0.21 | C3: Standard US corporate rate; S-1 silent on effective rate split. | AG3: 0.18 | AH3: 0.27 | AI3: triangle | AJ3: NO S-1 DATA: keep 21% federal stat
A4: Demand curve escalator: start rate (annual) | B4: 0.035 | C4: Early willingness-to-pay growth above inflation. Targets 2050 total Starlink revenue of roughly $640–660bn (before direct-to-cell). Monte Carlo range 0.045–0.060. | D4: 2025 | E4: 2026 | F4: 2027 | G4: 2028 | H4: 2029 | I4: 2030 | J4: 2031 | K4: 2032 | L4: 2033 | M4: 2034 | N4: 2035 | O4: 2036 | P4: 2037 | Q4: 2038 | R4: 2039 | S4: 2040 | AG4: 0.025 | AH4: 0.05 | AI4: triangle | AJ4: Escalator start rate; early willingness-to-pay growth above inflation
A5: Demand curve escalator: terminal rate (annual) | B5: 0.025 | C5: Mature-market escalator ≈ inflation. The tapered curve converges here after the taper ends. Monte Carlo range 0.035–0.045. | D5: 0 | E5: 1 | F5: 2 | G5: 3 | H5: 4 | I5: 5 | J5: 6 | K5: 7 | L5: 8 | M5: 9 | N5: 10 | O5: 11 | P5: 12 | Q5: 13 | R5: 14 | S5: 15 | AG5: 0.02 | AH5: 0.03 | AI5: triangle | AJ5: Escalator terminal rate ≈ inflation
A6: ALLOCATOR
A7: ▸ Cash pool boundary inputs
A8: Starting cash position EoY 2024 ($mm) | B8: 11385 | C8: S-1 p.21 BS audited cash & equivalents 12-31-24. Build Plan had $5,000, corrected by S-1. | AG8: 8000 | AH8: 25000 | AI8: triangle | AJ8: S-1 OVERRIDE p.21: MC top widened to capture EoY 2025 = $24,747M
A9: IPO injection amount ($mm) | B9: 45000 | C9: IPO proceeds target not disclosed; placeholder. | AG9: 30000 | AH9: 60000 | AI9: lognormal | AJ9: NO S-1 DATA: refresh on S-1/A pricing range
A10: IPO injection year | B10: 2027 | C10: S-1 filed May 2026 implies pricing 2H 2026 / early 2027. Holding 2027 pending S-1/A. | AG10: 2026 | AH10: 2028 | AI10: discrete | AJ10: S-1 PARTIAL: filed 2026-05-20
A11: ▸ Lunar/Mars strategic carve-out (Monte Carlo variable)
A12: Lunar/Mars carve-out % of prior-year Group FCF | B12: 0.15 | C12: Mars spend is not broken out separately (Starship R&D is co-mingled), so it is held here. | AG12: 0.03 | AH12: 0.35 | AI12: triangle | AJ12: No S-1 data: dedicated spend unknown
A13: Lunar/Mars carve-out floor ($mm/yr) | B13: 1000 | C13: Floor below which carve-out doesn't drop even if prior FCF is small. | AG13: 500 | AH13: 2500 | AI13: triangle | AJ13: NO S-1 DATA: MC-variable
A14: Lunar/Mars carve-out uses prior-year FCF (0/1) | B14: 1 | C14: 1 = prior year (breaks circularity per Principle 22). Structural input. | AI14: fixed | AJ14: Structural lock
A15: Lunar/Mars carve-out pre-first-mission-year R&D-only override ($mm/yr) | B15: 700 | C15: Q4'25 R425 anchored. Pre-2028 no missions; carve-out = R&D-only $700M. | AI15: fixed | AJ15: Q4'25 ANCHOR
A16: ▸ IRR-weighted allocation parameters
A17: Allocation sharpness β (top-level 3-module blend) | B17: 3 | C17: At β = 10, a 10pp IRR gap implies roughly a 73/27 share split — moderate concentration. | AG17: 3 | AH17: 20 | AI17: triangle | AJ17: NO S-1 DATA: MC tunes concentration vs diversification
A18: ▸ Per-module asset life L (canonical IRR formula input)
A19: Asset life L: Customer Launch Starship (years) | B19: 8 | C19: F9 booster analog (lifetime reuses ramp). | AG19: 6 | AH19: 10 | AI19: triangle | AJ19: NO S-1 DATA
A20: Asset life L: Customer Launch F9 (years) | B20: 8 | C20: Customer Launch IRR anchor. | AG20: 6 | AH20: 10 | AI20: triangle | AJ20: NO S-1 DATA
A21: Asset life L: AI/Compute Orbital DC (years) | B21: 5 | C21: Sat-based; matches Starlink sat life. | AG21: 4 | AH21: 7 | AI21: triangle | AJ21: NO S-1 DATA
A22: Asset life L: AI/Compute Terrestrial DC (years) | B22: 15 | C22: Industry norm for DC infrastructure. | AG22: 10 | AH22: 20 | AI22: triangle | AJ22: NO S-1 DATA
A23: Asset life L: AI/Compute AI Apps (years) | B23: 3 | C23: Customer subscription life / CAC payback. | AG23: 2 | AH23: 5 | AI23: triangle | AJ23: NO S-1 DATA
A24: ▸ Customer Launch IRR life clamps
A25: ▸ Vehicle build claim (demand-pulled, one-period lag)
A26: CAPACITY (Starship + F9)
A27: ▸ Starship vehicle physical + cost parameters
A28: Starship 2nd-stage manufacturing cost ($mm/unit, base) | B28: 23.4 | C28: Reusability matrix anchor. | AG28: 18 | AH28: 30 | AI28: triangle | AJ28: NO S-1 DATA
A29: Ship refurb % of manufacturing | B29: 0.02 | C29: Per-reuse refurb cost. | AG29: 0.01 | AH29: 0.05 | AI29: triangle | AJ29: NO S-1 DATA
A30: Payload: booster-only mode (kg-to-LEO) | B30: 150000 | C30: Expendable ship config. S-1 (p.92) confirms 100 mt V3 → 200 mt V4 potentially. 150K kg booster-only sits between V3 and V4. | AG30: 130000 | AH30: 200000 | AI30: triangle | AJ30: S-1 PARTIAL: keep, flag V4 upgrade
A31: Payload: fully reusable mode (kg-to-LEO) | B31: 100000 | C31: S-1 p.92 EXPLICIT: V3 design 100 mt. Match. | AG31: 80000 | AH31: 150000 | AI31: triangle | AJ31: S-1 CONFIRMS p.92
A32: ▸ Starship cadence (Wright's Law on cum upmass)
A33: Base turnaround time per booster (years/flight) | B33: 1 | C33: 2025 starting point. | AG33: 0.8 | AH33: 1.5 | AI33: triangle | AJ33: NO S-1 DATA
A34: WL learning rate: turnaround vs cum upmass doubling | B34: 0.21 | C34: Booster learning rate (0.21). Cumulative experience compounds faster than an annual proxy. Monte Carlo range 0.15–0.28. Holds the rising 6→~22 booster cadence ramp. | AG34: 0.05 | AH34: 0.25 | AI34: triangle | AJ34: NO S-1 DATA: Q4'25 R18 range
A35: Cadence ceiling (flights/booster/year) | B35: 60 | C35: Physical refly ceiling at full maturity. | AG35: 40 | AH35: 100 | AI35: triangle | AJ35: NO S-1 DATA
A36: ▸ Starship time-varying inputs (year-rows)
A37: Lifetime reuses per booster (year cap) | C37: Ramps 5 → 100. S-1 anchors F9 at 34x (p.4); soft-anchor 2025 to ~30-35 for F9-class maturity. | D37: 5 | E37: 8 | F37: 12 | G37: 18 | H37: 25 | I37: 30 | J37: 35 | K37: 42 | L37: 50 | M37: 58 | N37: 65 | O37: 70 | P37: 75 | Q37: 80 | R37: 85 | S37: 90 | AI37: fixed-yearrow | AJ37: S-1 PARTIAL p.4
A38: ▸ Falcon 9 physical + cost parameters
A39: F9 booster (1st stage) mfg cost ($mm/unit) | B39: 30 | C39: 60% of total per reusability matrix source notes. S-1 silent. | AG39: 25 | AH39: 35 | AI39: triangle | AJ39: NO S-1 DATA
A40: F9 2nd stage mfg cost ($mm/unit) | B40: 10 | C40: Expendable each flight. | AG40: 8 | AH40: 13 | AI40: triangle | AJ40: NO S-1 DATA
A41: F9 fairing cost net of 75% recovery ($mm/flight) | B41: 1.25 | C41: $5M × 25% non-recovered. | AG41: 1 | AH41: 2 | AI41: triangle | AJ41: NO S-1 DATA
A42: F9 per-launch ops cost ($mm) | B42: 5 | C42: Range, propellant, recovery. | AG42: 3 | AH42: 8 | AI42: triangle | AJ42: NO S-1 DATA
A43: F9 booster refurb % of mfg | B43: 0.03 | C43: Reusability matrix. | AG43: 0.02 | AH43: 0.05 | AI43: triangle | AJ43: NO S-1 DATA
A44: F9 payload to LEO (kg) | B44: 22800 | C44: Block 5 advertised. S-1 mass-to-orbit decomposition triangulates (p.85): 1,901 mt internal / 122 launches = 15.6 mt/launch, well below F9 stretch limit. | AI44: fixed | AJ44: S-1 CONFIRMS p.85
A45: F9 lifetime reuses per booster | B45: 35 | C45: S-1 p.4 reports 34 reflights demonstrated. Lowered Base from 50 to 35 to match demonstrated; upper MC tail to 100. | AG45: 30 | AH45: 100 | AI45: triangle | AJ45: S-1 PARTIAL p.4: base to demonstrated
A46: F9 Wright's Law mfg learning rate | B46: 0.02 | C46: Mature production line; minimal further learning. | AG46: 0 | AH46: 0.05 | AI46: triangle | AJ46: NO S-1 DATA
A47: F9 cadence per booster (flights/year, flat) | B47: 8 | C47: S-1 implies actual 2025 = ~5.9 flights/booster (165 launches ÷ 28 boosters). Build Plan 12 was mature ceiling; Base lowered to 8 to reflect actual ramp; MC top retained to 15. | AG47: 6 | AH47: 15 | AI47: triangle | AJ47: S-1 PARTIAL: actual << prior Base
A48: F9 base booster build rate (boosters/year, pre-V3-trigger) | B48: 8 | C48: Q4'25 had 17 manufactured in 2025, but that's pre-decay. Build floor stub. | AG48: 6 | AH48: 10 | AI48: triangle | AJ48: NO S-1 DATA
A49: V3 Starlink launch trigger year | B49: 2026 | C49: S-1 p.5, p.93 EXPLICIT: "V3 deployment begins 2H 2026 on Starship; 60 V3 sats per Starship launch." Build Plan had 2027, overridden. | AG49: 2026 | AH49: 2027 | AI49: discrete | AJ49: S-1 OVERRIDE p.5, p.93: was 2027
A50: F9 build-rate decay window (years) | B50: 8 | C50: Linear decay over 8 yrs post-trigger. | AG50: 6 | AH50: 12 | AI50: triangle | AJ50: NO S-1 DATA
A51: F9 starting fleet at 2025 SoY (boosters) | B51: 28 | C51: Q4'25 Earth R29 anchored. S-1 doesn't disclose fleet count but cadence math (165 launches ÷ 28 = 5.9 flights/booster) is plausible. V30.5 had 24, corrected. | AI51: fixed | AJ51: S-1 CONFIRMS (math) / Q4'25 ANCHOR
A52: ▸ F9 launch glide path (Customer Launch IN to Vehicle Build)
A53: CUSTOMER LAUNCH
A54: F9 customer launch price ($mm/launch) | B54: 54.8 | C54: 2025 Space segment revenue = $4,086M (Launch Services $2,576M + Launch & Delivery $1,510M) ÷ 43 commercial customer launches = $95.0M blended. Split: commercial ~$85.9M × ~30 launches + government/defense ~$116.2M × ~13 launches. Declines 3%/yr. Calibration target: 2025 Customer Launch revenue = $4,086M ±5%. | D54: 54.8 | E54: =$D$54*(1-0.03)^E$5 -> 53.156 | F54: =$D$54*(1-0.03)^F$5 -> 51.56132 | G54: =$D$54*(1-0.03)^G$5 -> 50.01448 | H54: =$D$54*(1-0.03)^H$5 -> 48.514046 | I54: =$D$54*(1-0.03)^I$5 -> 47.058625 | J54: =$D$54*(1-0.03)^J$5 -> 45.646866 | K54: =$D$54*(1-0.03)^K$5 -> 44.27746 | L54: =$D$54*(1-0.03)^L$5 -> 42.949136 | ... S54: =$D$54*(1-0.03)^S$5 -> 34.702165 | AI54: fixed-yearrow | AJ54: Source: S-1 p.247
A55: Starship customer launch price ($mm/launch): year-row | C55: S-1 p.5 confirms first commercial Starship payload delivery 2H 2026. Customer revenue from 2027 (1yr after first delivery). $100M stub stands; 8%/yr decline. | D55: 0 | E55: 0 | F55: 100 | G55: 92 | H55: 84.64 | I55: 77.87 | J55: 71.64 | K55: 65.91 | L55: 60.64 | M55: 55.79 | N55: 51.32 | O55: 47.21 | P55: 43.44 | Q55: 39.96 | R55: 36.77 | S55: 33.83 | AI55: fixed-yearrow | AJ55: S-1 PARTIAL p.5-2027 start confirmed
A56: Commercial launch market size ($mm/year): year-row | C56: Build plan $8B base + 8%/yr growth. The S-1 implies a ~70% SpaceX share of a ~$5.5B 2025 market, so this build plan may be too high. | D56: 8000 | E56: 8640 | F56: 9331.2 | G56: 10077.7 | H56: 10883.9 | I56: 11754.6 | J56: 12695 | K56: 13710.6 | L56: 14807.4 | M56: 15992 | N56: 17271.4 | O56: 18653.1 | P56: 20145.4 | Q56: 21757 | R56: 23497.5 | S56: 25377.4 | AI56: fixed-yearrow | AJ56: Source: S-1 p.81
A57: Government launch market size ($mm/year): year-row | C57: Build plan $4B + 5%/yr. 2025 Launch & Delivery of $1,510M (NASA CRS + DoW) implies a ~$1.7B market at 90% share, so this build plan looks high. | D57: 4000 | E57: 4200 | F57: 4410 | G57: 4630.5 | H57: 4862.02 | I57: 5105.13 | J57: 5360.38 | K57: 5628.4 | L57: 5909.82 | M57: 6205.31 | N57: 6515.58 | O57: 6841.36 | P57: 7183.43 | Q57: 7542.6 | R57: 7919.73 | S57: 8315.71 | AI57: fixed-yearrow | AJ57: Source: S-1
A58: SpaceX commercial market share % | C58: S-1 p.81 supports higher share than Build Plan's 70%. New trajectory: 75% (2025) → 80% (2040, linear). | D58: 0.75 | E58: 0.7533 | F58: 0.7567 | G58: 0.76 | H58: 0.7633 | I58: 0.7667 | J58: 0.77 | K58: 0.7733 | L58: 0.7767 | M58: 0.78 | N58: 0.7833 | O58: 0.7867 | P58: 0.79 | Q58: 0.7933 | R58: 0.7967 | S58: 0.8 | AI58: fixed-yearrow | AJ58: S-1 PARTIAL p.81: lifted to 75%
A59: SpaceX government market share % | C59: Customer A 20.9% concentration trend supports declining gov share. 90% → 80% linear. | D59: 0.9 | E59: 0.8933 | F59: 0.8867 | G59: 0.88 | H59: 0.8733 | I59: 0.8667 | J59: 0.86 | K59: 0.8533 | L59: 0.8467 | M59: 0.84 | N59: 0.8333 | O59: 0.8267 | P59: 0.82 | Q59: 0.8133 | R59: 0.8067 | S59: 0.8 | AI59: fixed-yearrow | AJ59: NO S-1 DATA
A60: Launch insurance % of external rev | B60: 0.05 | C60: Internal. | AG60: 0.03 | AH60: 0.08 | AI60: triangle | AJ60: NO S-1 DATA
A61: Launch other COGS % of external rev | B61: 0.02 | C61: Internal. | AG61: 0.01 | AH61: 0.04 | AI61: triangle | AJ61: NO S-1 DATA
A62: ▸ NEW S-1 derived inputs
A63: Memo: Avg customer payload size (mt/mission) | B63: 13 | C63: S-1 p.85: 13 mt average customer mission since 2023. Useful for kg-pool calibration. | AI63: fixed | AJ63: memo
A64: STARLINK
A65: ▸ Satellite physical
A66: ▸ Wright's Law parameters
A67: Satellite cost per kg: base year ($/kg) | B67: 650 | C67: Q4'25 $643.50; S-1 PP&E sat gross $11,949M / 9,600 sats × 575 kg ≈ $720/kg, within tolerance. | AG67: 500 | AH67: 800 | AI67: triangle | AJ67: S-1 CONFIRMS (within ±10%)
A68: Satellite cost per kg: learning rate | B68: 0.05 | C68: Internal. | AG68: 0.03 | AH68: 0.17 | AI68: triangle | AJ68: NO S-1 DATA
A69: Satellite cost floor ($/kg) | B69: 400 | C69: Internal. | AG69: 300 | AH69: 500 | AI69: triangle | AJ69: NO S-1 DATA
A70: ▸ Starshield
A71: ▸ Depreciation parameters
A72: Satellite Dep per kg: base year ($/kg/yr) | B72: 128.8 | C72: Constellation depreciation. S-1 property, plant & equipment: satellite gross $11,949M → ~$2,390M at a 5-year life; 2025 target ≈ $706.9M. | AG72: 110 | AH72: 150 | AI72: triangle | AJ72: Source: S-1 p.245, p.248
A73: ▸ Constellation opening balances (Mach33 historical anchors: hard)
A74: ▸ Deorbit parameters
A75: ▸ Subscribers + ARPU + Terminals (BIG S-1 IMPACTS)
A76: Starting BoY 2025 subscribers (millions) | B76: 4.4 | C76: S-1 p.22, p.87 audited EoY 2024 = BoY 2025 = 4.4M. Build Plan had 5.0M, overridden. | AG76: 3.5 | AH76: 6 | AI76: triangle | AJ76: S-1 OVERRIDE p.22, p.87
A77: Broadband ARPU ($/sub/mo): year-row | C77: S-1 p.22, p.87: 2025 = $81 (audited); Q1'26 = $66 (audited); mgmt guidance: continued decline as international growth + lower-priced plans land. Build Plan $100→$75 by 2030 OVERRIDDEN. New trajectory: $81 → $55 by 2030 → flat. | D77: 81 | E77: 75 | F77: 70 | G77: 65 | H77: 60 | I77: 55 | J77: 54 | K77: 53 | L77: 52 | M77: 51 | N77: 50 | O77: 49.5 | P77: 49 | Q77: 48.5 | R77: 48 | S77: 47.5 | AI77: triangle-yearrow | AJ77: S-1 OVERRIDE p.22, p.87: Triangle MC ±10
A78: DTC ARPU ($/sub/mo): year-row | C78: S-1 doesn't break out DTC ARPU. Hold Build Plan trajectory $16 → $10 by 2030 flat. | D78: 16 | E78: 14.8 | F78: 13.6 | G78: 12.4 | H78: 11.2 | I78: 10 | J78: 10 | K78: 10 | L78: 10 | M78: 10 | N78: 10 | O78: 10 | P78: 10 | Q78: 10 | R78: 10 | S78: 10 | AI78: fixed-yearrow | AJ78: NO S-1 DATA
A79: Terminal COGS per unit ($) | B79: 500 | C79: S-1 p.247 Connectivity products $1,510M is terminal-sales channel. No unit cost disclosed. | AG79: 400 | AH79: 700 | AI79: triangle | AJ79: S-1 PARTIAL p.247
A80: ▸ BB/DTC market mix
A81: ▸ Bandwidth flow → superseded by the AI/Compute section; see orbital-compute↔Starlink elimination
A82: ▸ NEW Starlink rows from S-1 disclosures
A83: Memo: MNO partner count | B83: 30 | C83: S-1 p.85: T-Mobile, Optus, Telstra, Rogers, KDDI, Kyivstar, ~24 others. Drives MNO-side TAM expansion. | AI83: fixed | AJ83: memo
A84: Memo: MNO addressable population (millions) | B84: 1900 | C84: S-1 p.85. Sanity-check upper bound on Mobile TAM. | AI84: fixed | AJ84: memo
A85: Memo: Countries served | B85: 164 | C85: S-1 p.4. Coverage anchor for international ARPU mix. | AI85: fixed | AJ85: memo
A86: Memo: Enterprise churn: qualitative | B86: 0 | C86: S-1 p.82: "no Enterprise customer >$750k rev has voluntarily churned since 2023." Moat narrative for Enterprise/Gov. | AI86: fixed | AJ86: memo
A87: Memo: Connectivity Adj EBITDA margin 2025: calibration target | B87: 0.629 | C87: Target margin 61.4%, per the S-1. | AI87: fixed | AJ87: memo
A88: Memo: Connectivity Consumer revenue 2025 ($M) | B88: 7208 | C88: S-1 p.247. Calibration spine. | AI88: fixed | AJ88: memo
A89: Memo: Connectivity E&G incl Mobile revenue 2025 ($M) | B89: 4179 | C89: S-1 p.247. Calibration spine. | AI89: fixed | AJ89: memo
A90: Memo: Connectivity COGS 2025 ($M) | B90: 5921 | C90: S-1 p.111. Calibration target. | AI90: fixed | AJ90: memo
A91: Memo: Connectivity SG&A 2025 ($M) | B91: 468 | C91: S-1 p.111. Calibration target. | AI91: fixed | AJ91: memo
A92: Memo: Connectivity R&D 2025 ($M) | B92: 575 | C92: S-1 p.111. Calibration target. | AI92: fixed | AJ92: memo
A93: ▸ Starlink R&D attribution rule
A94: ODC — RETIRED, superseded by the AI/Compute section. Memos below retained.
A95: F_ref: reference compute unit (TFLOPS, H100 FP8) | B95: 1979 | C95: Industry anchor. | AI95: fixed | AJ95: Structural
A96: ▸ Dual revenue model
A97: PUE_base (terrestrial colo) | B97: 1.4 | C97: Industry standard. | AG97: 1.3 | AH97: 1.6 | AI97: triangle | AJ97: NO S-1 DATA
A98: Orbital PUE | B98: 1.12 | C98: First-principles. | AG98: 1.05 | AH98: 1.25 | AI98: triangle | AJ98: NO S-1 DATA
A99: Memo: ODC first deployment year (anchor) | B99: 2028 | C99: S-1 p.3, p.10. Cash flows to ODC starting 2027 (1-yr build lead). | AI99: fixed | AJ99: S-1 NEW p.3, p.10
A100: Memo: Terrestrial AI compute draw (GW): year-row | C100: S-1 p.22, p.89: 0.3 EoY 2023 → 0.8 EoY 2025 → 1.0 Q1'26. COLOSSUS + COLOSSUS II buildout. Memo for AI Stack TAM sizing. | D100: 0.8 | E100: 1.5 | F100: 2.5 | G100: 4 | H100: 6 | I100: 8 | J100: 10 | K100: 12 | L100: 14 | M100: 16 | N100: 18 | O100: 20 | P100: 22 | Q100: 24 | R100: 26 | S100: 28 | AI100: fixed-yearrow | AJ100: memo
...

Sheet Demand Curves
A1: Demand Curves: Starlink BB + DTC piecewise-linear lookup
A2: Lookup form: INDEX/MATCH(..., 1) bracket-find + manual linear interp. NO FORECAST / TREND. Per Memory Snapshot v3 §2.4.
D4: 2025 | E4: 2026 | F4: 2027 | G4: 2028 | H4: 2029 | I4: 2030 | J4: 2031 | K4: 2032 | L4: 2033 | M4: 2034 | N4: 2035 | O4: 2036 | P4: 2037 | Q4: 2038 | R4: 2039 | S4: 2040
D5: 0 | E5: 1 | F5: 2 | G5: 3 | H5: 4 | I5: 5 | J5: 6 | K5: 7 | L5: 8 | M5: 9 | N5: 10 | O5: 11 | P5: 12 | Q5: 13 | R5: 14 | S5: 15
A15: DTC DEMAND CURVE (piecewise-linear Q→Revenue lookup)
A16: Constellation Bandwidth (Gbps) | B16: Q (Gbps) | C16: Annual DTC Revenue ($mm)
A17: DTC Q breakpoint #1 (Gbps) | B17: 280.2 | C17: 307
A18: DTC Q breakpoint #2 (Gbps) | B18: 560.3 | C18: 613
A19: DTC Q breakpoint #3 (Gbps) | B19: 840.5 | C19: 920
A20: DTC Q breakpoint #4 (Gbps) | B20: 1120.6 | C20: 1227
A21: DTC Q breakpoint #5 (Gbps) | B21: 1400.8 | C21: 1534
A22: DTC Q breakpoint #6 (Gbps) | B22: 1680.9 | C22: 1840
A23: DTC Q breakpoint #7 (Gbps) | B23: 1961.1 | C23: 2147
A24: DTC Q breakpoint #8 (Gbps) | B24: 2241.2 | C24: 2454
A25: DTC Q breakpoint #9 (Gbps) | B25: 2521.4 | C25: 2760
A26: DTC Q breakpoint #10 (Gbps) | B26: 2801.5 | C26: 3067
A27: DTC Q breakpoint #11 (Gbps) | B27: 3501.9 | C27: 3827
A28: DTC Q breakpoint #12 (Gbps) | B28: 4202.3 | C28: 4587
... A77: DTC Q breakpoint #61 (Gbps) | B77: 84046.3 | C77: 15920
A80: BB DEMAND CURVE (piecewise-linear Q→Revenue lookup)
A81: Capacity (Gbps) | B81: Q (Gbps) | C81: BB TAM/Revenue ($mm)
A82: BB Q breakpoint #1 (Gbps) | B82: 100000 | C82: 2936
A83: BB Q breakpoint #2 (Gbps) | B83: 200000 | C83: 3748
A84: BB Q breakpoint #3 (Gbps) | B84: 300000 | C84: 4559
A85: BB Q breakpoint #4 (Gbps) | B85: 400000 | C85: 5370
A86: BB Q breakpoint #5 (Gbps) | B86: 500000 | C86: 6157
A87: BB Q breakpoint #6 (Gbps) | B87: 1000000 | C87: 10055
A88: BB Q breakpoint #7 (Gbps) | B88: 2000000 | C88: 17173
A89: BB Q breakpoint #8 (Gbps) | B89: 3000000 | C89: 23037
A90: BB Q breakpoint #9 (Gbps) | B90: 4000000 | C90: 28430
A91: BB Q breakpoint #10 (Gbps) | B91: 5000000 | C91: 33451
A92: BB Q breakpoint #11 (Gbps) | B92: 6000000 | C92: 38244
A93: BB Q breakpoint #12 (Gbps) | B93: 7000000 | C93: 42520
... A137: BB Q breakpoint #56 (Gbps) | B137: 250000000 | C137: 187819
A140: ▸ Curve evaluators (year-row, read by the Starlink module)
A141: Annual TAM shift multiplier | D141: =1 -> 1 | E141: =D141*(1+E149) -> 1.035 | F141: =E141*(1+F149) -> 1.070075 | G141: =F141*(1+G149) -> 1.1051497 | H141: =G141*(1+H149) -> 1.1401461 | I141: =H141*(1+I149) -> 1.1749839 | J141: =I141*(1+J149) -> 1.2095806 | K141: =J141*(1+K149) -> 1.2438521 | L141: =K141*(1+L149) -> 1.2777125 | ... S141: =R141*(1+S149) -> 1.520445
A142: Starlink BB capacity input (Gbps) | D142: {=IFERROR(INDEX(Starlink!$D:$AC,MATCH("BB Gbps available for external Starlink revenue",Starlink!$A$1:$A$205,0),COLUMN()-COLUMN($D142)+1),0)} -> 489144 | E142: {=IFERROR(INDEX(Starlink!$D:$AC,MATCH("BB Gbps available for external Starlink revenue",Starlink!$A$1:$A$205,0),COLUMN()-COLUMN($D142)+1),0)} -> 756736 | F142: {=IFERROR(INDEX(Starlink!$D:$AC,MATCH("BB Gbps available for external Starlink revenue",Starlink!$A$1:$A$205,0),COLUMN()-COLUMN($D142)+1),0)} -> 4652054.4 | G142: {=IFERROR(INDEX(Starlink!$D:$AC,MATCH("BB Gbps available for external Starlink revenue",Starlink!$A$1:$A$205,0),COLUMN()-COLUMN($D142)+1),0)} -> 13909803 | H142: {=IFERROR(INDEX(Starlink!$D:$AC,MATCH("BB Gbps available for external Starlink revenue",Starlink!$A$1:$A$205,0),COLUMN()-COLUMN($D142)+1),0)} -> 34094523 | I142: {=IFERROR(INDEX(Starlink!$D:$AC,MATCH("BB Gbps available for external Starlink revenue",Starlink!$A$1:$A$205,0),COLUMN()-COLUMN($D142)+1),0)} -> 46320469 | J142: {=IFERROR(INDEX(Starlink!$D:$AC,MATCH("BB Gbps available for external Starlink revenue",Starlink!$A$1:$A$205,0),COLUMN()-COLUMN($D142)+1),0)} -> 73672560 | K142: {=IFERROR(INDEX(Starlink!$D:$AC,MATCH("BB Gbps available for external Starlink revenue",Starlink!$A$1:$A$205,0),COLUMN()-COLUMN($D142)+1),0)} -> 82297889 | ... S142: {=IFERROR(INDEX(Starlink!$D:$AC,MATCH("BB Gbps available for external Starlink revenue",Starlink!$A$1:$A$205,0),COLUMN()-COLUMN($D142)+1),0)} -> 1.9521171e+08
A143: Starlink DTC capacity input (Gbps) | D143: {=IFERROR(INDEX(Starlink!$D:$AC,MATCH("DTC Gbps available for external Starlink revenue",Starlink!$A$1:$A$205,0),COLUMN()-COLUMN($D143)+1),0)} -> 577.71 | E143: {=IFERROR(INDEX(Starlink!$D:$AC,MATCH("DTC Gbps available for external Starlink revenue",Starlink!$A$1:$A$205,0),COLUMN()-COLUMN($D143)+1),0)} -> 577.71 | F143: {=IFERROR(INDEX(Starlink!$D:$AC,MATCH("DTC Gbps available for external Starlink revenue",Starlink!$A$1:$A$205,0),COLUMN()-COLUMN($D143)+1),0)} -> 579.36898 | G143: {=IFERROR(INDEX(Starlink!$D:$AC,MATCH("DTC Gbps available for external Starlink revenue",Starlink!$A$1:$A$205,0),COLUMN()-COLUMN($D143)+1),0)} -> 649.97109 | H143: {=IFERROR(INDEX(Starlink!$D:$AC,MATCH("DTC Gbps available for external Starlink revenue",Starlink!$A$1:$A$205,0),COLUMN()-COLUMN($D143)+1),0)} -> 2675.9981 | I143: {=IFERROR(INDEX(Starlink!$D:$AC,MATCH("DTC Gbps available for external Starlink revenue",Starlink!$A$1:$A$205,0),COLUMN()-COLUMN($D143)+1),0)} -> 22412.908 | J143: {=IFERROR(INDEX(Starlink!$D:$AC,MATCH("DTC Gbps available for external Starlink revenue",Starlink!$A$1:$A$205,0),COLUMN()-COLUMN($D143)+1),0)} -> 47287.791 | K143: {=IFERROR(INDEX(Starlink!$D:$AC,MATCH("DTC Gbps available for external Starlink revenue",Starlink!$A$1:$A$205,0),COLUMN()-COLUMN($D143)+1),0)} -> 71156.613 | ... S143: {=IFERROR(INDEX(Starlink!$D:$AC,MATCH("DTC Gbps available for external Starlink revenue",Starlink!$A$1:$A$205,0),COLUMN()-COLUMN($D143)+1),0)} -> 136991.06
A144: Starlink BB Revenue from curve ($mm) | D144: {=((IF(D142>=INDEX($B$82:$B$137,COUNTA($B$82:$B$137)),INDEX($C$82:$C$137,COUNTA($B$82:$B$137))*D141,IF(D142<=INDEX($B$82:$B$137,1),INDEX($C$82:$C$137,1)*D141,(INDEX($C$82:$C$137,MATCH(D142,$B$82:$B$137,1))+(D142-INDEX($B$82:$B$137,MATCH(D142,$B$82:$B$137,1)))*(INDEX($C$82:$C$137,MATCH(D142,$B$82:$B$137,1)+1)-INDEX($C$82:$C$137,MATCH(D142,$B$82:$B$137,1)))/(INDEX($B$82:$B$137,MATCH(D142,$B$82:$B$137,1)+1)-INDEX($B$82:$B$137,MATCH(D142,$B$82:$B$137,1))))*D141)))*INDEX(Assumptions!$B:$B,MATCH("BB demand curve level multiplier",Assumptions!$A$1:$A$327,0)))*D151} -> 6721.2206 | E144: {=((IF(E142>=INDEX($B$82:$B$137,COUNTA($B$82:$B$137)),INDEX($C$82:$C$137,COUNTA($B$82:$B$137))*E141,IF(E142<=INDEX($B$82:$B$137,1),INDEX($C$82:$C$137,1)*E141,(INDEX($C$82:$C$137,MATCH(E142,$B$82:$B$137,1))+(E142-INDEX($B$82:$B$137,MATCH(E142,$B$82:$B$137,1)))*(INDEX($C$82:$C$137,MATCH(E142,$B$82:$B$137,1)+1)-INDEX($C$82:$C$137,MATCH(E142,$B$82:$B$137,1)))/(INDEX($B$82:$B$137,MATCH(E142,$B$82:$B$137,1)+1)-INDEX($B$82:$B$137,MATCH(E142,$B$82:$B$137,1))))*E141)))*INDEX(Assumptions!$B:$B,MATCH("BB demand curve level multiplier",Assumptions!$A$1:$A$327,0)))*E151} -> 9347.5765 | F144: {=((IF(F142>=INDEX($B$82:$B$137,COUNTA($B$82:$B$137)),INDEX($C$82:$C$137,COUNTA($B$82:$B$137))*F141,IF(F142<=INDEX($B$82:$B$137,1),INDEX($C$82:$C$137,1)*F141,(INDEX($C$82:$C$137,MATCH(F142,$B$82:$B$137,1))+(F142-INDEX($B$82:$B$137,MATCH(F142,$B$82:$B$137,1)))*(INDEX($C$82:$C$137,MATCH(F142,$B$82:$B$137,1)+1)-INDEX($C$82:$C$137,MATCH(F142,$B$82:$B$137,1)))/(INDEX($B$82:$B$137,MATCH(F142,$B$82:$B$137,1)+1)-INDEX($B$82:$B$137,MATCH(F142,$B$82:$B$137,1))))*F141)))*INDEX(Assumptions!$B:$B,MATCH("BB demand curve level multiplier",Assumptions!$A$1:$A$327,0)))*F151} -> 37555.662 | G144: {=((IF(G142>=INDEX($B$82:$B$137,COUNTA($B$82:$B$137)),INDEX($C$82:$C$137,COUNTA($B$82:$B$137))*G141,IF(G142<=INDEX($B$82:$B$137,1),INDEX($C$82:$C$137,1)*G141,(INDEX($C$82:$C$137,MATCH(G142,$B$82:$B$137,1))+(G142-INDEX($B$82:$B$137,MATCH(G142,$B$82:$B$137,1)))*(INDEX($C$82:$C$137,MATCH(G142,$B$82:$B$137,1)+1)-INDEX($C$82:$C$137,MATCH(G142,$B$82:$B$137,1)))/(INDEX($B$82:$B$137,MATCH(G142,$B$82:$B$137,1)+1)-INDEX($B$82:$B$137,MATCH(G142,$B$82:$B$137,1))))*G141)))*INDEX(Assumptions!$B:$B,MATCH("BB demand curve level multiplier",Assumptions!$A$1:$A$327,0)))*G151} -> 80517.638 | H144: {=((IF(H142>=INDEX($B$82:$B$137,COUNTA($B$82:$B$137)),INDEX($C$82:$C$137,COUNTA($B$82:$B$137))*H141,IF(H142<=INDEX($B$82:$B$137,1),INDEX($C$82:$C$137,1)*H141,(INDEX($C$82:$C$137,MATCH(H142,$B$82:$B$137,1))+(H142-INDEX($B$82:$B$137,MATCH(H142,$B$82:$B$137,1)))*(INDEX($C$82:$C$137,MATCH(H142,$B$82:$B$137,1)+1)-INDEX($C$82:$C$137,MATCH(H142,$B$82:$B$137,1)))/(INDEX($B$82:$B$137,MATCH(H142,$B$82:$B$137,1)+1)-INDEX($B$82:$B$137,MATCH(H142,$B$82:$B$137,1))))*H141)))*INDEX(Assumptions!$B:$B,MATCH("BB demand curve level multiplier",Assumptions!$A$1:$A$327,0)))*H151} -> 133572.61 | I144: {=((IF(I142>=INDEX($B$82:$B$137,COUNTA($B$82:$B$137)),INDEX($C$82:$C$137,COUNTA($B$82:$B$137))*I141,IF(I142<=INDEX($B$82:$B$137,1),INDEX($C$82:$C$137,1)*I141,(INDEX($C$82:$C$137,MATCH(I142,$B$82:$B$137,1))+(I142-INDEX($B$82:$B$137,MATCH(I142,$B$82:$B$137,1)))*(INDEX($C$82:$C$137,MATCH(I142,$B$82:$B$137,1)+1)-INDEX($C$82:$C$137,MATCH(I142,$B$82:$B$137,1)))/(INDEX($B$82:$B$137,MATCH(I142,$B$82:$B$137,1)+1)-INDEX($B$82:$B$137,MATCH(I142,$B$82:$B$137,1))))*I141)))*INDEX(Assumptions!$B:$B,MATCH("BB demand curve level multiplier",Assumptions!$A$1:$A$327,0)))*I151} -> 162366.46 | J144: {=((IF(J142>=INDEX($B$82:$B$137,COUNTA($B$82:$B$137)),INDEX($C$82:$C$137,COUNTA($B$82:$B$137))*J141,IF(J142<=INDEX($B$82:$B$137,1),INDEX($C$82:$C$137,1)*J141,(INDEX($C$82:$C$137,MATCH(J142,$B$82:$B$137,1))+(J142-INDEX($B$82:$B$137,MATCH(J142,$B$82:$B$137,1)))*(INDEX($C$82:$C$137,MATCH(J142,$B$82:$B$137,1)+1)-INDEX($C$82:$C$137,MATCH(J142,$B$82:$B$137,1)))/(INDEX($B$82:$B$137,MATCH(J142,$B$82:$B$137,1)+1)-INDEX($B$82:$B$137,MATCH(J142,$B$82:$B$137,1))))*J141)))*INDEX(Assumptions!$B:$B,MATCH("BB demand curve level multiplier",Assumptions!$A$1:$A$327,0)))*J151} -> 198728.63 | K144: {=((IF(K142>=INDEX($B$82:$B$137,COUNTA($B$82:$B$137)),INDEX($C$82:$C$137,COUNTA($B$82:$B$137))*K141,IF(K142<=INDEX($B$82:$B$137,1),INDEX($C$82:$C$137,1)*K141,(INDEX($C$82:$C$137,MATCH(K142,$B$82:$B$137,1))+(K142-INDEX($B$82:$B$137,MATCH(K142,$B$82:$B$137,1)))*(INDEX($C$82:$C$137,MATCH(K142,$B$82:$B$137,1)+1)-INDEX($C$82:$C$137,MATCH(K142,$B$82:$B$137,1)))/(INDEX($B$82:$B$137,MATCH(K142,$B$82:$B$137,1)+1)-INDEX($B$82:$B$137,MATCH(K142,$B$82:$B$137,1))))*K141)))*INDEX(Assumptions!$B:$B,MATCH("BB demand curve level multiplier",Assumptions!$A$1:$A$327,0)))*K151} -> 212218.52 | ... S144: {=((IF(S142>=INDEX($B$82:$B$137,COUNTA($B$82:$B$137)),INDEX($C$82:$C$137,COUNTA($B$82:$B$137))*S141,IF(S142<=INDEX($B$82:$B$137,1),INDEX($C$82:$C$137,1)*S141,(INDEX($C$82:$C$137,MATCH(S142,$B$82:$B$137,1))+(S142-INDEX($B$82:$B$137,MATCH(S142,$B$82:$B$137,1)))*(INDEX($C$82:$C$137,MATCH(S142,$B$82:$B$137,1)+1)-INDEX($C$82:$C$137,MATCH(S142,$B$82:$B$137,1)))/(INDEX($B$82:$B$137,MATCH(S142,$B$82:$B$137,1)+1)-INDEX($B$82:$B$137,MATCH(S142,$B$82:$B$137,1))))*S141)))*INDEX(Assumptions!$B:$B,MATCH("BB demand curve level multiplier",Assumptions!$A$1:$A$327,0)))*S151} -> 305981.36
A145: Starlink DTC Revenue from curve ($mm) | D145: {=((IF(D143<=0,0,IF(D143>=INDEX($B$17:$B$77,COUNTA($B$17:$B$77)),INDEX($C$17:$C$77,COUNTA($B$17:$B$77))*D141,IF(D143<INDEX($B$17:$B$77,1),D143/INDEX($B$17:$B$77,1)*INDEX($C$17:$C$77,1)*D141,(INDEX($C$17:$C$77,MATCH(D143,$B$17:$B$77,1))+(D143-INDEX($B$17:$B$77,MATCH(D143,$B$17:$B$77,1)))*(INDEX($C$17:$C$77,MATCH(D143,$B$17:$B$77,1)+1)-INDEX($C$17:$C$77,MATCH(D143,$B$17:$B$77,1)))/(INDEX($B$17:$B$77,MATCH(D143,$B$17:$B$77,1)+1)-INDEX($B$17:$B$77,MATCH(D143,$B$17:$B$77,1))))*D141))))*INDEX(Assumptions!$B:$B,MATCH("DTC demand curve level multiplier",Assumptions!$A$1:$A$327,0)))*D150} -> 632.0752 | E145: {=((IF(E143<=0,0,IF(E143>=INDEX($B$17:$B$77,COUNTA($B$17:$B$77)),INDEX($C$17:$C$77,COUNTA($B$17:$B$77))*E141,IF(E143<INDEX($B$17:$B$77,1),E143/INDEX($B$17:$B$77,1)*INDEX($C$17:$C$77,1)*E141,(INDEX($C$17:$C$77,MATCH(E143,$B$17:$B$77,1))+(E143-INDEX($B$17:$B$77,MATCH(E143,$B$17:$B$77,1)))*(INDEX($C$17:$C$77,MATCH(E143,$B$17:$B$77,1)+1)-INDEX($C$17:$C$77,MATCH(E143,$B$17:$B$77,1)))/(INDEX($B$17:$B$77,MATCH(E143,$B$17:$B$77,1)+1)-INDEX($B$17:$B$77,MATCH(E143,$B$17:$B$77,1))))*E141))))*INDEX(Assumptions!$B:$B,MATCH("DTC demand curve level multiplier",Assumptions!$A$1:$A$327,0)))*E150} -> 794.38308 | F145: {=((IF(F143<=0,0,IF(F143>=INDEX($B$17:$B$77,COUNTA($B$17:$B$77)),INDEX($C$17:$C$77,COUNTA($B$17:$B$77))*F141,IF(F143<INDEX($B$17:$B$77,1),F143/INDEX($B$17:$B$77,1)*INDEX($C$17:$C$77,1)*F141,(INDEX($C$17:$C$77,MATCH(F143,$B$17:$B$77,1))+(F143-INDEX($B$17:$B$77,MATCH(F143,$B$17:$B$77,1)))*(INDEX($C$17:$C$77,MATCH(F143,$B$17:$B$77,1)+1)-INDEX($C$17:$C$77,MATCH(F143,$B$17:$B$77,1)))/(INDEX($B$17:$B$77,MATCH(F143,$B$17:$B$77,1)+1)-INDEX($B$17:$B$77,MATCH(F143,$B$17:$B$77,1))))*F141))))*INDEX(Assumptions!$B:$B,MATCH("DTC demand curve level multiplier",Assumptions!$A$1:$A$327,0)))*F150} -> 969.01841 | G145: {=((IF(G143<=0,0,IF(G143>=INDEX($B$17:$B$77,COUNTA($B$17:$B$77)),INDEX($C$17:$C$77,COUNTA($B$17:$B$77))*G141,IF(G143<INDEX($B$17:$B$77,1),G143/INDEX($B$17:$B$77,1)*INDEX($C$17:$C$77,1)*G141,(INDEX($C$17:$C$77,MATCH(G143,$B$17:$B$77,1))+(G143-INDEX($B$17:$B$77,MATCH(G143,$B$17:$B$77,1)))*(INDEX($C$17:$C$77,MATCH(G143,$B$17:$B$77,1)+1)-INDEX($C$17:$C$77,MATCH(G143,$B$17:$B$77,1)))/(INDEX($B$17:$B$77,MATCH(G143,$B$17:$B$77,1)+1)-INDEX($B$17:$B$77,MATCH(G143,$B$17:$B$77,1))))*G141))))*INDEX(Assumptions!$B:$B,MATCH("DTC demand curve level multiplier",Assumptions!$A$1:$A$327,0)))*G150} -> 1291.3436 | H145: {=((IF(H143<=0,0,IF(H143>=INDEX($B$17:$B$77,COUNTA($B$17:$B$77)),INDEX($C$17:$C$77,COUNTA($B$17:$B$77))*H141,IF(H143<INDEX($B$17:$B$77,1),H143/INDEX($B$17:$B$77,1)*INDEX($C$17:$C$77,1)*H141,(INDEX($C$17:$C$77,MATCH(H143,$B$17:$B$77,1))+(H143-INDEX($B$17:$B$77,MATCH(H143,$B$17:$B$77,1)))*(INDEX($C$17:$C$77,MATCH(H143,$B$17:$B$77,1)+1)-INDEX($C$17:$C$77,MATCH(H143,$B$17:$B$77,1)))/(INDEX($B$17:$B$77,MATCH(H143,$B$17:$B$77,1)+1)-INDEX($B$17:$B$77,MATCH(H143,$B$17:$B$77,1))))*H141))))*INDEX(Assumptions!$B:$B,MATCH("DTC demand curve level multiplier",Assumptions!$A$1:$A$327,0)))*H150} -> 6202.8488 | I145: {=((IF(I143<=0,0,IF(I143>=INDEX($B$17:$B$77,COUNTA($B$17:$B$77)),INDEX($C$17:$C$77,COUNTA($B$17:$B$77))*I141,IF(I143<INDEX($B$17:$B$77,1),I143/INDEX($B$17:$B$77,1)*INDEX($C$17:$C$77,1)*I141,(INDEX($C$17:$C$77,MATCH(I143,$B$17:$B$77,1))+(I143-INDEX($B$17:$B$77,MATCH(I143,$B$17:$B$77,1)))*(INDEX($C$17:$C$77,MATCH(I143,$B$17:$B$77,1)+1)-INDEX($C$17:$C$77,MATCH(I143,$B$17:$B$77,1)))/(INDEX($B$17:$B$77,MATCH(I143,$B$17:$B$77,1)+1)-INDEX($B$17:$B$77,MATCH(I143,$B$17:$B$77,1))))*I141))))*INDEX(Assumptions!$B:$B,MATCH("DTC demand curve level multiplier",Assumptions!$A$1:$A$327,0)))*I150} -> 30569.893 | J145: {=((IF(J143<=0,0,IF(J143>=INDEX($B$17:$B$77,COUNTA($B$17:$B$77)),INDEX($C$17:$C$77,COUNTA($B$17:$B$77))*J141,IF(J143<INDEX($B$17:$B$77,1),J143/INDEX($B$17:$B$77,1)*INDEX($C$17:$C$77,1)*J141,(INDEX($C$17:$C$77,MATCH(J143,$B$17:$B$77,1))+(J143-INDEX($B$17:$B$77,MATCH(J143,$B$17:$B$77,1)))*(INDEX($C$17:$C$77,MATCH(J143,$B$17:$B$77,1)+1)-INDEX($C$17:$C$77,MATCH(J143,$B$17:$B$77,1)))/(INDEX($B$17:$B$77,MATCH(J143,$B$17:$B$77,1)+1)-INDEX($B$17:$B$77,MATCH(J143,$B$17:$B$77,1))))*J141))))*INDEX(Assumptions!$B:$B,MATCH("DTC demand curve level multiplier",Assumptions!$A$1:$A$327,0)))*J150} -> 40144.794 | K145: {=((IF(K143<=0,0,IF(K143>=INDEX($B$17:$B$77,COUNTA($B$17:$B$77)),INDEX($C$17:$C$77,COUNTA($B$17:$B$77))*K141,IF(K143<INDEX($B$17:$B$77,1),K143/INDEX($B$17:$B$77,1)*INDEX($C$17:$C$77,1)*K141,(INDEX($C$17:$C$77,MATCH(K143,$B$17:$B$77,1))+(K143-INDEX($B$17:$B$77,MATCH(K143,$B$17:$B$77,1)))*(INDEX($C$17:$C$77,MATCH(K143,$B$17:$B$77,1)+1)-INDEX($C$17:$C$77,MATCH(K143,$B$17:$B$77,1)))/(INDEX($B$17:$B$77,MATCH(K143,$B$17:$B$77,1)+1)-INDEX($B$17:$B$77,MATCH(K143,$B$17:$B$77,1))))*K141))))*INDEX(Assumptions!$B:$B,MATCH("DTC demand curve level multiplier",Assumptions!$A$1:$A$327,0)))*K150} -> 47979.431 | ... S145: {=((IF(S143<=0,0,IF(S143>=INDEX($B$17:$B$77,COUNTA($B$17:$B$77)),INDEX($C$17:$C$77,COUNTA($B$17:$B$77))*S141,IF(S143<INDEX($B$17:$B$77,1),S143/INDEX($B$17:$B$77,1)*INDEX($C$17:$C$77,1)*S141,(INDEX($C$17:$C$77,MATCH(S143,$B$17:$B$77,1))+(S143-INDEX($B$17:$B$77,MATCH(S143,$B$17:$B$77,1)))*(INDEX($C$17:$C$77,MATCH(S143,$B$17:$B$77,1)+1)-INDEX($C$17:$C$77,MATCH(S143,$B$17:$B$77,1)))/(INDEX($B$17:$B$77,MATCH(S143,$B$17:$B$77,1)+1)-INDEX($B$17:$B$77,MATCH(S143,$B$17:$B$77,1))))*S141))))*INDEX(Assumptions!$B:$B,MATCH("DTC demand curve level multiplier",Assumptions!$A$1:$A$327,0)))*S150} -> 60513.713
A146: Memo: Average $/Gbps BB from curve | D146: =IFERROR(D144*1000000/D142,0) -> 13740.781 | E146: =IFERROR(E144*1000000/E142,0) -> 12352.493 | F146: =IFERROR(F144*1000000/F142,0) -> 8072.9198 | G146: =IFERROR(G144*1000000/G142,0) -> 5788.5536 | H146: =IFERROR(H144*1000000/H142,0) -> 3917.7146 | I146: =IFERROR(I144*1000000/I142,0) -> 3505.2853 | J146: =IFERROR(J144*1000000/J142,0) -> 2697.4579 | K146: =IFERROR(K144*1000000/K142,0) -> 2578.663 | ... S146: =IFERROR(S144*1000000/S142,0) -> 1567.4334
A147: Memo: Average $/Gbps DTC from curve | D147: =IFERROR(D145*1000000/D143,0) -> 1094104.6 | E147: =IFERROR(E145*1000000/E143,0) -> 1375055.1 | F147: =IFERROR(F145*1000000/F143,0) -> 1672541.1 | G147: =IFERROR(G145*1000000/G143,0) -> 1986770.8 | H147: =IFERROR(H145*1000000/H143,0) -> 2317957.1 | I147: =IFERROR(I145*1000000/I143,0) -> 1363941.4 | J147: =IFERROR(J145*1000000/J143,0) -> 848946.28 | K147: =IFERROR(K145*1000000/K143,0) -> 674279.3 | ... S147: =IFERROR(S145*1000000/S143,0) -> 441734.75
A149: Annual escalator rate (derived, year-row) | D149: 0 | E149: =Assumptions!$B$4+(Assumptions!$B$5-Assumptions!$B$4)*MIN(E$5-1,Assumptions!$B$414-1)/(Assumptions!$B$414-1) -> 0.035 | F149: =Assumptions!$B$4+(Assumptions!$B$5-Assumptions!$B$4)*MIN(F$5-1,Assumptions!$B$414-1)/(Assumptions!$B$414-1) -> 0.033888889 | G149: =Assumptions!$B$4+(Assumptions!$B$5-Assumptions!$B$4)*MIN(G$5-1,Assumptions!$B$414-1)/(Assumptions!$B$414-1) -> 0.032777778 | H149: =Assumptions!$B$4+(Assumptions!$B$5-Assumptions!$B$4)*MIN(H$5-1,Assumptions!$B$414-1)/(Assumptions!$B$414-1) -> 0.031666667 | I149: =Assumptions!$B$4+(Assumptions!$B$5-Assumptions!$B$4)*MIN(I$5-1,Assumptions!$B$414-1)/(Assumptions!$B$414-1) -> 0.030555556 | J149: =Assumptions!$B$4+(Assumptions!$B$5-Assumptions!$B$4)*MIN(J$5-1,Assumptions!$B$414-1)/(Assumptions!$B$414-1) -> 0.029444444 | K149: =Assumptions!$B$4+(Assumptions!$B$5-Assumptions!$B$4)*MIN(K$5-1,Assumptions!$B$414-1)/(Assumptions!$B$414-1) -> 0.028333333 | L149: =Assumptions!$B$4+(Assumptions!$B$5-Assumptions!$B$4)*MIN(L$5-1,Assumptions!$B$414-1)/(Assumptions!$B$414-1) -> 0.027222222 | ... S149: =Assumptions!$B$4+(Assumptions!$B$5-Assumptions!$B$4)*MIN(S$5-1,Assumptions!$B$414-1)/(Assumptions!$B$414-1) -> 0.025
A150: DTC TAM uplift multiplier (Starlink Mobile, derived year-row) | D150: 1 | E150: =1+(Assumptions!$B$418-1)*MIN(E$5,Assumptions!$B$419)/Assumptions!$B$419 -> 1.2142857 | F150: =1+(Assumptions!$B$418-1)*MIN(F$5,Assumptions!$B$419)/Assumptions!$B$419 -> 1.4285714 | G150: =1+(Assumptions!$B$418-1)*MIN(G$5,Assumptions!$B$419)/Assumptions!$B$419 -> 1.6428571 | H150: =1+(Assumptions!$B$418-1)*MIN(H$5,Assumptions!$B$419)/Assumptions!$B$419 -> 1.8571429 | I150: =1+(Assumptions!$B$418-1)*MIN(I$5,Assumptions!$B$419)/Assumptions!$B$419 -> 2.0714286 | J150: =1+(Assumptions!$B$418-1)*MIN(J$5,Assumptions!$B$419)/Assumptions!$B$419 -> 2.2857143 | K150: =1+(Assumptions!$B$418-1)*MIN(K$5,Assumptions!$B$419)/Assumptions!$B$419 -> 2.5 | L150: =1+(Assumptions!$B$418-1)*MIN(L$5,Assumptions!$B$419)/Assumptions!$B$419 -> 2.5 | ... S150: =1+(Assumptions!$B$418-1)*MIN(S$5,Assumptions!$B$419)/Assumptions!$B$419 -> 2.5
A151: BB TAM uplift multiplier (data-intensity, derived year-row) | D151: 1 | E151: =1+(Assumptions!$B$434-1)*MIN(E$5,Assumptions!$B$435)/Assumptions!$B$435 -> 1 | F151: =1+(Assumptions!$B$434-1)*MIN(F$5,Assumptions!$B$435)/Assumptions!$B$435 -> 1 | G151: =1+(Assumptions!$B$434-1)*MIN(G$5,Assumptions!$B$435)/Assumptions!$B$435 -> 1 | H151: =1+(Assumptions!$B$434-1)*MIN(H$5,Assumptions!$B$435)/Assumptions!$B$435 -> 1 | I151: =1+(Assumptions!$B$434-1)*MIN(I$5,Assumptions!$B$435)/Assumptions!$B$435 -> 1 | J151: =1+(Assumptions!$B$434-1)*MIN(J$5,Assumptions!$B$435)/Assumptions!$B$435 -> 1 | K151: =1+(Assumptions!$B$434-1)*MIN(K$5,Assumptions!$B$435)/Assumptions!$B$435 -> 1 | L151: =1+(Assumptions!$B$434-1)*MIN(L$5,Assumptions!$B$435)/Assumptions!$B$435 -> 1 | ... S151: =1+(Assumptions!$B$434-1)*MIN(S$5,Assumptions!$B$435)/Assumptions!$B$435 -> 1

Sheet Starlink
A1: Starlink module — real cohorts + total-bandwidth revenue + full waterfall + 4-line OpEx + per-sat IRR
D4: 2025 | E4: 2026 | F4: 2027 | G4: 2028 | H4: 2029 | I4: 2030 | J4: 2031 | K4: 2032 | L4: 2033 | M4: 2034 | N4: 2035 | O4: 2036 | P4: 2037 | Q4: 2038 | R4: 2039 | S4: 2040
D5: 0 | E5: 1 | F5: 2 | G5: 3 | H5: 4 | I5: 5 | J5: 6 | K5: 7 | L5: 8 | M5: 9 | N5: 10 | O5: 11 | P5: 12 | Q5: 13 | R5: 14 | S5: 15
A10: ▸ ALLOCATOR IN (cross-tab reads)
A11: Starlink BB Revenue from curve ($mm) | D11: {=INDEX('Demand Curves'!$D:$AC, MATCH("Starlink BB Revenue from curve ($mm)", 'Demand Curves'!$A$1:$A$167, 0), COLUMN()-COLUMN($D11)+1)} -> 6721.2206 | E11: {=INDEX('Demand Curves'!$D:$AC, MATCH("Starlink BB Revenue from curve ($mm)", 'Demand Curves'!$A$1:$A$167, 0), COLUMN()-COLUMN($D11)+1)} -> 9347.5765 | F11: {=INDEX('Demand Curves'!$D:$AC, MATCH("Starlink BB Revenue from curve ($mm)", 'Demand Curves'!$A$1:$A$167, 0), COLUMN()-COLUMN($D11)+1)} -> 37555.662 | G11: {=INDEX('Demand Curves'!$D:$AC, MATCH("Starlink BB Revenue from curve ($mm)", 'Demand Curves'!$A$1:$A$167, 0), COLUMN()-COLUMN($D11)+1)} -> 80517.638 | H11: {=INDEX('Demand Curves'!$D:$AC, MATCH("Starlink BB Revenue from curve ($mm)", 'Demand Curves'!$A$1:$A$167, 0), COLUMN()-COLUMN($D11)+1)} -> 133572.61 | I11: {=INDEX('Demand Curves'!$D:$AC, MATCH("Starlink BB Revenue from curve ($mm)", 'Demand Curves'!$A$1:$A$167, 0), COLUMN()-COLUMN($D11)+1)} -> 162366.46 | J11: {=INDEX('Demand Curves'!$D:$AC, MATCH("Starlink BB Revenue from curve ($mm)", 'Demand Curves'!$A$1:$A$167, 0), COLUMN()-COLUMN($D11)+1)} -> 198728.63 | K11: {=INDEX('Demand Curves'!$D:$AC, MATCH("Starlink BB Revenue from curve ($mm)", 'Demand Curves'!$A$1:$A$167, 0), COLUMN()-COLUMN($D11)+1)} -> 212218.52 | ... S11: {=INDEX('Demand Curves'!$D:$AC, MATCH("Starlink BB Revenue from curve ($mm)", 'Demand Curves'!$A$1:$A$167, 0), COLUMN()-COLUMN($D11)+1)} -> 305981.36
A12: Starlink DTC Revenue from curve ($mm) | D12: {=INDEX('Demand Curves'!$D:$AC, MATCH("Starlink DTC Revenue from curve ($mm)", 'Demand Curves'!$A$1:$A$167, 0), COLUMN()-COLUMN($D12)+1)} -> 632.0752 | E12: {=INDEX('Demand Curves'!$D:$AC, MATCH("Starlink DTC Revenue from curve ($mm)", 'Demand Curves'!$A$1:$A$167, 0), COLUMN()-COLUMN($D12)+1)} -> 794.38308 | F12: {=INDEX('Demand Curves'!$D:$AC, MATCH("Starlink DTC Revenue from curve ($mm)", 'Demand Curves'!$A$1:$A$167, 0), COLUMN()-COLUMN($D12)+1)} -> 969.01841 | G12: {=INDEX('Demand Curves'!$D:$AC, MATCH("Starlink DTC Revenue from curve ($mm)", 'Demand Curves'!$A$1:$A$167, 0), COLUMN()-COLUMN($D12)+1)} -> 1291.3436 | H12: {=INDEX('Demand Curves'!$D:$AC, MATCH("Starlink DTC Revenue from curve ($mm)", 'Demand Curves'!$A$1:$A$167, 0), COLUMN()-COLUMN($D12)+1)} -> 6202.8488 | I12: {=INDEX('Demand Curves'!$D:$AC, MATCH("Starlink DTC Revenue from curve ($mm)", 'Demand Curves'!$A$1:$A$167, 0), COLUMN()-COLUMN($D12)+1)} -> 30569.893 | J12: {=INDEX('Demand Curves'!$D:$AC, MATCH("Starlink DTC Revenue from curve ($mm)", 'Demand Curves'!$A$1:$A$167, 0), COLUMN()-COLUMN($D12)+1)} -> 40144.794 | K12: {=INDEX('Demand Curves'!$D:$AC, MATCH("Starlink DTC Revenue from curve ($mm)", 'Demand Curves'!$A$1:$A$167, 0), COLUMN()-COLUMN($D12)+1)} -> 47979.431 | ... S12: {=INDEX('Demand Curves'!$D:$AC, MATCH("Starlink DTC Revenue from curve ($mm)", 'Demand Curves'!$A$1:$A$167, 0), COLUMN()-COLUMN($D12)+1)} -> 60513.713
A13: F9 at-cost rate per launch ($mm) | D13: {=INDEX(Assumptions!$D:$AC, MATCH("F9 at-cost rate per launch ($mm)", Assumptions!$A$1:$A$327, 0), COLUMN()-COLUMN($D13)+1)} -> 20 | E13: {=INDEX(Assumptions!$D:$AC, MATCH("F9 at-cost rate per launch ($mm)", Assumptions!$A$1:$A$327, 0), COLUMN()-COLUMN($D13)+1)} -> 19.6 | F13: {=INDEX(Assumptions!$D:$AC, MATCH("F9 at-cost rate per launch ($mm)", Assumptions!$A$1:$A$327, 0), COLUMN()-COLUMN($D13)+1)} -> 19.208 | G13: {=INDEX(Assumptions!$D:$AC, MATCH("F9 at-cost rate per launch ($mm)", Assumptions!$A$1:$A$327, 0), COLUMN()-COLUMN($D13)+1)} -> 18.824 | H13: {=INDEX(Assumptions!$D:$AC, MATCH("F9 at-cost rate per launch ($mm)", Assumptions!$A$1:$A$327, 0), COLUMN()-COLUMN($D13)+1)} -> 18.447 | I13: {=INDEX(Assumptions!$D:$AC, MATCH("F9 at-cost rate per launch ($mm)", Assumptions!$A$1:$A$327, 0), COLUMN()-COLUMN($D13)+1)} -> 18.078 | J13: {=INDEX(Assumptions!$D:$AC, MATCH("F9 at-cost rate per launch ($mm)", Assumptions!$A$1:$A$327, 0), COLUMN()-COLUMN($D13)+1)} -> 17.717 | K13: {=INDEX(Assumptions!$D:$AC, MATCH("F9 at-cost rate per launch ($mm)", Assumptions!$A$1:$A$327, 0), COLUMN()-COLUMN($D13)+1)} -> 17.363 | ... S13: {=INDEX(Assumptions!$D:$AC, MATCH("F9 at-cost rate per launch ($mm)", Assumptions!$A$1:$A$327, 0), COLUMN()-COLUMN($D13)+1)} -> 14.772
A14: Starship at-cost rate per launch ($mm) | D14: {=INDEX(Assumptions!$D:$AC, MATCH("Starship at-cost rate per launch ($mm)", Assumptions!$A$1:$A$327, 0), COLUMN()-COLUMN($D14)+1)} -> 0 | E14: {=INDEX(Assumptions!$D:$AC, MATCH("Starship at-cost rate per launch ($mm)", Assumptions!$A$1:$A$327, 0), COLUMN()-COLUMN($D14)+1)} -> 0 | F14: {=INDEX(Assumptions!$D:$AC, MATCH("Starship at-cost rate per launch ($mm)", Assumptions!$A$1:$A$327, 0), COLUMN()-COLUMN($D14)+1)} -> 25 | G14: {=INDEX(Assumptions!$D:$AC, MATCH("Starship at-cost rate per launch ($mm)", Assumptions!$A$1:$A$327, 0), COLUMN()-COLUMN($D14)+1)} -> 23 | H14: {=INDEX(Assumptions!$D:$AC, MATCH("Starship at-cost rate per launch ($mm)", Assumptions!$A$1:$A$327, 0), COLUMN()-COLUMN($D14)+1)} -> 21.16 | I14: {=INDEX(Assumptions!$D:$AC, MATCH("Starship at-cost rate per launch ($mm)", Assumptions!$A$1:$A$327, 0), COLUMN()-COLUMN($D14)+1)} -> 19.467 | J14: {=INDEX(Assumptions!$D:$AC, MATCH("Starship at-cost rate per launch ($mm)", Assumptions!$A$1:$A$327, 0), COLUMN()-COLUMN($D14)+1)} -> 17.91 | K14: {=INDEX(Assumptions!$D:$AC, MATCH("Starship at-cost rate per launch ($mm)", Assumptions!$A$1:$A$327, 0), COLUMN()-COLUMN($D14)+1)} -> 16.477 | ... S14: {=INDEX(Assumptions!$D:$AC, MATCH("Starship at-cost rate per launch ($mm)", Assumptions!$A$1:$A$327, 0), COLUMN()-COLUMN($D14)+1)} -> 8.456
A15: Sat operational life L (years) | D15: =INDEX(Assumptions!$B:$B, MATCH("Sat operational life L (years)", Assumptions!$A$1:$A$327, 0)) -> 5 | E15: =INDEX(Assumptions!$B:$B, MATCH("Sat operational life L (years)", Assumptions!$A$1:$A$327, 0)) -> 5 | F15: =INDEX(Assumptions!$B:$B, MATCH("Sat operational life L (years)", Assumptions!$A$1:$A$327, 0)) -> 5 | G15: =INDEX(Assumptions!$B:$B, MATCH("Sat operational life L (years)", Assumptions!$A$1:$A$327, 0)) -> 5 | H15: =INDEX(Assumptions!$B:$B, MATCH("Sat operational life L (years)", Assumptions!$A$1:$A$327, 0)) -> 5 | I15: =INDEX(Assumptions!$B:$B, MATCH("Sat operational life L (years)", Assumptions!$A$1:$A$327, 0)) -> 5 | J15: =INDEX(Assumptions!$B:$B, MATCH("Sat operational life L (years)", Assumptions!$A$1:$A$327, 0)) -> 5 | K15: =INDEX(Assumptions!$B:$B, MATCH("Sat operational life L (years)", Assumptions!$A$1:$A$327, 0)) -> 5 | ... S15: =INDEX(Assumptions!$B:$B, MATCH("Sat operational life L (years)", Assumptions!$A$1:$A$327, 0)) -> 5
A16: Group WACC | D16: =INDEX(Assumptions!$B:$B, MATCH("Group WACC", Assumptions!$A$1:$A$327, 0)) -> 0.1 | E16: =INDEX(Assumptions!$B:$B, MATCH("Group WACC", Assumptions!$A$1:$A$327, 0)) -> 0.1 | F16: =INDEX(Assumptions!$B:$B, MATCH("Group WACC", Assumptions!$A$1:$A$327, 0)) -> 0.1 | G16: =INDEX(Assumptions!$B:$B, MATCH("Group WACC", Assumptions!$A$1:$A$327, 0)) -> 0.1 | H16: =INDEX(Assumptions!$B:$B, MATCH("Group WACC", Assumptions!$A$1:$A$327, 0)) -> 0.1 | I16: =INDEX(Assumptions!$B:$B, MATCH("Group WACC", Assumptions!$A$1:$A$327, 0)) -> 0.1 | J16: =INDEX(Assumptions!$B:$B, MATCH("Group WACC", Assumptions!$A$1:$A$327, 0)) -> 0.1 | K16: =INDEX(Assumptions!$B:$B, MATCH("Group WACC", Assumptions!$A$1:$A$327, 0)) -> 0.1 | ... S16: =INDEX(Assumptions!$B:$B, MATCH("Group WACC", Assumptions!$A$1:$A$327, 0)) -> 0.1
A18: Starlink R&D as % of revenue (frac) | D18: =INDEX(Assumptions!$B:$B, MATCH("Starlink R&D: start % of (Starlink+Starshield) rev", Assumptions!$A$1:$A$327, 0)) -> 0.053 | E18: =INDEX(Assumptions!$B:$B, MATCH("Starlink R&D: start % of (Starlink+Starshield) rev", Assumptions!$A$1:$A$327, 0)) -> 0.053 | F18: =INDEX(Assumptions!$B:$B, MATCH("Starlink R&D: start % of (Starlink+Starshield) rev", Assumptions!$A$1:$A$327, 0)) -> 0.053 | G18: =INDEX(Assumptions!$B:$B, MATCH("Starlink R&D: start % of (Starlink+Starshield) rev", Assumptions!$A$1:$A$327, 0)) -> 0.053 | H18: =INDEX(Assumptions!$B:$B, MATCH("Starlink R&D: start % of (Starlink+Starshield) rev", Assumptions!$A$1:$A$327, 0)) -> 0.053 | I18: =INDEX(Assumptions!$B:$B, MATCH("Starlink R&D: start % of (Starlink+Starshield) rev", Assumptions!$A$1:$A$327, 0)) -> 0.053 | J18: =INDEX(Assumptions!$B:$B, MATCH("Starlink R&D: start % of (Starlink+Starshield) rev", Assumptions!$A$1:$A$327, 0)) -> 0.053 | K18: =INDEX(Assumptions!$B:$B, MATCH("Starlink R&D: start % of (Starlink+Starshield) rev", Assumptions!$A$1:$A$327, 0)) -> 0.053 | ... S18: =INDEX(Assumptions!$B:$B, MATCH("Starlink R&D: start % of (Starlink+Starshield) rev", Assumptions!$A$1:$A$327, 0)) -> 0.053
A19: Starlink module allocated cash ($mm/yr): live from Cash Allocation Engine | D19: =INDEX('Cash Allocation Engine'!D:D,MATCH("Allocated cash to Starlink ($mm)",'Cash Allocation Engine'!$A$1:$A$91,0)) -> 0 | E19: =INDEX('Cash Allocation Engine'!E:E,MATCH("Allocated cash to Starlink ($mm)",'Cash Allocation Engine'!$A$1:$A$91,0)) -> 25727.691 | F19: =INDEX('Cash Allocation Engine'!F:F,MATCH("Allocated cash to Starlink ($mm)",'Cash Allocation Engine'!$A$1:$A$91,0)) -> 48421.835 | G19: =INDEX('Cash Allocation Engine'!G:G,MATCH("Allocated cash to Starlink ($mm)",'Cash Allocation Engine'!$A$1:$A$91,0)) -> 35963.545 | H19: =INDEX('Cash Allocation Engine'!H:H,MATCH("Allocated cash to Starlink ($mm)",'Cash Allocation Engine'!$A$1:$A$91,0)) -> 33987.007 | I19: =INDEX('Cash Allocation Engine'!I:I,MATCH("Allocated cash to Starlink ($mm)",'Cash Allocation Engine'!$A$1:$A$91,0)) -> 47929.441 | J19: =INDEX('Cash Allocation Engine'!J:J,MATCH("Allocated cash to Starlink ($mm)",'Cash Allocation Engine'!$A$1:$A$91,0)) -> 71941.235 | K19: =INDEX('Cash Allocation Engine'!K:K,MATCH("Allocated cash to Starlink ($mm)",'Cash Allocation Engine'!$A$1:$A$91,0)) -> 48539.514 | L19: =INDEX('Cash Allocation Engine'!L:L,MATCH("Allocated cash to Starlink ($mm)",'Cash Allocation Engine'!$A$1:$A$91,0)) -> 56781.092 | M19: =INDEX('Cash Allocation Engine'!M:M,MATCH("Allocated cash to Starlink ($mm)",'Cash Allocation Engine'!$A$1:$A$91,0)) -> 79229.122 | N19: =INDEX('Cash Allocation Engine'!N:N,MATCH("Allocated cash to Starlink ($mm)",'Cash Allocation Engine'!$A$1:$A$91,0)) -> 91052.019 | O19: =INDEX('Cash Allocation Engine'!O:O,MATCH("Allocated cash to Starlink ($mm)",'Cash Allocation Engine'!$A$1:$A$91,0)) -> 123606.93 | P19: =INDEX('Cash Allocation Engine'!P:P,MATCH("Allocated cash to Starlink ($mm)",'Cash Allocation Engine'!$A$1:$A$91,0)) -> 106796.38 | Q19: =INDEX('Cash Allocation Engine'!Q:Q,MATCH("Allocated cash to Starlink ($mm)",'Cash Allocation Engine'!$A$1:$A$91,0)) -> 57814.378 | R19: =INDEX('Cash Allocation Engine'!R:R,MATCH("Allocated cash to Starlink ($mm)",'Cash Allocation Engine'!$A$1:$A$91,0)) -> 39109.523 | S19: =INDEX('Cash Allocation Engine'!S:S,MATCH("Allocated cash to Starlink ($mm)",'Cash Allocation Engine'!$A$1:$A$91,0)) -> 41495.9
A20: Starlink deployment 2025 anchor (sats) | D20: =INDEX(Assumptions!$B:$B, MATCH("Starlink deployment 2025 anchor (sats)", Assumptions!$A$1:$A$327, 0)) -> 3840
A21: Sat utilization (frac) | D21: =INDEX(Assumptions!$B:$B, MATCH("Sat utilization (frac)", Assumptions!$A$1:$A$327, 0)) -> 0.7 | E21: =INDEX(Assumptions!$B:$B, MATCH("Sat utilization (frac)", Assumptions!$A$1:$A$327, 0)) -> 0.7 | F21: =INDEX(Assumptions!$B:$B, MATCH("Sat utilization (frac)", Assumptions!$A$1:$A$327, 0)) -> 0.7 | G21: =INDEX(Assumptions!$B:$B, MATCH("Sat utilization (frac)", Assumptions!$A$1:$A$327, 0)) -> 0.7 | H21: =INDEX(Assumptions!$B:$B, MATCH("Sat utilization (frac)", Assumptions!$A$1:$A$327, 0)) -> 0.7 | I21: =INDEX(Assumptions!$B:$B, MATCH("Sat utilization (frac)", Assumptions!$A$1:$A$327, 0)) -> 0.7 | J21: =INDEX(Assumptions!$B:$B, MATCH("Sat utilization (frac)", Assumptions!$A$1:$A$327, 0)) -> 0.7 | K21: =INDEX(Assumptions!$B:$B, MATCH("Sat utilization (frac)", Assumptions!$A$1:$A$327, 0)) -> 0.7 | ... S21: =INDEX(Assumptions!$B:$B, MATCH("Sat utilization (frac)", Assumptions!$A$1:$A$327, 0)) -> 0.7
A22: Starship operational year | D22: =INDEX(Assumptions!$B:$B, MATCH("Starship operational year", Assumptions!$A$1:$A$327, 0)) -> 2026
A23: F9 launches V2-Starlink final year | D23: =INDEX(Assumptions!$B:$B, MATCH("F9 launches V2-Starlink final year", Assumptions!$A$1:$A$327, 0)) -> 2026
A24: F9 payload per launch (kg) | D24: {=INDEX('Vehicle Build'!$D:$AC, MATCH("F9 payload per launch (kg)", 'Vehicle Build'!$A$1:$A$119, 0), COLUMN()-COLUMN($D24)+1)} -> 22800 | E24: {=INDEX('Vehicle Build'!$D:$AC, MATCH("F9 payload per launch (kg)", 'Vehicle Build'!$A$1:$A$119, 0), COLUMN()-COLUMN($D24)+1)} -> 22800 | F24: {=INDEX('Vehicle Build'!$D:$AC, MATCH("F9 payload per launch (kg)", 'Vehicle Build'!$A$1:$A$119, 0), COLUMN()-COLUMN($D24)+1)} -> 22800 | G24: {=INDEX('Vehicle Build'!$D:$AC, MATCH("F9 payload per launch (kg)", 'Vehicle Build'!$A$1:$A$119, 0), COLUMN()-COLUMN($D24)+1)} -> 22800 | H24: {=INDEX('Vehicle Build'!$D:$AC, MATCH("F9 payload per launch (kg)", 'Vehicle Build'!$A$1:$A$119, 0), COLUMN()-COLUMN($D24)+1)} -> 22800 | I24: {=INDEX('Vehicle Build'!$D:$AC, MATCH("F9 payload per launch (kg)", 'Vehicle Build'!$A$1:$A$119, 0), COLUMN()-COLUMN($D24)+1)} -> 22800 | J24: {=INDEX('Vehicle Build'!$D:$AC, MATCH("F9 payload per launch (kg)", 'Vehicle Build'!$A$1:$A$119, 0), COLUMN()-COLUMN($D24)+1)} -> 22800 | K24: {=INDEX('Vehicle Build'!$D:$AC, MATCH("F9 payload per launch (kg)", 'Vehicle Build'!$A$1:$A$119, 0), COLUMN()-COLUMN($D24)+1)} -> 22800 | ... S24: {=INDEX('Vehicle Build'!$D:$AC, MATCH("F9 payload per launch (kg)", 'Vehicle Build'!$A$1:$A$119, 0), COLUMN()-COLUMN($D24)+1)} -> 22800
A25: Starship payload per launch (kg) | D25: {=INDEX('Vehicle Build'!$D:$AC, MATCH("Starship payload per launch (kg)", 'Vehicle Build'!$A$1:$A$119, 0), COLUMN()-COLUMN($D25)+1)} -> 100000 | E25: {=INDEX('Vehicle Build'!$D:$AC, MATCH("Starship payload per launch (kg)", 'Vehicle Build'!$A$1:$A$119, 0), COLUMN()-COLUMN($D25)+1)} -> 114869.84 | F25: {=INDEX('Vehicle Build'!$D:$AC, MATCH("Starship payload per launch (kg)", 'Vehicle Build'!$A$1:$A$119, 0), COLUMN()-COLUMN($D25)+1)} -> 131950.79 | G25: {=INDEX('Vehicle Build'!$D:$AC, MATCH("Starship payload per launch (kg)", 'Vehicle Build'!$A$1:$A$119, 0), COLUMN()-COLUMN($D25)+1)} -> 151571.66 | H25: {=INDEX('Vehicle Build'!$D:$AC, MATCH("Starship payload per launch (kg)", 'Vehicle Build'!$A$1:$A$119, 0), COLUMN()-COLUMN($D25)+1)} -> 174110.11 | I25: {=INDEX('Vehicle Build'!$D:$AC, MATCH("Starship payload per launch (kg)", 'Vehicle Build'!$A$1:$A$119, 0), COLUMN()-COLUMN($D25)+1)} -> 200000 | J25: {=INDEX('Vehicle Build'!$D:$AC, MATCH("Starship payload per launch (kg)", 'Vehicle Build'!$A$1:$A$119, 0), COLUMN()-COLUMN($D25)+1)} -> 200000 | K25: {=INDEX('Vehicle Build'!$D:$AC, MATCH("Starship payload per launch (kg)", 'Vehicle Build'!$A$1:$A$119, 0), COLUMN()-COLUMN($D25)+1)} -> 200000 | ... S25: {=INDEX('Vehicle Build'!$D:$AC, MATCH("Starship payload per launch (kg)", 'Vehicle Build'!$A$1:$A$119, 0), COLUMN()-COLUMN($D25)+1)} -> 200000
A27: ▸ CONSTELLATION BUILD (real cohorts → total bandwidth)
A28: V2 launch window active (1/0) | D28: =IF(D$4<=$D$23, 1, 0) -> 1 | E28: =IF(E$4<=$D$23, 1, 0) -> 1 | F28: =IF(F$4<=$D$23, 1, 0) -> 0 | G28: =IF(G$4<=$D$23, 1, 0) -> 0 | H28: =IF(H$4<=$D$23, 1, 0) -> 0 | I28: =IF(I$4<=$D$23, 1, 0) -> 0 | J28: =IF(J$4<=$D$23, 1, 0) -> 0 | K28: =IF(K$4<=$D$23, 1, 0) -> 0 | ... S28: =IF(S$4<=$D$23, 1, 0) -> 0
A29: V3 deployment active (1/0) | D29: =IF(D$4>=$D$22+1, 1, 0) -> 0 | E29: =IF(E$4>=$D$22+1, 1, 0) -> 0 | F29: =IF(F$4>=$D$22+1, 1, 0) -> 1 | G29: =IF(G$4>=$D$22+1, 1, 0) -> 1 | H29: =IF(H$4>=$D$22+1, 1, 0) -> 1 | I29: =IF(I$4>=$D$22+1, 1, 0) -> 1 | J29: =IF(J$4>=$D$22+1, 1, 0) -> 1 | K29: =IF(K$4>=$D$22+1, 1, 0) -> 1 | ... S29: =IF(S$4>=$D$22+1, 1, 0) -> 1
A31: Total new Starlink deployment (sats/yr) | D31: =SUM(D32:D35) -> 3840 | E31: =SUM(E32:E35) -> 3120 | F31: =SUM(F32:F35) -> 3918.7353 | G31: =SUM(G32:G35) -> 9497.38 | H31: =SUM(H32:H35) -> 22947.351 | I31: =SUM(I32:I35) -> 35068.944 | J31: =SUM(J32:J35) -> 55854.425 | K31: =SUM(K32:K35) -> 39606.221 | ... S31: =SUM(S32:S35) -> 39441.628
A32: New V2 BB deployment (sats/yr) | D32: =IF(D$4=2025, $D$20, IF(D$28=1, D203, 0)) -> 3840 | E32: =IF(E$4=2025, $D$20, IF(E$28=1, E203, 0)) -> 3120 | F32: =IF(F$4=2025, $D$20, IF(F$28=1, F203, 0)) -> 0 | G32: =IF(G$4=2025, $D$20, IF(G$28=1, G203, 0)) -> 0 | H32: =IF(H$4=2025, $D$20, IF(H$28=1, H203, 0)) -> 0 | I32: =IF(I$4=2025, $D$20, IF(I$28=1, I203, 0)) -> 0 | J32: =IF(J$4=2025, $D$20, IF(J$28=1, J203, 0)) -> 0 | K32: =IF(K$4=2025, $D$20, IF(K$28=1, K203, 0)) -> 0 | ... S32: =IF(S$4=2025, $D$20, IF(S$28=1, S203, 0)) -> 0
A33: New V2 DTC deployment (sats/yr) | D33: =0 -> 0 | E33: =0 -> 0 | F33: =0 -> 0 | G33: =0 -> 0 | H33: =0 -> 0 | I33: =0 -> 0 | J33: =0 -> 0 | K33: =0 -> 0 | ... S33: =0 -> 0
A34: New V3 BB deployment (sats/yr) | D34: =IF(D$29=1, D203, 0) -> 0 | E34: =IF(E$29=1, E203, 0) -> 0 | F34: =IF(F$29=1, F203, 0) -> 3916.8544 | G34: =IF(G$29=1, G203, 0) -> 9417.3322 | H34: =IF(H$29=1, H203, 0) -> 20322.768 | I34: =IF(I$29=1, I203, 0) -> 12363.994 | J34: =IF(J$29=1, J203, 0) -> 27651.611 | K34: =IF(K$29=1, K203, 0) -> 12542.183 | ... S34: =IF(S$29=1, S203, 0) -> 20227.328
A35: New V3 DTC deployment (sats/yr) | D35: =IF(D$29=1, D204, 0) -> 0 | E35: =IF(E$29=1, E204, 0) -> 0 | F35: =IF(F$29=1, F204, 0) -> 1.8809254 | G35: =IF(G$29=1, G204, 0) -> 80.047746 | H35: =IF(H$29=1, H204, 0) -> 2624.5828 | I35: =IF(I$29=1, I204, 0) -> 22704.949 | J35: =IF(J$29=1, J204, 0) -> 28202.814 | K35: =IF(K$29=1, K204, 0) -> 27064.038 | ... S35: =IF(S$29=1, S204, 0) -> 19214.3
A36: New Starshield deployment (sats/yr) | D36: =$D$31*0.12 -> 460.8 | E36: =$D$31*0.12 -> 460.8 | F36: =$D$31*0.12 -> 460.8 | G36: =$D$31*0.12 -> 460.8 | H36: =$D$31*0.12 -> 460.8 | I36: =$D$31*0.12 -> 460.8 | J36: =$D$31*0.12 -> 460.8 | K36: =$D$31*0.12 -> 460.8 | ... S36: =$D$31*0.12 -> 460.8
A37: Blended new-sat CapEx slug ($mm/sat): MEMO ONLY (feeds CAE R88 cap; no longer drives deployment) | D37: =IF(D$29=1, INDEX(Assumptions!$B:$B,MATCH("V3 BB share of new deployment (frac)",Assumptions!$A$1:$A$327,0))*D125 + INDEX(Assumptions!$B:$B,MATCH("V3 DTC share of new deployment (frac)",Assumptions!$A$1:$A$327,0))*D131, INDEX(Assumptions!$B:$B,MATCH("V2 BB share of new deployment (frac)",Assumptions!$A$1:$A$327,0))*D113 + INDEX(Assumptions!$B:$B,MATCH("V2 DTC share of new deployment (frac)",Assumptions!$A$1:$A$327,0))*D119 + 0.12*D137) -> 1.1597909 | E37: =IF(E$29=1, INDEX(Assumptions!$B:$B,MATCH("V3 BB share of new deployment (frac)",Assumptions!$A$1:$A$327,0))*E125 + INDEX(Assumptions!$B:$B,MATCH("V3 DTC share of new deployment (frac)",Assumptions!$A$1:$A$327,0))*E131, INDEX(Assumptions!$B:$B,MATCH("V2 BB share of new deployment (frac)",Assumptions!$A$1:$A$327,0))*E113 + INDEX(Assumptions!$B:$B,MATCH("V2 DTC share of new deployment (frac)",Assumptions!$A$1:$A$327,0))*E119 + 0.12*E137) -> 1.1722996 | F37: =IF(F$29=1, INDEX(Assumptions!$B:$B,MATCH("V3 BB share of new deployment (frac)",Assumptions!$A$1:$A$327,0))*F125 + INDEX(Assumptions!$B:$B,MATCH("V3 DTC share of new deployment (frac)",Assumptions!$A$1:$A$327,0))*F131, INDEX(Assumptions!$B:$B,MATCH("V2 BB share of new deployment (frac)",Assumptions!$A$1:$A$327,0))*F113 + INDEX(Assumptions!$B:$B,MATCH("V2 DTC share of new deployment (frac)",Assumptions!$A$1:$A$327,0))*F119 + 0.12*F137) -> 1.6698542 | G37: =IF(G$29=1, INDEX(Assumptions!$B:$B,MATCH("V3 BB share of new deployment (frac)",Assumptions!$A$1:$A$327,0))*G125 + INDEX(Assumptions!$B:$B,MATCH("V3 DTC share of new deployment (frac)",Assumptions!$A$1:$A$327,0))*G131, INDEX(Assumptions!$B:$B,MATCH("V2 BB share of new deployment (frac)",Assumptions!$A$1:$A$327,0))*G113 + INDEX(Assumptions!$B:$B,MATCH("V2 DTC share of new deployment (frac)",Assumptions!$A$1:$A$327,0))*G119 + 0.12*G137) -> 1.5893285 | H37: =IF(H$29=1, INDEX(Assumptions!$B:$B,MATCH("V3 BB share of new deployment (frac)",Assumptions!$A$1:$A$327,0))*H125 + INDEX(Assumptions!$B:$B,MATCH("V3 DTC share of new deployment (frac)",Assumptions!$A$1:$A$327,0))*H131, INDEX(Assumptions!$B:$B,MATCH("V2 BB share of new deployment (frac)",Assumptions!$A$1:$A$327,0))*H113 + INDEX(Assumptions!$B:$B,MATCH("V2 DTC share of new deployment (frac)",Assumptions!$A$1:$A$327,0))*H119 + 0.12*H137) -> 1.4810863 | I37: =IF(I$29=1, INDEX(Assumptions!$B:$B,MATCH("V3 BB share of new deployment (frac)",Assumptions!$A$1:$A$327,0))*I125 + INDEX(Assumptions!$B:$B,MATCH("V3 DTC share of new deployment (frac)",Assumptions!$A$1:$A$327,0))*I131, INDEX(Assumptions!$B:$B,MATCH("V2 BB share of new deployment (frac)",Assumptions!$A$1:$A$327,0))*I113 + INDEX(Assumptions!$B:$B,MATCH("V2 DTC share of new deployment (frac)",Assumptions!$A$1:$A$327,0))*I119 + 0.12*I137) -> 1.3667204 | J37: =IF(J$29=1, INDEX(Assumptions!$B:$B,MATCH("V3 BB share of new deployment (frac)",Assumptions!$A$1:$A$327,0))*J125 + INDEX(Assumptions!$B:$B,MATCH("V3 DTC share of new deployment (frac)",Assumptions!$A$1:$A$327,0))*J131, INDEX(Assumptions!$B:$B,MATCH("V2 BB share of new deployment (frac)",Assumptions!$A$1:$A$327,0))*J113 + INDEX(Assumptions!$B:$B,MATCH("V2 DTC share of new deployment (frac)",Assumptions!$A$1:$A$327,0))*J119 + 0.12*J137) -> 1.2880132 | K37: =IF(K$29=1, INDEX(Assumptions!$B:$B,MATCH("V3 BB share of new deployment (frac)",Assumptions!$A$1:$A$327,0))*K125 + INDEX(Assumptions!$B:$B,MATCH("V3 DTC share of new deployment (frac)",Assumptions!$A$1:$A$327,0))*K131, INDEX(Assumptions!$B:$B,MATCH("V2 BB share of new deployment (frac)",Assumptions!$A$1:$A$327,0))*K113 + INDEX(Assumptions!$B:$B,MATCH("V2 DTC share of new deployment (frac)",Assumptions!$A$1:$A$327,0))*K119 + 0.12*K137) -> 1.2255528 | ... S37: =IF(S$29=1, INDEX(Assumptions!$B:$B,MATCH("V3 BB share of new deployment (frac)",Assumptions!$A$1:$A$327,0))*S125 + INDEX(Assumptions!$B:$B,MATCH("V3 DTC share of new deployment (frac)",Assumptions!$A$1:$A$327,0))*S131, INDEX(Assumptions!$B:$B,MATCH("V2 BB share of new deployment (frac)",Assumptions!$A$1:$A$327,0))*S113 + INDEX(Assumptions!$B:$B,MATCH("V2 DTC share of new deployment (frac)",Assumptions!$A$1:$A$327,0))*S119 + 0.12*S137) -> 0.99762931
A38: Demand-saturation deployment headroom (sats) | D38: =MAX(0,(INDEX('Demand Curves'!$B:$B,MATCH("BB Q breakpoint #56 (Gbps)",'Demand Curves'!$A$1:$A$167,0))-D176)/INDEX(Assumptions!$B:$B,MATCH("V3 BB Gbps per sat",Assumptions!$A$1:$A$327,0))) -> 249585.86 | E38: =MAX(0,(INDEX('Demand Curves'!$B:$B,MATCH("BB Q breakpoint #56 (Gbps)",'Demand Curves'!$A$1:$A$167,0))-D176)/INDEX(Assumptions!$B:$B,MATCH("V3 BB Gbps per sat",Assumptions!$A$1:$A$327,0))) -> 249585.86 | F38: =MAX(0,(INDEX('Demand Curves'!$B:$B,MATCH("BB Q breakpoint #56 (Gbps)",'Demand Curves'!$A$1:$A$167,0))-E176)/INDEX(Assumptions!$B:$B,MATCH("V3 BB Gbps per sat",Assumptions!$A$1:$A$327,0))) -> 249286.34 | G38: =MAX(0,(INDEX('Demand Curves'!$B:$B,MATCH("BB Q breakpoint #56 (Gbps)",'Demand Curves'!$A$1:$A$167,0))-F176)/INDEX(Assumptions!$B:$B,MATCH("V3 BB Gbps per sat",Assumptions!$A$1:$A$327,0))) -> 245369.48 | H38: =MAX(0,(INDEX('Demand Curves'!$B:$B,MATCH("BB Q breakpoint #56 (Gbps)",'Demand Curves'!$A$1:$A$167,0))-G176)/INDEX(Assumptions!$B:$B,MATCH("V3 BB Gbps per sat",Assumptions!$A$1:$A$327,0))) -> 236090.2 | I38: =MAX(0,(INDEX('Demand Curves'!$B:$B,MATCH("BB Q breakpoint #56 (Gbps)",'Demand Curves'!$A$1:$A$167,0))-H176)/INDEX(Assumptions!$B:$B,MATCH("V3 BB Gbps per sat",Assumptions!$A$1:$A$327,0))) -> 215905.48 | J38: =MAX(0,(INDEX('Demand Curves'!$B:$B,MATCH("BB Q breakpoint #56 (Gbps)",'Demand Curves'!$A$1:$A$167,0))-I176)/INDEX(Assumptions!$B:$B,MATCH("V3 BB Gbps per sat",Assumptions!$A$1:$A$327,0))) -> 203679.53 | K38: =MAX(0,(INDEX('Demand Curves'!$B:$B,MATCH("BB Q breakpoint #56 (Gbps)",'Demand Curves'!$A$1:$A$167,0))-J176)/INDEX(Assumptions!$B:$B,MATCH("V3 BB Gbps per sat",Assumptions!$A$1:$A$327,0))) -> 176327.44 | L38: =MAX(0,(INDEX('Demand Curves'!$B:$B,MATCH("BB Q breakpoint #56 (Gbps)",'Demand Curves'!$A$1:$A$167,0))-K176)/INDEX(Assumptions!$B:$B,MATCH("V3 BB Gbps per sat",Assumptions!$A$1:$A$327,0))) -> 167702.11 | ... S38: =MAX(0,(INDEX('Demand Curves'!$B:$B,MATCH("BB Q breakpoint #56 (Gbps)",'Demand Curves'!$A$1:$A$167,0))-R176)/INDEX(Assumptions!$B:$B,MATCH("V3 BB Gbps per sat",Assumptions!$A$1:$A$327,0))) -> 41594.508
A39: BB FLEET (active sats by cohort)
A40: Legacy V1 active sats | D40: =INDEX(Assumptions!$B:$B,MATCH("Legacy V1 active sats end-2025",Assumptions!$A$1:$A$327,0)) -> 866 | E40: =MAX(0, D40 - IF(AND(E$4>=INDEX(Assumptions!$B:$B,MATCH("Legacy V1 base deorbit start year",Assumptions!$A$1:$A$327,0)),E$4<=INDEX(Assumptions!$B:$B,MATCH("Legacy V1 base deorbit end year",Assumptions!$A$1:$A$327,0))),$D$40/(INDEX(Assumptions!$B:$B,MATCH("Legacy V1 base deorbit end year",Assumptions!$A$1:$A$327,0))-INDEX(Assumptions!$B:$B,MATCH("Legacy V1 base deorbit start year",Assumptions!$A$1:$A$327,0))+1),0)) -> 0 | F40: =MAX(0, E40 - IF(AND(F$4>=INDEX(Assumptions!$B:$B,MATCH("Legacy V1 base deorbit start year",Assumptions!$A$1:$A$327,0)),F$4<=INDEX(Assumptions!$B:$B,MATCH("Legacy V1 base deorbit end year",Assumptions!$A$1:$A$327,0))),$D$40/(INDEX(Assumptions!$B:$B,MATCH("Legacy V1 base deorbit end year",Assumptions!$A$1:$A$327,0))-INDEX(Assumptions!$B:$B,MATCH("Legacy V1 base deorbit start year",Assumptions!$A$1:$A$327,0))+1),0)) -> 0 | G40: =MAX(0, F40 - IF(AND(G$4>=INDEX(Assumptions!$B:$B,MATCH("Legacy V1 base deorbit start year",Assumptions!$A$1:$A$327,0)),G$4<=INDEX(Assumptions!$B:$B,MATCH("Legacy V1 base deorbit end year",Assumptions!$A$1:$A$327,0))),$D$40/(INDEX(Assumptions!$B:$B,MATCH("Legacy V1 base deorbit end year",Assumptions!$A$1:$A$327,0))-INDEX(Assumptions!$B:$B,MATCH("Legacy V1 base deorbit start year",Assumptions!$A$1:$A$327,0))+1),0)) -> 0 | H40: =MAX(0, G40 - IF(AND(H$4>=INDEX(Assumptions!$B:$B,MATCH("Legacy V1 base deorbit start year",Assumptions!$A$1:$A$327,0)),H$4<=INDEX(Assumptions!$B:$B,MATCH("Legacy V1 base deorbit end year",Assumptions!$A$1:$A$327,0))),$D$40/(INDEX(Assumptions!$B:$B,MATCH("Legacy V1 base deorbit end year",Assumptions!$A$1:$A$327,0))-INDEX(Assumptions!$B:$B,MATCH("Legacy V1 base deorbit start year",Assumptions!$A$1:$A$327,0))+1),0)) -> 0 | I40: =MAX(0, H40 - IF(AND(I$4>=INDEX(Assumptions!$B:$B,MATCH("Legacy V1 base deorbit start year",Assumptions!$A$1:$A$327,0)),I$4<=INDEX(Assumptions!$B:$B,MATCH("Legacy V1 base deorbit end year",Assumptions!$A$1:$A$327,0))),$D$40/(INDEX(Assumptions!$B:$B,MATCH("Legacy V1 base deorbit end year",Assumptions!$A$1:$A$327,0))-INDEX(Assumptions!$B:$B,MATCH("Legacy V1 base deorbit start year",Assumptions!$A$1:$A$327,0))+1),0)) -> 0 | J40: =MAX(0, I40 - IF(AND(J$4>=INDEX(Assumptions!$B:$B,MATCH("Legacy V1 base deorbit start year",Assumptions!$A$1:$A$327,0)),J$4<=INDEX(Assumptions!$B:$B,MATCH("Legacy V1 base deorbit end year",Assumptions!$A$1:$A$327,0))),$D$40/(INDEX(Assumptions!$B:$B,MATCH("Legacy V1 base deorbit end year",Assumptions!$A$1:$A$327,0))-INDEX(Assumptions!$B:$B,MATCH("Legacy V1 base deorbit start year",Assumptions!$A$1:$A$327,0))+1),0)) -> 0 | K40: =MAX(0, J40 - IF(AND(K$4>=INDEX(Assumptions!$B:$B,MATCH("Legacy V1 base deorbit start year",Assumptions!$A$1:$A$327,0)),K$4<=INDEX(Assumptions!$B:$B,MATCH("Legacy V1 base deorbit end year",Assumptions!$A$1:$A$327,0))),$D$40/(INDEX(Assumptions!$B:$B,MATCH("Legacy V1 base deorbit end year",Assumptions!$A$1:$A$327,0))-INDEX(Assumptions!$B:$B,MATCH("Legacy V1 base deorbit start year",Assumptions!$A$1:$A$327,0))+1),0)) -> 0 | L40: =MAX(0, K40 - IF(AND(L$4>=INDEX(Assumptions!$B:$B,MATCH("Legacy V1 base deorbit start year",Assumptions!$A$1:$A$327,0)),L$4<=INDEX(Assumptions!$B:$B,MATCH("Legacy V1 base deorbit end year",Assumptions!$A$1:$A$327,0))),$D$40/(INDEX(Assumptions!$B:$B,MATCH("Legacy V1 base deorbit end year",Assumptions!$A$1:$A$327,0))-INDEX(Assumptions!$B:$B,MATCH("Legacy V1 base deorbit start year",Assumptions!$A$1:$A$327,0))+1),0)) -> 0 | ... S40: =MAX(0, R40 - IF(AND(S$4>=INDEX(Assumptions!$B:$B,MATCH("Legacy V1 base deorbit start year",Assumptions!$A$1:$A$327,0)),S$4<=INDEX(Assumptions!$B:$B,MATCH("Legacy V1 base deorbit end year",Assumptions!$A$1:$A$327,0))),$D$40/(INDEX(Assumptions!$B:$B,MATCH("Legacy V1 base deorbit end year",Assumptions!$A$1:$A$327,0))-INDEX(Assumptions!$B:$B,MATCH("Legacy V1 base deorbit start year",Assumptions!$A$1:$A$327,0))+1),0)) -> 0
A41: Legacy V1.5 active sats | D41: =INDEX(Assumptions!$B:$B,MATCH("Legacy V1.5 active sats end-2025",Assumptions!$A$1:$A$327,0)) -> 2692 | E41: =MAX(0, D41 - IF(AND(E$4>=INDEX(Assumptions!$B:$B,MATCH("Legacy V1.5 base deorbit start year",Assumptions!$A$1:$A$327,0)),E$4<=INDEX(Assumptions!$B:$B,MATCH("Legacy V1.5 base deorbit end year",Assumptions!$A$1:$A$327,0))),$D$41/(INDEX(Assumptions!$B:$B,MATCH("Legacy V1.5 base deorbit end year",Assumptions!$A$1:$A$327,0))-INDEX(Assumptions!$B:$B,MATCH("Legacy V1.5 base deorbit start year",Assumptions!$A$1:$A$327,0))+1),0)) -> 1794.6667 | F41: =MAX(0, E41 - IF(AND(F$4>=INDEX(Assumptions!$B:$B,MATCH("Legacy V1.5 base deorbit start year",Assumptions!$A$1:$A$327,0)),F$4<=INDEX(Assumptions!$B:$B,MATCH("Legacy V1.5 base deorbit end year",Assumptions!$A$1:$A$327,0))),$D$41/(INDEX(Assumptions!$B:$B,MATCH("Legacy V1.5 base deorbit end year",Assumptions!$A$1:$A$327,0))-INDEX(Assumptions!$B:$B,MATCH("Legacy V1.5 base deorbit start year",Assumptions!$A$1:$A$327,0))+1),0)) -> 897.33333 | G41: =MAX(0, F41 - IF(AND(G$4>=INDEX(Assumptions!$B:$B,MATCH("Legacy V1.5 base deorbit start year",Assumptions!$A$1:$A$327,0)),G$4<=INDEX(Assumptions!$B:$B,MATCH("Legacy V1.5 base deorbit end year",Assumptions!$A$1:$A$327,0))),$D$41/(INDEX(Assumptions!$B:$B,MATCH("Legacy V1.5 base deorbit end year",Assumptions!$A$1:$A$327,0))-INDEX(Assumptions!$B:$B,MATCH("Legacy V1.5 base deorbit start year",Assumptions!$A$1:$A$327,0))+1),0)) -> 0 | H41: =MAX(0, G41 - IF(AND(H$4>=INDEX(Assumptions!$B:$B,MATCH("Legacy V1.5 base deorbit start year",Assumptions!$A$1:$A$327,0)),H$4<=INDEX(Assumptions!$B:$B,MATCH("Legacy V1.5 base deorbit end year",Assumptions!$A$1:$A$327,0))),$D$41/(INDEX(Assumptions!$B:$B,MATCH("Legacy V1.5 base deorbit end year",Assumptions!$A$1:$A$327,0))-INDEX(Assumptions!$B:$B,MATCH("Legacy V1.5 base deorbit start year",Assumptions!$A$1:$A$327,0))+1),0)) -> 0 | I41: =MAX(0, H41 - IF(AND(I$4>=INDEX(Assumptions!$B:$B,MATCH("Legacy V1.5 base deorbit start year",Assumptions!$A$1:$A$327,0)),I$4<=INDEX(Assumptions!$B:$B,MATCH("Legacy V1.5 base deorbit end year",Assumptions!$A$1:$A$327,0))),$D$41/(INDEX(Assumptions!$B:$B,MATCH("Legacy V1.5 base deorbit end year",Assumptions!$A$1:$A$327,0))-INDEX(Assumptions!$B:$B,MATCH("Legacy V1.5 base deorbit start year",Assumptions!$A$1:$A$327,0))+1),0)) -> 0 | J41: =MAX(0, I41 - IF(AND(J$4>=INDEX(Assumptions!$B:$B,MATCH("Legacy V1.5 base deorbit start year",Assumptions!$A$1:$A$327,0)),J$4<=INDEX(Assumptions!$B:$B,MATCH("Legacy V1.5 base deorbit end year",Assumptions!$A$1:$A$327,0))),$D$41/(INDEX(Assumptions!$B:$B,MATCH("Legacy V1.5 base deorbit end year",Assumptions!$A$1:$A$327,0))-INDEX(Assumptions!$B:$B,MATCH("Legacy V1.5 base deorbit start year",Assumptions!$A$1:$A$327,0))+1),0)) -> 0 | K41: =MAX(0, J41 - IF(AND(K$4>=INDEX(Assumptions!$B:$B,MATCH("Legacy V1.5 base deorbit start year",Assumptions!$A$1:$A$327,0)),K$4<=INDEX(Assumptions!$B:$B,MATCH("Legacy V1.5 base deorbit end year",Assumptions!$A$1:$A$327,0))),$D$41/(INDEX(Assumptions!$B:$B,MATCH("Legacy V1.5 base deorbit end year",Assumptions!$A$1:$A$327,0))-INDEX(Assumptions!$B:$B,MATCH("Legacy V1.5 base deorbit start year",Assumptions!$A$1:$A$327,0))+1),0)) -> 0 | L41: =MAX(0, K41 - IF(AND(L$4>=INDEX(Assumptions!$B:$B,MATCH("Legacy V1.5 base deorbit start year",Assumptions!$A$1:$A$327,0)),L$4<=INDEX(Assumptions!$B:$B,MATCH("Legacy V1.5 base deorbit end year",Assumptions!$A$1:$A$327,0))),$D$41/(INDEX(Assumptions!$B:$B,MATCH("Legacy V1.5 base deorbit end year",Assumptions!$A$1:$A$327,0))-INDEX(Assumptions!$B:$B,MATCH("Legacy V1.5 base deorbit start year",Assumptions!$A$1:$A$327,0))+1),0)) -> 0 | ... S41: =MAX(0, R41 - IF(AND(S$4>=INDEX(Assumptions!$B:$B,MATCH("Legacy V1.5 base deorbit start year",Assumptions!$A$1:$A$327,0)),S$4<=INDEX(Assumptions!$B:$B,MATCH("Legacy V1.5 base deorbit end year",Assumptions!$A$1:$A$327,0))),$D$41/(INDEX(Assumptions!$B:$B,MATCH("Legacy V1.5 base deorbit end year",Assumptions!$A$1:$A$327,0))-INDEX(Assumptions!$B:$B,MATCH("Legacy V1.5 base deorbit start year",Assumptions!$A$1:$A$327,0))+1),0)) -> 0
A42: V2 Mini BB active sats | D42: =INDEX(Assumptions!$B:$B,MATCH("V2 Mini BB sats end-2025",Assumptions!$A$1:$A$327,0)) -> 4314 | E42: {=MAX(0, D42 + E$32 - IFERROR(IF(E$5-$D$15>=1, INDEX($D$32:$AC$32, E$5-$D$15+1), 0),0) - IF(AND(E$4>=INDEX(Assumptions!$B:$B,MATCH("V2 Mini BB base deorbit start year",Assumptions!$A$1:$A$327,0)),E$4<=INDEX(Assumptions!$B:$B,MATCH("V2 Mini BB base deorbit end year",Assumptions!$A$1:$A$327,0))),$D$42/(INDEX(Assumptions!$B:$B,MATCH("V2 Mini BB base deorbit end year",Assumptions!$A$1:$A$327,0))-INDEX(Assumptions!$B:$B,MATCH("V2 Mini BB base deorbit start year",Assumptions!$A$1:$A$327,0))+1),0))} -> 7434 | F42: {=MAX(0, E42 + F$32 - IFERROR(IF(F$5-$D$15>=1, INDEX($D$32:$AC$32, F$5-$D$15+1), 0),0) - IF(AND(F$4>=INDEX(Assumptions!$B:$B,MATCH("V2 Mini BB base deorbit start year",Assumptions!$A$1:$A$327,0)),F$4<=INDEX(Assumptions!$B:$B,MATCH("V2 Mini BB base deorbit end year",Assumptions!$A$1:$A$327,0))),$D$42/(INDEX(Assumptions!$B:$B,MATCH("V2 Mini BB base deorbit end year",Assumptions!$A$1:$A$327,0))-INDEX(Assumptions!$B:$B,MATCH("V2 Mini BB base deorbit start year",Assumptions!$A$1:$A$327,0))+1),0))} -> 7434 | G42: {=MAX(0, F42 + G$32 - IFERROR(IF(G$5-$D$15>=1, INDEX($D$32:$AC$32, G$5-$D$15+1), 0),0) - IF(AND(G$4>=INDEX(Assumptions!$B:$B,MATCH("V2 Mini BB base deorbit start year",Assumptions!$A$1:$A$327,0)),G$4<=INDEX(Assumptions!$B:$B,MATCH("V2 Mini BB base deorbit end year",Assumptions!$A$1:$A$327,0))),$D$42/(INDEX(Assumptions!$B:$B,MATCH("V2 Mini BB base deorbit end year",Assumptions!$A$1:$A$327,0))-INDEX(Assumptions!$B:$B,MATCH("V2 Mini BB base deorbit start year",Assumptions!$A$1:$A$327,0))+1),0))} -> 5996 | H42: {=MAX(0, G42 + H$32 - IFERROR(IF(H$5-$D$15>=1, INDEX($D$32:$AC$32, H$5-$D$15+1), 0),0) - IF(AND(H$4>=INDEX(Assumptions!$B:$B,MATCH("V2 Mini BB base deorbit start year",Assumptions!$A$1:$A$327,0)),H$4<=INDEX(Assumptions!$B:$B,MATCH("V2 Mini BB base deorbit end year",Assumptions!$A$1:$A$327,0))),$D$42/(INDEX(Assumptions!$B:$B,MATCH("V2 Mini BB base deorbit end year",Assumptions!$A$1:$A$327,0))-INDEX(Assumptions!$B:$B,MATCH("V2 Mini BB base deorbit start year",Assumptions!$A$1:$A$327,0))+1),0))} -> 4558 | I42: {=MAX(0, H42 + I$32 - IFERROR(IF(I$5-$D$15>=1, INDEX($D$32:$AC$32, I$5-$D$15+1), 0),0) - IF(AND(I$4>=INDEX(Assumptions!$B:$B,MATCH("V2 Mini BB base deorbit start year",Assumptions!$A$1:$A$327,0)),I$4<=INDEX(Assumptions!$B:$B,MATCH("V2 Mini BB base deorbit end year",Assumptions!$A$1:$A$327,0))),$D$42/(INDEX(Assumptions!$B:$B,MATCH("V2 Mini BB base deorbit end year",Assumptions!$A$1:$A$327,0))-INDEX(Assumptions!$B:$B,MATCH("V2 Mini BB base deorbit start year",Assumptions!$A$1:$A$327,0))+1),0))} -> 3120 | J42: {=MAX(0, I42 + J$32 - IFERROR(IF(J$5-$D$15>=1, INDEX($D$32:$AC$32, J$5-$D$15+1), 0),0) - IF(AND(J$4>=INDEX(Assumptions!$B:$B,MATCH("V2 Mini BB base deorbit start year",Assumptions!$A$1:$A$327,0)),J$4<=INDEX(Assumptions!$B:$B,MATCH("V2 Mini BB base deorbit end year",Assumptions!$A$1:$A$327,0))),$D$42/(INDEX(Assumptions!$B:$B,MATCH("V2 Mini BB base deorbit end year",Assumptions!$A$1:$A$327,0))-INDEX(Assumptions!$B:$B,MATCH("V2 Mini BB base deorbit start year",Assumptions!$A$1:$A$327,0))+1),0))} -> 0 | K42: {=MAX(0, J42 + K$32 - IFERROR(IF(K$5-$D$15>=1, INDEX($D$32:$AC$32, K$5-$D$15+1), 0),0) - IF(AND(K$4>=INDEX(Assumptions!$B:$B,MATCH("V2 Mini BB base deorbit start year",Assumptions!$A$1:$A$327,0)),K$4<=INDEX(Assumptions!$B:$B,MATCH("V2 Mini BB base deorbit end year",Assumptions!$A$1:$A$327,0))),$D$42/(INDEX(Assumptions!$B:$B,MATCH("V2 Mini BB base deorbit end year",Assumptions!$A$1:$A$327,0))-INDEX(Assumptions!$B:$B,MATCH("V2 Mini BB base deorbit start year",Assumptions!$A$1:$A$327,0))+1),0))} -> 0 | L42: {=MAX(0, K42 + L$32 - IFERROR(IF(L$5-$D$15>=1, INDEX($D$32:$AC$32, L$5-$D$15+1), 0),0) - IF(AND(L$4>=INDEX(Assumptions!$B:$B,MATCH("V2 Mini BB base deorbit start year",Assumptions!$A$1:$A$327,0)),L$4<=INDEX(Assumptions!$B:$B,MATCH("V2 Mini BB base deorbit end year",Assumptions!$A$1:$A$327,0))),$D$42/(INDEX(Assumptions!$B:$B,MATCH("V2 Mini BB base deorbit end year",Assumptions!$A$1:$A$327,0))-INDEX(Assumptions!$B:$B,MATCH("V2 Mini BB base deorbit start year",Assumptions!$A$1:$A$327,0))+1),0))} -> 0 | ... S42: {=MAX(0, R42 + S$32 - IFERROR(IF(S$5-$D$15>=1, INDEX($D$32:$AC$32, S$5-$D$15+1), 0),0) - IF(AND(S$4>=INDEX(Assumptions!$B:$B,MATCH("V2 Mini BB base deorbit start year",Assumptions!$A$1:$A$327,0)),S$4<=INDEX(Assumptions!$B:$B,MATCH("V2 Mini BB base deorbit end year",Assumptions!$A$1:$A$327,0))),$D$42/(INDEX(Assumptions!$B:$B,MATCH("V2 Mini BB base deorbit end year",Assumptions!$A$1:$A$327,0))-INDEX(Assumptions!$B:$B,MATCH("V2 Mini BB base deorbit start year",Assumptions!$A$1:$A$327,0))+1),0))} -> 0
A43: V3 BB active sats EoY | D43: =0 -> 0 | E43: {=MAX(0, D43 + E$34 - IFERROR(IF(E$5-$D$15>=1, INDEX($D$34:$AC$34, E$5-$D$15+1), 0),0))} -> 0 | F43: {=MAX(0, E43 + F$34 - IFERROR(IF(F$5-$D$15>=1, INDEX($D$34:$AC$34, F$5-$D$15+1), 0),0))} -> 3916.8544 | G43: {=MAX(0, F43 + G$34 - IFERROR(IF(G$5-$D$15>=1, INDEX($D$34:$AC$34, G$5-$D$15+1), 0),0))} -> 13334.187 | H43: {=MAX(0, G43 + H$34 - IFERROR(IF(H$5-$D$15>=1, INDEX($D$34:$AC$34, H$5-$D$15+1), 0),0))} -> 33656.955 | I43: {=MAX(0, H43 + I$34 - IFERROR(IF(I$5-$D$15>=1, INDEX($D$34:$AC$34, I$5-$D$15+1), 0),0))} -> 46020.949 | J43: {=MAX(0, I43 + J$34 - IFERROR(IF(J$5-$D$15>=1, INDEX($D$34:$AC$34, J$5-$D$15+1), 0),0))} -> 73672.56 | K43: {=MAX(0, J43 + K$34 - IFERROR(IF(K$5-$D$15>=1, INDEX($D$34:$AC$34, K$5-$D$15+1), 0),0))} -> 82297.889 | L43: {=MAX(0, K43 + L$34 - IFERROR(IF(L$5-$D$15>=1, INDEX($D$34:$AC$34, L$5-$D$15+1), 0),0))} -> 87623.985 | ... S43: {=MAX(0, R43 + S$34 - IFERROR(IF(S$5-$D$15>=1, INDEX($D$34:$AC$34, S$5-$D$15+1), 0),0))} -> 195211.71
A45: BB BANDWIDTH (Gbps by cohort)
A46: Legacy BB Gbps | D46: =D40*INDEX(Assumptions!$B:$B,MATCH("Legacy V1 Gbps per sat",Assumptions!$A$1:$A$327,0)) + D41*INDEX(Assumptions!$B:$B,MATCH("Legacy V1.5 Gbps per sat",Assumptions!$A$1:$A$327,0)) -> 75000 | E46: =E40*INDEX(Assumptions!$B:$B,MATCH("Legacy V1 Gbps per sat",Assumptions!$A$1:$A$327,0)) + E41*INDEX(Assumptions!$B:$B,MATCH("Legacy V1.5 Gbps per sat",Assumptions!$A$1:$A$327,0)) -> 43072 | F46: =F40*INDEX(Assumptions!$B:$B,MATCH("Legacy V1 Gbps per sat",Assumptions!$A$1:$A$327,0)) + F41*INDEX(Assumptions!$B:$B,MATCH("Legacy V1.5 Gbps per sat",Assumptions!$A$1:$A$327,0)) -> 21536 | G46: =G40*INDEX(Assumptions!$B:$B,MATCH("Legacy V1 Gbps per sat",Assumptions!$A$1:$A$327,0)) + G41*INDEX(Assumptions!$B:$B,MATCH("Legacy V1.5 Gbps per sat",Assumptions!$A$1:$A$327,0)) -> 0 | H46: =H40*INDEX(Assumptions!$B:$B,MATCH("Legacy V1 Gbps per sat",Assumptions!$A$1:$A$327,0)) + H41*INDEX(Assumptions!$B:$B,MATCH("Legacy V1.5 Gbps per sat",Assumptions!$A$1:$A$327,0)) -> 0 | I46: =I40*INDEX(Assumptions!$B:$B,MATCH("Legacy V1 Gbps per sat",Assumptions!$A$1:$A$327,0)) + I41*INDEX(Assumptions!$B:$B,MATCH("Legacy V1.5 Gbps per sat",Assumptions!$A$1:$A$327,0)) -> 0 | J46: =J40*INDEX(Assumptions!$B:$B,MATCH("Legacy V1 Gbps per sat",Assumptions!$A$1:$A$327,0)) + J41*INDEX(Assumptions!$B:$B,MATCH("Legacy V1.5 Gbps per sat",Assumptions!$A$1:$A$327,0)) -> 0 | K46: =K40*INDEX(Assumptions!$B:$B,MATCH("Legacy V1 Gbps per sat",Assumptions!$A$1:$A$327,0)) + K41*INDEX(Assumptions!$B:$B,MATCH("Legacy V1.5 Gbps per sat",Assumptions!$A$1:$A$327,0)) -> 0 | ... S46: =S40*INDEX(Assumptions!$B:$B,MATCH("Legacy V1 Gbps per sat",Assumptions!$A$1:$A$327,0)) + S41*INDEX(Assumptions!$B:$B,MATCH("Legacy V1.5 Gbps per sat",Assumptions!$A$1:$A$327,0)) -> 0
A47: V2 BB Gbps | D47: =D42*INDEX(Assumptions!$B:$B,MATCH("V2 BB Gbps per sat",Assumptions!$A$1:$A$327,0)) -> 414144 | E47: =E42*INDEX(Assumptions!$B:$B,MATCH("V2 BB Gbps per sat",Assumptions!$A$1:$A$327,0)) -> 713664 | F47: =F42*INDEX(Assumptions!$B:$B,MATCH("V2 BB Gbps per sat",Assumptions!$A$1:$A$327,0)) -> 713664 | G47: =G42*INDEX(Assumptions!$B:$B,MATCH("V2 BB Gbps per sat",Assumptions!$A$1:$A$327,0)) -> 575616 | H47: =H42*INDEX(Assumptions!$B:$B,MATCH("V2 BB Gbps per sat",Assumptions!$A$1:$A$327,0)) -> 437568 | I47: =I42*INDEX(Assumptions!$B:$B,MATCH("V2 BB Gbps per sat",Assumptions!$A$1:$A$327,0)) -> 299520 | J47: =J42*INDEX(Assumptions!$B:$B,MATCH("V2 BB Gbps per sat",Assumptions!$A$1:$A$327,0)) -> 0 | K47: =K42*INDEX(Assumptions!$B:$B,MATCH("V2 BB Gbps per sat",Assumptions!$A$1:$A$327,0)) -> 0 | ... S47: =S42*INDEX(Assumptions!$B:$B,MATCH("V2 BB Gbps per sat",Assumptions!$A$1:$A$327,0)) -> 0
A48: V3 BB Gbps | D48: =D43*INDEX(Assumptions!$B:$B,MATCH("V3 BB Gbps per sat",Assumptions!$A$1:$A$327,0)) -> 0 | E48: =E43*INDEX(Assumptions!$B:$B,MATCH("V3 BB Gbps per sat",Assumptions!$A$1:$A$327,0)) -> 0 | F48: =F43*INDEX(Assumptions!$B:$B,MATCH("V3 BB Gbps per sat",Assumptions!$A$1:$A$327,0)) -> 3916854.4 | G48: =G43*INDEX(Assumptions!$B:$B,MATCH("V3 BB Gbps per sat",Assumptions!$A$1:$A$327,0)) -> 13334187 | H48: =H43*INDEX(Assumptions!$B:$B,MATCH("V3 BB Gbps per sat",Assumptions!$A$1:$A$327,0)) -> 33656955 | I48: =I43*INDEX(Assumptions!$B:$B,MATCH("V3 BB Gbps per sat",Assumptions!$A$1:$A$327,0)) -> 46020949 | J48: =J43*INDEX(Assumptions!$B:$B,MATCH("V3 BB Gbps per sat",Assumptions!$A$1:$A$327,0)) -> 73672560 | K48: =K43*INDEX(Assumptions!$B:$B,MATCH("V3 BB Gbps per sat",Assumptions!$A$1:$A$327,0)) -> 82297889 | ... S48: =S43*INDEX(Assumptions!$B:$B,MATCH("V3 BB Gbps per sat",Assumptions!$A$1:$A$327,0)) -> 1.9521171e+08
A49: BB Gbps available for external Starlink revenue | D49: =D46+D47+D48 -> 489144 | E49: =E46+E47+E48 -> 756736 | F49: =F46+F47+F48 -> 4652054.4 | G49: =G46+G47+G48 -> 13909803 | H49: =H46+H47+H48 -> 34094523 | I49: =I46+I47+I48 -> 46320469 | J49: =J46+J47+J48 -> 73672560 | K49: =K46+K47+K48 -> 82297889 | ... S49: =S46+S47+S48 -> 1.9521171e+08
A51: DTC FLEET + BANDWIDTH
A52: V2 DTC active sats | D52: =INDEX(Assumptions!$B:$B,MATCH("V2 DTC active sats end-2025",Assumptions!$A$1:$A$327,0)) -> 655 | E52: =MAX(0, D52 - IF(AND(E$4>=INDEX(Assumptions!$B:$B,MATCH("V2 DTC base deorbit start year",Assumptions!$A$1:$A$327,0)),E$4<=INDEX(Assumptions!$B:$B,MATCH("V2 DTC base deorbit end year",Assumptions!$A$1:$A$327,0))),$D$52/(INDEX(Assumptions!$B:$B,MATCH("V2 DTC base deorbit end year",Assumptions!$A$1:$A$327,0))-INDEX(Assumptions!$B:$B,MATCH("V2 DTC base deorbit start year",Assumptions!$A$1:$A$327,0))+1),0)) -> 655 | F52: =MAX(0, E52 - IF(AND(F$4>=INDEX(Assumptions!$B:$B,MATCH("V2 DTC base deorbit start year",Assumptions!$A$1:$A$327,0)),F$4<=INDEX(Assumptions!$B:$B,MATCH("V2 DTC base deorbit end year",Assumptions!$A$1:$A$327,0))),$D$52/(INDEX(Assumptions!$B:$B,MATCH("V2 DTC base deorbit end year",Assumptions!$A$1:$A$327,0))-INDEX(Assumptions!$B:$B,MATCH("V2 DTC base deorbit start year",Assumptions!$A$1:$A$327,0))+1),0)) -> 655 | G52: =MAX(0, F52 - IF(AND(G$4>=INDEX(Assumptions!$B:$B,MATCH("V2 DTC base deorbit start year",Assumptions!$A$1:$A$327,0)),G$4<=INDEX(Assumptions!$B:$B,MATCH("V2 DTC base deorbit end year",Assumptions!$A$1:$A$327,0))),$D$52/(INDEX(Assumptions!$B:$B,MATCH("V2 DTC base deorbit end year",Assumptions!$A$1:$A$327,0))-INDEX(Assumptions!$B:$B,MATCH("V2 DTC base deorbit start year",Assumptions!$A$1:$A$327,0))+1),0)) -> 655 | H52: =MAX(0, G52 - IF(AND(H$4>=INDEX(Assumptions!$B:$B,MATCH("V2 DTC base deorbit start year",Assumptions!$A$1:$A$327,0)),H$4<=INDEX(Assumptions!$B:$B,MATCH("V2 DTC base deorbit end year",Assumptions!$A$1:$A$327,0))),$D$52/(INDEX(Assumptions!$B:$B,MATCH("V2 DTC base deorbit end year",Assumptions!$A$1:$A$327,0))-INDEX(Assumptions!$B:$B,MATCH("V2 DTC base deorbit start year",Assumptions!$A$1:$A$327,0))+1),0)) -> 327.5 | I52: =MAX(0, H52 - IF(AND(I$4>=INDEX(Assumptions!$B:$B,MATCH("V2 DTC base deorbit start year",Assumptions!$A$1:$A$327,0)),I$4<=INDEX(Assumptions!$B:$B,MATCH("V2 DTC base deorbit end year",Assumptions!$A$1:$A$327,0))),$D$52/(INDEX(Assumptions!$B:$B,MATCH("V2 DTC base deorbit end year",Assumptions!$A$1:$A$327,0))-INDEX(Assumptions!$B:$B,MATCH("V2 DTC base deorbit start year",Assumptions!$A$1:$A$327,0))+1),0)) -> 0 | J52: =MAX(0, I52 - IF(AND(J$4>=INDEX(Assumptions!$B:$B,MATCH("V2 DTC base deorbit start year",Assumptions!$A$1:$A$327,0)),J$4<=INDEX(Assumptions!$B:$B,MATCH("V2 DTC base deorbit end year",Assumptions!$A$1:$A$327,0))),$D$52/(INDEX(Assumptions!$B:$B,MATCH("V2 DTC base deorbit end year",Assumptions!$A$1:$A$327,0))-INDEX(Assumptions!$B:$B,MATCH("V2 DTC base deorbit start year",Assumptions!$A$1:$A$327,0))+1),0)) -> 0 | K52: =MAX(0, J52 - IF(AND(K$4>=INDEX(Assumptions!$B:$B,MATCH("V2 DTC base deorbit start year",Assumptions!$A$1:$A$327,0)),K$4<=INDEX(Assumptions!$B:$B,MATCH("V2 DTC base deorbit end year",Assumptions!$A$1:$A$327,0))),$D$52/(INDEX(Assumptions!$B:$B,MATCH("V2 DTC base deorbit end year",Assumptions!$A$1:$A$327,0))-INDEX(Assumptions!$B:$B,MATCH("V2 DTC base deorbit start year",Assumptions!$A$1:$A$327,0))+1),0)) -> 0 | L52: =MAX(0, K52 - IF(AND(L$4>=INDEX(Assumptions!$B:$B,MATCH("V2 DTC base deorbit start year",Assumptions!$A$1:$A$327,0)),L$4<=INDEX(Assumptions!$B:$B,MATCH("V2 DTC base deorbit end year",Assumptions!$A$1:$A$327,0))),$D$52/(INDEX(Assumptions!$B:$B,MATCH("V2 DTC base deorbit end year",Assumptions!$A$1:$A$327,0))-INDEX(Assumptions!$B:$B,MATCH("V2 DTC base deorbit start year",Assumptions!$A$1:$A$327,0))+1),0)) -> 0 | ... S52: =MAX(0, R52 - IF(AND(S$4>=INDEX(Assumptions!$B:$B,MATCH("V2 DTC base deorbit start year",Assumptions!$A$1:$A$327,0)),S$4<=INDEX(Assumptions!$B:$B,MATCH("V2 DTC base deorbit end year",Assumptions!$A$1:$A$327,0))),$D$52/(INDEX(Assumptions!$B:$B,MATCH("V2 DTC base deorbit end year",Assumptions!$A$1:$A$327,0))-INDEX(Assumptions!$B:$B,MATCH("V2 DTC base deorbit start year",Assumptions!$A$1:$A$327,0))+1),0)) -> 0
A53: V3 DTC active sats EoY | D53: =0 -> 0 | E53: {=MAX(0, D53 + E$35 - IFERROR(IF(E$5-$D$15>=1, INDEX($D$35:$AC$35, E$5-$D$15+1), 0),0))} -> 0 | F53: {=MAX(0, E53 + F$35 - IFERROR(IF(F$5-$D$15>=1, INDEX($D$35:$AC$35, F$5-$D$15+1), 0),0))} -> 1.8809254 | G53: {=MAX(0, F53 + G$35 - IFERROR(IF(G$5-$D$15>=1, INDEX($D$35:$AC$35, G$5-$D$15+1), 0),0))} -> 81.928671 | H53: {=MAX(0, G53 + H$35 - IFERROR(IF(H$5-$D$15>=1, INDEX($D$35:$AC$35, H$5-$D$15+1), 0),0))} -> 2706.5114 | I53: {=MAX(0, H53 + I$35 - IFERROR(IF(I$5-$D$15>=1, INDEX($D$35:$AC$35, I$5-$D$15+1), 0),0))} -> 25411.461 | J53: {=MAX(0, I53 + J$35 - IFERROR(IF(J$5-$D$15>=1, INDEX($D$35:$AC$35, J$5-$D$15+1), 0),0))} -> 53614.275 | K53: {=MAX(0, J53 + K$35 - IFERROR(IF(K$5-$D$15>=1, INDEX($D$35:$AC$35, K$5-$D$15+1), 0),0))} -> 80676.432 | L53: {=MAX(0, K53 + L$35 - IFERROR(IF(L$5-$D$15>=1, INDEX($D$35:$AC$35, L$5-$D$15+1), 0),0))} -> 113926.92 | ... S53: {=MAX(0, R53 + S$35 - IFERROR(IF(S$5-$D$15>=1, INDEX($D$35:$AC$35, S$5-$D$15+1), 0),0))} -> 155318.67
A54: V2 DTC effective Gbps | D54: =D52*INDEX(Assumptions!$B:$B,MATCH("Effective DTC Gbps per sat (revenue calibration)",Assumptions!$A$1:$A$327,0)) -> 577.71 | E54: =E52*INDEX(Assumptions!$B:$B,MATCH("Effective DTC Gbps per sat (revenue calibration)",Assumptions!$A$1:$A$327,0)) -> 577.71 | F54: =F52*INDEX(Assumptions!$B:$B,MATCH("Effective DTC Gbps per sat (revenue calibration)",Assumptions!$A$1:$A$327,0)) -> 577.71 | G54: =G52*INDEX(Assumptions!$B:$B,MATCH("Effective DTC Gbps per sat (revenue calibration)",Assumptions!$A$1:$A$327,0)) -> 577.71 | H54: =H52*INDEX(Assumptions!$B:$B,MATCH("Effective DTC Gbps per sat (revenue calibration)",Assumptions!$A$1:$A$327,0)) -> 288.855 | I54: =I52*INDEX(Assumptions!$B:$B,MATCH("Effective DTC Gbps per sat (revenue calibration)",Assumptions!$A$1:$A$327,0)) -> 0 | J54: =J52*INDEX(Assumptions!$B:$B,MATCH("Effective DTC Gbps per sat (revenue calibration)",Assumptions!$A$1:$A$327,0)) -> 0 | K54: =K52*INDEX(Assumptions!$B:$B,MATCH("Effective DTC Gbps per sat (revenue calibration)",Assumptions!$A$1:$A$327,0)) -> 0 | ... S54: =S52*INDEX(Assumptions!$B:$B,MATCH("Effective DTC Gbps per sat (revenue calibration)",Assumptions!$A$1:$A$327,0)) -> 0
A55: V3 DTC effective Gbps | D55: =D53*INDEX(Assumptions!$B:$B,MATCH("Effective DTC Gbps per sat (revenue calibration)",Assumptions!$A$1:$A$327,0)) -> 0 | E55: =E53*INDEX(Assumptions!$B:$B,MATCH("Effective DTC Gbps per sat (revenue calibration)",Assumptions!$A$1:$A$327,0)) -> 0 | F55: =F53*INDEX(Assumptions!$B:$B,MATCH("Effective DTC Gbps per sat (revenue calibration)",Assumptions!$A$1:$A$327,0)) -> 1.6589762 | G55: =G53*INDEX(Assumptions!$B:$B,MATCH("Effective DTC Gbps per sat (revenue calibration)",Assumptions!$A$1:$A$327,0)) -> 72.261088 | H55: =H53*INDEX(Assumptions!$B:$B,MATCH("Effective DTC Gbps per sat (revenue calibration)",Assumptions!$A$1:$A$327,0)) -> 2387.1431 | I55: =I53*INDEX(Assumptions!$B:$B,MATCH("Effective DTC Gbps per sat (revenue calibration)",Assumptions!$A$1:$A$327,0)) -> 22412.908 | J55: =J53*INDEX(Assumptions!$B:$B,MATCH("Effective DTC Gbps per sat (revenue calibration)",Assumptions!$A$1:$A$327,0)) -> 47287.791 | K55: =K53*INDEX(Assumptions!$B:$B,MATCH("Effective DTC Gbps per sat (revenue calibration)",Assumptions!$A$1:$A$327,0)) -> 71156.613 | ... S55: =S53*INDEX(Assumptions!$B:$B,MATCH("Effective DTC Gbps per sat (revenue calibration)",Assumptions!$A$1:$A$327,0)) -> 136991.06
A56: DTC Gbps available for external Starlink revenue | D56: =D54+D55 -> 577.71 | E56: =E54+E55 -> 577.71 | F56: =F54+F55 -> 579.36898 | G56: =G54+G55 -> 649.97109 | H56: =H54+H55 -> 2675.9981 | I56: =I54+I55 -> 22412.908 | J56: =J54+J55 -> 47287.791 | K56: =K54+K55 -> 71156.613 | ... S56: =S54+S55 -> 136991.06
A58: ▸ REVENUE
A59: Starshield active Gbps (working) | D59: {=INDEX(Assumptions!$D:$AC,MATCH("Starshield active Gbps (year-row)",Assumptions!$A$1:$A$327,0),COLUMN()-COLUMN($D$59)+1)} -> 15300 | E59: {=INDEX(Assumptions!$D:$AC,MATCH("Starshield active Gbps (year-row)",Assumptions!$A$1:$A$327,0),COLUMN()-COLUMN($D$59)+1)} -> 16524 | F59: {=INDEX(Assumptions!$D:$AC,MATCH("Starshield active Gbps (year-row)",Assumptions!$A$1:$A$327,0),COLUMN()-COLUMN($D$59)+1)} -> 17845.92 | G59: {=INDEX(Assumptions!$D:$AC,MATCH("Starshield active Gbps (year-row)",Assumptions!$A$1:$A$327,0),COLUMN()-COLUMN($D$59)+1)} -> 19273.594 | H59: {=INDEX(Assumptions!$D:$AC,MATCH("Starshield active Gbps (year-row)",Assumptions!$A$1:$A$327,0),COLUMN()-COLUMN($D$59)+1)} -> 20815.481 | I59: {=INDEX(Assumptions!$D:$AC,MATCH("Starshield active Gbps (year-row)",Assumptions!$A$1:$A$327,0),COLUMN()-COLUMN($D$59)+1)} -> 22480.72 | J59: {=INDEX(Assumptions!$D:$AC,MATCH("Starshield active Gbps (year-row)",Assumptions!$A$1:$A$327,0),COLUMN()-COLUMN($D$59)+1)} -> 24279.177 | K59: {=INDEX(Assumptions!$D:$AC,MATCH("Starshield active Gbps (year-row)",Assumptions!$A$1:$A$327,0),COLUMN()-COLUMN($D$59)+1)} -> 26221.511 | ... S59: {=INDEX(Assumptions!$D:$AC,MATCH("Starshield active Gbps (year-row)",Assumptions!$A$1:$A$327,0),COLUMN()-COLUMN($D$59)+1)} -> 48534.187
A60: Starshield $/Gbps ($/Gbps-yr) (working) | D60: =INDEX(Assumptions!$B:$B,MATCH("Starshield $/Gbps ($/Gbps-yr)",Assumptions!$A$1:$A$327,0)) -> 164699 | E60: =INDEX(Assumptions!$B:$B,MATCH("Starshield $/Gbps ($/Gbps-yr)",Assumptions!$A$1:$A$327,0)) -> 164699 | F60: =INDEX(Assumptions!$B:$B,MATCH("Starshield $/Gbps ($/Gbps-yr)",Assumptions!$A$1:$A$327,0)) -> 164699 | G60: =INDEX(Assumptions!$B:$B,MATCH("Starshield $/Gbps ($/Gbps-yr)",Assumptions!$A$1:$A$327,0)) -> 164699 | H60: =INDEX(Assumptions!$B:$B,MATCH("Starshield $/Gbps ($/Gbps-yr)",Assumptions!$A$1:$A$327,0)) -> 164699 | I60: =INDEX(Assumptions!$B:$B,MATCH("Starshield $/Gbps ($/Gbps-yr)",Assumptions!$A$1:$A$327,0)) -> 164699 | J60: =INDEX(Assumptions!$B:$B,MATCH("Starshield $/Gbps ($/Gbps-yr)",Assumptions!$A$1:$A$327,0)) -> 164699 | K60: =INDEX(Assumptions!$B:$B,MATCH("Starshield $/Gbps ($/Gbps-yr)",Assumptions!$A$1:$A$327,0)) -> 164699 | ... S60: =INDEX(Assumptions!$B:$B,MATCH("Starshield $/Gbps ($/Gbps-yr)",Assumptions!$A$1:$A$327,0)) -> 164699
A61: Total BB revenue ($mm) | D61: =D11 -> 6721.2206 | E61: =E11 -> 9347.5765 | F61: =F11 -> 37555.662 | G61: =G11 -> 80517.638 | H61: =H11 -> 133572.61 | I61: =I11 -> 162366.46 | J61: =J11 -> 198728.63 | K61: =K11 -> 212218.52 | ... S61: =S11 -> 305981.36
A62: Total DTC revenue ($mm) | D62: =D12 -> 632.0752 | E62: =E12 -> 794.38308 | F62: =F12 -> 969.01841 | G62: =G12 -> 1291.3436 | H62: =H12 -> 6202.8488 | I62: =I12 -> 30569.893 | J62: =J12 -> 40144.794 | K62: =K12 -> 47979.431 | ... S62: =S12 -> 60513.713
A63: Starshield revenue ($mm) | D63: =D$59*D$60/1000000*INDEX(Assumptions!$B:$B,MATCH("Starshield utilization (frac)",Assumptions!$A$1:$A$327,0)) -> 2519.8947 | E63: =E$59*E$60/1000000*INDEX(Assumptions!$B:$B,MATCH("Starshield utilization (frac)",Assumptions!$A$1:$A$327,0)) -> 2721.4863 | F63: =F$59*F$60/1000000*INDEX(Assumptions!$B:$B,MATCH("Starshield utilization (frac)",Assumptions!$A$1:$A$327,0)) -> 2939.2052 | G63: =G$59*G$60/1000000*INDEX(Assumptions!$B:$B,MATCH("Starshield utilization (frac)",Assumptions!$A$1:$A$327,0)) -> 3174.3416 | H63: =H$59*H$60/1000000*INDEX(Assumptions!$B:$B,MATCH("Starshield utilization (frac)",Assumptions!$A$1:$A$327,0)) -> 3428.2889 | I63: =I$59*I$60/1000000*INDEX(Assumptions!$B:$B,MATCH("Starshield utilization (frac)",Assumptions!$A$1:$A$327,0)) -> 3702.552 | J63: =J$59*J$60/1000000*INDEX(Assumptions!$B:$B,MATCH("Starshield utilization (frac)",Assumptions!$A$1:$A$327,0)) -> 3998.7562 | K63: =K$59*K$60/1000000*INDEX(Assumptions!$B:$B,MATCH("Starshield utilization (frac)",Assumptions!$A$1:$A$327,0)) -> 4318.6567 | ... S63: =S$59*S$60/1000000*INDEX(Assumptions!$B:$B,MATCH("Starshield utilization (frac)",Assumptions!$A$1:$A$327,0)) -> 7993.5321
A64: Hardware / kit revenue ($mm) | D64: =D$183*INDEX(Assumptions!$B:$B,MATCH("Blended kit sale price ($/kit)",Assumptions!$A$1:$A$327,0)) -> 1005.9344 | E64: =E$183*INDEX(Assumptions!$B:$B,MATCH("Blended kit sale price ($/kit)",Assumptions!$A$1:$A$327,0)) -> 1388.544 | F64: =F$183*INDEX(Assumptions!$B:$B,MATCH("Blended kit sale price ($/kit)",Assumptions!$A$1:$A$327,0)) -> 13729.17 | G64: =G$183*INDEX(Assumptions!$B:$B,MATCH("Blended kit sale price ($/kit)",Assumptions!$A$1:$A$327,0)) -> 23407.448 | H64: =H$183*INDEX(Assumptions!$B:$B,MATCH("Blended kit sale price ($/kit)",Assumptions!$A$1:$A$327,0)) -> 32915.91 | I64: =I$183*INDEX(Assumptions!$B:$B,MATCH("Blended kit sale price ($/kit)",Assumptions!$A$1:$A$327,0)) -> 24196.908 | J64: =J$183*INDEX(Assumptions!$B:$B,MATCH("Blended kit sale price ($/kit)",Assumptions!$A$1:$A$327,0)) -> 24268.079 | K64: =K$183*INDEX(Assumptions!$B:$B,MATCH("Blended kit sale price ($/kit)",Assumptions!$A$1:$A$327,0)) -> 10798.777 | ... S64: =S$183*INDEX(Assumptions!$B:$B,MATCH("Blended kit sale price ($/kit)",Assumptions!$A$1:$A$327,0)) -> 5546.9732
A65: Revenue | D65: =D61+D62+D63+D64 -> 10879.125 | E65: =E61+E62+E63+E64 -> 14251.99 | F65: =F61+F62+F63+F64 -> 55193.055 | G65: =G61+G62+G63+G64 -> 108390.77 | H65: =H61+H62+H63+H64 -> 176119.66 | I65: =I61+I62+I63+I64 -> 220835.81 | J65: =J61+J62+J63+J64 -> 267140.26 | K65: =K61+K62+K63+K64 -> 275315.39 | ... S65: =S61+S62+S63+S64 -> 380035.58
A66: Memo: Starlink+DTC revenue (excl. Starshield) | D66: =D61+D62 -> 7353.2957 | E66: =E61+E62 -> 10141.96 | F66: =F61+F62 -> 38524.68 | G66: =G61+G62 -> 81808.981 | H66: =H61+H62 -> 139775.46 | I66: =I61+I62 -> 192936.35 | J66: =J61+J62 -> 238873.42 | K66: =K61+K62 -> 260197.96 | ... S66: =S61+S62 -> 366495.07
A68: ▸ INTERNAL LAUNCHES + RETAIL FLEET (working)
A69: F9 internal launches per year (Starlink-driven) | D69: =IF(D$28=1, IFERROR(_xlfn.CEILING.MATH((D$32+D$33+D$36)/INDEX(Assumptions!$B:$B,MATCH("F9 sats per launch (V2 packing)",Assumptions!$A$1:$A$327,0))),0), 0) -> 166 | E69: =IF(E$28=1, IFERROR(_xlfn.CEILING.MATH((E$32+E$33+E$36)/INDEX(Assumptions!$B:$B,MATCH("F9 sats per launch (V2 packing)",Assumptions!$A$1:$A$327,0))),0), 0) -> 138 | F69: =IF(F$28=1, IFERROR(_xlfn.CEILING.MATH((F$32+F$33+F$36)/INDEX(Assumptions!$B:$B,MATCH("F9 sats per launch (V2 packing)",Assumptions!$A$1:$A$327,0))),0), 0) -> 0 | G69: =IF(G$28=1, IFERROR(_xlfn.CEILING.MATH((G$32+G$33+G$36)/INDEX(Assumptions!$B:$B,MATCH("F9 sats per launch (V2 packing)",Assumptions!$A$1:$A$327,0))),0), 0) -> 0 | H69: =IF(H$28=1, IFERROR(_xlfn.CEILING.MATH((H$32+H$33+H$36)/INDEX(Assumptions!$B:$B,MATCH("F9 sats per launch (V2 packing)",Assumptions!$A$1:$A$327,0))),0), 0) -> 0 | I69: =IF(I$28=1, IFERROR(_xlfn.CEILING.MATH((I$32+I$33+I$36)/INDEX(Assumptions!$B:$B,MATCH("F9 sats per launch (V2 packing)",Assumptions!$A$1:$A$327,0))),0), 0) -> 0 | J69: =IF(J$28=1, IFERROR(_xlfn.CEILING.MATH((J$32+J$33+J$36)/INDEX(Assumptions!$B:$B,MATCH("F9 sats per launch (V2 packing)",Assumptions!$A$1:$A$327,0))),0), 0) -> 0 | K69: =IF(K$28=1, IFERROR(_xlfn.CEILING.MATH((K$32+K$33+K$36)/INDEX(Assumptions!$B:$B,MATCH("F9 sats per launch (V2 packing)",Assumptions!$A$1:$A$327,0))),0), 0) -> 0 | ... S69: =IF(S$28=1, IFERROR(_xlfn.CEILING.MATH((S$32+S$33+S$36)/INDEX(Assumptions!$B:$B,MATCH("F9 sats per launch (V2 packing)",Assumptions!$A$1:$A$327,0))),0), 0) -> 0
A70: Starship internal launches per year (Starlink-driven) | D70: =IF(D$29=1, IFERROR(_xlfn.CEILING.MATH((D$34+D$35)/D205),0), 0) -> 0 | E70: =IF(E$29=1, IFERROR(_xlfn.CEILING.MATH((E$34+E$35)/E205),0), 0) -> 0 | F70: =IF(F$29=1, IFERROR(_xlfn.CEILING.MATH((F$34+F$35)/F205),0), 0) -> 61 | G70: =IF(G$29=1, IFERROR(_xlfn.CEILING.MATH((G$34+G$35)/G205),0), 0) -> 127 | H70: =IF(H$29=1, IFERROR(_xlfn.CEILING.MATH((H$34+H$35)/H205),0), 0) -> 264 | I70: =IF(I$29=1, IFERROR(_xlfn.CEILING.MATH((I$34+I$35)/I205),0), 0) -> 351 | J70: =IF(J$29=1, IFERROR(_xlfn.CEILING.MATH((J$34+J$35)/J205),0), 0) -> 559 | K70: =IF(K$29=1, IFERROR(_xlfn.CEILING.MATH((K$34+K$35)/K205),0), 0) -> 397 | ... S70: =IF(S$29=1, IFERROR(_xlfn.CEILING.MATH((S$34+S$35)/S205),0), 0) -> 395
A71: Active retail sats (BB + DTC, EoY) | D71: =D$42+D$43+D$52+D$53 -> 4969 | E71: =E$42+E$43+E$52+E$53 -> 8089 | F71: =F$42+F$43+F$52+F$53 -> 12007.735 | G71: =G$42+G$43+G$52+G$53 -> 20067.115 | H71: =H$42+H$43+H$52+H$53 -> 41248.966 | I71: =I$42+I$43+I$52+I$53 -> 74552.41 | J71: =J$42+J$43+J$52+J$53 -> 127286.84 | K71: =K$42+K$43+K$52+K$53 -> 162974.32 | ... S71: =S$42+S$43+S$52+S$53 -> 350530.38
A73: ▸ COGS → GROSS PROFIT
A74: Hardware / kit COGS ($mm) | D74: =D$183*INDEX(Assumptions!$B:$B,MATCH("Terminal COGS per unit ($)",Assumptions!$A$1:$A$327,0)) -> 1257.418 | E74: =E$183*INDEX(Assumptions!$B:$B,MATCH("Terminal COGS per unit ($)",Assumptions!$A$1:$A$327,0)) -> 1735.6801 | F74: =F$183*INDEX(Assumptions!$B:$B,MATCH("Terminal COGS per unit ($)",Assumptions!$A$1:$A$327,0)) -> 17161.463 | G74: =G$183*INDEX(Assumptions!$B:$B,MATCH("Terminal COGS per unit ($)",Assumptions!$A$1:$A$327,0)) -> 29259.31 | H74: =H$183*INDEX(Assumptions!$B:$B,MATCH("Terminal COGS per unit ($)",Assumptions!$A$1:$A$327,0)) -> 41144.887 | I74: =I$183*INDEX(Assumptions!$B:$B,MATCH("Terminal COGS per unit ($)",Assumptions!$A$1:$A$327,0)) -> 30246.135 | J74: =J$183*INDEX(Assumptions!$B:$B,MATCH("Terminal COGS per unit ($)",Assumptions!$A$1:$A$327,0)) -> 30335.099 | K74: =K$183*INDEX(Assumptions!$B:$B,MATCH("Terminal COGS per unit ($)",Assumptions!$A$1:$A$327,0)) -> 13498.471 | ... S74: =S$183*INDEX(Assumptions!$B:$B,MATCH("Terminal COGS per unit ($)",Assumptions!$A$1:$A$327,0)) -> 6933.7165
A75: Ground-network ops COGS ($mm) | D75: =D$65*INDEX(Assumptions!$B:$B,MATCH("Ground-network ops COGS (% of revenue)",Assumptions!$A$1:$A$327,0)) -> 217.5825 | E75: =E$65*INDEX(Assumptions!$B:$B,MATCH("Ground-network ops COGS (% of revenue)",Assumptions!$A$1:$A$327,0)) -> 285.0398 | F75: =F$65*INDEX(Assumptions!$B:$B,MATCH("Ground-network ops COGS (% of revenue)",Assumptions!$A$1:$A$327,0)) -> 1103.8611 | G75: =G$65*INDEX(Assumptions!$B:$B,MATCH("Ground-network ops COGS (% of revenue)",Assumptions!$A$1:$A$327,0)) -> 2167.8154 | H75: =H$65*INDEX(Assumptions!$B:$B,MATCH("Ground-network ops COGS (% of revenue)",Assumptions!$A$1:$A$327,0)) -> 3522.3932 | I75: =I$65*INDEX(Assumptions!$B:$B,MATCH("Ground-network ops COGS (% of revenue)",Assumptions!$A$1:$A$327,0)) -> 4416.7162 | J75: =J$65*INDEX(Assumptions!$B:$B,MATCH("Ground-network ops COGS (% of revenue)",Assumptions!$A$1:$A$327,0)) -> 5342.8052 | K75: =K$65*INDEX(Assumptions!$B:$B,MATCH("Ground-network ops COGS (% of revenue)",Assumptions!$A$1:$A$327,0)) -> 5506.3078 | ... S75: =S$65*INDEX(Assumptions!$B:$B,MATCH("Ground-network ops COGS (% of revenue)",Assumptions!$A$1:$A$327,0)) -> 7600.7115
A76: Asset insurance COGS ($mm) | D76: =D$65*INDEX(Assumptions!$B:$B,MATCH("Asset insurance COGS (% of revenue)",Assumptions!$A$1:$A$327,0)) -> 108.79125 | E76: =E$65*INDEX(Assumptions!$B:$B,MATCH("Asset insurance COGS (% of revenue)",Assumptions!$A$1:$A$327,0)) -> 142.5199 | F76: =F$65*INDEX(Assumptions!$B:$B,MATCH("Asset insurance COGS (% of revenue)",Assumptions!$A$1:$A$327,0)) -> 551.93055 | G76: =G$65*INDEX(Assumptions!$B:$B,MATCH("Asset insurance COGS (% of revenue)",Assumptions!$A$1:$A$327,0)) -> 1083.9077 | H76: =H$65*INDEX(Assumptions!$B:$B,MATCH("Asset insurance COGS (% of revenue)",Assumptions!$A$1:$A$327,0)) -> 1761.1966 | I76: =I$65*INDEX(Assumptions!$B:$B,MATCH("Asset insurance COGS (% of revenue)",Assumptions!$A$1:$A$327,0)) -> 2208.3581 | J76: =J$65*INDEX(Assumptions!$B:$B,MATCH("Asset insurance COGS (% of revenue)",Assumptions!$A$1:$A$327,0)) -> 2671.4026 | K76: =K$65*INDEX(Assumptions!$B:$B,MATCH("Asset insurance COGS (% of revenue)",Assumptions!$A$1:$A$327,0)) -> 2753.1539 | ... S76: =S$65*INDEX(Assumptions!$B:$B,MATCH("Asset insurance COGS (% of revenue)",Assumptions!$A$1:$A$327,0)) -> 3800.3558
A77: Variable launch COGS ($mm) | D77: {=D$69*INDEX(Assumptions!$D:$AC,MATCH("F9 variable cost per launch ($mm/launch)",Assumptions!$A$1:$A$327,0),D$5+1)+D$70*INDEX(Assumptions!$D:$AC,MATCH("Starship variable cost per launch ($mm/launch)",Assumptions!$A$1:$A$327,0),D$5+1)} -> 2697.5 | E77: {=E$69*INDEX(Assumptions!$D:$AC,MATCH("F9 variable cost per launch ($mm/launch)",Assumptions!$A$1:$A$327,0),E$5+1)+E$70*INDEX(Assumptions!$D:$AC,MATCH("Starship variable cost per launch ($mm/launch)",Assumptions!$A$1:$A$327,0),E$5+1)} -> 2197.65 | F77: {=F$69*INDEX(Assumptions!$D:$AC,MATCH("F9 variable cost per launch ($mm/launch)",Assumptions!$A$1:$A$327,0),F$5+1)+F$70*INDEX(Assumptions!$D:$AC,MATCH("Starship variable cost per launch ($mm/launch)",Assumptions!$A$1:$A$327,0),F$5+1)} -> 305 | G77: {=G$69*INDEX(Assumptions!$D:$AC,MATCH("F9 variable cost per launch ($mm/launch)",Assumptions!$A$1:$A$327,0),G$5+1)+G$70*INDEX(Assumptions!$D:$AC,MATCH("Starship variable cost per launch ($mm/launch)",Assumptions!$A$1:$A$327,0),G$5+1)} -> 584.2 | H77: {=H$69*INDEX(Assumptions!$D:$AC,MATCH("F9 variable cost per launch ($mm/launch)",Assumptions!$A$1:$A$327,0),H$5+1)+H$70*INDEX(Assumptions!$D:$AC,MATCH("Starship variable cost per launch ($mm/launch)",Assumptions!$A$1:$A$327,0),H$5+1)} -> 1117.248 | I77: {=I$69*INDEX(Assumptions!$D:$AC,MATCH("F9 variable cost per launch ($mm/launch)",Assumptions!$A$1:$A$327,0),I$5+1)+I$70*INDEX(Assumptions!$D:$AC,MATCH("Starship variable cost per launch ($mm/launch)",Assumptions!$A$1:$A$327,0),I$5+1)} -> 1366.5974 | J77: {=J$69*INDEX(Assumptions!$D:$AC,MATCH("F9 variable cost per launch ($mm/launch)",Assumptions!$A$1:$A$327,0),J$5+1)+J$70*INDEX(Assumptions!$D:$AC,MATCH("Starship variable cost per launch ($mm/launch)",Assumptions!$A$1:$A$327,0),J$5+1)} -> 2002.3183 | K77: {=K$69*INDEX(Assumptions!$D:$AC,MATCH("F9 variable cost per launch ($mm/launch)",Assumptions!$A$1:$A$327,0),K$5+1)+K$70*INDEX(Assumptions!$D:$AC,MATCH("Starship variable cost per launch ($mm/launch)",Assumptions!$A$1:$A$327,0),K$5+1)} -> 1308.2768 | ... S77: {=S$69*INDEX(Assumptions!$D:$AC,MATCH("F9 variable cost per launch ($mm/launch)",Assumptions!$A$1:$A$327,0),S$5+1)+S$70*INDEX(Assumptions!$D:$AC,MATCH("Starship variable cost per launch ($mm/launch)",Assumptions!$A$1:$A$327,0),S$5+1)} -> 668.04983
A78: COGS total ($mm) | D78: =SUM(D75:D77)+D74 -> 4281.2917 | E78: =SUM(E75:E77)+E74 -> 4360.8897 | F78: =SUM(F75:F77)+F74 -> 19122.254 | G78: =SUM(G75:G77)+G74 -> 33095.233 | H78: =SUM(H75:H77)+H74 -> 47545.725 | I78: =SUM(I75:I77)+I74 -> 38237.807 | J78: =SUM(J75:J77)+J74 -> 40351.625 | K78: =SUM(K75:K77)+K74 -> 23066.21 | ... S78: =SUM(S75:S77)+S74 -> 19002.834
A79: Gross Profit ($mm) | D79: =D$65-D$78 -> 6597.8331 | E79: =E$65-E$78 -> 9891.1001 | F79: =F$65-F$78 -> 36070.801 | G79: =G$65-G$78 -> 75295.538 | H79: =H$65-H$78 -> 128573.93 | I79: =I$65-I$78 -> 182598 | J79: =J$65-J$78 -> 226788.63 | K79: =K$65-K$78 -> 252249.18 | ... S79: =S$65-S$78 -> 361032.74
A80: Memo: Gross Margin % | D80: =IFERROR(D$79/D$65,0) -> 0.60646727 | E80: =IFERROR(E$79/E$65,0) -> 0.69401538 | F80: =IFERROR(F$79/F$65,0) -> 0.65353876 | G80: =IFERROR(G$79/G$65,0) -> 0.69466743 | H80: =IFERROR(H$79/H$65,0) -> 0.73003738 | I80: =IFERROR(I$79/I$65,0) -> 0.82684961 | J80: =IFERROR(J$79/J$65,0) -> 0.84894967 | K80: =IFERROR(K$79/K$65,0) -> 0.91621896 | ... S80: =IFERROR(S$79/S$65,0) -> 0.94999722
A82: ▸ MODULE OpEx
A83: Sales & Marketing ($mm) | D83: =D$65*MAX(INDEX(Assumptions!$B:$B,MATCH("Sales & Marketing: end-state % (floor)",Assumptions!$A$1:$A$327,0)), INDEX(Assumptions!$B:$B,MATCH("Sales & Marketing: start % of (Starlink+Starshield+CL ext) rev",Assumptions!$A$1:$A$327,0))*(1+INDEX(Assumptions!$B:$B,MATCH("Sales & Marketing: CAGR (taper)",Assumptions!$A$1:$A$327,0)))^D$5) -> 326.37374 | E83: =E$65*MAX(INDEX(Assumptions!$B:$B,MATCH("Sales & Marketing: end-state % (floor)",Assumptions!$A$1:$A$327,0)), INDEX(Assumptions!$B:$B,MATCH("Sales & Marketing: start % of (Starlink+Starshield+CL ext) rev",Assumptions!$A$1:$A$327,0))*(1+INDEX(Assumptions!$B:$B,MATCH("Sales & Marketing: CAGR (taper)",Assumptions!$A$1:$A$327,0)))^E$5) -> 393.35492 | F83: =F$65*MAX(INDEX(Assumptions!$B:$B,MATCH("Sales & Marketing: end-state % (floor)",Assumptions!$A$1:$A$327,0)), INDEX(Assumptions!$B:$B,MATCH("Sales & Marketing: start % of (Starlink+Starshield+CL ext) rev",Assumptions!$A$1:$A$327,0))*(1+INDEX(Assumptions!$B:$B,MATCH("Sales & Marketing: CAGR (taper)",Assumptions!$A$1:$A$327,0)))^F$5) -> 1401.4621 | G83: =G$65*MAX(INDEX(Assumptions!$B:$B,MATCH("Sales & Marketing: end-state % (floor)",Assumptions!$A$1:$A$327,0)), INDEX(Assumptions!$B:$B,MATCH("Sales & Marketing: start % of (Starlink+Starshield+CL ext) rev",Assumptions!$A$1:$A$327,0))*(1+INDEX(Assumptions!$B:$B,MATCH("Sales & Marketing: CAGR (taper)",Assumptions!$A$1:$A$327,0)))^G$5) -> 2532.0778 | H83: =H$65*MAX(INDEX(Assumptions!$B:$B,MATCH("Sales & Marketing: end-state % (floor)",Assumptions!$A$1:$A$327,0)), INDEX(Assumptions!$B:$B,MATCH("Sales & Marketing: start % of (Starlink+Starshield+CL ext) rev",Assumptions!$A$1:$A$327,0))*(1+INDEX(Assumptions!$B:$B,MATCH("Sales & Marketing: CAGR (taper)",Assumptions!$A$1:$A$327,0)))^H$5) -> 3785.1265 | I83: =I$65*MAX(INDEX(Assumptions!$B:$B,MATCH("Sales & Marketing: end-state % (floor)",Assumptions!$A$1:$A$327,0)), INDEX(Assumptions!$B:$B,MATCH("Sales & Marketing: start % of (Starlink+Starshield+CL ext) rev",Assumptions!$A$1:$A$327,0))*(1+INDEX(Assumptions!$B:$B,MATCH("Sales & Marketing: CAGR (taper)",Assumptions!$A$1:$A$327,0)))^I$5) -> 4416.7162 | J83: =J$65*MAX(INDEX(Assumptions!$B:$B,MATCH("Sales & Marketing: end-state % (floor)",Assumptions!$A$1:$A$327,0)), INDEX(Assumptions!$B:$B,MATCH("Sales & Marketing: start % of (Starlink+Starshield+CL ext) rev",Assumptions!$A$1:$A$327,0))*(1+INDEX(Assumptions!$B:$B,MATCH("Sales & Marketing: CAGR (taper)",Assumptions!$A$1:$A$327,0)))^J$5) -> 5342.8052 | K83: =K$65*MAX(INDEX(Assumptions!$B:$B,MATCH("Sales & Marketing: end-state % (floor)",Assumptions!$A$1:$A$327,0)), INDEX(Assumptions!$B:$B,MATCH("Sales & Marketing: start % of (Starlink+Starshield+CL ext) rev",Assumptions!$A$1:$A$327,0))*(1+INDEX(Assumptions!$B:$B,MATCH("Sales & Marketing: CAGR (taper)",Assumptions!$A$1:$A$327,0)))^K$5) -> 5506.3078 | ... S83: =S$65*MAX(INDEX(Assumptions!$B:$B,MATCH("Sales & Marketing: end-state % (floor)",Assumptions!$A$1:$A$327,0)), INDEX(Assumptions!$B:$B,MATCH("Sales & Marketing: start % of (Starlink+Starshield+CL ext) rev",Assumptions!$A$1:$A$327,0))*(1+INDEX(Assumptions!$B:$B,MATCH("Sales & Marketing: CAGR (taper)",Assumptions!$A$1:$A$327,0)))^S$5) -> 7600.7115
A84: Customer support & billing ($mm) | D84: =D$66*INDEX(Assumptions!$B:$B,MATCH("Customer Service: flat % of Starlink subscription rev",Assumptions!$A$1:$A$327,0)) -> 147.06591 | E84: =E$66*INDEX(Assumptions!$B:$B,MATCH("Customer Service: flat % of Starlink subscription rev",Assumptions!$A$1:$A$327,0)) -> 202.83919 | F84: =F$66*INDEX(Assumptions!$B:$B,MATCH("Customer Service: flat % of Starlink subscription rev",Assumptions!$A$1:$A$327,0)) -> 770.4936 | G84: =G$66*INDEX(Assumptions!$B:$B,MATCH("Customer Service: flat % of Starlink subscription rev",Assumptions!$A$1:$A$327,0)) -> 1636.1796 | H84: =H$66*INDEX(Assumptions!$B:$B,MATCH("Customer Service: flat % of Starlink subscription rev",Assumptions!$A$1:$A$327,0)) -> 2795.5092 | I84: =I$66*INDEX(Assumptions!$B:$B,MATCH("Customer Service: flat % of Starlink subscription rev",Assumptions!$A$1:$A$327,0)) -> 3858.727 | J84: =J$66*INDEX(Assumptions!$B:$B,MATCH("Customer Service: flat % of Starlink subscription rev",Assumptions!$A$1:$A$327,0)) -> 4777.4685 | K84: =K$66*INDEX(Assumptions!$B:$B,MATCH("Customer Service: flat % of Starlink subscription rev",Assumptions!$A$1:$A$327,0)) -> 5203.9591 | ... S84: =S$66*INDEX(Assumptions!$B:$B,MATCH("Customer Service: flat % of Starlink subscription rev",Assumptions!$A$1:$A$327,0)) -> 7329.9014
A85: Network operations ($mm) | D85: =D$65*INDEX(Assumptions!$B:$B,MATCH("Network ops & G&A (% of revenue)",Assumptions!$A$1:$A$327,0)) -> 271.97812 | E85: =E$65*INDEX(Assumptions!$B:$B,MATCH("Network ops & G&A (% of revenue)",Assumptions!$A$1:$A$327,0)) -> 356.29975 | F85: =F$65*INDEX(Assumptions!$B:$B,MATCH("Network ops & G&A (% of revenue)",Assumptions!$A$1:$A$327,0)) -> 1379.8264 | G85: =G$65*INDEX(Assumptions!$B:$B,MATCH("Network ops & G&A (% of revenue)",Assumptions!$A$1:$A$327,0)) -> 2709.7693 | H85: =H$65*INDEX(Assumptions!$B:$B,MATCH("Network ops & G&A (% of revenue)",Assumptions!$A$1:$A$327,0)) -> 4402.9914 | I85: =I$65*INDEX(Assumptions!$B:$B,MATCH("Network ops & G&A (% of revenue)",Assumptions!$A$1:$A$327,0)) -> 5520.8953 | J85: =J$65*INDEX(Assumptions!$B:$B,MATCH("Network ops & G&A (% of revenue)",Assumptions!$A$1:$A$327,0)) -> 6678.5065 | K85: =K$65*INDEX(Assumptions!$B:$B,MATCH("Network ops & G&A (% of revenue)",Assumptions!$A$1:$A$327,0)) -> 6882.8847 | ... S85: =S$65*INDEX(Assumptions!$B:$B,MATCH("Network ops & G&A (% of revenue)",Assumptions!$A$1:$A$327,0)) -> 9500.8894
A86: Spectrum licence OpEx ($mm) | D86: =D$65*INDEX(Assumptions!$B:$B,MATCH("Spectrum licence OpEx (% of revenue)",Assumptions!$A$1:$A$327,0)) -> 141.42862 | E86: =E$65*INDEX(Assumptions!$B:$B,MATCH("Spectrum licence OpEx (% of revenue)",Assumptions!$A$1:$A$327,0)) -> 185.27587 | F86: =F$65*INDEX(Assumptions!$B:$B,MATCH("Spectrum licence OpEx (% of revenue)",Assumptions!$A$1:$A$327,0)) -> 717.50972 | G86: =G$65*INDEX(Assumptions!$B:$B,MATCH("Spectrum licence OpEx (% of revenue)",Assumptions!$A$1:$A$327,0)) -> 1409.08 | H86: =H$65*INDEX(Assumptions!$B:$B,MATCH("Spectrum licence OpEx (% of revenue)",Assumptions!$A$1:$A$327,0)) -> 2289.5556 | I86: =I$65*INDEX(Assumptions!$B:$B,MATCH("Spectrum licence OpEx (% of revenue)",Assumptions!$A$1:$A$327,0)) -> 2870.8655 | J86: =J$65*INDEX(Assumptions!$B:$B,MATCH("Spectrum licence OpEx (% of revenue)",Assumptions!$A$1:$A$327,0)) -> 3472.8234 | K86: =K$65*INDEX(Assumptions!$B:$B,MATCH("Spectrum licence OpEx (% of revenue)",Assumptions!$A$1:$A$327,0)) -> 3579.1001 | ... S86: =S$65*INDEX(Assumptions!$B:$B,MATCH("Spectrum licence OpEx (% of revenue)",Assumptions!$A$1:$A$327,0)) -> 4940.4625
A87: Module OpEx total (incl. R&D) ($mm) | D87: =SUM(D83:D86)+D92 -> 1463.44 | E87: =SUM(E83:E86)+E92 -> 1817.5896 | F87: =SUM(F83:F86)+F92 -> 6638.7296 | G87: =SUM(G83:G86)+G92 -> 12475.001 | H87: =SUM(H83:H86)+H92 -> 19397.444 | I87: =SUM(I83:I86)+I92 -> 23578.475 | J87: =SUM(J83:J86)+J92 -> 28285.811 | K87: =SUM(K83:K86)+K92 -> 29431.713 | ... S87: =SUM(S83:S86)+S92 -> 40773.032
A88: Module EBITDA ($mm) | D88: =D79-D87 -> 5134.3931 | E88: =E79-E87 -> 8073.5105 | F88: =F79-F87 -> 29432.072 | G88: =G79-G87 -> 62820.537 | H88: =H79-H87 -> 109176.49 | I88: =I79-I87 -> 159019.53 | J88: =J79-J87 -> 198502.82 | K88: =K79-K87 -> 222817.47 | ... S88: =S79-S87 -> 320259.71
A89: EBITDA Margin % (memo) | D89: =IFERROR(D88/D65,0) -> 0.47194909 | E89: =IFERROR(E88/E65,0) -> 0.56648303 | F89: =IFERROR(F88/F65,0) -> 0.53325679 | G89: =IFERROR(G88/G65,0) -> 0.57957459 | H89: =IFERROR(H88/H65,0) -> 0.6198995 | I89: =IFERROR(I88/I65,0) -> 0.72008035 | J89: =IFERROR(J88/J65,0) -> 0.74306592 | K89: =IFERROR(K88/K65,0) -> 0.80931715 | ... S89: =IFERROR(S88/S65,0) -> 0.84270982
A91: ▸ EBITDA → EBIT (R&D is in Module OpEx above; only D&A below)
A92: Attributed R&D ($mm): component of Module OpEx total (row 87) | D92: =D$65*MAX(INDEX(Assumptions!$B:$B,MATCH("Starlink R&D: end-state % (floor)",Assumptions!$A$1:$A$327,0)), INDEX(Assumptions!$B:$B,MATCH("Starlink R&D: start % of (Starlink+Starshield) rev",Assumptions!$A$1:$A$327,0))*(1+INDEX(Assumptions!$B:$B,MATCH("Starlink R&D: CAGR (taper)",Assumptions!$A$1:$A$327,0)))^D$5) -> 576.59362 | E92: =E$65*MAX(INDEX(Assumptions!$B:$B,MATCH("Starlink R&D: end-state % (floor)",Assumptions!$A$1:$A$327,0)), INDEX(Assumptions!$B:$B,MATCH("Starlink R&D: start % of (Starlink+Starshield) rev",Assumptions!$A$1:$A$327,0))*(1+INDEX(Assumptions!$B:$B,MATCH("Starlink R&D: CAGR (taper)",Assumptions!$A$1:$A$327,0)))^E$5) -> 679.81992 | F92: =F$65*MAX(INDEX(Assumptions!$B:$B,MATCH("Starlink R&D: end-state % (floor)",Assumptions!$A$1:$A$327,0)), INDEX(Assumptions!$B:$B,MATCH("Starlink R&D: start % of (Starlink+Starshield) rev",Assumptions!$A$1:$A$327,0))*(1+INDEX(Assumptions!$B:$B,MATCH("Starlink R&D: CAGR (taper)",Assumptions!$A$1:$A$327,0)))^F$5) -> 2369.4379 | G92: =G$65*MAX(INDEX(Assumptions!$B:$B,MATCH("Starlink R&D: end-state % (floor)",Assumptions!$A$1:$A$327,0)), INDEX(Assumptions!$B:$B,MATCH("Starlink R&D: start % of (Starlink+Starshield) rev",Assumptions!$A$1:$A$327,0))*(1+INDEX(Assumptions!$B:$B,MATCH("Starlink R&D: CAGR (taper)",Assumptions!$A$1:$A$327,0)))^G$5) -> 4187.8942 | H92: =H$65*MAX(INDEX(Assumptions!$B:$B,MATCH("Starlink R&D: end-state % (floor)",Assumptions!$A$1:$A$327,0)), INDEX(Assumptions!$B:$B,MATCH("Starlink R&D: start % of (Starlink+Starshield) rev",Assumptions!$A$1:$A$327,0))*(1+INDEX(Assumptions!$B:$B,MATCH("Starlink R&D: CAGR (taper)",Assumptions!$A$1:$A$327,0)))^H$5) -> 6124.2617 | I92: =I$65*MAX(INDEX(Assumptions!$B:$B,MATCH("Starlink R&D: end-state % (floor)",Assumptions!$A$1:$A$327,0)), INDEX(Assumptions!$B:$B,MATCH("Starlink R&D: start % of (Starlink+Starshield) rev",Assumptions!$A$1:$A$327,0))*(1+INDEX(Assumptions!$B:$B,MATCH("Starlink R&D: CAGR (taper)",Assumptions!$A$1:$A$327,0)))^I$5) -> 6911.2709 | J92: =J$65*MAX(INDEX(Assumptions!$B:$B,MATCH("Starlink R&D: end-state % (floor)",Assumptions!$A$1:$A$327,0)), INDEX(Assumptions!$B:$B,MATCH("Starlink R&D: start % of (Starlink+Starshield) rev",Assumptions!$A$1:$A$327,0))*(1+INDEX(Assumptions!$B:$B,MATCH("Starlink R&D: CAGR (taper)",Assumptions!$A$1:$A$327,0)))^J$5) -> 8014.2078 | K92: =K$65*MAX(INDEX(Assumptions!$B:$B,MATCH("Starlink R&D: end-state % (floor)",Assumptions!$A$1:$A$327,0)), INDEX(Assumptions!$B:$B,MATCH("Starlink R&D: start % of (Starlink+Starshield) rev",Assumptions!$A$1:$A$327,0))*(1+INDEX(Assumptions!$B:$B,MATCH("Starlink R&D: CAGR (taper)",Assumptions!$A$1:$A$327,0)))^K$5) -> 8259.4617 | ... S92: =S$65*MAX(INDEX(Assumptions!$B:$B,MATCH("Starlink R&D: end-state % (floor)",Assumptions!$A$1:$A$327,0)), INDEX(Assumptions!$B:$B,MATCH("Starlink R&D: start % of (Starlink+Starshield) rev",Assumptions!$A$1:$A$327,0))*(1+INDEX(Assumptions!$B:$B,MATCH("Starlink R&D: CAGR (taper)",Assumptions!$A$1:$A$327,0)))^S$5) -> 11401.067
A93: Constellation D&A ($mm) | D93: =(D$40*INDEX(Assumptions!$B:$B,MATCH("Legacy V1 sat mass (kg)",Assumptions!$A$1:$A$327,0)) + D$41*INDEX(Assumptions!$B:$B,MATCH("Legacy V1.5 sat mass (kg)",Assumptions!$A$1:$A$327,0)) + D$42*INDEX(Assumptions!$B:$B,MATCH("V2 BB sat mass (kg)",Assumptions!$A$1:$A$327,0)) + D$43*INDEX(Assumptions!$B:$B,MATCH("V3 BB sat mass (kg)",Assumptions!$A$1:$A$327,0)) + D$52*INDEX(Assumptions!$B:$B,MATCH("V2 DTC sat mass (kg)",Assumptions!$A$1:$A$327,0)) + D$53*INDEX(Assumptions!$B:$B,MATCH("V3 DTC sat mass (kg)",Assumptions!$A$1:$A$327,0)) + D$135*INDEX(Assumptions!$B:$B,MATCH("Starshield sat mass (kg)",Assumptions!$A$1:$A$327,0)))*INDEX(Assumptions!$B:$B,MATCH("Satellite Dep per kg: base year ($/kg/yr)",Assumptions!$A$1:$A$327,0))/1000000 -> 550.58484 | E93: =(E$40*INDEX(Assumptions!$B:$B,MATCH("Legacy V1 sat mass (kg)",Assumptions!$A$1:$A$327,0)) + E$41*INDEX(Assumptions!$B:$B,MATCH("Legacy V1.5 sat mass (kg)",Assumptions!$A$1:$A$327,0)) + E$42*INDEX(Assumptions!$B:$B,MATCH("V2 BB sat mass (kg)",Assumptions!$A$1:$A$327,0)) + E$43*INDEX(Assumptions!$B:$B,MATCH("V3 BB sat mass (kg)",Assumptions!$A$1:$A$327,0)) + E$52*INDEX(Assumptions!$B:$B,MATCH("V2 DTC sat mass (kg)",Assumptions!$A$1:$A$327,0)) + E$53*INDEX(Assumptions!$B:$B,MATCH("V3 DTC sat mass (kg)",Assumptions!$A$1:$A$327,0)) + E$135*INDEX(Assumptions!$B:$B,MATCH("Starshield sat mass (kg)",Assumptions!$A$1:$A$327,0)))*INDEX(Assumptions!$B:$B,MATCH("Satellite Dep per kg: base year ($/kg/yr)",Assumptions!$A$1:$A$327,0))/1000000 -> 717.28501 | F93: =(F$40*INDEX(Assumptions!$B:$B,MATCH("Legacy V1 sat mass (kg)",Assumptions!$A$1:$A$327,0)) + F$41*INDEX(Assumptions!$B:$B,MATCH("Legacy V1.5 sat mass (kg)",Assumptions!$A$1:$A$327,0)) + F$42*INDEX(Assumptions!$B:$B,MATCH("V2 BB sat mass (kg)",Assumptions!$A$1:$A$327,0)) + F$43*INDEX(Assumptions!$B:$B,MATCH("V3 BB sat mass (kg)",Assumptions!$A$1:$A$327,0)) + F$52*INDEX(Assumptions!$B:$B,MATCH("V2 DTC sat mass (kg)",Assumptions!$A$1:$A$327,0)) + F$53*INDEX(Assumptions!$B:$B,MATCH("V3 DTC sat mass (kg)",Assumptions!$A$1:$A$327,0)) + F$135*INDEX(Assumptions!$B:$B,MATCH("Starshield sat mass (kg)",Assumptions!$A$1:$A$327,0)))*INDEX(Assumptions!$B:$B,MATCH("Satellite Dep per kg: base year ($/kg/yr)",Assumptions!$A$1:$A$327,0))/1000000 -> 1691.3848 | G93: =(G$40*INDEX(Assumptions!$B:$B,MATCH("Legacy V1 sat mass (kg)",Assumptions!$A$1:$A$327,0)) + G$41*INDEX(Assumptions!$B:$B,MATCH("Legacy V1.5 sat mass (kg)",Assumptions!$A$1:$A$327,0)) + G$42*INDEX(Assumptions!$B:$B,MATCH("V2 BB sat mass (kg)",Assumptions!$A$1:$A$327,0)) + G$43*INDEX(Assumptions!$B:$B,MATCH("V3 BB sat mass (kg)",Assumptions!$A$1:$A$327,0)) + G$52*INDEX(Assumptions!$B:$B,MATCH("V2 DTC sat mass (kg)",Assumptions!$A$1:$A$327,0)) + G$53*INDEX(Assumptions!$B:$B,MATCH("V3 DTC sat mass (kg)",Assumptions!$A$1:$A$327,0)) + G$135*INDEX(Assumptions!$B:$B,MATCH("Starshield sat mass (kg)",Assumptions!$A$1:$A$327,0)))*INDEX(Assumptions!$B:$B,MATCH("Satellite Dep per kg: base year ($/kg/yr)",Assumptions!$A$1:$A$327,0))/1000000 -> 3996.0452 | H93: =(H$40*INDEX(Assumptions!$B:$B,MATCH("Legacy V1 sat mass (kg)",Assumptions!$A$1:$A$327,0)) + H$41*INDEX(Assumptions!$B:$B,MATCH("Legacy V1.5 sat mass (kg)",Assumptions!$A$1:$A$327,0)) + H$42*INDEX(Assumptions!$B:$B,MATCH("V2 BB sat mass (kg)",Assumptions!$A$1:$A$327,0)) + H$43*INDEX(Assumptions!$B:$B,MATCH("V3 BB sat mass (kg)",Assumptions!$A$1:$A$327,0)) + H$52*INDEX(Assumptions!$B:$B,MATCH("V2 DTC sat mass (kg)",Assumptions!$A$1:$A$327,0)) + H$53*INDEX(Assumptions!$B:$B,MATCH("V3 DTC sat mass (kg)",Assumptions!$A$1:$A$327,0)) + H$135*INDEX(Assumptions!$B:$B,MATCH("Starshield sat mass (kg)",Assumptions!$A$1:$A$327,0)))*INDEX(Assumptions!$B:$B,MATCH("Satellite Dep per kg: base year ($/kg/yr)",Assumptions!$A$1:$A$327,0))/1000000 -> 9776.5299 | I93: =(I$40*INDEX(Assumptions!$B:$B,MATCH("Legacy V1 sat mass (kg)",Assumptions!$A$1:$A$327,0)) + I$41*INDEX(Assumptions!$B:$B,MATCH("Legacy V1.5 sat mass (kg)",Assumptions!$A$1:$A$327,0)) + I$42*INDEX(Assumptions!$B:$B,MATCH("V2 BB sat mass (kg)",Assumptions!$A$1:$A$327,0)) + I$43*INDEX(Assumptions!$B:$B,MATCH("V3 BB sat mass (kg)",Assumptions!$A$1:$A$327,0)) + I$52*INDEX(Assumptions!$B:$B,MATCH("V2 DTC sat mass (kg)",Assumptions!$A$1:$A$327,0)) + I$53*INDEX(Assumptions!$B:$B,MATCH("V3 DTC sat mass (kg)",Assumptions!$A$1:$A$327,0)) + I$135*INDEX(Assumptions!$B:$B,MATCH("Starshield sat mass (kg)",Assumptions!$A$1:$A$327,0)))*INDEX(Assumptions!$B:$B,MATCH("Satellite Dep per kg: base year ($/kg/yr)",Assumptions!$A$1:$A$327,0))/1000000 -> 18679.537 | J93: =(J$40*INDEX(Assumptions!$B:$B,MATCH("Legacy V1 sat mass (kg)",Assumptions!$A$1:$A$327,0)) + J$41*INDEX(Assumptions!$B:$B,MATCH("Legacy V1.5 sat mass (kg)",Assumptions!$A$1:$A$327,0)) + J$42*INDEX(Assumptions!$B:$B,MATCH("V2 BB sat mass (kg)",Assumptions!$A$1:$A$327,0)) + J$43*INDEX(Assumptions!$B:$B,MATCH("V3 BB sat mass (kg)",Assumptions!$A$1:$A$327,0)) + J$52*INDEX(Assumptions!$B:$B,MATCH("V2 DTC sat mass (kg)",Assumptions!$A$1:$A$327,0)) + J$53*INDEX(Assumptions!$B:$B,MATCH("V3 DTC sat mass (kg)",Assumptions!$A$1:$A$327,0)) + J$135*INDEX(Assumptions!$B:$B,MATCH("Starshield sat mass (kg)",Assumptions!$A$1:$A$327,0)))*INDEX(Assumptions!$B:$B,MATCH("Satellite Dep per kg: base year ($/kg/yr)",Assumptions!$A$1:$A$327,0))/1000000 -> 32836.57 | K93: =(K$40*INDEX(Assumptions!$B:$B,MATCH("Legacy V1 sat mass (kg)",Assumptions!$A$1:$A$327,0)) + K$41*INDEX(Assumptions!$B:$B,MATCH("Legacy V1.5 sat mass (kg)",Assumptions!$A$1:$A$327,0)) + K$42*INDEX(Assumptions!$B:$B,MATCH("V2 BB sat mass (kg)",Assumptions!$A$1:$A$327,0)) + K$43*INDEX(Assumptions!$B:$B,MATCH("V3 BB sat mass (kg)",Assumptions!$A$1:$A$327,0)) + K$52*INDEX(Assumptions!$B:$B,MATCH("V2 DTC sat mass (kg)",Assumptions!$A$1:$A$327,0)) + K$53*INDEX(Assumptions!$B:$B,MATCH("V3 DTC sat mass (kg)",Assumptions!$A$1:$A$327,0)) + K$135*INDEX(Assumptions!$B:$B,MATCH("Starshield sat mass (kg)",Assumptions!$A$1:$A$327,0)))*INDEX(Assumptions!$B:$B,MATCH("Satellite Dep per kg: base year ($/kg/yr)",Assumptions!$A$1:$A$327,0))/1000000 -> 42029.666 | ... S93: =(S$40*INDEX(Assumptions!$B:$B,MATCH("Legacy V1 sat mass (kg)",Assumptions!$A$1:$A$327,0)) + S$41*INDEX(Assumptions!$B:$B,MATCH("Legacy V1.5 sat mass (kg)",Assumptions!$A$1:$A$327,0)) + S$42*INDEX(Assumptions!$B:$B,MATCH("V2 BB sat mass (kg)",Assumptions!$A$1:$A$327,0)) + S$43*INDEX(Assumptions!$B:$B,MATCH("V3 BB sat mass (kg)",Assumptions!$A$1:$A$327,0)) + S$52*INDEX(Assumptions!$B:$B,MATCH("V2 DTC sat mass (kg)",Assumptions!$A$1:$A$327,0)) + S$53*INDEX(Assumptions!$B:$B,MATCH("V3 DTC sat mass (kg)",Assumptions!$A$1:$A$327,0)) + S$135*INDEX(Assumptions!$B:$B,MATCH("Starshield sat mass (kg)",Assumptions!$A$1:$A$327,0)))*INDEX(Assumptions!$B:$B,MATCH("Satellite Dep per kg: base year ($/kg/yr)",Assumptions!$A$1:$A$327,0))/1000000 -> 90344.106
A94: Owned launch-fleet D&A ($mm) | D94: =MIN(SUM($D$103:D103), SUM($D$103:D103)/IFERROR(INDEX(Assumptions!$B:$B,MATCH("F9 booster economic life (years)",Assumptions!$A$1:$A$327,0)),8)) -> 25.538462 | E94: =MIN(SUM($D$103:E103), SUM($D$103:E103)/IFERROR(INDEX(Assumptions!$B:$B,MATCH("F9 booster economic life (years)",Assumptions!$A$1:$A$327,0)),8)) -> 43.814137 | F94: =MIN(SUM($D$103:F103), SUM($D$103:F103)/IFERROR(INDEX(Assumptions!$B:$B,MATCH("F9 booster economic life (years)",Assumptions!$A$1:$A$327,0)),8)) -> 198.66394 | G94: =MIN(SUM($D$103:G103), SUM($D$103:G103)/IFERROR(INDEX(Assumptions!$B:$B,MATCH("F9 booster economic life (years)",Assumptions!$A$1:$A$327,0)),8)) -> 425.24616 | H94: =MIN(SUM($D$103:H103), SUM($D$103:H103)/IFERROR(INDEX(Assumptions!$B:$B,MATCH("F9 booster economic life (years)",Assumptions!$A$1:$A$327,0)),8)) -> 709.81505 | I94: =MIN(SUM($D$103:I103), SUM($D$103:I103)/IFERROR(INDEX(Assumptions!$B:$B,MATCH("F9 booster economic life (years)",Assumptions!$A$1:$A$327,0)),8)) -> 986.78601 | J94: =MIN(SUM($D$103:J103), SUM($D$103:J103)/IFERROR(INDEX(Assumptions!$B:$B,MATCH("F9 booster economic life (years)",Assumptions!$A$1:$A$327,0)),8)) -> 1318.5857 | K94: =MIN(SUM($D$103:K103), SUM($D$103:K103)/IFERROR(INDEX(Assumptions!$B:$B,MATCH("F9 booster economic life (years)",Assumptions!$A$1:$A$327,0)),8)) -> 1405.1215 | ... S94: =MIN(SUM($D$103:S103), SUM($D$103:S103)/IFERROR(INDEX(Assumptions!$B:$B,MATCH("F9 booster economic life (years)",Assumptions!$A$1:$A$327,0)),8)) -> 1735.3983
A95: Launch facility share (frac) | D95: {=IFERROR((D$69+D$70)/((D$69+D$70)+(INDEX('Customer Launch'!$D:$AC,MATCH("F9 customer launches per year",'Customer Launch'!$A$1:$A$153,0),D$5+1)+INDEX('Customer Launch'!$D:$AC,MATCH("Starship customer launches per year",'Customer Launch'!$A$1:$A$153,0),D$5+1))),0)} -> 0.85128205 | E95: {=IFERROR((E$69+E$70)/((E$69+E$70)+(INDEX('Customer Launch'!$D:$AC,MATCH("F9 customer launches per year",'Customer Launch'!$A$1:$A$153,0),E$5+1)+INDEX('Customer Launch'!$D:$AC,MATCH("Starship customer launches per year",'Customer Launch'!$A$1:$A$153,0),E$5+1))),0)} -> 0.62162162 | F95: {=IFERROR((F$69+F$70)/((F$69+F$70)+(INDEX('Customer Launch'!$D:$AC,MATCH("F9 customer launches per year",'Customer Launch'!$A$1:$A$153,0),F$5+1)+INDEX('Customer Launch'!$D:$AC,MATCH("Starship customer launches per year",'Customer Launch'!$A$1:$A$153,0),F$5+1))),0)} -> 0.23353253 | G95: {=IFERROR((G$69+G$70)/((G$69+G$70)+(INDEX('Customer Launch'!$D:$AC,MATCH("F9 customer launches per year",'Customer Launch'!$A$1:$A$153,0),G$5+1)+INDEX('Customer Launch'!$D:$AC,MATCH("Starship customer launches per year",'Customer Launch'!$A$1:$A$153,0),G$5+1))),0)} -> 0.36681855 | H95: {=IFERROR((H$69+H$70)/((H$69+H$70)+(INDEX('Customer Launch'!$D:$AC,MATCH("F9 customer launches per year",'Customer Launch'!$A$1:$A$153,0),H$5+1)+INDEX('Customer Launch'!$D:$AC,MATCH("Starship customer launches per year",'Customer Launch'!$A$1:$A$153,0),H$5+1))),0)} -> 0.52003926 | I95: {=IFERROR((I$69+I$70)/((I$69+I$70)+(INDEX('Customer Launch'!$D:$AC,MATCH("F9 customer launches per year",'Customer Launch'!$A$1:$A$153,0),I$5+1)+INDEX('Customer Launch'!$D:$AC,MATCH("Starship customer launches per year",'Customer Launch'!$A$1:$A$153,0),I$5+1))),0)} -> 0.56521739 | J95: {=IFERROR((J$69+J$70)/((J$69+J$70)+(INDEX('Customer Launch'!$D:$AC,MATCH("F9 customer launches per year",'Customer Launch'!$A$1:$A$153,0),J$5+1)+INDEX('Customer Launch'!$D:$AC,MATCH("Starship customer launches per year",'Customer Launch'!$A$1:$A$153,0),J$5+1))),0)} -> 0.67675545 | K95: {=IFERROR((K$69+K$70)/((K$69+K$70)+(INDEX('Customer Launch'!$D:$AC,MATCH("F9 customer launches per year",'Customer Launch'!$A$1:$A$153,0),K$5+1)+INDEX('Customer Launch'!$D:$AC,MATCH("Starship customer launches per year",'Customer Launch'!$A$1:$A$153,0),K$5+1))),0)} -> 0.54062268 | ... S95: {=IFERROR((S$69+S$70)/((S$69+S$70)+(INDEX('Customer Launch'!$D:$AC,MATCH("F9 customer launches per year",'Customer Launch'!$A$1:$A$153,0),S$5+1)+INDEX('Customer Launch'!$D:$AC,MATCH("Starship customer launches per year",'Customer Launch'!$A$1:$A$153,0),S$5+1))),0)} -> 0.98503741
A96: Facility / ground D&A ($mm) | D96: {=INDEX('Facilities Build'!$D:$AC,MATCH("Sat-mfg facility D&A ($mm)*",'Facilities Build'!$A$1:$A$74,0),D$5+1)+INDEX('Facilities Build'!$D:$AC,MATCH("Launch/vehicle facility D&A total ($mm)*",'Facilities Build'!$A$1:$A$74,0),D$5+1)*D$95} -> 26.26044 | E96: {=INDEX('Facilities Build'!$D:$AC,MATCH("Sat-mfg facility D&A ($mm)*",'Facilities Build'!$A$1:$A$74,0),E$5+1)+INDEX('Facilities Build'!$D:$AC,MATCH("Launch/vehicle facility D&A total ($mm)*",'Facilities Build'!$A$1:$A$74,0),E$5+1)*E$95} -> 43.29279 | F96: {=INDEX('Facilities Build'!$D:$AC,MATCH("Sat-mfg facility D&A ($mm)*",'Facilities Build'!$A$1:$A$74,0),F$5+1)+INDEX('Facilities Build'!$D:$AC,MATCH("Launch/vehicle facility D&A total ($mm)*",'Facilities Build'!$A$1:$A$74,0),F$5+1)*F$95} -> 54.346458 | G96: {=INDEX('Facilities Build'!$D:$AC,MATCH("Sat-mfg facility D&A ($mm)*",'Facilities Build'!$A$1:$A$74,0),G$5+1)+INDEX('Facilities Build'!$D:$AC,MATCH("Launch/vehicle facility D&A total ($mm)*",'Facilities Build'!$A$1:$A$74,0),G$5+1)*G$95} -> 102.7681 | H96: {=INDEX('Facilities Build'!$D:$AC,MATCH("Sat-mfg facility D&A ($mm)*",'Facilities Build'!$A$1:$A$74,0),H$5+1)+INDEX('Facilities Build'!$D:$AC,MATCH("Launch/vehicle facility D&A total ($mm)*",'Facilities Build'!$A$1:$A$74,0),H$5+1)*H$95} -> 192.85601 | I96: {=INDEX('Facilities Build'!$D:$AC,MATCH("Sat-mfg facility D&A ($mm)*",'Facilities Build'!$A$1:$A$74,0),I$5+1)+INDEX('Facilities Build'!$D:$AC,MATCH("Launch/vehicle facility D&A total ($mm)*",'Facilities Build'!$A$1:$A$74,0),I$5+1)*I$95} -> 267.42355 | J96: {=INDEX('Facilities Build'!$D:$AC,MATCH("Sat-mfg facility D&A ($mm)*",'Facilities Build'!$A$1:$A$74,0),J$5+1)+INDEX('Facilities Build'!$D:$AC,MATCH("Launch/vehicle facility D&A total ($mm)*",'Facilities Build'!$A$1:$A$74,0),J$5+1)*J$95} -> 394.99103 | K96: {=INDEX('Facilities Build'!$D:$AC,MATCH("Sat-mfg facility D&A ($mm)*",'Facilities Build'!$A$1:$A$74,0),K$5+1)+INDEX('Facilities Build'!$D:$AC,MATCH("Launch/vehicle facility D&A total ($mm)*",'Facilities Build'!$A$1:$A$74,0),K$5+1)*K$95} -> 389.95189 | ... S96: {=INDEX('Facilities Build'!$D:$AC,MATCH("Sat-mfg facility D&A ($mm)*",'Facilities Build'!$A$1:$A$74,0),S$5+1)+INDEX('Facilities Build'!$D:$AC,MATCH("Launch/vehicle facility D&A total ($mm)*",'Facilities Build'!$A$1:$A$74,0),S$5+1)*S$95} -> 922.25493
A97: D&A total ($mm) | D97: =D93+D94+D96 -> 602.38374 | E97: =E93+E94+E96 -> 804.39194 | F97: =F93+F94+F96 -> 1944.3952 | G97: =G93+G94+G96 -> 4524.0594 | H97: =H93+H94+H96 -> 10679.201 | I97: =I93+I94+I96 -> 19933.746 | J97: =J93+J94+J96 -> 34550.146 | K97: =K93+K94+K96 -> 43824.739 | ... S97: =S93+S94+S96 -> 93001.759
A98: Module EBIT ($mm) | D98: =D88-D97 -> 4532.0093 | E98: =E88-E97 -> 7269.1185 | F98: =F88-F97 -> 27487.676 | G98: =G88-G97 -> 58296.477 | H98: =H88-H97 -> 98497.288 | I98: =I88-I97 -> 139085.78 | J98: =J88-J97 -> 163952.68 | K98: =K88-K97 -> 178992.73 | ... S98: =S88-S97 -> 227257.95
A100: ▸ CAPEX → MODULE FCF
A101: Satellite build CapEx ($mm) | D101: =D$143/1000000*(D32*INDEX(Assumptions!$B:$B,MATCH("V2 BB sat mass (kg)",Assumptions!$A$1:$A$327,0)) + D33*INDEX(Assumptions!$B:$B,MATCH("V2 DTC sat mass (kg)",Assumptions!$A$1:$A$327,0)) + D34*INDEX(Assumptions!$B:$B,MATCH("V3 BB sat mass (kg)",Assumptions!$A$1:$A$327,0)) + D35*INDEX(Assumptions!$B:$B,MATCH("V3 DTC sat mass (kg)",Assumptions!$A$1:$A$327,0)) + D36*INDEX(Assumptions!$B:$B,MATCH("Starshield sat mass (kg)",Assumptions!$A$1:$A$327,0))) -> 1674.816 | E101: =E$143/1000000*(E32*INDEX(Assumptions!$B:$B,MATCH("V2 BB sat mass (kg)",Assumptions!$A$1:$A$327,0)) + E33*INDEX(Assumptions!$B:$B,MATCH("V2 DTC sat mass (kg)",Assumptions!$A$1:$A$327,0)) + E34*INDEX(Assumptions!$B:$B,MATCH("V3 BB sat mass (kg)",Assumptions!$A$1:$A$327,0)) + E35*INDEX(Assumptions!$B:$B,MATCH("V3 DTC sat mass (kg)",Assumptions!$A$1:$A$327,0)) + E36*INDEX(Assumptions!$B:$B,MATCH("Starshield sat mass (kg)",Assumptions!$A$1:$A$327,0))) -> 1405.716 | F101: =F$143/1000000*(F32*INDEX(Assumptions!$B:$B,MATCH("V2 BB sat mass (kg)",Assumptions!$A$1:$A$327,0)) + F33*INDEX(Assumptions!$B:$B,MATCH("V2 DTC sat mass (kg)",Assumptions!$A$1:$A$327,0)) + F34*INDEX(Assumptions!$B:$B,MATCH("V3 BB sat mass (kg)",Assumptions!$A$1:$A$327,0)) + F35*INDEX(Assumptions!$B:$B,MATCH("V3 DTC sat mass (kg)",Assumptions!$A$1:$A$327,0)) + F36*INDEX(Assumptions!$B:$B,MATCH("Starshield sat mass (kg)",Assumptions!$A$1:$A$327,0))) -> 5104.3212 | G101: =G$143/1000000*(G32*INDEX(Assumptions!$B:$B,MATCH("V2 BB sat mass (kg)",Assumptions!$A$1:$A$327,0)) + G33*INDEX(Assumptions!$B:$B,MATCH("V2 DTC sat mass (kg)",Assumptions!$A$1:$A$327,0)) + G34*INDEX(Assumptions!$B:$B,MATCH("V3 BB sat mass (kg)",Assumptions!$A$1:$A$327,0)) + G35*INDEX(Assumptions!$B:$B,MATCH("V3 DTC sat mass (kg)",Assumptions!$A$1:$A$327,0)) + G36*INDEX(Assumptions!$B:$B,MATCH("Starshield sat mass (kg)",Assumptions!$A$1:$A$327,0))) -> 11652.75 | H101: =H$143/1000000*(H32*INDEX(Assumptions!$B:$B,MATCH("V2 BB sat mass (kg)",Assumptions!$A$1:$A$327,0)) + H33*INDEX(Assumptions!$B:$B,MATCH("V2 DTC sat mass (kg)",Assumptions!$A$1:$A$327,0)) + H34*INDEX(Assumptions!$B:$B,MATCH("V3 BB sat mass (kg)",Assumptions!$A$1:$A$327,0)) + H35*INDEX(Assumptions!$B:$B,MATCH("V3 DTC sat mass (kg)",Assumptions!$A$1:$A$327,0)) + H36*INDEX(Assumptions!$B:$B,MATCH("Starshield sat mass (kg)",Assumptions!$A$1:$A$327,0))) -> 26577.582 | I101: =I$143/1000000*(I32*INDEX(Assumptions!$B:$B,MATCH("V2 BB sat mass (kg)",Assumptions!$A$1:$A$327,0)) + I33*INDEX(Assumptions!$B:$B,MATCH("V2 DTC sat mass (kg)",Assumptions!$A$1:$A$327,0)) + I34*INDEX(Assumptions!$B:$B,MATCH("V3 BB sat mass (kg)",Assumptions!$A$1:$A$327,0)) + I35*INDEX(Assumptions!$B:$B,MATCH("V3 DTC sat mass (kg)",Assumptions!$A$1:$A$327,0)) + I36*INDEX(Assumptions!$B:$B,MATCH("Starshield sat mass (kg)",Assumptions!$A$1:$A$327,0))) -> 38305.847 | J101: =J$143/1000000*(J32*INDEX(Assumptions!$B:$B,MATCH("V2 BB sat mass (kg)",Assumptions!$A$1:$A$327,0)) + J33*INDEX(Assumptions!$B:$B,MATCH("V2 DTC sat mass (kg)",Assumptions!$A$1:$A$327,0)) + J34*INDEX(Assumptions!$B:$B,MATCH("V3 BB sat mass (kg)",Assumptions!$A$1:$A$327,0)) + J35*INDEX(Assumptions!$B:$B,MATCH("V3 DTC sat mass (kg)",Assumptions!$A$1:$A$327,0)) + J36*INDEX(Assumptions!$B:$B,MATCH("Starshield sat mass (kg)",Assumptions!$A$1:$A$327,0))) -> 58276.737 | K101: =K$143/1000000*(K32*INDEX(Assumptions!$B:$B,MATCH("V2 BB sat mass (kg)",Assumptions!$A$1:$A$327,0)) + K33*INDEX(Assumptions!$B:$B,MATCH("V2 DTC sat mass (kg)",Assumptions!$A$1:$A$327,0)) + K34*INDEX(Assumptions!$B:$B,MATCH("V3 BB sat mass (kg)",Assumptions!$A$1:$A$327,0)) + K35*INDEX(Assumptions!$B:$B,MATCH("V3 DTC sat mass (kg)",Assumptions!$A$1:$A$327,0)) + K36*INDEX(Assumptions!$B:$B,MATCH("Starshield sat mass (kg)",Assumptions!$A$1:$A$327,0))) -> 39764.718 | ... S101: =S$143/1000000*(S32*INDEX(Assumptions!$B:$B,MATCH("V2 BB sat mass (kg)",Assumptions!$A$1:$A$327,0)) + S33*INDEX(Assumptions!$B:$B,MATCH("V2 DTC sat mass (kg)",Assumptions!$A$1:$A$327,0)) + S34*INDEX(Assumptions!$B:$B,MATCH("V3 BB sat mass (kg)",Assumptions!$A$1:$A$327,0)) + S35*INDEX(Assumptions!$B:$B,MATCH("V3 DTC sat mass (kg)",Assumptions!$A$1:$A$327,0)) + S36*INDEX(Assumptions!$B:$B,MATCH("Starshield sat mass (kg)",Assumptions!$A$1:$A$327,0))) -> 35103.201
A102: Facility / ground CapEx ($mm) | D102: {=IFERROR(INDEX('Facilities Build'!$D:$AC,MATCH("Sat-mfg facility CapEx total ($mm)*",'Facilities Build'!$A$1:$A$74,0),D$5+1),0)} -> 107.35165 | E102: {=IFERROR(INDEX('Facilities Build'!$D:$AC,MATCH("Sat-mfg facility CapEx total ($mm)*",'Facilities Build'!$A$1:$A$74,0),E$5+1),0)} -> 144.66642 | F102: {=IFERROR(INDEX('Facilities Build'!$D:$AC,MATCH("Sat-mfg facility CapEx total ($mm)*",'Facilities Build'!$A$1:$A$74,0),F$5+1),0)} -> 553.84364 | G102: {=IFERROR(INDEX('Facilities Build'!$D:$AC,MATCH("Sat-mfg facility CapEx total ($mm)*",'Facilities Build'!$A$1:$A$74,0),G$5+1),0)} -> 903.66398 | H102: {=IFERROR(INDEX('Facilities Build'!$D:$AC,MATCH("Sat-mfg facility CapEx total ($mm)*",'Facilities Build'!$A$1:$A$74,0),H$5+1),0)} -> 1776.2951 | I102: {=IFERROR(INDEX('Facilities Build'!$D:$AC,MATCH("Sat-mfg facility CapEx total ($mm)*",'Facilities Build'!$A$1:$A$74,0),I$5+1),0)} -> 1529.4637 | J102: {=IFERROR(INDEX('Facilities Build'!$D:$AC,MATCH("Sat-mfg facility CapEx total ($mm)*",'Facilities Build'!$A$1:$A$74,0),J$5+1),0)} -> 2560.4991 | K102: {=IFERROR(INDEX('Facilities Build'!$D:$AC,MATCH("Sat-mfg facility CapEx total ($mm)*",'Facilities Build'!$A$1:$A$74,0),K$5+1),0)} -> 93.855319 | ... S102: {=IFERROR(INDEX('Facilities Build'!$D:$AC,MATCH("Sat-mfg facility CapEx total ($mm)*",'Facilities Build'!$A$1:$A$74,0),S$5+1),0)} -> 78.675805
A103: Owned launch-vehicle CapEx ($mm) | D103: {=IFERROR(D69/INDEX('Vehicle Build'!$D:$AC,MATCH("Memo: Total F9 launches (internal + customer)",'Vehicle Build'!$A$1:$A$119,0),D$5+1),0)*INDEX('Vehicle Build'!$D:$AC,MATCH("F9 boosters built per year",'Vehicle Build'!$A$1:$A$119,0),D$5+1)*INDEX(Assumptions!$B:$B,MATCH("F9 booster (1st stage) mfg cost ($mm/unit)",Assumptions!$A$1:$A$327,0))*(1-INDEX(Assumptions!$B:$B,MATCH("F9 Wright's Law mfg learning rate",Assumptions!$A$1:$A$327,0)))^D$5+IFERROR(D70/INDEX('Vehicle Build'!$D:$AC,MATCH("Starship launches per year",'Vehicle Build'!$A$1:$A$119,0),D$5+1),0)*INDEX('Vehicle Build'!$D:$AC,MATCH("Total Starship build CapEx ($mm)",'Vehicle Build'!$A$1:$A$119,0),D$5+1)} -> 204.30769 | E103: {=IFERROR(E69/INDEX('Vehicle Build'!$D:$AC,MATCH("Memo: Total F9 launches (internal + customer)",'Vehicle Build'!$A$1:$A$119,0),E$5+1),0)*INDEX('Vehicle Build'!$D:$AC,MATCH("F9 boosters built per year",'Vehicle Build'!$A$1:$A$119,0),E$5+1)*INDEX(Assumptions!$B:$B,MATCH("F9 booster (1st stage) mfg cost ($mm/unit)",Assumptions!$A$1:$A$327,0))*(1-INDEX(Assumptions!$B:$B,MATCH("F9 Wright's Law mfg learning rate",Assumptions!$A$1:$A$327,0)))^E$5+IFERROR(E70/INDEX('Vehicle Build'!$D:$AC,MATCH("Starship launches per year",'Vehicle Build'!$A$1:$A$119,0),E$5+1),0)*INDEX('Vehicle Build'!$D:$AC,MATCH("Total Starship build CapEx ($mm)",'Vehicle Build'!$A$1:$A$119,0),E$5+1)} -> 146.20541 | F103: {=IFERROR(F69/INDEX('Vehicle Build'!$D:$AC,MATCH("Memo: Total F9 launches (internal + customer)",'Vehicle Build'!$A$1:$A$119,0),F$5+1),0)*INDEX('Vehicle Build'!$D:$AC,MATCH("F9 boosters built per year",'Vehicle Build'!$A$1:$A$119,0),F$5+1)*INDEX(Assumptions!$B:$B,MATCH("F9 booster (1st stage) mfg cost ($mm/unit)",Assumptions!$A$1:$A$327,0))*(1-INDEX(Assumptions!$B:$B,MATCH("F9 Wright's Law mfg learning rate",Assumptions!$A$1:$A$327,0)))^F$5+IFERROR(F70/INDEX('Vehicle Build'!$D:$AC,MATCH("Starship launches per year",'Vehicle Build'!$A$1:$A$119,0),F$5+1),0)*INDEX('Vehicle Build'!$D:$AC,MATCH("Total Starship build CapEx ($mm)",'Vehicle Build'!$A$1:$A$119,0),F$5+1)} -> 1238.7984 | G103: {=IFERROR(G69/INDEX('Vehicle Build'!$D:$AC,MATCH("Memo: Total F9 launches (internal + customer)",'Vehicle Build'!$A$1:$A$119,0),G$5+1),0)*INDEX('Vehicle Build'!$D:$AC,MATCH("F9 boosters built per year",'Vehicle Build'!$A$1:$A$119,0),G$5+1)*INDEX(Assumptions!$B:$B,MATCH("F9 booster (1st stage) mfg cost ($mm/unit)",Assumptions!$A$1:$A$327,0))*(1-INDEX(Assumptions!$B:$B,MATCH("F9 Wright's Law mfg learning rate",Assumptions!$A$1:$A$327,0)))^G$5+IFERROR(G70/INDEX('Vehicle Build'!$D:$AC,MATCH("Starship launches per year",'Vehicle Build'!$A$1:$A$119,0),G$5+1),0)*INDEX('Vehicle Build'!$D:$AC,MATCH("Total Starship build CapEx ($mm)",'Vehicle Build'!$A$1:$A$119,0),G$5+1)} -> 1812.6578 | H103: {=IFERROR(H69/INDEX('Vehicle Build'!$D:$AC,MATCH("Memo: Total F9 launches (internal + customer)",'Vehicle Build'!$A$1:$A$119,0),H$5+1),0)*INDEX('Vehicle Build'!$D:$AC,MATCH("F9 boosters built per year",'Vehicle Build'!$A$1:$A$119,0),H$5+1)*INDEX(Assumptions!$B:$B,MATCH("F9 booster (1st stage) mfg cost ($mm/unit)",Assumptions!$A$1:$A$327,0))*(1-INDEX(Assumptions!$B:$B,MATCH("F9 Wright's Law mfg learning rate",Assumptions!$A$1:$A$327,0)))^H$5+IFERROR(H70/INDEX('Vehicle Build'!$D:$AC,MATCH("Starship launches per year",'Vehicle Build'!$A$1:$A$119,0),H$5+1),0)*INDEX('Vehicle Build'!$D:$AC,MATCH("Total Starship build CapEx ($mm)",'Vehicle Build'!$A$1:$A$119,0),H$5+1)} -> 2276.5511 | I103: {=IFERROR(I69/INDEX('Vehicle Build'!$D:$AC,MATCH("Memo: Total F9 launches (internal + customer)",'Vehicle Build'!$A$1:$A$119,0),I$5+1),0)*INDEX('Vehicle Build'!$D:$AC,MATCH("F9 boosters built per year",'Vehicle Build'!$A$1:$A$119,0),I$5+1)*INDEX(Assumptions!$B:$B,MATCH("F9 booster (1st stage) mfg cost ($mm/unit)",Assumptions!$A$1:$A$327,0))*(1-INDEX(Assumptions!$B:$B,MATCH("F9 Wright's Law mfg learning rate",Assumptions!$A$1:$A$327,0)))^I$5+IFERROR(I70/INDEX('Vehicle Build'!$D:$AC,MATCH("Starship launches per year",'Vehicle Build'!$A$1:$A$119,0),I$5+1),0)*INDEX('Vehicle Build'!$D:$AC,MATCH("Total Starship build CapEx ($mm)",'Vehicle Build'!$A$1:$A$119,0),I$5+1)} -> 2215.7676 | J103: {=IFERROR(J69/INDEX('Vehicle Build'!$D:$AC,MATCH("Memo: Total F9 launches (internal + customer)",'Vehicle Build'!$A$1:$A$119,0),J$5+1),0)*INDEX('Vehicle Build'!$D:$AC,MATCH("F9 boosters built per year",'Vehicle Build'!$A$1:$A$119,0),J$5+1)*INDEX(Assumptions!$B:$B,MATCH("F9 booster (1st stage) mfg cost ($mm/unit)",Assumptions!$A$1:$A$327,0))*(1-INDEX(Assumptions!$B:$B,MATCH("F9 Wright's Law mfg learning rate",Assumptions!$A$1:$A$327,0)))^J$5+IFERROR(J70/INDEX('Vehicle Build'!$D:$AC,MATCH("Starship launches per year",'Vehicle Build'!$A$1:$A$119,0),J$5+1),0)*INDEX('Vehicle Build'!$D:$AC,MATCH("Total Starship build CapEx ($mm)",'Vehicle Build'!$A$1:$A$119,0),J$5+1)} -> 2654.3976 | K103: {=IFERROR(K69/INDEX('Vehicle Build'!$D:$AC,MATCH("Memo: Total F9 launches (internal + customer)",'Vehicle Build'!$A$1:$A$119,0),K$5+1),0)*INDEX('Vehicle Build'!$D:$AC,MATCH("F9 boosters built per year",'Vehicle Build'!$A$1:$A$119,0),K$5+1)*INDEX(Assumptions!$B:$B,MATCH("F9 booster (1st stage) mfg cost ($mm/unit)",Assumptions!$A$1:$A$327,0))*(1-INDEX(Assumptions!$B:$B,MATCH("F9 Wright's Law mfg learning rate",Assumptions!$A$1:$A$327,0)))^K$5+IFERROR(K70/INDEX('Vehicle Build'!$D:$AC,MATCH("Starship launches per year",'Vehicle Build'!$A$1:$A$119,0),K$5+1),0)*INDEX('Vehicle Build'!$D:$AC,MATCH("Total Starship build CapEx ($mm)",'Vehicle Build'!$A$1:$A$119,0),K$5+1)} -> 692.28638 | ... S103: {=IFERROR(S69/INDEX('Vehicle Build'!$D:$AC,MATCH("Memo: Total F9 launches (internal + customer)",'Vehicle Build'!$A$1:$A$119,0),S$5+1),0)*INDEX('Vehicle Build'!$D:$AC,MATCH("F9 boosters built per year",'Vehicle Build'!$A$1:$A$119,0),S$5+1)*INDEX(Assumptions!$B:$B,MATCH("F9 booster (1st stage) mfg cost ($mm/unit)",Assumptions!$A$1:$A$327,0))*(1-INDEX(Assumptions!$B:$B,MATCH("F9 Wright's Law mfg learning rate",Assumptions!$A$1:$A$327,0)))^S$5+IFERROR(S70/INDEX('Vehicle Build'!$D:$AC,MATCH("Starship launches per year",'Vehicle Build'!$A$1:$A$119,0),S$5+1),0)*INDEX('Vehicle Build'!$D:$AC,MATCH("Total Starship build CapEx ($mm)",'Vehicle Build'!$A$1:$A$119,0),S$5+1)} -> 432.75561
A104: Working capital ΔWC ($mm) | D104: =(D32+D33+D34+D35+D36)*INDEX(Assumptions!$B:$B,MATCH("Working capital per sat ($mm/sat): ΔWC T0",Assumptions!$A$1:$A$327,0)) -> 21.504 | E104: =(E32+E33+E34+E35+E36)*INDEX(Assumptions!$B:$B,MATCH("Working capital per sat ($mm/sat): ΔWC T0",Assumptions!$A$1:$A$327,0)) -> 17.904 | F104: =(F32+F33+F34+F35+F36)*INDEX(Assumptions!$B:$B,MATCH("Working capital per sat ($mm/sat): ΔWC T0",Assumptions!$A$1:$A$327,0)) -> 21.897677 | G104: =(G32+G33+G34+G35+G36)*INDEX(Assumptions!$B:$B,MATCH("Working capital per sat ($mm/sat): ΔWC T0",Assumptions!$A$1:$A$327,0)) -> 49.7909 | H104: =(H32+H33+H34+H35+H36)*INDEX(Assumptions!$B:$B,MATCH("Working capital per sat ($mm/sat): ΔWC T0",Assumptions!$A$1:$A$327,0)) -> 117.04075 | I104: =(I32+I33+I34+I35+I36)*INDEX(Assumptions!$B:$B,MATCH("Working capital per sat ($mm/sat): ΔWC T0",Assumptions!$A$1:$A$327,0)) -> 177.64872 | J104: =(J32+J33+J34+J35+J36)*INDEX(Assumptions!$B:$B,MATCH("Working capital per sat ($mm/sat): ΔWC T0",Assumptions!$A$1:$A$327,0)) -> 281.57613 | K104: =(K32+K33+K34+K35+K36)*INDEX(Assumptions!$B:$B,MATCH("Working capital per sat ($mm/sat): ΔWC T0",Assumptions!$A$1:$A$327,0)) -> 200.33511 | ... S104: =(S32+S33+S34+S35+S36)*INDEX(Assumptions!$B:$B,MATCH("Working capital per sat ($mm/sat): ΔWC T0",Assumptions!$A$1:$A$327,0)) -> 199.51214
A105: Module CapEx total ($mm) | D105: =SUM(D101:D104) -> 2007.9793 | E105: =SUM(E101:E104) -> 1714.4918 | F105: =SUM(F101:F104) -> 6918.861 | G105: =SUM(G101:G104) -> 14418.862 | H105: =SUM(H101:H104) -> 30747.469 | I105: =SUM(I101:I104) -> 42228.727 | J105: =SUM(J101:J104) -> 63773.21 | K105: =SUM(K101:K104) -> 40751.195 | ... S105: =SUM(S101:S104) -> 35814.144
A106: Module FCF ($mm) | D106: =D98+D97-D105 -> 3126.4137 | E106: =E98+E97-E105 -> 6359.0186 | F106: =F98+F97-F105 -> 22513.211 | G106: =G98+G97-G105 -> 48401.674 | H106: =H98+H97-H105 -> 78429.02 | I106: =I98+I97-I105 -> 116790.8 | J106: =J98+J97-J105 -> 134729.61 | K106: =K98+K97-K105 -> 182066.27 | ... S106: =S98+S97-S105 -> 284445.57
A108: ▸ PER-SAT IRR ENGINE (v4 canonical): per cohort, one cost base
A109: Avg $/Gbps BB at Q (price-at-Q) | D109: {=INDEX('Demand Curves'!$D:$AC,MATCH("Memo: Average $/Gbps BB from curve",'Demand Curves'!$A$1:$A$167,0),COLUMN()-COLUMN($D109)+1)} -> 13740.781 | E109: {=INDEX('Demand Curves'!$D:$AC,MATCH("Memo: Average $/Gbps BB from curve",'Demand Curves'!$A$1:$A$167,0),COLUMN()-COLUMN($D109)+1)} -> 12352.493 | F109: {=INDEX('Demand Curves'!$D:$AC,MATCH("Memo: Average $/Gbps BB from curve",'Demand Curves'!$A$1:$A$167,0),COLUMN()-COLUMN($D109)+1)} -> 8072.9198 | G109: {=INDEX('Demand Curves'!$D:$AC,MATCH("Memo: Average $/Gbps BB from curve",'Demand Curves'!$A$1:$A$167,0),COLUMN()-COLUMN($D109)+1)} -> 5788.5536 | H109: {=INDEX('Demand Curves'!$D:$AC,MATCH("Memo: Average $/Gbps BB from curve",'Demand Curves'!$A$1:$A$167,0),COLUMN()-COLUMN($D109)+1)} -> 3917.7146 | I109: {=INDEX('Demand Curves'!$D:$AC,MATCH("Memo: Average $/Gbps BB from curve",'Demand Curves'!$A$1:$A$167,0),COLUMN()-COLUMN($D109)+1)} -> 3505.2853 | J109: {=INDEX('Demand Curves'!$D:$AC,MATCH("Memo: Average $/Gbps BB from curve",'Demand Curves'!$A$1:$A$167,0),COLUMN()-COLUMN($D109)+1)} -> 2697.4579 | K109: {=INDEX('Demand Curves'!$D:$AC,MATCH("Memo: Average $/Gbps BB from curve",'Demand Curves'!$A$1:$A$167,0),COLUMN()-COLUMN($D109)+1)} -> 2578.663 | ... S109: {=INDEX('Demand Curves'!$D:$AC,MATCH("Memo: Average $/Gbps BB from curve",'Demand Curves'!$A$1:$A$167,0),COLUMN()-COLUMN($D109)+1)} -> 1567.4334
A110: Avg $/Gbps DTC at Q (price-at-Q) | D110: {=INDEX('Demand Curves'!$D:$AC,MATCH("Memo: Average $/Gbps DTC from curve",'Demand Curves'!$A$1:$A$167,0),COLUMN()-COLUMN($D110)+1)} -> 1094104.6 | E110: {=INDEX('Demand Curves'!$D:$AC,MATCH("Memo: Average $/Gbps DTC from curve",'Demand Curves'!$A$1:$A$167,0),COLUMN()-COLUMN($D110)+1)} -> 1375055.1 | F110: {=INDEX('Demand Curves'!$D:$AC,MATCH("Memo: Average $/Gbps DTC from curve",'Demand Curves'!$A$1:$A$167,0),COLUMN()-COLUMN($D110)+1)} -> 1672541.1 | G110: {=INDEX('Demand Curves'!$D:$AC,MATCH("Memo: Average $/Gbps DTC from curve",'Demand Curves'!$A$1:$A$167,0),COLUMN()-COLUMN($D110)+1)} -> 1986770.8 | H110: {=INDEX('Demand Curves'!$D:$AC,MATCH("Memo: Average $/Gbps DTC from curve",'Demand Curves'!$A$1:$A$167,0),COLUMN()-COLUMN($D110)+1)} -> 2317957.1 | I110: {=INDEX('Demand Curves'!$D:$AC,MATCH("Memo: Average $/Gbps DTC from curve",'Demand Curves'!$A$1:$A$167,0),COLUMN()-COLUMN($D110)+1)} -> 1363941.4 | J110: {=INDEX('Demand Curves'!$D:$AC,MATCH("Memo: Average $/Gbps DTC from curve",'Demand Curves'!$A$1:$A$167,0),COLUMN()-COLUMN($D110)+1)} -> 848946.28 | K110: {=INDEX('Demand Curves'!$D:$AC,MATCH("Memo: Average $/Gbps DTC from curve",'Demand Curves'!$A$1:$A$167,0),COLUMN()-COLUMN($D110)+1)} -> 674279.3 | ... S110: {=INDEX('Demand Curves'!$D:$AC,MATCH("Memo: Average $/Gbps DTC from curve",'Demand Curves'!$A$1:$A$167,0),COLUMN()-COLUMN($D110)+1)} -> 441734.75
A112: V2 BB: margin per sat-yr ($mm) | D112: =IFERROR(D$109*INDEX(Assumptions!$B:$B,MATCH("V2 BB Gbps per sat",Assumptions!$A$1:$A$327,0))*D$21/1000000*(1-(D$87+D$75+D$76)/D$65) - INDEX(Assumptions!$B:$B,MATCH("Bandwidth/peering cost per Gbps ($mm/Gbps-yr)",Assumptions!$A$1:$A$327,0))*INDEX(Assumptions!$B:$B,MATCH("V2 BB Gbps per sat",Assumptions!$A$1:$A$327,0))*D$21, 0) -> 0.63706761 | E112: =IFERROR(E$109*INDEX(Assumptions!$B:$B,MATCH("V2 BB Gbps per sat",Assumptions!$A$1:$A$327,0))*E$21/1000000*(1-(E$87+E$75+E$76)/E$65) - INDEX(Assumptions!$B:$B,MATCH("Bandwidth/peering cost per Gbps ($mm/Gbps-yr)",Assumptions!$A$1:$A$327,0))*INDEX(Assumptions!$B:$B,MATCH("V2 BB Gbps per sat",Assumptions!$A$1:$A$327,0))*E$21, 0) -> 0.56492192 | F112: =IFERROR(F$109*INDEX(Assumptions!$B:$B,MATCH("V2 BB Gbps per sat",Assumptions!$A$1:$A$327,0))*F$21/1000000*(1-(F$87+F$75+F$76)/F$65) - INDEX(Assumptions!$B:$B,MATCH("Bandwidth/peering cost per Gbps ($mm/Gbps-yr)",Assumptions!$A$1:$A$327,0))*INDEX(Assumptions!$B:$B,MATCH("V2 BB Gbps per sat",Assumptions!$A$1:$A$327,0))*F$21, 0) -> 0.32657221 | G112: =IFERROR(G$109*INDEX(Assumptions!$B:$B,MATCH("V2 BB Gbps per sat",Assumptions!$A$1:$A$327,0))*G$21/1000000*(1-(G$87+G$75+G$76)/G$65) - INDEX(Assumptions!$B:$B,MATCH("Bandwidth/peering cost per Gbps ($mm/Gbps-yr)",Assumptions!$A$1:$A$327,0))*INDEX(Assumptions!$B:$B,MATCH("V2 BB Gbps per sat",Assumptions!$A$1:$A$327,0))*G$21, 0) -> 0.19815102 | H112: =IFERROR(H$109*INDEX(Assumptions!$B:$B,MATCH("V2 BB Gbps per sat",Assumptions!$A$1:$A$327,0))*H$21/1000000*(1-(H$87+H$75+H$76)/H$65) - INDEX(Assumptions!$B:$B,MATCH("Bandwidth/peering cost per Gbps ($mm/Gbps-yr)",Assumptions!$A$1:$A$327,0))*INDEX(Assumptions!$B:$B,MATCH("V2 BB Gbps per sat",Assumptions!$A$1:$A$327,0))*H$21, 0) -> 0.091976266 | I112: =IFERROR(I$109*INDEX(Assumptions!$B:$B,MATCH("V2 BB Gbps per sat",Assumptions!$A$1:$A$327,0))*I$21/1000000*(1-(I$87+I$75+I$76)/I$65) - INDEX(Assumptions!$B:$B,MATCH("Bandwidth/peering cost per Gbps ($mm/Gbps-yr)",Assumptions!$A$1:$A$327,0))*INDEX(Assumptions!$B:$B,MATCH("V2 BB Gbps per sat",Assumptions!$A$1:$A$327,0))*I$21, 0) -> 0.068938465 | J112: =IFERROR(J$109*INDEX(Assumptions!$B:$B,MATCH("V2 BB Gbps per sat",Assumptions!$A$1:$A$327,0))*J$21/1000000*(1-(J$87+J$75+J$76)/J$65) - INDEX(Assumptions!$B:$B,MATCH("Bandwidth/peering cost per Gbps ($mm/Gbps-yr)",Assumptions!$A$1:$A$327,0))*INDEX(Assumptions!$B:$B,MATCH("V2 BB Gbps per sat",Assumptions!$A$1:$A$327,0))*J$21, 0) -> 0.022237637 | K112: =IFERROR(K$109*INDEX(Assumptions!$B:$B,MATCH("V2 BB Gbps per sat",Assumptions!$A$1:$A$327,0))*K$21/1000000*(1-(K$87+K$75+K$76)/K$65) - INDEX(Assumptions!$B:$B,MATCH("Bandwidth/peering cost per Gbps ($mm/Gbps-yr)",Assumptions!$A$1:$A$327,0))*INDEX(Assumptions!$B:$B,MATCH("V2 BB Gbps per sat",Assumptions!$A$1:$A$327,0))*K$21, 0) -> 0.015162968 | ... S112: =IFERROR(S$109*INDEX(Assumptions!$B:$B,MATCH("V2 BB Gbps per sat",Assumptions!$A$1:$A$327,0))*S$21/1000000*(1-(S$87+S$75+S$76)/S$65) - INDEX(Assumptions!$B:$B,MATCH("Bandwidth/peering cost per Gbps ($mm/Gbps-yr)",Assumptions!$A$1:$A$327,0))*INDEX(Assumptions!$B:$B,MATCH("V2 BB Gbps per sat",Assumptions!$A$1:$A$327,0))*S$21, 0) -> -0.043529166
A113: V2 BB: CapEx slug per sat ($mm) | D113: =D$143*INDEX(Assumptions!$B:$B,MATCH("V2 BB sat mass (kg)",Assumptions!$A$1:$A$327,0))/1000000 + IFERROR(D$13/INDEX(Assumptions!$B:$B,MATCH("F9 sats per launch (V2 packing)",Assumptions!$A$1:$A$327,0)),0) + INDEX(Assumptions!$B:$B,MATCH("Working capital per sat ($mm/sat): ΔWC T0",Assumptions!$A$1:$A$327,0)) -> 1.1479808 | E113: =E$143*INDEX(Assumptions!$B:$B,MATCH("V2 BB sat mass (kg)",Assumptions!$A$1:$A$327,0))/1000000 + IFERROR(E$13/INDEX(Assumptions!$B:$B,MATCH("F9 sats per launch (V2 packing)",Assumptions!$A$1:$A$327,0)),0) + IFERROR(SUM($D$102:D102)/D142,0) + INDEX(Assumptions!$B:$B,MATCH("Working capital per sat ($mm/sat): ΔWC T0",Assumptions!$A$1:$A$327,0)) -> 1.1605523 | F113: =F$143*INDEX(Assumptions!$B:$B,MATCH("V2 BB sat mass (kg)",Assumptions!$A$1:$A$327,0))/1000000 + IFERROR(F$13/INDEX(Assumptions!$B:$B,MATCH("F9 sats per launch (V2 packing)",Assumptions!$A$1:$A$327,0)),0) + IFERROR(SUM($D$102:E102)/E142,0) + INDEX(Assumptions!$B:$B,MATCH("Working capital per sat ($mm/sat): ΔWC T0",Assumptions!$A$1:$A$327,0)) -> 1.1376372 | G113: =G$143*INDEX(Assumptions!$B:$B,MATCH("V2 BB sat mass (kg)",Assumptions!$A$1:$A$327,0))/1000000 + IFERROR(G$13/INDEX(Assumptions!$B:$B,MATCH("F9 sats per launch (V2 packing)",Assumptions!$A$1:$A$327,0)),0) + IFERROR(SUM($D$102:F102)/F142,0) + INDEX(Assumptions!$B:$B,MATCH("Working capital per sat ($mm/sat): ΔWC T0",Assumptions!$A$1:$A$327,0)) -> 1.1491075 | H113: =H$143*INDEX(Assumptions!$B:$B,MATCH("V2 BB sat mass (kg)",Assumptions!$A$1:$A$327,0))/1000000 + IFERROR(H$13/INDEX(Assumptions!$B:$B,MATCH("F9 sats per launch (V2 packing)",Assumptions!$A$1:$A$327,0)),0) + IFERROR(SUM($D$102:G102)/G142,0) + INDEX(Assumptions!$B:$B,MATCH("Working capital per sat ($mm/sat): ΔWC T0",Assumptions!$A$1:$A$327,0)) -> 1.1287272 | I113: =I$143*INDEX(Assumptions!$B:$B,MATCH("V2 BB sat mass (kg)",Assumptions!$A$1:$A$327,0))/1000000 + IFERROR(I$13/INDEX(Assumptions!$B:$B,MATCH("F9 sats per launch (V2 packing)",Assumptions!$A$1:$A$327,0)),0) + IFERROR(SUM($D$102:H102)/H142,0) + INDEX(Assumptions!$B:$B,MATCH("Working capital per sat ($mm/sat): ΔWC T0",Assumptions!$A$1:$A$327,0)) -> 1.0931627 | J113: =J$143*INDEX(Assumptions!$B:$B,MATCH("V2 BB sat mass (kg)",Assumptions!$A$1:$A$327,0))/1000000 + IFERROR(J$13/INDEX(Assumptions!$B:$B,MATCH("F9 sats per launch (V2 packing)",Assumptions!$A$1:$A$327,0)),0) + IFERROR(SUM($D$102:I102)/I142,0) + INDEX(Assumptions!$B:$B,MATCH("Working capital per sat ($mm/sat): ΔWC T0",Assumptions!$A$1:$A$327,0)) -> 1.0493815 | K113: =K$143*INDEX(Assumptions!$B:$B,MATCH("V2 BB sat mass (kg)",Assumptions!$A$1:$A$327,0))/1000000 + IFERROR(K$13/INDEX(Assumptions!$B:$B,MATCH("F9 sats per launch (V2 packing)",Assumptions!$A$1:$A$327,0)),0) + IFERROR(SUM($D$102:J102)/J142,0) + INDEX(Assumptions!$B:$B,MATCH("Working capital per sat ($mm/sat): ΔWC T0",Assumptions!$A$1:$A$327,0)) -> 1.0165529 | L113: =L$143*INDEX(Assumptions!$B:$B,MATCH("V2 BB sat mass (kg)",Assumptions!$A$1:$A$327,0))/1000000 + IFERROR(L$13/INDEX(Assumptions!$B:$B,MATCH("F9 sats per launch (V2 packing)",Assumptions!$A$1:$A$327,0)),0) + IFERROR(SUM($D$102:K102)/K142,0) + INDEX(Assumptions!$B:$B,MATCH("Working capital per sat ($mm/sat): ΔWC T0",Assumptions!$A$1:$A$327,0)) -> 0.98540768 | ... S113: =S$143*INDEX(Assumptions!$B:$B,MATCH("V2 BB sat mass (kg)",Assumptions!$A$1:$A$327,0))/1000000 + IFERROR(S$13/INDEX(Assumptions!$B:$B,MATCH("F9 sats per launch (V2 packing)",Assumptions!$A$1:$A$327,0)),0) + IFERROR(SUM($D$102:R102)/R142,0) + INDEX(Assumptions!$B:$B,MATCH("Working capital per sat ($mm/sat): ΔWC T0",Assumptions!$A$1:$A$327,0)) -> 0.85004506
A114: V2 BB: Spot IRR | D114: =IFERROR(MIN(3, IFERROR(RATE(D$15,D112,-D113,0,0,0.1), IFERROR(RATE(D$15,D112,-D113,0,0,0.5), RATE(D$15,D112,-D113,0,0,1.5)))), IF(D112*D$15>D113,3,0)) -> 0.47562964 | E114: =IFERROR(MIN(3, IFERROR(RATE(E$15,E112,-E113,0,0,0.1), IFERROR(RATE(E$15,E112,-E113,0,0,0.5), RATE(E$15,E112,-E113,0,0,1.5)))), IF(E112*E$15>E113,3,0)) -> 0.39444565 | F114: =IFERROR(MIN(3, IFERROR(RATE(F$15,F112,-F113,0,0,0.1), IFERROR(RATE(F$15,F112,-F113,0,0,0.5), RATE(F$15,F112,-F113,0,0,1.5)))), IF(F112*F$15>F113,3,0)) -> 0.13395307 | G114: =IFERROR(MIN(3, IFERROR(RATE(G$15,G112,-G113,0,0,0.1), IFERROR(RATE(G$15,G112,-G113,0,0,0.5), RATE(G$15,G112,-G113,0,0,1.5)))), IF(G112*G$15>G113,3,0)) -> -0.047472577 | H114: =IFERROR(MIN(3, IFERROR(RATE(H$15,H112,-H113,0,0,0.1), IFERROR(RATE(H$15,H112,-H113,0,0,0.5), RATE(H$15,H112,-H113,0,0,1.5)))), IF(H112*H$15>H113,3,0)) -> -0.24009571 | I114: =IFERROR(MIN(3, IFERROR(RATE(I$15,I112,-I113,0,0,0.1), IFERROR(RATE(I$15,I112,-I113,0,0,0.5), RATE(I$15,I112,-I113,0,0,1.5)))), IF(I112*I$15>I113,3,0)) -> -0.29237677 | J114: =IFERROR(MIN(3, IFERROR(RATE(J$15,J112,-J113,0,0,0.1), IFERROR(RATE(J$15,J112,-J113,0,0,0.5), RATE(J$15,J112,-J113,0,0,1.5)))), IF(J112*J$15>J113,3,0)) -> -0.46576384 | K114: =IFERROR(MIN(3, IFERROR(RATE(K$15,K112,-K113,0,0,0.1), IFERROR(RATE(K$15,K112,-K113,0,0,0.5), RATE(K$15,K112,-K113,0,0,1.5)))), IF(K112*K$15>K113,3,0)) -> -0.50928231 | ... S114: =IFERROR(MIN(3, IFERROR(RATE(S$15,S112,-S113,0,0,0.1), IFERROR(RATE(S$15,S112,-S113,0,0,0.5), RATE(S$15,S112,-S113,0,0,1.5)))), IF(S112*S$15>S113,3,0)) -> 0
A118: V2 DTC: margin per sat-yr ($mm) | D118: =IFERROR(D$110*INDEX(Assumptions!$B:$B,MATCH("Effective DTC Gbps per sat (revenue calibration)",Assumptions!$A$1:$A$327,0))*D$21/1000000*(1-(D$87+D$75+D$76)/D$65) - INDEX(Assumptions!$B:$B,MATCH("Bandwidth/peering cost per Gbps ($mm/Gbps-yr)",Assumptions!$A$1:$A$327,0))*INDEX(Assumptions!$B:$B,MATCH("Effective DTC Gbps per sat (revenue calibration)",Assumptions!$A$1:$A$327,0))*D$21, 0) -> 0.56313335 | E118: =IFERROR(E$110*INDEX(Assumptions!$B:$B,MATCH("Effective DTC Gbps per sat (revenue calibration)",Assumptions!$A$1:$A$327,0))*E$21/1000000*(1-(E$87+E$75+E$76)/E$65) - INDEX(Assumptions!$B:$B,MATCH("Bandwidth/peering cost per Gbps ($mm/Gbps-yr)",Assumptions!$A$1:$A$327,0))*INDEX(Assumptions!$B:$B,MATCH("Effective DTC Gbps per sat (revenue calibration)",Assumptions!$A$1:$A$327,0))*E$21, 0) -> 0.71398571 | F118: =IFERROR(F$110*INDEX(Assumptions!$B:$B,MATCH("Effective DTC Gbps per sat (revenue calibration)",Assumptions!$A$1:$A$327,0))*F$21/1000000*(1-(F$87+F$75+F$76)/F$65) - INDEX(Assumptions!$B:$B,MATCH("Bandwidth/peering cost per Gbps ($mm/Gbps-yr)",Assumptions!$A$1:$A$327,0))*INDEX(Assumptions!$B:$B,MATCH("Effective DTC Gbps per sat (revenue calibration)",Assumptions!$A$1:$A$327,0))*F$21, 0) -> 0.87620686 | G118: =IFERROR(G$110*INDEX(Assumptions!$B:$B,MATCH("Effective DTC Gbps per sat (revenue calibration)",Assumptions!$A$1:$A$327,0))*G$21/1000000*(1-(G$87+G$75+G$76)/G$65) - INDEX(Assumptions!$B:$B,MATCH("Bandwidth/peering cost per Gbps ($mm/Gbps-yr)",Assumptions!$A$1:$A$327,0))*INDEX(Assumptions!$B:$B,MATCH("Effective DTC Gbps per sat (revenue calibration)",Assumptions!$A$1:$A$327,0))*G$21, 0) -> 1.047422 | H118: =IFERROR(H$110*INDEX(Assumptions!$B:$B,MATCH("Effective DTC Gbps per sat (revenue calibration)",Assumptions!$A$1:$A$327,0))*H$21/1000000*(1-(H$87+H$75+H$76)/H$65) - INDEX(Assumptions!$B:$B,MATCH("Bandwidth/peering cost per Gbps ($mm/Gbps-yr)",Assumptions!$A$1:$A$327,0))*INDEX(Assumptions!$B:$B,MATCH("Effective DTC Gbps per sat (revenue calibration)",Assumptions!$A$1:$A$327,0))*H$21, 0) -> 1.2293197 | I118: =IFERROR(I$110*INDEX(Assumptions!$B:$B,MATCH("Effective DTC Gbps per sat (revenue calibration)",Assumptions!$A$1:$A$327,0))*I$21/1000000*(1-(I$87+I$75+I$76)/I$65) - INDEX(Assumptions!$B:$B,MATCH("Bandwidth/peering cost per Gbps ($mm/Gbps-yr)",Assumptions!$A$1:$A$327,0))*INDEX(Assumptions!$B:$B,MATCH("Effective DTC Gbps per sat (revenue calibration)",Assumptions!$A$1:$A$327,0))*I$21, 0) -> 0.72568956 | J118: =IFERROR(J$110*INDEX(Assumptions!$B:$B,MATCH("Effective DTC Gbps per sat (revenue calibration)",Assumptions!$A$1:$A$327,0))*J$21/1000000*(1-(J$87+J$75+J$76)/J$65) - INDEX(Assumptions!$B:$B,MATCH("Bandwidth/peering cost per Gbps ($mm/Gbps-yr)",Assumptions!$A$1:$A$327,0))*INDEX(Assumptions!$B:$B,MATCH("Effective DTC Gbps per sat (revenue calibration)",Assumptions!$A$1:$A$327,0))*J$21, 0) -> 0.4516826 | K118: =IFERROR(K$110*INDEX(Assumptions!$B:$B,MATCH("Effective DTC Gbps per sat (revenue calibration)",Assumptions!$A$1:$A$327,0))*K$21/1000000*(1-(K$87+K$75+K$76)/K$65) - INDEX(Assumptions!$B:$B,MATCH("Bandwidth/peering cost per Gbps ($mm/Gbps-yr)",Assumptions!$A$1:$A$327,0))*INDEX(Assumptions!$B:$B,MATCH("Effective DTC Gbps per sat (revenue calibration)",Assumptions!$A$1:$A$327,0))*K$21, 0) -> 0.35807301 | ... S118: =IFERROR(S$110*INDEX(Assumptions!$B:$B,MATCH("Effective DTC Gbps per sat (revenue calibration)",Assumptions!$A$1:$A$327,0))*S$21/1000000*(1-(S$87+S$75+S$76)/S$65) - INDEX(Assumptions!$B:$B,MATCH("Bandwidth/peering cost per Gbps ($mm/Gbps-yr)",Assumptions!$A$1:$A$327,0))*INDEX(Assumptions!$B:$B,MATCH("Effective DTC Gbps per sat (revenue calibration)",Assumptions!$A$1:$A$327,0))*S$21, 0) -> 0.23405024
A119: V2 DTC: CapEx slug per sat ($mm) | D119: =D$143*INDEX(Assumptions!$B:$B,MATCH("V2 DTC sat mass (kg)",Assumptions!$A$1:$A$327,0))/1000000 + IFERROR(D$13/INDEX(Assumptions!$B:$B,MATCH("F9 sats per launch (V2 packing)",Assumptions!$A$1:$A$327,0)),0) + INDEX(Assumptions!$B:$B,MATCH("Working capital per sat ($mm/sat): ΔWC T0",Assumptions!$A$1:$A$327,0)) -> 1.1479808 | E119: =E$143*INDEX(Assumptions!$B:$B,MATCH("V2 DTC sat mass (kg)",Assumptions!$A$1:$A$327,0))/1000000 + IFERROR(E$13/INDEX(Assumptions!$B:$B,MATCH("F9 sats per launch (V2 packing)",Assumptions!$A$1:$A$327,0)),0) + IFERROR(SUM($D$102:D102)/D142,0) + INDEX(Assumptions!$B:$B,MATCH("Working capital per sat ($mm/sat): ΔWC T0",Assumptions!$A$1:$A$327,0)) -> 1.1605523 | F119: =F$143*INDEX(Assumptions!$B:$B,MATCH("V2 DTC sat mass (kg)",Assumptions!$A$1:$A$327,0))/1000000 + IFERROR(F$13/INDEX(Assumptions!$B:$B,MATCH("F9 sats per launch (V2 packing)",Assumptions!$A$1:$A$327,0)),0) + IFERROR(SUM($D$102:E102)/E142,0) + INDEX(Assumptions!$B:$B,MATCH("Working capital per sat ($mm/sat): ΔWC T0",Assumptions!$A$1:$A$327,0)) -> 1.1376372 | G119: =G$143*INDEX(Assumptions!$B:$B,MATCH("V2 DTC sat mass (kg)",Assumptions!$A$1:$A$327,0))/1000000 + IFERROR(G$13/INDEX(Assumptions!$B:$B,MATCH("F9 sats per launch (V2 packing)",Assumptions!$A$1:$A$327,0)),0) + IFERROR(SUM($D$102:F102)/F142,0) + INDEX(Assumptions!$B:$B,MATCH("Working capital per sat ($mm/sat): ΔWC T0",Assumptions!$A$1:$A$327,0)) -> 1.1491075 | H119: =H$143*INDEX(Assumptions!$B:$B,MATCH("V2 DTC sat mass (kg)",Assumptions!$A$1:$A$327,0))/1000000 + IFERROR(H$13/INDEX(Assumptions!$B:$B,MATCH("F9 sats per launch (V2 packing)",Assumptions!$A$1:$A$327,0)),0) + IFERROR(SUM($D$102:G102)/G142,0) + INDEX(Assumptions!$B:$B,MATCH("Working capital per sat ($mm/sat): ΔWC T0",Assumptions!$A$1:$A$327,0)) -> 1.1287272 | I119: =I$143*INDEX(Assumptions!$B:$B,MATCH("V2 DTC sat mass (kg)",Assumptions!$A$1:$A$327,0))/1000000 + IFERROR(I$13/INDEX(Assumptions!$B:$B,MATCH("F9 sats per launch (V2 packing)",Assumptions!$A$1:$A$327,0)),0) + IFERROR(SUM($D$102:H102)/H142,0) + INDEX(Assumptions!$B:$B,MATCH("Working capital per sat ($mm/sat): ΔWC T0",Assumptions!$A$1:$A$327,0)) -> 1.0931627 | J119: =J$143*INDEX(Assumptions!$B:$B,MATCH("V2 DTC sat mass (kg)",Assumptions!$A$1:$A$327,0))/1000000 + IFERROR(J$13/INDEX(Assumptions!$B:$B,MATCH("F9 sats per launch (V2 packing)",Assumptions!$A$1:$A$327,0)),0) + IFERROR(SUM($D$102:I102)/I142,0) + INDEX(Assumptions!$B:$B,MATCH("Working capital per sat ($mm/sat): ΔWC T0",Assumptions!$A$1:$A$327,0)) -> 1.0493815 | K119: =K$143*INDEX(Assumptions!$B:$B,MATCH("V2 DTC sat mass (kg)",Assumptions!$A$1:$A$327,0))/1000000 + IFERROR(K$13/INDEX(Assumptions!$B:$B,MATCH("F9 sats per launch (V2 packing)",Assumptions!$A$1:$A$327,0)),0) + IFERROR(SUM($D$102:J102)/J142,0) + INDEX(Assumptions!$B:$B,MATCH("Working capital per sat ($mm/sat): ΔWC T0",Assumptions!$A$1:$A$327,0)) -> 1.0165529 | L119: =L$143*INDEX(Assumptions!$B:$B,MATCH("V2 DTC sat mass (kg)",Assumptions!$A$1:$A$327,0))/1000000 + IFERROR(L$13/INDEX(Assumptions!$B:$B,MATCH("F9 sats per launch (V2 packing)",Assumptions!$A$1:$A$327,0)),0) + IFERROR(SUM($D$102:K102)/K142,0) + INDEX(Assumptions!$B:$B,MATCH("Working capital per sat ($mm/sat): ΔWC T0",Assumptions!$A$1:$A$327,0)) -> 0.98540768 | ... S119: =S$143*INDEX(Assumptions!$B:$B,MATCH("V2 DTC sat mass (kg)",Assumptions!$A$1:$A$327,0))/1000000 + IFERROR(S$13/INDEX(Assumptions!$B:$B,MATCH("F9 sats per launch (V2 packing)",Assumptions!$A$1:$A$327,0)),0) + IFERROR(SUM($D$102:R102)/R142,0) + INDEX(Assumptions!$B:$B,MATCH("Working capital per sat ($mm/sat): ΔWC T0",Assumptions!$A$1:$A$327,0)) -> 0.85004506
A120: V2 DTC: Spot IRR | D120: =IFERROR(MIN(3, IFERROR(RATE(D$15,D118,-D119,0,0,0.1), IFERROR(RATE(D$15,D118,-D119,0,0,0.5), RATE(D$15,D118,-D119,0,0,1.5)))), IF(D118*D$15>D119,3,0)) -> 0.39901086 | E120: =IFERROR(MIN(3, IFERROR(RATE(E$15,E118,-E119,0,0,0.1), IFERROR(RATE(E$15,E118,-E119,0,0,0.5), RATE(E$15,E118,-E119,0,0,1.5)))), IF(E118*E$15>E119,3,0)) -> 0.5454228 | F120: =IFERROR(MIN(3, IFERROR(RATE(F$15,F118,-F119,0,0,0.1), IFERROR(RATE(F$15,F118,-F119,0,0,0.5), RATE(F$15,F118,-F119,0,0,1.5)))), IF(F118*F$15>F119,3,0)) -> 0.71886639 | G120: =IFERROR(MIN(3, IFERROR(RATE(G$15,G118,-G119,0,0,0.1), IFERROR(RATE(G$15,G118,-G119,0,0,0.5), RATE(G$15,G118,-G119,0,0,1.5)))), IF(G118*G$15>G119,3,0)) -> 0.87184359 | H120: =IFERROR(MIN(3, IFERROR(RATE(H$15,H118,-H119,0,0,0.1), IFERROR(RATE(H$15,H118,-H119,0,0,0.5), RATE(H$15,H118,-H119,0,0,1.5)))), IF(H118*H$15>H119,3,0)) -> 1.0597431 | I120: =IFERROR(MIN(3, IFERROR(RATE(I$15,I118,-I119,0,0,0.1), IFERROR(RATE(I$15,I118,-I119,0,0,0.5), RATE(I$15,I118,-I119,0,0,1.5)))), IF(I118*I$15>I119,3,0)) -> 0.6006667 | J120: =IFERROR(MIN(3, IFERROR(RATE(J$15,J118,-J119,0,0,0.1), IFERROR(RATE(J$15,J118,-J119,0,0,0.5), RATE(J$15,J118,-J119,0,0,1.5)))), IF(J118*J$15>J119,3,0)) -> 0.32505366 | K120: =IFERROR(MIN(3, IFERROR(RATE(K$15,K118,-K119,0,0,0.1), IFERROR(RATE(K$15,K118,-K119,0,0,0.5), RATE(K$15,K118,-K119,0,0,1.5)))), IF(K118*K$15>K119,3,0)) -> 0.22406017 | ... S120: =IFERROR(MIN(3, IFERROR(RATE(S$15,S118,-S119,0,0,0.1), IFERROR(RATE(S$15,S118,-S119,0,0,0.5), RATE(S$15,S118,-S119,0,0,1.5)))), IF(S118*S$15>S119,3,0)) -> 0.11698197
A124: V3 BB: margin per sat-yr ($mm) | D124: =IFERROR(D$109*INDEX(Assumptions!$B:$B,MATCH("V3 BB Gbps per sat",Assumptions!$A$1:$A$327,0))*D$21/1000000*(1-(D$87+D$75+D$76)/D$65) - INDEX(Assumptions!$B:$B,MATCH("Bandwidth/peering cost per Gbps ($mm/Gbps-yr)",Assumptions!$A$1:$A$327,0))*INDEX(Assumptions!$B:$B,MATCH("V3 BB Gbps per sat",Assumptions!$A$1:$A$327,0))*D$21, 0) -> 6.6361209 | E124: =IFERROR(E$109*INDEX(Assumptions!$B:$B,MATCH("V3 BB Gbps per sat",Assumptions!$A$1:$A$327,0))*E$21/1000000*(1-(E$87+E$75+E$76)/E$65) - INDEX(Assumptions!$B:$B,MATCH("Bandwidth/peering cost per Gbps ($mm/Gbps-yr)",Assumptions!$A$1:$A$327,0))*INDEX(Assumptions!$B:$B,MATCH("V3 BB Gbps per sat",Assumptions!$A$1:$A$327,0))*E$21, 0) -> 5.8846033 | F124: =IFERROR(F$109*INDEX(Assumptions!$B:$B,MATCH("V3 BB Gbps per sat",Assumptions!$A$1:$A$327,0))*F$21/1000000*(1-(F$87+F$75+F$76)/F$65) - INDEX(Assumptions!$B:$B,MATCH("Bandwidth/peering cost per Gbps ($mm/Gbps-yr)",Assumptions!$A$1:$A$327,0))*INDEX(Assumptions!$B:$B,MATCH("V3 BB Gbps per sat",Assumptions!$A$1:$A$327,0))*F$21, 0) -> 3.4017938 | G124: =IFERROR(G$109*INDEX(Assumptions!$B:$B,MATCH("V3 BB Gbps per sat",Assumptions!$A$1:$A$327,0))*G$21/1000000*(1-(G$87+G$75+G$76)/G$65) - INDEX(Assumptions!$B:$B,MATCH("Bandwidth/peering cost per Gbps ($mm/Gbps-yr)",Assumptions!$A$1:$A$327,0))*INDEX(Assumptions!$B:$B,MATCH("V3 BB Gbps per sat",Assumptions!$A$1:$A$327,0))*G$21, 0) -> 2.0640732 | H124: =IFERROR(H$109*INDEX(Assumptions!$B:$B,MATCH("V3 BB Gbps per sat",Assumptions!$A$1:$A$327,0))*H$21/1000000*(1-(H$87+H$75+H$76)/H$65) - INDEX(Assumptions!$B:$B,MATCH("Bandwidth/peering cost per Gbps ($mm/Gbps-yr)",Assumptions!$A$1:$A$327,0))*INDEX(Assumptions!$B:$B,MATCH("V3 BB Gbps per sat",Assumptions!$A$1:$A$327,0))*H$21, 0) -> 0.9580861 | I124: =IFERROR(I$109*INDEX(Assumptions!$B:$B,MATCH("V3 BB Gbps per sat",Assumptions!$A$1:$A$327,0))*I$21/1000000*(1-(I$87+I$75+I$76)/I$65) - INDEX(Assumptions!$B:$B,MATCH("Bandwidth/peering cost per Gbps ($mm/Gbps-yr)",Assumptions!$A$1:$A$327,0))*INDEX(Assumptions!$B:$B,MATCH("V3 BB Gbps per sat",Assumptions!$A$1:$A$327,0))*I$21, 0) -> 0.71810901 | J124: =IFERROR(J$109*INDEX(Assumptions!$B:$B,MATCH("V3 BB Gbps per sat",Assumptions!$A$1:$A$327,0))*J$21/1000000*(1-(J$87+J$75+J$76)/J$65) - INDEX(Assumptions!$B:$B,MATCH("Bandwidth/peering cost per Gbps ($mm/Gbps-yr)",Assumptions!$A$1:$A$327,0))*INDEX(Assumptions!$B:$B,MATCH("V3 BB Gbps per sat",Assumptions!$A$1:$A$327,0))*J$21, 0) -> 0.23164205 | K124: =IFERROR(K$109*INDEX(Assumptions!$B:$B,MATCH("V3 BB Gbps per sat",Assumptions!$A$1:$A$327,0))*K$21/1000000*(1-(K$87+K$75+K$76)/K$65) - INDEX(Assumptions!$B:$B,MATCH("Bandwidth/peering cost per Gbps ($mm/Gbps-yr)",Assumptions!$A$1:$A$327,0))*INDEX(Assumptions!$B:$B,MATCH("V3 BB Gbps per sat",Assumptions!$A$1:$A$327,0))*K$21, 0) -> 0.15794758 | ... S124: =IFERROR(S$109*INDEX(Assumptions!$B:$B,MATCH("V3 BB Gbps per sat",Assumptions!$A$1:$A$327,0))*S$21/1000000*(1-(S$87+S$75+S$76)/S$65) - INDEX(Assumptions!$B:$B,MATCH("Bandwidth/peering cost per Gbps ($mm/Gbps-yr)",Assumptions!$A$1:$A$327,0))*INDEX(Assumptions!$B:$B,MATCH("V3 BB Gbps per sat",Assumptions!$A$1:$A$327,0))*S$21, 0) -> -0.45342881
A125: V3 BB: CapEx slug per sat ($mm) | D125: =D$143*INDEX(Assumptions!$B:$B,MATCH("V3 BB sat mass (kg)",Assumptions!$A$1:$A$327,0))/1000000 + IFERROR(D$14/D205,0) + INDEX(Assumptions!$B:$B,MATCH("Working capital per sat ($mm/sat): ΔWC T0",Assumptions!$A$1:$A$327,0)) -> 1.305 | E125: =E$143*INDEX(Assumptions!$B:$B,MATCH("V3 BB sat mass (kg)",Assumptions!$A$1:$A$327,0))/1000000 + IFERROR(E$14/E205,0) + IFERROR(SUM($D$102:D102)/D142,0) + INDEX(Assumptions!$B:$B,MATCH("Working capital per sat ($mm/sat): ΔWC T0",Assumptions!$A$1:$A$327,0)) -> 1.3329562 | F125: =F$143*INDEX(Assumptions!$B:$B,MATCH("V3 BB sat mass (kg)",Assumptions!$A$1:$A$327,0))/1000000 + IFERROR(F$14/F205,0) + IFERROR(SUM($D$102:E102)/E142,0) + INDEX(Assumptions!$B:$B,MATCH("Working capital per sat ($mm/sat): ΔWC T0",Assumptions!$A$1:$A$327,0)) -> 1.6698542 | G125: =G$143*INDEX(Assumptions!$B:$B,MATCH("V3 BB sat mass (kg)",Assumptions!$A$1:$A$327,0))/1000000 + IFERROR(G$14/G205,0) + IFERROR(SUM($D$102:F102)/F142,0) + INDEX(Assumptions!$B:$B,MATCH("Working capital per sat ($mm/sat): ΔWC T0",Assumptions!$A$1:$A$327,0)) -> 1.5893285 | H125: =H$143*INDEX(Assumptions!$B:$B,MATCH("V3 BB sat mass (kg)",Assumptions!$A$1:$A$327,0))/1000000 + IFERROR(H$14/H205,0) + IFERROR(SUM($D$102:G102)/G142,0) + INDEX(Assumptions!$B:$B,MATCH("Working capital per sat ($mm/sat): ΔWC T0",Assumptions!$A$1:$A$327,0)) -> 1.4810863 | I125: =I$143*INDEX(Assumptions!$B:$B,MATCH("V3 BB sat mass (kg)",Assumptions!$A$1:$A$327,0))/1000000 + IFERROR(I$14/I205,0) + IFERROR(SUM($D$102:H102)/H142,0) + INDEX(Assumptions!$B:$B,MATCH("Working capital per sat ($mm/sat): ΔWC T0",Assumptions!$A$1:$A$327,0)) -> 1.3667204 | J125: =J$143*INDEX(Assumptions!$B:$B,MATCH("V3 BB sat mass (kg)",Assumptions!$A$1:$A$327,0))/1000000 + IFERROR(J$14/J205,0) + IFERROR(SUM($D$102:I102)/I142,0) + INDEX(Assumptions!$B:$B,MATCH("Working capital per sat ($mm/sat): ΔWC T0",Assumptions!$A$1:$A$327,0)) -> 1.2880132 | K125: =K$143*INDEX(Assumptions!$B:$B,MATCH("V3 BB sat mass (kg)",Assumptions!$A$1:$A$327,0))/1000000 + IFERROR(K$14/K205,0) + IFERROR(SUM($D$102:J102)/J142,0) + INDEX(Assumptions!$B:$B,MATCH("Working capital per sat ($mm/sat): ΔWC T0",Assumptions!$A$1:$A$327,0)) -> 1.2255528 | L125: =L$143*INDEX(Assumptions!$B:$B,MATCH("V3 BB sat mass (kg)",Assumptions!$A$1:$A$327,0))/1000000 + IFERROR(L$14/L205,0) + IFERROR(SUM($D$102:K102)/K142,0) + INDEX(Assumptions!$B:$B,MATCH("Working capital per sat ($mm/sat): ΔWC T0",Assumptions!$A$1:$A$327,0)) -> 1.1811194 | ... S125: =S$143*INDEX(Assumptions!$B:$B,MATCH("V3 BB sat mass (kg)",Assumptions!$A$1:$A$327,0))/1000000 + IFERROR(S$14/S205,0) + IFERROR(SUM($D$102:R102)/R142,0) + INDEX(Assumptions!$B:$B,MATCH("Working capital per sat ($mm/sat): ΔWC T0",Assumptions!$A$1:$A$327,0)) -> 0.99762931
...

Sheet Customer Launch
A1: Customer Launch module — module = Space segment · 2-stream revenue $4,086M · full waterfall, R&D above EBITDA · separate F9 + Starship D&A · Spot IRR · per-launch D&A interface
A4: YEAR | D4: 2025 | E4: 2026 | F4: 2027 | G4: 2028 | H4: 2029 | I4: 2030 | J4: 2031 | K4: 2032 | L4: 2033 | M4: 2034 | N4: 2035 | O4: 2036 | P4: 2037 | Q4: 2038 | R4: 2039 | S4: 2040
A5: Year offset | D5: 0 | E5: 1 | F5: 2 | G5: 3 | H5: 4 | I5: 5 | J5: 6 | K5: 7 | L5: 8 | M5: 9 | N5: 10 | O5: 11 | P5: 12 | Q5: 13 | R5: 14 | S5: 15
A8: ▸ BLOCK A: ALLOCATOR IN (cross-tab reads)
A9: F9 internal launches per year (Starlink-driven) | D9: {=INDEX(Starlink!$D:$AC, MATCH("F9 internal launches per year (Starlink-driven)", Starlink!$A$1:$A$205, 0), COLUMN()-COLUMN($D9)+1)} -> 166 | E9: {=INDEX(Starlink!$D:$AC, MATCH("F9 internal launches per year (Starlink-driven)", Starlink!$A$1:$A$205, 0), COLUMN()-COLUMN($D9)+1)} -> 138 | F9: {=INDEX(Starlink!$D:$AC, MATCH("F9 internal launches per year (Starlink-driven)", Starlink!$A$1:$A$205, 0), COLUMN()-COLUMN($D9)+1)} -> 0 | G9: {=INDEX(Starlink!$D:$AC, MATCH("F9 internal launches per year (Starlink-driven)", Starlink!$A$1:$A$205, 0), COLUMN()-COLUMN($D9)+1)} -> 0 | H9: {=INDEX(Starlink!$D:$AC, MATCH("F9 internal launches per year (Starlink-driven)", Starlink!$A$1:$A$205, 0), COLUMN()-COLUMN($D9)+1)} -> 0 | I9: {=INDEX(Starlink!$D:$AC, MATCH("F9 internal launches per year (Starlink-driven)", Starlink!$A$1:$A$205, 0), COLUMN()-COLUMN($D9)+1)} -> 0 | J9: {=INDEX(Starlink!$D:$AC, MATCH("F9 internal launches per year (Starlink-driven)", Starlink!$A$1:$A$205, 0), COLUMN()-COLUMN($D9)+1)} -> 0 | K9: {=INDEX(Starlink!$D:$AC, MATCH("F9 internal launches per year (Starlink-driven)", Starlink!$A$1:$A$205, 0), COLUMN()-COLUMN($D9)+1)} -> 0 | ... S9: {=INDEX(Starlink!$D:$AC, MATCH("F9 internal launches per year (Starlink-driven)", Starlink!$A$1:$A$205, 0), COLUMN()-COLUMN($D9)+1)} -> 0
A10: Starship internal launches per year (Starlink-driven) | D10: {=INDEX(Starlink!$D:$AC, MATCH("Starship internal launches per year (Starlink-driven)", Starlink!$A$1:$A$205, 0), COLUMN()-COLUMN($D10)+1)} -> 0 | E10: {=INDEX(Starlink!$D:$AC, MATCH("Starship internal launches per year (Starlink-driven)", Starlink!$A$1:$A$205, 0), COLUMN()-COLUMN($D10)+1)} -> 0 | F10: {=INDEX(Starlink!$D:$AC, MATCH("Starship internal launches per year (Starlink-driven)", Starlink!$A$1:$A$205, 0), COLUMN()-COLUMN($D10)+1)} -> 61 | G10: {=INDEX(Starlink!$D:$AC, MATCH("Starship internal launches per year (Starlink-driven)", Starlink!$A$1:$A$205, 0), COLUMN()-COLUMN($D10)+1)} -> 127 | H10: {=INDEX(Starlink!$D:$AC, MATCH("Starship internal launches per year (Starlink-driven)", Starlink!$A$1:$A$205, 0), COLUMN()-COLUMN($D10)+1)} -> 264 | I10: {=INDEX(Starlink!$D:$AC, MATCH("Starship internal launches per year (Starlink-driven)", Starlink!$A$1:$A$205, 0), COLUMN()-COLUMN($D10)+1)} -> 351 | J10: {=INDEX(Starlink!$D:$AC, MATCH("Starship internal launches per year (Starlink-driven)", Starlink!$A$1:$A$205, 0), COLUMN()-COLUMN($D10)+1)} -> 559 | K10: {=INDEX(Starlink!$D:$AC, MATCH("Starship internal launches per year (Starlink-driven)", Starlink!$A$1:$A$205, 0), COLUMN()-COLUMN($D10)+1)} -> 397 | ... S10: {=INDEX(Starlink!$D:$AC, MATCH("Starship internal launches per year (Starlink-driven)", Starlink!$A$1:$A$205, 0), COLUMN()-COLUMN($D10)+1)} -> 395
A11: F9 customer launch price ($mm/launch) | D11: =INDEX(Assumptions!$B:$B, MATCH("F9 customer launch price ($mm/launch)", Assumptions!$A$1:$A$327, 0)) -> 54.8 | E11: =INDEX(Assumptions!$B:$B, MATCH("F9 customer launch price ($mm/launch)", Assumptions!$A$1:$A$327, 0)) -> 54.8 | F11: =INDEX(Assumptions!$B:$B, MATCH("F9 customer launch price ($mm/launch)", Assumptions!$A$1:$A$327, 0)) -> 54.8 | G11: =INDEX(Assumptions!$B:$B, MATCH("F9 customer launch price ($mm/launch)", Assumptions!$A$1:$A$327, 0)) -> 54.8 | H11: =INDEX(Assumptions!$B:$B, MATCH("F9 customer launch price ($mm/launch)", Assumptions!$A$1:$A$327, 0)) -> 54.8 | I11: =INDEX(Assumptions!$B:$B, MATCH("F9 customer launch price ($mm/launch)", Assumptions!$A$1:$A$327, 0)) -> 54.8 | J11: =INDEX(Assumptions!$B:$B, MATCH("F9 customer launch price ($mm/launch)", Assumptions!$A$1:$A$327, 0)) -> 54.8 | K11: =INDEX(Assumptions!$B:$B, MATCH("F9 customer launch price ($mm/launch)", Assumptions!$A$1:$A$327, 0)) -> 54.8 | ... S11: =INDEX(Assumptions!$B:$B, MATCH("F9 customer launch price ($mm/launch)", Assumptions!$A$1:$A$327, 0)) -> 54.8
A12: Starship customer launch price ($mm/launch) | D12: {=INDEX(Assumptions!$D:$AC, MATCH("Starship customer launch price ($mm/launch): year-row", Assumptions!$A$1:$A$327, 0), COLUMN()-COLUMN($D12)+1)} -> 0 | E12: {=INDEX(Assumptions!$D:$AC, MATCH("Starship customer launch price ($mm/launch): year-row", Assumptions!$A$1:$A$327, 0), COLUMN()-COLUMN($D12)+1)} -> 0 | F12: {=INDEX(Assumptions!$D:$AC, MATCH("Starship customer launch price ($mm/launch): year-row", Assumptions!$A$1:$A$327, 0), COLUMN()-COLUMN($D12)+1)} -> 100 | G12: {=INDEX(Assumptions!$D:$AC, MATCH("Starship customer launch price ($mm/launch): year-row", Assumptions!$A$1:$A$327, 0), COLUMN()-COLUMN($D12)+1)} -> 92 | H12: {=INDEX(Assumptions!$D:$AC, MATCH("Starship customer launch price ($mm/launch): year-row", Assumptions!$A$1:$A$327, 0), COLUMN()-COLUMN($D12)+1)} -> 84.64 | I12: {=INDEX(Assumptions!$D:$AC, MATCH("Starship customer launch price ($mm/launch): year-row", Assumptions!$A$1:$A$327, 0), COLUMN()-COLUMN($D12)+1)} -> 77.87 | J12: {=INDEX(Assumptions!$D:$AC, MATCH("Starship customer launch price ($mm/launch): year-row", Assumptions!$A$1:$A$327, 0), COLUMN()-COLUMN($D12)+1)} -> 71.64 | K12: {=INDEX(Assumptions!$D:$AC, MATCH("Starship customer launch price ($mm/launch): year-row", Assumptions!$A$1:$A$327, 0), COLUMN()-COLUMN($D12)+1)} -> 65.91 | ... S12: {=INDEX(Assumptions!$D:$AC, MATCH("Starship customer launch price ($mm/launch): year-row", Assumptions!$A$1:$A$327, 0), COLUMN()-COLUMN($D12)+1)} -> 33.83
A13: Commercial launch market size ($mm/yr) | D13: {=INDEX(Assumptions!$D:$AC, MATCH("Commercial launch market size ($mm/year): year-row", Assumptions!$A$1:$A$327, 0), COLUMN()-COLUMN($D13)+1)} -> 8000 | E13: {=INDEX(Assumptions!$D:$AC, MATCH("Commercial launch market size ($mm/year): year-row", Assumptions!$A$1:$A$327, 0), COLUMN()-COLUMN($D13)+1)} -> 8640 | F13: {=INDEX(Assumptions!$D:$AC, MATCH("Commercial launch market size ($mm/year): year-row", Assumptions!$A$1:$A$327, 0), COLUMN()-COLUMN($D13)+1)} -> 9331.2 | G13: {=INDEX(Assumptions!$D:$AC, MATCH("Commercial launch market size ($mm/year): year-row", Assumptions!$A$1:$A$327, 0), COLUMN()-COLUMN($D13)+1)} -> 10077.7 | H13: {=INDEX(Assumptions!$D:$AC, MATCH("Commercial launch market size ($mm/year): year-row", Assumptions!$A$1:$A$327, 0), COLUMN()-COLUMN($D13)+1)} -> 10883.9 | I13: {=INDEX(Assumptions!$D:$AC, MATCH("Commercial launch market size ($mm/year): year-row", Assumptions!$A$1:$A$327, 0), COLUMN()-COLUMN($D13)+1)} -> 11754.6 | J13: {=INDEX(Assumptions!$D:$AC, MATCH("Commercial launch market size ($mm/year): year-row", Assumptions!$A$1:$A$327, 0), COLUMN()-COLUMN($D13)+1)} -> 12695 | K13: {=INDEX(Assumptions!$D:$AC, MATCH("Commercial launch market size ($mm/year): year-row", Assumptions!$A$1:$A$327, 0), COLUMN()-COLUMN($D13)+1)} -> 13710.6 | ... S13: {=INDEX(Assumptions!$D:$AC, MATCH("Commercial launch market size ($mm/year): year-row", Assumptions!$A$1:$A$327, 0), COLUMN()-COLUMN($D13)+1)} -> 25377.4
A14: Government launch market size ($mm/yr) | D14: {=INDEX(Assumptions!$D:$AC, MATCH("Government launch market size ($mm/year): year-row", Assumptions!$A$1:$A$327, 0), COLUMN()-COLUMN($D14)+1)} -> 4000 | E14: {=INDEX(Assumptions!$D:$AC, MATCH("Government launch market size ($mm/year): year-row", Assumptions!$A$1:$A$327, 0), COLUMN()-COLUMN($D14)+1)} -> 4200 | F14: {=INDEX(Assumptions!$D:$AC, MATCH("Government launch market size ($mm/year): year-row", Assumptions!$A$1:$A$327, 0), COLUMN()-COLUMN($D14)+1)} -> 4410 | G14: {=INDEX(Assumptions!$D:$AC, MATCH("Government launch market size ($mm/year): year-row", Assumptions!$A$1:$A$327, 0), COLUMN()-COLUMN($D14)+1)} -> 4630.5 | H14: {=INDEX(Assumptions!$D:$AC, MATCH("Government launch market size ($mm/year): year-row", Assumptions!$A$1:$A$327, 0), COLUMN()-COLUMN($D14)+1)} -> 4862.02 | I14: {=INDEX(Assumptions!$D:$AC, MATCH("Government launch market size ($mm/year): year-row", Assumptions!$A$1:$A$327, 0), COLUMN()-COLUMN($D14)+1)} -> 5105.13 | J14: {=INDEX(Assumptions!$D:$AC, MATCH("Government launch market size ($mm/year): year-row", Assumptions!$A$1:$A$327, 0), COLUMN()-COLUMN($D14)+1)} -> 5360.38 | K14: {=INDEX(Assumptions!$D:$AC, MATCH("Government launch market size ($mm/year): year-row", Assumptions!$A$1:$A$327, 0), COLUMN()-COLUMN($D14)+1)} -> 5628.4 | ... S14: {=INDEX(Assumptions!$D:$AC, MATCH("Government launch market size ($mm/year): year-row", Assumptions!$A$1:$A$327, 0), COLUMN()-COLUMN($D14)+1)} -> 8315.71
A15: SpaceX commercial market share | D15: {=INDEX(Assumptions!$D:$AC, MATCH("SpaceX commercial market share %", Assumptions!$A$1:$A$327, 0), COLUMN()-COLUMN($D15)+1)} -> 0.75 | E15: {=INDEX(Assumptions!$D:$AC, MATCH("SpaceX commercial market share %", Assumptions!$A$1:$A$327, 0), COLUMN()-COLUMN($D15)+1)} -> 0.7533 | F15: {=INDEX(Assumptions!$D:$AC, MATCH("SpaceX commercial market share %", Assumptions!$A$1:$A$327, 0), COLUMN()-COLUMN($D15)+1)} -> 0.7567 | G15: {=INDEX(Assumptions!$D:$AC, MATCH("SpaceX commercial market share %", Assumptions!$A$1:$A$327, 0), COLUMN()-COLUMN($D15)+1)} -> 0.76 | H15: {=INDEX(Assumptions!$D:$AC, MATCH("SpaceX commercial market share %", Assumptions!$A$1:$A$327, 0), COLUMN()-COLUMN($D15)+1)} -> 0.7633 | I15: {=INDEX(Assumptions!$D:$AC, MATCH("SpaceX commercial market share %", Assumptions!$A$1:$A$327, 0), COLUMN()-COLUMN($D15)+1)} -> 0.7667 | J15: {=INDEX(Assumptions!$D:$AC, MATCH("SpaceX commercial market share %", Assumptions!$A$1:$A$327, 0), COLUMN()-COLUMN($D15)+1)} -> 0.77 | K15: {=INDEX(Assumptions!$D:$AC, MATCH("SpaceX commercial market share %", Assumptions!$A$1:$A$327, 0), COLUMN()-COLUMN($D15)+1)} -> 0.7733 | ... S15: {=INDEX(Assumptions!$D:$AC, MATCH("SpaceX commercial market share %", Assumptions!$A$1:$A$327, 0), COLUMN()-COLUMN($D15)+1)} -> 0.8
A16: SpaceX government market share | D16: {=INDEX(Assumptions!$D:$AC, MATCH("SpaceX government market share %", Assumptions!$A$1:$A$327, 0), COLUMN()-COLUMN($D16)+1)} -> 0.9 | E16: {=INDEX(Assumptions!$D:$AC, MATCH("SpaceX government market share %", Assumptions!$A$1:$A$327, 0), COLUMN()-COLUMN($D16)+1)} -> 0.8933 | F16: {=INDEX(Assumptions!$D:$AC, MATCH("SpaceX government market share %", Assumptions!$A$1:$A$327, 0), COLUMN()-COLUMN($D16)+1)} -> 0.8867 | G16: {=INDEX(Assumptions!$D:$AC, MATCH("SpaceX government market share %", Assumptions!$A$1:$A$327, 0), COLUMN()-COLUMN($D16)+1)} -> 0.88 | H16: {=INDEX(Assumptions!$D:$AC, MATCH("SpaceX government market share %", Assumptions!$A$1:$A$327, 0), COLUMN()-COLUMN($D16)+1)} -> 0.8733 | I16: {=INDEX(Assumptions!$D:$AC, MATCH("SpaceX government market share %", Assumptions!$A$1:$A$327, 0), COLUMN()-COLUMN($D16)+1)} -> 0.8667 | J16: {=INDEX(Assumptions!$D:$AC, MATCH("SpaceX government market share %", Assumptions!$A$1:$A$327, 0), COLUMN()-COLUMN($D16)+1)} -> 0.86 | K16: {=INDEX(Assumptions!$D:$AC, MATCH("SpaceX government market share %", Assumptions!$A$1:$A$327, 0), COLUMN()-COLUMN($D16)+1)} -> 0.8533 | ... S16: {=INDEX(Assumptions!$D:$AC, MATCH("SpaceX government market share %", Assumptions!$A$1:$A$327, 0), COLUMN()-COLUMN($D16)+1)} -> 0.8
A17: Launch & Development revenue ($mm/yr) | D17: {=INDEX(Assumptions!$D:$AC, MATCH("Launch & Development revenue ($mm/yr): year-row", Assumptions!$A$1:$A$327, 0), COLUMN()-COLUMN($D17)+1)} -> 1510 | E17: {=INDEX(Assumptions!$D:$AC, MATCH("Launch & Development revenue ($mm/yr): year-row", Assumptions!$A$1:$A$327, 0), COLUMN()-COLUMN($D17)+1)} -> 1585.5 | F17: {=INDEX(Assumptions!$D:$AC, MATCH("Launch & Development revenue ($mm/yr): year-row", Assumptions!$A$1:$A$327, 0), COLUMN()-COLUMN($D17)+1)} -> 1664.775 | G17: {=INDEX(Assumptions!$D:$AC, MATCH("Launch & Development revenue ($mm/yr): year-row", Assumptions!$A$1:$A$327, 0), COLUMN()-COLUMN($D17)+1)} -> 1748.0138 | H17: {=INDEX(Assumptions!$D:$AC, MATCH("Launch & Development revenue ($mm/yr): year-row", Assumptions!$A$1:$A$327, 0), COLUMN()-COLUMN($D17)+1)} -> 1835.4144 | I17: {=INDEX(Assumptions!$D:$AC, MATCH("Launch & Development revenue ($mm/yr): year-row", Assumptions!$A$1:$A$327, 0), COLUMN()-COLUMN($D17)+1)} -> 1927.1852 | J17: {=INDEX(Assumptions!$D:$AC, MATCH("Launch & Development revenue ($mm/yr): year-row", Assumptions!$A$1:$A$327, 0), COLUMN()-COLUMN($D17)+1)} -> 2023.5444 | K17: {=INDEX(Assumptions!$D:$AC, MATCH("Launch & Development revenue ($mm/yr): year-row", Assumptions!$A$1:$A$327, 0), COLUMN()-COLUMN($D17)+1)} -> 2124.7216 | ... S17: {=INDEX(Assumptions!$D:$AC, MATCH("Launch & Development revenue ($mm/yr): year-row", Assumptions!$A$1:$A$327, 0), COLUMN()-COLUMN($D17)+1)} -> 3139.1816
A18: Starship commercial-readiness factor | D18: {=INDEX(Assumptions!$D:$AC, MATCH("Starship commercial-readiness factor: year-row", Assumptions!$A$1:$A$327, 0), COLUMN()-COLUMN($D18)+1)} -> 0 | E18: {=INDEX(Assumptions!$D:$AC, MATCH("Starship commercial-readiness factor: year-row", Assumptions!$A$1:$A$327, 0), COLUMN()-COLUMN($D18)+1)} -> 0 | F18: {=INDEX(Assumptions!$D:$AC, MATCH("Starship commercial-readiness factor: year-row", Assumptions!$A$1:$A$327, 0), COLUMN()-COLUMN($D18)+1)} -> 0 | G18: {=INDEX(Assumptions!$D:$AC, MATCH("Starship commercial-readiness factor: year-row", Assumptions!$A$1:$A$327, 0), COLUMN()-COLUMN($D18)+1)} -> 0.07585818 | H18: {=INDEX(Assumptions!$D:$AC, MATCH("Starship commercial-readiness factor: year-row", Assumptions!$A$1:$A$327, 0), COLUMN()-COLUMN($D18)+1)} -> 0.18242552 | I18: {=INDEX(Assumptions!$D:$AC, MATCH("Starship commercial-readiness factor: year-row", Assumptions!$A$1:$A$327, 0), COLUMN()-COLUMN($D18)+1)} -> 0.37754067 | J18: {=INDEX(Assumptions!$D:$AC, MATCH("Starship commercial-readiness factor: year-row", Assumptions!$A$1:$A$327, 0), COLUMN()-COLUMN($D18)+1)} -> 0.62245933 | K18: {=INDEX(Assumptions!$D:$AC, MATCH("Starship commercial-readiness factor: year-row", Assumptions!$A$1:$A$327, 0), COLUMN()-COLUMN($D18)+1)} -> 0.81757448 | ... S18: {=INDEX(Assumptions!$D:$AC, MATCH("Starship commercial-readiness factor: year-row", Assumptions!$A$1:$A$327, 0), COLUMN()-COLUMN($D18)+1)} -> 0.99992515
A19: F9 at-cost rate per launch ($mm) | D19: =INDEX(Assumptions!$B:$B, MATCH("F9 at-cost rate per launch ($mm)", Assumptions!$A$1:$A$327, 0)) -> 20 | E19: =INDEX(Assumptions!$B:$B, MATCH("F9 at-cost rate per launch ($mm)", Assumptions!$A$1:$A$327, 0)) -> 20 | F19: =INDEX(Assumptions!$B:$B, MATCH("F9 at-cost rate per launch ($mm)", Assumptions!$A$1:$A$327, 0)) -> 20 | G19: =INDEX(Assumptions!$B:$B, MATCH("F9 at-cost rate per launch ($mm)", Assumptions!$A$1:$A$327, 0)) -> 20 | H19: =INDEX(Assumptions!$B:$B, MATCH("F9 at-cost rate per launch ($mm)", Assumptions!$A$1:$A$327, 0)) -> 20 | I19: =INDEX(Assumptions!$B:$B, MATCH("F9 at-cost rate per launch ($mm)", Assumptions!$A$1:$A$327, 0)) -> 20 | J19: =INDEX(Assumptions!$B:$B, MATCH("F9 at-cost rate per launch ($mm)", Assumptions!$A$1:$A$327, 0)) -> 20 | K19: =INDEX(Assumptions!$B:$B, MATCH("F9 at-cost rate per launch ($mm)", Assumptions!$A$1:$A$327, 0)) -> 20 | ... S19: =INDEX(Assumptions!$B:$B, MATCH("F9 at-cost rate per launch ($mm)", Assumptions!$A$1:$A$327, 0)) -> 20
A20: Starship at-cost rate per launch ($mm) | D20: {=INDEX('Vehicle Build'!$D:$AC,MATCH("Starship at-cost rate, fully reusable ($mm/launch)",'Vehicle Build'!$A$1:$A$119,0),D$5+1)} -> 18.192564 | E20: {=INDEX('Vehicle Build'!$D:$AC,MATCH("Starship at-cost rate, fully reusable ($mm/launch)",'Vehicle Build'!$A$1:$A$119,0),E$5+1)} -> 14.499424 | F20: {=INDEX('Vehicle Build'!$D:$AC,MATCH("Starship at-cost rate, fully reusable ($mm/launch)",'Vehicle Build'!$A$1:$A$119,0),F$5+1)} -> 11.804893 | G20: {=INDEX('Vehicle Build'!$D:$AC,MATCH("Starship at-cost rate, fully reusable ($mm/launch)",'Vehicle Build'!$A$1:$A$119,0),G$5+1)} -> 9.9704187 | H20: {=INDEX('Vehicle Build'!$D:$AC,MATCH("Starship at-cost rate, fully reusable ($mm/launch)",'Vehicle Build'!$A$1:$A$119,0),H$5+1)} -> 8.8283343 | I20: {=INDEX('Vehicle Build'!$D:$AC,MATCH("Starship at-cost rate, fully reusable ($mm/launch)",'Vehicle Build'!$A$1:$A$119,0),I$5+1)} -> 8.120365 | J20: {=INDEX('Vehicle Build'!$D:$AC,MATCH("Starship at-cost rate, fully reusable ($mm/launch)",'Vehicle Build'!$A$1:$A$119,0),J$5+1)} -> 7.5835393 | K20: {=INDEX('Vehicle Build'!$D:$AC,MATCH("Starship at-cost rate, fully reusable ($mm/launch)",'Vehicle Build'!$A$1:$A$119,0),K$5+1)} -> 7.1354969 | ... S20: {=INDEX('Vehicle Build'!$D:$AC,MATCH("Starship at-cost rate, fully reusable ($mm/launch)",'Vehicle Build'!$A$1:$A$119,0),S$5+1)} -> 6.1585846
A21: F9 booster build cost ($mm) | D21: =INDEX(Assumptions!$B:$B, MATCH("F9 booster (1st stage) mfg cost ($mm/unit)", Assumptions!$A$1:$A$327, 0)) -> 30 | E21: =INDEX(Assumptions!$B:$B, MATCH("F9 booster (1st stage) mfg cost ($mm/unit)", Assumptions!$A$1:$A$327, 0)) -> 30 | F21: =INDEX(Assumptions!$B:$B, MATCH("F9 booster (1st stage) mfg cost ($mm/unit)", Assumptions!$A$1:$A$327, 0)) -> 30 | G21: =INDEX(Assumptions!$B:$B, MATCH("F9 booster (1st stage) mfg cost ($mm/unit)", Assumptions!$A$1:$A$327, 0)) -> 30 | H21: =INDEX(Assumptions!$B:$B, MATCH("F9 booster (1st stage) mfg cost ($mm/unit)", Assumptions!$A$1:$A$327, 0)) -> 30 | I21: =INDEX(Assumptions!$B:$B, MATCH("F9 booster (1st stage) mfg cost ($mm/unit)", Assumptions!$A$1:$A$327, 0)) -> 30 | J21: =INDEX(Assumptions!$B:$B, MATCH("F9 booster (1st stage) mfg cost ($mm/unit)", Assumptions!$A$1:$A$327, 0)) -> 30 | K21: =INDEX(Assumptions!$B:$B, MATCH("F9 booster (1st stage) mfg cost ($mm/unit)", Assumptions!$A$1:$A$327, 0)) -> 30 | ... S21: =INDEX(Assumptions!$B:$B, MATCH("F9 booster (1st stage) mfg cost ($mm/unit)", Assumptions!$A$1:$A$327, 0)) -> 30
A22: Starship vehicle build cost ($mm) | D22: {=INDEX('Vehicle Build'!$D:$AC,MATCH("Starship build cost ($mm/stack)",'Vehicle Build'!$A$1:$A$119,0),D$5+1)} -> 65.071945 | E22: {=INDEX('Vehicle Build'!$D:$AC,MATCH("Starship build cost ($mm/stack)",'Vehicle Build'!$A$1:$A$119,0),E$5+1)} -> 60.97101 | F22: {=INDEX('Vehicle Build'!$D:$AC,MATCH("Starship build cost ($mm/stack)",'Vehicle Build'!$A$1:$A$119,0),F$5+1)} -> 53.8608 | G22: {=INDEX('Vehicle Build'!$D:$AC,MATCH("Starship build cost ($mm/stack)",'Vehicle Build'!$A$1:$A$119,0),G$5+1)} -> 47.701521 | H22: {=INDEX('Vehicle Build'!$D:$AC,MATCH("Starship build cost ($mm/stack)",'Vehicle Build'!$A$1:$A$119,0),H$5+1)} -> 42.953795 | I22: {=INDEX('Vehicle Build'!$D:$AC,MATCH("Starship build cost ($mm/stack)",'Vehicle Build'!$A$1:$A$119,0),I$5+1)} -> 39.290393 | J22: {=INDEX('Vehicle Build'!$D:$AC,MATCH("Starship build cost ($mm/stack)",'Vehicle Build'!$A$1:$A$119,0),J$5+1)} -> 36.395225 | K22: {=INDEX('Vehicle Build'!$D:$AC,MATCH("Starship build cost ($mm/stack)",'Vehicle Build'!$A$1:$A$119,0),K$5+1)} -> 34.0481 | ... S22: {=INDEX('Vehicle Build'!$D:$AC,MATCH("Starship build cost ($mm/stack)",'Vehicle Build'!$A$1:$A$119,0),S$5+1)} -> 29.046443
A23: F9 cadence per booster (flights/yr) | D23: =INDEX(Assumptions!$B:$B, MATCH("F9 cadence per booster (flights/year)", Assumptions!$A$1:$A$327, 0)) -> 6 | E23: =INDEX(Assumptions!$B:$B, MATCH("F9 cadence per booster (flights/year)", Assumptions!$A$1:$A$327, 0)) -> 6 | F23: =INDEX(Assumptions!$B:$B, MATCH("F9 cadence per booster (flights/year)", Assumptions!$A$1:$A$327, 0)) -> 6 | G23: =INDEX(Assumptions!$B:$B, MATCH("F9 cadence per booster (flights/year)", Assumptions!$A$1:$A$327, 0)) -> 6 | H23: =INDEX(Assumptions!$B:$B, MATCH("F9 cadence per booster (flights/year)", Assumptions!$A$1:$A$327, 0)) -> 6 | I23: =INDEX(Assumptions!$B:$B, MATCH("F9 cadence per booster (flights/year)", Assumptions!$A$1:$A$327, 0)) -> 6 | J23: =INDEX(Assumptions!$B:$B, MATCH("F9 cadence per booster (flights/year)", Assumptions!$A$1:$A$327, 0)) -> 6 | K23: =INDEX(Assumptions!$B:$B, MATCH("F9 cadence per booster (flights/year)", Assumptions!$A$1:$A$327, 0)) -> 6 | ... S23: =INDEX(Assumptions!$B:$B, MATCH("F9 cadence per booster (flights/year)", Assumptions!$A$1:$A$327, 0)) -> 6
A24: Starship cadence per vehicle (flights/yr) | D24: {=INDEX('Vehicle Build'!$D:$AC,MATCH("Starship BOOSTER cadence per vehicle in service",'Vehicle Build'!$A$1:$A$119,0),D$5+1)} -> 1 | E24: {=INDEX('Vehicle Build'!$D:$AC,MATCH("Starship BOOSTER cadence per vehicle in service",'Vehicle Build'!$A$1:$A$119,0),E$5+1)} -> 2 | F24: {=INDEX('Vehicle Build'!$D:$AC,MATCH("Starship BOOSTER cadence per vehicle in service",'Vehicle Build'!$A$1:$A$119,0),F$5+1)} -> 2 | G24: {=INDEX('Vehicle Build'!$D:$AC,MATCH("Starship BOOSTER cadence per vehicle in service",'Vehicle Build'!$A$1:$A$119,0),G$5+1)} -> 3.5133635 | H24: {=INDEX('Vehicle Build'!$D:$AC,MATCH("Starship BOOSTER cadence per vehicle in service",'Vehicle Build'!$A$1:$A$119,0),H$5+1)} -> 5.3222908 | I24: {=INDEX('Vehicle Build'!$D:$AC,MATCH("Starship BOOSTER cadence per vehicle in service",'Vehicle Build'!$A$1:$A$119,0),I$5+1)} -> 7.4456972 | J24: {=INDEX('Vehicle Build'!$D:$AC,MATCH("Starship BOOSTER cadence per vehicle in service",'Vehicle Build'!$A$1:$A$119,0),J$5+1)} -> 9.6678002 | K24: {=INDEX('Vehicle Build'!$D:$AC,MATCH("Starship BOOSTER cadence per vehicle in service",'Vehicle Build'!$A$1:$A$119,0),K$5+1)} -> 11.819765 | ... S24: {=INDEX('Vehicle Build'!$D:$AC,MATCH("Starship BOOSTER cadence per vehicle in service",'Vehicle Build'!$A$1:$A$119,0),S$5+1)} -> 24.060474
A25: F9 vehicle life L (years) | D25: =INDEX(Assumptions!$B:$B, MATCH("Asset life L: Customer Launch F9 (years)", Assumptions!$A$1:$A$327, 0)) -> 8 | E25: =INDEX(Assumptions!$B:$B, MATCH("Asset life L: Customer Launch F9 (years)", Assumptions!$A$1:$A$327, 0)) -> 8 | F25: =INDEX(Assumptions!$B:$B, MATCH("Asset life L: Customer Launch F9 (years)", Assumptions!$A$1:$A$327, 0)) -> 8 | G25: =INDEX(Assumptions!$B:$B, MATCH("Asset life L: Customer Launch F9 (years)", Assumptions!$A$1:$A$327, 0)) -> 8 | H25: =INDEX(Assumptions!$B:$B, MATCH("Asset life L: Customer Launch F9 (years)", Assumptions!$A$1:$A$327, 0)) -> 8 | I25: =INDEX(Assumptions!$B:$B, MATCH("Asset life L: Customer Launch F9 (years)", Assumptions!$A$1:$A$327, 0)) -> 8 | J25: =INDEX(Assumptions!$B:$B, MATCH("Asset life L: Customer Launch F9 (years)", Assumptions!$A$1:$A$327, 0)) -> 8 | K25: =INDEX(Assumptions!$B:$B, MATCH("Asset life L: Customer Launch F9 (years)", Assumptions!$A$1:$A$327, 0)) -> 8 | ... S25: =INDEX(Assumptions!$B:$B, MATCH("Asset life L: Customer Launch F9 (years)", Assumptions!$A$1:$A$327, 0)) -> 8
A26: Starship vehicle life L (years) | D26: =INDEX(Assumptions!$B:$B, MATCH("Asset life L: Customer Launch Starship (years)", Assumptions!$A$1:$A$327, 0)) -> 8 | E26: =INDEX(Assumptions!$B:$B, MATCH("Asset life L: Customer Launch Starship (years)", Assumptions!$A$1:$A$327, 0)) -> 8 | F26: =INDEX(Assumptions!$B:$B, MATCH("Asset life L: Customer Launch Starship (years)", Assumptions!$A$1:$A$327, 0)) -> 8 | G26: =INDEX(Assumptions!$B:$B, MATCH("Asset life L: Customer Launch Starship (years)", Assumptions!$A$1:$A$327, 0)) -> 8 | H26: =INDEX(Assumptions!$B:$B, MATCH("Asset life L: Customer Launch Starship (years)", Assumptions!$A$1:$A$327, 0)) -> 8 | I26: =INDEX(Assumptions!$B:$B, MATCH("Asset life L: Customer Launch Starship (years)", Assumptions!$A$1:$A$327, 0)) -> 8 | J26: =INDEX(Assumptions!$B:$B, MATCH("Asset life L: Customer Launch Starship (years)", Assumptions!$A$1:$A$327, 0)) -> 8 | K26: =INDEX(Assumptions!$B:$B, MATCH("Asset life L: Customer Launch Starship (years)", Assumptions!$A$1:$A$327, 0)) -> 8 | ... S26: =INDEX(Assumptions!$B:$B, MATCH("Asset life L: Customer Launch Starship (years)", Assumptions!$A$1:$A$327, 0)) -> 8
A27: Group WACC | D27: =INDEX(Assumptions!$B:$B, MATCH("Group WACC", Assumptions!$A$1:$A$327, 0)) -> 0.1 | E27: =INDEX(Assumptions!$B:$B, MATCH("Group WACC", Assumptions!$A$1:$A$327, 0)) -> 0.1 | F27: =INDEX(Assumptions!$B:$B, MATCH("Group WACC", Assumptions!$A$1:$A$327, 0)) -> 0.1 | G27: =INDEX(Assumptions!$B:$B, MATCH("Group WACC", Assumptions!$A$1:$A$327, 0)) -> 0.1 | H27: =INDEX(Assumptions!$B:$B, MATCH("Group WACC", Assumptions!$A$1:$A$327, 0)) -> 0.1 | I27: =INDEX(Assumptions!$B:$B, MATCH("Group WACC", Assumptions!$A$1:$A$327, 0)) -> 0.1 | J27: =INDEX(Assumptions!$B:$B, MATCH("Group WACC", Assumptions!$A$1:$A$327, 0)) -> 0.1 | K27: =INDEX(Assumptions!$B:$B, MATCH("Group WACC", Assumptions!$A$1:$A$327, 0)) -> 0.1 | ... S27: =INDEX(Assumptions!$B:$B, MATCH("Group WACC", Assumptions!$A$1:$A$327, 0)) -> 0.1
A28: Customer Launch R&D % (start) | D28: =INDEX(Assumptions!$B:$B, MATCH("Customer Launch R&D: start % of external rev", Assumptions!$A$1:$A$327, 0)) -> 0.735 | E28: =INDEX(Assumptions!$B:$B, MATCH("Customer Launch R&D: start % of external rev", Assumptions!$A$1:$A$327, 0)) -> 0.735 | F28: =INDEX(Assumptions!$B:$B, MATCH("Customer Launch R&D: start % of external rev", Assumptions!$A$1:$A$327, 0)) -> 0.735 | G28: =INDEX(Assumptions!$B:$B, MATCH("Customer Launch R&D: start % of external rev", Assumptions!$A$1:$A$327, 0)) -> 0.735 | H28: =INDEX(Assumptions!$B:$B, MATCH("Customer Launch R&D: start % of external rev", Assumptions!$A$1:$A$327, 0)) -> 0.735 | I28: =INDEX(Assumptions!$B:$B, MATCH("Customer Launch R&D: start % of external rev", Assumptions!$A$1:$A$327, 0)) -> 0.735 | J28: =INDEX(Assumptions!$B:$B, MATCH("Customer Launch R&D: start % of external rev", Assumptions!$A$1:$A$327, 0)) -> 0.735 | K28: =INDEX(Assumptions!$B:$B, MATCH("Customer Launch R&D: start % of external rev", Assumptions!$A$1:$A$327, 0)) -> 0.735 | ... S28: =INDEX(Assumptions!$B:$B, MATCH("Customer Launch R&D: start % of external rev", Assumptions!$A$1:$A$327, 0)) -> 0.735
A29: Customer Launch R&D % (floor) | D29: =INDEX(Assumptions!$B:$B, MATCH("Customer Launch R&D: end-state % (floor)", Assumptions!$A$1:$A$327, 0)) -> 0.04 | E29: =INDEX(Assumptions!$B:$B, MATCH("Customer Launch R&D: end-state % (floor)", Assumptions!$A$1:$A$327, 0)) -> 0.04 | F29: =INDEX(Assumptions!$B:$B, MATCH("Customer Launch R&D: end-state % (floor)", Assumptions!$A$1:$A$327, 0)) -> 0.04 | G29: =INDEX(Assumptions!$B:$B, MATCH("Customer Launch R&D: end-state % (floor)", Assumptions!$A$1:$A$327, 0)) -> 0.04 | H29: =INDEX(Assumptions!$B:$B, MATCH("Customer Launch R&D: end-state % (floor)", Assumptions!$A$1:$A$327, 0)) -> 0.04 | I29: =INDEX(Assumptions!$B:$B, MATCH("Customer Launch R&D: end-state % (floor)", Assumptions!$A$1:$A$327, 0)) -> 0.04 | J29: =INDEX(Assumptions!$B:$B, MATCH("Customer Launch R&D: end-state % (floor)", Assumptions!$A$1:$A$327, 0)) -> 0.04 | K29: =INDEX(Assumptions!$B:$B, MATCH("Customer Launch R&D: end-state % (floor)", Assumptions!$A$1:$A$327, 0)) -> 0.04 | ... S29: =INDEX(Assumptions!$B:$B, MATCH("Customer Launch R&D: end-state % (floor)", Assumptions!$A$1:$A$327, 0)) -> 0.04
A30: Customer Launch R&D % (CAGR) | D30: =INDEX(Assumptions!$B:$B, MATCH("Customer Launch R&D: CAGR (taper)", Assumptions!$A$1:$A$327, 0)) -> -0.25 | E30: =INDEX(Assumptions!$B:$B, MATCH("Customer Launch R&D: CAGR (taper)", Assumptions!$A$1:$A$327, 0)) -> -0.25 | F30: =INDEX(Assumptions!$B:$B, MATCH("Customer Launch R&D: CAGR (taper)", Assumptions!$A$1:$A$327, 0)) -> -0.25 | G30: =INDEX(Assumptions!$B:$B, MATCH("Customer Launch R&D: CAGR (taper)", Assumptions!$A$1:$A$327, 0)) -> -0.25 | H30: =INDEX(Assumptions!$B:$B, MATCH("Customer Launch R&D: CAGR (taper)", Assumptions!$A$1:$A$327, 0)) -> -0.25 | I30: =INDEX(Assumptions!$B:$B, MATCH("Customer Launch R&D: CAGR (taper)", Assumptions!$A$1:$A$327, 0)) -> -0.25 | J30: =INDEX(Assumptions!$B:$B, MATCH("Customer Launch R&D: CAGR (taper)", Assumptions!$A$1:$A$327, 0)) -> -0.25 | K30: =INDEX(Assumptions!$B:$B, MATCH("Customer Launch R&D: CAGR (taper)", Assumptions!$A$1:$A$327, 0)) -> -0.25 | ... S30: =INDEX(Assumptions!$B:$B, MATCH("Customer Launch R&D: CAGR (taper)", Assumptions!$A$1:$A$327, 0)) -> -0.25
A31: Launch / vehicle facility CapEx ($mm) | D31: {=INDEX('Facilities Build'!$D:$AC, MATCH("Launch/vehicle facility CapEx total ($mm) ◄ launch/vehicle", 'Facilities Build'!$A$1:$A$74, 0), COLUMN()-COLUMN($D31)+1)} -> 750 | E31: {=INDEX('Facilities Build'!$D:$AC, MATCH("Launch/vehicle facility CapEx total ($mm) ◄ launch/vehicle", 'Facilities Build'!$A$1:$A$74, 0), COLUMN()-COLUMN($D31)+1)} -> 750 | F31: {=INDEX('Facilities Build'!$D:$AC, MATCH("Launch/vehicle facility CapEx total ($mm) ◄ launch/vehicle", 'Facilities Build'!$A$1:$A$74, 0), COLUMN()-COLUMN($D31)+1)} -> 375 | G31: {=INDEX('Facilities Build'!$D:$AC, MATCH("Launch/vehicle facility CapEx total ($mm) ◄ launch/vehicle", 'Facilities Build'!$A$1:$A$74, 0), COLUMN()-COLUMN($D31)+1)} -> 471.4 | H31: {=INDEX('Facilities Build'!$D:$AC, MATCH("Launch/vehicle facility CapEx total ($mm) ◄ launch/vehicle", 'Facilities Build'!$A$1:$A$74, 0), COLUMN()-COLUMN($D31)+1)} -> 892 | I31: {=INDEX('Facilities Build'!$D:$AC, MATCH("Launch/vehicle facility CapEx total ($mm) ◄ launch/vehicle", 'Facilities Build'!$A$1:$A$74, 0), COLUMN()-COLUMN($D31)+1)} -> 892 | J31: {=INDEX('Facilities Build'!$D:$AC, MATCH("Launch/vehicle facility CapEx total ($mm) ◄ launch/vehicle", 'Facilities Build'!$A$1:$A$74, 0), COLUMN()-COLUMN($D31)+1)} -> 1092 | K31: {=INDEX('Facilities Build'!$D:$AC, MATCH("Launch/vehicle facility CapEx total ($mm) ◄ launch/vehicle", 'Facilities Build'!$A$1:$A$74, 0), COLUMN()-COLUMN($D31)+1)} -> 775 | ... S31: {=INDEX('Facilities Build'!$D:$AC, MATCH("Launch/vehicle facility CapEx total ($mm) ◄ launch/vehicle", 'Facilities Build'!$A$1:$A$74, 0), COLUMN()-COLUMN($D31)+1)} -> 375
