Workbook

Sheet Assumptions
A1: 0.01 | D1: 2025 | E1: 2026 | F1: 2027 | G1: 2028 | H1: 2029 | I1: 2030 | J1: 2031 | K1: 2032 | L1: 2033 | M1: 2034 | N1: 2035 | O1: 2036 | P1: 2037 | Q1: 2038 | R1: 2039 | S1: 2040
A2: GLOBAL | D2: 0 | E2: 1 | F2: 2 | G2: 3 | H2: 4 | I2: 5 | J2: 6 | K2: 7 | L2: 8 | M2: 9 | N2: 10 | O2: 11 | P2: 12 | Q2: 13 | R2: 14 | S2: 15
A3: Tax rate (corporate, US federal + state blended) | B3: 0.21 | C3: Standard US corporate rate; S-1 silent on effective rate split. | W3: 0.18 | X3: 0.27 | Y3: triangle
A4: Demand curve escalator: start rate (annual) | B4: 0.035 | C4: Early willingness-to-pay growth above inflation. | D4: 2025 | E4: 2026 | F4: 2027 | G4: 2028 | H4: 2029 | I4: 2030 | J4: 2031 | K4: 2032 | L4: 2033 | M4: 2034 | N4: 2035 | O4: 2036 | P4: 2037 | Q4: 2038 | R4: 2039 | S4: 2040 | W4: 0.025 | X4: 0.05 | Y4: triangle
A5: Demand curve escalator: terminal rate (annual) | B5: 0.025 | C5: Mature-market escalator ≈ inflation. The tapered curve converges here after the taper ends. | D5: 0 | E5: 1 | F5: 2 | G5: 3 | H5: 4 | I5: 5 | J5: 6 | K5: 7 | L5: 8 | M5: 9 | N5: 10 | O5: 11 | P5: 12 | Q5: 13 | R5: 14 | S5: 15 | W5: 0.02 | X5: 0.03 | Y5: triangle
A6: ALLOCATOR
A7: ▸ Cash pool boundary inputs
A8: IPO injection amount ($mm) | B8: 75000 | C8: IPO proceeds target not disclosed; placeholder.
A9: IPO injection year | B9: 2027 | W9: 2026 | X9: 2028 | Y9: discrete
A10: ▸ Lunar/Mars strategic carve-out (Monte Carlo variable)
A11: Lunar/Mars carve-out % of prior-year Group FCF | B11: 0.15 | W11: 0.03 | X11: 0.35 | Y11: triangle
A12: Lunar/Mars carve-out floor ($mm/yr) | B12: 1000 | C12: Floor below which carve-out doesn't drop even if prior FCF is small. | W12: 500 | X12: 2500 | Y12: triangle
A13: Lunar/Mars carve-out uses prior-year FCF (0/1) | B13: 1 | C13: 1 = prior year (breaks circularity per Principle 22). Structural input. | Y13: fixed
A14: Lunar/Mars carve-out pre-first-mission-year R&D-only override ($mm/yr) | B14: 750 | W14: 500 | X14: 1000 | Y14: triangle
A15: ▸ IRR-weighted allocation parameters
A16: Allocation sharpness β (top-level 3-module blend) | B16: 3 | W16: 1 | X16: 10 | Y16: triangle
A17: ▸ Per-module asset life L (canonical IRR formula input)
A18: Asset life L: Customer Launch Starship (years) | B18: 8 | C18: F9 booster analog (lifetime reuses ramp). | W18: 6 | X18: 10 | Y18: triangle
A19: Asset life L: Customer Launch F9 (years) | B19: 8 | C19: Customer Launch IRR anchor. | W19: 6 | X19: 10 | Y19: triangle
A20: Asset life L: AI/Compute Orbital DC (years) | B20: 5 | C20: Sat-based; matches Starlink sat life. | W20: 4 | X20: 7 | Y20: triangle
A21: Asset life L: AI/Compute Terrestrial DC (years) | B21: 15 | C21: Industry norm for DC infrastructure. | W21: 10 | X21: 20 | Y21: triangle
A22: Asset life L: AI/Compute AI Apps (years) | B22: 3 | C22: Customer subscription life / CAC payback. | W22: 2 | X22: 5 | Y22: triangle
A23: ▸ Customer Launch IRR life clamps
A24: ▸ Vehicle build claim (demand-pulled, one-period lag)
A25: CAPACITY (Starship + F9)
A26: ▸ Starship vehicle physical + cost parameters
A27: Starship 2nd-stage manufacturing cost ($mm/unit, base) | B27: 23.4 | C27: Reusability matrix anchor. | W27: 18 | X27: 30 | Y27: triangle
A28: Ship refurb % of manufacturing | B28: 0.02 | C28: Per-reuse refurb cost. | W28: 0.01 | X28: 0.05 | Y28: triangle
A29: Payload: booster-only mode (kg-to-LEO) | B29: 150000 | C29: Expendable ship config. S-1 (p.92) confirms 100 mt V3 → 200 mt V4 potentially. 150K kg booster-only sits between V3 and V4. | W29: 130000 | X29: 200000 | Y29: triangle
A30: Payload: fully reusable mode (kg-to-LEO) | B30: 100000 | C30: S-1 p.92 EXPLICIT: V3 design 100 mt. Match. | W30: 80000 | X30: 150000 | Y30: triangle
A31: ▸ Starship cadence (Wright's Law on cum upmass)
A32: Base turnaround time per booster (years/flight) | B32: 1 | C32: 2025 starting point. | W32: 0.8 | X32: 1.5 | Y32: triangle
A33: WL learning rate: turnaround vs cum upmass doubling | B33: 0.21 | C33: Booster learning rate (0.21). Cumulative experience compounds faster than an annual proxy. Monte Carlo range 0.15–0.28. Holds the rising 6→~22 booster cadence ramp. | W33: 0.05 | X33: 0.25 | Y33: triangle
A34: Cadence ceiling (flights/booster/year) | B34: 60 | C34: Physical refly ceiling at full maturity. | W34: 40 | X34: 100 | Y34: triangle
A35: ▸ Starship time-varying inputs (year-rows)
A36: Lifetime reuses per booster (year cap) | C36: Ramps 5 → 100. S-1 anchors F9 at 34x (p.4); soft-anchor 2025 to ~30-35 for F9-class maturity. | D36: =5*$B$481 -> 5 | E36: =8*$B$481 -> 8 | F36: =12*$B$481 -> 12 | G36: =18*$B$481 -> 18 | H36: =25*$B$481 -> 25 | I36: =30*$B$481 -> 30 | J36: =35*$B$481 -> 35 | K36: =42*$B$481 -> 42 | L36: =50*$B$481 -> 50 | M36: =58*$B$481 -> 58 | N36: =65*$B$481 -> 65 | O36: =70*$B$481 -> 70 | P36: =75*$B$481 -> 75 | Q36: =80*$B$481 -> 80 | R36: =85*$B$481 -> 85 | S36: =90*$B$481 -> 90 | Y36: fixed-yearrow
A37: ▸ Falcon 9 physical + cost parameters
A38: F9 booster (1st stage) mfg cost ($mm/unit) | B38: 30 | C38: 60% of total per reusability matrix source notes. S-1 silent. | W38: 25 | X38: 35 | Y38: triangle
A39: F9 2nd stage mfg cost ($mm/unit) | B39: 10 | C39: Expendable each flight. | W39: 8 | X39: 13 | Y39: triangle
A40: F9 fairing cost net of 75% recovery ($mm/flight) | B40: 1.25 | C40: $5M × 25% non-recovered. | W40: 1 | X40: 2 | Y40: triangle
A41: F9 per-launch ops cost ($mm) | B41: 5 | C41: Range, propellant, recovery. | W41: 3 | X41: 8 | Y41: triangle
A42: F9 booster refurb % of mfg | B42: 0.03 | C42: Reusability matrix. | W42: 0.02 | X42: 0.05 | Y42: triangle
A43: F9 payload to LEO (kg) | B43: 22800 | C43: Block 5 advertised. S-1 mass-to-orbit decomposition triangulates (p.85): 1,901 mt internal / 122 launches = 15.6 mt/launch, well below F9 stretch limit. | Y43: fixed
A44: F9 lifetime reuses per booster | B44: 35 | C44: S-1 p.4 reports 34 reflights demonstrated. Lowered Base from 50 to 35 to match demonstrated; upper MC tail to 100. | W44: 30 | X44: 100 | Y44: triangle
A45: F9 Wright's Law mfg learning rate | B45: 0.02 | C45: Mature production line; minimal further learning. | W45: 0 | X45: 0.05 | Y45: triangle
A46: F9 cadence per booster (flights/year, flat) | B46: 8 | C46: S-1 implies actual 2025 = ~5.9 flights/booster (165 launches ÷ 28 boosters). Build Plan 12 was mature ceiling; Base lowered to 8 to reflect actual ramp; MC top retained to 15. | W46: 6 | X46: 15 | Y46: triangle
A47: F9 base booster build rate (boosters/year, pre-V3-trigger) | B47: 8 | C47: Q4'25 had 17 manufactured in 2025, but that's pre-decay. Build floor stub. | W47: 6 | X47: 10 | Y47: triangle
A48: V3 Starlink launch trigger year | B48: 2026 | C48: S-1 p.5, p.93 EXPLICIT: "V3 deployment begins 2H 2026 on Starship; 60 V3 sats per Starship launch." Build Plan had 2027, overridden. | W48: 2026 | X48: 2027 | Y48: discrete
A49: F9 build-rate decay window (years) | B49: 8 | C49: Linear decay over 8 yrs post-trigger. | W49: 6 | X49: 12 | Y49: triangle
A50: F9 starting fleet at 2025 SoY (boosters) | B50: 28 | C50: Q4'25 Earth R29 anchored. S-1 doesn't disclose fleet count but cadence math (165 launches ÷ 28 = 5.9 flights/booster) is plausible. V30.5 had 24, corrected. | Y50: fixed
A51: ▸ F9 launch glide path (Customer Launch IN to Vehicle Build)
A52: CUSTOMER LAUNCH
A53: F9 customer launch price ($mm/launch) | B53: 54.8 | C53: 2025 Space segment revenue = $4,086M (Launch Services $2,576M + Launch & Delivery $1,510M) ÷ 43 commercial customer launches = $95.0M blended. Split: commercial ~$85.9M × ~30 launches + government/defense ~$116.2M × ~13 launches. Declines 3%/yr. Calibration target: 2025 Customer Launch revenue = $4,086M ±5%. | Y53: fixed-yearrow
A54: Starship customer launch price ($mm/launch): year-row | C54: S-1 p.5 confirms first commercial Starship payload delivery 2H 2026. Customer revenue from 2027 (1yr after first delivery). $100M stub stands; 8%/yr decline. | D54: 0 | E54: 0 | F54: 100 | G54: =$F54*(1+$B$458)^(G$2-2) -> 92 | H54: =$F54*(1+$B$458)^(H$2-2) -> 84.64 | I54: =$F54*(1+$B$458)^(I$2-2) -> 77.8688 | J54: =$F54*(1+$B$458)^(J$2-2) -> 71.639296 | K54: =$F54*(1+$B$458)^(K$2-2) -> 65.908152 | L54: =$F54*(1+$B$458)^(L$2-2) -> 60.6355 | M54: =$F54*(1+$B$458)^(M$2-2) -> 55.78466 | N54: =$F54*(1+$B$458)^(N$2-2) -> 51.321887 | ... S54: =$F54*(1+$B$458)^(S$2-2) -> 33.825308 | Y54: fixed-yearrow
A55: Commercial launch market size ($mm/year): year-row | C55: Build plan $8B base + 8%/yr growth. The S-1 implies a ~70% SpaceX share of a ~$5.5B 2025 market, so this build plan may be too high. | D55: 8000 | E55: =$D55*(1+$B$459)^E$2 -> 8640 | F55: =$D55*(1+$B$459)^F$2 -> 9331.2 | G55: =$D55*(1+$B$459)^G$2 -> 10077.696 | H55: =$D55*(1+$B$459)^H$2 -> 10883.912 | I55: =$D55*(1+$B$459)^I$2 -> 11754.625 | J55: =$D55*(1+$B$459)^J$2 -> 12694.995 | K55: =$D55*(1+$B$459)^K$2 -> 13710.594 | L55: =$D55*(1+$B$459)^L$2 -> 14807.442 | ... S55: =$D55*(1+$B$459)^S$2 -> 25377.353 | Y55: fixed-yearrow
A56: Government launch market size ($mm/year): year-row | C56: Build plan $4B + 5%/yr. 2025 Launch & Delivery of $1,510M (NASA CRS + DoW) implies a ~$1.7B market at 90% share, so this build plan looks high. | D56: 4000 | E56: =$D56*(1+$B$460)^E$2 -> 4200 | F56: =$D56*(1+$B$460)^F$2 -> 4410 | G56: =$D56*(1+$B$460)^G$2 -> 4630.5 | H56: =$D56*(1+$B$460)^H$2 -> 4862.025 | I56: =$D56*(1+$B$460)^I$2 -> 5105.1263 | J56: =$D56*(1+$B$460)^J$2 -> 5360.3826 | K56: =$D56*(1+$B$460)^K$2 -> 5628.4017 | L56: =$D56*(1+$B$460)^L$2 -> 5909.8218 | ... S56: =$D56*(1+$B$460)^S$2 -> 8315.7127 | Y56: fixed-yearrow
A57: SpaceX commercial market share % | C57: S-1 p.81 supports higher share than Build Plan's 70%. New trajectory: 75% (2025) → 80% (2040, linear). | D57: 0.75 | E57: =MIN(0.8,$D57+$B$461*E$2) -> 0.75333333 | F57: =MIN(0.8,$D57+$B$461*F$2) -> 0.75666667 | G57: =MIN(0.8,$D57+$B$461*G$2) -> 0.76 | H57: =MIN(0.8,$D57+$B$461*H$2) -> 0.76333333 | I57: =MIN(0.8,$D57+$B$461*I$2) -> 0.76666667 | J57: =MIN(0.8,$D57+$B$461*J$2) -> 0.77 | K57: =MIN(0.8,$D57+$B$461*K$2) -> 0.77333333 | L57: =MIN(0.8,$D57+$B$461*L$2) -> 0.77666667 | ... S57: =MIN(0.8,$D57+$B$461*S$2) -> 0.8 | Y57: fixed-yearrow
A58: SpaceX government market share % | C58: Customer A 20.9% concentration trend supports declining gov share. 90% → 80% linear. | D58: 0.9 | E58: =MAX(0.8,$D58+$B$462*E$2) -> 0.89333333 | F58: =MAX(0.8,$D58+$B$462*F$2) -> 0.88666667 | G58: =MAX(0.8,$D58+$B$462*G$2) -> 0.88 | H58: =MAX(0.8,$D58+$B$462*H$2) -> 0.87333333 | I58: =MAX(0.8,$D58+$B$462*I$2) -> 0.86666667 | J58: =MAX(0.8,$D58+$B$462*J$2) -> 0.86 | K58: =MAX(0.8,$D58+$B$462*K$2) -> 0.85333333 | L58: =MAX(0.8,$D58+$B$462*L$2) -> 0.84666667 | ... S58: =MAX(0.8,$D58+$B$462*S$2) -> 0.8 | Y58: fixed-yearrow
A59: Launch insurance % of external rev | B59: 0.05 | C59: Internal. | W59: 0.03 | X59: 0.08 | Y59: triangle
A60: Launch other COGS % of external rev | B60: 0.02 | C60: Internal. | W60: 0.01 | X60: 0.04 | Y60: triangle
A61: ▸ NEW S-1 derived inputs
A62: STARLINK
A63: ▸ Wright's Law parameters
A64: Satellite cost per kg: base year ($/kg) | B64: 650 | C64: Q4'25 $643.50; S-1 PP&E sat gross $11,949M / 9,600 sats × 575 kg ≈ $720/kg, within tolerance. | W64: 500 | X64: 800 | Y64: triangle
A65: Satellite cost per kg: learning rate | B65: 0.05 | C65: Internal. | W65: 0.03 | X65: 0.17 | Y65: triangle
A66: Satellite cost floor ($/kg) | B66: 400 | C66: Internal. | W66: 300 | X66: 500 | Y66: triangle
A67: ▸ Depreciation parameters
A68: Satellite Dep per kg: base year ($/kg/yr) | B68: 128.8 | C68: Constellation depreciation. S-1 property, plant & equipment: satellite gross $11,949M → ~$2,390M at a 5-year life; 2025 target ≈ $706.9M. | W68: 110 | X68: 150 | Y68: triangle
A69: ▸ Subscribers + ARPU + Terminals (BIG S-1 IMPACTS)
A70: Starting BoY 2025 subscribers (millions) | B70: 4.4 | C70: S-1 p.22, p.87 audited EoY 2024 = BoY 2025 = 4.4M. Build Plan had 5.0M, overridden. | W70: 3.5 | X70: 6 | Y70: triangle
A71: Broadband ARPU ($/sub/mo): year-row | C71: S-1 p.22, p.87: 2025 = $81 (audited); Q1'26 = $66 (audited); mgmt guidance: continued decline as international growth + lower-priced plans land. Build Plan $100→$75 by 2030 OVERRIDDEN. New trajectory: $81 → $55 by 2030 → flat. | D71: 81 | E71: =MAX($B$466,$D71*(1+$B$465)^E$2) -> 75.978 | F71: =MAX($B$466,$D71*(1+$B$465)^F$2) -> 71.267364 | G71: =MAX($B$466,$D71*(1+$B$465)^G$2) -> 66.848787 | H71: =MAX($B$466,$D71*(1+$B$465)^H$2) -> 62.704163 | I71: =MAX($B$466,$D71*(1+$B$465)^I$2) -> 58.816505 | J71: =MAX($B$466,$D71*(1+$B$465)^J$2) -> 55.169881 | K71: =MAX($B$466,$D71*(1+$B$465)^K$2) -> 51.749349 | L71: =MAX($B$466,$D71*(1+$B$465)^L$2) -> 48.540889 | ... S71: =MAX($B$466,$D71*(1+$B$465)^S$2) -> 47.5 | Y71: triangle-yearrow
A72: Terminal COGS per unit ($) | B72: 500 | C72: S-1 p.247 Connectivity products $1,510M is terminal-sales channel. No unit cost disclosed. | W72: 400 | X72: 700 | Y72: triangle
A73: ODC — RETIRED, superseded by the AI/Compute section. Memos below retained.
A74: F_ref: reference compute unit (TFLOPS, H100 FP8) | B74: 1979 | Y74: fixed
A75: ▸ Dual revenue model
A76: PUE_base (terrestrial colo) | B76: 1.4 | C76: Industry standard. | W76: 1.3 | X76: 1.6 | Y76: triangle
A77: Orbital PUE | B77: 1.12 | C77: First-principles. | W77: 1.05 | X77: 1.25 | Y77: triangle
A78: Memo: ODC first deployment year (anchor) | B78: 2028 | C78: S-1 p.3, p.10. Cash flows to ODC starting 2027 (1-yr build lead). | Y78: fixed
A79: Memo: Terrestrial AI compute draw (GW): year-row | C79: S-1 p.22, p.89: 0.3 EoY 2023 → 0.8 EoY 2025 → 1.0 Q1'26. COLOSSUS + COLOSSUS II buildout. Memo for AI Stack TAM sizing. | D79: =0.8*$B$482 -> 0.8 | E79: =1.5*$B$482 -> 1.5 | F79: =2.5*$B$482 -> 2.5 | G79: =4*$B$482 -> 4 | H79: =6*$B$482 -> 6 | I79: =8*$B$482 -> 8 | J79: =10*$B$482 -> 10 | K79: =12*$B$482 -> 12 | L79: =14*$B$482 -> 14 | M79: =16*$B$482 -> 16 | N79: =18*$B$482 -> 18 | O79: =20*$B$482 -> 20 | P79: =22*$B$482 -> 22 | Q79: =24*$B$482 -> 24 | R79: =26*$B$482 -> 26 | S79: =28*$B$482 -> 28 | Y79: fixed-yearrow
A80: LUNAR / MARS (strategic carve-out: not in the IRR queue)
A81: ▸ Module-wide parameters
A82: Capital lifetime: BV straight-line depreciation (years) | B82: 10 | C82: Reuses Asset Life L from R31. Q4'25 R205. | W82: 7 | X82: 15 | Y82: triangle
A83: Module operating cost: Lunar (% of Lunar CapEx) | B83: 0.05 | C83: 5% mission ops. | W83: 0.03 | X83: 0.1 | Y83: triangle
A84: Module operating cost: Mars (% of Mars CapEx) | B84: 0.05 | C84: Same. | W84: 0.03 | X84: 0.1 | Y84: triangle
A85: First mission year (Lunar Mars) | B85: 2030 | C85: Gates deployment before 2028 to zero. | Y85: fixed
A86: ▸ Labour unit shared parameters (Optimus-class proxy)
A87: Labour unit mass (kg) | B87: 60 | C87: Robotic class proxy. | W87: 40 | X87: 100 | Y87: triangle
A88: Labour unit base hourly output ($/hr; burdened $22/0.7) | B88: 31.43 | C88: Derived. | Y88: fixed
A89: Labour unit daily working hours | B89: 22 | C89: Robots don't sleep. | W89: 18 | X89: 24 | Y89: triangle
A90: Labour unit productivity factor vs human baseline | B90: 1 | C90: Parity stub. | W90: 0.25 | X90: 2 | Y90: triangle
A91: Labour unit productivity learning rate (%/yr) | B91: 0.05 | C91: 5%/yr productivity gain. | W91: 0.02 | X91: 0.15 | Y91: triangle
A92: Labour unit operational lifespan on surface (years) | B92: 5 | C92: Retirement vintage. | W92: 3 | X92: 8 | Y92: triangle
A93: ▸ Lunar-specific
A94: Lunar fuel depot multiplier per outbound Starship | B94: 5 | C94: 5 tanker per moon ship. | W94: 4 | X94: 6 | Y94: triangle
A95: Lunar payload per surface-landed Starship (kg) | B95: 100000 | C95: Translunar with landing reserve. | W95: 80000 | X95: 120000 | Y95: triangle
A96: Lunar % payload as labour units | B96: 0.3 | C96: 30% labour / 70% hardware. | W96: 0.1 | X96: 0.5 | Y96: triangle
A97: ▸ Mars-specific
A98: Mars fuel depot multiplier per outbound Starship | B98: 5 | C98: Rocket equation; 5 tankers per Mars ship. | W98: 3 | X98: 8 | Y98: triangle
A99: Mars payload per surface-landed Starship (kg) | B99: 100000 | C99: Cargo Starship Mars landing. | W99: 70000 | X99: 130000 | Y99: triangle
A100: Mars % payload as labour units | B100: 0.3 | C100: Same as Lunar. | W100: 0.1 | X100: 0.5 | Y100: triangle
...

Sheet Demand Curves
A1: Demand Curves: Starlink BB + DTC piecewise-linear lookup
A2: Lookup form: INDEX/MATCH(..., 1) bracket-find + manual linear interp. NO FORECAST / TREND. Per Memory Snapshot v3 §2.4.
D4: 2025 | E4: 2026 | F4: 2027 | G4: 2028 | H4: 2029 | I4: 2030 | J4: 2031 | K4: 2032 | L4: 2033 | M4: 2034 | N4: 2035 | O4: 2036 | P4: 2037 | Q4: 2038 | R4: 2039 | S4: 2040
D5: 0 | E5: 1 | F5: 2 | G5: 3 | H5: 4 | I5: 5 | J5: 6 | K5: 7 | L5: 8 | M5: 9 | N5: 10 | O5: 11 | P5: 12 | Q5: 13 | R5: 14 | S5: 15
A15: DTC DEMAND CURVE (piecewise-linear Q→Revenue lookup)
A16: Constellation Bandwidth (Gbps) | B16: Q (Gbps) | C16: Annual DTC Revenue ($mm)
A17: DTC Q breakpoint #1 (Gbps) | B17: 280.2 | C17: 307
A18: DTC Q breakpoint #2 (Gbps) | B18: 560.3 | C18: 613
A19: DTC Q breakpoint #3 (Gbps) | B19: 840.5 | C19: 920
A20: DTC Q breakpoint #4 (Gbps) | B20: 1120.6 | C20: 1227
A21: DTC Q breakpoint #5 (Gbps) | B21: 1400.8 | C21: 1534
A22: DTC Q breakpoint #6 (Gbps) | B22: 1680.9 | C22: 1840
A23: DTC Q breakpoint #7 (Gbps) | B23: 1961.1 | C23: 2147
A24: DTC Q breakpoint #8 (Gbps) | B24: 2241.2 | C24: 2454
A25: DTC Q breakpoint #9 (Gbps) | B25: 2521.4 | C25: 2760
A26: DTC Q breakpoint #10 (Gbps) | B26: 2801.5 | C26: 3067
A27: DTC Q breakpoint #11 (Gbps) | B27: 3501.9 | C27: 3827
A28: DTC Q breakpoint #12 (Gbps) | B28: 4202.3 | C28: 4587
... A77: DTC Q breakpoint #61 (Gbps) | B77: 84046.3 | C77: 15920
A80: BB DEMAND CURVE (piecewise-linear Q→Revenue lookup)
A81: Capacity (Gbps) | B81: Q (Gbps) | C81: BB TAM/Revenue ($mm)
A82: BB Q breakpoint #1 (Gbps) | B82: 100000 | C82: 2936
A83: BB Q breakpoint #2 (Gbps) | B83: 200000 | C83: 3748
A84: BB Q breakpoint #3 (Gbps) | B84: 300000 | C84: 4559
A85: BB Q breakpoint #4 (Gbps) | B85: 400000 | C85: 5370
A86: BB Q breakpoint #5 (Gbps) | B86: 500000 | C86: 6157
A87: BB Q breakpoint #6 (Gbps) | B87: 1000000 | C87: 10055
A88: BB Q breakpoint #7 (Gbps) | B88: 2000000 | C88: 17173
A89: BB Q breakpoint #8 (Gbps) | B89: 3000000 | C89: 23037
A90: BB Q breakpoint #9 (Gbps) | B90: 4000000 | C90: 28430
A91: BB Q breakpoint #10 (Gbps) | B91: 5000000 | C91: 33451
A92: BB Q breakpoint #11 (Gbps) | B92: 6000000 | C92: 38244
A93: BB Q breakpoint #12 (Gbps) | B93: 7000000 | C93: 42520
... A137: BB Q breakpoint #56 (Gbps) | B137: 250000000 | C137: 187819
A140: ▸ Curve evaluators (year-row, read by the Starlink module)
A141: Annual TAM shift multiplier | D141: =1 -> 1 | E141: =D141*(1+E149) -> 1.035 | F141: =E141*(1+F149) -> 1.070075 | G141: =F141*(1+G149) -> 1.1051497 | H141: =G141*(1+H149) -> 1.1401461 | I141: =H141*(1+I149) -> 1.1749839 | J141: =I141*(1+J149) -> 1.2095806 | K141: =J141*(1+K149) -> 1.2438521 | L141: =K141*(1+L149) -> 1.2777125 | ... S141: =R141*(1+S149) -> 1.520445
A142: Starlink BB capacity input (Gbps) | D142: {=IFERROR(INDEX(Starlink!$D:$AC,MATCH("BB Gbps available for external Starlink revenue",Starlink!$A$1:$A$204,0),COLUMN()-COLUMN($D142)+1),0)} -> 489144 | E142: {=IFERROR(INDEX(Starlink!$D:$AC,MATCH("BB Gbps available for external Starlink revenue",Starlink!$A$1:$A$204,0),COLUMN()-COLUMN($D142)+1),0)} -> 756736 | F142: {=IFERROR(INDEX(Starlink!$D:$AC,MATCH("BB Gbps available for external Starlink revenue",Starlink!$A$1:$A$204,0),COLUMN()-COLUMN($D142)+1),0)} -> 4652053.4 | G142: {=IFERROR(INDEX(Starlink!$D:$AC,MATCH("BB Gbps available for external Starlink revenue",Starlink!$A$1:$A$204,0),COLUMN()-COLUMN($D142)+1),0)} -> 13909825 | H142: {=IFERROR(INDEX(Starlink!$D:$AC,MATCH("BB Gbps available for external Starlink revenue",Starlink!$A$1:$A$204,0),COLUMN()-COLUMN($D142)+1),0)} -> 37706339 | I142: {=IFERROR(INDEX(Starlink!$D:$AC,MATCH("BB Gbps available for external Starlink revenue",Starlink!$A$1:$A$204,0),COLUMN()-COLUMN($D142)+1),0)} -> 52599406 | J142: {=IFERROR(INDEX(Starlink!$D:$AC,MATCH("BB Gbps available for external Starlink revenue",Starlink!$A$1:$A$204,0),COLUMN()-COLUMN($D142)+1),0)} -> 81246796 | K142: {=IFERROR(INDEX(Starlink!$D:$AC,MATCH("BB Gbps available for external Starlink revenue",Starlink!$A$1:$A$204,0),COLUMN()-COLUMN($D142)+1),0)} -> 93730001 | ... S142: {=IFERROR(INDEX(Starlink!$D:$AC,MATCH("BB Gbps available for external Starlink revenue",Starlink!$A$1:$A$204,0),COLUMN()-COLUMN($D142)+1),0)} -> 1.8886232e+08
A143: Starlink DTC capacity input (Gbps) | D143: {=IFERROR(INDEX(Starlink!$D:$AC,MATCH("DTC Gbps available for external Starlink revenue",Starlink!$A$1:$A$204,0),COLUMN()-COLUMN($D143)+1),0)} -> 577.71 | E143: {=IFERROR(INDEX(Starlink!$D:$AC,MATCH("DTC Gbps available for external Starlink revenue",Starlink!$A$1:$A$204,0),COLUMN()-COLUMN($D143)+1),0)} -> 577.71 | F143: {=IFERROR(INDEX(Starlink!$D:$AC,MATCH("DTC Gbps available for external Starlink revenue",Starlink!$A$1:$A$204,0),COLUMN()-COLUMN($D143)+1),0)} -> 579.3698 | G143: {=IFERROR(INDEX(Starlink!$D:$AC,MATCH("DTC Gbps available for external Starlink revenue",Starlink!$A$1:$A$204,0),COLUMN()-COLUMN($D143)+1),0)} -> 649.95121 | H143: {=IFERROR(INDEX(Starlink!$D:$AC,MATCH("DTC Gbps available for external Starlink revenue",Starlink!$A$1:$A$204,0),COLUMN()-COLUMN($D143)+1),0)} -> 3085.5434 | I143: {=IFERROR(INDEX(Starlink!$D:$AC,MATCH("DTC Gbps available for external Starlink revenue",Starlink!$A$1:$A$204,0),COLUMN()-COLUMN($D143)+1),0)} -> 33938.701 | J143: {=IFERROR(INDEX(Starlink!$D:$AC,MATCH("DTC Gbps available for external Starlink revenue",Starlink!$A$1:$A$204,0),COLUMN()-COLUMN($D143)+1),0)} -> 55683.285 | K143: {=IFERROR(INDEX(Starlink!$D:$AC,MATCH("DTC Gbps available for external Starlink revenue",Starlink!$A$1:$A$204,0),COLUMN()-COLUMN($D143)+1),0)} -> 97088.151 | ... S143: {=IFERROR(INDEX(Starlink!$D:$AC,MATCH("DTC Gbps available for external Starlink revenue",Starlink!$A$1:$A$204,0),COLUMN()-COLUMN($D143)+1),0)} -> 134521.12
A144: Starlink BB Revenue from curve ($mm) | D144: {=((IF(D142>=INDEX($B$82:$B$137,COUNTA($B$82:$B$137)),INDEX($C$82:$C$137,COUNTA($B$82:$B$137))*D141,IF(D142<=INDEX($B$82:$B$137,1),INDEX($C$82:$C$137,1)*D141,(INDEX($C$82:$C$137,MATCH(D142,$B$82:$B$137,1))+(D142-INDEX($B$82:$B$137,MATCH(D142,$B$82:$B$137,1)))*(INDEX($C$82:$C$137,MATCH(D142,$B$82:$B$137,1)+1)-INDEX($C$82:$C$137,MATCH(D142,$B$82:$B$137,1)))/(INDEX($B$82:$B$137,MATCH(D142,$B$82:$B$137,1)+1)-INDEX($B$82:$B$137,MATCH(D142,$B$82:$B$137,1))))*D141)))*INDEX(Assumptions!$B:$B,MATCH("BB demand curve level multiplier",Assumptions!$A$1:$A$257,0)))*D151} -> 6721.2206 | E144: {=((IF(E142>=INDEX($B$82:$B$137,COUNTA($B$82:$B$137)),INDEX($C$82:$C$137,COUNTA($B$82:$B$137))*E141,IF(E142<=INDEX($B$82:$B$137,1),INDEX($C$82:$C$137,1)*E141,(INDEX($C$82:$C$137,MATCH(E142,$B$82:$B$137,1))+(E142-INDEX($B$82:$B$137,MATCH(E142,$B$82:$B$137,1)))*(INDEX($C$82:$C$137,MATCH(E142,$B$82:$B$137,1)+1)-INDEX($C$82:$C$137,MATCH(E142,$B$82:$B$137,1)))/(INDEX($B$82:$B$137,MATCH(E142,$B$82:$B$137,1)+1)-INDEX($B$82:$B$137,MATCH(E142,$B$82:$B$137,1))))*E141)))*INDEX(Assumptions!$B:$B,MATCH("BB demand curve level multiplier",Assumptions!$A$1:$A$257,0)))*E151} -> 9347.5765 | F144: {=((IF(F142>=INDEX($B$82:$B$137,COUNTA($B$82:$B$137)),INDEX($C$82:$C$137,COUNTA($B$82:$B$137))*F141,IF(F142<=INDEX($B$82:$B$137,1),INDEX($C$82:$C$137,1)*F141,(INDEX($C$82:$C$137,MATCH(F142,$B$82:$B$137,1))+(F142-INDEX($B$82:$B$137,MATCH(F142,$B$82:$B$137,1)))*(INDEX($C$82:$C$137,MATCH(F142,$B$82:$B$137,1)+1)-INDEX($C$82:$C$137,MATCH(F142,$B$82:$B$137,1)))/(INDEX($B$82:$B$137,MATCH(F142,$B$82:$B$137,1)+1)-INDEX($B$82:$B$137,MATCH(F142,$B$82:$B$137,1))))*F141)))*INDEX(Assumptions!$B:$B,MATCH("BB demand curve level multiplier",Assumptions!$A$1:$A$257,0)))*F151} -> 37555.656 | G144: {=((IF(G142>=INDEX($B$82:$B$137,COUNTA($B$82:$B$137)),INDEX($C$82:$C$137,COUNTA($B$82:$B$137))*G141,IF(G142<=INDEX($B$82:$B$137,1),INDEX($C$82:$C$137,1)*G141,(INDEX($C$82:$C$137,MATCH(G142,$B$82:$B$137,1))+(G142-INDEX($B$82:$B$137,MATCH(G142,$B$82:$B$137,1)))*(INDEX($C$82:$C$137,MATCH(G142,$B$82:$B$137,1)+1)-INDEX($C$82:$C$137,MATCH(G142,$B$82:$B$137,1)))/(INDEX($B$82:$B$137,MATCH(G142,$B$82:$B$137,1)+1)-INDEX($B$82:$B$137,MATCH(G142,$B$82:$B$137,1))))*G141)))*INDEX(Assumptions!$B:$B,MATCH("BB demand curve level multiplier",Assumptions!$A$1:$A$257,0)))*G151} -> 80517.71 | H144: {=((IF(H142>=INDEX($B$82:$B$137,COUNTA($B$82:$B$137)),INDEX($C$82:$C$137,COUNTA($B$82:$B$137))*H141,IF(H142<=INDEX($B$82:$B$137,1),INDEX($C$82:$C$137,1)*H141,(INDEX($C$82:$C$137,MATCH(H142,$B$82:$B$137,1))+(H142-INDEX($B$82:$B$137,MATCH(H142,$B$82:$B$137,1)))*(INDEX($C$82:$C$137,MATCH(H142,$B$82:$B$137,1)+1)-INDEX($C$82:$C$137,MATCH(H142,$B$82:$B$137,1)))/(INDEX($B$82:$B$137,MATCH(H142,$B$82:$B$137,1)+1)-INDEX($B$82:$B$137,MATCH(H142,$B$82:$B$137,1))))*H141)))*INDEX(Assumptions!$B:$B,MATCH("BB demand curve level multiplier",Assumptions!$A$1:$A$257,0)))*H151} -> 141004.93 | I144: {=((IF(I142>=INDEX($B$82:$B$137,COUNTA($B$82:$B$137)),INDEX($C$82:$C$137,COUNTA($B$82:$B$137))*I141,IF(I142<=INDEX($B$82:$B$137,1),INDEX($C$82:$C$137,1)*I141,(INDEX($C$82:$C$137,MATCH(I142,$B$82:$B$137,1))+(I142-INDEX($B$82:$B$137,MATCH(I142,$B$82:$B$137,1)))*(INDEX($C$82:$C$137,MATCH(I142,$B$82:$B$137,1)+1)-INDEX($C$82:$C$137,MATCH(I142,$B$82:$B$137,1)))/(INDEX($B$82:$B$137,MATCH(I142,$B$82:$B$137,1)+1)-INDEX($B$82:$B$137,MATCH(I142,$B$82:$B$137,1))))*I141)))*INDEX(Assumptions!$B:$B,MATCH("BB demand curve level multiplier",Assumptions!$A$1:$A$257,0)))*I151} -> 172279.32 | J144: {=((IF(J142>=INDEX($B$82:$B$137,COUNTA($B$82:$B$137)),INDEX($C$82:$C$137,COUNTA($B$82:$B$137))*J141,IF(J142<=INDEX($B$82:$B$137,1),INDEX($C$82:$C$137,1)*J141,(INDEX($C$82:$C$137,MATCH(J142,$B$82:$B$137,1))+(J142-INDEX($B$82:$B$137,MATCH(J142,$B$82:$B$137,1)))*(INDEX($C$82:$C$137,MATCH(J142,$B$82:$B$137,1)+1)-INDEX($C$82:$C$137,MATCH(J142,$B$82:$B$137,1)))/(INDEX($B$82:$B$137,MATCH(J142,$B$82:$B$137,1)+1)-INDEX($B$82:$B$137,MATCH(J142,$B$82:$B$137,1))))*J141)))*INDEX(Assumptions!$B:$B,MATCH("BB demand curve level multiplier",Assumptions!$A$1:$A$257,0)))*J151} -> 205461.3 | K144: {=((IF(K142>=INDEX($B$82:$B$137,COUNTA($B$82:$B$137)),INDEX($C$82:$C$137,COUNTA($B$82:$B$137))*K141,IF(K142<=INDEX($B$82:$B$137,1),INDEX($C$82:$C$137,1)*K141,(INDEX($C$82:$C$137,MATCH(K142,$B$82:$B$137,1))+(K142-INDEX($B$82:$B$137,MATCH(K142,$B$82:$B$137,1)))*(INDEX($C$82:$C$137,MATCH(K142,$B$82:$B$137,1)+1)-INDEX($C$82:$C$137,MATCH(K142,$B$82:$B$137,1)))/(INDEX($B$82:$B$137,MATCH(K142,$B$82:$B$137,1)+1)-INDEX($B$82:$B$137,MATCH(K142,$B$82:$B$137,1))))*K141)))*INDEX(Assumptions!$B:$B,MATCH("BB demand curve level multiplier",Assumptions!$A$1:$A$257,0)))*K151} -> 221249.49 | ... S144: {=((IF(S142>=INDEX($B$82:$B$137,COUNTA($B$82:$B$137)),INDEX($C$82:$C$137,COUNTA($B$82:$B$137))*S141,IF(S142<=INDEX($B$82:$B$137,1),INDEX($C$82:$C$137,1)*S141,(INDEX($C$82:$C$137,MATCH(S142,$B$82:$B$137,1))+(S142-INDEX($B$82:$B$137,MATCH(S142,$B$82:$B$137,1)))*(INDEX($C$82:$C$137,MATCH(S142,$B$82:$B$137,1)+1)-INDEX($C$82:$C$137,MATCH(S142,$B$82:$B$137,1)))/(INDEX($B$82:$B$137,MATCH(S142,$B$82:$B$137,1)+1)-INDEX($B$82:$B$137,MATCH(S142,$B$82:$B$137,1))))*S141)))*INDEX(Assumptions!$B:$B,MATCH("BB demand curve level multiplier",Assumptions!$A$1:$A$257,0)))*S151} -> 304575.99
A145: Starlink DTC Revenue from curve ($mm) | D145: {=((IF(D143<=0,0,IF(D143>=INDEX($B$17:$B$77,COUNTA($B$17:$B$77)),INDEX($C$17:$C$77,COUNTA($B$17:$B$77))*D141,IF(D143<INDEX($B$17:$B$77,1),D143/INDEX($B$17:$B$77,1)*INDEX($C$17:$C$77,1)*D141,(INDEX($C$17:$C$77,MATCH(D143,$B$17:$B$77,1))+(D143-INDEX($B$17:$B$77,MATCH(D143,$B$17:$B$77,1)))*(INDEX($C$17:$C$77,MATCH(D143,$B$17:$B$77,1)+1)-INDEX($C$17:$C$77,MATCH(D143,$B$17:$B$77,1)))/(INDEX($B$17:$B$77,MATCH(D143,$B$17:$B$77,1)+1)-INDEX($B$17:$B$77,MATCH(D143,$B$17:$B$77,1))))*D141))))*INDEX(Assumptions!$B:$B,MATCH("DTC demand curve level multiplier",Assumptions!$A$1:$A$257,0)))*D150} -> 632.0752 | E145: {=((IF(E143<=0,0,IF(E143>=INDEX($B$17:$B$77,COUNTA($B$17:$B$77)),INDEX($C$17:$C$77,COUNTA($B$17:$B$77))*E141,IF(E143<INDEX($B$17:$B$77,1),E143/INDEX($B$17:$B$77,1)*INDEX($C$17:$C$77,1)*E141,(INDEX($C$17:$C$77,MATCH(E143,$B$17:$B$77,1))+(E143-INDEX($B$17:$B$77,MATCH(E143,$B$17:$B$77,1)))*(INDEX($C$17:$C$77,MATCH(E143,$B$17:$B$77,1)+1)-INDEX($C$17:$C$77,MATCH(E143,$B$17:$B$77,1)))/(INDEX($B$17:$B$77,MATCH(E143,$B$17:$B$77,1)+1)-INDEX($B$17:$B$77,MATCH(E143,$B$17:$B$77,1))))*E141))))*INDEX(Assumptions!$B:$B,MATCH("DTC demand curve level multiplier",Assumptions!$A$1:$A$257,0)))*E150} -> 794.38308 | F145: {=((IF(F143<=0,0,IF(F143>=INDEX($B$17:$B$77,COUNTA($B$17:$B$77)),INDEX($C$17:$C$77,COUNTA($B$17:$B$77))*F141,IF(F143<INDEX($B$17:$B$77,1),F143/INDEX($B$17:$B$77,1)*INDEX($C$17:$C$77,1)*F141,(INDEX($C$17:$C$77,MATCH(F143,$B$17:$B$77,1))+(F143-INDEX($B$17:$B$77,MATCH(F143,$B$17:$B$77,1)))*(INDEX($C$17:$C$77,MATCH(F143,$B$17:$B$77,1)+1)-INDEX($C$17:$C$77,MATCH(F143,$B$17:$B$77,1)))/(INDEX($B$17:$B$77,MATCH(F143,$B$17:$B$77,1)+1)-INDEX($B$17:$B$77,MATCH(F143,$B$17:$B$77,1))))*F141))))*INDEX(Assumptions!$B:$B,MATCH("DTC demand curve level multiplier",Assumptions!$A$1:$A$257,0)))*F150} -> 969.01979 | G145: {=((IF(G143<=0,0,IF(G143>=INDEX($B$17:$B$77,COUNTA($B$17:$B$77)),INDEX($C$17:$C$77,COUNTA($B$17:$B$77))*G141,IF(G143<INDEX($B$17:$B$77,1),G143/INDEX($B$17:$B$77,1)*INDEX($C$17:$C$77,1)*G141,(INDEX($C$17:$C$77,MATCH(G143,$B$17:$B$77,1))+(G143-INDEX($B$17:$B$77,MATCH(G143,$B$17:$B$77,1)))*(INDEX($C$17:$C$77,MATCH(G143,$B$17:$B$77,1)+1)-INDEX($C$17:$C$77,MATCH(G143,$B$17:$B$77,1)))/(INDEX($B$17:$B$77,MATCH(G143,$B$17:$B$77,1)+1)-INDEX($B$17:$B$77,MATCH(G143,$B$17:$B$77,1))))*G141))))*INDEX(Assumptions!$B:$B,MATCH("DTC demand curve level multiplier",Assumptions!$A$1:$A$257,0)))*G150} -> 1291.3041 | H145: {=((IF(H143<=0,0,IF(H143>=INDEX($B$17:$B$77,COUNTA($B$17:$B$77)),INDEX($C$17:$C$77,COUNTA($B$17:$B$77))*H141,IF(H143<INDEX($B$17:$B$77,1),H143/INDEX($B$17:$B$77,1)*INDEX($C$17:$C$77,1)*H141,(INDEX($C$17:$C$77,MATCH(H143,$B$17:$B$77,1))+(H143-INDEX($B$17:$B$77,MATCH(H143,$B$17:$B$77,1)))*(INDEX($C$17:$C$77,MATCH(H143,$B$17:$B$77,1)+1)-INDEX($C$17:$C$77,MATCH(H143,$B$17:$B$77,1)))/(INDEX($B$17:$B$77,MATCH(H143,$B$17:$B$77,1)+1)-INDEX($B$17:$B$77,MATCH(H143,$B$17:$B$77,1))))*H141))))*INDEX(Assumptions!$B:$B,MATCH("DTC demand curve level multiplier",Assumptions!$A$1:$A$257,0)))*H150} -> 7146.7257 | I145: {=((IF(I143<=0,0,IF(I143>=INDEX($B$17:$B$77,COUNTA($B$17:$B$77)),INDEX($C$17:$C$77,COUNTA($B$17:$B$77))*I141,IF(I143<INDEX($B$17:$B$77,1),I143/INDEX($B$17:$B$77,1)*INDEX($C$17:$C$77,1)*I141,(INDEX($C$17:$C$77,MATCH(I143,$B$17:$B$77,1))+(I143-INDEX($B$17:$B$77,MATCH(I143,$B$17:$B$77,1)))*(INDEX($C$17:$C$77,MATCH(I143,$B$17:$B$77,1)+1)-INDEX($C$17:$C$77,MATCH(I143,$B$17:$B$77,1)))/(INDEX($B$17:$B$77,MATCH(I143,$B$17:$B$77,1)+1)-INDEX($B$17:$B$77,MATCH(I143,$B$17:$B$77,1))))*I141))))*INDEX(Assumptions!$B:$B,MATCH("DTC demand curve level multiplier",Assumptions!$A$1:$A$257,0)))*I150} -> 33355.216 | J145: {=((IF(J143<=0,0,IF(J143>=INDEX($B$17:$B$77,COUNTA($B$17:$B$77)),INDEX($C$17:$C$77,COUNTA($B$17:$B$77))*J141,IF(J143<INDEX($B$17:$B$77,1),J143/INDEX($B$17:$B$77,1)*INDEX($C$17:$C$77,1)*J141,(INDEX($C$17:$C$77,MATCH(J143,$B$17:$B$77,1))+(J143-INDEX($B$17:$B$77,MATCH(J143,$B$17:$B$77,1)))*(INDEX($C$17:$C$77,MATCH(J143,$B$17:$B$77,1)+1)-INDEX($C$17:$C$77,MATCH(J143,$B$17:$B$77,1)))/(INDEX($B$17:$B$77,MATCH(J143,$B$17:$B$77,1)+1)-INDEX($B$17:$B$77,MATCH(J143,$B$17:$B$77,1))))*J141))))*INDEX(Assumptions!$B:$B,MATCH("DTC demand curve level multiplier",Assumptions!$A$1:$A$257,0)))*J150} -> 41028.563 | K145: {=((IF(K143<=0,0,IF(K143>=INDEX($B$17:$B$77,COUNTA($B$17:$B$77)),INDEX($C$17:$C$77,COUNTA($B$17:$B$77))*K141,IF(K143<INDEX($B$17:$B$77,1),K143/INDEX($B$17:$B$77,1)*INDEX($C$17:$C$77,1)*K141,(INDEX($C$17:$C$77,MATCH(K143,$B$17:$B$77,1))+(K143-INDEX($B$17:$B$77,MATCH(K143,$B$17:$B$77,1)))*(INDEX($C$17:$C$77,MATCH(K143,$B$17:$B$77,1)+1)-INDEX($C$17:$C$77,MATCH(K143,$B$17:$B$77,1)))/(INDEX($B$17:$B$77,MATCH(K143,$B$17:$B$77,1)+1)-INDEX($B$17:$B$77,MATCH(K143,$B$17:$B$77,1))))*K141))))*INDEX(Assumptions!$B:$B,MATCH("DTC demand curve level multiplier",Assumptions!$A$1:$A$257,0)))*K150} -> 49505.313 | ... S145: {=((IF(S143<=0,0,IF(S143>=INDEX($B$17:$B$77,COUNTA($B$17:$B$77)),INDEX($C$17:$C$77,COUNTA($B$17:$B$77))*S141,IF(S143<INDEX($B$17:$B$77,1),S143/INDEX($B$17:$B$77,1)*INDEX($C$17:$C$77,1)*S141,(INDEX($C$17:$C$77,MATCH(S143,$B$17:$B$77,1))+(S143-INDEX($B$17:$B$77,MATCH(S143,$B$17:$B$77,1)))*(INDEX($C$17:$C$77,MATCH(S143,$B$17:$B$77,1)+1)-INDEX($C$17:$C$77,MATCH(S143,$B$17:$B$77,1)))/(INDEX($B$17:$B$77,MATCH(S143,$B$17:$B$77,1)+1)-INDEX($B$17:$B$77,MATCH(S143,$B$17:$B$77,1))))*S141))))*INDEX(Assumptions!$B:$B,MATCH("DTC demand curve level multiplier",Assumptions!$A$1:$A$257,0)))*S150} -> 60513.713
A146: Memo: Average $/Gbps BB from curve | D146: =IFERROR(D144*1000000/D142,0) -> 13740.781 | E146: =IFERROR(E144*1000000/E142,0) -> 12352.493 | F146: =IFERROR(F144*1000000/F142,0) -> 8072.9202 | G146: =IFERROR(G144*1000000/G142,0) -> 5788.5494 | H146: =IFERROR(H144*1000000/H142,0) -> 3739.5549 | I146: =IFERROR(I144*1000000/I142,0) -> 3275.3092 | J146: =IFERROR(J144*1000000/J142,0) -> 2528.8542 | K146: =IFERROR(K144*1000000/K142,0) -> 2360.4981 | ... S146: =IFERROR(S144*1000000/S142,0) -> 1612.6879
A147: Memo: Average $/Gbps DTC from curve | D147: =IFERROR(D145*1000000/D143,0) -> 1094104.6 | E147: =IFERROR(E145*1000000/E143,0) -> 1375055.1 | F147: =IFERROR(F145*1000000/F143,0) -> 1672541.1 | G147: =IFERROR(G145*1000000/G143,0) -> 1986770.8 | H147: =IFERROR(H145*1000000/H143,0) -> 2316196.8 | I147: =IFERROR(I145*1000000/I143,0) -> 982807.67 | J147: =IFERROR(J145*1000000/J143,0) -> 736820.1 | K147: =IFERROR(K145*1000000/K143,0) -> 509900.66 | ... S147: =IFERROR(S145*1000000/S143,0) -> 449845.43
A149: Annual escalator rate (derived, year-row) | D149: 0 | E149: =Assumptions!$B$4+(Assumptions!$B$5-Assumptions!$B$4)*MIN(E$5-1,Assumptions!$B$343-1)/(Assumptions!$B$343-1) -> 0.035 | F149: =Assumptions!$B$4+(Assumptions!$B$5-Assumptions!$B$4)*MIN(F$5-1,Assumptions!$B$343-1)/(Assumptions!$B$343-1) -> 0.033888889 | G149: =Assumptions!$B$4+(Assumptions!$B$5-Assumptions!$B$4)*MIN(G$5-1,Assumptions!$B$343-1)/(Assumptions!$B$343-1) -> 0.032777778 | H149: =Assumptions!$B$4+(Assumptions!$B$5-Assumptions!$B$4)*MIN(H$5-1,Assumptions!$B$343-1)/(Assumptions!$B$343-1) -> 0.031666667 | I149: =Assumptions!$B$4+(Assumptions!$B$5-Assumptions!$B$4)*MIN(I$5-1,Assumptions!$B$343-1)/(Assumptions!$B$343-1) -> 0.030555556 | J149: =Assumptions!$B$4+(Assumptions!$B$5-Assumptions!$B$4)*MIN(J$5-1,Assumptions!$B$343-1)/(Assumptions!$B$343-1) -> 0.029444444 | K149: =Assumptions!$B$4+(Assumptions!$B$5-Assumptions!$B$4)*MIN(K$5-1,Assumptions!$B$343-1)/(Assumptions!$B$343-1) -> 0.028333333 | L149: =Assumptions!$B$4+(Assumptions!$B$5-Assumptions!$B$4)*MIN(L$5-1,Assumptions!$B$343-1)/(Assumptions!$B$343-1) -> 0.027222222 | ... S149: =Assumptions!$B$4+(Assumptions!$B$5-Assumptions!$B$4)*MIN(S$5-1,Assumptions!$B$343-1)/(Assumptions!$B$343-1) -> 0.025
A150: DTC TAM uplift multiplier (Starlink Mobile, derived year-row) | D150: 1 | E150: =1+(Assumptions!$B$347-1)*MIN(E$5,Assumptions!$B$348)/Assumptions!$B$348 -> 1.2142857 | F150: =1+(Assumptions!$B$347-1)*MIN(F$5,Assumptions!$B$348)/Assumptions!$B$348 -> 1.4285714 | G150: =1+(Assumptions!$B$347-1)*MIN(G$5,Assumptions!$B$348)/Assumptions!$B$348 -> 1.6428571 | H150: =1+(Assumptions!$B$347-1)*MIN(H$5,Assumptions!$B$348)/Assumptions!$B$348 -> 1.8571429 | I150: =1+(Assumptions!$B$347-1)*MIN(I$5,Assumptions!$B$348)/Assumptions!$B$348 -> 2.0714286 | J150: =1+(Assumptions!$B$347-1)*MIN(J$5,Assumptions!$B$348)/Assumptions!$B$348 -> 2.2857143 | K150: =1+(Assumptions!$B$347-1)*MIN(K$5,Assumptions!$B$348)/Assumptions!$B$348 -> 2.5 | L150: =1+(Assumptions!$B$347-1)*MIN(L$5,Assumptions!$B$348)/Assumptions!$B$348 -> 2.5 | ... S150: =1+(Assumptions!$B$347-1)*MIN(S$5,Assumptions!$B$348)/Assumptions!$B$348 -> 2.5
A151: BB TAM uplift multiplier (data-intensity, derived year-row) | D151: 1 | E151: =1+(Assumptions!$B$363-1)*MIN(E$5,Assumptions!$B$364)/Assumptions!$B$364 -> 1 | F151: =1+(Assumptions!$B$363-1)*MIN(F$5,Assumptions!$B$364)/Assumptions!$B$364 -> 1 | G151: =1+(Assumptions!$B$363-1)*MIN(G$5,Assumptions!$B$364)/Assumptions!$B$364 -> 1 | H151: =1+(Assumptions!$B$363-1)*MIN(H$5,Assumptions!$B$364)/Assumptions!$B$364 -> 1 | I151: =1+(Assumptions!$B$363-1)*MIN(I$5,Assumptions!$B$364)/Assumptions!$B$364 -> 1 | J151: =1+(Assumptions!$B$363-1)*MIN(J$5,Assumptions!$B$364)/Assumptions!$B$364 -> 1 | K151: =1+(Assumptions!$B$363-1)*MIN(K$5,Assumptions!$B$364)/Assumptions!$B$364 -> 1 | L151: =1+(Assumptions!$B$363-1)*MIN(L$5,Assumptions!$B$364)/Assumptions!$B$364 -> 1 | ... S151: =1+(Assumptions!$B$363-1)*MIN(S$5,Assumptions!$B$364)/Assumptions!$B$364 -> 1

Sheet Starlink
A1: Starlink module — real cohorts + total-bandwidth revenue + full waterfall + 4-line OpEx + per-sat IRR
D4: 2025 | E4: 2026 | F4: 2027 | G4: 2028 | H4: 2029 | I4: 2030 | J4: 2031 | K4: 2032 | L4: 2033 | M4: 2034 | N4: 2035 | O4: 2036 | P4: 2037 | Q4: 2038 | R4: 2039 | S4: 2040
D5: 0 | E5: 1 | F5: 2 | G5: 3 | H5: 4 | I5: 5 | J5: 6 | K5: 7 | L5: 8 | M5: 9 | N5: 10 | O5: 11 | P5: 12 | Q5: 13 | R5: 14 | S5: 15
A10: ▸ ALLOCATOR IN (cross-tab reads)
A11: Starlink BB Revenue from curve ($mm) | D11: {=INDEX('Demand Curves'!$D:$AC, MATCH("Starlink BB Revenue from curve ($mm)", 'Demand Curves'!$A$1:$A$167, 0), COLUMN()-COLUMN($D11)+1)} -> 6721.2206 | E11: {=INDEX('Demand Curves'!$D:$AC, MATCH("Starlink BB Revenue from curve ($mm)", 'Demand Curves'!$A$1:$A$167, 0), COLUMN()-COLUMN($D11)+1)} -> 9347.5765 | F11: {=INDEX('Demand Curves'!$D:$AC, MATCH("Starlink BB Revenue from curve ($mm)", 'Demand Curves'!$A$1:$A$167, 0), COLUMN()-COLUMN($D11)+1)} -> 37555.656 | G11: {=INDEX('Demand Curves'!$D:$AC, MATCH("Starlink BB Revenue from curve ($mm)", 'Demand Curves'!$A$1:$A$167, 0), COLUMN()-COLUMN($D11)+1)} -> 80517.71 | H11: {=INDEX('Demand Curves'!$D:$AC, MATCH("Starlink BB Revenue from curve ($mm)", 'Demand Curves'!$A$1:$A$167, 0), COLUMN()-COLUMN($D11)+1)} -> 141004.93 | I11: {=INDEX('Demand Curves'!$D:$AC, MATCH("Starlink BB Revenue from curve ($mm)", 'Demand Curves'!$A$1:$A$167, 0), COLUMN()-COLUMN($D11)+1)} -> 172279.32 | J11: {=INDEX('Demand Curves'!$D:$AC, MATCH("Starlink BB Revenue from curve ($mm)", 'Demand Curves'!$A$1:$A$167, 0), COLUMN()-COLUMN($D11)+1)} -> 205461.3 | K11: {=INDEX('Demand Curves'!$D:$AC, MATCH("Starlink BB Revenue from curve ($mm)", 'Demand Curves'!$A$1:$A$167, 0), COLUMN()-COLUMN($D11)+1)} -> 221249.49 | ... S11: {=INDEX('Demand Curves'!$D:$AC, MATCH("Starlink BB Revenue from curve ($mm)", 'Demand Curves'!$A$1:$A$167, 0), COLUMN()-COLUMN($D11)+1)} -> 304575.99
A12: Starlink DTC Revenue from curve ($mm) | D12: {=INDEX('Demand Curves'!$D:$AC, MATCH("Starlink DTC Revenue from curve ($mm)", 'Demand Curves'!$A$1:$A$167, 0), COLUMN()-COLUMN($D12)+1)} -> 632.0752 | E12: {=INDEX('Demand Curves'!$D:$AC, MATCH("Starlink DTC Revenue from curve ($mm)", 'Demand Curves'!$A$1:$A$167, 0), COLUMN()-COLUMN($D12)+1)} -> 794.38308 | F12: {=INDEX('Demand Curves'!$D:$AC, MATCH("Starlink DTC Revenue from curve ($mm)", 'Demand Curves'!$A$1:$A$167, 0), COLUMN()-COLUMN($D12)+1)} -> 969.01979 | G12: {=INDEX('Demand Curves'!$D:$AC, MATCH("Starlink DTC Revenue from curve ($mm)", 'Demand Curves'!$A$1:$A$167, 0), COLUMN()-COLUMN($D12)+1)} -> 1291.3041 | H12: {=INDEX('Demand Curves'!$D:$AC, MATCH("Starlink DTC Revenue from curve ($mm)", 'Demand Curves'!$A$1:$A$167, 0), COLUMN()-COLUMN($D12)+1)} -> 7146.7257 | I12: {=INDEX('Demand Curves'!$D:$AC, MATCH("Starlink DTC Revenue from curve ($mm)", 'Demand Curves'!$A$1:$A$167, 0), COLUMN()-COLUMN($D12)+1)} -> 33355.216 | J12: {=INDEX('Demand Curves'!$D:$AC, MATCH("Starlink DTC Revenue from curve ($mm)", 'Demand Curves'!$A$1:$A$167, 0), COLUMN()-COLUMN($D12)+1)} -> 41028.563 | K12: {=INDEX('Demand Curves'!$D:$AC, MATCH("Starlink DTC Revenue from curve ($mm)", 'Demand Curves'!$A$1:$A$167, 0), COLUMN()-COLUMN($D12)+1)} -> 49505.313 | ... S12: {=INDEX('Demand Curves'!$D:$AC, MATCH("Starlink DTC Revenue from curve ($mm)", 'Demand Curves'!$A$1:$A$167, 0), COLUMN()-COLUMN($D12)+1)} -> 60513.713
A13: F9 at-cost rate per launch ($mm) | D13: {=INDEX(Assumptions!$D:$S, MATCH("F9 at-cost rate per launch ($mm)", Assumptions!$A$1:$A$257, 0), COLUMN()-COLUMN($D13)+1)} -> 20 | E13: {=INDEX(Assumptions!$D:$S, MATCH("F9 at-cost rate per launch ($mm)", Assumptions!$A$1:$A$257, 0), COLUMN()-COLUMN($D13)+1)} -> 19.6 | F13: {=INDEX(Assumptions!$D:$S, MATCH("F9 at-cost rate per launch ($mm)", Assumptions!$A$1:$A$257, 0), COLUMN()-COLUMN($D13)+1)} -> 19.208 | G13: {=INDEX(Assumptions!$D:$S, MATCH("F9 at-cost rate per launch ($mm)", Assumptions!$A$1:$A$257, 0), COLUMN()-COLUMN($D13)+1)} -> 18.824 | H13: {=INDEX(Assumptions!$D:$S, MATCH("F9 at-cost rate per launch ($mm)", Assumptions!$A$1:$A$257, 0), COLUMN()-COLUMN($D13)+1)} -> 18.447 | I13: {=INDEX(Assumptions!$D:$S, MATCH("F9 at-cost rate per launch ($mm)", Assumptions!$A$1:$A$257, 0), COLUMN()-COLUMN($D13)+1)} -> 18.078 | J13: {=INDEX(Assumptions!$D:$S, MATCH("F9 at-cost rate per launch ($mm)", Assumptions!$A$1:$A$257, 0), COLUMN()-COLUMN($D13)+1)} -> 17.717 | K13: {=INDEX(Assumptions!$D:$S, MATCH("F9 at-cost rate per launch ($mm)", Assumptions!$A$1:$A$257, 0), COLUMN()-COLUMN($D13)+1)} -> 17.363 | ... S13: {=INDEX(Assumptions!$D:$S, MATCH("F9 at-cost rate per launch ($mm)", Assumptions!$A$1:$A$257, 0), COLUMN()-COLUMN($D13)+1)} -> 14.772
A14: Starship at-cost rate per launch ($mm) | D14: {=INDEX(Assumptions!$D:$S, MATCH("Starship at-cost rate per launch ($mm)", Assumptions!$A$1:$A$257, 0), COLUMN()-COLUMN($D14)+1)} -> 0 | E14: {=INDEX(Assumptions!$D:$S, MATCH("Starship at-cost rate per launch ($mm)", Assumptions!$A$1:$A$257, 0), COLUMN()-COLUMN($D14)+1)} -> 0 | F14: {=INDEX(Assumptions!$D:$S, MATCH("Starship at-cost rate per launch ($mm)", Assumptions!$A$1:$A$257, 0), COLUMN()-COLUMN($D14)+1)} -> 25 | G14: {=INDEX(Assumptions!$D:$S, MATCH("Starship at-cost rate per launch ($mm)", Assumptions!$A$1:$A$257, 0), COLUMN()-COLUMN($D14)+1)} -> 23 | H14: {=INDEX(Assumptions!$D:$S, MATCH("Starship at-cost rate per launch ($mm)", Assumptions!$A$1:$A$257, 0), COLUMN()-COLUMN($D14)+1)} -> 21.16 | I14: {=INDEX(Assumptions!$D:$S, MATCH("Starship at-cost rate per launch ($mm)", Assumptions!$A$1:$A$257, 0), COLUMN()-COLUMN($D14)+1)} -> 19.4672 | J14: {=INDEX(Assumptions!$D:$S, MATCH("Starship at-cost rate per launch ($mm)", Assumptions!$A$1:$A$257, 0), COLUMN()-COLUMN($D14)+1)} -> 17.909824 | K14: {=INDEX(Assumptions!$D:$S, MATCH("Starship at-cost rate per launch ($mm)", Assumptions!$A$1:$A$257, 0), COLUMN()-COLUMN($D14)+1)} -> 16.477038 | ... S14: {=INDEX(Assumptions!$D:$S, MATCH("Starship at-cost rate per launch ($mm)", Assumptions!$A$1:$A$257, 0), COLUMN()-COLUMN($D14)+1)} -> 8.4563269
A15: Sat operational life L (years) | D15: =INDEX(Assumptions!$B:$B, MATCH("Sat operational life L (years)", Assumptions!$A$1:$A$257, 0)) -> 5 | E15: =INDEX(Assumptions!$B:$B, MATCH("Sat operational life L (years)", Assumptions!$A$1:$A$257, 0)) -> 5 | F15: =INDEX(Assumptions!$B:$B, MATCH("Sat operational life L (years)", Assumptions!$A$1:$A$257, 0)) -> 5 | G15: =INDEX(Assumptions!$B:$B, MATCH("Sat operational life L (years)", Assumptions!$A$1:$A$257, 0)) -> 5 | H15: =INDEX(Assumptions!$B:$B, MATCH("Sat operational life L (years)", Assumptions!$A$1:$A$257, 0)) -> 5 | I15: =INDEX(Assumptions!$B:$B, MATCH("Sat operational life L (years)", Assumptions!$A$1:$A$257, 0)) -> 5 | J15: =INDEX(Assumptions!$B:$B, MATCH("Sat operational life L (years)", Assumptions!$A$1:$A$257, 0)) -> 5 | K15: =INDEX(Assumptions!$B:$B, MATCH("Sat operational life L (years)", Assumptions!$A$1:$A$257, 0)) -> 5 | ... S15: =INDEX(Assumptions!$B:$B, MATCH("Sat operational life L (years)", Assumptions!$A$1:$A$257, 0)) -> 5
A16: Group WACC | D16: =INDEX(Assumptions!$B:$B, MATCH("Group WACC", Assumptions!$A$1:$A$257, 0)) -> 0.1 | E16: =INDEX(Assumptions!$B:$B, MATCH("Group WACC", Assumptions!$A$1:$A$257, 0)) -> 0.1 | F16: =INDEX(Assumptions!$B:$B, MATCH("Group WACC", Assumptions!$A$1:$A$257, 0)) -> 0.1 | G16: =INDEX(Assumptions!$B:$B, MATCH("Group WACC", Assumptions!$A$1:$A$257, 0)) -> 0.1 | H16: =INDEX(Assumptions!$B:$B, MATCH("Group WACC", Assumptions!$A$1:$A$257, 0)) -> 0.1 | I16: =INDEX(Assumptions!$B:$B, MATCH("Group WACC", Assumptions!$A$1:$A$257, 0)) -> 0.1 | J16: =INDEX(Assumptions!$B:$B, MATCH("Group WACC", Assumptions!$A$1:$A$257, 0)) -> 0.1 | K16: =INDEX(Assumptions!$B:$B, MATCH("Group WACC", Assumptions!$A$1:$A$257, 0)) -> 0.1 | ... S16: =INDEX(Assumptions!$B:$B, MATCH("Group WACC", Assumptions!$A$1:$A$257, 0)) -> 0.1
A18: Starlink R&D as % of revenue (frac) | D18: =INDEX(Assumptions!$B:$B, MATCH("Starlink R&D: start % of (Starlink+Starshield) rev", Assumptions!$A$1:$A$257, 0)) -> 0.053 | E18: =INDEX(Assumptions!$B:$B, MATCH("Starlink R&D: start % of (Starlink+Starshield) rev", Assumptions!$A$1:$A$257, 0)) -> 0.053 | F18: =INDEX(Assumptions!$B:$B, MATCH("Starlink R&D: start % of (Starlink+Starshield) rev", Assumptions!$A$1:$A$257, 0)) -> 0.053 | G18: =INDEX(Assumptions!$B:$B, MATCH("Starlink R&D: start % of (Starlink+Starshield) rev", Assumptions!$A$1:$A$257, 0)) -> 0.053 | H18: =INDEX(Assumptions!$B:$B, MATCH("Starlink R&D: start % of (Starlink+Starshield) rev", Assumptions!$A$1:$A$257, 0)) -> 0.053 | I18: =INDEX(Assumptions!$B:$B, MATCH("Starlink R&D: start % of (Starlink+Starshield) rev", Assumptions!$A$1:$A$257, 0)) -> 0.053 | J18: =INDEX(Assumptions!$B:$B, MATCH("Starlink R&D: start % of (Starlink+Starshield) rev", Assumptions!$A$1:$A$257, 0)) -> 0.053 | K18: =INDEX(Assumptions!$B:$B, MATCH("Starlink R&D: start % of (Starlink+Starshield) rev", Assumptions!$A$1:$A$257, 0)) -> 0.053 | ... S18: =INDEX(Assumptions!$B:$B, MATCH("Starlink R&D: start % of (Starlink+Starshield) rev", Assumptions!$A$1:$A$257, 0)) -> 0.053
A19: Starlink module allocated cash ($mm/yr): live from Cash Allocation Engine | D19: ='Cash Allocation Engine'!D39 -> 0 | E19: ='Cash Allocation Engine'!E39 -> 13695.09 | F19: ='Cash Allocation Engine'!F39 -> 56677.18 | G19: ='Cash Allocation Engine'!G39 -> 57774.103 | H19: ='Cash Allocation Engine'!H39 -> 67795.202 | I19: ='Cash Allocation Engine'!I39 -> 68617.687 | J19: ='Cash Allocation Engine'!J39 -> 68448.419 | K19: ='Cash Allocation Engine'!K39 -> 76570.128 | ... S19: ='Cash Allocation Engine'!S39 -> 35740.836
A20: Starlink deployment 2025 anchor (sats) | D20: =INDEX(Assumptions!$B:$B, MATCH("Starlink deployment 2025 anchor (sats)", Assumptions!$A$1:$A$257, 0)) -> 3840
A21: Sat utilization (frac) | D21: =INDEX(Assumptions!$B:$B, MATCH("Sat utilization (frac)", Assumptions!$A$1:$A$257, 0)) -> 0.7 | E21: =INDEX(Assumptions!$B:$B, MATCH("Sat utilization (frac)", Assumptions!$A$1:$A$257, 0)) -> 0.7 | F21: =INDEX(Assumptions!$B:$B, MATCH("Sat utilization (frac)", Assumptions!$A$1:$A$257, 0)) -> 0.7 | G21: =INDEX(Assumptions!$B:$B, MATCH("Sat utilization (frac)", Assumptions!$A$1:$A$257, 0)) -> 0.7 | H21: =INDEX(Assumptions!$B:$B, MATCH("Sat utilization (frac)", Assumptions!$A$1:$A$257, 0)) -> 0.7 | I21: =INDEX(Assumptions!$B:$B, MATCH("Sat utilization (frac)", Assumptions!$A$1:$A$257, 0)) -> 0.7 | J21: =INDEX(Assumptions!$B:$B, MATCH("Sat utilization (frac)", Assumptions!$A$1:$A$257, 0)) -> 0.7 | K21: =INDEX(Assumptions!$B:$B, MATCH("Sat utilization (frac)", Assumptions!$A$1:$A$257, 0)) -> 0.7 | ... S21: =INDEX(Assumptions!$B:$B, MATCH("Sat utilization (frac)", Assumptions!$A$1:$A$257, 0)) -> 0.7
A22: Starship operational year | D22: =INDEX(Assumptions!$B:$B, MATCH("Starship operational year", Assumptions!$A$1:$A$257, 0)) -> 2026
A23: F9 launches V2-Starlink final year | D23: =INDEX(Assumptions!$B:$B, MATCH("F9 launches V2-Starlink final year", Assumptions!$A$1:$A$257, 0)) -> 2026
A24: F9 payload per launch (kg) | D24: {=INDEX('Vehicle Build'!$D:$AC, MATCH("F9 payload per launch (kg)", 'Vehicle Build'!$A$1:$A$119, 0), COLUMN()-COLUMN($D24)+1)} -> 22800 | E24: {=INDEX('Vehicle Build'!$D:$AC, MATCH("F9 payload per launch (kg)", 'Vehicle Build'!$A$1:$A$119, 0), COLUMN()-COLUMN($D24)+1)} -> 22800 | F24: {=INDEX('Vehicle Build'!$D:$AC, MATCH("F9 payload per launch (kg)", 'Vehicle Build'!$A$1:$A$119, 0), COLUMN()-COLUMN($D24)+1)} -> 22800 | G24: {=INDEX('Vehicle Build'!$D:$AC, MATCH("F9 payload per launch (kg)", 'Vehicle Build'!$A$1:$A$119, 0), COLUMN()-COLUMN($D24)+1)} -> 22800 | H24: {=INDEX('Vehicle Build'!$D:$AC, MATCH("F9 payload per launch (kg)", 'Vehicle Build'!$A$1:$A$119, 0), COLUMN()-COLUMN($D24)+1)} -> 22800 | I24: {=INDEX('Vehicle Build'!$D:$AC, MATCH("F9 payload per launch (kg)", 'Vehicle Build'!$A$1:$A$119, 0), COLUMN()-COLUMN($D24)+1)} -> 22800 | J24: {=INDEX('Vehicle Build'!$D:$AC, MATCH("F9 payload per launch (kg)", 'Vehicle Build'!$A$1:$A$119, 0), COLUMN()-COLUMN($D24)+1)} -> 22800 | K24: {=INDEX('Vehicle Build'!$D:$AC, MATCH("F9 payload per launch (kg)", 'Vehicle Build'!$A$1:$A$119, 0), COLUMN()-COLUMN($D24)+1)} -> 22800 | ... S24: {=INDEX('Vehicle Build'!$D:$AC, MATCH("F9 payload per launch (kg)", 'Vehicle Build'!$A$1:$A$119, 0), COLUMN()-COLUMN($D24)+1)} -> 22800
A25: Starship payload per launch (kg) | D25: {=INDEX('Vehicle Build'!$D:$AC, MATCH("Starship payload per launch (kg)", 'Vehicle Build'!$A$1:$A$119, 0), COLUMN()-COLUMN($D25)+1)} -> 100000 | E25: {=INDEX('Vehicle Build'!$D:$AC, MATCH("Starship payload per launch (kg)", 'Vehicle Build'!$A$1:$A$119, 0), COLUMN()-COLUMN($D25)+1)} -> 114869.84 | F25: {=INDEX('Vehicle Build'!$D:$AC, MATCH("Starship payload per launch (kg)", 'Vehicle Build'!$A$1:$A$119, 0), COLUMN()-COLUMN($D25)+1)} -> 131950.79 | G25: {=INDEX('Vehicle Build'!$D:$AC, MATCH("Starship payload per launch (kg)", 'Vehicle Build'!$A$1:$A$119, 0), COLUMN()-COLUMN($D25)+1)} -> 151571.66 | H25: {=INDEX('Vehicle Build'!$D:$AC, MATCH("Starship payload per launch (kg)", 'Vehicle Build'!$A$1:$A$119, 0), COLUMN()-COLUMN($D25)+1)} -> 174110.11 | I25: {=INDEX('Vehicle Build'!$D:$AC, MATCH("Starship payload per launch (kg)", 'Vehicle Build'!$A$1:$A$119, 0), COLUMN()-COLUMN($D25)+1)} -> 200000 | J25: {=INDEX('Vehicle Build'!$D:$AC, MATCH("Starship payload per launch (kg)", 'Vehicle Build'!$A$1:$A$119, 0), COLUMN()-COLUMN($D25)+1)} -> 200000 | K25: {=INDEX('Vehicle Build'!$D:$AC, MATCH("Starship payload per launch (kg)", 'Vehicle Build'!$A$1:$A$119, 0), COLUMN()-COLUMN($D25)+1)} -> 200000 | ... S25: {=INDEX('Vehicle Build'!$D:$AC, MATCH("Starship payload per launch (kg)", 'Vehicle Build'!$A$1:$A$119, 0), COLUMN()-COLUMN($D25)+1)} -> 200000
A27: ▸ CONSTELLATION BUILD (real cohorts → total bandwidth)
A28: V2 launch window active (1/0) | D28: =IF(D$4<=$D$23, 1, 0) -> 1 | E28: =IF(E$4<=$D$23, 1, 0) -> 1 | F28: =IF(F$4<=$D$23, 1, 0) -> 0 | G28: =IF(G$4<=$D$23, 1, 0) -> 0 | H28: =IF(H$4<=$D$23, 1, 0) -> 0 | I28: =IF(I$4<=$D$23, 1, 0) -> 0 | J28: =IF(J$4<=$D$23, 1, 0) -> 0 | K28: =IF(K$4<=$D$23, 1, 0) -> 0 | ... S28: =IF(S$4<=$D$23, 1, 0) -> 0
A29: V3 deployment active (1/0) | D29: =IF(D$4>=$D$22+1, 1, 0) -> 0 | E29: =IF(E$4>=$D$22+1, 1, 0) -> 0 | F29: =IF(F$4>=$D$22+1, 1, 0) -> 1 | G29: =IF(G$4>=$D$22+1, 1, 0) -> 1 | H29: =IF(H$4>=$D$22+1, 1, 0) -> 1 | I29: =IF(I$4>=$D$22+1, 1, 0) -> 1 | J29: =IF(J$4>=$D$22+1, 1, 0) -> 1 | K29: =IF(K$4>=$D$22+1, 1, 0) -> 1 | ... S29: =IF(S$4>=$D$22+1, 1, 0) -> 1
A31: Total new Starlink deployment (sats/yr) | D31: =SUM(D32:D35) -> 3840 | E31: =SUM(E32:E35) -> 3120 | F31: =SUM(F32:F35) -> 3918.7353 | G31: =SUM(G32:G35) -> 9497.38 | H31: =SUM(H32:H35) -> 27023.504 | I31: =SUM(I32:I35) -> 50339.52 | J31: =SUM(J32:J35) -> 53600.633 | K31: =SUM(K32:K35) -> 63346.234 | ... S31: =SUM(S32:S35) -> 33596.994
A32: New V2 BB deployment (sats/yr) | D32: =IF(D$4=2025, $D$20, IF(D$28=1, D202, 0)) -> 3840 | E32: =IF(E$4=2025, $D$20, IF(E$28=1, E202, 0)) -> 3120 | F32: =IF(F$4=2025, $D$20, IF(F$28=1, F202, 0)) -> 0 | G32: =IF(G$4=2025, $D$20, IF(G$28=1, G202, 0)) -> 0 | H32: =IF(H$4=2025, $D$20, IF(H$28=1, H202, 0)) -> 0 | I32: =IF(I$4=2025, $D$20, IF(I$28=1, I202, 0)) -> 0 | J32: =IF(J$4=2025, $D$20, IF(J$28=1, J202, 0)) -> 0 | K32: =IF(K$4=2025, $D$20, IF(K$28=1, K202, 0)) -> 0 | ... S32: =IF(S$4=2025, $D$20, IF(S$28=1, S202, 0)) -> 0
A33: New V2 DTC deployment (sats/yr) | D33: =0 -> 0 | E33: =0 -> 0 | F33: =0 -> 0 | G33: =0 -> 0 | H33: =0 -> 0 | I33: =0 -> 0 | J33: =0 -> 0 | K33: =0 -> 0 | ... S33: =0 -> 0
A34: New V3 BB deployment (sats/yr) | D34: =IF(D$29=1, D202, 0) -> 0 | E34: =IF(E$29=1, E202, 0) -> 0 | F34: =IF(F$29=1, F202, 0) -> 3916.8534 | G34: =IF(G$29=1, G202, 0) -> 9417.3557 | H34: =IF(H$29=1, H202, 0) -> 23934.562 | I34: =IF(I$29=1, I202, 0) -> 15031.115 | J34: =IF(J$29=1, J202, 0) -> 28946.91 | K34: =IF(K$29=1, K202, 0) -> 16400.059 | ... S34: =IF(S$29=1, S202, 0) -> 17069.962
A35: New V3 DTC deployment (sats/yr) | D35: =IF(D$29=1, D203, 0) -> 0 | E35: =IF(E$29=1, E203, 0) -> 0 | F35: =IF(F$29=1, F203, 0) -> 1.8818572 | G35: =IF(G$29=1, G203, 0) -> 80.024272 | H35: =IF(H$29=1, H203, 0) -> 3088.9424 | I35: =IF(I$29=1, I203, 0) -> 35308.405 | J35: =IF(J$29=1, J203, 0) -> 24653.723 | K35: =IF(K$29=1, K203, 0) -> 46946.175 | ... S35: =IF(S$29=1, S203, 0) -> 16527.032
A36: New Starshield deployment (sats/yr) | D36: =$D$31*0.12 -> 460.8 | E36: =$D$31*0.12 -> 460.8 | F36: =$D$31*0.12 -> 460.8 | G36: =$D$31*0.12 -> 460.8 | H36: =$D$31*0.12 -> 460.8 | I36: =$D$31*0.12 -> 460.8 | J36: =$D$31*0.12 -> 460.8 | K36: =$D$31*0.12 -> 460.8 | ... S36: =$D$31*0.12 -> 460.8
A37: Blended new-sat CapEx slug ($mm/sat): MEMO ONLY (feeds CAE R88 cap; no longer drives deployment) | D37: 1.7 | E37: 1.7 | F37: =IF(F$29=1, INDEX(Assumptions!$B:$B,MATCH("V3 BB share of new deployment (frac)",Assumptions!$A$1:$A$257,0))*F125 + INDEX(Assumptions!$B:$B,MATCH("V3 DTC share of new deployment (frac)",Assumptions!$A$1:$A$257,0))*F131, INDEX(Assumptions!$B:$B,MATCH("V2 BB share of new deployment (frac)",Assumptions!$A$1:$A$257,0))*F113 + INDEX(Assumptions!$B:$B,MATCH("V2 DTC share of new deployment (frac)",Assumptions!$A$1:$A$257,0))*F119 + 0.12*F137) -> 1.6698542 | G37: =IF(G$29=1, INDEX(Assumptions!$B:$B,MATCH("V3 BB share of new deployment (frac)",Assumptions!$A$1:$A$257,0))*G125 + INDEX(Assumptions!$B:$B,MATCH("V3 DTC share of new deployment (frac)",Assumptions!$A$1:$A$257,0))*G131, INDEX(Assumptions!$B:$B,MATCH("V2 BB share of new deployment (frac)",Assumptions!$A$1:$A$257,0))*G113 + INDEX(Assumptions!$B:$B,MATCH("V2 DTC share of new deployment (frac)",Assumptions!$A$1:$A$257,0))*G119 + 0.12*G137) -> 1.5893285 | H37: =IF(H$29=1, INDEX(Assumptions!$B:$B,MATCH("V3 BB share of new deployment (frac)",Assumptions!$A$1:$A$257,0))*H125 + INDEX(Assumptions!$B:$B,MATCH("V3 DTC share of new deployment (frac)",Assumptions!$A$1:$A$257,0))*H131, INDEX(Assumptions!$B:$B,MATCH("V2 BB share of new deployment (frac)",Assumptions!$A$1:$A$257,0))*H113 + INDEX(Assumptions!$B:$B,MATCH("V2 DTC share of new deployment (frac)",Assumptions!$A$1:$A$257,0))*H119 + 0.12*H137) -> 1.4810863 | I37: =IF(I$29=1, INDEX(Assumptions!$B:$B,MATCH("V3 BB share of new deployment (frac)",Assumptions!$A$1:$A$257,0))*I125 + INDEX(Assumptions!$B:$B,MATCH("V3 DTC share of new deployment (frac)",Assumptions!$A$1:$A$257,0))*I131, INDEX(Assumptions!$B:$B,MATCH("V2 BB share of new deployment (frac)",Assumptions!$A$1:$A$257,0))*I113 + INDEX(Assumptions!$B:$B,MATCH("V2 DTC share of new deployment (frac)",Assumptions!$A$1:$A$257,0))*I119 + 0.12*I137) -> 1.3630978 | J37: =IF(J$29=1, INDEX(Assumptions!$B:$B,MATCH("V3 BB share of new deployment (frac)",Assumptions!$A$1:$A$257,0))*J125 + INDEX(Assumptions!$B:$B,MATCH("V3 DTC share of new deployment (frac)",Assumptions!$A$1:$A$257,0))*J131, INDEX(Assumptions!$B:$B,MATCH("V2 BB share of new deployment (frac)",Assumptions!$A$1:$A$257,0))*J113 + INDEX(Assumptions!$B:$B,MATCH("V2 DTC share of new deployment (frac)",Assumptions!$A$1:$A$257,0))*J119 + 0.12*J137) -> 1.2770077 | K37: =IF(K$29=1, INDEX(Assumptions!$B:$B,MATCH("V3 BB share of new deployment (frac)",Assumptions!$A$1:$A$257,0))*K125 + INDEX(Assumptions!$B:$B,MATCH("V3 DTC share of new deployment (frac)",Assumptions!$A$1:$A$257,0))*K131, INDEX(Assumptions!$B:$B,MATCH("V2 BB share of new deployment (frac)",Assumptions!$A$1:$A$257,0))*K113 + INDEX(Assumptions!$B:$B,MATCH("V2 DTC share of new deployment (frac)",Assumptions!$A$1:$A$257,0))*K119 + 0.12*K137) -> 1.2087558 | L37: =IF(L$29=1, INDEX(Assumptions!$B:$B,MATCH("V3 BB share of new deployment (frac)",Assumptions!$A$1:$A$257,0))*L125 + INDEX(Assumptions!$B:$B,MATCH("V3 DTC share of new deployment (frac)",Assumptions!$A$1:$A$257,0))*L131, INDEX(Assumptions!$B:$B,MATCH("V2 BB share of new deployment (frac)",Assumptions!$A$1:$A$257,0))*L113 + INDEX(Assumptions!$B:$B,MATCH("V2 DTC share of new deployment (frac)",Assumptions!$A$1:$A$257,0))*L119 + 0.12*L137) -> 1.1617272 | M37: =IF(M$29=1, INDEX(Assumptions!$B:$B,MATCH("V3 BB share of new deployment (frac)",Assumptions!$A$1:$A$257,0))*M125 + INDEX(Assumptions!$B:$B,MATCH("V3 DTC share of new deployment (frac)",Assumptions!$A$1:$A$257,0))*M131, INDEX(Assumptions!$B:$B,MATCH("V2 BB share of new deployment (frac)",Assumptions!$A$1:$A$257,0))*M113 + INDEX(Assumptions!$B:$B,MATCH("V2 DTC share of new deployment (frac)",Assumptions!$A$1:$A$257,0))*M119 + 0.12*M137) -> 1.1373993 | ... S37: =IF(S$29=1, INDEX(Assumptions!$B:$B,MATCH("V3 BB share of new deployment (frac)",Assumptions!$A$1:$A$257,0))*S125 + INDEX(Assumptions!$B:$B,MATCH("V3 DTC share of new deployment (frac)",Assumptions!$A$1:$A$257,0))*S131, INDEX(Assumptions!$B:$B,MATCH("V2 BB share of new deployment (frac)",Assumptions!$A$1:$A$257,0))*S113 + INDEX(Assumptions!$B:$B,MATCH("V2 DTC share of new deployment (frac)",Assumptions!$A$1:$A$257,0))*S119 + 0.12*S137) -> 0.99913786
A38: Demand-saturation deployment headroom (sats) | D38: =MAX(0,(INDEX('Demand Curves'!$B:$B,MATCH("BB Q breakpoint #56 (Gbps)",'Demand Curves'!$A$1:$A$167,0))-D176)/INDEX(Assumptions!$B:$B,MATCH("V3 BB Gbps per sat",Assumptions!$A$1:$A$257,0))) -> 249585.86 | E38: =MAX(0,(INDEX('Demand Curves'!$B:$B,MATCH("BB Q breakpoint #56 (Gbps)",'Demand Curves'!$A$1:$A$167,0))-D176)/INDEX(Assumptions!$B:$B,MATCH("V3 BB Gbps per sat",Assumptions!$A$1:$A$257,0))) -> 249585.86 | F38: =MAX(0,(INDEX('Demand Curves'!$B:$B,MATCH("BB Q breakpoint #56 (Gbps)",'Demand Curves'!$A$1:$A$167,0))-E176)/INDEX(Assumptions!$B:$B,MATCH("V3 BB Gbps per sat",Assumptions!$A$1:$A$257,0))) -> 249286.34 | G38: =MAX(0,(INDEX('Demand Curves'!$B:$B,MATCH("BB Q breakpoint #56 (Gbps)",'Demand Curves'!$A$1:$A$167,0))-F176)/INDEX(Assumptions!$B:$B,MATCH("V3 BB Gbps per sat",Assumptions!$A$1:$A$257,0))) -> 245369.48 | H38: =MAX(0,(INDEX('Demand Curves'!$B:$B,MATCH("BB Q breakpoint #56 (Gbps)",'Demand Curves'!$A$1:$A$167,0))-G176)/INDEX(Assumptions!$B:$B,MATCH("V3 BB Gbps per sat",Assumptions!$A$1:$A$257,0))) -> 236090.17 | I38: =MAX(0,(INDEX('Demand Curves'!$B:$B,MATCH("BB Q breakpoint #56 (Gbps)",'Demand Curves'!$A$1:$A$167,0))-H176)/INDEX(Assumptions!$B:$B,MATCH("V3 BB Gbps per sat",Assumptions!$A$1:$A$257,0))) -> 212293.66 | J38: =MAX(0,(INDEX('Demand Curves'!$B:$B,MATCH("BB Q breakpoint #56 (Gbps)",'Demand Curves'!$A$1:$A$167,0))-I176)/INDEX(Assumptions!$B:$B,MATCH("V3 BB Gbps per sat",Assumptions!$A$1:$A$257,0))) -> 197400.59 | K38: =MAX(0,(INDEX('Demand Curves'!$B:$B,MATCH("BB Q breakpoint #56 (Gbps)",'Demand Curves'!$A$1:$A$167,0))-J176)/INDEX(Assumptions!$B:$B,MATCH("V3 BB Gbps per sat",Assumptions!$A$1:$A$257,0))) -> 168753.2 | L38: =MAX(0,(INDEX('Demand Curves'!$B:$B,MATCH("BB Q breakpoint #56 (Gbps)",'Demand Curves'!$A$1:$A$167,0))-K176)/INDEX(Assumptions!$B:$B,MATCH("V3 BB Gbps per sat",Assumptions!$A$1:$A$257,0))) -> 156270 | ... S38: =MAX(0,(INDEX('Demand Curves'!$B:$B,MATCH("BB Q breakpoint #56 (Gbps)",'Demand Curves'!$A$1:$A$167,0))-R176)/INDEX(Assumptions!$B:$B,MATCH("V3 BB Gbps per sat",Assumptions!$A$1:$A$257,0))) -> 35771.676
A39: BB FLEET (active sats by cohort)
A40: Legacy V1 active sats | D40: =INDEX(Assumptions!$B:$B,MATCH("Legacy V1 active sats end-2025",Assumptions!$A$1:$A$257,0)) -> 866 | E40: =MAX(0, D40 - IF(AND(E$4>=INDEX(Assumptions!$B:$B,MATCH("Legacy V1 base deorbit start year",Assumptions!$A$1:$A$257,0)),E$4<=INDEX(Assumptions!$B:$B,MATCH("Legacy V1 base deorbit end year",Assumptions!$A$1:$A$257,0))),$D$40/(INDEX(Assumptions!$B:$B,MATCH("Legacy V1 base deorbit end year",Assumptions!$A$1:$A$257,0))-INDEX(Assumptions!$B:$B,MATCH("Legacy V1 base deorbit start year",Assumptions!$A$1:$A$257,0))+1),0)) -> 0 | F40: =MAX(0, E40 - IF(AND(F$4>=INDEX(Assumptions!$B:$B,MATCH("Legacy V1 base deorbit start year",Assumptions!$A$1:$A$257,0)),F$4<=INDEX(Assumptions!$B:$B,MATCH("Legacy V1 base deorbit end year",Assumptions!$A$1:$A$257,0))),$D$40/(INDEX(Assumptions!$B:$B,MATCH("Legacy V1 base deorbit end year",Assumptions!$A$1:$A$257,0))-INDEX(Assumptions!$B:$B,MATCH("Legacy V1 base deorbit start year",Assumptions!$A$1:$A$257,0))+1),0)) -> 0 | G40: =MAX(0, F40 - IF(AND(G$4>=INDEX(Assumptions!$B:$B,MATCH("Legacy V1 base deorbit start year",Assumptions!$A$1:$A$257,0)),G$4<=INDEX(Assumptions!$B:$B,MATCH("Legacy V1 base deorbit end year",Assumptions!$A$1:$A$257,0))),$D$40/(INDEX(Assumptions!$B:$B,MATCH("Legacy V1 base deorbit end year",Assumptions!$A$1:$A$257,0))-INDEX(Assumptions!$B:$B,MATCH("Legacy V1 base deorbit start year",Assumptions!$A$1:$A$257,0))+1),0)) -> 0 | H40: =MAX(0, G40 - IF(AND(H$4>=INDEX(Assumptions!$B:$B,MATCH("Legacy V1 base deorbit start year",Assumptions!$A$1:$A$257,0)),H$4<=INDEX(Assumptions!$B:$B,MATCH("Legacy V1 base deorbit end year",Assumptions!$A$1:$A$257,0))),$D$40/(INDEX(Assumptions!$B:$B,MATCH("Legacy V1 base deorbit end year",Assumptions!$A$1:$A$257,0))-INDEX(Assumptions!$B:$B,MATCH("Legacy V1 base deorbit start year",Assumptions!$A$1:$A$257,0))+1),0)) -> 0 | I40: =MAX(0, H40 - IF(AND(I$4>=INDEX(Assumptions!$B:$B,MATCH("Legacy V1 base deorbit start year",Assumptions!$A$1:$A$257,0)),I$4<=INDEX(Assumptions!$B:$B,MATCH("Legacy V1 base deorbit end year",Assumptions!$A$1:$A$257,0))),$D$40/(INDEX(Assumptions!$B:$B,MATCH("Legacy V1 base deorbit end year",Assumptions!$A$1:$A$257,0))-INDEX(Assumptions!$B:$B,MATCH("Legacy V1 base deorbit start year",Assumptions!$A$1:$A$257,0))+1),0)) -> 0 | J40: =MAX(0, I40 - IF(AND(J$4>=INDEX(Assumptions!$B:$B,MATCH("Legacy V1 base deorbit start year",Assumptions!$A$1:$A$257,0)),J$4<=INDEX(Assumptions!$B:$B,MATCH("Legacy V1 base deorbit end year",Assumptions!$A$1:$A$257,0))),$D$40/(INDEX(Assumptions!$B:$B,MATCH("Legacy V1 base deorbit end year",Assumptions!$A$1:$A$257,0))-INDEX(Assumptions!$B:$B,MATCH("Legacy V1 base deorbit start year",Assumptions!$A$1:$A$257,0))+1),0)) -> 0 | K40: =MAX(0, J40 - IF(AND(K$4>=INDEX(Assumptions!$B:$B,MATCH("Legacy V1 base deorbit start year",Assumptions!$A$1:$A$257,0)),K$4<=INDEX(Assumptions!$B:$B,MATCH("Legacy V1 base deorbit end year",Assumptions!$A$1:$A$257,0))),$D$40/(INDEX(Assumptions!$B:$B,MATCH("Legacy V1 base deorbit end year",Assumptions!$A$1:$A$257,0))-INDEX(Assumptions!$B:$B,MATCH("Legacy V1 base deorbit start year",Assumptions!$A$1:$A$257,0))+1),0)) -> 0 | L40: =MAX(0, K40 - IF(AND(L$4>=INDEX(Assumptions!$B:$B,MATCH("Legacy V1 base deorbit start year",Assumptions!$A$1:$A$257,0)),L$4<=INDEX(Assumptions!$B:$B,MATCH("Legacy V1 base deorbit end year",Assumptions!$A$1:$A$257,0))),$D$40/(INDEX(Assumptions!$B:$B,MATCH("Legacy V1 base deorbit end year",Assumptions!$A$1:$A$257,0))-INDEX(Assumptions!$B:$B,MATCH("Legacy V1 base deorbit start year",Assumptions!$A$1:$A$257,0))+1),0)) -> 0 | ... S40: =MAX(0, R40 - IF(AND(S$4>=INDEX(Assumptions!$B:$B,MATCH("Legacy V1 base deorbit start year",Assumptions!$A$1:$A$257,0)),S$4<=INDEX(Assumptions!$B:$B,MATCH("Legacy V1 base deorbit end year",Assumptions!$A$1:$A$257,0))),$D$40/(INDEX(Assumptions!$B:$B,MATCH("Legacy V1 base deorbit end year",Assumptions!$A$1:$A$257,0))-INDEX(Assumptions!$B:$B,MATCH("Legacy V1 base deorbit start year",Assumptions!$A$1:$A$257,0))+1),0)) -> 0
A41: Legacy V1.5 active sats | D41: =INDEX(Assumptions!$B:$B,MATCH("Legacy V1.5 active sats end-2025",Assumptions!$A$1:$A$257,0)) -> 2692 | E41: =MAX(0, D41 - IF(AND(E$4>=INDEX(Assumptions!$B:$B,MATCH("Legacy V1.5 base deorbit start year",Assumptions!$A$1:$A$257,0)),E$4<=INDEX(Assumptions!$B:$B,MATCH("Legacy V1.5 base deorbit end year",Assumptions!$A$1:$A$257,0))),$D$41/(INDEX(Assumptions!$B:$B,MATCH("Legacy V1.5 base deorbit end year",Assumptions!$A$1:$A$257,0))-INDEX(Assumptions!$B:$B,MATCH("Legacy V1.5 base deorbit start year",Assumptions!$A$1:$A$257,0))+1),0)) -> 1794.6667 | F41: =MAX(0, E41 - IF(AND(F$4>=INDEX(Assumptions!$B:$B,MATCH("Legacy V1.5 base deorbit start year",Assumptions!$A$1:$A$257,0)),F$4<=INDEX(Assumptions!$B:$B,MATCH("Legacy V1.5 base deorbit end year",Assumptions!$A$1:$A$257,0))),$D$41/(INDEX(Assumptions!$B:$B,MATCH("Legacy V1.5 base deorbit end year",Assumptions!$A$1:$A$257,0))-INDEX(Assumptions!$B:$B,MATCH("Legacy V1.5 base deorbit start year",Assumptions!$A$1:$A$257,0))+1),0)) -> 897.33333 | G41: =MAX(0, F41 - IF(AND(G$4>=INDEX(Assumptions!$B:$B,MATCH("Legacy V1.5 base deorbit start year",Assumptions!$A$1:$A$257,0)),G$4<=INDEX(Assumptions!$B:$B,MATCH("Legacy V1.5 base deorbit end year",Assumptions!$A$1:$A$257,0))),$D$41/(INDEX(Assumptions!$B:$B,MATCH("Legacy V1.5 base deorbit end year",Assumptions!$A$1:$A$257,0))-INDEX(Assumptions!$B:$B,MATCH("Legacy V1.5 base deorbit start year",Assumptions!$A$1:$A$257,0))+1),0)) -> 0 | H41: =MAX(0, G41 - IF(AND(H$4>=INDEX(Assumptions!$B:$B,MATCH("Legacy V1.5 base deorbit start year",Assumptions!$A$1:$A$257,0)),H$4<=INDEX(Assumptions!$B:$B,MATCH("Legacy V1.5 base deorbit end year",Assumptions!$A$1:$A$257,0))),$D$41/(INDEX(Assumptions!$B:$B,MATCH("Legacy V1.5 base deorbit end year",Assumptions!$A$1:$A$257,0))-INDEX(Assumptions!$B:$B,MATCH("Legacy V1.5 base deorbit start year",Assumptions!$A$1:$A$257,0))+1),0)) -> 0 | I41: =MAX(0, H41 - IF(AND(I$4>=INDEX(Assumptions!$B:$B,MATCH("Legacy V1.5 base deorbit start year",Assumptions!$A$1:$A$257,0)),I$4<=INDEX(Assumptions!$B:$B,MATCH("Legacy V1.5 base deorbit end year",Assumptions!$A$1:$A$257,0))),$D$41/(INDEX(Assumptions!$B:$B,MATCH("Legacy V1.5 base deorbit end year",Assumptions!$A$1:$A$257,0))-INDEX(Assumptions!$B:$B,MATCH("Legacy V1.5 base deorbit start year",Assumptions!$A$1:$A$257,0))+1),0)) -> 0 | J41: =MAX(0, I41 - IF(AND(J$4>=INDEX(Assumptions!$B:$B,MATCH("Legacy V1.5 base deorbit start year",Assumptions!$A$1:$A$257,0)),J$4<=INDEX(Assumptions!$B:$B,MATCH("Legacy V1.5 base deorbit end year",Assumptions!$A$1:$A$257,0))),$D$41/(INDEX(Assumptions!$B:$B,MATCH("Legacy V1.5 base deorbit end year",Assumptions!$A$1:$A$257,0))-INDEX(Assumptions!$B:$B,MATCH("Legacy V1.5 base deorbit start year",Assumptions!$A$1:$A$257,0))+1),0)) -> 0 | K41: =MAX(0, J41 - IF(AND(K$4>=INDEX(Assumptions!$B:$B,MATCH("Legacy V1.5 base deorbit start year",Assumptions!$A$1:$A$257,0)),K$4<=INDEX(Assumptions!$B:$B,MATCH("Legacy V1.5 base deorbit end year",Assumptions!$A$1:$A$257,0))),$D$41/(INDEX(Assumptions!$B:$B,MATCH("Legacy V1.5 base deorbit end year",Assumptions!$A$1:$A$257,0))-INDEX(Assumptions!$B:$B,MATCH("Legacy V1.5 base deorbit start year",Assumptions!$A$1:$A$257,0))+1),0)) -> 0 | L41: =MAX(0, K41 - IF(AND(L$4>=INDEX(Assumptions!$B:$B,MATCH("Legacy V1.5 base deorbit start year",Assumptions!$A$1:$A$257,0)),L$4<=INDEX(Assumptions!$B:$B,MATCH("Legacy V1.5 base deorbit end year",Assumptions!$A$1:$A$257,0))),$D$41/(INDEX(Assumptions!$B:$B,MATCH("Legacy V1.5 base deorbit end year",Assumptions!$A$1:$A$257,0))-INDEX(Assumptions!$B:$B,MATCH("Legacy V1.5 base deorbit start year",Assumptions!$A$1:$A$257,0))+1),0)) -> 0 | ... S41: =MAX(0, R41 - IF(AND(S$4>=INDEX(Assumptions!$B:$B,MATCH("Legacy V1.5 base deorbit start year",Assumptions!$A$1:$A$257,0)),S$4<=INDEX(Assumptions!$B:$B,MATCH("Legacy V1.5 base deorbit end year",Assumptions!$A$1:$A$257,0))),$D$41/(INDEX(Assumptions!$B:$B,MATCH("Legacy V1.5 base deorbit end year",Assumptions!$A$1:$A$257,0))-INDEX(Assumptions!$B:$B,MATCH("Legacy V1.5 base deorbit start year",Assumptions!$A$1:$A$257,0))+1),0)) -> 0
A42: V2 Mini BB active sats | D42: =INDEX(Assumptions!$B:$B,MATCH("V2 Mini BB sats end-2025",Assumptions!$A$1:$A$257,0)) -> 4314 | E42: {=MAX(0, D42 + E$32 - IFERROR(IF(E$5-$D$15>=1, INDEX($D$32:$AC$32, E$5-$D$15+1), 0),0) - IF(AND(E$4>=INDEX(Assumptions!$B:$B,MATCH("V2 Mini BB base deorbit start year",Assumptions!$A$1:$A$257,0)),E$4<=INDEX(Assumptions!$B:$B,MATCH("V2 Mini BB base deorbit end year",Assumptions!$A$1:$A$257,0))),$D$42/(INDEX(Assumptions!$B:$B,MATCH("V2 Mini BB base deorbit end year",Assumptions!$A$1:$A$257,0))-INDEX(Assumptions!$B:$B,MATCH("V2 Mini BB base deorbit start year",Assumptions!$A$1:$A$257,0))+1),0))} -> 7434 | F42: {=MAX(0, E42 + F$32 - IFERROR(IF(F$5-$D$15>=1, INDEX($D$32:$AC$32, F$5-$D$15+1), 0),0) - IF(AND(F$4>=INDEX(Assumptions!$B:$B,MATCH("V2 Mini BB base deorbit start year",Assumptions!$A$1:$A$257,0)),F$4<=INDEX(Assumptions!$B:$B,MATCH("V2 Mini BB base deorbit end year",Assumptions!$A$1:$A$257,0))),$D$42/(INDEX(Assumptions!$B:$B,MATCH("V2 Mini BB base deorbit end year",Assumptions!$A$1:$A$257,0))-INDEX(Assumptions!$B:$B,MATCH("V2 Mini BB base deorbit start year",Assumptions!$A$1:$A$257,0))+1),0))} -> 7434 | G42: {=MAX(0, F42 + G$32 - IFERROR(IF(G$5-$D$15>=1, INDEX($D$32:$AC$32, G$5-$D$15+1), 0),0) - IF(AND(G$4>=INDEX(Assumptions!$B:$B,MATCH("V2 Mini BB base deorbit start year",Assumptions!$A$1:$A$257,0)),G$4<=INDEX(Assumptions!$B:$B,MATCH("V2 Mini BB base deorbit end year",Assumptions!$A$1:$A$257,0))),$D$42/(INDEX(Assumptions!$B:$B,MATCH("V2 Mini BB base deorbit end year",Assumptions!$A$1:$A$257,0))-INDEX(Assumptions!$B:$B,MATCH("V2 Mini BB base deorbit start year",Assumptions!$A$1:$A$257,0))+1),0))} -> 5996 | H42: {=MAX(0, G42 + H$32 - IFERROR(IF(H$5-$D$15>=1, INDEX($D$32:$AC$32, H$5-$D$15+1), 0),0) - IF(AND(H$4>=INDEX(Assumptions!$B:$B,MATCH("V2 Mini BB base deorbit start year",Assumptions!$A$1:$A$257,0)),H$4<=INDEX(Assumptions!$B:$B,MATCH("V2 Mini BB base deorbit end year",Assumptions!$A$1:$A$257,0))),$D$42/(INDEX(Assumptions!$B:$B,MATCH("V2 Mini BB base deorbit end year",Assumptions!$A$1:$A$257,0))-INDEX(Assumptions!$B:$B,MATCH("V2 Mini BB base deorbit start year",Assumptions!$A$1:$A$257,0))+1),0))} -> 4558 | I42: {=MAX(0, H42 + I$32 - IFERROR(IF(I$5-$D$15>=1, INDEX($D$32:$AC$32, I$5-$D$15+1), 0),0) - IF(AND(I$4>=INDEX(Assumptions!$B:$B,MATCH("V2 Mini BB base deorbit start year",Assumptions!$A$1:$A$257,0)),I$4<=INDEX(Assumptions!$B:$B,MATCH("V2 Mini BB base deorbit end year",Assumptions!$A$1:$A$257,0))),$D$42/(INDEX(Assumptions!$B:$B,MATCH("V2 Mini BB base deorbit end year",Assumptions!$A$1:$A$257,0))-INDEX(Assumptions!$B:$B,MATCH("V2 Mini BB base deorbit start year",Assumptions!$A$1:$A$257,0))+1),0))} -> 3120 | J42: {=MAX(0, I42 + J$32 - IFERROR(IF(J$5-$D$15>=1, INDEX($D$32:$AC$32, J$5-$D$15+1), 0),0) - IF(AND(J$4>=INDEX(Assumptions!$B:$B,MATCH("V2 Mini BB base deorbit start year",Assumptions!$A$1:$A$257,0)),J$4<=INDEX(Assumptions!$B:$B,MATCH("V2 Mini BB base deorbit end year",Assumptions!$A$1:$A$257,0))),$D$42/(INDEX(Assumptions!$B:$B,MATCH("V2 Mini BB base deorbit end year",Assumptions!$A$1:$A$257,0))-INDEX(Assumptions!$B:$B,MATCH("V2 Mini BB base deorbit start year",Assumptions!$A$1:$A$257,0))+1),0))} -> 0 | K42: {=MAX(0, J42 + K$32 - IFERROR(IF(K$5-$D$15>=1, INDEX($D$32:$AC$32, K$5-$D$15+1), 0),0) - IF(AND(K$4>=INDEX(Assumptions!$B:$B,MATCH("V2 Mini BB base deorbit start year",Assumptions!$A$1:$A$257,0)),K$4<=INDEX(Assumptions!$B:$B,MATCH("V2 Mini BB base deorbit end year",Assumptions!$A$1:$A$257,0))),$D$42/(INDEX(Assumptions!$B:$B,MATCH("V2 Mini BB base deorbit end year",Assumptions!$A$1:$A$257,0))-INDEX(Assumptions!$B:$B,MATCH("V2 Mini BB base deorbit start year",Assumptions!$A$1:$A$257,0))+1),0))} -> 0 | L42: {=MAX(0, K42 + L$32 - IFERROR(IF(L$5-$D$15>=1, INDEX($D$32:$AC$32, L$5-$D$15+1), 0),0) - IF(AND(L$4>=INDEX(Assumptions!$B:$B,MATCH("V2 Mini BB base deorbit start year",Assumptions!$A$1:$A$257,0)),L$4<=INDEX(Assumptions!$B:$B,MATCH("V2 Mini BB base deorbit end year",Assumptions!$A$1:$A$257,0))),$D$42/(INDEX(Assumptions!$B:$B,MATCH("V2 Mini BB base deorbit end year",Assumptions!$A$1:$A$257,0))-INDEX(Assumptions!$B:$B,MATCH("V2 Mini BB base deorbit start year",Assumptions!$A$1:$A$257,0))+1),0))} -> 0 | ... S42: {=MAX(0, R42 + S$32 - IFERROR(IF(S$5-$D$15>=1, INDEX($D$32:$AC$32, S$5-$D$15+1), 0),0) - IF(AND(S$4>=INDEX(Assumptions!$B:$B,MATCH("V2 Mini BB base deorbit start year",Assumptions!$A$1:$A$257,0)),S$4<=INDEX(Assumptions!$B:$B,MATCH("V2 Mini BB base deorbit end year",Assumptions!$A$1:$A$257,0))),$D$42/(INDEX(Assumptions!$B:$B,MATCH("V2 Mini BB base deorbit end year",Assumptions!$A$1:$A$257,0))-INDEX(Assumptions!$B:$B,MATCH("V2 Mini BB base deorbit start year",Assumptions!$A$1:$A$257,0))+1),0))} -> 0
A43: V3 BB active sats EoY | D43: =0 -> 0 | E43: {=MAX(0, D43 + E$34 - IFERROR(IF(E$5-$D$15>=1, INDEX($D$34:$AC$34, E$5-$D$15+1), 0),0))} -> 0 | F43: {=MAX(0, E43 + F$34 - IFERROR(IF(F$5-$D$15>=1, INDEX($D$34:$AC$34, F$5-$D$15+1), 0),0))} -> 3916.8534 | G43: {=MAX(0, F43 + G$34 - IFERROR(IF(G$5-$D$15>=1, INDEX($D$34:$AC$34, G$5-$D$15+1), 0),0))} -> 13334.209 | H43: {=MAX(0, G43 + H$34 - IFERROR(IF(H$5-$D$15>=1, INDEX($D$34:$AC$34, H$5-$D$15+1), 0),0))} -> 37268.771 | I43: {=MAX(0, H43 + I$34 - IFERROR(IF(I$5-$D$15>=1, INDEX($D$34:$AC$34, I$5-$D$15+1), 0),0))} -> 52299.886 | J43: {=MAX(0, I43 + J$34 - IFERROR(IF(J$5-$D$15>=1, INDEX($D$34:$AC$34, J$5-$D$15+1), 0),0))} -> 81246.796 | K43: {=MAX(0, J43 + K$34 - IFERROR(IF(K$5-$D$15>=1, INDEX($D$34:$AC$34, K$5-$D$15+1), 0),0))} -> 93730.001 | L43: {=MAX(0, K43 + L$34 - IFERROR(IF(L$5-$D$15>=1, INDEX($D$34:$AC$34, L$5-$D$15+1), 0),0))} -> 89181.52 | ... S43: {=MAX(0, R43 + S$34 - IFERROR(IF(S$5-$D$15>=1, INDEX($D$34:$AC$34, S$5-$D$15+1), 0),0))} -> 188862.32
A45: BB BANDWIDTH (Gbps by cohort)
A46: Legacy BB Gbps | D46: =D40*INDEX(Assumptions!$B:$B,MATCH("Legacy V1 Gbps per sat",Assumptions!$A$1:$A$257,0)) + D41*INDEX(Assumptions!$B:$B,MATCH("Legacy V1.5 Gbps per sat",Assumptions!$A$1:$A$257,0)) -> 75000 | E46: =E40*INDEX(Assumptions!$B:$B,MATCH("Legacy V1 Gbps per sat",Assumptions!$A$1:$A$257,0)) + E41*INDEX(Assumptions!$B:$B,MATCH("Legacy V1.5 Gbps per sat",Assumptions!$A$1:$A$257,0)) -> 43072 | F46: =F40*INDEX(Assumptions!$B:$B,MATCH("Legacy V1 Gbps per sat",Assumptions!$A$1:$A$257,0)) + F41*INDEX(Assumptions!$B:$B,MATCH("Legacy V1.5 Gbps per sat",Assumptions!$A$1:$A$257,0)) -> 21536 | G46: =G40*INDEX(Assumptions!$B:$B,MATCH("Legacy V1 Gbps per sat",Assumptions!$A$1:$A$257,0)) + G41*INDEX(Assumptions!$B:$B,MATCH("Legacy V1.5 Gbps per sat",Assumptions!$A$1:$A$257,0)) -> 0 | H46: =H40*INDEX(Assumptions!$B:$B,MATCH("Legacy V1 Gbps per sat",Assumptions!$A$1:$A$257,0)) + H41*INDEX(Assumptions!$B:$B,MATCH("Legacy V1.5 Gbps per sat",Assumptions!$A$1:$A$257,0)) -> 0 | I46: =I40*INDEX(Assumptions!$B:$B,MATCH("Legacy V1 Gbps per sat",Assumptions!$A$1:$A$257,0)) + I41*INDEX(Assumptions!$B:$B,MATCH("Legacy V1.5 Gbps per sat",Assumptions!$A$1:$A$257,0)) -> 0 | J46: =J40*INDEX(Assumptions!$B:$B,MATCH("Legacy V1 Gbps per sat",Assumptions!$A$1:$A$257,0)) + J41*INDEX(Assumptions!$B:$B,MATCH("Legacy V1.5 Gbps per sat",Assumptions!$A$1:$A$257,0)) -> 0 | K46: =K40*INDEX(Assumptions!$B:$B,MATCH("Legacy V1 Gbps per sat",Assumptions!$A$1:$A$257,0)) + K41*INDEX(Assumptions!$B:$B,MATCH("Legacy V1.5 Gbps per sat",Assumptions!$A$1:$A$257,0)) -> 0 | ... S46: =S40*INDEX(Assumptions!$B:$B,MATCH("Legacy V1 Gbps per sat",Assumptions!$A$1:$A$257,0)) + S41*INDEX(Assumptions!$B:$B,MATCH("Legacy V1.5 Gbps per sat",Assumptions!$A$1:$A$257,0)) -> 0
A47: V2 BB Gbps | D47: =D42*INDEX(Assumptions!$B:$B,MATCH("V2 BB Gbps per sat",Assumptions!$A$1:$A$257,0)) -> 414144 | E47: =E42*INDEX(Assumptions!$B:$B,MATCH("V2 BB Gbps per sat",Assumptions!$A$1:$A$257,0)) -> 713664 | F47: =F42*INDEX(Assumptions!$B:$B,MATCH("V2 BB Gbps per sat",Assumptions!$A$1:$A$257,0)) -> 713664 | G47: =G42*INDEX(Assumptions!$B:$B,MATCH("V2 BB Gbps per sat",Assumptions!$A$1:$A$257,0)) -> 575616 | H47: =H42*INDEX(Assumptions!$B:$B,MATCH("V2 BB Gbps per sat",Assumptions!$A$1:$A$257,0)) -> 437568 | I47: =I42*INDEX(Assumptions!$B:$B,MATCH("V2 BB Gbps per sat",Assumptions!$A$1:$A$257,0)) -> 299520 | J47: =J42*INDEX(Assumptions!$B:$B,MATCH("V2 BB Gbps per sat",Assumptions!$A$1:$A$257,0)) -> 0 | K47: =K42*INDEX(Assumptions!$B:$B,MATCH("V2 BB Gbps per sat",Assumptions!$A$1:$A$257,0)) -> 0 | ... S47: =S42*INDEX(Assumptions!$B:$B,MATCH("V2 BB Gbps per sat",Assumptions!$A$1:$A$257,0)) -> 0
A48: V3 BB Gbps | D48: =D43*INDEX(Assumptions!$B:$B,MATCH("V3 BB Gbps per sat",Assumptions!$A$1:$A$257,0)) -> 0 | E48: =E43*INDEX(Assumptions!$B:$B,MATCH("V3 BB Gbps per sat",Assumptions!$A$1:$A$257,0)) -> 0 | F48: =F43*INDEX(Assumptions!$B:$B,MATCH("V3 BB Gbps per sat",Assumptions!$A$1:$A$257,0)) -> 3916853.4 | G48: =G43*INDEX(Assumptions!$B:$B,MATCH("V3 BB Gbps per sat",Assumptions!$A$1:$A$257,0)) -> 13334209 | H48: =H43*INDEX(Assumptions!$B:$B,MATCH("V3 BB Gbps per sat",Assumptions!$A$1:$A$257,0)) -> 37268771 | I48: =I43*INDEX(Assumptions!$B:$B,MATCH("V3 BB Gbps per sat",Assumptions!$A$1:$A$257,0)) -> 52299886 | J48: =J43*INDEX(Assumptions!$B:$B,MATCH("V3 BB Gbps per sat",Assumptions!$A$1:$A$257,0)) -> 81246796 | K48: =K43*INDEX(Assumptions!$B:$B,MATCH("V3 BB Gbps per sat",Assumptions!$A$1:$A$257,0)) -> 93730001 | ... S48: =S43*INDEX(Assumptions!$B:$B,MATCH("V3 BB Gbps per sat",Assumptions!$A$1:$A$257,0)) -> 1.8886232e+08
A49: BB Gbps available for external Starlink revenue | D49: =D46+D47+D48 -> 489144 | E49: =E46+E47+E48 -> 756736 | F49: =F46+F47+F48 -> 4652053.4 | G49: =G46+G47+G48 -> 13909825 | H49: =H46+H47+H48 -> 37706339 | I49: =I46+I47+I48 -> 52599406 | J49: =J46+J47+J48 -> 81246796 | K49: =K46+K47+K48 -> 93730001 | ... S49: =S46+S47+S48 -> 1.8886232e+08
A51: DTC FLEET + BANDWIDTH
A52: V2 DTC active sats | D52: =INDEX(Assumptions!$B:$B,MATCH("V2 DTC active sats end-2025",Assumptions!$A$1:$A$257,0)) -> 655 | E52: =MAX(0, D52 - IF(AND(E$4>=INDEX(Assumptions!$B:$B,MATCH("V2 DTC base deorbit start year",Assumptions!$A$1:$A$257,0)),E$4<=INDEX(Assumptions!$B:$B,MATCH("V2 DTC base deorbit end year",Assumptions!$A$1:$A$257,0))),$D$52/(INDEX(Assumptions!$B:$B,MATCH("V2 DTC base deorbit end year",Assumptions!$A$1:$A$257,0))-INDEX(Assumptions!$B:$B,MATCH("V2 DTC base deorbit start year",Assumptions!$A$1:$A$257,0))+1),0)) -> 655 | F52: =MAX(0, E52 - IF(AND(F$4>=INDEX(Assumptions!$B:$B,MATCH("V2 DTC base deorbit start year",Assumptions!$A$1:$A$257,0)),F$4<=INDEX(Assumptions!$B:$B,MATCH("V2 DTC base deorbit end year",Assumptions!$A$1:$A$257,0))),$D$52/(INDEX(Assumptions!$B:$B,MATCH("V2 DTC base deorbit end year",Assumptions!$A$1:$A$257,0))-INDEX(Assumptions!$B:$B,MATCH("V2 DTC base deorbit start year",Assumptions!$A$1:$A$257,0))+1),0)) -> 655 | G52: =MAX(0, F52 - IF(AND(G$4>=INDEX(Assumptions!$B:$B,MATCH("V2 DTC base deorbit start year",Assumptions!$A$1:$A$257,0)),G$4<=INDEX(Assumptions!$B:$B,MATCH("V2 DTC base deorbit end year",Assumptions!$A$1:$A$257,0))),$D$52/(INDEX(Assumptions!$B:$B,MATCH("V2 DTC base deorbit end year",Assumptions!$A$1:$A$257,0))-INDEX(Assumptions!$B:$B,MATCH("V2 DTC base deorbit start year",Assumptions!$A$1:$A$257,0))+1),0)) -> 655 | H52: =MAX(0, G52 - IF(AND(H$4>=INDEX(Assumptions!$B:$B,MATCH("V2 DTC base deorbit start year",Assumptions!$A$1:$A$257,0)),H$4<=INDEX(Assumptions!$B:$B,MATCH("V2 DTC base deorbit end year",Assumptions!$A$1:$A$257,0))),$D$52/(INDEX(Assumptions!$B:$B,MATCH("V2 DTC base deorbit end year",Assumptions!$A$1:$A$257,0))-INDEX(Assumptions!$B:$B,MATCH("V2 DTC base deorbit start year",Assumptions!$A$1:$A$257,0))+1),0)) -> 327.5 | I52: =MAX(0, H52 - IF(AND(I$4>=INDEX(Assumptions!$B:$B,MATCH("V2 DTC base deorbit start year",Assumptions!$A$1:$A$257,0)),I$4<=INDEX(Assumptions!$B:$B,MATCH("V2 DTC base deorbit end year",Assumptions!$A$1:$A$257,0))),$D$52/(INDEX(Assumptions!$B:$B,MATCH("V2 DTC base deorbit end year",Assumptions!$A$1:$A$257,0))-INDEX(Assumptions!$B:$B,MATCH("V2 DTC base deorbit start year",Assumptions!$A$1:$A$257,0))+1),0)) -> 0 | J52: =MAX(0, I52 - IF(AND(J$4>=INDEX(Assumptions!$B:$B,MATCH("V2 DTC base deorbit start year",Assumptions!$A$1:$A$257,0)),J$4<=INDEX(Assumptions!$B:$B,MATCH("V2 DTC base deorbit end year",Assumptions!$A$1:$A$257,0))),$D$52/(INDEX(Assumptions!$B:$B,MATCH("V2 DTC base deorbit end year",Assumptions!$A$1:$A$257,0))-INDEX(Assumptions!$B:$B,MATCH("V2 DTC base deorbit start year",Assumptions!$A$1:$A$257,0))+1),0)) -> 0 | K52: =MAX(0, J52 - IF(AND(K$4>=INDEX(Assumptions!$B:$B,MATCH("V2 DTC base deorbit start year",Assumptions!$A$1:$A$257,0)),K$4<=INDEX(Assumptions!$B:$B,MATCH("V2 DTC base deorbit end year",Assumptions!$A$1:$A$257,0))),$D$52/(INDEX(Assumptions!$B:$B,MATCH("V2 DTC base deorbit end year",Assumptions!$A$1:$A$257,0))-INDEX(Assumptions!$B:$B,MATCH("V2 DTC base deorbit start year",Assumptions!$A$1:$A$257,0))+1),0)) -> 0 | L52: =MAX(0, K52 - IF(AND(L$4>=INDEX(Assumptions!$B:$B,MATCH("V2 DTC base deorbit start year",Assumptions!$A$1:$A$257,0)),L$4<=INDEX(Assumptions!$B:$B,MATCH("V2 DTC base deorbit end year",Assumptions!$A$1:$A$257,0))),$D$52/(INDEX(Assumptions!$B:$B,MATCH("V2 DTC base deorbit end year",Assumptions!$A$1:$A$257,0))-INDEX(Assumptions!$B:$B,MATCH("V2 DTC base deorbit start year",Assumptions!$A$1:$A$257,0))+1),0)) -> 0 | ... S52: =MAX(0, R52 - IF(AND(S$4>=INDEX(Assumptions!$B:$B,MATCH("V2 DTC base deorbit start year",Assumptions!$A$1:$A$257,0)),S$4<=INDEX(Assumptions!$B:$B,MATCH("V2 DTC base deorbit end year",Assumptions!$A$1:$A$257,0))),$D$52/(INDEX(Assumptions!$B:$B,MATCH("V2 DTC base deorbit end year",Assumptions!$A$1:$A$257,0))-INDEX(Assumptions!$B:$B,MATCH("V2 DTC base deorbit start year",Assumptions!$A$1:$A$257,0))+1),0)) -> 0
A53: V3 DTC active sats EoY | D53: =0 -> 0 | E53: {=MAX(0, D53 + E$35 - IFERROR(IF(E$5-$D$15>=1, INDEX($D$35:$AC$35, E$5-$D$15+1), 0),0))} -> 0 | F53: {=MAX(0, E53 + F$35 - IFERROR(IF(F$5-$D$15>=1, INDEX($D$35:$AC$35, F$5-$D$15+1), 0),0))} -> 1.8818572 | G53: {=MAX(0, F53 + G$35 - IFERROR(IF(G$5-$D$15>=1, INDEX($D$35:$AC$35, G$5-$D$15+1), 0),0))} -> 81.906129 | H53: {=MAX(0, G53 + H$35 - IFERROR(IF(H$5-$D$15>=1, INDEX($D$35:$AC$35, H$5-$D$15+1), 0),0))} -> 3170.8486 | I53: {=MAX(0, H53 + I$35 - IFERROR(IF(I$5-$D$15>=1, INDEX($D$35:$AC$35, I$5-$D$15+1), 0),0))} -> 38479.253 | J53: {=MAX(0, I53 + J$35 - IFERROR(IF(J$5-$D$15>=1, INDEX($D$35:$AC$35, J$5-$D$15+1), 0),0))} -> 63132.976 | K53: {=MAX(0, J53 + K$35 - IFERROR(IF(K$5-$D$15>=1, INDEX($D$35:$AC$35, K$5-$D$15+1), 0),0))} -> 110077.27 | L53: {=MAX(0, K53 + L$35 - IFERROR(IF(L$5-$D$15>=1, INDEX($D$35:$AC$35, L$5-$D$15+1), 0),0))} -> 131332.75 | ... S53: {=MAX(0, R53 + S$35 - IFERROR(IF(S$5-$D$15>=1, INDEX($D$35:$AC$35, S$5-$D$15+1), 0),0))} -> 152518.28
A54: V2 DTC effective Gbps | D54: =D52*INDEX(Assumptions!$B:$B,MATCH("Effective DTC Gbps per sat (revenue calibration)",Assumptions!$A$1:$A$257,0)) -> 577.71 | E54: =E52*INDEX(Assumptions!$B:$B,MATCH("Effective DTC Gbps per sat (revenue calibration)",Assumptions!$A$1:$A$257,0)) -> 577.71 | F54: =F52*INDEX(Assumptions!$B:$B,MATCH("Effective DTC Gbps per sat (revenue calibration)",Assumptions!$A$1:$A$257,0)) -> 577.71 | G54: =G52*INDEX(Assumptions!$B:$B,MATCH("Effective DTC Gbps per sat (revenue calibration)",Assumptions!$A$1:$A$257,0)) -> 577.71 | H54: =H52*INDEX(Assumptions!$B:$B,MATCH("Effective DTC Gbps per sat (revenue calibration)",Assumptions!$A$1:$A$257,0)) -> 288.855 | I54: =I52*INDEX(Assumptions!$B:$B,MATCH("Effective DTC Gbps per sat (revenue calibration)",Assumptions!$A$1:$A$257,0)) -> 0 | J54: =J52*INDEX(Assumptions!$B:$B,MATCH("Effective DTC Gbps per sat (revenue calibration)",Assumptions!$A$1:$A$257,0)) -> 0 | K54: =K52*INDEX(Assumptions!$B:$B,MATCH("Effective DTC Gbps per sat (revenue calibration)",Assumptions!$A$1:$A$257,0)) -> 0 | ... S54: =S52*INDEX(Assumptions!$B:$B,MATCH("Effective DTC Gbps per sat (revenue calibration)",Assumptions!$A$1:$A$257,0)) -> 0
A55: V3 DTC effective Gbps | D55: =D53*INDEX(Assumptions!$B:$B,MATCH("Effective DTC Gbps per sat (revenue calibration)",Assumptions!$A$1:$A$257,0)) -> 0 | E55: =E53*INDEX(Assumptions!$B:$B,MATCH("Effective DTC Gbps per sat (revenue calibration)",Assumptions!$A$1:$A$257,0)) -> 0 | F55: =F53*INDEX(Assumptions!$B:$B,MATCH("Effective DTC Gbps per sat (revenue calibration)",Assumptions!$A$1:$A$257,0)) -> 1.659798 | G55: =G53*INDEX(Assumptions!$B:$B,MATCH("Effective DTC Gbps per sat (revenue calibration)",Assumptions!$A$1:$A$257,0)) -> 72.241206 | H55: =H53*INDEX(Assumptions!$B:$B,MATCH("Effective DTC Gbps per sat (revenue calibration)",Assumptions!$A$1:$A$257,0)) -> 2796.6884 | I55: =I53*INDEX(Assumptions!$B:$B,MATCH("Effective DTC Gbps per sat (revenue calibration)",Assumptions!$A$1:$A$257,0)) -> 33938.701 | J55: =J53*INDEX(Assumptions!$B:$B,MATCH("Effective DTC Gbps per sat (revenue calibration)",Assumptions!$A$1:$A$257,0)) -> 55683.285 | K55: =K53*INDEX(Assumptions!$B:$B,MATCH("Effective DTC Gbps per sat (revenue calibration)",Assumptions!$A$1:$A$257,0)) -> 97088.151 | ... S55: =S53*INDEX(Assumptions!$B:$B,MATCH("Effective DTC Gbps per sat (revenue calibration)",Assumptions!$A$1:$A$257,0)) -> 134521.12
A56: DTC Gbps available for external Starlink revenue | D56: =D54+D55 -> 577.71 | E56: =E54+E55 -> 577.71 | F56: =F54+F55 -> 579.3698 | G56: =G54+G55 -> 649.95121 | H56: =H54+H55 -> 3085.5434 | I56: =I54+I55 -> 33938.701 | J56: =J54+J55 -> 55683.285 | K56: =K54+K55 -> 97088.151 | ... S56: =S54+S55 -> 134521.12
A58: ▸ REVENUE
A59: Starshield active Gbps (working) | D59: {=INDEX(Assumptions!$D:$S,MATCH("Starshield active Gbps (year-row)",Assumptions!$A$1:$A$257,0),COLUMN()-COLUMN($D$59)+1)} -> 15300 | E59: {=INDEX(Assumptions!$D:$S,MATCH("Starshield active Gbps (year-row)",Assumptions!$A$1:$A$257,0),COLUMN()-COLUMN($D$59)+1)} -> 16524 | F59: {=INDEX(Assumptions!$D:$S,MATCH("Starshield active Gbps (year-row)",Assumptions!$A$1:$A$257,0),COLUMN()-COLUMN($D$59)+1)} -> 17845.92 | G59: {=INDEX(Assumptions!$D:$S,MATCH("Starshield active Gbps (year-row)",Assumptions!$A$1:$A$257,0),COLUMN()-COLUMN($D$59)+1)} -> 19273.594 | H59: {=INDEX(Assumptions!$D:$S,MATCH("Starshield active Gbps (year-row)",Assumptions!$A$1:$A$257,0),COLUMN()-COLUMN($D$59)+1)} -> 20815.481 | I59: {=INDEX(Assumptions!$D:$S,MATCH("Starshield active Gbps (year-row)",Assumptions!$A$1:$A$257,0),COLUMN()-COLUMN($D$59)+1)} -> 22480.72 | J59: {=INDEX(Assumptions!$D:$S,MATCH("Starshield active Gbps (year-row)",Assumptions!$A$1:$A$257,0),COLUMN()-COLUMN($D$59)+1)} -> 24279.177 | K59: {=INDEX(Assumptions!$D:$S,MATCH("Starshield active Gbps (year-row)",Assumptions!$A$1:$A$257,0),COLUMN()-COLUMN($D$59)+1)} -> 26221.511 | ... S59: {=INDEX(Assumptions!$D:$S,MATCH("Starshield active Gbps (year-row)",Assumptions!$A$1:$A$257,0),COLUMN()-COLUMN($D$59)+1)} -> 48534.187
A60: Starshield $/Gbps ($/Gbps-yr) (working) | D60: =INDEX(Assumptions!$B:$B,MATCH("Starshield $/Gbps ($/Gbps-yr)",Assumptions!$A$1:$A$257,0)) -> 164699 | E60: =INDEX(Assumptions!$B:$B,MATCH("Starshield $/Gbps ($/Gbps-yr)",Assumptions!$A$1:$A$257,0)) -> 164699 | F60: =INDEX(Assumptions!$B:$B,MATCH("Starshield $/Gbps ($/Gbps-yr)",Assumptions!$A$1:$A$257,0)) -> 164699 | G60: =INDEX(Assumptions!$B:$B,MATCH("Starshield $/Gbps ($/Gbps-yr)",Assumptions!$A$1:$A$257,0)) -> 164699 | H60: =INDEX(Assumptions!$B:$B,MATCH("Starshield $/Gbps ($/Gbps-yr)",Assumptions!$A$1:$A$257,0)) -> 164699 | I60: =INDEX(Assumptions!$B:$B,MATCH("Starshield $/Gbps ($/Gbps-yr)",Assumptions!$A$1:$A$257,0)) -> 164699 | J60: =INDEX(Assumptions!$B:$B,MATCH("Starshield $/Gbps ($/Gbps-yr)",Assumptions!$A$1:$A$257,0)) -> 164699 | K60: =INDEX(Assumptions!$B:$B,MATCH("Starshield $/Gbps ($/Gbps-yr)",Assumptions!$A$1:$A$257,0)) -> 164699 | ... S60: =INDEX(Assumptions!$B:$B,MATCH("Starshield $/Gbps ($/Gbps-yr)",Assumptions!$A$1:$A$257,0)) -> 164699
A61: Total BB revenue ($mm) | D61: =D11 -> 6721.2206 | E61: =E11 -> 9347.5765 | F61: =F11 -> 37555.656 | G61: =G11 -> 80517.71 | H61: =H11 -> 141004.93 | I61: =I11 -> 172279.32 | J61: =J11 -> 205461.3 | K61: =K11 -> 221249.49 | ... S61: =S11 -> 304575.99
A62: Total DTC revenue ($mm) | D62: =D12 -> 632.0752 | E62: =E12 -> 794.38308 | F62: =F12 -> 969.01979 | G62: =G12 -> 1291.3041 | H62: =H12 -> 7146.7257 | I62: =I12 -> 33355.216 | J62: =J12 -> 41028.563 | K62: =K12 -> 49505.313 | ... S62: =S12 -> 60513.713
A63: Starshield revenue ($mm) | D63: =D$59*D$60/1000000*INDEX(Assumptions!$B:$B,MATCH("Starshield utilization (frac)",Assumptions!$A$1:$A$257,0)) -> 2519.8947 | E63: =E$59*E$60/1000000*INDEX(Assumptions!$B:$B,MATCH("Starshield utilization (frac)",Assumptions!$A$1:$A$257,0)) -> 2721.4863 | F63: =F$59*F$60/1000000*INDEX(Assumptions!$B:$B,MATCH("Starshield utilization (frac)",Assumptions!$A$1:$A$257,0)) -> 2939.2052 | G63: =G$59*G$60/1000000*INDEX(Assumptions!$B:$B,MATCH("Starshield utilization (frac)",Assumptions!$A$1:$A$257,0)) -> 3174.3416 | H63: =H$59*H$60/1000000*INDEX(Assumptions!$B:$B,MATCH("Starshield utilization (frac)",Assumptions!$A$1:$A$257,0)) -> 3428.2889 | I63: =I$59*I$60/1000000*INDEX(Assumptions!$B:$B,MATCH("Starshield utilization (frac)",Assumptions!$A$1:$A$257,0)) -> 3702.552 | J63: =J$59*J$60/1000000*INDEX(Assumptions!$B:$B,MATCH("Starshield utilization (frac)",Assumptions!$A$1:$A$257,0)) -> 3998.7562 | K63: =K$59*K$60/1000000*INDEX(Assumptions!$B:$B,MATCH("Starshield utilization (frac)",Assumptions!$A$1:$A$257,0)) -> 4318.6567 | ... S63: =S$59*S$60/1000000*INDEX(Assumptions!$B:$B,MATCH("Starshield utilization (frac)",Assumptions!$A$1:$A$257,0)) -> 7993.5321
A64: Hardware / kit revenue ($mm) | D64: =D$185*INDEX(Assumptions!$B:$B,MATCH("Blended kit sale price ($/kit)",Assumptions!$A$1:$A$454,0)) -> 1181.9344 | E64: =E$185*INDEX(Assumptions!$B:$B,MATCH("Blended kit sale price ($/kit)",Assumptions!$A$1:$A$454,0)) -> 1611.6604 | F64: =F$185*INDEX(Assumptions!$B:$B,MATCH("Blended kit sale price ($/kit)",Assumptions!$A$1:$A$454,0)) -> 13874.716 | G64: =G$185*INDEX(Assumptions!$B:$B,MATCH("Blended kit sale price ($/kit)",Assumptions!$A$1:$A$454,0)) -> 24340.12 | H64: =H$185*INDEX(Assumptions!$B:$B,MATCH("Blended kit sale price ($/kit)",Assumptions!$A$1:$A$454,0)) -> 38823.512 | I64: =I$185*INDEX(Assumptions!$B:$B,MATCH("Blended kit sale price ($/kit)",Assumptions!$A$1:$A$454,0)) -> 30174.615 | J64: =J$185*INDEX(Assumptions!$B:$B,MATCH("Blended kit sale price ($/kit)",Assumptions!$A$1:$A$454,0)) -> 36265.62 | K64: =K$185*INDEX(Assumptions!$B:$B,MATCH("Blended kit sale price ($/kit)",Assumptions!$A$1:$A$454,0)) -> 30788.83 | ... S64: =S$185*INDEX(Assumptions!$B:$B,MATCH("Blended kit sale price ($/kit)",Assumptions!$A$1:$A$454,0)) -> 22794.774
A65: Revenue | D65: =D61+D62+D63+D64 -> 11055.125 | E65: =E61+E62+E63+E64 -> 14475.106 | F65: =F61+F62+F63+F64 -> 55338.597 | G65: =G61+G62+G63+G64 -> 109323.48 | H65: =H61+H62+H63+H64 -> 190403.45 | I65: =I61+I62+I63+I64 -> 239511.7 | J65: =J61+J62+J63+J64 -> 286754.24 | K65: =K61+K62+K63+K64 -> 305862.29 | ... S65: =S61+S62+S63+S64 -> 395878.01
A66: Memo: Starlink+DTC revenue (excl. Starshield) | D66: =D61+D62 -> 7353.2957 | E66: =E61+E62 -> 10141.96 | F66: =F61+F62 -> 38524.676 | G66: =G61+G62 -> 81809.015 | H66: =H61+H62 -> 148151.65 | I66: =I61+I62 -> 205634.54 | J66: =J61+J62 -> 246489.86 | K66: =K61+K62 -> 270754.8 | ... S66: =S61+S62 -> 365089.7
A68: ▸ INTERNAL LAUNCHES + RETAIL FLEET (working)
A69: F9 internal launches per year (Starlink-driven) | D69: =IF(D$28=1, IFERROR(_xlfn.CEILING.MATH((D$32+D$33+D$36)/INDEX(Assumptions!$B:$B,MATCH("F9 sats per launch (V2 packing)",Assumptions!$A$1:$A$257,0))),0), 0) -> 166 | E69: =IF(E$28=1, IFERROR(_xlfn.CEILING.MATH((E$32+E$33+E$36)/INDEX(Assumptions!$B:$B,MATCH("F9 sats per launch (V2 packing)",Assumptions!$A$1:$A$257,0))),0), 0) -> 138 | F69: =IF(F$28=1, IFERROR(_xlfn.CEILING.MATH((F$32+F$33+F$36)/INDEX(Assumptions!$B:$B,MATCH("F9 sats per launch (V2 packing)",Assumptions!$A$1:$A$257,0))),0), 0) -> 0 | G69: =IF(G$28=1, IFERROR(_xlfn.CEILING.MATH((G$32+G$33+G$36)/INDEX(Assumptions!$B:$B,MATCH("F9 sats per launch (V2 packing)",Assumptions!$A$1:$A$257,0))),0), 0) -> 0 | H69: =IF(H$28=1, IFERROR(_xlfn.CEILING.MATH((H$32+H$33+H$36)/INDEX(Assumptions!$B:$B,MATCH("F9 sats per launch (V2 packing)",Assumptions!$A$1:$A$257,0))),0), 0) -> 0 | I69: =IF(I$28=1, IFERROR(_xlfn.CEILING.MATH((I$32+I$33+I$36)/INDEX(Assumptions!$B:$B,MATCH("F9 sats per launch (V2 packing)",Assumptions!$A$1:$A$257,0))),0), 0) -> 0 | J69: =IF(J$28=1, IFERROR(_xlfn.CEILING.MATH((J$32+J$33+J$36)/INDEX(Assumptions!$B:$B,MATCH("F9 sats per launch (V2 packing)",Assumptions!$A$1:$A$257,0))),0), 0) -> 0 | K69: =IF(K$28=1, IFERROR(_xlfn.CEILING.MATH((K$32+K$33+K$36)/INDEX(Assumptions!$B:$B,MATCH("F9 sats per launch (V2 packing)",Assumptions!$A$1:$A$257,0))),0), 0) -> 0 | ... S69: =IF(S$28=1, IFERROR(_xlfn.CEILING.MATH((S$32+S$33+S$36)/INDEX(Assumptions!$B:$B,MATCH("F9 sats per launch (V2 packing)",Assumptions!$A$1:$A$257,0))),0), 0) -> 0
A70: Starship internal launches per year (Starlink-driven) | D70: =IF(D$29=1, IFERROR(_xlfn.CEILING.MATH((D$34+D$35)/D204),0), 0) -> 0 | E70: =IF(E$29=1, IFERROR(_xlfn.CEILING.MATH((E$34+E$35)/E204),0), 0) -> 0 | F70: =IF(F$29=1, IFERROR(_xlfn.CEILING.MATH((F$34+F$35)/F204),0), 0) -> 61 | G70: =IF(G$29=1, IFERROR(_xlfn.CEILING.MATH((G$34+G$35)/G204),0), 0) -> 127 | H70: =IF(H$29=1, IFERROR(_xlfn.CEILING.MATH((H$34+H$35)/H204),0), 0) -> 311 | I70: =IF(I$29=1, IFERROR(_xlfn.CEILING.MATH((I$34+I$35)/I204),0), 0) -> 504 | J70: =IF(J$29=1, IFERROR(_xlfn.CEILING.MATH((J$34+J$35)/J204),0), 0) -> 537 | K70: =IF(K$29=1, IFERROR(_xlfn.CEILING.MATH((K$34+K$35)/K204),0), 0) -> 634 | ... S70: =IF(S$29=1, IFERROR(_xlfn.CEILING.MATH((S$34+S$35)/S204),0), 0) -> 336
A71: Active retail sats (BB + DTC, EoY) | D71: =D$42+D$43+D$52+D$53 -> 4969 | E71: =E$42+E$43+E$52+E$53 -> 8089 | F71: =F$42+F$43+F$52+F$53 -> 12007.735 | G71: =G$42+G$43+G$52+G$53 -> 20067.115 | H71: =H$42+H$43+H$52+H$53 -> 45325.119 | I71: =I$42+I$43+I$52+I$53 -> 93899.139 | J71: =J$42+J$43+J$52+J$53 -> 144379.77 | K71: =K$42+K$43+K$52+K$53 -> 203807.27 | ... S71: =S$42+S$43+S$52+S$53 -> 341380.6
A73: ▸ COGS → GROSS PROFIT
A74: Hardware / kit COGS ($mm) | D74: =D$185*INDEX(Assumptions!$B:$B,MATCH("Terminal COGS per unit ($)",Assumptions!$A$1:$A$454,0)) -> 1477.418 | E74: =E$185*INDEX(Assumptions!$B:$B,MATCH("Terminal COGS per unit ($)",Assumptions!$A$1:$A$454,0)) -> 2014.5755 | F74: =F$185*INDEX(Assumptions!$B:$B,MATCH("Terminal COGS per unit ($)",Assumptions!$A$1:$A$454,0)) -> 17343.394 | G74: =G$185*INDEX(Assumptions!$B:$B,MATCH("Terminal COGS per unit ($)",Assumptions!$A$1:$A$454,0)) -> 30425.15 | H74: =H$185*INDEX(Assumptions!$B:$B,MATCH("Terminal COGS per unit ($)",Assumptions!$A$1:$A$454,0)) -> 48529.39 | I74: =I$185*INDEX(Assumptions!$B:$B,MATCH("Terminal COGS per unit ($)",Assumptions!$A$1:$A$454,0)) -> 37718.269 | J74: =J$185*INDEX(Assumptions!$B:$B,MATCH("Terminal COGS per unit ($)",Assumptions!$A$1:$A$454,0)) -> 45332.025 | K74: =K$185*INDEX(Assumptions!$B:$B,MATCH("Terminal COGS per unit ($)",Assumptions!$A$1:$A$454,0)) -> 38486.037 | ... S74: =S$185*INDEX(Assumptions!$B:$B,MATCH("Terminal COGS per unit ($)",Assumptions!$A$1:$A$454,0)) -> 28493.467
A75: Ground-network ops COGS ($mm) | D75: =D$65*INDEX(Assumptions!$B:$B,MATCH("Ground-network ops COGS (% of revenue)",Assumptions!$A$1:$A$257,0)) -> 221.1025 | E75: =E$65*INDEX(Assumptions!$B:$B,MATCH("Ground-network ops COGS (% of revenue)",Assumptions!$A$1:$A$257,0)) -> 289.50212 | F75: =F$65*INDEX(Assumptions!$B:$B,MATCH("Ground-network ops COGS (% of revenue)",Assumptions!$A$1:$A$257,0)) -> 1106.7719 | G75: =G$65*INDEX(Assumptions!$B:$B,MATCH("Ground-network ops COGS (% of revenue)",Assumptions!$A$1:$A$257,0)) -> 2186.4695 | H75: =H$65*INDEX(Assumptions!$B:$B,MATCH("Ground-network ops COGS (% of revenue)",Assumptions!$A$1:$A$257,0)) -> 3808.069 | I75: =I$65*INDEX(Assumptions!$B:$B,MATCH("Ground-network ops COGS (% of revenue)",Assumptions!$A$1:$A$257,0)) -> 4790.234 | J75: =J$65*INDEX(Assumptions!$B:$B,MATCH("Ground-network ops COGS (% of revenue)",Assumptions!$A$1:$A$257,0)) -> 5735.0848 | K75: =K$65*INDEX(Assumptions!$B:$B,MATCH("Ground-network ops COGS (% of revenue)",Assumptions!$A$1:$A$257,0)) -> 6117.2457 | ... S75: =S$65*INDEX(Assumptions!$B:$B,MATCH("Ground-network ops COGS (% of revenue)",Assumptions!$A$1:$A$257,0)) -> 7917.5601
A76: Asset insurance COGS ($mm) | D76: =D$65*INDEX(Assumptions!$B:$B,MATCH("Asset insurance COGS (% of revenue)",Assumptions!$A$1:$A$257,0)) -> 110.55125 | E76: =E$65*INDEX(Assumptions!$B:$B,MATCH("Asset insurance COGS (% of revenue)",Assumptions!$A$1:$A$257,0)) -> 144.75106 | F76: =F$65*INDEX(Assumptions!$B:$B,MATCH("Asset insurance COGS (% of revenue)",Assumptions!$A$1:$A$257,0)) -> 553.38597 | G76: =G$65*INDEX(Assumptions!$B:$B,MATCH("Asset insurance COGS (% of revenue)",Assumptions!$A$1:$A$257,0)) -> 1093.2348 | H76: =H$65*INDEX(Assumptions!$B:$B,MATCH("Asset insurance COGS (% of revenue)",Assumptions!$A$1:$A$257,0)) -> 1904.0345 | I76: =I$65*INDEX(Assumptions!$B:$B,MATCH("Asset insurance COGS (% of revenue)",Assumptions!$A$1:$A$257,0)) -> 2395.117 | J76: =J$65*INDEX(Assumptions!$B:$B,MATCH("Asset insurance COGS (% of revenue)",Assumptions!$A$1:$A$257,0)) -> 2867.5424 | K76: =K$65*INDEX(Assumptions!$B:$B,MATCH("Asset insurance COGS (% of revenue)",Assumptions!$A$1:$A$257,0)) -> 3058.6229 | ... S76: =S$65*INDEX(Assumptions!$B:$B,MATCH("Asset insurance COGS (% of revenue)",Assumptions!$A$1:$A$257,0)) -> 3958.7801
A77: Variable launch COGS ($mm) | D77: {=D$69*INDEX(Assumptions!$D:$S,MATCH("F9 variable cost per launch ($mm/launch)",Assumptions!$A$1:$A$257,0),D$5+1)+D$70*INDEX(Assumptions!$D:$S,MATCH("Starship variable cost per launch ($mm/launch)",Assumptions!$A$1:$A$257,0),D$5+1)} -> 2697.5 | E77: {=E$69*INDEX(Assumptions!$D:$S,MATCH("F9 variable cost per launch ($mm/launch)",Assumptions!$A$1:$A$257,0),E$5+1)+E$70*INDEX(Assumptions!$D:$S,MATCH("Starship variable cost per launch ($mm/launch)",Assumptions!$A$1:$A$257,0),E$5+1)} -> 2197.65 | F77: {=F$69*INDEX(Assumptions!$D:$S,MATCH("F9 variable cost per launch ($mm/launch)",Assumptions!$A$1:$A$257,0),F$5+1)+F$70*INDEX(Assumptions!$D:$S,MATCH("Starship variable cost per launch ($mm/launch)",Assumptions!$A$1:$A$257,0),F$5+1)} -> 305 | G77: {=G$69*INDEX(Assumptions!$D:$S,MATCH("F9 variable cost per launch ($mm/launch)",Assumptions!$A$1:$A$257,0),G$5+1)+G$70*INDEX(Assumptions!$D:$S,MATCH("Starship variable cost per launch ($mm/launch)",Assumptions!$A$1:$A$257,0),G$5+1)} -> 584.2 | H77: {=H$69*INDEX(Assumptions!$D:$S,MATCH("F9 variable cost per launch ($mm/launch)",Assumptions!$A$1:$A$257,0),H$5+1)+H$70*INDEX(Assumptions!$D:$S,MATCH("Starship variable cost per launch ($mm/launch)",Assumptions!$A$1:$A$257,0),H$5+1)} -> 1316.152 | I77: {=I$69*INDEX(Assumptions!$D:$S,MATCH("F9 variable cost per launch ($mm/launch)",Assumptions!$A$1:$A$257,0),I$5+1)+I$70*INDEX(Assumptions!$D:$S,MATCH("Starship variable cost per launch ($mm/launch)",Assumptions!$A$1:$A$257,0),I$5+1)} -> 1962.2938 | J77: {=J$69*INDEX(Assumptions!$D:$S,MATCH("F9 variable cost per launch ($mm/launch)",Assumptions!$A$1:$A$257,0),J$5+1)+J$70*INDEX(Assumptions!$D:$S,MATCH("Starship variable cost per launch ($mm/launch)",Assumptions!$A$1:$A$257,0),J$5+1)} -> 1923.5151 | K77: {=K$69*INDEX(Assumptions!$D:$S,MATCH("F9 variable cost per launch ($mm/launch)",Assumptions!$A$1:$A$257,0),K$5+1)+K$70*INDEX(Assumptions!$D:$S,MATCH("Starship variable cost per launch ($mm/launch)",Assumptions!$A$1:$A$257,0),K$5+1)} -> 2089.2884 | ... S77: {=S$69*INDEX(Assumptions!$D:$S,MATCH("F9 variable cost per launch ($mm/launch)",Assumptions!$A$1:$A$257,0),S$5+1)+S$70*INDEX(Assumptions!$D:$S,MATCH("Starship variable cost per launch ($mm/launch)",Assumptions!$A$1:$A$257,0),S$5+1)} -> 568.26517
A78: COGS total ($mm) | D78: =SUM(D75:D77)+D74 -> 4506.5717 | E78: =SUM(E75:E77)+E74 -> 4646.4787 | F78: =SUM(F75:F77)+F74 -> 19308.552 | G78: =SUM(G75:G77)+G74 -> 34289.054 | H78: =SUM(H75:H77)+H74 -> 55557.645 | I78: =SUM(I75:I77)+I74 -> 46865.914 | J78: =SUM(J75:J77)+J74 -> 55858.167 | K78: =SUM(K75:K77)+K74 -> 49751.194 | ... S78: =SUM(S75:S77)+S74 -> 40938.073
A79: Gross Profit ($mm) | D79: =D$65-D$78 -> 6548.5531 | E79: =E$65-E$78 -> 9828.6275 | F79: =F$65-F$78 -> 36030.044 | G79: =G$65-G$78 -> 75034.422 | H79: =H$65-H$78 -> 134845.81 | I79: =I$65-I$78 -> 192645.79 | J79: =J$65-J$78 -> 230896.07 | K79: =K$65-K$78 -> 256111.09 | ... S79: =S$65-S$78 -> 354939.93
A80: Memo: Gross Margin % | D80: =IFERROR(D$79/D$65,0) -> 0.59235451 | E80: =IFERROR(E$79/E$65,0) -> 0.6790021 | F80: =IFERROR(F$79/F$65,0) -> 0.65108345 | G80: =IFERROR(G$79/G$65,0) -> 0.68635232 | H80: =IFERROR(H$79/H$65,0) -> 0.70821093 | I80: =IFERROR(I$79/I$65,0) -> 0.80432725 | J80: =IFERROR(J$79/J$65,0) -> 0.80520544 | K80: =IFERROR(K$79/K$65,0) -> 0.83734119 | ... S80: =IFERROR(S$79/S$65,0) -> 0.89658917
A82: ▸ MODULE OpEx
A83: Sales & Marketing ($mm) | D83: =D$65*MAX(INDEX(Assumptions!$B:$B,MATCH("Sales & Marketing: end-state % (floor)",Assumptions!$A$1:$A$257,0)), INDEX(Assumptions!$B:$B,MATCH("Sales & Marketing: start % of (Starlink+Starshield+CL ext) rev",Assumptions!$A$1:$A$257,0))*(1+INDEX(Assumptions!$B:$B,MATCH("Sales & Marketing: CAGR (taper)",Assumptions!$A$1:$A$257,0)))^D$5) -> 331.65374 | E83: =E$65*MAX(INDEX(Assumptions!$B:$B,MATCH("Sales & Marketing: end-state % (floor)",Assumptions!$A$1:$A$257,0)), INDEX(Assumptions!$B:$B,MATCH("Sales & Marketing: start % of (Starlink+Starshield+CL ext) rev",Assumptions!$A$1:$A$257,0))*(1+INDEX(Assumptions!$B:$B,MATCH("Sales & Marketing: CAGR (taper)",Assumptions!$A$1:$A$257,0)))^E$5) -> 399.51293 | F83: =F$65*MAX(INDEX(Assumptions!$B:$B,MATCH("Sales & Marketing: end-state % (floor)",Assumptions!$A$1:$A$257,0)), INDEX(Assumptions!$B:$B,MATCH("Sales & Marketing: start % of (Starlink+Starshield+CL ext) rev",Assumptions!$A$1:$A$257,0))*(1+INDEX(Assumptions!$B:$B,MATCH("Sales & Marketing: CAGR (taper)",Assumptions!$A$1:$A$257,0)))^F$5) -> 1405.1576 | G83: =G$65*MAX(INDEX(Assumptions!$B:$B,MATCH("Sales & Marketing: end-state % (floor)",Assumptions!$A$1:$A$257,0)), INDEX(Assumptions!$B:$B,MATCH("Sales & Marketing: start % of (Starlink+Starshield+CL ext) rev",Assumptions!$A$1:$A$257,0))*(1+INDEX(Assumptions!$B:$B,MATCH("Sales & Marketing: CAGR (taper)",Assumptions!$A$1:$A$257,0)))^G$5) -> 2553.8664 | H83: =H$65*MAX(INDEX(Assumptions!$B:$B,MATCH("Sales & Marketing: end-state % (floor)",Assumptions!$A$1:$A$257,0)), INDEX(Assumptions!$B:$B,MATCH("Sales & Marketing: start % of (Starlink+Starshield+CL ext) rev",Assumptions!$A$1:$A$257,0))*(1+INDEX(Assumptions!$B:$B,MATCH("Sales & Marketing: CAGR (taper)",Assumptions!$A$1:$A$257,0)))^H$5) -> 4092.1108 | I83: =I$65*MAX(INDEX(Assumptions!$B:$B,MATCH("Sales & Marketing: end-state % (floor)",Assumptions!$A$1:$A$257,0)), INDEX(Assumptions!$B:$B,MATCH("Sales & Marketing: start % of (Starlink+Starshield+CL ext) rev",Assumptions!$A$1:$A$257,0))*(1+INDEX(Assumptions!$B:$B,MATCH("Sales & Marketing: CAGR (taper)",Assumptions!$A$1:$A$257,0)))^I$5) -> 4790.234 | J83: =J$65*MAX(INDEX(Assumptions!$B:$B,MATCH("Sales & Marketing: end-state % (floor)",Assumptions!$A$1:$A$257,0)), INDEX(Assumptions!$B:$B,MATCH("Sales & Marketing: start % of (Starlink+Starshield+CL ext) rev",Assumptions!$A$1:$A$257,0))*(1+INDEX(Assumptions!$B:$B,MATCH("Sales & Marketing: CAGR (taper)",Assumptions!$A$1:$A$257,0)))^J$5) -> 5735.0848 | K83: =K$65*MAX(INDEX(Assumptions!$B:$B,MATCH("Sales & Marketing: end-state % (floor)",Assumptions!$A$1:$A$257,0)), INDEX(Assumptions!$B:$B,MATCH("Sales & Marketing: start % of (Starlink+Starshield+CL ext) rev",Assumptions!$A$1:$A$257,0))*(1+INDEX(Assumptions!$B:$B,MATCH("Sales & Marketing: CAGR (taper)",Assumptions!$A$1:$A$257,0)))^K$5) -> 6117.2457 | ... S83: =S$65*MAX(INDEX(Assumptions!$B:$B,MATCH("Sales & Marketing: end-state % (floor)",Assumptions!$A$1:$A$257,0)), INDEX(Assumptions!$B:$B,MATCH("Sales & Marketing: start % of (Starlink+Starshield+CL ext) rev",Assumptions!$A$1:$A$257,0))*(1+INDEX(Assumptions!$B:$B,MATCH("Sales & Marketing: CAGR (taper)",Assumptions!$A$1:$A$257,0)))^S$5) -> 7917.5601
A84: Customer support & billing ($mm) | D84: =D$66*INDEX(Assumptions!$B:$B,MATCH("Customer Service: flat % of Starlink subscription rev",Assumptions!$A$1:$A$257,0)) -> 147.06591 | E84: =E$66*INDEX(Assumptions!$B:$B,MATCH("Customer Service: flat % of Starlink subscription rev",Assumptions!$A$1:$A$257,0)) -> 202.83919 | F84: =F$66*INDEX(Assumptions!$B:$B,MATCH("Customer Service: flat % of Starlink subscription rev",Assumptions!$A$1:$A$257,0)) -> 770.49352 | G84: =G$66*INDEX(Assumptions!$B:$B,MATCH("Customer Service: flat % of Starlink subscription rev",Assumptions!$A$1:$A$257,0)) -> 1636.1803 | H84: =H$66*INDEX(Assumptions!$B:$B,MATCH("Customer Service: flat % of Starlink subscription rev",Assumptions!$A$1:$A$257,0)) -> 2963.033 | I84: =I$66*INDEX(Assumptions!$B:$B,MATCH("Customer Service: flat % of Starlink subscription rev",Assumptions!$A$1:$A$257,0)) -> 4112.6907 | J84: =J$66*INDEX(Assumptions!$B:$B,MATCH("Customer Service: flat % of Starlink subscription rev",Assumptions!$A$1:$A$257,0)) -> 4929.7973 | K84: =K$66*INDEX(Assumptions!$B:$B,MATCH("Customer Service: flat % of Starlink subscription rev",Assumptions!$A$1:$A$257,0)) -> 5415.096 | ... S84: =S$66*INDEX(Assumptions!$B:$B,MATCH("Customer Service: flat % of Starlink subscription rev",Assumptions!$A$1:$A$257,0)) -> 7301.794
A85: Network operations ($mm) | D85: =D$65*INDEX(Assumptions!$B:$B,MATCH("Network ops & G&A (% of revenue)",Assumptions!$A$1:$A$257,0)) -> 276.37812 | E85: =E$65*INDEX(Assumptions!$B:$B,MATCH("Network ops & G&A (% of revenue)",Assumptions!$A$1:$A$257,0)) -> 361.87766 | F85: =F$65*INDEX(Assumptions!$B:$B,MATCH("Network ops & G&A (% of revenue)",Assumptions!$A$1:$A$257,0)) -> 1383.4649 | G85: =G$65*INDEX(Assumptions!$B:$B,MATCH("Network ops & G&A (% of revenue)",Assumptions!$A$1:$A$257,0)) -> 2733.0869 | H85: =H$65*INDEX(Assumptions!$B:$B,MATCH("Network ops & G&A (% of revenue)",Assumptions!$A$1:$A$257,0)) -> 4760.0863 | I85: =I$65*INDEX(Assumptions!$B:$B,MATCH("Network ops & G&A (% of revenue)",Assumptions!$A$1:$A$257,0)) -> 5987.7926 | J85: =J$65*INDEX(Assumptions!$B:$B,MATCH("Network ops & G&A (% of revenue)",Assumptions!$A$1:$A$257,0)) -> 7168.856 | K85: =K$65*INDEX(Assumptions!$B:$B,MATCH("Network ops & G&A (% of revenue)",Assumptions!$A$1:$A$257,0)) -> 7646.5571 | ... S85: =S$65*INDEX(Assumptions!$B:$B,MATCH("Network ops & G&A (% of revenue)",Assumptions!$A$1:$A$257,0)) -> 9896.9502
A86: Spectrum licence OpEx ($mm) | D86: =D$65*INDEX(Assumptions!$B:$B,MATCH("Spectrum licence OpEx (% of revenue)",Assumptions!$A$1:$A$257,0)) -> 143.71662 | E86: =E$65*INDEX(Assumptions!$B:$B,MATCH("Spectrum licence OpEx (% of revenue)",Assumptions!$A$1:$A$257,0)) -> 188.17638 | F86: =F$65*INDEX(Assumptions!$B:$B,MATCH("Spectrum licence OpEx (% of revenue)",Assumptions!$A$1:$A$257,0)) -> 719.40176 | G86: =G$65*INDEX(Assumptions!$B:$B,MATCH("Spectrum licence OpEx (% of revenue)",Assumptions!$A$1:$A$257,0)) -> 1421.2052 | H86: =H$65*INDEX(Assumptions!$B:$B,MATCH("Spectrum licence OpEx (% of revenue)",Assumptions!$A$1:$A$257,0)) -> 2475.2449 | I86: =I$65*INDEX(Assumptions!$B:$B,MATCH("Spectrum licence OpEx (% of revenue)",Assumptions!$A$1:$A$257,0)) -> 3113.6521 | J86: =J$65*INDEX(Assumptions!$B:$B,MATCH("Spectrum licence OpEx (% of revenue)",Assumptions!$A$1:$A$257,0)) -> 3727.8051 | K86: =K$65*INDEX(Assumptions!$B:$B,MATCH("Spectrum licence OpEx (% of revenue)",Assumptions!$A$1:$A$257,0)) -> 3976.2097 | ... S86: =S$65*INDEX(Assumptions!$B:$B,MATCH("Spectrum licence OpEx (% of revenue)",Assumptions!$A$1:$A$257,0)) -> 5146.4141
A87: Module OpEx total (incl. R&D) ($mm) | D87: =SUM(D83:D86)+D92 -> 1484.736 | E87: =SUM(E83:E86)+E92 -> 1842.8687 | F87: =SUM(F83:F86)+F92 -> 6654.2038 | G87: =SUM(G83:G86)+G92 -> 12568.27 | H87: =SUM(H83:H86)+H92 -> 20911.431 | I87: =SUM(I83:I86)+I92 -> 25500.12 | J87: =SUM(J83:J86)+J92 -> 30164.17 | K87: =SUM(K83:K86)+K92 -> 32330.977 | ... S87: =SUM(S83:S86)+S92 -> 42139.059
A88: Module EBITDA ($mm) | D88: =D79-D87 -> 5063.8171 | E88: =E79-E87 -> 7985.7588 | F88: =F79-F87 -> 29375.841 | G88: =G79-G87 -> 62466.152 | H88: =H79-H87 -> 113934.37 | I88: =I79-I87 -> 167145.67 | J88: =J79-J87 -> 200731.9 | K88: =K79-K87 -> 223780.11 | ... S88: =S79-S87 -> 312800.88
A89: EBITDA Margin % (memo) | D89: =IFERROR(D88/D65,0) -> 0.45805155 | E89: =IFERROR(E88/E65,0) -> 0.55168913 | F89: =IFERROR(F88/F65,0) -> 0.53083819 | G89: =IFERROR(G88/G65,0) -> 0.57138827 | H89: =IFERROR(H88/H65,0) -> 0.59838398 | I89: =IFERROR(I88/I65,0) -> 0.69786013 | J89: =IFERROR(J88/J65,0) -> 0.70001372 | K89: =IFERROR(K88/K65,0) -> 0.73163683 | ... S89: =IFERROR(S88/S65,0) -> 0.79014462
A91: ▸ EBITDA → EBIT (R&D is in Module OpEx above; only D&A below)
A92: Attributed R&D ($mm): component of Module OpEx total (row 87) | D92: =D$65*MAX(INDEX(Assumptions!$B:$B,MATCH("Starlink R&D: end-state % (floor)",Assumptions!$A$1:$A$257,0)), INDEX(Assumptions!$B:$B,MATCH("Starlink R&D: start % of (Starlink+Starshield) rev",Assumptions!$A$1:$A$257,0))*(1+INDEX(Assumptions!$B:$B,MATCH("Starlink R&D: CAGR (taper)",Assumptions!$A$1:$A$257,0)))^D$5) -> 585.92162 | E92: =E$65*MAX(INDEX(Assumptions!$B:$B,MATCH("Starlink R&D: end-state % (floor)",Assumptions!$A$1:$A$257,0)), INDEX(Assumptions!$B:$B,MATCH("Starlink R&D: start % of (Starlink+Starshield) rev",Assumptions!$A$1:$A$257,0))*(1+INDEX(Assumptions!$B:$B,MATCH("Starlink R&D: CAGR (taper)",Assumptions!$A$1:$A$257,0)))^E$5) -> 690.46257 | F92: =F$65*MAX(INDEX(Assumptions!$B:$B,MATCH("Starlink R&D: end-state % (floor)",Assumptions!$A$1:$A$257,0)), INDEX(Assumptions!$B:$B,MATCH("Starlink R&D: start % of (Starlink+Starshield) rev",Assumptions!$A$1:$A$257,0))*(1+INDEX(Assumptions!$B:$B,MATCH("Starlink R&D: CAGR (taper)",Assumptions!$A$1:$A$257,0)))^F$5) -> 2375.686 | G92: =G$65*MAX(INDEX(Assumptions!$B:$B,MATCH("Starlink R&D: end-state % (floor)",Assumptions!$A$1:$A$257,0)), INDEX(Assumptions!$B:$B,MATCH("Starlink R&D: start % of (Starlink+Starshield) rev",Assumptions!$A$1:$A$257,0))*(1+INDEX(Assumptions!$B:$B,MATCH("Starlink R&D: CAGR (taper)",Assumptions!$A$1:$A$257,0)))^G$5) -> 4223.9312 | H92: =H$65*MAX(INDEX(Assumptions!$B:$B,MATCH("Starlink R&D: end-state % (floor)",Assumptions!$A$1:$A$257,0)), INDEX(Assumptions!$B:$B,MATCH("Starlink R&D: start % of (Starlink+Starshield) rev",Assumptions!$A$1:$A$257,0))*(1+INDEX(Assumptions!$B:$B,MATCH("Starlink R&D: CAGR (taper)",Assumptions!$A$1:$A$257,0)))^H$5) -> 6620.9563 | I92: =I$65*MAX(INDEX(Assumptions!$B:$B,MATCH("Starlink R&D: end-state % (floor)",Assumptions!$A$1:$A$257,0)), INDEX(Assumptions!$B:$B,MATCH("Starlink R&D: start % of (Starlink+Starshield) rev",Assumptions!$A$1:$A$257,0))*(1+INDEX(Assumptions!$B:$B,MATCH("Starlink R&D: CAGR (taper)",Assumptions!$A$1:$A$257,0)))^I$5) -> 7495.751 | J92: =J$65*MAX(INDEX(Assumptions!$B:$B,MATCH("Starlink R&D: end-state % (floor)",Assumptions!$A$1:$A$257,0)), INDEX(Assumptions!$B:$B,MATCH("Starlink R&D: start % of (Starlink+Starshield) rev",Assumptions!$A$1:$A$257,0))*(1+INDEX(Assumptions!$B:$B,MATCH("Starlink R&D: CAGR (taper)",Assumptions!$A$1:$A$257,0)))^J$5) -> 8602.6272 | K92: =K$65*MAX(INDEX(Assumptions!$B:$B,MATCH("Starlink R&D: end-state % (floor)",Assumptions!$A$1:$A$257,0)), INDEX(Assumptions!$B:$B,MATCH("Starlink R&D: start % of (Starlink+Starshield) rev",Assumptions!$A$1:$A$257,0))*(1+INDEX(Assumptions!$B:$B,MATCH("Starlink R&D: CAGR (taper)",Assumptions!$A$1:$A$257,0)))^K$5) -> 9175.8686 | ... S92: =S$65*MAX(INDEX(Assumptions!$B:$B,MATCH("Starlink R&D: end-state % (floor)",Assumptions!$A$1:$A$257,0)), INDEX(Assumptions!$B:$B,MATCH("Starlink R&D: start % of (Starlink+Starshield) rev",Assumptions!$A$1:$A$257,0))*(1+INDEX(Assumptions!$B:$B,MATCH("Starlink R&D: CAGR (taper)",Assumptions!$A$1:$A$257,0)))^S$5) -> 11876.34
A93: Constellation D&A ($mm) | D93: =(D$40*INDEX(Assumptions!$B:$B,MATCH("Legacy V1 sat mass (kg)",Assumptions!$A$1:$A$257,0)) + D$41*INDEX(Assumptions!$B:$B,MATCH("Legacy V1.5 sat mass (kg)",Assumptions!$A$1:$A$257,0)) + D$42*INDEX(Assumptions!$B:$B,MATCH("V2 BB sat mass (kg)",Assumptions!$A$1:$A$257,0)) + D$43*INDEX(Assumptions!$B:$B,MATCH("V3 BB sat mass (kg)",Assumptions!$A$1:$A$257,0)) + D$52*INDEX(Assumptions!$B:$B,MATCH("V2 DTC sat mass (kg)",Assumptions!$A$1:$A$257,0)) + D$53*INDEX(Assumptions!$B:$B,MATCH("V3 DTC sat mass (kg)",Assumptions!$A$1:$A$257,0)) + D$135*INDEX(Assumptions!$B:$B,MATCH("Starshield sat mass (kg)",Assumptions!$A$1:$A$257,0)))*INDEX(Assumptions!$B:$B,MATCH("Satellite Dep per kg: base year ($/kg/yr)",Assumptions!$A$1:$A$257,0))/1000000 -> 550.58484 | E93: =(E$40*INDEX(Assumptions!$B:$B,MATCH("Legacy V1 sat mass (kg)",Assumptions!$A$1:$A$257,0)) + E$41*INDEX(Assumptions!$B:$B,MATCH("Legacy V1.5 sat mass (kg)",Assumptions!$A$1:$A$257,0)) + E$42*INDEX(Assumptions!$B:$B,MATCH("V2 BB sat mass (kg)",Assumptions!$A$1:$A$257,0)) + E$43*INDEX(Assumptions!$B:$B,MATCH("V3 BB sat mass (kg)",Assumptions!$A$1:$A$257,0)) + E$52*INDEX(Assumptions!$B:$B,MATCH("V2 DTC sat mass (kg)",Assumptions!$A$1:$A$257,0)) + E$53*INDEX(Assumptions!$B:$B,MATCH("V3 DTC sat mass (kg)",Assumptions!$A$1:$A$257,0)) + E$135*INDEX(Assumptions!$B:$B,MATCH("Starshield sat mass (kg)",Assumptions!$A$1:$A$257,0)))*INDEX(Assumptions!$B:$B,MATCH("Satellite Dep per kg: base year ($/kg/yr)",Assumptions!$A$1:$A$257,0))/1000000 -> 717.28501 | F93: =(F$40*INDEX(Assumptions!$B:$B,MATCH("Legacy V1 sat mass (kg)",Assumptions!$A$1:$A$257,0)) + F$41*INDEX(Assumptions!$B:$B,MATCH("Legacy V1.5 sat mass (kg)",Assumptions!$A$1:$A$257,0)) + F$42*INDEX(Assumptions!$B:$B,MATCH("V2 BB sat mass (kg)",Assumptions!$A$1:$A$257,0)) + F$43*INDEX(Assumptions!$B:$B,MATCH("V3 BB sat mass (kg)",Assumptions!$A$1:$A$257,0)) + F$52*INDEX(Assumptions!$B:$B,MATCH("V2 DTC sat mass (kg)",Assumptions!$A$1:$A$257,0)) + F$53*INDEX(Assumptions!$B:$B,MATCH("V3 DTC sat mass (kg)",Assumptions!$A$1:$A$257,0)) + F$135*INDEX(Assumptions!$B:$B,MATCH("Starshield sat mass (kg)",Assumptions!$A$1:$A$257,0)))*INDEX(Assumptions!$B:$B,MATCH("Satellite Dep per kg: base year ($/kg/yr)",Assumptions!$A$1:$A$257,0))/1000000 -> 1691.3848 | G93: =(G$40*INDEX(Assumptions!$B:$B,MATCH("Legacy V1 sat mass (kg)",Assumptions!$A$1:$A$257,0)) + G$41*INDEX(Assumptions!$B:$B,MATCH("Legacy V1.5 sat mass (kg)",Assumptions!$A$1:$A$257,0)) + G$42*INDEX(Assumptions!$B:$B,MATCH("V2 BB sat mass (kg)",Assumptions!$A$1:$A$257,0)) + G$43*INDEX(Assumptions!$B:$B,MATCH("V3 BB sat mass (kg)",Assumptions!$A$1:$A$257,0)) + G$52*INDEX(Assumptions!$B:$B,MATCH("V2 DTC sat mass (kg)",Assumptions!$A$1:$A$257,0)) + G$53*INDEX(Assumptions!$B:$B,MATCH("V3 DTC sat mass (kg)",Assumptions!$A$1:$A$257,0)) + G$135*INDEX(Assumptions!$B:$B,MATCH("Starshield sat mass (kg)",Assumptions!$A$1:$A$257,0)))*INDEX(Assumptions!$B:$B,MATCH("Satellite Dep per kg: base year ($/kg/yr)",Assumptions!$A$1:$A$257,0))/1000000 -> 3996.0452 | H93: =(H$40*INDEX(Assumptions!$B:$B,MATCH("Legacy V1 sat mass (kg)",Assumptions!$A$1:$A$257,0)) + H$41*INDEX(Assumptions!$B:$B,MATCH("Legacy V1.5 sat mass (kg)",Assumptions!$A$1:$A$257,0)) + H$42*INDEX(Assumptions!$B:$B,MATCH("V2 BB sat mass (kg)",Assumptions!$A$1:$A$257,0)) + H$43*INDEX(Assumptions!$B:$B,MATCH("V3 BB sat mass (kg)",Assumptions!$A$1:$A$257,0)) + H$52*INDEX(Assumptions!$B:$B,MATCH("V2 DTC sat mass (kg)",Assumptions!$A$1:$A$257,0)) + H$53*INDEX(Assumptions!$B:$B,MATCH("V3 DTC sat mass (kg)",Assumptions!$A$1:$A$257,0)) + H$135*INDEX(Assumptions!$B:$B,MATCH("Starshield sat mass (kg)",Assumptions!$A$1:$A$257,0)))*INDEX(Assumptions!$B:$B,MATCH("Satellite Dep per kg: base year ($/kg/yr)",Assumptions!$A$1:$A$257,0))/1000000 -> 10826.547 | I93: =(I$40*INDEX(Assumptions!$B:$B,MATCH("Legacy V1 sat mass (kg)",Assumptions!$A$1:$A$257,0)) + I$41*INDEX(Assumptions!$B:$B,MATCH("Legacy V1.5 sat mass (kg)",Assumptions!$A$1:$A$257,0)) + I$42*INDEX(Assumptions!$B:$B,MATCH("V2 BB sat mass (kg)",Assumptions!$A$1:$A$257,0)) + I$43*INDEX(Assumptions!$B:$B,MATCH("V3 BB sat mass (kg)",Assumptions!$A$1:$A$257,0)) + I$52*INDEX(Assumptions!$B:$B,MATCH("V2 DTC sat mass (kg)",Assumptions!$A$1:$A$257,0)) + I$53*INDEX(Assumptions!$B:$B,MATCH("V3 DTC sat mass (kg)",Assumptions!$A$1:$A$257,0)) + I$135*INDEX(Assumptions!$B:$B,MATCH("Starshield sat mass (kg)",Assumptions!$A$1:$A$257,0)))*INDEX(Assumptions!$B:$B,MATCH("Satellite Dep per kg: base year ($/kg/yr)",Assumptions!$A$1:$A$257,0))/1000000 -> 23663.254 | J93: =(J$40*INDEX(Assumptions!$B:$B,MATCH("Legacy V1 sat mass (kg)",Assumptions!$A$1:$A$257,0)) + J$41*INDEX(Assumptions!$B:$B,MATCH("Legacy V1.5 sat mass (kg)",Assumptions!$A$1:$A$257,0)) + J$42*INDEX(Assumptions!$B:$B,MATCH("V2 BB sat mass (kg)",Assumptions!$A$1:$A$257,0)) + J$43*INDEX(Assumptions!$B:$B,MATCH("V3 BB sat mass (kg)",Assumptions!$A$1:$A$257,0)) + J$52*INDEX(Assumptions!$B:$B,MATCH("V2 DTC sat mass (kg)",Assumptions!$A$1:$A$257,0)) + J$53*INDEX(Assumptions!$B:$B,MATCH("V3 DTC sat mass (kg)",Assumptions!$A$1:$A$257,0)) + J$135*INDEX(Assumptions!$B:$B,MATCH("Starshield sat mass (kg)",Assumptions!$A$1:$A$257,0)))*INDEX(Assumptions!$B:$B,MATCH("Satellite Dep per kg: base year ($/kg/yr)",Assumptions!$A$1:$A$257,0))/1000000 -> 37239.71 | K93: =(K$40*INDEX(Assumptions!$B:$B,MATCH("Legacy V1 sat mass (kg)",Assumptions!$A$1:$A$257,0)) + K$41*INDEX(Assumptions!$B:$B,MATCH("Legacy V1.5 sat mass (kg)",Assumptions!$A$1:$A$257,0)) + K$42*INDEX(Assumptions!$B:$B,MATCH("V2 BB sat mass (kg)",Assumptions!$A$1:$A$257,0)) + K$43*INDEX(Assumptions!$B:$B,MATCH("V3 BB sat mass (kg)",Assumptions!$A$1:$A$257,0)) + K$52*INDEX(Assumptions!$B:$B,MATCH("V2 DTC sat mass (kg)",Assumptions!$A$1:$A$257,0)) + K$53*INDEX(Assumptions!$B:$B,MATCH("V3 DTC sat mass (kg)",Assumptions!$A$1:$A$257,0)) + K$135*INDEX(Assumptions!$B:$B,MATCH("Starshield sat mass (kg)",Assumptions!$A$1:$A$257,0)))*INDEX(Assumptions!$B:$B,MATCH("Satellite Dep per kg: base year ($/kg/yr)",Assumptions!$A$1:$A$257,0))/1000000 -> 52548.234 | ... S93: =(S$40*INDEX(Assumptions!$B:$B,MATCH("Legacy V1 sat mass (kg)",Assumptions!$A$1:$A$257,0)) + S$41*INDEX(Assumptions!$B:$B,MATCH("Legacy V1.5 sat mass (kg)",Assumptions!$A$1:$A$257,0)) + S$42*INDEX(Assumptions!$B:$B,MATCH("V2 BB sat mass (kg)",Assumptions!$A$1:$A$257,0)) + S$43*INDEX(Assumptions!$B:$B,MATCH("V3 BB sat mass (kg)",Assumptions!$A$1:$A$257,0)) + S$52*INDEX(Assumptions!$B:$B,MATCH("V2 DTC sat mass (kg)",Assumptions!$A$1:$A$257,0)) + S$53*INDEX(Assumptions!$B:$B,MATCH("V3 DTC sat mass (kg)",Assumptions!$A$1:$A$257,0)) + S$135*INDEX(Assumptions!$B:$B,MATCH("Starshield sat mass (kg)",Assumptions!$A$1:$A$257,0)))*INDEX(Assumptions!$B:$B,MATCH("Satellite Dep per kg: base year ($/kg/yr)",Assumptions!$A$1:$A$257,0))/1000000 -> 87987.124
A94: Owned launch-fleet D&A ($mm) | D94: =MIN(SUM($D$103:D103), SUM($D$103:D103)/IFERROR(INDEX(Assumptions!$B:$B,MATCH("F9 booster economic life (years)",Assumptions!$A$1:$A$257,0)),8)) -> 25.538462 | E94: =MIN(SUM($D$103:E103), SUM($D$103:E103)/IFERROR(INDEX(Assumptions!$B:$B,MATCH("F9 booster economic life (years)",Assumptions!$A$1:$A$257,0)),8)) -> 43.814137 | F94: =MIN(SUM($D$103:F103), SUM($D$103:F103)/IFERROR(INDEX(Assumptions!$B:$B,MATCH("F9 booster economic life (years)",Assumptions!$A$1:$A$257,0)),8)) -> 198.66394 | G94: =MIN(SUM($D$103:G103), SUM($D$103:G103)/IFERROR(INDEX(Assumptions!$B:$B,MATCH("F9 booster economic life (years)",Assumptions!$A$1:$A$257,0)),8)) -> 425.24616 | H94: =MIN(SUM($D$103:H103), SUM($D$103:H103)/IFERROR(INDEX(Assumptions!$B:$B,MATCH("F9 booster economic life (years)",Assumptions!$A$1:$A$257,0)),8)) -> 709.81505 | I94: =MIN(SUM($D$103:I103), SUM($D$103:I103)/IFERROR(INDEX(Assumptions!$B:$B,MATCH("F9 booster economic life (years)",Assumptions!$A$1:$A$257,0)),8)) -> 997.85349 | J94: =MIN(SUM($D$103:J103), SUM($D$103:J103)/IFERROR(INDEX(Assumptions!$B:$B,MATCH("F9 booster economic life (years)",Assumptions!$A$1:$A$257,0)),8)) -> 1334.3462 | K94: =MIN(SUM($D$103:K103), SUM($D$103:K103)/IFERROR(INDEX(Assumptions!$B:$B,MATCH("F9 booster economic life (years)",Assumptions!$A$1:$A$257,0)),8)) -> 1435.9841 | ... S94: =MIN(SUM($D$103:S103), SUM($D$103:S103)/IFERROR(INDEX(Assumptions!$B:$B,MATCH("F9 booster economic life (years)",Assumptions!$A$1:$A$257,0)),8)) -> 1759.6618
A95: Launch facility share (frac) | D95: {=IFERROR((D$69+D$70)/((D$69+D$70)+(INDEX('Customer Launch'!$D:$S,MATCH("F9 customer launches per year",'Customer Launch'!$A$1:$A$153,0),D$5+1)+INDEX('Customer Launch'!$D:$S,MATCH("Starship customer launches per year",'Customer Launch'!$A$1:$A$153,0),D$5+1))),0)} -> 0.85128205 | E95: {=IFERROR((E$69+E$70)/((E$69+E$70)+(INDEX('Customer Launch'!$D:$S,MATCH("F9 customer launches per year",'Customer Launch'!$A$1:$A$153,0),E$5+1)+INDEX('Customer Launch'!$D:$S,MATCH("Starship customer launches per year",'Customer Launch'!$A$1:$A$153,0),E$5+1))),0)} -> 0.62162162 | F95: {=IFERROR((F$69+F$70)/((F$69+F$70)+(INDEX('Customer Launch'!$D:$S,MATCH("F9 customer launches per year",'Customer Launch'!$A$1:$A$153,0),F$5+1)+INDEX('Customer Launch'!$D:$S,MATCH("Starship customer launches per year",'Customer Launch'!$A$1:$A$153,0),F$5+1))),0)} -> 0.23354 | G95: {=IFERROR((G$69+G$70)/((G$69+G$70)+(INDEX('Customer Launch'!$D:$S,MATCH("F9 customer launches per year",'Customer Launch'!$A$1:$A$153,0),G$5+1)+INDEX('Customer Launch'!$D:$S,MATCH("Starship customer launches per year",'Customer Launch'!$A$1:$A$153,0),G$5+1))),0)} -> 0.36681861 | H95: {=IFERROR((H$69+H$70)/((H$69+H$70)+(INDEX('Customer Launch'!$D:$S,MATCH("F9 customer launches per year",'Customer Launch'!$A$1:$A$153,0),H$5+1)+INDEX('Customer Launch'!$D:$S,MATCH("Starship customer launches per year",'Customer Launch'!$A$1:$A$153,0),H$5+1))),0)} -> 0.56069938 | I95: {=IFERROR((I$69+I$70)/((I$69+I$70)+(INDEX('Customer Launch'!$D:$S,MATCH("F9 customer launches per year",'Customer Launch'!$A$1:$A$153,0),I$5+1)+INDEX('Customer Launch'!$D:$S,MATCH("Starship customer launches per year",'Customer Launch'!$A$1:$A$153,0),I$5+1))),0)} -> 0.65116279 | J95: {=IFERROR((J$69+J$70)/((J$69+J$70)+(INDEX('Customer Launch'!$D:$S,MATCH("F9 customer launches per year",'Customer Launch'!$A$1:$A$153,0),J$5+1)+INDEX('Customer Launch'!$D:$S,MATCH("Starship customer launches per year",'Customer Launch'!$A$1:$A$153,0),J$5+1))),0)} -> 0.66791045 | K95: {=IFERROR((K$69+K$70)/((K$69+K$70)+(INDEX('Customer Launch'!$D:$S,MATCH("F9 customer launches per year",'Customer Launch'!$A$1:$A$153,0),K$5+1)+INDEX('Customer Launch'!$D:$S,MATCH("Starship customer launches per year",'Customer Launch'!$A$1:$A$153,0),K$5+1))),0)} -> 0.6526982 | ... S95: {=IFERROR((S$69+S$70)/((S$69+S$70)+(INDEX('Customer Launch'!$D:$S,MATCH("F9 customer launches per year",'Customer Launch'!$A$1:$A$153,0),S$5+1)+INDEX('Customer Launch'!$D:$S,MATCH("Starship customer launches per year",'Customer Launch'!$A$1:$A$153,0),S$5+1))),0)} -> 0.98245614
A96: Facility / ground D&A ($mm) | D96: {=INDEX('Facilities Build'!$D:$AC,MATCH("Sat-mfg facility D&A ($mm)*",'Facilities Build'!$A$1:$A$74,0),D$5+1)+INDEX('Facilities Build'!$D:$AC,MATCH("Launch/vehicle facility D&A total ($mm)*",'Facilities Build'!$A$1:$A$74,0),D$5+1)*D$95} -> 26.26044 | E96: {=INDEX('Facilities Build'!$D:$AC,MATCH("Sat-mfg facility D&A ($mm)*",'Facilities Build'!$A$1:$A$74,0),E$5+1)+INDEX('Facilities Build'!$D:$AC,MATCH("Launch/vehicle facility D&A total ($mm)*",'Facilities Build'!$A$1:$A$74,0),E$5+1)*E$95} -> 43.29279 | F96: {=INDEX('Facilities Build'!$D:$AC,MATCH("Sat-mfg facility D&A ($mm)*",'Facilities Build'!$A$1:$A$74,0),F$5+1)+INDEX('Facilities Build'!$D:$AC,MATCH("Launch/vehicle facility D&A total ($mm)*",'Facilities Build'!$A$1:$A$74,0),F$5+1)*F$95} -> 54.346919 | G96: {=INDEX('Facilities Build'!$D:$AC,MATCH("Sat-mfg facility D&A ($mm)*",'Facilities Build'!$A$1:$A$74,0),G$5+1)+INDEX('Facilities Build'!$D:$AC,MATCH("Launch/vehicle facility D&A total ($mm)*",'Facilities Build'!$A$1:$A$74,0),G$5+1)*G$95} -> 102.76812 | H96: {=INDEX('Facilities Build'!$D:$AC,MATCH("Sat-mfg facility D&A ($mm)*",'Facilities Build'!$A$1:$A$74,0),H$5+1)+INDEX('Facilities Build'!$D:$AC,MATCH("Launch/vehicle facility D&A total ($mm)*",'Facilities Build'!$A$1:$A$74,0),H$5+1)*H$95} -> 217.93792 | I96: {=INDEX('Facilities Build'!$D:$AC,MATCH("Sat-mfg facility D&A ($mm)*",'Facilities Build'!$A$1:$A$74,0),I$5+1)+INDEX('Facilities Build'!$D:$AC,MATCH("Launch/vehicle facility D&A total ($mm)*",'Facilities Build'!$A$1:$A$74,0),I$5+1)*I$95} -> 348.61532 | J96: {=INDEX('Facilities Build'!$D:$AC,MATCH("Sat-mfg facility D&A ($mm)*",'Facilities Build'!$A$1:$A$74,0),J$5+1)+INDEX('Facilities Build'!$D:$AC,MATCH("Launch/vehicle facility D&A total ($mm)*",'Facilities Build'!$A$1:$A$74,0),J$5+1)*J$95} -> 381.27795 | K96: {=INDEX('Facilities Build'!$D:$AC,MATCH("Sat-mfg facility D&A ($mm)*",'Facilities Build'!$A$1:$A$74,0),K$5+1)+INDEX('Facilities Build'!$D:$AC,MATCH("Launch/vehicle facility D&A total ($mm)*",'Facilities Build'!$A$1:$A$74,0),K$5+1)*K$95} -> 455.77419 | ... S96: {=INDEX('Facilities Build'!$D:$AC,MATCH("Sat-mfg facility D&A ($mm)*",'Facilities Build'!$A$1:$A$74,0),S$5+1)+INDEX('Facilities Build'!$D:$AC,MATCH("Launch/vehicle facility D&A total ($mm)*",'Facilities Build'!$A$1:$A$74,0),S$5+1)*S$95} -> 1019.586
A97: D&A total ($mm) | D97: =D93+D94+D96 -> 602.38374 | E97: =E93+E94+E96 -> 804.39194 | F97: =F93+F94+F96 -> 1944.3957 | G97: =G93+G94+G96 -> 4524.0595 | H97: =H93+H94+H96 -> 11754.3 | I97: =I93+I94+I96 -> 25009.723 | J97: =J93+J94+J96 -> 38955.334 | K97: =K93+K94+K96 -> 54439.992 | ... S97: =S93+S94+S96 -> 90766.372
A98: Module EBIT ($mm) | D98: =D88-D97 -> 4461.4333 | E98: =E88-E97 -> 7181.3669 | F98: =F88-F97 -> 27431.445 | G98: =G88-G97 -> 57942.092 | H98: =H88-H97 -> 102180.08 | I98: =I88-I97 -> 142135.95 | J98: =J88-J97 -> 161776.57 | K98: =K88-K97 -> 169340.12 | ... S98: =S88-S97 -> 222034.5
A100: ▸ CAPEX → MODULE FCF
A101: Satellite build CapEx ($mm) | D101: =D$143/1000000*(D32*INDEX(Assumptions!$B:$B,MATCH("V2 BB sat mass (kg)",Assumptions!$A$1:$A$257,0)) + D33*INDEX(Assumptions!$B:$B,MATCH("V2 DTC sat mass (kg)",Assumptions!$A$1:$A$257,0)) + D34*INDEX(Assumptions!$B:$B,MATCH("V3 BB sat mass (kg)",Assumptions!$A$1:$A$257,0)) + D35*INDEX(Assumptions!$B:$B,MATCH("V3 DTC sat mass (kg)",Assumptions!$A$1:$A$257,0)) + D36*INDEX(Assumptions!$B:$B,MATCH("Starshield sat mass (kg)",Assumptions!$A$1:$A$257,0))) -> 1674.816 | E101: =E$143/1000000*(E32*INDEX(Assumptions!$B:$B,MATCH("V2 BB sat mass (kg)",Assumptions!$A$1:$A$257,0)) + E33*INDEX(Assumptions!$B:$B,MATCH("V2 DTC sat mass (kg)",Assumptions!$A$1:$A$257,0)) + E34*INDEX(Assumptions!$B:$B,MATCH("V3 BB sat mass (kg)",Assumptions!$A$1:$A$257,0)) + E35*INDEX(Assumptions!$B:$B,MATCH("V3 DTC sat mass (kg)",Assumptions!$A$1:$A$257,0)) + E36*INDEX(Assumptions!$B:$B,MATCH("Starshield sat mass (kg)",Assumptions!$A$1:$A$257,0))) -> 1405.716 | F101: =F$143/1000000*(F32*INDEX(Assumptions!$B:$B,MATCH("V2 BB sat mass (kg)",Assumptions!$A$1:$A$257,0)) + F33*INDEX(Assumptions!$B:$B,MATCH("V2 DTC sat mass (kg)",Assumptions!$A$1:$A$257,0)) + F34*INDEX(Assumptions!$B:$B,MATCH("V3 BB sat mass (kg)",Assumptions!$A$1:$A$257,0)) + F35*INDEX(Assumptions!$B:$B,MATCH("V3 DTC sat mass (kg)",Assumptions!$A$1:$A$257,0)) + F36*INDEX(Assumptions!$B:$B,MATCH("Starshield sat mass (kg)",Assumptions!$A$1:$A$257,0))) -> 5104.3212 | G101: =G$143/1000000*(G32*INDEX(Assumptions!$B:$B,MATCH("V2 BB sat mass (kg)",Assumptions!$A$1:$A$257,0)) + G33*INDEX(Assumptions!$B:$B,MATCH("V2 DTC sat mass (kg)",Assumptions!$A$1:$A$257,0)) + G34*INDEX(Assumptions!$B:$B,MATCH("V3 BB sat mass (kg)",Assumptions!$A$1:$A$257,0)) + G35*INDEX(Assumptions!$B:$B,MATCH("V3 DTC sat mass (kg)",Assumptions!$A$1:$A$257,0)) + G36*INDEX(Assumptions!$B:$B,MATCH("Starshield sat mass (kg)",Assumptions!$A$1:$A$257,0))) -> 11652.75 | H101: =H$143/1000000*(H32*INDEX(Assumptions!$B:$B,MATCH("V2 BB sat mass (kg)",Assumptions!$A$1:$A$257,0)) + H33*INDEX(Assumptions!$B:$B,MATCH("V2 DTC sat mass (kg)",Assumptions!$A$1:$A$257,0)) + H34*INDEX(Assumptions!$B:$B,MATCH("V3 BB sat mass (kg)",Assumptions!$A$1:$A$257,0)) + H35*INDEX(Assumptions!$B:$B,MATCH("V3 DTC sat mass (kg)",Assumptions!$A$1:$A$257,0)) + H36*INDEX(Assumptions!$B:$B,MATCH("Starshield sat mass (kg)",Assumptions!$A$1:$A$257,0))) -> 31260.957 | I101: =I$143/1000000*(I32*INDEX(Assumptions!$B:$B,MATCH("V2 BB sat mass (kg)",Assumptions!$A$1:$A$257,0)) + I33*INDEX(Assumptions!$B:$B,MATCH("V2 DTC sat mass (kg)",Assumptions!$A$1:$A$257,0)) + I34*INDEX(Assumptions!$B:$B,MATCH("V3 BB sat mass (kg)",Assumptions!$A$1:$A$257,0)) + I35*INDEX(Assumptions!$B:$B,MATCH("V3 DTC sat mass (kg)",Assumptions!$A$1:$A$257,0)) + I36*INDEX(Assumptions!$B:$B,MATCH("Starshield sat mass (kg)",Assumptions!$A$1:$A$257,0))) -> 54534.613 | J101: =J$143/1000000*(J32*INDEX(Assumptions!$B:$B,MATCH("V2 BB sat mass (kg)",Assumptions!$A$1:$A$257,0)) + J33*INDEX(Assumptions!$B:$B,MATCH("V2 DTC sat mass (kg)",Assumptions!$A$1:$A$257,0)) + J34*INDEX(Assumptions!$B:$B,MATCH("V3 BB sat mass (kg)",Assumptions!$A$1:$A$257,0)) + J35*INDEX(Assumptions!$B:$B,MATCH("V3 DTC sat mass (kg)",Assumptions!$A$1:$A$257,0)) + J36*INDEX(Assumptions!$B:$B,MATCH("Starshield sat mass (kg)",Assumptions!$A$1:$A$257,0))) -> 55027.371 | K101: =K$143/1000000*(K32*INDEX(Assumptions!$B:$B,MATCH("V2 BB sat mass (kg)",Assumptions!$A$1:$A$257,0)) + K33*INDEX(Assumptions!$B:$B,MATCH("V2 DTC sat mass (kg)",Assumptions!$A$1:$A$257,0)) + K34*INDEX(Assumptions!$B:$B,MATCH("V3 BB sat mass (kg)",Assumptions!$A$1:$A$257,0)) + K35*INDEX(Assumptions!$B:$B,MATCH("V3 DTC sat mass (kg)",Assumptions!$A$1:$A$257,0)) + K36*INDEX(Assumptions!$B:$B,MATCH("Starshield sat mass (kg)",Assumptions!$A$1:$A$257,0))) -> 62928.742 | ... S101: =S$143/1000000*(S32*INDEX(Assumptions!$B:$B,MATCH("V2 BB sat mass (kg)",Assumptions!$A$1:$A$257,0)) + S33*INDEX(Assumptions!$B:$B,MATCH("V2 DTC sat mass (kg)",Assumptions!$A$1:$A$257,0)) + S34*INDEX(Assumptions!$B:$B,MATCH("V3 BB sat mass (kg)",Assumptions!$A$1:$A$257,0)) + S35*INDEX(Assumptions!$B:$B,MATCH("V3 DTC sat mass (kg)",Assumptions!$A$1:$A$257,0)) + S36*INDEX(Assumptions!$B:$B,MATCH("Starshield sat mass (kg)",Assumptions!$A$1:$A$257,0))) -> 29878.413
A102: Facility / ground CapEx ($mm) | D102: {=IFERROR(INDEX('Facilities Build'!$D:$AC,MATCH("Sat-mfg facility CapEx total ($mm)*",'Facilities Build'!$A$1:$A$74,0),D$5+1),0)} -> 107.35165 | E102: {=IFERROR(INDEX('Facilities Build'!$D:$AC,MATCH("Sat-mfg facility CapEx total ($mm)*",'Facilities Build'!$A$1:$A$74,0),E$5+1),0)} -> 144.66642 | F102: {=IFERROR(INDEX('Facilities Build'!$D:$AC,MATCH("Sat-mfg facility CapEx total ($mm)*",'Facilities Build'!$A$1:$A$74,0),F$5+1),0)} -> 553.84353 | G102: {=IFERROR(INDEX('Facilities Build'!$D:$AC,MATCH("Sat-mfg facility CapEx total ($mm)*",'Facilities Build'!$A$1:$A$74,0),G$5+1),0)} -> 903.66444 | H102: {=IFERROR(INDEX('Facilities Build'!$D:$AC,MATCH("Sat-mfg facility CapEx total ($mm)*",'Facilities Build'!$A$1:$A$74,0),H$5+1),0)} -> 2274.0321 | I102: {=IFERROR(INDEX('Facilities Build'!$D:$AC,MATCH("Sat-mfg facility CapEx total ($mm)*",'Facilities Build'!$A$1:$A$74,0),I$5+1),0)} -> 2839.5809 | J102: {=IFERROR(INDEX('Facilities Build'!$D:$AC,MATCH("Sat-mfg facility CapEx total ($mm)*",'Facilities Build'!$A$1:$A$74,0),J$5+1),0)} -> 510.51626 | K102: {=IFERROR(INDEX('Facilities Build'!$D:$AC,MATCH("Sat-mfg facility CapEx total ($mm)*",'Facilities Build'!$A$1:$A$74,0),K$5+1),0)} -> 1234.8194 | ... S102: {=IFERROR(INDEX('Facilities Build'!$D:$AC,MATCH("Sat-mfg facility CapEx total ($mm)*",'Facilities Build'!$A$1:$A$74,0),S$5+1),0)} -> 74.051316
A103: Owned launch-vehicle CapEx ($mm) | D103: {=IFERROR(D69/INDEX('Vehicle Build'!$D:$AC,MATCH("Memo: Total F9 launches (internal + customer)",'Vehicle Build'!$A$1:$A$119,0),D$5+1),0)*INDEX('Vehicle Build'!$D:$AC,MATCH("F9 boosters built per year",'Vehicle Build'!$A$1:$A$119,0),D$5+1)*INDEX(Assumptions!$B:$B,MATCH("F9 booster (1st stage) mfg cost ($mm/unit)",Assumptions!$A$1:$A$257,0))*(1-INDEX(Assumptions!$B:$B,MATCH("F9 Wright's Law mfg learning rate",Assumptions!$A$1:$A$257,0)))^D$5+IFERROR(D70/INDEX('Vehicle Build'!$D:$AC,MATCH("Starship launches per year",'Vehicle Build'!$A$1:$A$119,0),D$5+1),0)*INDEX('Vehicle Build'!$D:$AC,MATCH("Total Starship build CapEx ($mm)",'Vehicle Build'!$A$1:$A$119,0),D$5+1)} -> 204.30769 | E103: {=IFERROR(E69/INDEX('Vehicle Build'!$D:$AC,MATCH("Memo: Total F9 launches (internal + customer)",'Vehicle Build'!$A$1:$A$119,0),E$5+1),0)*INDEX('Vehicle Build'!$D:$AC,MATCH("F9 boosters built per year",'Vehicle Build'!$A$1:$A$119,0),E$5+1)*INDEX(Assumptions!$B:$B,MATCH("F9 booster (1st stage) mfg cost ($mm/unit)",Assumptions!$A$1:$A$257,0))*(1-INDEX(Assumptions!$B:$B,MATCH("F9 Wright's Law mfg learning rate",Assumptions!$A$1:$A$257,0)))^E$5+IFERROR(E70/INDEX('Vehicle Build'!$D:$AC,MATCH("Starship launches per year",'Vehicle Build'!$A$1:$A$119,0),E$5+1),0)*INDEX('Vehicle Build'!$D:$AC,MATCH("Total Starship build CapEx ($mm)",'Vehicle Build'!$A$1:$A$119,0),E$5+1)} -> 146.20541 | F103: {=IFERROR(F69/INDEX('Vehicle Build'!$D:$AC,MATCH("Memo: Total F9 launches (internal + customer)",'Vehicle Build'!$A$1:$A$119,0),F$5+1),0)*INDEX('Vehicle Build'!$D:$AC,MATCH("F9 boosters built per year",'Vehicle Build'!$A$1:$A$119,0),F$5+1)*INDEX(Assumptions!$B:$B,MATCH("F9 booster (1st stage) mfg cost ($mm/unit)",Assumptions!$A$1:$A$257,0))*(1-INDEX(Assumptions!$B:$B,MATCH("F9 Wright's Law mfg learning rate",Assumptions!$A$1:$A$257,0)))^F$5+IFERROR(F70/INDEX('Vehicle Build'!$D:$AC,MATCH("Starship launches per year",'Vehicle Build'!$A$1:$A$119,0),F$5+1),0)*INDEX('Vehicle Build'!$D:$AC,MATCH("Total Starship build CapEx ($mm)",'Vehicle Build'!$A$1:$A$119,0),F$5+1)} -> 1238.7984 | G103: {=IFERROR(G69/INDEX('Vehicle Build'!$D:$AC,MATCH("Memo: Total F9 launches (internal + customer)",'Vehicle Build'!$A$1:$A$119,0),G$5+1),0)*INDEX('Vehicle Build'!$D:$AC,MATCH("F9 boosters built per year",'Vehicle Build'!$A$1:$A$119,0),G$5+1)*INDEX(Assumptions!$B:$B,MATCH("F9 booster (1st stage) mfg cost ($mm/unit)",Assumptions!$A$1:$A$257,0))*(1-INDEX(Assumptions!$B:$B,MATCH("F9 Wright's Law mfg learning rate",Assumptions!$A$1:$A$257,0)))^G$5+IFERROR(G70/INDEX('Vehicle Build'!$D:$AC,MATCH("Starship launches per year",'Vehicle Build'!$A$1:$A$119,0),G$5+1),0)*INDEX('Vehicle Build'!$D:$AC,MATCH("Total Starship build CapEx ($mm)",'Vehicle Build'!$A$1:$A$119,0),G$5+1)} -> 1812.6578 | H103: {=IFERROR(H69/INDEX('Vehicle Build'!$D:$AC,MATCH("Memo: Total F9 launches (internal + customer)",'Vehicle Build'!$A$1:$A$119,0),H$5+1),0)*INDEX('Vehicle Build'!$D:$AC,MATCH("F9 boosters built per year",'Vehicle Build'!$A$1:$A$119,0),H$5+1)*INDEX(Assumptions!$B:$B,MATCH("F9 booster (1st stage) mfg cost ($mm/unit)",Assumptions!$A$1:$A$257,0))*(1-INDEX(Assumptions!$B:$B,MATCH("F9 Wright's Law mfg learning rate",Assumptions!$A$1:$A$257,0)))^H$5+IFERROR(H70/INDEX('Vehicle Build'!$D:$AC,MATCH("Starship launches per year",'Vehicle Build'!$A$1:$A$119,0),H$5+1),0)*INDEX('Vehicle Build'!$D:$AC,MATCH("Total Starship build CapEx ($mm)",'Vehicle Build'!$A$1:$A$119,0),H$5+1)} -> 2276.5511 | I103: {=IFERROR(I69/INDEX('Vehicle Build'!$D:$AC,MATCH("Memo: Total F9 launches (internal + customer)",'Vehicle Build'!$A$1:$A$119,0),I$5+1),0)*INDEX('Vehicle Build'!$D:$AC,MATCH("F9 boosters built per year",'Vehicle Build'!$A$1:$A$119,0),I$5+1)*INDEX(Assumptions!$B:$B,MATCH("F9 booster (1st stage) mfg cost ($mm/unit)",Assumptions!$A$1:$A$257,0))*(1-INDEX(Assumptions!$B:$B,MATCH("F9 Wright's Law mfg learning rate",Assumptions!$A$1:$A$257,0)))^I$5+IFERROR(I70/INDEX('Vehicle Build'!$D:$AC,MATCH("Starship launches per year",'Vehicle Build'!$A$1:$A$119,0),I$5+1),0)*INDEX('Vehicle Build'!$D:$AC,MATCH("Total Starship build CapEx ($mm)",'Vehicle Build'!$A$1:$A$119,0),I$5+1)} -> 2304.3075 | J103: {=IFERROR(J69/INDEX('Vehicle Build'!$D:$AC,MATCH("Memo: Total F9 launches (internal + customer)",'Vehicle Build'!$A$1:$A$119,0),J$5+1),0)*INDEX('Vehicle Build'!$D:$AC,MATCH("F9 boosters built per year",'Vehicle Build'!$A$1:$A$119,0),J$5+1)*INDEX(Assumptions!$B:$B,MATCH("F9 booster (1st stage) mfg cost ($mm/unit)",Assumptions!$A$1:$A$257,0))*(1-INDEX(Assumptions!$B:$B,MATCH("F9 Wright's Law mfg learning rate",Assumptions!$A$1:$A$257,0)))^J$5+IFERROR(J70/INDEX('Vehicle Build'!$D:$AC,MATCH("Starship launches per year",'Vehicle Build'!$A$1:$A$119,0),J$5+1),0)*INDEX('Vehicle Build'!$D:$AC,MATCH("Total Starship build CapEx ($mm)",'Vehicle Build'!$A$1:$A$119,0),J$5+1)} -> 2691.9414 | K103: {=IFERROR(K69/INDEX('Vehicle Build'!$D:$AC,MATCH("Memo: Total F9 launches (internal + customer)",'Vehicle Build'!$A$1:$A$119,0),K$5+1),0)*INDEX('Vehicle Build'!$D:$AC,MATCH("F9 boosters built per year",'Vehicle Build'!$A$1:$A$119,0),K$5+1)*INDEX(Assumptions!$B:$B,MATCH("F9 booster (1st stage) mfg cost ($mm/unit)",Assumptions!$A$1:$A$257,0))*(1-INDEX(Assumptions!$B:$B,MATCH("F9 Wright's Law mfg learning rate",Assumptions!$A$1:$A$257,0)))^K$5+IFERROR(K70/INDEX('Vehicle Build'!$D:$AC,MATCH("Starship launches per year",'Vehicle Build'!$A$1:$A$119,0),K$5+1),0)*INDEX('Vehicle Build'!$D:$AC,MATCH("Total Starship build CapEx ($mm)",'Vehicle Build'!$A$1:$A$119,0),K$5+1)} -> 813.10378 | ... S103: {=IFERROR(S69/INDEX('Vehicle Build'!$D:$AC,MATCH("Memo: Total F9 launches (internal + customer)",'Vehicle Build'!$A$1:$A$119,0),S$5+1),0)*INDEX('Vehicle Build'!$D:$AC,MATCH("F9 boosters built per year",'Vehicle Build'!$A$1:$A$119,0),S$5+1)*INDEX(Assumptions!$B:$B,MATCH("F9 booster (1st stage) mfg cost ($mm/unit)",Assumptions!$A$1:$A$257,0))*(1-INDEX(Assumptions!$B:$B,MATCH("F9 Wright's Law mfg learning rate",Assumptions!$A$1:$A$257,0)))^S$5+IFERROR(S70/INDEX('Vehicle Build'!$D:$AC,MATCH("Starship launches per year",'Vehicle Build'!$A$1:$A$119,0),S$5+1),0)*INDEX('Vehicle Build'!$D:$AC,MATCH("Total Starship build CapEx ($mm)",'Vehicle Build'!$A$1:$A$119,0),S$5+1)} -> 372.183
A104: Working capital ΔWC ($mm) | D104: =(D32+D33+D34+D35+D36)*INDEX(Assumptions!$B:$B,MATCH("Working capital per sat ($mm/sat): ΔWC T0",Assumptions!$A$1:$A$257,0)) -> 21.504 | E104: =(E32+E33+E34+E35+E36)*INDEX(Assumptions!$B:$B,MATCH("Working capital per sat ($mm/sat): ΔWC T0",Assumptions!$A$1:$A$257,0)) -> 17.904 | F104: =(F32+F33+F34+F35+F36)*INDEX(Assumptions!$B:$B,MATCH("Working capital per sat ($mm/sat): ΔWC T0",Assumptions!$A$1:$A$257,0)) -> 21.897677 | G104: =(G32+G33+G34+G35+G36)*INDEX(Assumptions!$B:$B,MATCH("Working capital per sat ($mm/sat): ΔWC T0",Assumptions!$A$1:$A$257,0)) -> 49.7909 | H104: =(H32+H33+H34+H35+H36)*INDEX(Assumptions!$B:$B,MATCH("Working capital per sat ($mm/sat): ΔWC T0",Assumptions!$A$1:$A$257,0)) -> 137.42152 | I104: =(I32+I33+I34+I35+I36)*INDEX(Assumptions!$B:$B,MATCH("Working capital per sat ($mm/sat): ΔWC T0",Assumptions!$A$1:$A$257,0)) -> 254.0016 | J104: =(J32+J33+J34+J35+J36)*INDEX(Assumptions!$B:$B,MATCH("Working capital per sat ($mm/sat): ΔWC T0",Assumptions!$A$1:$A$257,0)) -> 270.30716 | K104: =(K32+K33+K34+K35+K36)*INDEX(Assumptions!$B:$B,MATCH("Working capital per sat ($mm/sat): ΔWC T0",Assumptions!$A$1:$A$257,0)) -> 319.03517 | ... S104: =(S32+S33+S34+S35+S36)*INDEX(Assumptions!$B:$B,MATCH("Working capital per sat ($mm/sat): ΔWC T0",Assumptions!$A$1:$A$257,0)) -> 170.28897
A105: Module CapEx total ($mm) | D105: =SUM(D101:D104) -> 2007.9793 | E105: =SUM(E101:E104) -> 1714.4918 | F105: =SUM(F101:F104) -> 6918.8609 | G105: =SUM(G101:G104) -> 14418.863 | H105: =SUM(H101:H104) -> 35948.962 | I105: =SUM(I101:I104) -> 59932.503 | J105: =SUM(J101:J104) -> 58500.136 | K105: =SUM(K101:K104) -> 65295.701 | ... S105: =SUM(S101:S104) -> 30494.936
A106: Module FCF ($mm) | D106: =D98+D97-D105 -> 3055.8377 | E106: =E98+E97-E105 -> 6271.267 | F106: =F98+F97-F105 -> 22456.98 | G106: =G98+G97-G105 -> 48047.289 | H106: =H98+H97-H105 -> 77985.413 | I106: =I98+I97-I105 -> 107213.17 | J106: =J98+J97-J105 -> 142231.77 | K106: =K98+K97-K105 -> 158484.41 | ... S106: =S98+S97-S105 -> 282305.94
A108: ▸ PER-SAT IRR ENGINE (v4 canonical): per cohort, one cost base
A109: Avg $/Gbps BB at Q (price-at-Q) | D109: {=INDEX('Demand Curves'!$D:$AC,MATCH("Memo: Average $/Gbps BB from curve",'Demand Curves'!$A$1:$A$167,0),COLUMN()-COLUMN($D109)+1)} -> 13740.781 | E109: {=INDEX('Demand Curves'!$D:$AC,MATCH("Memo: Average $/Gbps BB from curve",'Demand Curves'!$A$1:$A$167,0),COLUMN()-COLUMN($D109)+1)} -> 12352.493 | F109: {=INDEX('Demand Curves'!$D:$AC,MATCH("Memo: Average $/Gbps BB from curve",'Demand Curves'!$A$1:$A$167,0),COLUMN()-COLUMN($D109)+1)} -> 8072.9202 | G109: {=INDEX('Demand Curves'!$D:$AC,MATCH("Memo: Average $/Gbps BB from curve",'Demand Curves'!$A$1:$A$167,0),COLUMN()-COLUMN($D109)+1)} -> 5788.5494 | H109: {=INDEX('Demand Curves'!$D:$AC,MATCH("Memo: Average $/Gbps BB from curve",'Demand Curves'!$A$1:$A$167,0),COLUMN()-COLUMN($D109)+1)} -> 3739.5549 | I109: {=INDEX('Demand Curves'!$D:$AC,MATCH("Memo: Average $/Gbps BB from curve",'Demand Curves'!$A$1:$A$167,0),COLUMN()-COLUMN($D109)+1)} -> 3275.3092 | J109: {=INDEX('Demand Curves'!$D:$AC,MATCH("Memo: Average $/Gbps BB from curve",'Demand Curves'!$A$1:$A$167,0),COLUMN()-COLUMN($D109)+1)} -> 2528.8542 | K109: {=INDEX('Demand Curves'!$D:$AC,MATCH("Memo: Average $/Gbps BB from curve",'Demand Curves'!$A$1:$A$167,0),COLUMN()-COLUMN($D109)+1)} -> 2360.4981 | ... S109: {=INDEX('Demand Curves'!$D:$AC,MATCH("Memo: Average $/Gbps BB from curve",'Demand Curves'!$A$1:$A$167,0),COLUMN()-COLUMN($D109)+1)} -> 1612.6879
A110: Avg $/Gbps DTC at Q (price-at-Q) | D110: {=INDEX('Demand Curves'!$D:$AC,MATCH("Memo: Average $/Gbps DTC from curve",'Demand Curves'!$A$1:$A$167,0),COLUMN()-COLUMN($D110)+1)} -> 1094104.6 | E110: {=INDEX('Demand Curves'!$D:$AC,MATCH("Memo: Average $/Gbps DTC from curve",'Demand Curves'!$A$1:$A$167,0),COLUMN()-COLUMN($D110)+1)} -> 1375055.1 | F110: {=INDEX('Demand Curves'!$D:$AC,MATCH("Memo: Average $/Gbps DTC from curve",'Demand Curves'!$A$1:$A$167,0),COLUMN()-COLUMN($D110)+1)} -> 1672541.1 | G110: {=INDEX('Demand Curves'!$D:$AC,MATCH("Memo: Average $/Gbps DTC from curve",'Demand Curves'!$A$1:$A$167,0),COLUMN()-COLUMN($D110)+1)} -> 1986770.8 | H110: {=INDEX('Demand Curves'!$D:$AC,MATCH("Memo: Average $/Gbps DTC from curve",'Demand Curves'!$A$1:$A$167,0),COLUMN()-COLUMN($D110)+1)} -> 2316196.8 | I110: {=INDEX('Demand Curves'!$D:$AC,MATCH("Memo: Average $/Gbps DTC from curve",'Demand Curves'!$A$1:$A$167,0),COLUMN()-COLUMN($D110)+1)} -> 982807.67 | J110: {=INDEX('Demand Curves'!$D:$AC,MATCH("Memo: Average $/Gbps DTC from curve",'Demand Curves'!$A$1:$A$167,0),COLUMN()-COLUMN($D110)+1)} -> 736820.1 | K110: {=INDEX('Demand Curves'!$D:$AC,MATCH("Memo: Average $/Gbps DTC from curve",'Demand Curves'!$A$1:$A$167,0),COLUMN()-COLUMN($D110)+1)} -> 509900.66 | ... S110: {=INDEX('Demand Curves'!$D:$AC,MATCH("Memo: Average $/Gbps DTC from curve",'Demand Curves'!$A$1:$A$167,0),COLUMN()-COLUMN($D110)+1)} -> 449845.43
A112: V2 BB: margin per sat-yr ($mm) | D112: =IFERROR(D$109*INDEX(Assumptions!$B:$B,MATCH("V2 BB Gbps per sat",Assumptions!$A$1:$A$257,0))*D$21/1000000*(1-(D$87+D$75+D$76)/D$65) - INDEX(Assumptions!$B:$B,MATCH("Bandwidth/peering cost per Gbps ($mm/Gbps-yr)",Assumptions!$A$1:$A$257,0))*INDEX(Assumptions!$B:$B,MATCH("V2 BB Gbps per sat",Assumptions!$A$1:$A$257,0))*D$21, 0) -> 0.63726633 | E112: =IFERROR(E$109*INDEX(Assumptions!$B:$B,MATCH("V2 BB Gbps per sat",Assumptions!$A$1:$A$257,0))*E$21/1000000*(1-(E$87+E$75+E$76)/E$65) - INDEX(Assumptions!$B:$B,MATCH("Bandwidth/peering cost per Gbps ($mm/Gbps-yr)",Assumptions!$A$1:$A$257,0))*INDEX(Assumptions!$B:$B,MATCH("V2 BB Gbps per sat",Assumptions!$A$1:$A$257,0))*E$21, 0) -> 0.56510402 | F112: =IFERROR(F$109*INDEX(Assumptions!$B:$B,MATCH("V2 BB Gbps per sat",Assumptions!$A$1:$A$257,0))*F$21/1000000*(1-(F$87+F$75+F$76)/F$65) - INDEX(Assumptions!$B:$B,MATCH("Bandwidth/peering cost per Gbps ($mm/Gbps-yr)",Assumptions!$A$1:$A$257,0))*INDEX(Assumptions!$B:$B,MATCH("V2 BB Gbps per sat",Assumptions!$A$1:$A$257,0))*F$21, 0) -> 0.32659215 | G112: =IFERROR(G$109*INDEX(Assumptions!$B:$B,MATCH("V2 BB Gbps per sat",Assumptions!$A$1:$A$257,0))*G$21/1000000*(1-(G$87+G$75+G$76)/G$65) - INDEX(Assumptions!$B:$B,MATCH("Bandwidth/peering cost per Gbps ($mm/Gbps-yr)",Assumptions!$A$1:$A$257,0))*INDEX(Assumptions!$B:$B,MATCH("V2 BB Gbps per sat",Assumptions!$A$1:$A$257,0))*G$21, 0) -> 0.19820088 | H112: =IFERROR(H$109*INDEX(Assumptions!$B:$B,MATCH("V2 BB Gbps per sat",Assumptions!$A$1:$A$257,0))*H$21/1000000*(1-(H$87+H$75+H$76)/H$65) - INDEX(Assumptions!$B:$B,MATCH("Bandwidth/peering cost per Gbps ($mm/Gbps-yr)",Assumptions!$A$1:$A$257,0))*INDEX(Assumptions!$B:$B,MATCH("V2 BB Gbps per sat",Assumptions!$A$1:$A$257,0))*H$21, 0) -> 0.081759844 | I112: =IFERROR(I$109*INDEX(Assumptions!$B:$B,MATCH("V2 BB Gbps per sat",Assumptions!$A$1:$A$257,0))*I$21/1000000*(1-(I$87+I$75+I$76)/I$65) - INDEX(Assumptions!$B:$B,MATCH("Bandwidth/peering cost per Gbps ($mm/Gbps-yr)",Assumptions!$A$1:$A$257,0))*INDEX(Assumptions!$B:$B,MATCH("V2 BB Gbps per sat",Assumptions!$A$1:$A$257,0))*I$21, 0) -> 0.055664261 | J112: =IFERROR(J$109*INDEX(Assumptions!$B:$B,MATCH("V2 BB Gbps per sat",Assumptions!$A$1:$A$257,0))*J$21/1000000*(1-(J$87+J$75+J$76)/J$65) - INDEX(Assumptions!$B:$B,MATCH("Bandwidth/peering cost per Gbps ($mm/Gbps-yr)",Assumptions!$A$1:$A$257,0))*INDEX(Assumptions!$B:$B,MATCH("V2 BB Gbps per sat",Assumptions!$A$1:$A$257,0))*J$21, 0) -> 0.012564656 | K112: =IFERROR(K$109*INDEX(Assumptions!$B:$B,MATCH("V2 BB Gbps per sat",Assumptions!$A$1:$A$257,0))*K$21/1000000*(1-(K$87+K$75+K$76)/K$65) - INDEX(Assumptions!$B:$B,MATCH("Bandwidth/peering cost per Gbps ($mm/Gbps-yr)",Assumptions!$A$1:$A$257,0))*INDEX(Assumptions!$B:$B,MATCH("V2 BB Gbps per sat",Assumptions!$A$1:$A$257,0))*K$21, 0) -> 0.0026993015 | ... S112: =IFERROR(S$109*INDEX(Assumptions!$B:$B,MATCH("V2 BB Gbps per sat",Assumptions!$A$1:$A$257,0))*S$21/1000000*(1-(S$87+S$75+S$76)/S$65) - INDEX(Assumptions!$B:$B,MATCH("Bandwidth/peering cost per Gbps ($mm/Gbps-yr)",Assumptions!$A$1:$A$257,0))*INDEX(Assumptions!$B:$B,MATCH("V2 BB Gbps per sat",Assumptions!$A$1:$A$257,0))*S$21, 0) -> -0.040814226
A113: V2 BB: CapEx slug per sat ($mm) | D113: =D$143*INDEX(Assumptions!$B:$B,MATCH("V2 BB sat mass (kg)",Assumptions!$A$1:$A$257,0))/1000000 + IFERROR(D$13/INDEX(Assumptions!$B:$B,MATCH("F9 sats per launch (V2 packing)",Assumptions!$A$1:$A$257,0)),0) + INDEX(Assumptions!$B:$B,MATCH("Working capital per sat ($mm/sat): ΔWC T0",Assumptions!$A$1:$A$257,0)) -> 1.1479808 | E113: =E$143*INDEX(Assumptions!$B:$B,MATCH("V2 BB sat mass (kg)",Assumptions!$A$1:$A$257,0))/1000000 + IFERROR(E$13/INDEX(Assumptions!$B:$B,MATCH("F9 sats per launch (V2 packing)",Assumptions!$A$1:$A$257,0)),0) + IFERROR(SUM($D$102:D102)/D142,0) + INDEX(Assumptions!$B:$B,MATCH("Working capital per sat ($mm/sat): ΔWC T0",Assumptions!$A$1:$A$257,0)) -> 1.1605523 | F113: =F$143*INDEX(Assumptions!$B:$B,MATCH("V2 BB sat mass (kg)",Assumptions!$A$1:$A$257,0))/1000000 + IFERROR(F$13/INDEX(Assumptions!$B:$B,MATCH("F9 sats per launch (V2 packing)",Assumptions!$A$1:$A$257,0)),0) + IFERROR(SUM($D$102:E102)/E142,0) + INDEX(Assumptions!$B:$B,MATCH("Working capital per sat ($mm/sat): ΔWC T0",Assumptions!$A$1:$A$257,0)) -> 1.1376372 | G113: =G$143*INDEX(Assumptions!$B:$B,MATCH("V2 BB sat mass (kg)",Assumptions!$A$1:$A$257,0))/1000000 + IFERROR(G$13/INDEX(Assumptions!$B:$B,MATCH("F9 sats per launch (V2 packing)",Assumptions!$A$1:$A$257,0)),0) + IFERROR(SUM($D$102:F102)/F142,0) + INDEX(Assumptions!$B:$B,MATCH("Working capital per sat ($mm/sat): ΔWC T0",Assumptions!$A$1:$A$257,0)) -> 1.1491075 | H113: =H$143*INDEX(Assumptions!$B:$B,MATCH("V2 BB sat mass (kg)",Assumptions!$A$1:$A$257,0))/1000000 + IFERROR(H$13/INDEX(Assumptions!$B:$B,MATCH("F9 sats per launch (V2 packing)",Assumptions!$A$1:$A$257,0)),0) + IFERROR(SUM($D$102:G102)/G142,0) + INDEX(Assumptions!$B:$B,MATCH("Working capital per sat ($mm/sat): ΔWC T0",Assumptions!$A$1:$A$257,0)) -> 1.1287272 | I113: =I$143*INDEX(Assumptions!$B:$B,MATCH("V2 BB sat mass (kg)",Assumptions!$A$1:$A$257,0))/1000000 + IFERROR(I$13/INDEX(Assumptions!$B:$B,MATCH("F9 sats per launch (V2 packing)",Assumptions!$A$1:$A$257,0)),0) + IFERROR(SUM($D$102:H102)/H142,0) + INDEX(Assumptions!$B:$B,MATCH("Working capital per sat ($mm/sat): ΔWC T0",Assumptions!$A$1:$A$257,0)) -> 1.0946725 | J113: =J$143*INDEX(Assumptions!$B:$B,MATCH("V2 BB sat mass (kg)",Assumptions!$A$1:$A$257,0))/1000000 + IFERROR(J$13/INDEX(Assumptions!$B:$B,MATCH("F9 sats per launch (V2 packing)",Assumptions!$A$1:$A$257,0)),0) + IFERROR(SUM($D$102:I102)/I142,0) + INDEX(Assumptions!$B:$B,MATCH("Working capital per sat ($mm/sat): ΔWC T0",Assumptions!$A$1:$A$257,0)) -> 1.0503739 | K113: =K$143*INDEX(Assumptions!$B:$B,MATCH("V2 BB sat mass (kg)",Assumptions!$A$1:$A$257,0))/1000000 + IFERROR(K$13/INDEX(Assumptions!$B:$B,MATCH("F9 sats per launch (V2 packing)",Assumptions!$A$1:$A$257,0)),0) + IFERROR(SUM($D$102:J102)/J142,0) + INDEX(Assumptions!$B:$B,MATCH("Working capital per sat ($mm/sat): ΔWC T0",Assumptions!$A$1:$A$257,0)) -> 1.0060425 | L113: =L$143*INDEX(Assumptions!$B:$B,MATCH("V2 BB sat mass (kg)",Assumptions!$A$1:$A$257,0))/1000000 + IFERROR(L$13/INDEX(Assumptions!$B:$B,MATCH("F9 sats per launch (V2 packing)",Assumptions!$A$1:$A$257,0)),0) + IFERROR(SUM($D$102:K102)/K142,0) + INDEX(Assumptions!$B:$B,MATCH("Working capital per sat ($mm/sat): ΔWC T0",Assumptions!$A$1:$A$257,0)) -> 0.97683744 | ... S113: =S$143*INDEX(Assumptions!$B:$B,MATCH("V2 BB sat mass (kg)",Assumptions!$A$1:$A$257,0))/1000000 + IFERROR(S$13/INDEX(Assumptions!$B:$B,MATCH("F9 sats per launch (V2 packing)",Assumptions!$A$1:$A$257,0)),0) + IFERROR(SUM($D$102:R102)/R142,0) + INDEX(Assumptions!$B:$B,MATCH("Working capital per sat ($mm/sat): ΔWC T0",Assumptions!$A$1:$A$257,0)) -> 0.85254664
A114: V2 BB: Spot IRR | D114: =IFERROR(MIN(3, IFERROR(RATE(D$15,D112,-D113,0,0,0.1), IFERROR(RATE(D$15,D112,-D113,0,0,0.5), RATE(D$15,D112,-D113,0,0,1.5)))), IF(D112*D$15>D113,3,0)) -> 0.47583253 | E114: =IFERROR(MIN(3, IFERROR(RATE(E$15,E112,-E113,0,0,0.1), IFERROR(RATE(E$15,E112,-E113,0,0,0.5), RATE(E$15,E112,-E113,0,0,1.5)))), IF(E112*E$15>E113,3,0)) -> 0.39463571 | F114: =IFERROR(MIN(3, IFERROR(RATE(F$15,F112,-F113,0,0,0.1), IFERROR(RATE(F$15,F112,-F113,0,0,0.5), RATE(F$15,F112,-F113,0,0,1.5)))), IF(F112*F$15>F113,3,0)) -> 0.13397824 | G114: =IFERROR(MIN(3, IFERROR(RATE(G$15,G112,-G113,0,0,0.1), IFERROR(RATE(G$15,G112,-G113,0,0,0.5), RATE(G$15,G112,-G113,0,0,1.5)))), IF(G112*G$15>G113,3,0)) -> -0.047395198 | H114: =IFERROR(MIN(3, IFERROR(RATE(H$15,H112,-H113,0,0,0.1), IFERROR(RATE(H$15,H112,-H113,0,0,0.5), RATE(H$15,H112,-H113,0,0,1.5)))), IF(H112*H$15>H113,3,0)) -> -0.26480579 | I114: =IFERROR(MIN(3, IFERROR(RATE(I$15,I112,-I113,0,0,0.1), IFERROR(RATE(I$15,I112,-I113,0,0,0.5), RATE(I$15,I112,-I113,0,0,1.5)))), IF(I112*I$15>I113,3,0)) -> -0.33229228 | J114: =IFERROR(MIN(3, IFERROR(RATE(J$15,J112,-J113,0,0,0.1), IFERROR(RATE(J$15,J112,-J113,0,0,0.5), RATE(J$15,J112,-J113,0,0,1.5)))), IF(J112*J$15>J113,3,0)) -> -0.53433247 | K114: =IFERROR(MIN(3, IFERROR(RATE(K$15,K112,-K113,0,0,0.1), IFERROR(RATE(K$15,K112,-K113,0,0,0.5), RATE(K$15,K112,-K113,0,0,1.5)))), IF(K112*K$15>K113,3,0)) -> -0.66860561 | ... S114: =IFERROR(MIN(3, IFERROR(RATE(S$15,S112,-S113,0,0,0.1), IFERROR(RATE(S$15,S112,-S113,0,0,0.5), RATE(S$15,S112,-S113,0,0,1.5)))), IF(S112*S$15>S113,3,0)) -> 0
A118: V2 DTC: margin per sat-yr ($mm) | D118: =IFERROR(D$110*INDEX(Assumptions!$B:$B,MATCH("Effective DTC Gbps per sat (revenue calibration)",Assumptions!$A$1:$A$257,0))*D$21/1000000*(1-(D$87+D$75+D$76)/D$65) - INDEX(Assumptions!$B:$B,MATCH("Bandwidth/peering cost per Gbps ($mm/Gbps-yr)",Assumptions!$A$1:$A$257,0))*INDEX(Assumptions!$B:$B,MATCH("Effective DTC Gbps per sat (revenue calibration)",Assumptions!$A$1:$A$257,0))*D$21, 0) -> 0.56327872 | E118: =IFERROR(E$110*INDEX(Assumptions!$B:$B,MATCH("Effective DTC Gbps per sat (revenue calibration)",Assumptions!$A$1:$A$257,0))*E$21/1000000*(1-(E$87+E$75+E$76)/E$65) - INDEX(Assumptions!$B:$B,MATCH("Bandwidth/peering cost per Gbps ($mm/Gbps-yr)",Assumptions!$A$1:$A$257,0))*INDEX(Assumptions!$B:$B,MATCH("Effective DTC Gbps per sat (revenue calibration)",Assumptions!$A$1:$A$257,0))*E$21, 0) -> 0.71417195 | F118: =IFERROR(F$110*INDEX(Assumptions!$B:$B,MATCH("Effective DTC Gbps per sat (revenue calibration)",Assumptions!$A$1:$A$257,0))*F$21/1000000*(1-(F$87+F$75+F$76)/F$65) - INDEX(Assumptions!$B:$B,MATCH("Bandwidth/peering cost per Gbps ($mm/Gbps-yr)",Assumptions!$A$1:$A$257,0))*INDEX(Assumptions!$B:$B,MATCH("Effective DTC Gbps per sat (revenue calibration)",Assumptions!$A$1:$A$257,0))*F$21, 0) -> 0.87624477 | G118: =IFERROR(G$110*INDEX(Assumptions!$B:$B,MATCH("Effective DTC Gbps per sat (revenue calibration)",Assumptions!$A$1:$A$257,0))*G$21/1000000*(1-(G$87+G$75+G$76)/G$65) - INDEX(Assumptions!$B:$B,MATCH("Bandwidth/peering cost per Gbps ($mm/Gbps-yr)",Assumptions!$A$1:$A$257,0))*INDEX(Assumptions!$B:$B,MATCH("Effective DTC Gbps per sat (revenue calibration)",Assumptions!$A$1:$A$257,0))*G$21, 0) -> 1.0475799 | H118: =IFERROR(H$110*INDEX(Assumptions!$B:$B,MATCH("Effective DTC Gbps per sat (revenue calibration)",Assumptions!$A$1:$A$257,0))*H$21/1000000*(1-(H$87+H$75+H$76)/H$65) - INDEX(Assumptions!$B:$B,MATCH("Bandwidth/peering cost per Gbps ($mm/Gbps-yr)",Assumptions!$A$1:$A$257,0))*INDEX(Assumptions!$B:$B,MATCH("Effective DTC Gbps per sat (revenue calibration)",Assumptions!$A$1:$A$257,0))*H$21, 0) -> 1.2288298 | I118: =IFERROR(I$110*INDEX(Assumptions!$B:$B,MATCH("Effective DTC Gbps per sat (revenue calibration)",Assumptions!$A$1:$A$257,0))*I$21/1000000*(1-(I$87+I$75+I$76)/I$65) - INDEX(Assumptions!$B:$B,MATCH("Bandwidth/peering cost per Gbps ($mm/Gbps-yr)",Assumptions!$A$1:$A$257,0))*INDEX(Assumptions!$B:$B,MATCH("Effective DTC Gbps per sat (revenue calibration)",Assumptions!$A$1:$A$257,0))*I$21, 0) -> 0.52274439 | J118: =IFERROR(J$110*INDEX(Assumptions!$B:$B,MATCH("Effective DTC Gbps per sat (revenue calibration)",Assumptions!$A$1:$A$257,0))*J$21/1000000*(1-(J$87+J$75+J$76)/J$65) - INDEX(Assumptions!$B:$B,MATCH("Bandwidth/peering cost per Gbps ($mm/Gbps-yr)",Assumptions!$A$1:$A$257,0))*INDEX(Assumptions!$B:$B,MATCH("Effective DTC Gbps per sat (revenue calibration)",Assumptions!$A$1:$A$257,0))*J$21, 0) -> 0.3921775 | K118: =IFERROR(K$110*INDEX(Assumptions!$B:$B,MATCH("Effective DTC Gbps per sat (revenue calibration)",Assumptions!$A$1:$A$257,0))*K$21/1000000*(1-(K$87+K$75+K$76)/K$65) - INDEX(Assumptions!$B:$B,MATCH("Bandwidth/peering cost per Gbps ($mm/Gbps-yr)",Assumptions!$A$1:$A$257,0))*INDEX(Assumptions!$B:$B,MATCH("Effective DTC Gbps per sat (revenue calibration)",Assumptions!$A$1:$A$257,0))*K$21, 0) -> 0.27085642 | ... S118: =IFERROR(S$110*INDEX(Assumptions!$B:$B,MATCH("Effective DTC Gbps per sat (revenue calibration)",Assumptions!$A$1:$A$257,0))*S$21/1000000*(1-(S$87+S$75+S$76)/S$65) - INDEX(Assumptions!$B:$B,MATCH("Bandwidth/peering cost per Gbps ($mm/Gbps-yr)",Assumptions!$A$1:$A$257,0))*INDEX(Assumptions!$B:$B,MATCH("Effective DTC Gbps per sat (revenue calibration)",Assumptions!$A$1:$A$257,0))*S$21, 0) -> 0.2386044
A119: V2 DTC: CapEx slug per sat ($mm) | D119: =D$143*INDEX(Assumptions!$B:$B,MATCH("V2 DTC sat mass (kg)",Assumptions!$A$1:$A$257,0))/1000000 + IFERROR(D$13/INDEX(Assumptions!$B:$B,MATCH("F9 sats per launch (V2 packing)",Assumptions!$A$1:$A$257,0)),0) + INDEX(Assumptions!$B:$B,MATCH("Working capital per sat ($mm/sat): ΔWC T0",Assumptions!$A$1:$A$257,0)) -> 1.1479808 | E119: =E$143*INDEX(Assumptions!$B:$B,MATCH("V2 DTC sat mass (kg)",Assumptions!$A$1:$A$257,0))/1000000 + IFERROR(E$13/INDEX(Assumptions!$B:$B,MATCH("F9 sats per launch (V2 packing)",Assumptions!$A$1:$A$257,0)),0) + IFERROR(SUM($D$102:D102)/D142,0) + INDEX(Assumptions!$B:$B,MATCH("Working capital per sat ($mm/sat): ΔWC T0",Assumptions!$A$1:$A$257,0)) -> 1.1605523 | F119: =F$143*INDEX(Assumptions!$B:$B,MATCH("V2 DTC sat mass (kg)",Assumptions!$A$1:$A$257,0))/1000000 + IFERROR(F$13/INDEX(Assumptions!$B:$B,MATCH("F9 sats per launch (V2 packing)",Assumptions!$A$1:$A$257,0)),0) + IFERROR(SUM($D$102:E102)/E142,0) + INDEX(Assumptions!$B:$B,MATCH("Working capital per sat ($mm/sat): ΔWC T0",Assumptions!$A$1:$A$257,0)) -> 1.1376372 | G119: =G$143*INDEX(Assumptions!$B:$B,MATCH("V2 DTC sat mass (kg)",Assumptions!$A$1:$A$257,0))/1000000 + IFERROR(G$13/INDEX(Assumptions!$B:$B,MATCH("F9 sats per launch (V2 packing)",Assumptions!$A$1:$A$257,0)),0) + IFERROR(SUM($D$102:F102)/F142,0) + INDEX(Assumptions!$B:$B,MATCH("Working capital per sat ($mm/sat): ΔWC T0",Assumptions!$A$1:$A$257,0)) -> 1.1491075 | H119: =H$143*INDEX(Assumptions!$B:$B,MATCH("V2 DTC sat mass (kg)",Assumptions!$A$1:$A$257,0))/1000000 + IFERROR(H$13/INDEX(Assumptions!$B:$B,MATCH("F9 sats per launch (V2 packing)",Assumptions!$A$1:$A$257,0)),0) + IFERROR(SUM($D$102:G102)/G142,0) + INDEX(Assumptions!$B:$B,MATCH("Working capital per sat ($mm/sat): ΔWC T0",Assumptions!$A$1:$A$257,0)) -> 1.1287272 | I119: =I$143*INDEX(Assumptions!$B:$B,MATCH("V2 DTC sat mass (kg)",Assumptions!$A$1:$A$257,0))/1000000 + IFERROR(I$13/INDEX(Assumptions!$B:$B,MATCH("F9 sats per launch (V2 packing)",Assumptions!$A$1:$A$257,0)),0) + IFERROR(SUM($D$102:H102)/H142,0) + INDEX(Assumptions!$B:$B,MATCH("Working capital per sat ($mm/sat): ΔWC T0",Assumptions!$A$1:$A$257,0)) -> 1.0946725 | J119: =J$143*INDEX(Assumptions!$B:$B,MATCH("V2 DTC sat mass (kg)",Assumptions!$A$1:$A$257,0))/1000000 + IFERROR(J$13/INDEX(Assumptions!$B:$B,MATCH("F9 sats per launch (V2 packing)",Assumptions!$A$1:$A$257,0)),0) + IFERROR(SUM($D$102:I102)/I142,0) + INDEX(Assumptions!$B:$B,MATCH("Working capital per sat ($mm/sat): ΔWC T0",Assumptions!$A$1:$A$257,0)) -> 1.0503739 | K119: =K$143*INDEX(Assumptions!$B:$B,MATCH("V2 DTC sat mass (kg)",Assumptions!$A$1:$A$257,0))/1000000 + IFERROR(K$13/INDEX(Assumptions!$B:$B,MATCH("F9 sats per launch (V2 packing)",Assumptions!$A$1:$A$257,0)),0) + IFERROR(SUM($D$102:J102)/J142,0) + INDEX(Assumptions!$B:$B,MATCH("Working capital per sat ($mm/sat): ΔWC T0",Assumptions!$A$1:$A$257,0)) -> 1.0060425 | L119: =L$143*INDEX(Assumptions!$B:$B,MATCH("V2 DTC sat mass (kg)",Assumptions!$A$1:$A$257,0))/1000000 + IFERROR(L$13/INDEX(Assumptions!$B:$B,MATCH("F9 sats per launch (V2 packing)",Assumptions!$A$1:$A$257,0)),0) + IFERROR(SUM($D$102:K102)/K142,0) + INDEX(Assumptions!$B:$B,MATCH("Working capital per sat ($mm/sat): ΔWC T0",Assumptions!$A$1:$A$257,0)) -> 0.97683744 | ... S119: =S$143*INDEX(Assumptions!$B:$B,MATCH("V2 DTC sat mass (kg)",Assumptions!$A$1:$A$257,0))/1000000 + IFERROR(S$13/INDEX(Assumptions!$B:$B,MATCH("F9 sats per launch (V2 packing)",Assumptions!$A$1:$A$257,0)),0) + IFERROR(SUM($D$102:R102)/R142,0) + INDEX(Assumptions!$B:$B,MATCH("Working capital per sat ($mm/sat): ΔWC T0",Assumptions!$A$1:$A$257,0)) -> 0.85254664
A120: V2 DTC: Spot IRR | D120: =IFERROR(MIN(3, IFERROR(RATE(D$15,D118,-D119,0,0,0.1), IFERROR(RATE(D$15,D118,-D119,0,0,0.5), RATE(D$15,D118,-D119,0,0,1.5)))), IF(D118*D$15>D119,3,0)) -> 0.39916394 | E120: =IFERROR(MIN(3, IFERROR(RATE(E$15,E118,-E119,0,0,0.1), IFERROR(RATE(E$15,E118,-E119,0,0,0.5), RATE(E$15,E118,-E119,0,0,1.5)))), IF(E118*E$15>E119,3,0)) -> 0.54560656 | F120: =IFERROR(MIN(3, IFERROR(RATE(F$15,F118,-F119,0,0,0.1), IFERROR(RATE(F$15,F118,-F119,0,0,0.5), RATE(F$15,F118,-F119,0,0,1.5)))), IF(F118*F$15>F119,3,0)) -> 0.71890295 | G120: =IFERROR(MIN(3, IFERROR(RATE(G$15,G118,-G119,0,0,0.1), IFERROR(RATE(G$15,G118,-G119,0,0,0.5), RATE(G$15,G118,-G119,0,0,1.5)))), IF(G118*G$15>G119,3,0)) -> 0.87199063 | H120: =IFERROR(MIN(3, IFERROR(RATE(H$15,H118,-H119,0,0,0.1), IFERROR(RATE(H$15,H118,-H119,0,0,0.5), RATE(H$15,H118,-H119,0,0,1.5)))), IF(H118*H$15>H119,3,0)) -> 1.0592883 | I120: =IFERROR(MIN(3, IFERROR(RATE(I$15,I118,-I119,0,0,0.1), IFERROR(RATE(I$15,I118,-I119,0,0,0.5), RATE(I$15,I118,-I119,0,0,1.5)))), IF(I118*I$15>I119,3,0)) -> 0.38323044 | J120: =IFERROR(MIN(3, IFERROR(RATE(J$15,J118,-J119,0,0,0.1), IFERROR(RATE(J$15,J118,-J119,0,0,0.5), RATE(J$15,J118,-J119,0,0,1.5)))), IF(J118*J$15>J119,3,0)) -> 0.25199574 | K120: =IFERROR(MIN(3, IFERROR(RATE(K$15,K118,-K119,0,0,0.1), IFERROR(RATE(K$15,K118,-K119,0,0,0.5), RATE(K$15,K118,-K119,0,0,1.5)))), IF(K118*K$15>K119,3,0)) -> 0.1080283 | ... S120: =IFERROR(MIN(3, IFERROR(RATE(S$15,S118,-S119,0,0,0.1), IFERROR(RATE(S$15,S118,-S119,0,0,0.5), RATE(S$15,S118,-S119,0,0,1.5)))), IF(S118*S$15>S119,3,0)) -> 0.1235776
A124: V3 BB: margin per sat-yr ($mm) | D124: =IFERROR(D$109*INDEX(Assumptions!$B:$B,MATCH("V3 BB Gbps per sat",Assumptions!$A$1:$A$257,0))*D$21/1000000*(1-(D$87+D$75+D$76)/D$65) - INDEX(Assumptions!$B:$B,MATCH("Bandwidth/peering cost per Gbps ($mm/Gbps-yr)",Assumptions!$A$1:$A$257,0))*INDEX(Assumptions!$B:$B,MATCH("V3 BB Gbps per sat",Assumptions!$A$1:$A$257,0))*D$21, 0) -> 6.6381909 | E124: =IFERROR(E$109*INDEX(Assumptions!$B:$B,MATCH("V3 BB Gbps per sat",Assumptions!$A$1:$A$257,0))*E$21/1000000*(1-(E$87+E$75+E$76)/E$65) - INDEX(Assumptions!$B:$B,MATCH("Bandwidth/peering cost per Gbps ($mm/Gbps-yr)",Assumptions!$A$1:$A$257,0))*INDEX(Assumptions!$B:$B,MATCH("V3 BB Gbps per sat",Assumptions!$A$1:$A$257,0))*E$21, 0) -> 5.8865002 | F124: =IFERROR(F$109*INDEX(Assumptions!$B:$B,MATCH("V3 BB Gbps per sat",Assumptions!$A$1:$A$257,0))*F$21/1000000*(1-(F$87+F$75+F$76)/F$65) - INDEX(Assumptions!$B:$B,MATCH("Bandwidth/peering cost per Gbps ($mm/Gbps-yr)",Assumptions!$A$1:$A$257,0))*INDEX(Assumptions!$B:$B,MATCH("V3 BB Gbps per sat",Assumptions!$A$1:$A$257,0))*F$21, 0) -> 3.4020016 | G124: =IFERROR(G$109*INDEX(Assumptions!$B:$B,MATCH("V3 BB Gbps per sat",Assumptions!$A$1:$A$257,0))*G$21/1000000*(1-(G$87+G$75+G$76)/G$65) - INDEX(Assumptions!$B:$B,MATCH("Bandwidth/peering cost per Gbps ($mm/Gbps-yr)",Assumptions!$A$1:$A$257,0))*INDEX(Assumptions!$B:$B,MATCH("V3 BB Gbps per sat",Assumptions!$A$1:$A$257,0))*G$21, 0) -> 2.0645925 | H124: =IFERROR(H$109*INDEX(Assumptions!$B:$B,MATCH("V3 BB Gbps per sat",Assumptions!$A$1:$A$257,0))*H$21/1000000*(1-(H$87+H$75+H$76)/H$65) - INDEX(Assumptions!$B:$B,MATCH("Bandwidth/peering cost per Gbps ($mm/Gbps-yr)",Assumptions!$A$1:$A$257,0))*INDEX(Assumptions!$B:$B,MATCH("V3 BB Gbps per sat",Assumptions!$A$1:$A$257,0))*H$21, 0) -> 0.85166504 | I124: =IFERROR(I$109*INDEX(Assumptions!$B:$B,MATCH("V3 BB Gbps per sat",Assumptions!$A$1:$A$257,0))*I$21/1000000*(1-(I$87+I$75+I$76)/I$65) - INDEX(Assumptions!$B:$B,MATCH("Bandwidth/peering cost per Gbps ($mm/Gbps-yr)",Assumptions!$A$1:$A$257,0))*INDEX(Assumptions!$B:$B,MATCH("V3 BB Gbps per sat",Assumptions!$A$1:$A$257,0))*I$21, 0) -> 0.57983605 | J124: =IFERROR(J$109*INDEX(Assumptions!$B:$B,MATCH("V3 BB Gbps per sat",Assumptions!$A$1:$A$257,0))*J$21/1000000*(1-(J$87+J$75+J$76)/J$65) - INDEX(Assumptions!$B:$B,MATCH("Bandwidth/peering cost per Gbps ($mm/Gbps-yr)",Assumptions!$A$1:$A$257,0))*INDEX(Assumptions!$B:$B,MATCH("V3 BB Gbps per sat",Assumptions!$A$1:$A$257,0))*J$21, 0) -> 0.13088183 | K124: =IFERROR(K$109*INDEX(Assumptions!$B:$B,MATCH("V3 BB Gbps per sat",Assumptions!$A$1:$A$257,0))*K$21/1000000*(1-(K$87+K$75+K$76)/K$65) - INDEX(Assumptions!$B:$B,MATCH("Bandwidth/peering cost per Gbps ($mm/Gbps-yr)",Assumptions!$A$1:$A$257,0))*INDEX(Assumptions!$B:$B,MATCH("V3 BB Gbps per sat",Assumptions!$A$1:$A$257,0))*K$21, 0) -> 0.028117724 | ... S124: =IFERROR(S$109*INDEX(Assumptions!$B:$B,MATCH("V3 BB Gbps per sat",Assumptions!$A$1:$A$257,0))*S$21/1000000*(1-(S$87+S$75+S$76)/S$65) - INDEX(Assumptions!$B:$B,MATCH("Bandwidth/peering cost per Gbps ($mm/Gbps-yr)",Assumptions!$A$1:$A$257,0))*INDEX(Assumptions!$B:$B,MATCH("V3 BB Gbps per sat",Assumptions!$A$1:$A$257,0))*S$21, 0) -> -0.42514819
A125: V3 BB: CapEx slug per sat ($mm) | D125: =D$143*INDEX(Assumptions!$B:$B,MATCH("V3 BB sat mass (kg)",Assumptions!$A$1:$A$257,0))/1000000 + IFERROR(D$14/D204,0) + INDEX(Assumptions!$B:$B,MATCH("Working capital per sat ($mm/sat): ΔWC T0",Assumptions!$A$1:$A$257,0)) -> 1.305 | E125: =E$143*INDEX(Assumptions!$B:$B,MATCH("V3 BB sat mass (kg)",Assumptions!$A$1:$A$257,0))/1000000 + IFERROR(E$14/E204,0) + IFERROR(SUM($D$102:D102)/D142,0) + INDEX(Assumptions!$B:$B,MATCH("Working capital per sat ($mm/sat): ΔWC T0",Assumptions!$A$1:$A$257,0)) -> 1.3329562 | F125: =F$143*INDEX(Assumptions!$B:$B,MATCH("V3 BB sat mass (kg)",Assumptions!$A$1:$A$257,0))/1000000 + IFERROR(F$14/F204,0) + IFERROR(SUM($D$102:E102)/E142,0) + INDEX(Assumptions!$B:$B,MATCH("Working capital per sat ($mm/sat): ΔWC T0",Assumptions!$A$1:$A$257,0)) -> 1.6698542 | G125: =G$143*INDEX(Assumptions!$B:$B,MATCH("V3 BB sat mass (kg)",Assumptions!$A$1:$A$257,0))/1000000 + IFERROR(G$14/G204,0) + IFERROR(SUM($D$102:F102)/F142,0) + INDEX(Assumptions!$B:$B,MATCH("Working capital per sat ($mm/sat): ΔWC T0",Assumptions!$A$1:$A$257,0)) -> 1.5893285 | H125: =H$143*INDEX(Assumptions!$B:$B,MATCH("V3 BB sat mass (kg)",Assumptions!$A$1:$A$257,0))/1000000 + IFERROR(H$14/H204,0) + IFERROR(SUM($D$102:G102)/G142,0) + INDEX(Assumptions!$B:$B,MATCH("Working capital per sat ($mm/sat): ΔWC T0",Assumptions!$A$1:$A$257,0)) -> 1.4810863 | I125: =I$143*INDEX(Assumptions!$B:$B,MATCH("V3 BB sat mass (kg)",Assumptions!$A$1:$A$257,0))/1000000 + IFERROR(I$14/I204,0) + IFERROR(SUM($D$102:H102)/H142,0) + INDEX(Assumptions!$B:$B,MATCH("Working capital per sat ($mm/sat): ΔWC T0",Assumptions!$A$1:$A$257,0)) -> 1.3630978 | J125: =J$143*INDEX(Assumptions!$B:$B,MATCH("V3 BB sat mass (kg)",Assumptions!$A$1:$A$257,0))/1000000 + IFERROR(J$14/J204,0) + IFERROR(SUM($D$102:I102)/I142,0) + INDEX(Assumptions!$B:$B,MATCH("Working capital per sat ($mm/sat): ΔWC T0",Assumptions!$A$1:$A$257,0)) -> 1.2770077 | K125: =K$143*INDEX(Assumptions!$B:$B,MATCH("V3 BB sat mass (kg)",Assumptions!$A$1:$A$257,0))/1000000 + IFERROR(K$14/K204,0) + IFERROR(SUM($D$102:J102)/J142,0) + INDEX(Assumptions!$B:$B,MATCH("Working capital per sat ($mm/sat): ΔWC T0",Assumptions!$A$1:$A$257,0)) -> 1.2087558 | L125: =L$143*INDEX(Assumptions!$B:$B,MATCH("V3 BB sat mass (kg)",Assumptions!$A$1:$A$257,0))/1000000 + IFERROR(L$14/L204,0) + IFERROR(SUM($D$102:K102)/K142,0) + INDEX(Assumptions!$B:$B,MATCH("Working capital per sat ($mm/sat): ΔWC T0",Assumptions!$A$1:$A$257,0)) -> 1.1617272 | ... S125: =S$143*INDEX(Assumptions!$B:$B,MATCH("V3 BB sat mass (kg)",Assumptions!$A$1:$A$257,0))/1000000 + IFERROR(S$14/S204,0) + IFERROR(SUM($D$102:R102)/R142,0) + INDEX(Assumptions!$B:$B,MATCH("Working capital per sat ($mm/sat): ΔWC T0",Assumptions!$A$1:$A$257,0)) -> 0.99913786
...

Sheet Customer Launch
A1: Customer Launch module — module = Space segment · 2-stream revenue $4,086M · full waterfall, R&D above EBITDA · separate F9 + Starship D&A · Spot IRR · per-launch D&A interface
A4: YEAR | D4: 2025 | E4: 2026 | F4: 2027 | G4: 2028 | H4: 2029 | I4: 2030 | J4: 2031 | K4: 2032 | L4: 2033 | M4: 2034 | N4: 2035 | O4: 2036 | P4: 2037 | Q4: 2038 | R4: 2039 | S4: 2040
A5: Year offset | D5: 0 | E5: 1 | F5: 2 | G5: 3 | H5: 4 | I5: 5 | J5: 6 | K5: 7 | L5: 8 | M5: 9 | N5: 10 | O5: 11 | P5: 12 | Q5: 13 | R5: 14 | S5: 15
A8: ▸ BLOCK A: ALLOCATOR IN (cross-tab reads)
A9: F9 internal launches per year (Starlink-driven) | D9: {=INDEX(Starlink!$D:$AC, MATCH("F9 internal launches per year (Starlink-driven)", Starlink!$A$1:$A$204, 0), COLUMN()-COLUMN($D9)+1)} -> 166 | E9: {=INDEX(Starlink!$D:$AC, MATCH("F9 internal launches per year (Starlink-driven)", Starlink!$A$1:$A$204, 0), COLUMN()-COLUMN($D9)+1)} -> 138 | F9: {=INDEX(Starlink!$D:$AC, MATCH("F9 internal launches per year (Starlink-driven)", Starlink!$A$1:$A$204, 0), COLUMN()-COLUMN($D9)+1)} -> 0 | G9: {=INDEX(Starlink!$D:$AC, MATCH("F9 internal launches per year (Starlink-driven)", Starlink!$A$1:$A$204, 0), COLUMN()-COLUMN($D9)+1)} -> 0 | H9: {=INDEX(Starlink!$D:$AC, MATCH("F9 internal launches per year (Starlink-driven)", Starlink!$A$1:$A$204, 0), COLUMN()-COLUMN($D9)+1)} -> 0 | I9: {=INDEX(Starlink!$D:$AC, MATCH("F9 internal launches per year (Starlink-driven)", Starlink!$A$1:$A$204, 0), COLUMN()-COLUMN($D9)+1)} -> 0 | J9: {=INDEX(Starlink!$D:$AC, MATCH("F9 internal launches per year (Starlink-driven)", Starlink!$A$1:$A$204, 0), COLUMN()-COLUMN($D9)+1)} -> 0 | K9: {=INDEX(Starlink!$D:$AC, MATCH("F9 internal launches per year (Starlink-driven)", Starlink!$A$1:$A$204, 0), COLUMN()-COLUMN($D9)+1)} -> 0 | ... S9: {=INDEX(Starlink!$D:$AC, MATCH("F9 internal launches per year (Starlink-driven)", Starlink!$A$1:$A$204, 0), COLUMN()-COLUMN($D9)+1)} -> 0
A10: Starship internal launches per year (Starlink-driven) | D10: {=INDEX(Starlink!$D:$AC, MATCH("Starship internal launches per year (Starlink-driven)", Starlink!$A$1:$A$204, 0), COLUMN()-COLUMN($D10)+1)} -> 0 | E10: {=INDEX(Starlink!$D:$AC, MATCH("Starship internal launches per year (Starlink-driven)", Starlink!$A$1:$A$204, 0), COLUMN()-COLUMN($D10)+1)} -> 0 | F10: {=INDEX(Starlink!$D:$AC, MATCH("Starship internal launches per year (Starlink-driven)", Starlink!$A$1:$A$204, 0), COLUMN()-COLUMN($D10)+1)} -> 61 | G10: {=INDEX(Starlink!$D:$AC, MATCH("Starship internal launches per year (Starlink-driven)", Starlink!$A$1:$A$204, 0), COLUMN()-COLUMN($D10)+1)} -> 127 | H10: {=INDEX(Starlink!$D:$AC, MATCH("Starship internal launches per year (Starlink-driven)", Starlink!$A$1:$A$204, 0), COLUMN()-COLUMN($D10)+1)} -> 311 | I10: {=INDEX(Starlink!$D:$AC, MATCH("Starship internal launches per year (Starlink-driven)", Starlink!$A$1:$A$204, 0), COLUMN()-COLUMN($D10)+1)} -> 504 | J10: {=INDEX(Starlink!$D:$AC, MATCH("Starship internal launches per year (Starlink-driven)", Starlink!$A$1:$A$204, 0), COLUMN()-COLUMN($D10)+1)} -> 537 | K10: {=INDEX(Starlink!$D:$AC, MATCH("Starship internal launches per year (Starlink-driven)", Starlink!$A$1:$A$204, 0), COLUMN()-COLUMN($D10)+1)} -> 634 | ... S10: {=INDEX(Starlink!$D:$AC, MATCH("Starship internal launches per year (Starlink-driven)", Starlink!$A$1:$A$204, 0), COLUMN()-COLUMN($D10)+1)} -> 336
A11: F9 customer launch price ($mm/launch) | D11: =INDEX(Assumptions!$B:$B, MATCH("F9 customer launch price ($mm/launch)", Assumptions!$A$1:$A$257, 0)) -> 54.8 | E11: =INDEX(Assumptions!$B:$B, MATCH("F9 customer launch price ($mm/launch)", Assumptions!$A$1:$A$257, 0)) -> 54.8 | F11: =INDEX(Assumptions!$B:$B, MATCH("F9 customer launch price ($mm/launch)", Assumptions!$A$1:$A$257, 0)) -> 54.8 | G11: =INDEX(Assumptions!$B:$B, MATCH("F9 customer launch price ($mm/launch)", Assumptions!$A$1:$A$257, 0)) -> 54.8 | H11: =INDEX(Assumptions!$B:$B, MATCH("F9 customer launch price ($mm/launch)", Assumptions!$A$1:$A$257, 0)) -> 54.8 | I11: =INDEX(Assumptions!$B:$B, MATCH("F9 customer launch price ($mm/launch)", Assumptions!$A$1:$A$257, 0)) -> 54.8 | J11: =INDEX(Assumptions!$B:$B, MATCH("F9 customer launch price ($mm/launch)", Assumptions!$A$1:$A$257, 0)) -> 54.8 | K11: =INDEX(Assumptions!$B:$B, MATCH("F9 customer launch price ($mm/launch)", Assumptions!$A$1:$A$257, 0)) -> 54.8 | ... S11: =INDEX(Assumptions!$B:$B, MATCH("F9 customer launch price ($mm/launch)", Assumptions!$A$1:$A$257, 0)) -> 54.8
A12: Starship customer launch price ($mm/launch) | D12: {=INDEX(Assumptions!$D:$S, MATCH("Starship customer launch price ($mm/launch): year-row", Assumptions!$A$1:$A$257, 0), COLUMN()-COLUMN($D12)+1)} -> 0 | E12: {=INDEX(Assumptions!$D:$S, MATCH("Starship customer launch price ($mm/launch): year-row", Assumptions!$A$1:$A$257, 0), COLUMN()-COLUMN($D12)+1)} -> 0 | F12: {=INDEX(Assumptions!$D:$S, MATCH("Starship customer launch price ($mm/launch): year-row", Assumptions!$A$1:$A$257, 0), COLUMN()-COLUMN($D12)+1)} -> 100 | G12: {=INDEX(Assumptions!$D:$S, MATCH("Starship customer launch price ($mm/launch): year-row", Assumptions!$A$1:$A$257, 0), COLUMN()-COLUMN($D12)+1)} -> 92 | H12: {=INDEX(Assumptions!$D:$S, MATCH("Starship customer launch price ($mm/launch): year-row", Assumptions!$A$1:$A$257, 0), COLUMN()-COLUMN($D12)+1)} -> 84.64 | I12: {=INDEX(Assumptions!$D:$S, MATCH("Starship customer launch price ($mm/launch): year-row", Assumptions!$A$1:$A$257, 0), COLUMN()-COLUMN($D12)+1)} -> 77.8688 | J12: {=INDEX(Assumptions!$D:$S, MATCH("Starship customer launch price ($mm/launch): year-row", Assumptions!$A$1:$A$257, 0), COLUMN()-COLUMN($D12)+1)} -> 71.639296 | K12: {=INDEX(Assumptions!$D:$S, MATCH("Starship customer launch price ($mm/launch): year-row", Assumptions!$A$1:$A$257, 0), COLUMN()-COLUMN($D12)+1)} -> 65.908152 | ... S12: {=INDEX(Assumptions!$D:$S, MATCH("Starship customer launch price ($mm/launch): year-row", Assumptions!$A$1:$A$257, 0), COLUMN()-COLUMN($D12)+1)} -> 33.825308
A13: Commercial launch market size ($mm/yr) | D13: {=INDEX(Assumptions!$D:$S, MATCH("Commercial launch market size ($mm/year): year-row", Assumptions!$A$1:$A$257, 0), COLUMN()-COLUMN($D13)+1)} -> 8000 | E13: {=INDEX(Assumptions!$D:$S, MATCH("Commercial launch market size ($mm/year): year-row", Assumptions!$A$1:$A$257, 0), COLUMN()-COLUMN($D13)+1)} -> 8640 | F13: {=INDEX(Assumptions!$D:$S, MATCH("Commercial launch market size ($mm/year): year-row", Assumptions!$A$1:$A$257, 0), COLUMN()-COLUMN($D13)+1)} -> 9331.2 | G13: {=INDEX(Assumptions!$D:$S, MATCH("Commercial launch market size ($mm/year): year-row", Assumptions!$A$1:$A$257, 0), COLUMN()-COLUMN($D13)+1)} -> 10077.696 | H13: {=INDEX(Assumptions!$D:$S, MATCH("Commercial launch market size ($mm/year): year-row", Assumptions!$A$1:$A$257, 0), COLUMN()-COLUMN($D13)+1)} -> 10883.912 | I13: {=INDEX(Assumptions!$D:$S, MATCH("Commercial launch market size ($mm/year): year-row", Assumptions!$A$1:$A$257, 0), COLUMN()-COLUMN($D13)+1)} -> 11754.625 | J13: {=INDEX(Assumptions!$D:$S, MATCH("Commercial launch market size ($mm/year): year-row", Assumptions!$A$1:$A$257, 0), COLUMN()-COLUMN($D13)+1)} -> 12694.995 | K13: {=INDEX(Assumptions!$D:$S, MATCH("Commercial launch market size ($mm/year): year-row", Assumptions!$A$1:$A$257, 0), COLUMN()-COLUMN($D13)+1)} -> 13710.594 | ... S13: {=INDEX(Assumptions!$D:$S, MATCH("Commercial launch market size ($mm/year): year-row", Assumptions!$A$1:$A$257, 0), COLUMN()-COLUMN($D13)+1)} -> 25377.353
A14: Government launch market size ($mm/yr) | D14: {=INDEX(Assumptions!$D:$S, MATCH("Government launch market size ($mm/year): year-row", Assumptions!$A$1:$A$257, 0), COLUMN()-COLUMN($D14)+1)} -> 4000 | E14: {=INDEX(Assumptions!$D:$S, MATCH("Government launch market size ($mm/year): year-row", Assumptions!$A$1:$A$257, 0), COLUMN()-COLUMN($D14)+1)} -> 4200 | F14: {=INDEX(Assumptions!$D:$S, MATCH("Government launch market size ($mm/year): year-row", Assumptions!$A$1:$A$257, 0), COLUMN()-COLUMN($D14)+1)} -> 4410 | G14: {=INDEX(Assumptions!$D:$S, MATCH("Government launch market size ($mm/year): year-row", Assumptions!$A$1:$A$257, 0), COLUMN()-COLUMN($D14)+1)} -> 4630.5 | H14: {=INDEX(Assumptions!$D:$S, MATCH("Government launch market size ($mm/year): year-row", Assumptions!$A$1:$A$257, 0), COLUMN()-COLUMN($D14)+1)} -> 4862.025 | I14: {=INDEX(Assumptions!$D:$S, MATCH("Government launch market size ($mm/year): year-row", Assumptions!$A$1:$A$257, 0), COLUMN()-COLUMN($D14)+1)} -> 5105.1263 | J14: {=INDEX(Assumptions!$D:$S, MATCH("Government launch market size ($mm/year): year-row", Assumptions!$A$1:$A$257, 0), COLUMN()-COLUMN($D14)+1)} -> 5360.3826 | K14: {=INDEX(Assumptions!$D:$S, MATCH("Government launch market size ($mm/year): year-row", Assumptions!$A$1:$A$257, 0), COLUMN()-COLUMN($D14)+1)} -> 5628.4017 | ... S14: {=INDEX(Assumptions!$D:$S, MATCH("Government launch market size ($mm/year): year-row", Assumptions!$A$1:$A$257, 0), COLUMN()-COLUMN($D14)+1)} -> 8315.7127
A15: SpaceX commercial market share | D15: {=INDEX(Assumptions!$D:$S, MATCH("SpaceX commercial market share %", Assumptions!$A$1:$A$257, 0), COLUMN()-COLUMN($D15)+1)} -> 0.75 | E15: {=INDEX(Assumptions!$D:$S, MATCH("SpaceX commercial market share %", Assumptions!$A$1:$A$257, 0), COLUMN()-COLUMN($D15)+1)} -> 0.75333333 | F15: {=INDEX(Assumptions!$D:$S, MATCH("SpaceX commercial market share %", Assumptions!$A$1:$A$257, 0), COLUMN()-COLUMN($D15)+1)} -> 0.75666667 | G15: {=INDEX(Assumptions!$D:$S, MATCH("SpaceX commercial market share %", Assumptions!$A$1:$A$257, 0), COLUMN()-COLUMN($D15)+1)} -> 0.76 | H15: {=INDEX(Assumptions!$D:$S, MATCH("SpaceX commercial market share %", Assumptions!$A$1:$A$257, 0), COLUMN()-COLUMN($D15)+1)} -> 0.76333333 | I15: {=INDEX(Assumptions!$D:$S, MATCH("SpaceX commercial market share %", Assumptions!$A$1:$A$257, 0), COLUMN()-COLUMN($D15)+1)} -> 0.76666667 | J15: {=INDEX(Assumptions!$D:$S, MATCH("SpaceX commercial market share %", Assumptions!$A$1:$A$257, 0), COLUMN()-COLUMN($D15)+1)} -> 0.77 | K15: {=INDEX(Assumptions!$D:$S, MATCH("SpaceX commercial market share %", Assumptions!$A$1:$A$257, 0), COLUMN()-COLUMN($D15)+1)} -> 0.77333333 | ... S15: {=INDEX(Assumptions!$D:$S, MATCH("SpaceX commercial market share %", Assumptions!$A$1:$A$257, 0), COLUMN()-COLUMN($D15)+1)} -> 0.8
A16: SpaceX government market share | D16: {=INDEX(Assumptions!$D:$S, MATCH("SpaceX government market share %", Assumptions!$A$1:$A$257, 0), COLUMN()-COLUMN($D16)+1)} -> 0.9 | E16: {=INDEX(Assumptions!$D:$S, MATCH("SpaceX government market share %", Assumptions!$A$1:$A$257, 0), COLUMN()-COLUMN($D16)+1)} -> 0.89333333 | F16: {=INDEX(Assumptions!$D:$S, MATCH("SpaceX government market share %", Assumptions!$A$1:$A$257, 0), COLUMN()-COLUMN($D16)+1)} -> 0.88666667 | G16: {=INDEX(Assumptions!$D:$S, MATCH("SpaceX government market share %", Assumptions!$A$1:$A$257, 0), COLUMN()-COLUMN($D16)+1)} -> 0.88 | H16: {=INDEX(Assumptions!$D:$S, MATCH("SpaceX government market share %", Assumptions!$A$1:$A$257, 0), COLUMN()-COLUMN($D16)+1)} -> 0.87333333 | I16: {=INDEX(Assumptions!$D:$S, MATCH("SpaceX government market share %", Assumptions!$A$1:$A$257, 0), COLUMN()-COLUMN($D16)+1)} -> 0.86666667 | J16: {=INDEX(Assumptions!$D:$S, MATCH("SpaceX government market share %", Assumptions!$A$1:$A$257, 0), COLUMN()-COLUMN($D16)+1)} -> 0.86 | K16: {=INDEX(Assumptions!$D:$S, MATCH("SpaceX government market share %", Assumptions!$A$1:$A$257, 0), COLUMN()-COLUMN($D16)+1)} -> 0.85333333 | ... S16: {=INDEX(Assumptions!$D:$S, MATCH("SpaceX government market share %", Assumptions!$A$1:$A$257, 0), COLUMN()-COLUMN($D16)+1)} -> 0.8
A17: Launch & Development revenue ($mm/yr) | D17: {=INDEX(Assumptions!$D:$S, MATCH("Launch & Development revenue ($mm/yr): year-row", Assumptions!$A$1:$A$257, 0), COLUMN()-COLUMN($D17)+1)} -> 1510 | E17: {=INDEX(Assumptions!$D:$S, MATCH("Launch & Development revenue ($mm/yr): year-row", Assumptions!$A$1:$A$257, 0), COLUMN()-COLUMN($D17)+1)} -> 1585.5 | F17: {=INDEX(Assumptions!$D:$S, MATCH("Launch & Development revenue ($mm/yr): year-row", Assumptions!$A$1:$A$257, 0), COLUMN()-COLUMN($D17)+1)} -> 1664.775 | G17: {=INDEX(Assumptions!$D:$S, MATCH("Launch & Development revenue ($mm/yr): year-row", Assumptions!$A$1:$A$257, 0), COLUMN()-COLUMN($D17)+1)} -> 1748.0138 | H17: {=INDEX(Assumptions!$D:$S, MATCH("Launch & Development revenue ($mm/yr): year-row", Assumptions!$A$1:$A$257, 0), COLUMN()-COLUMN($D17)+1)} -> 1835.4144 | I17: {=INDEX(Assumptions!$D:$S, MATCH("Launch & Development revenue ($mm/yr): year-row", Assumptions!$A$1:$A$257, 0), COLUMN()-COLUMN($D17)+1)} -> 1927.1852 | J17: {=INDEX(Assumptions!$D:$S, MATCH("Launch & Development revenue ($mm/yr): year-row", Assumptions!$A$1:$A$257, 0), COLUMN()-COLUMN($D17)+1)} -> 2023.5444 | K17: {=INDEX(Assumptions!$D:$S, MATCH("Launch & Development revenue ($mm/yr): year-row", Assumptions!$A$1:$A$257, 0), COLUMN()-COLUMN($D17)+1)} -> 2124.7216 | ... S17: {=INDEX(Assumptions!$D:$S, MATCH("Launch & Development revenue ($mm/yr): year-row", Assumptions!$A$1:$A$257, 0), COLUMN()-COLUMN($D17)+1)} -> 3139.1816
A18: Starship commercial-readiness factor | D18: {=INDEX(Assumptions!$D:$S, MATCH("Starship commercial-readiness factor: year-row", Assumptions!$A$1:$A$257, 0), COLUMN()-COLUMN($D18)+1)} -> 0 | E18: {=INDEX(Assumptions!$D:$S, MATCH("Starship commercial-readiness factor: year-row", Assumptions!$A$1:$A$257, 0), COLUMN()-COLUMN($D18)+1)} -> 0 | F18: {=INDEX(Assumptions!$D:$S, MATCH("Starship commercial-readiness factor: year-row", Assumptions!$A$1:$A$257, 0), COLUMN()-COLUMN($D18)+1)} -> 0 | G18: {=INDEX(Assumptions!$D:$S, MATCH("Starship commercial-readiness factor: year-row", Assumptions!$A$1:$A$257, 0), COLUMN()-COLUMN($D18)+1)} -> 0.07585818 | H18: {=INDEX(Assumptions!$D:$S, MATCH("Starship commercial-readiness factor: year-row", Assumptions!$A$1:$A$257, 0), COLUMN()-COLUMN($D18)+1)} -> 0.18242552 | I18: {=INDEX(Assumptions!$D:$S, MATCH("Starship commercial-readiness factor: year-row", Assumptions!$A$1:$A$257, 0), COLUMN()-COLUMN($D18)+1)} -> 0.37754067 | J18: {=INDEX(Assumptions!$D:$S, MATCH("Starship commercial-readiness factor: year-row", Assumptions!$A$1:$A$257, 0), COLUMN()-COLUMN($D18)+1)} -> 0.62245933 | K18: {=INDEX(Assumptions!$D:$S, MATCH("Starship commercial-readiness factor: year-row", Assumptions!$A$1:$A$257, 0), COLUMN()-COLUMN($D18)+1)} -> 0.81757448 | ... S18: {=INDEX(Assumptions!$D:$S, MATCH("Starship commercial-readiness factor: year-row", Assumptions!$A$1:$A$257, 0), COLUMN()-COLUMN($D18)+1)} -> 0.99992515
A19: F9 at-cost rate per launch ($mm) | D19: =INDEX(Assumptions!$B:$B, MATCH("F9 at-cost rate per launch ($mm)", Assumptions!$A$1:$A$257, 0)) -> 20 | E19: =INDEX(Assumptions!$B:$B, MATCH("F9 at-cost rate per launch ($mm)", Assumptions!$A$1:$A$257, 0)) -> 20 | F19: =INDEX(Assumptions!$B:$B, MATCH("F9 at-cost rate per launch ($mm)", Assumptions!$A$1:$A$257, 0)) -> 20 | G19: =INDEX(Assumptions!$B:$B, MATCH("F9 at-cost rate per launch ($mm)", Assumptions!$A$1:$A$257, 0)) -> 20 | H19: =INDEX(Assumptions!$B:$B, MATCH("F9 at-cost rate per launch ($mm)", Assumptions!$A$1:$A$257, 0)) -> 20 | I19: =INDEX(Assumptions!$B:$B, MATCH("F9 at-cost rate per launch ($mm)", Assumptions!$A$1:$A$257, 0)) -> 20 | J19: =INDEX(Assumptions!$B:$B, MATCH("F9 at-cost rate per launch ($mm)", Assumptions!$A$1:$A$257, 0)) -> 20 | K19: =INDEX(Assumptions!$B:$B, MATCH("F9 at-cost rate per launch ($mm)", Assumptions!$A$1:$A$257, 0)) -> 20 | ... S19: =INDEX(Assumptions!$B:$B, MATCH("F9 at-cost rate per launch ($mm)", Assumptions!$A$1:$A$257, 0)) -> 20
A20: Starship at-cost rate per launch ($mm) | D20: {=INDEX('Vehicle Build'!$D:$AC,MATCH("Starship at-cost rate, fully reusable ($mm/launch)",'Vehicle Build'!$A$1:$A$119,0),D$5+1)} -> 18.192564 | E20: {=INDEX('Vehicle Build'!$D:$AC,MATCH("Starship at-cost rate, fully reusable ($mm/launch)",'Vehicle Build'!$A$1:$A$119,0),E$5+1)} -> 14.499424 | F20: {=INDEX('Vehicle Build'!$D:$AC,MATCH("Starship at-cost rate, fully reusable ($mm/launch)",'Vehicle Build'!$A$1:$A$119,0),F$5+1)} -> 11.804893 | G20: {=INDEX('Vehicle Build'!$D:$AC,MATCH("Starship at-cost rate, fully reusable ($mm/launch)",'Vehicle Build'!$A$1:$A$119,0),G$5+1)} -> 9.9704187 | H20: {=INDEX('Vehicle Build'!$D:$AC,MATCH("Starship at-cost rate, fully reusable ($mm/launch)",'Vehicle Build'!$A$1:$A$119,0),H$5+1)} -> 8.8283343 | I20: {=INDEX('Vehicle Build'!$D:$AC,MATCH("Starship at-cost rate, fully reusable ($mm/launch)",'Vehicle Build'!$A$1:$A$119,0),I$5+1)} -> 8.120365 | J20: {=INDEX('Vehicle Build'!$D:$AC,MATCH("Starship at-cost rate, fully reusable ($mm/launch)",'Vehicle Build'!$A$1:$A$119,0),J$5+1)} -> 7.5835393 | K20: {=INDEX('Vehicle Build'!$D:$AC,MATCH("Starship at-cost rate, fully reusable ($mm/launch)",'Vehicle Build'!$A$1:$A$119,0),K$5+1)} -> 7.1354969 | ... S20: {=INDEX('Vehicle Build'!$D:$AC,MATCH("Starship at-cost rate, fully reusable ($mm/launch)",'Vehicle Build'!$A$1:$A$119,0),S$5+1)} -> 6.1470556
A21: F9 booster build cost ($mm) | D21: =INDEX(Assumptions!$B:$B, MATCH("F9 booster (1st stage) mfg cost ($mm/unit)", Assumptions!$A$1:$A$257, 0)) -> 30 | E21: =INDEX(Assumptions!$B:$B, MATCH("F9 booster (1st stage) mfg cost ($mm/unit)", Assumptions!$A$1:$A$257, 0)) -> 30 | F21: =INDEX(Assumptions!$B:$B, MATCH("F9 booster (1st stage) mfg cost ($mm/unit)", Assumptions!$A$1:$A$257, 0)) -> 30 | G21: =INDEX(Assumptions!$B:$B, MATCH("F9 booster (1st stage) mfg cost ($mm/unit)", Assumptions!$A$1:$A$257, 0)) -> 30 | H21: =INDEX(Assumptions!$B:$B, MATCH("F9 booster (1st stage) mfg cost ($mm/unit)", Assumptions!$A$1:$A$257, 0)) -> 30 | I21: =INDEX(Assumptions!$B:$B, MATCH("F9 booster (1st stage) mfg cost ($mm/unit)", Assumptions!$A$1:$A$257, 0)) -> 30 | J21: =INDEX(Assumptions!$B:$B, MATCH("F9 booster (1st stage) mfg cost ($mm/unit)", Assumptions!$A$1:$A$257, 0)) -> 30 | K21: =INDEX(Assumptions!$B:$B, MATCH("F9 booster (1st stage) mfg cost ($mm/unit)", Assumptions!$A$1:$A$257, 0)) -> 30 | ... S21: =INDEX(Assumptions!$B:$B, MATCH("F9 booster (1st stage) mfg cost ($mm/unit)", Assumptions!$A$1:$A$257, 0)) -> 30
A22: Starship vehicle build cost ($mm) | D22: {=INDEX('Vehicle Build'!$D:$AC,MATCH("Starship build cost ($mm/stack)",'Vehicle Build'!$A$1:$A$119,0),D$5+1)} -> 65.071945 | E22: {=INDEX('Vehicle Build'!$D:$AC,MATCH("Starship build cost ($mm/stack)",'Vehicle Build'!$A$1:$A$119,0),E$5+1)} -> 60.97101 | F22: {=INDEX('Vehicle Build'!$D:$AC,MATCH("Starship build cost ($mm/stack)",'Vehicle Build'!$A$1:$A$119,0),F$5+1)} -> 53.8608 | G22: {=INDEX('Vehicle Build'!$D:$AC,MATCH("Starship build cost ($mm/stack)",'Vehicle Build'!$A$1:$A$119,0),G$5+1)} -> 47.701521 | H22: {=INDEX('Vehicle Build'!$D:$AC,MATCH("Starship build cost ($mm/stack)",'Vehicle Build'!$A$1:$A$119,0),H$5+1)} -> 42.953795 | I22: {=INDEX('Vehicle Build'!$D:$AC,MATCH("Starship build cost ($mm/stack)",'Vehicle Build'!$A$1:$A$119,0),I$5+1)} -> 39.290393 | J22: {=INDEX('Vehicle Build'!$D:$AC,MATCH("Starship build cost ($mm/stack)",'Vehicle Build'!$A$1:$A$119,0),J$5+1)} -> 36.395225 | K22: {=INDEX('Vehicle Build'!$D:$AC,MATCH("Starship build cost ($mm/stack)",'Vehicle Build'!$A$1:$A$119,0),K$5+1)} -> 34.0481 | ... S22: {=INDEX('Vehicle Build'!$D:$AC,MATCH("Starship build cost ($mm/stack)",'Vehicle Build'!$A$1:$A$119,0),S$5+1)} -> 28.967956
A23: F9 cadence per booster (flights/yr) | D23: =INDEX(Assumptions!$B:$B, MATCH("F9 cadence per booster (flights/year)", Assumptions!$A$1:$A$257, 0)) -> 6 | E23: =INDEX(Assumptions!$B:$B, MATCH("F9 cadence per booster (flights/year)", Assumptions!$A$1:$A$257, 0)) -> 6 | F23: =INDEX(Assumptions!$B:$B, MATCH("F9 cadence per booster (flights/year)", Assumptions!$A$1:$A$257, 0)) -> 6 | G23: =INDEX(Assumptions!$B:$B, MATCH("F9 cadence per booster (flights/year)", Assumptions!$A$1:$A$257, 0)) -> 6 | H23: =INDEX(Assumptions!$B:$B, MATCH("F9 cadence per booster (flights/year)", Assumptions!$A$1:$A$257, 0)) -> 6 | I23: =INDEX(Assumptions!$B:$B, MATCH("F9 cadence per booster (flights/year)", Assumptions!$A$1:$A$257, 0)) -> 6 | J23: =INDEX(Assumptions!$B:$B, MATCH("F9 cadence per booster (flights/year)", Assumptions!$A$1:$A$257, 0)) -> 6 | K23: =INDEX(Assumptions!$B:$B, MATCH("F9 cadence per booster (flights/year)", Assumptions!$A$1:$A$257, 0)) -> 6 | ... S23: =INDEX(Assumptions!$B:$B, MATCH("F9 cadence per booster (flights/year)", Assumptions!$A$1:$A$257, 0)) -> 6
A24: Starship cadence per vehicle (flights/yr) | D24: {=INDEX('Vehicle Build'!$D:$AC,MATCH("Starship BOOSTER cadence per vehicle in service",'Vehicle Build'!$A$1:$A$119,0),D$5+1)} -> 1 | E24: {=INDEX('Vehicle Build'!$D:$AC,MATCH("Starship BOOSTER cadence per vehicle in service",'Vehicle Build'!$A$1:$A$119,0),E$5+1)} -> 2 | F24: {=INDEX('Vehicle Build'!$D:$AC,MATCH("Starship BOOSTER cadence per vehicle in service",'Vehicle Build'!$A$1:$A$119,0),F$5+1)} -> 2 | G24: {=INDEX('Vehicle Build'!$D:$AC,MATCH("Starship BOOSTER cadence per vehicle in service",'Vehicle Build'!$A$1:$A$119,0),G$5+1)} -> 3.5133635 | H24: {=INDEX('Vehicle Build'!$D:$AC,MATCH("Starship BOOSTER cadence per vehicle in service",'Vehicle Build'!$A$1:$A$119,0),H$5+1)} -> 5.3222908 | I24: {=INDEX('Vehicle Build'!$D:$AC,MATCH("Starship BOOSTER cadence per vehicle in service",'Vehicle Build'!$A$1:$A$119,0),I$5+1)} -> 7.7186961 | J24: {=INDEX('Vehicle Build'!$D:$AC,MATCH("Starship BOOSTER cadence per vehicle in service",'Vehicle Build'!$A$1:$A$119,0),J$5+1)} -> 10.446735 | K24: {=INDEX('Vehicle Build'!$D:$AC,MATCH("Starship BOOSTER cadence per vehicle in service",'Vehicle Build'!$A$1:$A$119,0),K$5+1)} -> 12.277403 | ... S24: {=INDEX('Vehicle Build'!$D:$AC,MATCH("Starship BOOSTER cadence per vehicle in service",'Vehicle Build'!$A$1:$A$119,0),S$5+1)} -> 24.270969
A25: F9 vehicle life L (years) | D25: =INDEX(Assumptions!$B:$B, MATCH("Asset life L: Customer Launch F9 (years)", Assumptions!$A$1:$A$257, 0)) -> 8 | E25: =INDEX(Assumptions!$B:$B, MATCH("Asset life L: Customer Launch F9 (years)", Assumptions!$A$1:$A$257, 0)) -> 8 | F25: =INDEX(Assumptions!$B:$B, MATCH("Asset life L: Customer Launch F9 (years)", Assumptions!$A$1:$A$257, 0)) -> 8 | G25: =INDEX(Assumptions!$B:$B, MATCH("Asset life L: Customer Launch F9 (years)", Assumptions!$A$1:$A$257, 0)) -> 8 | H25: =INDEX(Assumptions!$B:$B, MATCH("Asset life L: Customer Launch F9 (years)", Assumptions!$A$1:$A$257, 0)) -> 8 | I25: =INDEX(Assumptions!$B:$B, MATCH("Asset life L: Customer Launch F9 (years)", Assumptions!$A$1:$A$257, 0)) -> 8 | J25: =INDEX(Assumptions!$B:$B, MATCH("Asset life L: Customer Launch F9 (years)", Assumptions!$A$1:$A$257, 0)) -> 8 | K25: =INDEX(Assumptions!$B:$B, MATCH("Asset life L: Customer Launch F9 (years)", Assumptions!$A$1:$A$257, 0)) -> 8 | ... S25: =INDEX(Assumptions!$B:$B, MATCH("Asset life L: Customer Launch F9 (years)", Assumptions!$A$1:$A$257, 0)) -> 8
A26: Starship vehicle life L (years) | D26: =INDEX(Assumptions!$B:$B, MATCH("Asset life L: Customer Launch Starship (years)", Assumptions!$A$1:$A$257, 0)) -> 8 | E26: =INDEX(Assumptions!$B:$B, MATCH("Asset life L: Customer Launch Starship (years)", Assumptions!$A$1:$A$257, 0)) -> 8 | F26: =INDEX(Assumptions!$B:$B, MATCH("Asset life L: Customer Launch Starship (years)", Assumptions!$A$1:$A$257, 0)) -> 8 | G26: =INDEX(Assumptions!$B:$B, MATCH("Asset life L: Customer Launch Starship (years)", Assumptions!$A$1:$A$257, 0)) -> 8 | H26: =INDEX(Assumptions!$B:$B, MATCH("Asset life L: Customer Launch Starship (years)", Assumptions!$A$1:$A$257, 0)) -> 8 | I26: =INDEX(Assumptions!$B:$B, MATCH("Asset life L: Customer Launch Starship (years)", Assumptions!$A$1:$A$257, 0)) -> 8 | J26: =INDEX(Assumptions!$B:$B, MATCH("Asset life L: Customer Launch Starship (years)", Assumptions!$A$1:$A$257, 0)) -> 8 | K26: =INDEX(Assumptions!$B:$B, MATCH("Asset life L: Customer Launch Starship (years)", Assumptions!$A$1:$A$257, 0)) -> 8 | ... S26: =INDEX(Assumptions!$B:$B, MATCH("Asset life L: Customer Launch Starship (years)", Assumptions!$A$1:$A$257, 0)) -> 8
A27: Group WACC | D27: =INDEX(Assumptions!$B:$B, MATCH("Group WACC", Assumptions!$A$1:$A$257, 0)) -> 0.1 | E27: =INDEX(Assumptions!$B:$B, MATCH("Group WACC", Assumptions!$A$1:$A$257, 0)) -> 0.1 | F27: =INDEX(Assumptions!$B:$B, MATCH("Group WACC", Assumptions!$A$1:$A$257, 0)) -> 0.1 | G27: =INDEX(Assumptions!$B:$B, MATCH("Group WACC", Assumptions!$A$1:$A$257, 0)) -> 0.1 | H27: =INDEX(Assumptions!$B:$B, MATCH("Group WACC", Assumptions!$A$1:$A$257, 0)) -> 0.1 | I27: =INDEX(Assumptions!$B:$B, MATCH("Group WACC", Assumptions!$A$1:$A$257, 0)) -> 0.1 | J27: =INDEX(Assumptions!$B:$B, MATCH("Group WACC", Assumptions!$A$1:$A$257, 0)) -> 0.1 | K27: =INDEX(Assumptions!$B:$B, MATCH("Group WACC", Assumptions!$A$1:$A$257, 0)) -> 0.1 | ... S27: =INDEX(Assumptions!$B:$B, MATCH("Group WACC", Assumptions!$A$1:$A$257, 0)) -> 0.1
A28: Customer Launch R&D % (start) | D28: =INDEX(Assumptions!$B:$B, MATCH("Customer Launch R&D: start % of external rev", Assumptions!$A$1:$A$257, 0)) -> 0.05 | E28: =INDEX(Assumptions!$B:$B, MATCH("Customer Launch R&D: start % of external rev", Assumptions!$A$1:$A$257, 0)) -> 0.05 | F28: =INDEX(Assumptions!$B:$B, MATCH("Customer Launch R&D: start % of external rev", Assumptions!$A$1:$A$257, 0)) -> 0.05 | G28: =INDEX(Assumptions!$B:$B, MATCH("Customer Launch R&D: start % of external rev", Assumptions!$A$1:$A$257, 0)) -> 0.05 | H28: =INDEX(Assumptions!$B:$B, MATCH("Customer Launch R&D: start % of external rev", Assumptions!$A$1:$A$257, 0)) -> 0.05 | I28: =INDEX(Assumptions!$B:$B, MATCH("Customer Launch R&D: start % of external rev", Assumptions!$A$1:$A$257, 0)) -> 0.05 | J28: =INDEX(Assumptions!$B:$B, MATCH("Customer Launch R&D: start % of external rev", Assumptions!$A$1:$A$257, 0)) -> 0.05 | K28: =INDEX(Assumptions!$B:$B, MATCH("Customer Launch R&D: start % of external rev", Assumptions!$A$1:$A$257, 0)) -> 0.05 | ... S28: =INDEX(Assumptions!$B:$B, MATCH("Customer Launch R&D: start % of external rev", Assumptions!$A$1:$A$257, 0)) -> 0.05
A29: Customer Launch R&D % (floor) — retired (flat sustaining rate, see A111)
A30: Customer Launch R&D % (CAGR) — retired (flat sustaining rate, see A111)
A31: Launch / vehicle facility CapEx ($mm) | D31: {=INDEX('Facilities Build'!$D:$AC, MATCH("Launch/vehicle facility CapEx total ($mm) ◄ launch/vehicle", 'Facilities Build'!$A$1:$A$74, 0), COLUMN()-COLUMN($D31)+1)} -> 750 | E31: {=INDEX('Facilities Build'!$D:$AC, MATCH("Launch/vehicle facility CapEx total ($mm) ◄ launch/vehicle", 'Facilities Build'!$A$1:$A$74, 0), COLUMN()-COLUMN($D31)+1)} -> 750 | F31: {=INDEX('Facilities Build'!$D:$AC, MATCH("Launch/vehicle facility CapEx total ($mm) ◄ launch/vehicle", 'Facilities Build'!$A$1:$A$74, 0), COLUMN()-COLUMN($D31)+1)} -> 375 | G31: {=INDEX('Facilities Build'!$D:$AC, MATCH("Launch/vehicle facility CapEx total ($mm) ◄ launch/vehicle", 'Facilities Build'!$A$1:$A$74, 0), COLUMN()-COLUMN($D31)+1)} -> 471.4 | H31: {=INDEX('Facilities Build'!$D:$AC, MATCH("Launch/vehicle facility CapEx total ($mm) ◄ launch/vehicle", 'Facilities Build'!$A$1:$A$74, 0), COLUMN()-COLUMN($D31)+1)} -> 1092 | I31: {=INDEX('Facilities Build'!$D:$AC, MATCH("Launch/vehicle facility CapEx total ($mm) ◄ launch/vehicle", 'Facilities Build'!$A$1:$A$74, 0), COLUMN()-COLUMN($D31)+1)} -> 1092 | J31: {=INDEX('Facilities Build'!$D:$AC, MATCH("Launch/vehicle facility CapEx total ($mm) ◄ launch/vehicle", 'Facilities Build'!$A$1:$A$74, 0), COLUMN()-COLUMN($D31)+1)} -> 492 | K31: {=INDEX('Facilities Build'!$D:$AC, MATCH("Launch/vehicle facility CapEx total ($mm) ◄ launch/vehicle", 'Facilities Build'!$A$1:$A$74, 0), COLUMN()-COLUMN($D31)+1)} -> 1575 | ... S31: {=INDEX('Facilities Build'!$D:$AC, MATCH("Launch/vehicle facility CapEx total ($mm) ◄ launch/vehicle", 'Facilities Build'!$A$1:$A$74, 0), COLUMN()-COLUMN($D31)+1)} -> 375
A32: Launch / vehicle facility D&A ($mm) | D32: {=INDEX('Facilities Build'!$D:$AC, MATCH("Launch/vehicle facility D&A total ($mm) ◄ launch/vehicle", 'Facilities Build'!$A$1:$A$74, 0), COLUMN()-COLUMN($D32)+1)} -> 25 | E32: {=INDEX('Facilities Build'!$D:$AC, MATCH("Launch/vehicle facility D&A total ($mm) ◄ launch/vehicle", 'Facilities Build'!$A$1:$A$74, 0), COLUMN()-COLUMN($D32)+1)} -> 50 | F32: {=INDEX('Facilities Build'!$D:$AC, MATCH("Launch/vehicle facility D&A total ($mm) ◄ launch/vehicle", 'Facilities Build'!$A$1:$A$74, 0), COLUMN()-COLUMN($D32)+1)} -> 62.5 | G32: {=INDEX('Facilities Build'!$D:$AC, MATCH("Launch/vehicle facility D&A total ($mm) ◄ launch/vehicle", 'Facilities Build'!$A$1:$A$74, 0), COLUMN()-COLUMN($D32)+1)} -> 78.213333 | H32: {=INDEX('Facilities Build'!$D:$AC, MATCH("Launch/vehicle facility D&A total ($mm) ◄ launch/vehicle", 'Facilities Build'!$A$1:$A$74, 0), COLUMN()-COLUMN($D32)+1)} -> 114.61333 | I32: {=INDEX('Facilities Build'!$D:$AC, MATCH("Launch/vehicle facility D&A total ($mm) ◄ launch/vehicle", 'Facilities Build'!$A$1:$A$74, 0), COLUMN()-COLUMN($D32)+1)} -> 151.01333 | J32: {=INDEX('Facilities Build'!$D:$AC, MATCH("Launch/vehicle facility D&A total ($mm) ◄ launch/vehicle", 'Facilities Build'!$A$1:$A$74, 0), COLUMN()-COLUMN($D32)+1)} -> 167.41333 | K32: {=INDEX('Facilities Build'!$D:$AC, MATCH("Launch/vehicle facility D&A total ($mm) ◄ launch/vehicle", 'Facilities Build'!$A$1:$A$74, 0), COLUMN()-COLUMN($D32)+1)} -> 219.91333 | ... S32: {=INDEX('Facilities Build'!$D:$AC, MATCH("Launch/vehicle facility D&A total ($mm) ◄ launch/vehicle", 'Facilities Build'!$A$1:$A$74, 0), COLUMN()-COLUMN($D32)+1)} -> 399.91333
A35: ▸ BLOCK B: LAUNCH DEMAND & FLEET BUILD
A36: External commercial launch demand (count) | D36: =IFERROR(D13*D15/D11*D139,0) -> 109.48905 | E36: =IFERROR(E13*E15/E11*E139,0) -> 118.77372 | F36: =IFERROR(F13*F15/F11*F139,0) -> 128.84321 | G36: =IFERROR(G13*G15/G11*G139,0) -> 143.09135 | H36: =IFERROR(H13*H15/H11*H139,0) -> 161.25069 | I36: =IFERROR(I13*I15/I11*I139,0) -> 190.49019 | J36: =IFERROR(J13*J15/J11*J139,0) -> 214.05429 | K36: =IFERROR(K13*K15/K11*K139,0) -> 232.1794 | ... S36: =IFERROR(S13*S15/S11*S139,0) -> 444.56677
A37: External government launch demand (count) | D37: =IFERROR(D14*D16/D11*D139,0) -> 65.693431 | E37: =IFERROR(E14*E16/E11*E139,0) -> 68.467153 | F37: =IFERROR(F14*F16/F11*F139,0) -> 71.354015 | G37: =IFERROR(G14*G16/G11*G139,0) -> 76.128818 | H37: =IFERROR(H14*H16/H11*H139,0) -> 82.413731 | I37: =IFERROR(I14*I16/I11*I139,0) -> 93.522446 | J37: =IFERROR(J14*J16/J11*J139,0) -> 100.94735 | K37: =IFERROR(K14*K16/K11*K139,0) -> 105.17305 | ... S37: =IFERROR(S14*S16/S11*S139,0) -> 145.67672
A38: F9 boosters built (yr) | D38: =INDEX(Assumptions!$B:$B,MATCH("F9 base booster build rate (boosters/year, pre-V3-trigger)",Assumptions!$A$1:$A$257,0)) -> 8 | E38: =MAX(0, INDEX(Assumptions!$B:$B,MATCH("F9 base booster build rate (boosters/year, pre-V3-trigger)",Assumptions!$A$1:$A$257,0)) * (1 - MAX(0, E$4 - INDEX(Assumptions!$B:$B,MATCH("V3 Starlink launch trigger year",Assumptions!$A$1:$A$257,0))) / INDEX(Assumptions!$B:$B,MATCH("F9 build-rate decay window (years)",Assumptions!$A$1:$A$257,0)))) -> 8 | F38: =MAX(0, INDEX(Assumptions!$B:$B,MATCH("F9 base booster build rate (boosters/year, pre-V3-trigger)",Assumptions!$A$1:$A$257,0)) * (1 - MAX(0, F$4 - INDEX(Assumptions!$B:$B,MATCH("V3 Starlink launch trigger year",Assumptions!$A$1:$A$257,0))) / INDEX(Assumptions!$B:$B,MATCH("F9 build-rate decay window (years)",Assumptions!$A$1:$A$257,0)))) -> 7 | G38: =MAX(0, INDEX(Assumptions!$B:$B,MATCH("F9 base booster build rate (boosters/year, pre-V3-trigger)",Assumptions!$A$1:$A$257,0)) * (1 - MAX(0, G$4 - INDEX(Assumptions!$B:$B,MATCH("V3 Starlink launch trigger year",Assumptions!$A$1:$A$257,0))) / INDEX(Assumptions!$B:$B,MATCH("F9 build-rate decay window (years)",Assumptions!$A$1:$A$257,0)))) -> 6 | H38: =MAX(0, INDEX(Assumptions!$B:$B,MATCH("F9 base booster build rate (boosters/year, pre-V3-trigger)",Assumptions!$A$1:$A$257,0)) * (1 - MAX(0, H$4 - INDEX(Assumptions!$B:$B,MATCH("V3 Starlink launch trigger year",Assumptions!$A$1:$A$257,0))) / INDEX(Assumptions!$B:$B,MATCH("F9 build-rate decay window (years)",Assumptions!$A$1:$A$257,0)))) -> 5 | I38: =MAX(0, INDEX(Assumptions!$B:$B,MATCH("F9 base booster build rate (boosters/year, pre-V3-trigger)",Assumptions!$A$1:$A$257,0)) * (1 - MAX(0, I$4 - INDEX(Assumptions!$B:$B,MATCH("V3 Starlink launch trigger year",Assumptions!$A$1:$A$257,0))) / INDEX(Assumptions!$B:$B,MATCH("F9 build-rate decay window (years)",Assumptions!$A$1:$A$257,0)))) -> 4 | J38: =MAX(0, INDEX(Assumptions!$B:$B,MATCH("F9 base booster build rate (boosters/year, pre-V3-trigger)",Assumptions!$A$1:$A$257,0)) * (1 - MAX(0, J$4 - INDEX(Assumptions!$B:$B,MATCH("V3 Starlink launch trigger year",Assumptions!$A$1:$A$257,0))) / INDEX(Assumptions!$B:$B,MATCH("F9 build-rate decay window (years)",Assumptions!$A$1:$A$257,0)))) -> 3 | K38: =MAX(0, INDEX(Assumptions!$B:$B,MATCH("F9 base booster build rate (boosters/year, pre-V3-trigger)",Assumptions!$A$1:$A$257,0)) * (1 - MAX(0, K$4 - INDEX(Assumptions!$B:$B,MATCH("V3 Starlink launch trigger year",Assumptions!$A$1:$A$257,0))) / INDEX(Assumptions!$B:$B,MATCH("F9 build-rate decay window (years)",Assumptions!$A$1:$A$257,0)))) -> 2 | L38: =MAX(0, INDEX(Assumptions!$B:$B,MATCH("F9 base booster build rate (boosters/year, pre-V3-trigger)",Assumptions!$A$1:$A$257,0)) * (1 - MAX(0, L$4 - INDEX(Assumptions!$B:$B,MATCH("V3 Starlink launch trigger year",Assumptions!$A$1:$A$257,0))) / INDEX(Assumptions!$B:$B,MATCH("F9 build-rate decay window (years)",Assumptions!$A$1:$A$257,0)))) -> 1 | ... S38: =MAX(0, INDEX(Assumptions!$B:$B,MATCH("F9 base booster build rate (boosters/year, pre-V3-trigger)",Assumptions!$A$1:$A$257,0)) * (1 - MAX(0, S$4 - INDEX(Assumptions!$B:$B,MATCH("V3 Starlink launch trigger year",Assumptions!$A$1:$A$257,0))) / INDEX(Assumptions!$B:$B,MATCH("F9 build-rate decay window (years)",Assumptions!$A$1:$A$257,0)))) -> 0
