Workbook

Sheet Assumptions
D1: 2025 | E1: 2026 | F1: 2027 | G1: 2028 | H1: 2029 | I1: 2030 | J1: 2031 | K1: 2032 | L1: 2033 | M1: 2034 | N1: 2035 | O1: 2036 | P1: 2037 | Q1: 2038 | R1: 2039 | S1: 2040 | T1: 2041 | U1: 2042 | V1: 2043 | W1: 2044 | X1: 2045 | Y1: 2046 | Z1: 2047 | AA1: 2048 | AB1: 2049 | AC1: 2050
A2: §1 GLOBAL | D2: 0 | E2: 1 | F2: 2 | G2: 3 | H2: 4 | I2: 5 | J2: 6 | K2: 7 | L2: 8 | M2: 9 | N2: 10 | O2: 11 | P2: 12 | Q2: 13 | R2: 14 | S2: 15 | T2: 16 | U2: 17 | V2: 18 | W2: 19 | X2: 20 | Y2: 21 | Z2: 22 | AA2: 23 | AB2: 24 | AC2: 25
A3: Tax rate (corporate, US federal + state blended) | B3: 0.21 | C3: Standard US corporate rate; Q4'25 confirms. | AG3: 0.18 | AH3: 0.27 | AI3: triangle | AJ3: MC range covers blue-state vs Trump-era tax reform variability
A4: TAM inflation rate (annual) | B4: 0.025 | C4: TAM growth; industry standard. V30.5 R56 + Q4'25 confirms. | AG4: 0.01 | AH4: 0.05 | AI4: triangle | AJ4: MC range per Q4'25 Valuation Inputs
A5: GNI per capita growth rate (annual) | B5: 0.03 | C5: Used in Starlink demand-curve scaling. | AG5: 0.01 | AH5: 0.06 | AI5: triangle
A6: §2 ALLOCATOR
A7: ▸ Cash pool boundary inputs
A8: Starting cash position EoY 2024 ($mm) | B8: 5000 | C8: Q4'25 anchored ($4.70B rounded). V30.5 had $20B — corrected. | AG8: 3000 | AH8: 7000 | AI8: triangle | AJ8: Q4'25 Valuation Inputs central was within this range
A9: IPO injection amount ($mm) | B9: 30000 | C9: Q4'25 Valuation Inputs R31 central $40B; using $30B as Vlad-locked Base Case. | AG9: 15000 | AH9: 60000 | AI9: lognormal | AJ9: Q4'25 spread; tail upside is meaningful for terminal valuation
A10: IPO injection year | B10: 2027 | C10: Vlad-locked. | AG10: 2026 | AH10: 2028 | AI10: discrete | AJ10: Q4'25 had 2027/2028 split; discrete sample
A11: ▸ Moon/Mars strategic carve-out (Vlad-confirmed MC-variable)
A12: Mars carve-out % of prior-year Group FCF | B12: 0.15 | C12: Spec 06+07 stub. Vlad lock 2026-05-19: central uncertainty on how much SpaceX dedicates to Mars vs terrestrial IRR lines. MC-WIDE. | AG12: 0.03 | AH12: 0.35 | AI12: triangle | AJ12: Wide range — Vlad: 'we don't know how much they'll dedicate'
A13: Mars carve-out floor ($mm/yr) | B13: 1000 | C13: Floor below which carve-out doesn't drop even if prior FCF is small. | AG13: 500 | AH13: 2500 | AI13: triangle | AJ13: MC-variable
A14: Mars carve-out uses prior-year FCF (0/1) | B14: 1 | C14: 1 = prior year (breaks circularity per Principle 22). Structural input. | AI14: fixed
A15: ▸ IRR engine + sigmoid blend parameters
A16: Sigmoid IRR-blend exponent k | B16: 2 | C16: Spec 09 §2.1. Default k=2 across all sigmoid queues. | AG16: 1 | AH16: 3 | AI16: triangle | AJ16: MC tunes allocator concentration vs diversification
A17: Forward IRR weight w (Blended = (1-w)·Spot + w·Forward) | B17: 0.7 | C17: Spec 09 §2.10 unified. V30.5 B82 = 0.7. Same value used at module + vehicle level. | AG17: 0.5 | AH17: 0.85 | AI17: triangle | AJ17: MC tunes forward-looking vs current-period weight
A18: Forward IRR look-ahead horizon (years) | B18: 2 | C18: Y+2 throughout. Spec 09 kept; Y+5 not introduced. | AI18: fixed | AJ18: Structural
A19: MFW-IRR — Starlink economic life N (years) | B19: 5 | C19: Per-vehicle marginal IRR window. Sat useful life. | AG19: 4 | AH19: 7 | AI19: triangle
A20: MFW-IRR — ODC economic life N (years) | B20: 5 | C20: Per-sat marginal IRR window. Compute hardware life. | AG20: 4 | AH20: 7 | AI20: triangle
A21: MFW-IRR — AI Stack economic life N (years) | B21: 5 | C21: Per-product marginal IRR window. | AG21: 3 | AH21: 7 | AI21: triangle
A22: MFW-IRR — Customer Launch economic life clamp MIN (years) | B22: 1 | C22: Lower bound on endogenous N (cadence × lifetime reuses). | AI22: fixed
A23: MFW-IRR — Customer Launch economic life clamp MAX (years) | B23: 10 | C23: Upper bound on endogenous N. | AI23: fixed
A24: ▸ Vehicle build claim (Spec 09 architecture)
A25: Vehicle build claim toggle (0=legacy mode, 1=forward-demand-sized non-module claim) | B25: 1 | C25: Spec 09 architecture. Locked = 1. | AI25: fixed | AJ25: Structural
A26: Vehicle build lead time (years) | B26: 2 | C26: Matches Forward IRR Y+2 horizon. | AG26: 1 | AH26: 3 | AI26: discrete
A27: Launches per Starship vehicle per year (cadence × variant blend, used for sizing) | B27: 24 | C27: Spec 09 stub. ~30 cadence × ~80% variant blend. | AG27: 18 | AH27: 36 | AI27: triangle
A28: Vehicle masked-demand large default (sats; effectively uncapped) | B28: 1000000 | C28: Spec 09 mechanic. Vehicle eligibility binds at pool sizing, not internal ask. | AI28: fixed | AJ28: Structural
A29: Forward aggregate kg demand growth cap (× current capacity) | B29: 2 | C29: Cap on year-over-year demand growth used to size vehicle build claim. | AG29: 1.5 | AH29: 3 | AI29: triangle
A30: §3 CAPACITY (Starship + F9)
A31: ▸ Starship vehicle physical + cost parameters
A32: Super Heavy manufacturing cost ($mm/unit, base year) | B32: 54 | C32: Mach33: booster 60% × $90M total mfg = $54M today. ±25% MC range. Updated Sprint 3 Patch E §6.13. | AG32: 42 | AH32: 70 | AI32: triangle
A33: Starship 2nd-stage manufacturing cost ($mm/unit, base) | B33: 36 | C33: Mach33: ship 40% × $90M total mfg = $36M today. ±25% MC range. Updated Sprint 3 Patch E §6.13. | AG33: 27 | AH33: 50 | AI33: triangle
A34: Payload — booster-only mode (kg-to-LEO) | B34: 150000 | C34: Expendable ship config. Higher because no landing margin. | AG34: 130000 | AH34: 200000 | AI34: triangle | AJ34: Q4'25 Valuation Inputs R19 central 187K — covers MC
A35: Payload — fully reusable mode (kg-to-LEO) | B35: 100000 | C35: Reusable both stages. | AG35: 80000 | AH35: 150000 | AI35: triangle
A36: Lifetime reuses per ship (cap) | B36: 30 | C36: Ship useful life cap. | AG36: 20 | AH36: 50 | AI36: triangle
A37: Manufacturing learning rate (per doubling of cum units) | B37: 0.1 | C37: 10% per doubling. Q4'25 Valuation Inputs R18 central 0.145. | AG37: 0.05 | AH37: 0.2 | AI37: triangle
A38: ▸ Starship cadence (Wright's Law on cum upmass)
A39: Base turnaround time per booster (years/flight) | B39: 1 | C39: 2025 starting point. | AG39: 0.8 | AH39: 1.5 | AI39: triangle
A40: WL learning rate — turnaround vs cum upmass doubling | B40: 0.145 | C40: Legacy model midpoint. Q4'25 confirms. | AG40: 0.05 | AH40: 0.25 | AI40: triangle | AJ40: Q4'25 Valuation Inputs R18 range
A41: Anchor year for cum-upmass Wright's Law | B41: 2025 | C41: Anchor year for the doublings count. | AI41: fixed
A42: Cadence ceiling (flights/booster/year) | B42: 60 | C42: Physical refly ceiling at full maturity. | AG42: 40 | AH42: 100 | AI42: triangle
A43: Max annual production growth rate (multiplier) | B43: 2 | C43: Mfg ceiling (×2/yr max). Q4'25 R27 central 2.5x. | AG43: 1.5 | AH43: 4 | AI43: triangle
A44: ▸ Starship time-varying inputs (year-rows)
A45: Variant mix (% fully reusable) | C45: Step function 0 → 1.0 at 2027 per Vlad lock 2026-05-20. 2025-2026 pre-commercial test era; 2027+ 100% fully reusable LEO. Sprint 7 Lunar Mars reads booster-only memo R41 for ship-expended; LEO consumers (Sprint 3/4/5/10) read R40. Updated Sprint 3 Patch E §6.13. | D45: 0 | E45: 0 | F45: 1 | G45: 1 | H45: 1 | I45: 1 | J45: 1 | K45: 1 | L45: 1 | M45: 1 | N45: 1 | O45: 1 | P45: 1 | Q45: 1 | R45: 1 | S45: 1 | T45: 1 | U45: 1 | V45: 1 | W45: 1 | X45: 1 | Y45: 1 | Z45: 1 | AA45: 1 | AB45: 1 | AC45: 1 | AI45: fixed-yearrow | AJ45: Tech-readiness curve
A46: Lifetime reuses per booster (year cap) | C46: Ramps 5 → 100 as reliability matures. | D46: 5 | E46: 8 | F46: 12 | G46: 18 | H46: 25 | I46: 30 | J46: 35 | K46: 42 | L46: 50 | M46: 58 | N46: 65 | O46: 70 | P46: 75 | Q46: 80 | R46: 85 | S46: 90 | T46: 92 | U46: 94 | V46: 96 | W46: 98 | X46: 100 | Y46: 100 | Z46: 100 | AA46: 100 | AB46: 100 | AC46: 100 | AI46: fixed-yearrow
A47: ▸ Falcon 9 physical + cost parameters
A48: F9 booster (1st stage) mfg cost ($mm/unit) | B48: 30 | C48: 60% of total per reusability matrix source notes. | AG48: 25 | AH48: 35 | AI48: triangle
A49: F9 2nd stage mfg cost ($mm/unit) | B49: 10 | C49: Expendable each flight. | AG49: 8 | AH49: 13 | AI49: triangle
A50: F9 fairing cost net of 75% recovery ($mm/flight) | B50: 1.25 | C50: $5M × 25% non-recovered. | AG50: 1 | AH50: 2 | AI50: triangle
A51: F9 per-launch ops cost ($mm) | B51: 5 | C51: Range, propellant, recovery. | AG51: 3 | AH51: 8 | AI51: triangle
A52: F9 booster refurb % of mfg | B52: 0.03 | C52: Reusability matrix. | AG52: 0.02 | AH52: 0.05 | AI52: triangle
A53: F9 payload to LEO (kg) | B53: 22800 | C53: Block 5 advertised. | AI53: fixed | AJ53: Disclosed
A54: F9 lifetime reuses per booster | B54: 50 | C54: Block 5 demonstrated ~30, theoretical 100+. | AG54: 30 | AH54: 100 | AI54: triangle
A55: F9 Wright's Law mfg learning rate | B55: 0.02 | C55: Mature production line; minimal further learning. | AG55: 0 | AH55: 0.05 | AI55: triangle
A56: F9 cadence per booster (flights/year, flat) | B56: 12 | C56: F9 past learning curve. | AG56: 10 | AH56: 15 | AI56: triangle
A57: F9 base booster build rate (boosters/year, pre-V3-trigger) | B57: 8 | C57: Q4'25 had 17 manufactured in 2025 — but that's pre-decay; this is build floor. | AG57: 6 | AH57: 10 | AI57: triangle
A58: V3 Starlink launch trigger year | B58: 2027 | C58: V3 heavy sats require Starship → F9 demand evaporates. | AG58: 2026 | AH58: 2028 | AI58: discrete
A59: F9 build-rate decay window (years) | B59: 8 | C59: Linear decay over 8 yrs post-trigger. | AG59: 6 | AH59: 12 | AI59: triangle
A60: F9 starting fleet at 2025 SoY (boosters) | B60: 28 | C60: Q4'25 Earth R29 anchored. V30.5 had 24 — corrected. | AI60: fixed | AJ60: Historical anchor
A61: §4 CUSTOMER LAUNCH
A62: F9 customer launch price ($mm/launch) — 2025 anchor | C62: Q4'25 Earth R132 anchored at $111M. V30.5 had $67M — corrected. Year-row with -3%/yr decline. | D62: 111 | E62: 107.67 | F62: 104.44 | G62: 101.3 | H62: 98.26 | I62: 95.31 | J62: 92.45 | K62: 89.68 | L62: 87 | M62: 84.39 | N62: 81.86 | O62: 79.4 | P62: 77.02 | Q62: 74.71 | R62: 72.47 | S62: 70.29 | T62: 68.18 | U62: 66.13 | V62: 64.15 | W62: 62.22 | X62: 60.36 | Y62: 58.55 | Z62: 56.79 | AA62: 55.09 | AB62: 53.43 | AC62: 51.83 | AI62: fixed-yearrow | AJ62: Anchored to Q4'25; declines at 3%/yr
A63: Starship customer launch price ($mm/launch) — year-row | C63: Starts at $100M in 2027, declines 8%/yr (V30.5 R196 trajectory). | D63: 0 | E63: 0 | F63: 100 | G63: 92 | H63: 84.64 | I63: 77.87 | J63: 71.64 | K63: 65.91 | L63: 60.64 | M63: 55.79 | N63: 51.32 | O63: 47.21 | P63: 43.44 | Q63: 39.96 | R63: 36.77 | S63: 33.83 | T63: 31.13 | U63: 28.64 | V63: 26.35 | W63: 24.24 | X63: 22.3 | Y63: 20.52 | Z63: 18.88 | AA63: 17.37 | AB63: 15.98 | AC63: 14.7 | AI63: fixed-yearrow | AJ63: Starts 2027, 8%/yr deflation
A64: Commercial launch market size ($mm/year) — year-row | C64: $8B base 2025, 8% annual growth. | D64: 8000 | E64: 8640 | F64: 9331.2 | G64: 10077.7 | H64: 10883.9 | I64: 11754.6 | J64: 12695 | K64: 13710.6 | L64: 14807.4 | M64: 15992 | N64: 17271.4 | O64: 18653.1 | P64: 20145.4 | Q64: 21757 | R64: 23497.5 | S64: 25377.4 | T64: 27407.5 | U64: 29600.1 | V64: 31968.2 | W64: 34525.6 | X64: 37287.7 | Y64: 40270.7 | Z64: 43492.3 | AA64: 46971.7 | AB64: 50729.4 | AC64: 54787.8 | AI64: fixed-yearrow | AJ64: $8B + 8%/yr growth
A65: Government launch market size ($mm/year) — year-row | C65: $4B base 2025, 5% annual growth. | D65: 4000 | E65: 4200 | F65: 4410 | G65: 4630.5 | H65: 4862.02 | I65: 5105.13 | J65: 5360.38 | K65: 5628.4 | L65: 5909.82 | M65: 6205.31 | N65: 6515.58 | O65: 6841.36 | P65: 7183.43 | Q65: 7542.6 | R65: 7919.73 | S65: 8315.71 | T65: 8731.5 | U65: 9168.07 | V65: 9626.48 | W65: 10107.8 | X65: 10613.2 | Y65: 11143.9 | Z65: 11701 | AA65: 12286.1 | AB65: 12900.4 | AC65: 13545.4 | AI65: fixed-yearrow | AJ65: $4B + 5%/yr growth
A66: SpaceX commercial market share % — year-row | C66: 2025: 70% → 2040: 80% (linear glide). | D66: 0.7 | E66: 0.7067 | F66: 0.7133 | G66: 0.72 | H66: 0.7267 | I66: 0.7333 | J66: 0.74 | K66: 0.7467 | L66: 0.7533 | M66: 0.76 | N66: 0.7667 | O66: 0.7733 | P66: 0.78 | Q66: 0.7867 | R66: 0.7933 | S66: 0.8 | T66: 0.8 | U66: 0.8 | V66: 0.8 | W66: 0.8 | X66: 0.8 | Y66: 0.8 | Z66: 0.8 | AA66: 0.8 | AB66: 0.8 | AC66: 0.8 | AI66: fixed-yearrow
A67: SpaceX government market share % — year-row | C67: 2025: 90% → 2040: 80% (linear decline). | D67: 0.9 | E67: 0.8933 | F67: 0.8867 | G67: 0.88 | H67: 0.8733 | I67: 0.8667 | J67: 0.86 | K67: 0.8533 | L67: 0.8467 | M67: 0.84 | N67: 0.8333 | O67: 0.8267 | P67: 0.82 | Q67: 0.8133 | R67: 0.8067 | S67: 0.8 | T67: 0.8 | U67: 0.8 | V67: 0.8 | W67: 0.8 | X67: 0.8 | Y67: 0.8 | Z67: 0.8 | AA67: 0.8 | AB67: 0.8 | AC67: 0.8 | AI67: fixed-yearrow
A68: Launch insurance % of external revenue | B68: 0.05 | C68: 5% insurance on commercial launches. | AG68: 0.03 | AH68: 0.08 | AI68: triangle
A69: Launch other COGS % of external revenue | B69: 0.02 | C69: Catch-all 2%. | AG69: 0.01 | AH69: 0.04 | AI69: triangle
A70: Customer Launch depreciation useful life (years) | B70: 5 | C70: Spec 02 stub. | AG70: 4 | AH70: 7 | AI70: triangle
A71: §5 STARLINK
A72: ▸ Satellite physical
A73: V2 Mini Mass (kg) | B73: 575 | C73: Disclosed. | AI73: fixed | AJ73: Hard anchor
A74: V3 Mass (kg) | B74: 2000 | C74: V3 estimated. | AG74: 1800 | AH74: 2200 | AI74: triangle
A75: V2 Mini Bandwidth per Sat — BB (Gbps) | B75: 96 | C75: Disclosed. | AI75: fixed | AJ75: Hard anchor
A76: V2 Mini Bandwidth per Sat — DTC (Gbps) | B76: 0.2 | C76: Slim slice for direct-to-cell. Wide MC. | AG76: 0.1 | AH76: 5 | AI76: triangle
A77: V3 BB Bandwidth per Sat — base year (Gbps) | B77: 1000 | C77: V3 design target. Speculative. | AG77: 500 | AH77: 2000 | AI77: triangle
A78: V3 DTC Bandwidth per Sat (Gbps) | B78: 2.75 | C78: V3 DTC design. | AG78: 1 | AH78: 8 | AI78: triangle
A79: Satellite useful life — V2 Mini (years) | B79: 5 | C79: Standard LEO sat life. | AG79: 4 | AH79: 6 | AI79: triangle
A80: Satellite useful life — V3 (years) | B80: 5 | C80: Same useful life assumption. | AG80: 4 | AH80: 7 | AI80: triangle
A81: CapEx Lag (years) | B81: 1 | C81: Year between mfg CapEx and on-orbit deploy. | AI81: fixed
A82: ▸ Wright's Law parameters
A83: Satellite cost per kg — base year ($/kg) | B83: 650 | C83: V2 unit cost / mass. Q4'25 confirms $643.50 in 2025. | AG83: 500 | AH83: 800 | AI83: triangle
A84: Satellite cost per kg — learning rate | B84: 0.05 | C84: 5% per doubling. | AG84: 0.03 | AH84: 0.17 | AI84: triangle | AJ84: Q4'25 wide range
A85: V3 bandwidth per sat — learning rate | B85: 0.05 | C85: Bandwidth learning. | AG85: 0.03 | AH85: 0.17 | AI85: triangle
A86: Cumulative sats at base year (end-2024) | B86: 7486 | C86: Mach33 tracking anchor. | AI86: fixed | AJ86: Historical
A87: Satellite cost floor ($/kg) | B87: 400 | C87: Irreducible mfg cost. | AG87: 300 | AH87: 500 | AI87: triangle
A88: V3 bandwidth cap (Gbps) | B88: 5000 | C88: Physical bandwidth ceiling. | AG88: 3000 | AH88: 7000 | AI88: triangle
A89: V2 Mini cost per kg — base year ($/kg) | B89: 650 | C89: Same as V3 base (shared production line). | AG89: 500 | AH89: 800 | AI89: triangle
A90: V2 Mini cost per kg — learning rate | B90: 0.05 | C90: Wright's Law. | AG90: 0.03 | AH90: 0.1 | AI90: triangle
A91: V2 Mini cost floor ($/kg) | B91: 400 | C91: Symmetric with V3. | AG91: 300 | AH91: 500 | AI91: triangle
A92: ▸ Starshield (Vlad-corrected from Q4'25)
A93: Starshield Reserved % — start | B93: 0.0257 | C93: 2.57% of bandwidth reserved 2025. | AG93: 0.015 | AH93: 0.04 | AI93: triangle
A94: Starshield Reserved % — floor | B94: 0.0001 | C94: Decays toward 0.01%. | AG94: 5e-05 | AH94: 0.005 | AI94: triangle
A95: Starshield Reserved % — decay rate | B95: 0.25 | C95: Q4'25 Valuation Inputs R30 = 0.25. V30.5 had 1.0 — CORRECTED. | AG95: 0.15 | AH95: 0.4 | AI95: triangle | AJ95: Q4'25 anchored
A96: Starshield Rev per Gbps — base year ($/Gbps) | B96: 164699 | C96: Q4'25 Earth R120 anchored. V30.5 had $167,421 — small correction. | AG96: 120000 | AH96: 220000 | AI96: triangle
A97: Starshield Rev per Gbps — decay rate | B97: 0.05 | C97: Price compression. | AG97: 0.03 | AH97: 0.1 | AI97: triangle
A98: ▸ Depreciation parameters
A99: Satellite Dep per kg — base year ($/kg/yr) | B99: 128.8 | C99: Q4'25 R194 confirms. = $650/kg × annual depreciation rate. | AG99: 110 | AH99: 150 | AI99: triangle
A100: Satellite Dep per kg — annual decay rate | B100: 0.01 | C100: Annual decline in dep rate. | AG100: 0.005 | AH100: 0.02 | AI100: triangle
...

Sheet Allocator
AE2: =IFERROR(MATCH("Vehicle build claim ($mm)", $A:$A, 0), "NOT FOUND") -> 23
AE3: =IFERROR(MATCH("Vehicle build claim", $A:$A, 0), "NOT FOUND") -> NOT FOUND
D4: 2025 | E4: 2026 | F4: 2027 | G4: 2028 | H4: 2029 | I4: 2030 | J4: 2031 | K4: 2032 | L4: 2033 | M4: 2034 | N4: 2035 | O4: 2036 | P4: 2037 | Q4: 2038 | R4: 2039 | S4: 2040 | T4: 2041 | U4: 2042 | V4: 2043 | W4: 2044 | X4: 2045 | Y4: 2046 | Z4: 2047 | AA4: 2048 | AB4: 2049 | AC4: 2050 | AE4: =IFERROR(MATCH("Required vehicles ($mm)", $A:$A, 0), "NOT FOUND") -> NOT FOUND
D5: 0 | E5: 1 | F5: 2 | G5: 3 | H5: 4 | I5: 5 | J5: 6 | K5: 7 | L5: 8 | M5: 9 | N5: 10 | O5: 11 | P5: 12 | Q5: 13 | R5: 14 | S5: 15 | T5: 16 | U5: 17 | V5: 18 | W5: 19 | X5: 20 | Y5: 21 | Z5: 22 | AA5: 23 | AB5: 24 | AC5: 25 | AE5: =IFERROR(MATCH("Total vehicle build claim ($mm)", $A:$A, 0), "NOT FOUND") -> NOT FOUND
A7: §1 CASH POOL TRACKER
A8: Starting cash position EoY 2024 ($mm) | D8: =IF(D$5=0, INDEX(Assumptions!$B:$B, MATCH("Starting cash position EoY 2024 ($mm)", Assumptions!$A:$A, 0)), 0) -> 5000 | E8: =0 -> 0 | F8: =0 -> 0 | G8: =0 -> 0 | H8: =0 -> 0 | I8: =0 -> 0 | J8: =0 -> 0 | K8: =0 -> 0 | L8: =0 -> 0 | ... AC8: =0 -> 0
A9: IPO injection this year ($mm) | D9: =IF(D$4=INDEX(Assumptions!$B:$B, MATCH("IPO injection year", Assumptions!$A:$A, 0)), INDEX(Assumptions!$B:$B, MATCH("IPO injection amount ($mm)", Assumptions!$A:$A, 0)), 0) -> 0 | E9: =IF(E$4=INDEX(Assumptions!$B:$B, MATCH("IPO injection year", Assumptions!$A:$A, 0)), INDEX(Assumptions!$B:$B, MATCH("IPO injection amount ($mm)", Assumptions!$A:$A, 0)), 0) -> 0 | F9: =IF(F$4=INDEX(Assumptions!$B:$B, MATCH("IPO injection year", Assumptions!$A:$A, 0)), INDEX(Assumptions!$B:$B, MATCH("IPO injection amount ($mm)", Assumptions!$A:$A, 0)), 0) -> 30000 | G9: =IF(G$4=INDEX(Assumptions!$B:$B, MATCH("IPO injection year", Assumptions!$A:$A, 0)), INDEX(Assumptions!$B:$B, MATCH("IPO injection amount ($mm)", Assumptions!$A:$A, 0)), 0) -> 0 | H9: =IF(H$4=INDEX(Assumptions!$B:$B, MATCH("IPO injection year", Assumptions!$A:$A, 0)), INDEX(Assumptions!$B:$B, MATCH("IPO injection amount ($mm)", Assumptions!$A:$A, 0)), 0) -> 0 | I9: =IF(I$4=INDEX(Assumptions!$B:$B, MATCH("IPO injection year", Assumptions!$A:$A, 0)), INDEX(Assumptions!$B:$B, MATCH("IPO injection amount ($mm)", Assumptions!$A:$A, 0)), 0) -> 0 | J9: =IF(J$4=INDEX(Assumptions!$B:$B, MATCH("IPO injection year", Assumptions!$A:$A, 0)), INDEX(Assumptions!$B:$B, MATCH("IPO injection amount ($mm)", Assumptions!$A:$A, 0)), 0) -> 0 | K9: =IF(K$4=INDEX(Assumptions!$B:$B, MATCH("IPO injection year", Assumptions!$A:$A, 0)), INDEX(Assumptions!$B:$B, MATCH("IPO injection amount ($mm)", Assumptions!$A:$A, 0)), 0) -> 0 | ... AC9: =IF(AC$4=INDEX(Assumptions!$B:$B, MATCH("IPO injection year", Assumptions!$A:$A, 0)), INDEX(Assumptions!$B:$B, MATCH("IPO injection amount ($mm)", Assumptions!$A:$A, 0)), 0) -> 0
A10: Prior-year Group FCF read ($mm) | D10: {=IFERROR(IF(D$5=0, 0, INDEX('Group P&L'!$D:$AC, MATCH("GROUP FCF ($mm)", 'Group P&L'!$A:$A, 0), D$5)), 0)} -> 0 | E10: {=IFERROR(IF(E$5=0, 0, INDEX('Group P&L'!$D:$AC, MATCH("GROUP FCF ($mm)", 'Group P&L'!$A:$A, 0), E$5)), 0)} -> -2982.4363 | F10: {=IFERROR(IF(F$5=0, 0, INDEX('Group P&L'!$D:$AC, MATCH("GROUP FCF ($mm)", 'Group P&L'!$A:$A, 0), F$5)), 0)} -> -3764.0125 | G10: {=IFERROR(IF(G$5=0, 0, INDEX('Group P&L'!$D:$AC, MATCH("GROUP FCF ($mm)", 'Group P&L'!$A:$A, 0), G$5)), 0)} -> -1752.1013 | H10: {=IFERROR(IF(H$5=0, 0, INDEX('Group P&L'!$D:$AC, MATCH("GROUP FCF ($mm)", 'Group P&L'!$A:$A, 0), H$5)), 0)} -> -560.14791 | I10: {=IFERROR(IF(I$5=0, 0, INDEX('Group P&L'!$D:$AC, MATCH("GROUP FCF ($mm)", 'Group P&L'!$A:$A, 0), I$5)), 0)} -> 693.5007 | J10: {=IFERROR(IF(J$5=0, 0, INDEX('Group P&L'!$D:$AC, MATCH("GROUP FCF ($mm)", 'Group P&L'!$A:$A, 0), J$5)), 0)} -> 552.68545 | K10: {=IFERROR(IF(K$5=0, 0, INDEX('Group P&L'!$D:$AC, MATCH("GROUP FCF ($mm)", 'Group P&L'!$A:$A, 0), K$5)), 0)} -> 732.04703 | ... AC10: {=IFERROR(IF(AC$5=0, 0, INDEX('Group P&L'!$D:$AC, MATCH("GROUP FCF ($mm)", 'Group P&L'!$A:$A, 0), AC$5)), 0)} -> 7872.0421
A15: Cash BoY ($mm) | D15: =D8+D9+D10 -> 5000 | E15: =D15+E10+E9 -> 2017.5637 | F15: =E15+F10+F9 -> 28253.551 | G15: =F15+G10+G9 -> 26501.45 | H15: =G15+H10+H9 -> 25941.302 | I15: =H15+I10+I9 -> 26634.803 | J15: =I15+J10+J9 -> 27187.488 | K15: =J15+K10+K9 -> 27919.535 | L15: =K15+L10+L9 -> 28477.906 | ... AC15: =AB15+AC10+AC9 -> 82182.842
A17: §2 QUEUE GATE
A18: OpEx claim ($mm) | D18: {=IFERROR(INDEX(OpEx!$D:$AC, MATCH("Total OpEx ($mm)", OpEx!$A:$A, 0), D$5+1), 0)} -> 4309.6782 | E18: {=IFERROR(INDEX(OpEx!$D:$AC, MATCH("Total OpEx ($mm)", OpEx!$A:$A, 0), E$5+1), 0)} -> 3948.6144 | F18: {=IFERROR(INDEX(OpEx!$D:$AC, MATCH("Total OpEx ($mm)", OpEx!$A:$A, 0), F$5+1), 0)} -> 3884.7616 | G18: {=IFERROR(INDEX(OpEx!$D:$AC, MATCH("Total OpEx ($mm)", OpEx!$A:$A, 0), G$5+1), 0)} -> 3657.8936 | H18: {=IFERROR(INDEX(OpEx!$D:$AC, MATCH("Total OpEx ($mm)", OpEx!$A:$A, 0), H$5+1), 0)} -> 3414.6507 | I18: {=IFERROR(INDEX(OpEx!$D:$AC, MATCH("Total OpEx ($mm)", OpEx!$A:$A, 0), I$5+1), 0)} -> 3435.6386 | J18: {=IFERROR(INDEX(OpEx!$D:$AC, MATCH("Total OpEx ($mm)", OpEx!$A:$A, 0), J$5+1), 0)} -> 3525.0708 | K18: {=IFERROR(INDEX(OpEx!$D:$AC, MATCH("Total OpEx ($mm)", OpEx!$A:$A, 0), K$5+1), 0)} -> 3568.6303 | ... AC18: {=IFERROR(INDEX(OpEx!$D:$AC, MATCH("Total OpEx ($mm)", OpEx!$A:$A, 0), AC$5+1), 0)} -> 2471.9799
A19: Corporate CapEx claim ($mm) | D19: {=IFERROR(INDEX(CapEx!$D:$AC, MATCH("Total Corporate CapEx ($mm)", CapEx!$A:$A, 0), D$5+1), 0)} -> 110 | E19: {=IFERROR(INDEX(CapEx!$D:$AC, MATCH("Total Corporate CapEx ($mm)", CapEx!$A:$A, 0), E$5+1), 0)} -> 110 | F19: {=IFERROR(INDEX(CapEx!$D:$AC, MATCH("Total Corporate CapEx ($mm)", CapEx!$A:$A, 0), F$5+1), 0)} -> 110 | G19: {=IFERROR(INDEX(CapEx!$D:$AC, MATCH("Total Corporate CapEx ($mm)", CapEx!$A:$A, 0), G$5+1), 0)} -> 110 | H19: {=IFERROR(INDEX(CapEx!$D:$AC, MATCH("Total Corporate CapEx ($mm)", CapEx!$A:$A, 0), H$5+1), 0)} -> 110 | I19: {=IFERROR(INDEX(CapEx!$D:$AC, MATCH("Total Corporate CapEx ($mm)", CapEx!$A:$A, 0), I$5+1), 0)} -> 110 | J19: {=IFERROR(INDEX(CapEx!$D:$AC, MATCH("Total Corporate CapEx ($mm)", CapEx!$A:$A, 0), J$5+1), 0)} -> 110 | K19: {=IFERROR(INDEX(CapEx!$D:$AC, MATCH("Total Corporate CapEx ($mm)", CapEx!$A:$A, 0), K$5+1), 0)} -> 110 | ... AC19: {=IFERROR(INDEX(CapEx!$D:$AC, MATCH("Total Corporate CapEx ($mm)", CapEx!$A:$A, 0), AC$5+1), 0)} -> 110
A20: Spectrum CapEx claim ($mm) | D20: {=IFERROR(INDEX(CapEx!$D:$AC, MATCH("EchoStar mid-band CapEx ($mm)", CapEx!$A:$A, 0), D$5+1), 0)} -> 5000 | E20: {=IFERROR(INDEX(CapEx!$D:$AC, MATCH("EchoStar mid-band CapEx ($mm)", CapEx!$A:$A, 0), E$5+1), 0)} -> 8000 | F20: {=IFERROR(INDEX(CapEx!$D:$AC, MATCH("EchoStar mid-band CapEx ($mm)", CapEx!$A:$A, 0), F$5+1), 0)} -> 5000 | G20: {=IFERROR(INDEX(CapEx!$D:$AC, MATCH("EchoStar mid-band CapEx ($mm)", CapEx!$A:$A, 0), G$5+1), 0)} -> 2000 | H20: {=IFERROR(INDEX(CapEx!$D:$AC, MATCH("EchoStar mid-band CapEx ($mm)", CapEx!$A:$A, 0), H$5+1), 0)} -> 0 | I20: {=IFERROR(INDEX(CapEx!$D:$AC, MATCH("EchoStar mid-band CapEx ($mm)", CapEx!$A:$A, 0), I$5+1), 0)} -> 0 | J20: {=IFERROR(INDEX(CapEx!$D:$AC, MATCH("EchoStar mid-band CapEx ($mm)", CapEx!$A:$A, 0), J$5+1), 0)} -> 0 | K20: {=IFERROR(INDEX(CapEx!$D:$AC, MATCH("EchoStar mid-band CapEx ($mm)", CapEx!$A:$A, 0), K$5+1), 0)} -> 0 | ... AC20: {=IFERROR(INDEX(CapEx!$D:$AC, MATCH("EchoStar mid-band CapEx ($mm)", CapEx!$A:$A, 0), AC$5+1), 0)} -> 0
A21: Taxes claim ($mm) | D21: {=IFERROR(INDEX('Group P&L'!$D:$AC, MATCH("Taxes ($mm)", 'Group P&L'!$A:$A, 0), D$5+1), 0)} -> 819.83327 | E21: {=IFERROR(INDEX('Group P&L'!$D:$AC, MATCH("Taxes ($mm)", 'Group P&L'!$A:$A, 0), E$5+1), 0)} -> 1023.0916 | F21: {=IFERROR(INDEX('Group P&L'!$D:$AC, MATCH("Taxes ($mm)", 'Group P&L'!$A:$A, 0), F$5+1), 0)} -> 710.21719 | G21: {=IFERROR(INDEX('Group P&L'!$D:$AC, MATCH("Taxes ($mm)", 'Group P&L'!$A:$A, 0), G$5+1), 0)} -> 492.51791 | H21: {=IFERROR(INDEX('Group P&L'!$D:$AC, MATCH("Taxes ($mm)", 'Group P&L'!$A:$A, 0), H$5+1), 0)} -> 285.70274 | I21: {=IFERROR(INDEX('Group P&L'!$D:$AC, MATCH("Taxes ($mm)", 'Group P&L'!$A:$A, 0), I$5+1), 0)} -> 226.45926 | J21: {=IFERROR(INDEX('Group P&L'!$D:$AC, MATCH("Taxes ($mm)", 'Group P&L'!$A:$A, 0), J$5+1), 0)} -> 190.39148 | K21: {=IFERROR(INDEX('Group P&L'!$D:$AC, MATCH("Taxes ($mm)", 'Group P&L'!$A:$A, 0), K$5+1), 0)} -> 11.024267 | ... AC21: {=IFERROR(INDEX('Group P&L'!$D:$AC, MATCH("Taxes ($mm)", 'Group P&L'!$A:$A, 0), AC$5+1), 0)} -> 0
A22: Mars/Moon carve-out claim ($mm) | D22: =D35 -> 1000 | E22: =E35 -> 1000 | F22: =F35 -> 1000 | G22: =G35 -> 1000 | H22: =H35 -> 1000 | I22: =I35 -> 1000 | J22: =J35 -> 1000 | K22: =K35 -> 1000 | ... AC22: =AC35 -> 1000
A23: Vehicle build claim ($mm) | D23: =D156 -> 0 | E23: =E156 -> 83.711001 | F23: =F156 -> 126.98606 | G23: =G156 -> 126.48848 | H23: =H156 -> 152.67406 | I23: =I156 -> 97.909678 | J23: =J156 -> 185.01994 | K23: =K156 -> 152.23353 | ... AC23: =AC156 -> 0
A28: Year-N non-module claims ($mm) | D28: =SUM(D18:D23) -> 11239.512 | E28: =SUM(E18:E23) -> 14165.417 | F28: =SUM(F18:F23) -> 10831.965 | G28: =SUM(G18:G23) -> 7386.8999 | H28: =SUM(H18:H23) -> 4963.0275 | I28: =SUM(I18:I23) -> 4870.0075 | J28: =SUM(J18:J23) -> 5010.4822 | K28: =SUM(K18:K23) -> 4841.8881 | ... AC28: =SUM(AC18:AC23) -> 3581.9799
A29: Available cash for IRR queue ($mm) | D29: =MAX(0, D15-D28) -> 0 | E29: =MAX(0, E15-E28) -> 0 | F29: =MAX(0, F15-F28) -> 17421.586 | G29: =MAX(0, G15-G28) -> 19114.55 | H29: =MAX(0, H15-H28) -> 20978.275 | I29: =MAX(0, I15-I28) -> 21764.795 | J29: =MAX(0, J15-J28) -> 22177.006 | K29: =MAX(0, K15-K28) -> 23077.647 | ... AC29: =MAX(0, AC15-AC28) -> 78600.862
A31: §3 MARS/MOON STRATEGIC CARVE-OUT
A32: Mars carve-out % of prior-year Group FCF (input) | C32: Reads Assumptions R12 by canonical label. Base Case 15%; MC [3%, 35%] triangle. | D32: =INDEX(Assumptions!$B:$B, MATCH("Mars carve-out % of prior-year Group FCF", Assumptions!$A:$A, 0)) -> 0.15 | E32: =INDEX(Assumptions!$B:$B, MATCH("Mars carve-out % of prior-year Group FCF", Assumptions!$A:$A, 0)) -> 0.15 | F32: =INDEX(Assumptions!$B:$B, MATCH("Mars carve-out % of prior-year Group FCF", Assumptions!$A:$A, 0)) -> 0.15 | G32: =INDEX(Assumptions!$B:$B, MATCH("Mars carve-out % of prior-year Group FCF", Assumptions!$A:$A, 0)) -> 0.15 | H32: =INDEX(Assumptions!$B:$B, MATCH("Mars carve-out % of prior-year Group FCF", Assumptions!$A:$A, 0)) -> 0.15 | I32: =INDEX(Assumptions!$B:$B, MATCH("Mars carve-out % of prior-year Group FCF", Assumptions!$A:$A, 0)) -> 0.15 | J32: =INDEX(Assumptions!$B:$B, MATCH("Mars carve-out % of prior-year Group FCF", Assumptions!$A:$A, 0)) -> 0.15 | K32: =INDEX(Assumptions!$B:$B, MATCH("Mars carve-out % of prior-year Group FCF", Assumptions!$A:$A, 0)) -> 0.15 | ... AC32: =INDEX(Assumptions!$B:$B, MATCH("Mars carve-out % of prior-year Group FCF", Assumptions!$A:$A, 0)) -> 0.15
A33: Mars carve-out floor ($mm/yr) (input) | C33: Reads Assumptions R13. Base Case $1,000M; MC [$500M, $2,500M] triangle. | D33: =INDEX(Assumptions!$B:$B, MATCH("Mars carve-out floor ($mm/yr)", Assumptions!$A:$A, 0)) -> 1000 | E33: =INDEX(Assumptions!$B:$B, MATCH("Mars carve-out floor ($mm/yr)", Assumptions!$A:$A, 0)) -> 1000 | F33: =INDEX(Assumptions!$B:$B, MATCH("Mars carve-out floor ($mm/yr)", Assumptions!$A:$A, 0)) -> 1000 | G33: =INDEX(Assumptions!$B:$B, MATCH("Mars carve-out floor ($mm/yr)", Assumptions!$A:$A, 0)) -> 1000 | H33: =INDEX(Assumptions!$B:$B, MATCH("Mars carve-out floor ($mm/yr)", Assumptions!$A:$A, 0)) -> 1000 | I33: =INDEX(Assumptions!$B:$B, MATCH("Mars carve-out floor ($mm/yr)", Assumptions!$A:$A, 0)) -> 1000 | J33: =INDEX(Assumptions!$B:$B, MATCH("Mars carve-out floor ($mm/yr)", Assumptions!$A:$A, 0)) -> 1000 | K33: =INDEX(Assumptions!$B:$B, MATCH("Mars carve-out floor ($mm/yr)", Assumptions!$A:$A, 0)) -> 1000 | ... AC33: =INDEX(Assumptions!$B:$B, MATCH("Mars carve-out floor ($mm/yr)", Assumptions!$A:$A, 0)) -> 1000
A34: Prior-year Group FCF read ($mm/yr) | C34: Sprint 9 fix: (1) label drift Sprint 7 used 'GROUP FCF' → Sprint 9 publishes 'GROUP FCF ($mm)' canonical; (2) column reference bug Sprint 7 used E$5 (next column year-offset) → Sprint 9 uses D$5 (current column year-offset) for correct prior-year lookback. D34 (2025) reads INDEX col_num=0 → IFERROR returns 0; E34 (2026) reads col_num=1 = 2025 FCF; ... AC34 (2050) reads col_num=25 = 2049 FCF. | D34: {=IFERROR(IF(D$5=0, 0, INDEX('Group P&L'!$D:$AC, MATCH("GROUP FCF ($mm)", 'Group P&L'!$A:$A, 0), D$5)), 0)} -> 0 | E34: {=IFERROR(IF(E$5=0, 0, INDEX('Group P&L'!$D:$AC, MATCH("GROUP FCF ($mm)", 'Group P&L'!$A:$A, 0), E$5)), 0)} -> -2982.4363 | F34: {=IFERROR(IF(F$5=0, 0, INDEX('Group P&L'!$D:$AC, MATCH("GROUP FCF ($mm)", 'Group P&L'!$A:$A, 0), F$5)), 0)} -> -3764.0125 | G34: {=IFERROR(IF(G$5=0, 0, INDEX('Group P&L'!$D:$AC, MATCH("GROUP FCF ($mm)", 'Group P&L'!$A:$A, 0), G$5)), 0)} -> -1752.1013 | H34: {=IFERROR(IF(H$5=0, 0, INDEX('Group P&L'!$D:$AC, MATCH("GROUP FCF ($mm)", 'Group P&L'!$A:$A, 0), H$5)), 0)} -> -560.14791 | I34: {=IFERROR(IF(I$5=0, 0, INDEX('Group P&L'!$D:$AC, MATCH("GROUP FCF ($mm)", 'Group P&L'!$A:$A, 0), I$5)), 0)} -> 693.5007 | J34: {=IFERROR(IF(J$5=0, 0, INDEX('Group P&L'!$D:$AC, MATCH("GROUP FCF ($mm)", 'Group P&L'!$A:$A, 0), J$5)), 0)} -> 552.68545 | K34: {=IFERROR(IF(K$5=0, 0, INDEX('Group P&L'!$D:$AC, MATCH("GROUP FCF ($mm)", 'Group P&L'!$A:$A, 0), K$5)), 0)} -> 732.04703 | ... AC34: {=IFERROR(IF(AC$5=0, 0, INDEX('Group P&L'!$D:$AC, MATCH("GROUP FCF ($mm)", 'Group P&L'!$A:$A, 0), AC$5)), 0)} -> 7872.0421
A35: Mars/Moon strategic carve-out ($mm/yr) | C35: Architecture §11.1: MAX(floor, prior-year FCF × pct). Pre-Sprint-9: prior FCF=0 → carve-out hits floor. CANONICAL ROW Sprint 10 Queue Gate subtracts + Lunar Mars module reads. | D35: =MAX(D33, D32*D34) -> 1000 | E35: =MAX(E33, E32*E34) -> 1000 | F35: =MAX(F33, F32*F34) -> 1000 | G35: =MAX(G33, G32*G34) -> 1000 | H35: =MAX(H33, H32*H34) -> 1000 | I35: =MAX(I33, I32*I34) -> 1000 | J35: =MAX(J33, J32*J34) -> 1000 | K35: =MAX(K33, K32*K34) -> 1000 | ... AC35: =MAX(AC33, AC32*AC34) -> 1180.8063
A36: Lunar share of carve-out (% — year-row) | C36: Reads Assumptions R226 year-row by canonical label. | D36: {=INDEX(Assumptions!$D:$AC, MATCH("Lunar share of Mars/Moon carve-out cash — year-row", Assumptions!$A:$A, 0), D$5+1)} -> 1 | E36: {=INDEX(Assumptions!$D:$AC, MATCH("Lunar share of Mars/Moon carve-out cash — year-row", Assumptions!$A:$A, 0), E$5+1)} -> 1 | F36: {=INDEX(Assumptions!$D:$AC, MATCH("Lunar share of Mars/Moon carve-out cash — year-row", Assumptions!$A:$A, 0), F$5+1)} -> 1 | G36: {=INDEX(Assumptions!$D:$AC, MATCH("Lunar share of Mars/Moon carve-out cash — year-row", Assumptions!$A:$A, 0), G$5+1)} -> 0.7 | H36: {=INDEX(Assumptions!$D:$AC, MATCH("Lunar share of Mars/Moon carve-out cash — year-row", Assumptions!$A:$A, 0), H$5+1)} -> 0.7 | I36: {=INDEX(Assumptions!$D:$AC, MATCH("Lunar share of Mars/Moon carve-out cash — year-row", Assumptions!$A:$A, 0), I$5+1)} -> 0.7 | J36: {=INDEX(Assumptions!$D:$AC, MATCH("Lunar share of Mars/Moon carve-out cash — year-row", Assumptions!$A:$A, 0), J$5+1)} -> 0.7 | K36: {=INDEX(Assumptions!$D:$AC, MATCH("Lunar share of Mars/Moon carve-out cash — year-row", Assumptions!$A:$A, 0), K$5+1)} -> 0.7 | ... AC36: {=INDEX(Assumptions!$D:$AC, MATCH("Lunar share of Mars/Moon carve-out cash — year-row", Assumptions!$A:$A, 0), AC$5+1)} -> 0.7
A37: Mars share of carve-out (% — year-row) | C37: Reads Assumptions R227 year-row by canonical label. | D37: {=INDEX(Assumptions!$D:$AC, MATCH("Mars share of carve-out cash — year-row", Assumptions!$A:$A, 0), D$5+1)} -> 0 | E37: {=INDEX(Assumptions!$D:$AC, MATCH("Mars share of carve-out cash — year-row", Assumptions!$A:$A, 0), E$5+1)} -> 0 | F37: {=INDEX(Assumptions!$D:$AC, MATCH("Mars share of carve-out cash — year-row", Assumptions!$A:$A, 0), F$5+1)} -> 0 | G37: {=INDEX(Assumptions!$D:$AC, MATCH("Mars share of carve-out cash — year-row", Assumptions!$A:$A, 0), G$5+1)} -> 0.3 | H37: {=INDEX(Assumptions!$D:$AC, MATCH("Mars share of carve-out cash — year-row", Assumptions!$A:$A, 0), H$5+1)} -> 0.3 | I37: {=INDEX(Assumptions!$D:$AC, MATCH("Mars share of carve-out cash — year-row", Assumptions!$A:$A, 0), I$5+1)} -> 0.3 | J37: {=INDEX(Assumptions!$D:$AC, MATCH("Mars share of carve-out cash — year-row", Assumptions!$A:$A, 0), J$5+1)} -> 0.3 | K37: {=INDEX(Assumptions!$D:$AC, MATCH("Mars share of carve-out cash — year-row", Assumptions!$A:$A, 0), K$5+1)} -> 0.3 | ... AC37: {=INDEX(Assumptions!$D:$AC, MATCH("Mars share of carve-out cash — year-row", Assumptions!$A:$A, 0), AC$5+1)} -> 0.3
A39: §4 CASH IRR-PRIORITY SIGMOID QUEUE
A41: ▸ Customer Launch (in-queue module)
A42: Customer Launch Blended IRR | D42: {=IFERROR(INDEX('Customer Launch'!$D:$AC, MATCH("Blended IRR", 'Customer Launch'!$A:$A, 0), D$5+1), 0)} -> 2.672961 | E42: {=IFERROR(INDEX('Customer Launch'!$D:$AC, MATCH("Blended IRR", 'Customer Launch'!$A:$A, 0), E$5+1), 0)} -> 2.5531329 | F42: {=IFERROR(INDEX('Customer Launch'!$D:$AC, MATCH("Blended IRR", 'Customer Launch'!$A:$A, 0), F$5+1), 0)} -> 2.3854104 | G42: {=IFERROR(INDEX('Customer Launch'!$D:$AC, MATCH("Blended IRR", 'Customer Launch'!$A:$A, 0), G$5+1), 0)} -> 2.2397201 | H42: {=IFERROR(INDEX('Customer Launch'!$D:$AC, MATCH("Blended IRR", 'Customer Launch'!$A:$A, 0), H$5+1), 0)} -> 2.1144672 | I42: {=IFERROR(INDEX('Customer Launch'!$D:$AC, MATCH("Blended IRR", 'Customer Launch'!$A:$A, 0), I$5+1), 0)} -> 1.8066341 | J42: {=IFERROR(INDEX('Customer Launch'!$D:$AC, MATCH("Blended IRR", 'Customer Launch'!$A:$A, 0), J$5+1), 0)} -> 1.8979413 | K42: {=IFERROR(INDEX('Customer Launch'!$D:$AC, MATCH("Blended IRR", 'Customer Launch'!$A:$A, 0), K$5+1), 0)} -> 1.4068518 | ... AC42: {=IFERROR(INDEX('Customer Launch'!$D:$AC, MATCH("Blended IRR", 'Customer Launch'!$A:$A, 0), AC$5+1), 0)} -> -0.0050735922
A43: Customer Launch cash demand ($mm) | D43: {=IFERROR(INDEX('Customer Launch'!$D:$AC, MATCH("Module CapEx ($mm)", 'Customer Launch'!$A:$A, 0), D$5+1), 0)} -> 32.86065 | E43: {=IFERROR(INDEX('Customer Launch'!$D:$AC, MATCH("Module CapEx ($mm)", 'Customer Launch'!$A:$A, 0), E$5+1), 0)} -> 21.80802 | F43: {=IFERROR(INDEX('Customer Launch'!$D:$AC, MATCH("Module CapEx ($mm)", 'Customer Launch'!$A:$A, 0), F$5+1), 0)} -> 21.780008 | G43: {=IFERROR(INDEX('Customer Launch'!$D:$AC, MATCH("Module CapEx ($mm)", 'Customer Launch'!$A:$A, 0), G$5+1), 0)} -> 21.752738 | H43: {=IFERROR(INDEX('Customer Launch'!$D:$AC, MATCH("Module CapEx ($mm)", 'Customer Launch'!$A:$A, 0), H$5+1), 0)} -> 21.278337 | I43: {=IFERROR(INDEX('Customer Launch'!$D:$AC, MATCH("Module CapEx ($mm)", 'Customer Launch'!$A:$A, 0), I$5+1), 0)} -> 20.738221 | J43: {=IFERROR(INDEX('Customer Launch'!$D:$AC, MATCH("Module CapEx ($mm)", 'Customer Launch'!$A:$A, 0), J$5+1), 0)} -> 20.554165 | K43: {=IFERROR(INDEX('Customer Launch'!$D:$AC, MATCH("Module CapEx ($mm)", 'Customer Launch'!$A:$A, 0), K$5+1), 0)} -> 17.606898 | ... AC43: {=IFERROR(INDEX('Customer Launch'!$D:$AC, MATCH("Module CapEx ($mm)", 'Customer Launch'!$A:$A, 0), AC$5+1), 0)} -> 9.1984314
A44: Customer Launch weight | D44: =MAX(D42, 0)^INDEX(Assumptions!$B:$B, MATCH("Sigmoid IRR-blend exponent k", Assumptions!$A:$A, 0)) * IF(D43 > 0, 1, 0) -> 7.1447205 | E44: =MAX(E42, 0)^INDEX(Assumptions!$B:$B, MATCH("Sigmoid IRR-blend exponent k", Assumptions!$A:$A, 0)) * IF(E43 > 0, 1, 0) -> 6.5184874 | F44: =MAX(F42, 0)^INDEX(Assumptions!$B:$B, MATCH("Sigmoid IRR-blend exponent k", Assumptions!$A:$A, 0)) * IF(F43 > 0, 1, 0) -> 5.6901826 | G44: =MAX(G42, 0)^INDEX(Assumptions!$B:$B, MATCH("Sigmoid IRR-blend exponent k", Assumptions!$A:$A, 0)) * IF(G43 > 0, 1, 0) -> 5.0163459 | H44: =MAX(H42, 0)^INDEX(Assumptions!$B:$B, MATCH("Sigmoid IRR-blend exponent k", Assumptions!$A:$A, 0)) * IF(H43 > 0, 1, 0) -> 4.4709717 | I44: =MAX(I42, 0)^INDEX(Assumptions!$B:$B, MATCH("Sigmoid IRR-blend exponent k", Assumptions!$A:$A, 0)) * IF(I43 > 0, 1, 0) -> 3.2639266 | J44: =MAX(J42, 0)^INDEX(Assumptions!$B:$B, MATCH("Sigmoid IRR-blend exponent k", Assumptions!$A:$A, 0)) * IF(J43 > 0, 1, 0) -> 3.6021813 | K44: =MAX(K42, 0)^INDEX(Assumptions!$B:$B, MATCH("Sigmoid IRR-blend exponent k", Assumptions!$A:$A, 0)) * IF(K43 > 0, 1, 0) -> 1.9792321 | ... AC44: =MAX(AC42, 0)^INDEX(Assumptions!$B:$B, MATCH("Sigmoid IRR-blend exponent k", Assumptions!$A:$A, 0)) * IF(AC43 > 0, 1, 0) -> 0
A45: Customer Launch proposed allocation ($mm) | D45: =MIN(IF(D42 > 0, D43, 0), $D$29 * D44 / IF($D$80 > 0, $D$80, 1)) -> 0 | E45: =MIN(IF(E42 > 0, E43, 0), $D$29 * E44 / IF($D$80 > 0, $D$80, 1)) -> 0 | F45: =MIN(IF(F42 > 0, F43, 0), $D$29 * F44 / IF($D$80 > 0, $D$80, 1)) -> 0 | G45: =MIN(IF(G42 > 0, G43, 0), $D$29 * G44 / IF($D$80 > 0, $D$80, 1)) -> 0 | H45: =MIN(IF(H42 > 0, H43, 0), $D$29 * H44 / IF($D$80 > 0, $D$80, 1)) -> 0 | I45: =MIN(IF(I42 > 0, I43, 0), $D$29 * I44 / IF($D$80 > 0, $D$80, 1)) -> 0 | J45: =MIN(IF(J42 > 0, J43, 0), $D$29 * J44 / IF($D$80 > 0, $D$80, 1)) -> 0 | K45: =MIN(IF(K42 > 0, K43, 0), $D$29 * K44 / IF($D$80 > 0, $D$80, 1)) -> 0 | ... AC45: =MIN(IF(AC42 > 0, AC43, 0), $D$29 * AC44 / IF($D$80 > 0, $D$80, 1)) -> 0
A46: ▸ Starlink V2 BB
A47: Starlink V2 BB Blended IRR | D47: {=IFERROR(INDEX(Starlink!$D:$AC, MATCH("Memo: V2 BB Blended IRR", Starlink!$A:$A, 0), D$5+1), 0)} -> 1.0015767 | E47: {=IFERROR(INDEX(Starlink!$D:$AC, MATCH("Memo: V2 BB Blended IRR", Starlink!$A:$A, 0), E$5+1), 0)} -> 1.3773794 | F47: {=IFERROR(INDEX(Starlink!$D:$AC, MATCH("Memo: V2 BB Blended IRR", Starlink!$A:$A, 0), F$5+1), 0)} -> 1.827446 | G47: {=IFERROR(INDEX(Starlink!$D:$AC, MATCH("Memo: V2 BB Blended IRR", Starlink!$A:$A, 0), G$5+1), 0)} -> -0.21617069 | H47: {=IFERROR(INDEX(Starlink!$D:$AC, MATCH("Memo: V2 BB Blended IRR", Starlink!$A:$A, 0), H$5+1), 0)} -> -0.07171016 | I47: {=IFERROR(INDEX(Starlink!$D:$AC, MATCH("Memo: V2 BB Blended IRR", Starlink!$A:$A, 0), I$5+1), 0)} -> -1 | J47: {=IFERROR(INDEX(Starlink!$D:$AC, MATCH("Memo: V2 BB Blended IRR", Starlink!$A:$A, 0), J$5+1), 0)} -> -1 | K47: {=IFERROR(INDEX(Starlink!$D:$AC, MATCH("Memo: V2 BB Blended IRR", Starlink!$A:$A, 0), K$5+1), 0)} -> -1 | ... AC47: {=IFERROR(INDEX(Starlink!$D:$AC, MATCH("Memo: V2 BB Blended IRR", Starlink!$A:$A, 0), AC$5+1), 0)} -> -1
A48: Starlink V2 BB cash demand ($mm) | D48: {=IF(D$4 >= INDEX(Assumptions!$B:$B, MATCH("V2 phase-out year (no V2 BB / V2 DTC launches from this year)", Assumptions!$A:$A, 0)), 0, IFERROR(INDEX(Starlink!$D:$AC, MATCH("V2 BB sat CapEx ($mm)", Starlink!$A:$A, 0), D$5+1) + INDEX(Starlink!$D:$AC, MATCH("V2 BB facility CapEx ($mm)", Starlink!$A:$A, 0), D$5+1), 0))} -> 1116.3913 | E48: {=IF(E$4 >= INDEX(Assumptions!$B:$B, MATCH("V2 phase-out year (no V2 BB / V2 DTC launches from this year)", Assumptions!$A:$A, 0)), 0, IFERROR(INDEX(Starlink!$D:$AC, MATCH("V2 BB sat CapEx ($mm)", Starlink!$A:$A, 0), E$5+1) + INDEX(Starlink!$D:$AC, MATCH("V2 BB facility CapEx ($mm)", Starlink!$A:$A, 0), E$5+1), 0))} -> 0 | F48: {=IF(F$4 >= INDEX(Assumptions!$B:$B, MATCH("V2 phase-out year (no V2 BB / V2 DTC launches from this year)", Assumptions!$A:$A, 0)), 0, IFERROR(INDEX(Starlink!$D:$AC, MATCH("V2 BB sat CapEx ($mm)", Starlink!$A:$A, 0), F$5+1) + INDEX(Starlink!$D:$AC, MATCH("V2 BB facility CapEx ($mm)", Starlink!$A:$A, 0), F$5+1), 0))} -> 0 | G48: {=IF(G$4 >= INDEX(Assumptions!$B:$B, MATCH("V2 phase-out year (no V2 BB / V2 DTC launches from this year)", Assumptions!$A:$A, 0)), 0, IFERROR(INDEX(Starlink!$D:$AC, MATCH("V2 BB sat CapEx ($mm)", Starlink!$A:$A, 0), G$5+1) + INDEX(Starlink!$D:$AC, MATCH("V2 BB facility CapEx ($mm)", Starlink!$A:$A, 0), G$5+1), 0))} -> 0 | H48: {=IF(H$4 >= INDEX(Assumptions!$B:$B, MATCH("V2 phase-out year (no V2 BB / V2 DTC launches from this year)", Assumptions!$A:$A, 0)), 0, IFERROR(INDEX(Starlink!$D:$AC, MATCH("V2 BB sat CapEx ($mm)", Starlink!$A:$A, 0), H$5+1) + INDEX(Starlink!$D:$AC, MATCH("V2 BB facility CapEx ($mm)", Starlink!$A:$A, 0), H$5+1), 0))} -> 0 | I48: {=IF(I$4 >= INDEX(Assumptions!$B:$B, MATCH("V2 phase-out year (no V2 BB / V2 DTC launches from this year)", Assumptions!$A:$A, 0)), 0, IFERROR(INDEX(Starlink!$D:$AC, MATCH("V2 BB sat CapEx ($mm)", Starlink!$A:$A, 0), I$5+1) + INDEX(Starlink!$D:$AC, MATCH("V2 BB facility CapEx ($mm)", Starlink!$A:$A, 0), I$5+1), 0))} -> 0 | J48: {=IF(J$4 >= INDEX(Assumptions!$B:$B, MATCH("V2 phase-out year (no V2 BB / V2 DTC launches from this year)", Assumptions!$A:$A, 0)), 0, IFERROR(INDEX(Starlink!$D:$AC, MATCH("V2 BB sat CapEx ($mm)", Starlink!$A:$A, 0), J$5+1) + INDEX(Starlink!$D:$AC, MATCH("V2 BB facility CapEx ($mm)", Starlink!$A:$A, 0), J$5+1), 0))} -> 0 | K48: {=IF(K$4 >= INDEX(Assumptions!$B:$B, MATCH("V2 phase-out year (no V2 BB / V2 DTC launches from this year)", Assumptions!$A:$A, 0)), 0, IFERROR(INDEX(Starlink!$D:$AC, MATCH("V2 BB sat CapEx ($mm)", Starlink!$A:$A, 0), K$5+1) + INDEX(Starlink!$D:$AC, MATCH("V2 BB facility CapEx ($mm)", Starlink!$A:$A, 0), K$5+1), 0))} -> 0 | ... AC48: {=IF(AC$4 >= INDEX(Assumptions!$B:$B, MATCH("V2 phase-out year (no V2 BB / V2 DTC launches from this year)", Assumptions!$A:$A, 0)), 0, IFERROR(INDEX(Starlink!$D:$AC, MATCH("V2 BB sat CapEx ($mm)", Starlink!$A:$A, 0), AC$5+1) + INDEX(Starlink!$D:$AC, MATCH("V2 BB facility CapEx ($mm)", Starlink!$A:$A, 0), AC$5+1), 0))} -> 0
A49: Starlink V2 BB weight | D49: =MAX(D47, 0)^INDEX(Assumptions!$B:$B, MATCH("Sigmoid IRR-blend exponent k", Assumptions!$A:$A, 0)) * IF(D48 > 0, 1, 0) -> 1.0031558 | E49: =MAX(E47, 0)^INDEX(Assumptions!$B:$B, MATCH("Sigmoid IRR-blend exponent k", Assumptions!$A:$A, 0)) * IF(E48 > 0, 1, 0) -> 0 | F49: =MAX(F47, 0)^INDEX(Assumptions!$B:$B, MATCH("Sigmoid IRR-blend exponent k", Assumptions!$A:$A, 0)) * IF(F48 > 0, 1, 0) -> 0 | G49: =MAX(G47, 0)^INDEX(Assumptions!$B:$B, MATCH("Sigmoid IRR-blend exponent k", Assumptions!$A:$A, 0)) * IF(G48 > 0, 1, 0) -> 0 | H49: =MAX(H47, 0)^INDEX(Assumptions!$B:$B, MATCH("Sigmoid IRR-blend exponent k", Assumptions!$A:$A, 0)) * IF(H48 > 0, 1, 0) -> 0 | I49: =MAX(I47, 0)^INDEX(Assumptions!$B:$B, MATCH("Sigmoid IRR-blend exponent k", Assumptions!$A:$A, 0)) * IF(I48 > 0, 1, 0) -> 0 | J49: =MAX(J47, 0)^INDEX(Assumptions!$B:$B, MATCH("Sigmoid IRR-blend exponent k", Assumptions!$A:$A, 0)) * IF(J48 > 0, 1, 0) -> 0 | K49: =MAX(K47, 0)^INDEX(Assumptions!$B:$B, MATCH("Sigmoid IRR-blend exponent k", Assumptions!$A:$A, 0)) * IF(K48 > 0, 1, 0) -> 0 | ... AC49: =MAX(AC47, 0)^INDEX(Assumptions!$B:$B, MATCH("Sigmoid IRR-blend exponent k", Assumptions!$A:$A, 0)) * IF(AC48 > 0, 1, 0) -> 0
A50: Starlink V2 BB proposed allocation ($mm) | D50: =MIN(IF(D47 > 0, D48, 0), $D$29 * D49 / IF($D$80 > 0, $D$80, 1)) -> 0 | E50: =MIN(IF(E47 > 0, E48, 0), $D$29 * E49 / IF($D$80 > 0, $D$80, 1)) -> 0 | F50: =MIN(IF(F47 > 0, F48, 0), $D$29 * F49 / IF($D$80 > 0, $D$80, 1)) -> 0 | G50: =MIN(IF(G47 > 0, G48, 0), $D$29 * G49 / IF($D$80 > 0, $D$80, 1)) -> 0 | H50: =MIN(IF(H47 > 0, H48, 0), $D$29 * H49 / IF($D$80 > 0, $D$80, 1)) -> 0 | I50: =MIN(IF(I47 > 0, I48, 0), $D$29 * I49 / IF($D$80 > 0, $D$80, 1)) -> 0 | J50: =MIN(IF(J47 > 0, J48, 0), $D$29 * J49 / IF($D$80 > 0, $D$80, 1)) -> 0 | K50: =MIN(IF(K47 > 0, K48, 0), $D$29 * K49 / IF($D$80 > 0, $D$80, 1)) -> 0 | ... AC50: =MIN(IF(AC47 > 0, AC48, 0), $D$29 * AC49 / IF($D$80 > 0, $D$80, 1)) -> 0
A51: ▸ Starlink V2 DTC
A52: Starlink V2 DTC Blended IRR | D52: {=IFERROR(INDEX(Starlink!$D:$AC, MATCH("Memo: V2 DTC Blended IRR", Starlink!$A:$A, 0), D$5+1), 0)} -> 0.13805576 | E52: {=IFERROR(INDEX(Starlink!$D:$AC, MATCH("Memo: V2 DTC Blended IRR", Starlink!$A:$A, 0), E$5+1), 0)} -> 0.27607671 | F52: {=IFERROR(INDEX(Starlink!$D:$AC, MATCH("Memo: V2 DTC Blended IRR", Starlink!$A:$A, 0), F$5+1), 0)} -> 0.42717676 | G52: {=IFERROR(INDEX(Starlink!$D:$AC, MATCH("Memo: V2 DTC Blended IRR", Starlink!$A:$A, 0), G$5+1), 0)} -> 0.52736311 | H52: {=IFERROR(INDEX(Starlink!$D:$AC, MATCH("Memo: V2 DTC Blended IRR", Starlink!$A:$A, 0), H$5+1), 0)} -> 0.63751435 | I52: {=IFERROR(INDEX(Starlink!$D:$AC, MATCH("Memo: V2 DTC Blended IRR", Starlink!$A:$A, 0), I$5+1), 0)} -> 0.73028364 | J52: {=IFERROR(INDEX(Starlink!$D:$AC, MATCH("Memo: V2 DTC Blended IRR", Starlink!$A:$A, 0), J$5+1), 0)} -> 0.83195988 | K52: {=IFERROR(INDEX(Starlink!$D:$AC, MATCH("Memo: V2 DTC Blended IRR", Starlink!$A:$A, 0), K$5+1), 0)} -> 0.94366019 | ... AC52: {=IFERROR(INDEX(Starlink!$D:$AC, MATCH("Memo: V2 DTC Blended IRR", Starlink!$A:$A, 0), AC$5+1), 0)} -> 0.15189202
A53: Starlink V2 DTC cash demand ($mm) | D53: {=IF(D$4 >= INDEX(Assumptions!$B:$B, MATCH("V2 phase-out year (no V2 BB / V2 DTC launches from this year)", Assumptions!$A:$A, 0)), 0, IFERROR(INDEX(Starlink!$D:$AC, MATCH("V2 DTC sat CapEx ($mm)", Starlink!$A:$A, 0), D$5+1) + INDEX(Starlink!$D:$AC, MATCH("V2 DTC facility CapEx ($mm)", Starlink!$A:$A, 0), D$5+1), 0))} -> 68.0225 | E53: {=IF(E$4 >= INDEX(Assumptions!$B:$B, MATCH("V2 phase-out year (no V2 BB / V2 DTC launches from this year)", Assumptions!$A:$A, 0)), 0, IFERROR(INDEX(Starlink!$D:$AC, MATCH("V2 DTC sat CapEx ($mm)", Starlink!$A:$A, 0), E$5+1) + INDEX(Starlink!$D:$AC, MATCH("V2 DTC facility CapEx ($mm)", Starlink!$A:$A, 0), E$5+1), 0))} -> 0 | F53: {=IF(F$4 >= INDEX(Assumptions!$B:$B, MATCH("V2 phase-out year (no V2 BB / V2 DTC launches from this year)", Assumptions!$A:$A, 0)), 0, IFERROR(INDEX(Starlink!$D:$AC, MATCH("V2 DTC sat CapEx ($mm)", Starlink!$A:$A, 0), F$5+1) + INDEX(Starlink!$D:$AC, MATCH("V2 DTC facility CapEx ($mm)", Starlink!$A:$A, 0), F$5+1), 0))} -> 0 | G53: {=IF(G$4 >= INDEX(Assumptions!$B:$B, MATCH("V2 phase-out year (no V2 BB / V2 DTC launches from this year)", Assumptions!$A:$A, 0)), 0, IFERROR(INDEX(Starlink!$D:$AC, MATCH("V2 DTC sat CapEx ($mm)", Starlink!$A:$A, 0), G$5+1) + INDEX(Starlink!$D:$AC, MATCH("V2 DTC facility CapEx ($mm)", Starlink!$A:$A, 0), G$5+1), 0))} -> 0 | H53: {=IF(H$4 >= INDEX(Assumptions!$B:$B, MATCH("V2 phase-out year (no V2 BB / V2 DTC launches from this year)", Assumptions!$A:$A, 0)), 0, IFERROR(INDEX(Starlink!$D:$AC, MATCH("V2 DTC sat CapEx ($mm)", Starlink!$A:$A, 0), H$5+1) + INDEX(Starlink!$D:$AC, MATCH("V2 DTC facility CapEx ($mm)", Starlink!$A:$A, 0), H$5+1), 0))} -> 0 | I53: {=IF(I$4 >= INDEX(Assumptions!$B:$B, MATCH("V2 phase-out year (no V2 BB / V2 DTC launches from this year)", Assumptions!$A:$A, 0)), 0, IFERROR(INDEX(Starlink!$D:$AC, MATCH("V2 DTC sat CapEx ($mm)", Starlink!$A:$A, 0), I$5+1) + INDEX(Starlink!$D:$AC, MATCH("V2 DTC facility CapEx ($mm)", Starlink!$A:$A, 0), I$5+1), 0))} -> 0 | J53: {=IF(J$4 >= INDEX(Assumptions!$B:$B, MATCH("V2 phase-out year (no V2 BB / V2 DTC launches from this year)", Assumptions!$A:$A, 0)), 0, IFERROR(INDEX(Starlink!$D:$AC, MATCH("V2 DTC sat CapEx ($mm)", Starlink!$A:$A, 0), J$5+1) + INDEX(Starlink!$D:$AC, MATCH("V2 DTC facility CapEx ($mm)", Starlink!$A:$A, 0), J$5+1), 0))} -> 0 | K53: {=IF(K$4 >= INDEX(Assumptions!$B:$B, MATCH("V2 phase-out year (no V2 BB / V2 DTC launches from this year)", Assumptions!$A:$A, 0)), 0, IFERROR(INDEX(Starlink!$D:$AC, MATCH("V2 DTC sat CapEx ($mm)", Starlink!$A:$A, 0), K$5+1) + INDEX(Starlink!$D:$AC, MATCH("V2 DTC facility CapEx ($mm)", Starlink!$A:$A, 0), K$5+1), 0))} -> 0 | ... AC53: {=IF(AC$4 >= INDEX(Assumptions!$B:$B, MATCH("V2 phase-out year (no V2 BB / V2 DTC launches from this year)", Assumptions!$A:$A, 0)), 0, IFERROR(INDEX(Starlink!$D:$AC, MATCH("V2 DTC sat CapEx ($mm)", Starlink!$A:$A, 0), AC$5+1) + INDEX(Starlink!$D:$AC, MATCH("V2 DTC facility CapEx ($mm)", Starlink!$A:$A, 0), AC$5+1), 0))} -> 0
A54: Starlink V2 DTC weight | D54: =MAX(D52, 0)^INDEX(Assumptions!$B:$B, MATCH("Sigmoid IRR-blend exponent k", Assumptions!$A:$A, 0)) * IF(D53 > 0, 1, 0) -> 0.019059393 | E54: =MAX(E52, 0)^INDEX(Assumptions!$B:$B, MATCH("Sigmoid IRR-blend exponent k", Assumptions!$A:$A, 0)) * IF(E53 > 0, 1, 0) -> 0 | F54: =MAX(F52, 0)^INDEX(Assumptions!$B:$B, MATCH("Sigmoid IRR-blend exponent k", Assumptions!$A:$A, 0)) * IF(F53 > 0, 1, 0) -> 0 | G54: =MAX(G52, 0)^INDEX(Assumptions!$B:$B, MATCH("Sigmoid IRR-blend exponent k", Assumptions!$A:$A, 0)) * IF(G53 > 0, 1, 0) -> 0 | H54: =MAX(H52, 0)^INDEX(Assumptions!$B:$B, MATCH("Sigmoid IRR-blend exponent k", Assumptions!$A:$A, 0)) * IF(H53 > 0, 1, 0) -> 0 | I54: =MAX(I52, 0)^INDEX(Assumptions!$B:$B, MATCH("Sigmoid IRR-blend exponent k", Assumptions!$A:$A, 0)) * IF(I53 > 0, 1, 0) -> 0 | J54: =MAX(J52, 0)^INDEX(Assumptions!$B:$B, MATCH("Sigmoid IRR-blend exponent k", Assumptions!$A:$A, 0)) * IF(J53 > 0, 1, 0) -> 0 | K54: =MAX(K52, 0)^INDEX(Assumptions!$B:$B, MATCH("Sigmoid IRR-blend exponent k", Assumptions!$A:$A, 0)) * IF(K53 > 0, 1, 0) -> 0 | ... AC54: =MAX(AC52, 0)^INDEX(Assumptions!$B:$B, MATCH("Sigmoid IRR-blend exponent k", Assumptions!$A:$A, 0)) * IF(AC53 > 0, 1, 0) -> 0
A55: Starlink V2 DTC proposed allocation ($mm) | D55: =MIN(IF(D52 > 0, D53, 0), $D$29 * D54 / IF($D$80 > 0, $D$80, 1)) -> 0 | E55: =MIN(IF(E52 > 0, E53, 0), $D$29 * E54 / IF($D$80 > 0, $D$80, 1)) -> 0 | F55: =MIN(IF(F52 > 0, F53, 0), $D$29 * F54 / IF($D$80 > 0, $D$80, 1)) -> 0 | G55: =MIN(IF(G52 > 0, G53, 0), $D$29 * G54 / IF($D$80 > 0, $D$80, 1)) -> 0 | H55: =MIN(IF(H52 > 0, H53, 0), $D$29 * H54 / IF($D$80 > 0, $D$80, 1)) -> 0 | I55: =MIN(IF(I52 > 0, I53, 0), $D$29 * I54 / IF($D$80 > 0, $D$80, 1)) -> 0 | J55: =MIN(IF(J52 > 0, J53, 0), $D$29 * J54 / IF($D$80 > 0, $D$80, 1)) -> 0 | K55: =MIN(IF(K52 > 0, K53, 0), $D$29 * K54 / IF($D$80 > 0, $D$80, 1)) -> 0 | ... AC55: =MIN(IF(AC52 > 0, AC53, 0), $D$29 * AC54 / IF($D$80 > 0, $D$80, 1)) -> 0
A56: ▸ Starlink V3 BB
A57: Starlink V3 BB Blended IRR | D57: {=IFERROR(INDEX(Starlink!$D:$AC, MATCH("Memo: V3 BB Blended IRR", Starlink!$A:$A, 0), D$5+1), 0)} -> 3.5735863 | E57: {=IFERROR(INDEX(Starlink!$D:$AC, MATCH("Memo: V3 BB Blended IRR", Starlink!$A:$A, 0), E$5+1), 0)} -> 4.7830801 | F57: {=IFERROR(INDEX(Starlink!$D:$AC, MATCH("Memo: V3 BB Blended IRR", Starlink!$A:$A, 0), F$5+1), 0)} -> 6.2508513 | G57: {=IFERROR(INDEX(Starlink!$D:$AC, MATCH("Memo: V3 BB Blended IRR", Starlink!$A:$A, 0), G$5+1), 0)} -> 0.96348162 | H57: {=IFERROR(INDEX(Starlink!$D:$AC, MATCH("Memo: V3 BB Blended IRR", Starlink!$A:$A, 0), H$5+1), 0)} -> 1.4370641 | I57: {=IFERROR(INDEX(Starlink!$D:$AC, MATCH("Memo: V3 BB Blended IRR", Starlink!$A:$A, 0), I$5+1), 0)} -> -1 | J57: {=IFERROR(INDEX(Starlink!$D:$AC, MATCH("Memo: V3 BB Blended IRR", Starlink!$A:$A, 0), J$5+1), 0)} -> -1 | K57: {=IFERROR(INDEX(Starlink!$D:$AC, MATCH("Memo: V3 BB Blended IRR", Starlink!$A:$A, 0), K$5+1), 0)} -> -1 | ... AC57: {=IFERROR(INDEX(Starlink!$D:$AC, MATCH("Memo: V3 BB Blended IRR", Starlink!$A:$A, 0), AC$5+1), 0)} -> -1
A58: Starlink V3 BB cash demand ($mm) | D58: {=IF(D$4 < INDEX('Launch Capacity'!$D:$AC, MATCH("V3 Starlink launch trigger year", 'Launch Capacity'!$A:$A, 0), 1), 0, IFERROR(INDEX(Starlink!$D:$AC, MATCH("V3 BB sat CapEx ($mm)", Starlink!$A:$A, 0), D$5+1) + INDEX(Starlink!$D:$AC, MATCH("V3 BB facility CapEx ($mm)", Starlink!$A:$A, 0), D$5+1), 0))} -> 0 | E58: {=IF(E$4 < INDEX('Launch Capacity'!$D:$AC, MATCH("V3 Starlink launch trigger year", 'Launch Capacity'!$A:$A, 0), 1), 0, IFERROR(INDEX(Starlink!$D:$AC, MATCH("V3 BB sat CapEx ($mm)", Starlink!$A:$A, 0), E$5+1) + INDEX(Starlink!$D:$AC, MATCH("V3 BB facility CapEx ($mm)", Starlink!$A:$A, 0), E$5+1), 0))} -> 0 | F58: {=IF(F$4 < INDEX('Launch Capacity'!$D:$AC, MATCH("V3 Starlink launch trigger year", 'Launch Capacity'!$A:$A, 0), 1), 0, IFERROR(INDEX(Starlink!$D:$AC, MATCH("V3 BB sat CapEx ($mm)", Starlink!$A:$A, 0), F$5+1) + INDEX(Starlink!$D:$AC, MATCH("V3 BB facility CapEx ($mm)", Starlink!$A:$A, 0), F$5+1), 0))} -> 0 | G58: {=IF(G$4 < INDEX('Launch Capacity'!$D:$AC, MATCH("V3 Starlink launch trigger year", 'Launch Capacity'!$A:$A, 0), 1), 0, IFERROR(INDEX(Starlink!$D:$AC, MATCH("V3 BB sat CapEx ($mm)", Starlink!$A:$A, 0), G$5+1) + INDEX(Starlink!$D:$AC, MATCH("V3 BB facility CapEx ($mm)", Starlink!$A:$A, 0), G$5+1), 0))} -> 0 | H58: {=IF(H$4 < INDEX('Launch Capacity'!$D:$AC, MATCH("V3 Starlink launch trigger year", 'Launch Capacity'!$A:$A, 0), 1), 0, IFERROR(INDEX(Starlink!$D:$AC, MATCH("V3 BB sat CapEx ($mm)", Starlink!$A:$A, 0), H$5+1) + INDEX(Starlink!$D:$AC, MATCH("V3 BB facility CapEx ($mm)", Starlink!$A:$A, 0), H$5+1), 0))} -> 0 | I58: {=IF(I$4 < INDEX('Launch Capacity'!$D:$AC, MATCH("V3 Starlink launch trigger year", 'Launch Capacity'!$A:$A, 0), 1), 0, IFERROR(INDEX(Starlink!$D:$AC, MATCH("V3 BB sat CapEx ($mm)", Starlink!$A:$A, 0), I$5+1) + INDEX(Starlink!$D:$AC, MATCH("V3 BB facility CapEx ($mm)", Starlink!$A:$A, 0), I$5+1), 0))} -> 0 | J58: {=IF(J$4 < INDEX('Launch Capacity'!$D:$AC, MATCH("V3 Starlink launch trigger year", 'Launch Capacity'!$A:$A, 0), 1), 0, IFERROR(INDEX(Starlink!$D:$AC, MATCH("V3 BB sat CapEx ($mm)", Starlink!$A:$A, 0), J$5+1) + INDEX(Starlink!$D:$AC, MATCH("V3 BB facility CapEx ($mm)", Starlink!$A:$A, 0), J$5+1), 0))} -> 0 | K58: {=IF(K$4 < INDEX('Launch Capacity'!$D:$AC, MATCH("V3 Starlink launch trigger year", 'Launch Capacity'!$A:$A, 0), 1), 0, IFERROR(INDEX(Starlink!$D:$AC, MATCH("V3 BB sat CapEx ($mm)", Starlink!$A:$A, 0), K$5+1) + INDEX(Starlink!$D:$AC, MATCH("V3 BB facility CapEx ($mm)", Starlink!$A:$A, 0), K$5+1), 0))} -> 0 | ... AC58: {=IF(AC$4 < INDEX('Launch Capacity'!$D:$AC, MATCH("V3 Starlink launch trigger year", 'Launch Capacity'!$A:$A, 0), 1), 0, IFERROR(INDEX(Starlink!$D:$AC, MATCH("V3 BB sat CapEx ($mm)", Starlink!$A:$A, 0), AC$5+1) + INDEX(Starlink!$D:$AC, MATCH("V3 BB facility CapEx ($mm)", Starlink!$A:$A, 0), AC$5+1), 0))} -> 0
A59: Starlink V3 BB weight | D59: =MAX(D57, 0)^INDEX(Assumptions!$B:$B, MATCH("Sigmoid IRR-blend exponent k", Assumptions!$A:$A, 0)) * IF(D58 > 0, 1, 0) -> 0 | E59: =MAX(E57, 0)^INDEX(Assumptions!$B:$B, MATCH("Sigmoid IRR-blend exponent k", Assumptions!$A:$A, 0)) * IF(E58 > 0, 1, 0) -> 0 | F59: =MAX(F57, 0)^INDEX(Assumptions!$B:$B, MATCH("Sigmoid IRR-blend exponent k", Assumptions!$A:$A, 0)) * IF(F58 > 0, 1, 0) -> 0 | G59: =MAX(G57, 0)^INDEX(Assumptions!$B:$B, MATCH("Sigmoid IRR-blend exponent k", Assumptions!$A:$A, 0)) * IF(G58 > 0, 1, 0) -> 0 | H59: =MAX(H57, 0)^INDEX(Assumptions!$B:$B, MATCH("Sigmoid IRR-blend exponent k", Assumptions!$A:$A, 0)) * IF(H58 > 0, 1, 0) -> 0 | I59: =MAX(I57, 0)^INDEX(Assumptions!$B:$B, MATCH("Sigmoid IRR-blend exponent k", Assumptions!$A:$A, 0)) * IF(I58 > 0, 1, 0) -> 0 | J59: =MAX(J57, 0)^INDEX(Assumptions!$B:$B, MATCH("Sigmoid IRR-blend exponent k", Assumptions!$A:$A, 0)) * IF(J58 > 0, 1, 0) -> 0 | K59: =MAX(K57, 0)^INDEX(Assumptions!$B:$B, MATCH("Sigmoid IRR-blend exponent k", Assumptions!$A:$A, 0)) * IF(K58 > 0, 1, 0) -> 0 | ... AC59: =MAX(AC57, 0)^INDEX(Assumptions!$B:$B, MATCH("Sigmoid IRR-blend exponent k", Assumptions!$A:$A, 0)) * IF(AC58 > 0, 1, 0) -> 0
A60: Starlink V3 BB proposed allocation ($mm) | D60: =MIN(IF(D57 > 0, D58, 0), $D$29 * D59 / IF($D$80 > 0, $D$80, 1)) -> 0 | E60: =MIN(IF(E57 > 0, E58, 0), $D$29 * E59 / IF($D$80 > 0, $D$80, 1)) -> 0 | F60: =MIN(IF(F57 > 0, F58, 0), $D$29 * F59 / IF($D$80 > 0, $D$80, 1)) -> 0 | G60: =MIN(IF(G57 > 0, G58, 0), $D$29 * G59 / IF($D$80 > 0, $D$80, 1)) -> 0 | H60: =MIN(IF(H57 > 0, H58, 0), $D$29 * H59 / IF($D$80 > 0, $D$80, 1)) -> 0 | I60: =MIN(IF(I57 > 0, I58, 0), $D$29 * I59 / IF($D$80 > 0, $D$80, 1)) -> 0 | J60: =MIN(IF(J57 > 0, J58, 0), $D$29 * J59 / IF($D$80 > 0, $D$80, 1)) -> 0 | K60: =MIN(IF(K57 > 0, K58, 0), $D$29 * K59 / IF($D$80 > 0, $D$80, 1)) -> 0 | ... AC60: =MIN(IF(AC57 > 0, AC58, 0), $D$29 * AC59 / IF($D$80 > 0, $D$80, 1)) -> 0
A61: ▸ Starlink V3 DTC
A62: Starlink V3 DTC Blended IRR | D62: {=IFERROR(INDEX(Starlink!$D:$AC, MATCH("Memo: V3 DTC Blended IRR", Starlink!$A:$A, 0), D$5+1), 0)} -> 1.3133112 | E62: {=IFERROR(INDEX(Starlink!$D:$AC, MATCH("Memo: V3 DTC Blended IRR", Starlink!$A:$A, 0), E$5+1), 0)} -> 1.7738377 | F62: {=IFERROR(INDEX(Starlink!$D:$AC, MATCH("Memo: V3 DTC Blended IRR", Starlink!$A:$A, 0), F$5+1), 0)} -> 2.3146497 | G62: {=IFERROR(INDEX(Starlink!$D:$AC, MATCH("Memo: V3 DTC Blended IRR", Starlink!$A:$A, 0), G$5+1), 0)} -> 2.6775147 | H62: {=IFERROR(INDEX(Starlink!$D:$AC, MATCH("Memo: V3 DTC Blended IRR", Starlink!$A:$A, 0), H$5+1), 0)} -> 3.0909264 | I62: {=IFERROR(INDEX(Starlink!$D:$AC, MATCH("Memo: V3 DTC Blended IRR", Starlink!$A:$A, 0), I$5+1), 0)} -> 3.4450014 | J62: {=IFERROR(INDEX(Starlink!$D:$AC, MATCH("Memo: V3 DTC Blended IRR", Starlink!$A:$A, 0), J$5+1), 0)} -> 3.8387491 | K62: {=IFERROR(INDEX(Starlink!$D:$AC, MATCH("Memo: V3 DTC Blended IRR", Starlink!$A:$A, 0), K$5+1), 0)} -> 4.276672 | ... AC62: {=IFERROR(INDEX(Starlink!$D:$AC, MATCH("Memo: V3 DTC Blended IRR", Starlink!$A:$A, 0), AC$5+1), 0)} -> 2.7390884
A63: Starlink V3 DTC cash demand ($mm) | D63: {=IF(D$4 < INDEX('Launch Capacity'!$D:$AC, MATCH("V3 Starlink launch trigger year", 'Launch Capacity'!$A:$A, 0), 1), 0, IFERROR(INDEX(Starlink!$D:$AC, MATCH("V3 DTC sat CapEx ($mm)", Starlink!$A:$A, 0), D$5+1) + INDEX(Starlink!$D:$AC, MATCH("V3 DTC facility CapEx ($mm)", Starlink!$A:$A, 0), D$5+1), 0))} -> 0 | E63: {=IF(E$4 < INDEX('Launch Capacity'!$D:$AC, MATCH("V3 Starlink launch trigger year", 'Launch Capacity'!$A:$A, 0), 1), 0, IFERROR(INDEX(Starlink!$D:$AC, MATCH("V3 DTC sat CapEx ($mm)", Starlink!$A:$A, 0), E$5+1) + INDEX(Starlink!$D:$AC, MATCH("V3 DTC facility CapEx ($mm)", Starlink!$A:$A, 0), E$5+1), 0))} -> 0 | F63: {=IF(F$4 < INDEX('Launch Capacity'!$D:$AC, MATCH("V3 Starlink launch trigger year", 'Launch Capacity'!$A:$A, 0), 1), 0, IFERROR(INDEX(Starlink!$D:$AC, MATCH("V3 DTC sat CapEx ($mm)", Starlink!$A:$A, 0), F$5+1) + INDEX(Starlink!$D:$AC, MATCH("V3 DTC facility CapEx ($mm)", Starlink!$A:$A, 0), F$5+1), 0))} -> 0 | G63: {=IF(G$4 < INDEX('Launch Capacity'!$D:$AC, MATCH("V3 Starlink launch trigger year", 'Launch Capacity'!$A:$A, 0), 1), 0, IFERROR(INDEX(Starlink!$D:$AC, MATCH("V3 DTC sat CapEx ($mm)", Starlink!$A:$A, 0), G$5+1) + INDEX(Starlink!$D:$AC, MATCH("V3 DTC facility CapEx ($mm)", Starlink!$A:$A, 0), G$5+1), 0))} -> 0 | H63: {=IF(H$4 < INDEX('Launch Capacity'!$D:$AC, MATCH("V3 Starlink launch trigger year", 'Launch Capacity'!$A:$A, 0), 1), 0, IFERROR(INDEX(Starlink!$D:$AC, MATCH("V3 DTC sat CapEx ($mm)", Starlink!$A:$A, 0), H$5+1) + INDEX(Starlink!$D:$AC, MATCH("V3 DTC facility CapEx ($mm)", Starlink!$A:$A, 0), H$5+1), 0))} -> 0 | I63: {=IF(I$4 < INDEX('Launch Capacity'!$D:$AC, MATCH("V3 Starlink launch trigger year", 'Launch Capacity'!$A:$A, 0), 1), 0, IFERROR(INDEX(Starlink!$D:$AC, MATCH("V3 DTC sat CapEx ($mm)", Starlink!$A:$A, 0), I$5+1) + INDEX(Starlink!$D:$AC, MATCH("V3 DTC facility CapEx ($mm)", Starlink!$A:$A, 0), I$5+1), 0))} -> 0 | J63: {=IF(J$4 < INDEX('Launch Capacity'!$D:$AC, MATCH("V3 Starlink launch trigger year", 'Launch Capacity'!$A:$A, 0), 1), 0, IFERROR(INDEX(Starlink!$D:$AC, MATCH("V3 DTC sat CapEx ($mm)", Starlink!$A:$A, 0), J$5+1) + INDEX(Starlink!$D:$AC, MATCH("V3 DTC facility CapEx ($mm)", Starlink!$A:$A, 0), J$5+1), 0))} -> 0 | K63: {=IF(K$4 < INDEX('Launch Capacity'!$D:$AC, MATCH("V3 Starlink launch trigger year", 'Launch Capacity'!$A:$A, 0), 1), 0, IFERROR(INDEX(Starlink!$D:$AC, MATCH("V3 DTC sat CapEx ($mm)", Starlink!$A:$A, 0), K$5+1) + INDEX(Starlink!$D:$AC, MATCH("V3 DTC facility CapEx ($mm)", Starlink!$A:$A, 0), K$5+1), 0))} -> 0 | ... AC63: {=IF(AC$4 < INDEX('Launch Capacity'!$D:$AC, MATCH("V3 Starlink launch trigger year", 'Launch Capacity'!$A:$A, 0), 1), 0, IFERROR(INDEX(Starlink!$D:$AC, MATCH("V3 DTC sat CapEx ($mm)", Starlink!$A:$A, 0), AC$5+1) + INDEX(Starlink!$D:$AC, MATCH("V3 DTC facility CapEx ($mm)", Starlink!$A:$A, 0), AC$5+1), 0))} -> 0
A64: Starlink V3 DTC weight | D64: =MAX(D62, 0)^INDEX(Assumptions!$B:$B, MATCH("Sigmoid IRR-blend exponent k", Assumptions!$A:$A, 0)) * IF(D63 > 0, 1, 0) -> 0 | E64: =MAX(E62, 0)^INDEX(Assumptions!$B:$B, MATCH("Sigmoid IRR-blend exponent k", Assumptions!$A:$A, 0)) * IF(E63 > 0, 1, 0) -> 0 | F64: =MAX(F62, 0)^INDEX(Assumptions!$B:$B, MATCH("Sigmoid IRR-blend exponent k", Assumptions!$A:$A, 0)) * IF(F63 > 0, 1, 0) -> 0 | G64: =MAX(G62, 0)^INDEX(Assumptions!$B:$B, MATCH("Sigmoid IRR-blend exponent k", Assumptions!$A:$A, 0)) * IF(G63 > 0, 1, 0) -> 0 | H64: =MAX(H62, 0)^INDEX(Assumptions!$B:$B, MATCH("Sigmoid IRR-blend exponent k", Assumptions!$A:$A, 0)) * IF(H63 > 0, 1, 0) -> 0 | I64: =MAX(I62, 0)^INDEX(Assumptions!$B:$B, MATCH("Sigmoid IRR-blend exponent k", Assumptions!$A:$A, 0)) * IF(I63 > 0, 1, 0) -> 0 | J64: =MAX(J62, 0)^INDEX(Assumptions!$B:$B, MATCH("Sigmoid IRR-blend exponent k", Assumptions!$A:$A, 0)) * IF(J63 > 0, 1, 0) -> 0 | K64: =MAX(K62, 0)^INDEX(Assumptions!$B:$B, MATCH("Sigmoid IRR-blend exponent k", Assumptions!$A:$A, 0)) * IF(K63 > 0, 1, 0) -> 0 | ... AC64: =MAX(AC62, 0)^INDEX(Assumptions!$B:$B, MATCH("Sigmoid IRR-blend exponent k", Assumptions!$A:$A, 0)) * IF(AC63 > 0, 1, 0) -> 0
A65: Starlink V3 DTC proposed allocation ($mm) | D65: =MIN(IF(D62 > 0, D63, 0), $D$29 * D64 / IF($D$80 > 0, $D$80, 1)) -> 0 | E65: =MIN(IF(E62 > 0, E63, 0), $D$29 * E64 / IF($D$80 > 0, $D$80, 1)) -> 0 | F65: =MIN(IF(F62 > 0, F63, 0), $D$29 * F64 / IF($D$80 > 0, $D$80, 1)) -> 0 | G65: =MIN(IF(G62 > 0, G63, 0), $D$29 * G64 / IF($D$80 > 0, $D$80, 1)) -> 0 | H65: =MIN(IF(H62 > 0, H63, 0), $D$29 * H64 / IF($D$80 > 0, $D$80, 1)) -> 0 | I65: =MIN(IF(I62 > 0, I63, 0), $D$29 * I64 / IF($D$80 > 0, $D$80, 1)) -> 0 | J65: =MIN(IF(J62 > 0, J63, 0), $D$29 * J64 / IF($D$80 > 0, $D$80, 1)) -> 0 | K65: =MIN(IF(K62 > 0, K63, 0), $D$29 * K64 / IF($D$80 > 0, $D$80, 1)) -> 0 | ... AC65: =MIN(IF(AC62 > 0, AC63, 0), $D$29 * AC64 / IF($D$80 > 0, $D$80, 1)) -> 0
A66: ▸ ODC (in-queue module)
A67: ODC Blended IRR | D67: {=IFERROR(INDEX(ODC!$D:$AC, MATCH("Blended IRR", ODC!$A:$A, 0), D$5+1), 0)} -> -0.29679999 | E67: {=IFERROR(INDEX(ODC!$D:$AC, MATCH("Blended IRR", ODC!$A:$A, 0), E$5+1), 0)} -> -0.21105041 | F67: {=IFERROR(INDEX(ODC!$D:$AC, MATCH("Blended IRR", ODC!$A:$A, 0), F$5+1), 0)} -> -0.16557326 | G67: {=IFERROR(INDEX(ODC!$D:$AC, MATCH("Blended IRR", ODC!$A:$A, 0), G$5+1), 0)} -> -0.11544122 | H67: {=IFERROR(INDEX(ODC!$D:$AC, MATCH("Blended IRR", ODC!$A:$A, 0), H$5+1), 0)} -> -0.085999093 | I67: {=IFERROR(INDEX(ODC!$D:$AC, MATCH("Blended IRR", ODC!$A:$A, 0), I$5+1), 0)} -> -0.072553759 | J67: {=IFERROR(INDEX(ODC!$D:$AC, MATCH("Blended IRR", ODC!$A:$A, 0), J$5+1), 0)} -> -0.061917273 | K67: {=IFERROR(INDEX(ODC!$D:$AC, MATCH("Blended IRR", ODC!$A:$A, 0), K$5+1), 0)} -> -0.058045907 | ... AC67: {=IFERROR(INDEX(ODC!$D:$AC, MATCH("Blended IRR", ODC!$A:$A, 0), AC$5+1), 0)} -> -0.14402434
A68: ODC cash demand ($mm) | D68: {=IFERROR(INDEX(ODC!$D:$AC, MATCH("Module CapEx ($mm)", ODC!$A:$A, 0), D$5+1), 0)} -> 0 | E68: {=IFERROR(INDEX(ODC!$D:$AC, MATCH("Module CapEx ($mm)", ODC!$A:$A, 0), E$5+1), 0)} -> 0 | F68: {=IFERROR(INDEX(ODC!$D:$AC, MATCH("Module CapEx ($mm)", ODC!$A:$A, 0), F$5+1), 0)} -> 0 | G68: {=IFERROR(INDEX(ODC!$D:$AC, MATCH("Module CapEx ($mm)", ODC!$A:$A, 0), G$5+1), 0)} -> 0 | H68: {=IFERROR(INDEX(ODC!$D:$AC, MATCH("Module CapEx ($mm)", ODC!$A:$A, 0), H$5+1), 0)} -> 0 | I68: {=IFERROR(INDEX(ODC!$D:$AC, MATCH("Module CapEx ($mm)", ODC!$A:$A, 0), I$5+1), 0)} -> 0 | J68: {=IFERROR(INDEX(ODC!$D:$AC, MATCH("Module CapEx ($mm)", ODC!$A:$A, 0), J$5+1), 0)} -> 0 | K68: {=IFERROR(INDEX(ODC!$D:$AC, MATCH("Module CapEx ($mm)", ODC!$A:$A, 0), K$5+1), 0)} -> 0 | ... AC68: {=IFERROR(INDEX(ODC!$D:$AC, MATCH("Module CapEx ($mm)", ODC!$A:$A, 0), AC$5+1), 0)} -> 0
A69: ODC weight | D69: =MAX(D67, 0)^INDEX(Assumptions!$B:$B, MATCH("Sigmoid IRR-blend exponent k", Assumptions!$A:$A, 0)) * IF(D68 > 0, 1, 0) -> 0 | E69: =MAX(E67, 0)^INDEX(Assumptions!$B:$B, MATCH("Sigmoid IRR-blend exponent k", Assumptions!$A:$A, 0)) * IF(E68 > 0, 1, 0) -> 0 | F69: =MAX(F67, 0)^INDEX(Assumptions!$B:$B, MATCH("Sigmoid IRR-blend exponent k", Assumptions!$A:$A, 0)) * IF(F68 > 0, 1, 0) -> 0 | G69: =MAX(G67, 0)^INDEX(Assumptions!$B:$B, MATCH("Sigmoid IRR-blend exponent k", Assumptions!$A:$A, 0)) * IF(G68 > 0, 1, 0) -> 0 | H69: =MAX(H67, 0)^INDEX(Assumptions!$B:$B, MATCH("Sigmoid IRR-blend exponent k", Assumptions!$A:$A, 0)) * IF(H68 > 0, 1, 0) -> 0 | I69: =MAX(I67, 0)^INDEX(Assumptions!$B:$B, MATCH("Sigmoid IRR-blend exponent k", Assumptions!$A:$A, 0)) * IF(I68 > 0, 1, 0) -> 0 | J69: =MAX(J67, 0)^INDEX(Assumptions!$B:$B, MATCH("Sigmoid IRR-blend exponent k", Assumptions!$A:$A, 0)) * IF(J68 > 0, 1, 0) -> 0 | K69: =MAX(K67, 0)^INDEX(Assumptions!$B:$B, MATCH("Sigmoid IRR-blend exponent k", Assumptions!$A:$A, 0)) * IF(K68 > 0, 1, 0) -> 0 | ... AC69: =MAX(AC67, 0)^INDEX(Assumptions!$B:$B, MATCH("Sigmoid IRR-blend exponent k", Assumptions!$A:$A, 0)) * IF(AC68 > 0, 1, 0) -> 0
A70: ODC proposed allocation ($mm) | D70: =MIN(IF(D67 > 0, D68, 0), $D$29 * D69 / IF($D$80 > 0, $D$80, 1)) -> 0 | E70: =MIN(IF(E67 > 0, E68, 0), $D$29 * E69 / IF($D$80 > 0, $D$80, 1)) -> 0 | F70: =MIN(IF(F67 > 0, F68, 0), $D$29 * F69 / IF($D$80 > 0, $D$80, 1)) -> 0 | G70: =MIN(IF(G67 > 0, G68, 0), $D$29 * G69 / IF($D$80 > 0, $D$80, 1)) -> 0 | H70: =MIN(IF(H67 > 0, H68, 0), $D$29 * H69 / IF($D$80 > 0, $D$80, 1)) -> 0 | I70: =MIN(IF(I67 > 0, I68, 0), $D$29 * I69 / IF($D$80 > 0, $D$80, 1)) -> 0 | J70: =MIN(IF(J67 > 0, J68, 0), $D$29 * J69 / IF($D$80 > 0, $D$80, 1)) -> 0 | K70: =MIN(IF(K67 > 0, K68, 0), $D$29 * K69 / IF($D$80 > 0, $D$80, 1)) -> 0 | ... AC70: =MIN(IF(AC67 > 0, AC68, 0), $D$29 * AC69 / IF($D$80 > 0, $D$80, 1)) -> 0
A71: ▸ AI Stack (in-queue module)
A72: AI Stack Blended IRR | D72: {=IFERROR(INDEX('AI Stack'!$D:$AC, MATCH("Blended IRR", 'AI Stack'!$A:$A, 0), D$5+1), 0)} -> 0 | E72: {=IFERROR(INDEX('AI Stack'!$D:$AC, MATCH("Blended IRR", 'AI Stack'!$A:$A, 0), E$5+1), 0)} -> 0 | F72: {=IFERROR(INDEX('AI Stack'!$D:$AC, MATCH("Blended IRR", 'AI Stack'!$A:$A, 0), F$5+1), 0)} -> 0 | G72: {=IFERROR(INDEX('AI Stack'!$D:$AC, MATCH("Blended IRR", 'AI Stack'!$A:$A, 0), G$5+1), 0)} -> 0 | H72: {=IFERROR(INDEX('AI Stack'!$D:$AC, MATCH("Blended IRR", 'AI Stack'!$A:$A, 0), H$5+1), 0)} -> 0 | I72: {=IFERROR(INDEX('AI Stack'!$D:$AC, MATCH("Blended IRR", 'AI Stack'!$A:$A, 0), I$5+1), 0)} -> 0 | J72: {=IFERROR(INDEX('AI Stack'!$D:$AC, MATCH("Blended IRR", 'AI Stack'!$A:$A, 0), J$5+1), 0)} -> 0 | K72: {=IFERROR(INDEX('AI Stack'!$D:$AC, MATCH("Blended IRR", 'AI Stack'!$A:$A, 0), K$5+1), 0)} -> 0 | ... AC72: {=IFERROR(INDEX('AI Stack'!$D:$AC, MATCH("Blended IRR", 'AI Stack'!$A:$A, 0), AC$5+1), 0)} -> 0
A73: AI Stack cash demand ($mm) | D73: {=IFERROR(INDEX('AI Stack'!$D:$AC, MATCH("Module CapEx ($mm)", 'AI Stack'!$A:$A, 0), D$5+1), 0)} -> 0 | E73: {=IFERROR(INDEX('AI Stack'!$D:$AC, MATCH("Module CapEx ($mm)", 'AI Stack'!$A:$A, 0), E$5+1), 0)} -> 0 | F73: {=IFERROR(INDEX('AI Stack'!$D:$AC, MATCH("Module CapEx ($mm)", 'AI Stack'!$A:$A, 0), F$5+1), 0)} -> 0 | G73: {=IFERROR(INDEX('AI Stack'!$D:$AC, MATCH("Module CapEx ($mm)", 'AI Stack'!$A:$A, 0), G$5+1), 0)} -> 0 | H73: {=IFERROR(INDEX('AI Stack'!$D:$AC, MATCH("Module CapEx ($mm)", 'AI Stack'!$A:$A, 0), H$5+1), 0)} -> 0 | I73: {=IFERROR(INDEX('AI Stack'!$D:$AC, MATCH("Module CapEx ($mm)", 'AI Stack'!$A:$A, 0), I$5+1), 0)} -> 0 | J73: {=IFERROR(INDEX('AI Stack'!$D:$AC, MATCH("Module CapEx ($mm)", 'AI Stack'!$A:$A, 0), J$5+1), 0)} -> 0 | K73: {=IFERROR(INDEX('AI Stack'!$D:$AC, MATCH("Module CapEx ($mm)", 'AI Stack'!$A:$A, 0), K$5+1), 0)} -> 0 | ... AC73: {=IFERROR(INDEX('AI Stack'!$D:$AC, MATCH("Module CapEx ($mm)", 'AI Stack'!$A:$A, 0), AC$5+1), 0)} -> 0
A74: AI Stack weight | D74: =MAX(D72, 0)^INDEX(Assumptions!$B:$B, MATCH("Sigmoid IRR-blend exponent k", Assumptions!$A:$A, 0)) * IF(D73 > 0, 1, 0) -> 0 | E74: =MAX(E72, 0)^INDEX(Assumptions!$B:$B, MATCH("Sigmoid IRR-blend exponent k", Assumptions!$A:$A, 0)) * IF(E73 > 0, 1, 0) -> 0 | F74: =MAX(F72, 0)^INDEX(Assumptions!$B:$B, MATCH("Sigmoid IRR-blend exponent k", Assumptions!$A:$A, 0)) * IF(F73 > 0, 1, 0) -> 0 | G74: =MAX(G72, 0)^INDEX(Assumptions!$B:$B, MATCH("Sigmoid IRR-blend exponent k", Assumptions!$A:$A, 0)) * IF(G73 > 0, 1, 0) -> 0 | H74: =MAX(H72, 0)^INDEX(Assumptions!$B:$B, MATCH("Sigmoid IRR-blend exponent k", Assumptions!$A:$A, 0)) * IF(H73 > 0, 1, 0) -> 0 | I74: =MAX(I72, 0)^INDEX(Assumptions!$B:$B, MATCH("Sigmoid IRR-blend exponent k", Assumptions!$A:$A, 0)) * IF(I73 > 0, 1, 0) -> 0 | J74: =MAX(J72, 0)^INDEX(Assumptions!$B:$B, MATCH("Sigmoid IRR-blend exponent k", Assumptions!$A:$A, 0)) * IF(J73 > 0, 1, 0) -> 0 | K74: =MAX(K72, 0)^INDEX(Assumptions!$B:$B, MATCH("Sigmoid IRR-blend exponent k", Assumptions!$A:$A, 0)) * IF(K73 > 0, 1, 0) -> 0 | ... AC74: =MAX(AC72, 0)^INDEX(Assumptions!$B:$B, MATCH("Sigmoid IRR-blend exponent k", Assumptions!$A:$A, 0)) * IF(AC73 > 0, 1, 0) -> 0
A75: AI Stack proposed allocation ($mm) | D75: =MIN(IF(D72 > 0, D73, 0), $D$29 * D74 / IF($D$80 > 0, $D$80, 1)) -> 0 | E75: =MIN(IF(E72 > 0, E73, 0), $D$29 * E74 / IF($D$80 > 0, $D$80, 1)) -> 0 | F75: =MIN(IF(F72 > 0, F73, 0), $D$29 * F74 / IF($D$80 > 0, $D$80, 1)) -> 0 | G75: =MIN(IF(G72 > 0, G73, 0), $D$29 * G74 / IF($D$80 > 0, $D$80, 1)) -> 0 | H75: =MIN(IF(H72 > 0, H73, 0), $D$29 * H74 / IF($D$80 > 0, $D$80, 1)) -> 0 | I75: =MIN(IF(I72 > 0, I73, 0), $D$29 * I74 / IF($D$80 > 0, $D$80, 1)) -> 0 | J75: =MIN(IF(J72 > 0, J73, 0), $D$29 * J74 / IF($D$80 > 0, $D$80, 1)) -> 0 | K75: =MIN(IF(K72 > 0, K73, 0), $D$29 * K74 / IF($D$80 > 0, $D$80, 1)) -> 0 | ... AC75: =MIN(IF(AC72 > 0, AC73, 0), $D$29 * AC74 / IF($D$80 > 0, $D$80, 1)) -> 0
A80: Σ cash weights (denominator for shares) | D80: =D44+D49+D54+D59+D64+D69+D74 -> 8.1669357 | E80: =E44+E49+E54+E59+E64+E69+E74 -> 6.5184874 | F80: =F44+F49+F54+F59+F64+F69+F74 -> 5.6901826 | G80: =G44+G49+G54+G59+G64+G69+G74 -> 5.0163459 | H80: =H44+H49+H54+H59+H64+H69+H74 -> 4.4709717 | I80: =I44+I49+I54+I59+I64+I69+I74 -> 3.2639266 | J80: =J44+J49+J54+J59+J64+J69+J74 -> 3.6021813 | K80: =K44+K49+K54+K59+K64+K69+K74 -> 1.9792321 | ... AC80: =AC44+AC49+AC54+AC59+AC64+AC69+AC74 -> 0
A82: §5 MODULE CASH ALLOCATIONS (canonical labels — read by module IN blocks)
A83: Customer Launch cash allocation | C83: Sprint 10 populates from sigmoid blend (§4). Sprint 1 = 0 placeholder. | D83: =IFERROR(INDEX('Customer Launch'!$D:$AC, MATCH("Module CapEx ($mm)", 'Customer Launch'!$A:$A, 0), 1), 0) -> 32.86065 | E83: =D46 -> 0 | F83: =E46 -> 0 | G83: =F46 -> 0 | H83: =G46 -> 0 | I83: =H46 -> 0 | J83: =I46 -> 0 | K83: =J46 -> 0 | L83: =K46 -> 0 | ... AC83: =AB46 -> 0
A84: Starlink cash allocation | C84: Sprint 10 populates from sigmoid blend (§4). Sprint 1 = 0 placeholder. | D84: =D88+D89+D90+D91 -> 1184.4138 | E84: =E88+E89+E90+E91 -> 0 | F84: =F88+F89+F90+F91 -> 0 | G84: =G88+G89+G90+G91 -> 0 | H84: =H88+H89+H90+H91 -> 0 | I84: =I88+I89+I90+I91 -> 0 | J84: =J88+J89+J90+J91 -> 0 | K84: =K88+K89+K90+K91 -> 0 | ... AC84: =AC88+AC89+AC90+AC91 -> 0
A85: ODC cash allocation | C85: Sprint 10 populates from sigmoid blend (§4). Sprint 1 = 0 placeholder. | D85: =IFERROR(INDEX(ODC!$D:$AC, MATCH("Module CapEx ($mm)", ODC!$A:$A, 0), 1), 0) -> 0 | E85: =D62 -> 1.3133112 | F85: =E62 -> 1.7738377 | G85: =F62 -> 2.3146497 | H85: =G62 -> 2.6775147 | I85: =H62 -> 3.0909264 | J85: =I62 -> 3.4450014 | K85: =J62 -> 3.8387491 | L85: =K62 -> 4.276672 | ... AC85: =AB62 -> 2.5545626
A86: AI Stack cash allocation | C86: Sprint 10 populates from sigmoid blend (§4). Sprint 1 = 0 placeholder. | D86: =IFERROR(INDEX('AI Stack'!$D:$AC, MATCH("Module CapEx ($mm)", 'AI Stack'!$A:$A, 0), 1), 0) -> 0 | E86: =D70 -> 0 | F86: =E70 -> 0 | G86: =F70 -> 0 | H86: =G70 -> 0 | I86: =H70 -> 0 | J86: =I70 -> 0 | K86: =J70 -> 0 | L86: =K70 -> 0 | ... AC86: =AB70 -> 0
A87: Lunar Mars cash allocation | C87: Sprint 10 populates from sigmoid blend (§4). Sprint 1 = 0 placeholder. | D87: =D35 -> 1000 | E87: =E35 -> 1000 | F87: =F35 -> 1000 | G87: =G35 -> 1000 | H87: =H35 -> 1000 | I87: =I35 -> 1000 | J87: =J35 -> 1000 | K87: =K35 -> 1000 | ... AC87: =AC35 -> 1180.8063
A88: Starlink V2 BB cash allocation | D88: =IFERROR(INDEX(Starlink!$D:$AC, MATCH("V2 BB sat CapEx ($mm)", Starlink!$A:$A, 0), 1) + INDEX(Starlink!$D:$AC, MATCH("V2 BB facility CapEx ($mm)", Starlink!$A:$A, 0), 1), 0) -> 1116.3913 | E88: =D50 -> 0 | F88: =E50 -> 0 | G88: =F50 -> 0 | H88: =G50 -> 0 | I88: =H50 -> 0 | J88: =I50 -> 0 | K88: =J50 -> 0 | L88: =K50 -> 0 | ... AC88: =AB50 -> 0
A89: Starlink V2 DTC cash allocation | D89: =IFERROR(INDEX(Starlink!$D:$AC, MATCH("V2 DTC sat CapEx ($mm)", Starlink!$A:$A, 0), 1) + INDEX(Starlink!$D:$AC, MATCH("V2 DTC facility CapEx ($mm)", Starlink!$A:$A, 0), 1), 0) -> 68.0225 | E89: =D55 -> 0 | F89: =E55 -> 0 | G89: =F55 -> 0 | H89: =G55 -> 0 | I89: =H55 -> 0 | J89: =I55 -> 0 | K89: =J55 -> 0 | L89: =K55 -> 0 | ... AC89: =AB55 -> 0
A90: Starlink V3 BB cash allocation | D90: =IFERROR(INDEX(Starlink!$D:$AC, MATCH("V3 BB facility CapEx ($mm)", Starlink!$A:$A, 0), 1), 0) -> 0 | E90: =D60 -> 0 | F90: =E60 -> 0 | G90: =F60 -> 0 | H90: =G60 -> 0 | I90: =H60 -> 0 | J90: =I60 -> 0 | K90: =J60 -> 0 | L90: =K60 -> 0 | ... AC90: =AB60 -> 0
A91: Starlink V3 DTC cash allocation | D91: =IFERROR(INDEX(Starlink!$D:$AC, MATCH("V3 DTC facility CapEx ($mm)", Starlink!$A:$A, 0), 1), 0) -> 0 | E91: =D65 -> 0 | F91: =E65 -> 0 | G91: =F65 -> 0 | H91: =G65 -> 0 | I91: =H65 -> 0 | J91: =I65 -> 0 | K91: =J65 -> 0 | L91: =K65 -> 0 | ... AC91: =AB65 -> 0
A93: §6 KG IRR-PRIORITY SIGMOID QUEUE
A94: Total Starship capacity (kg-to-LEO) | D94: {=IFERROR(INDEX('Launch Capacity'!$D:$AC, MATCH("Total Annual Capacity (kg-to-LEO)", 'Launch Capacity'!$A:$A, 0), D$5+1), 0)} -> 242.05561 | E94: {=IFERROR(INDEX('Launch Capacity'!$D:$AC, MATCH("Total Annual Capacity (kg-to-LEO)", 'Launch Capacity'!$A:$A, 0), E$5+1), 0)} -> 138407.54 | F94: {=IFERROR(INDEX('Launch Capacity'!$D:$AC, MATCH("Total Annual Capacity (kg-to-LEO)", 'Launch Capacity'!$A:$A, 0), F$5+1), 0)} -> 232172.87 | G94: {=IFERROR(INDEX('Launch Capacity'!$D:$AC, MATCH("Total Annual Capacity (kg-to-LEO)", 'Launch Capacity'!$A:$A, 0), G$5+1), 0)} -> 423134.28 | H94: {=IFERROR(INDEX('Launch Capacity'!$D:$AC, MATCH("Total Annual Capacity (kg-to-LEO)", 'Launch Capacity'!$A:$A, 0), H$5+1), 0)} -> 665049.24 | I94: {=IFERROR(INDEX('Launch Capacity'!$D:$AC, MATCH("Total Annual Capacity (kg-to-LEO)", 'Launch Capacity'!$A:$A, 0), I$5+1), 0)} -> 1155020.2 | J94: {=IFERROR(INDEX('Launch Capacity'!$D:$AC, MATCH("Total Annual Capacity (kg-to-LEO)", 'Launch Capacity'!$A:$A, 0), J$5+1), 0)} -> 1578855.8 | K94: {=IFERROR(INDEX('Launch Capacity'!$D:$AC, MATCH("Total Annual Capacity (kg-to-LEO)", 'Launch Capacity'!$A:$A, 0), K$5+1), 0)} -> 1644199.4 | ... AC94: {=IFERROR(INDEX('Launch Capacity'!$D:$AC, MATCH("Total Annual Capacity (kg-to-LEO)", 'Launch Capacity'!$A:$A, 0), AC$5+1), 0)} -> 5026680.7
A95: Lunar Mars kg reserved (off-the-top) | D95: {=IFERROR(INDEX('Lunar Mars'!$D:$AC, MATCH("Capacity Demand (kg-to-LEO)", 'Lunar Mars'!$A:$A, 0), D$5+1), 0)} -> 0 | E95: {=IFERROR(INDEX('Lunar Mars'!$D:$AC, MATCH("Capacity Demand (kg-to-LEO)", 'Lunar Mars'!$A:$A, 0), E$5+1), 0)} -> 0 | F95: {=IFERROR(INDEX('Lunar Mars'!$D:$AC, MATCH("Capacity Demand (kg-to-LEO)", 'Lunar Mars'!$A:$A, 0), F$5+1), 0)} -> 0 | G95: {=IFERROR(INDEX('Lunar Mars'!$D:$AC, MATCH("Capacity Demand (kg-to-LEO)", 'Lunar Mars'!$A:$A, 0), G$5+1), 0)} -> 3326909.7 | H95: {=IFERROR(INDEX('Lunar Mars'!$D:$AC, MATCH("Capacity Demand (kg-to-LEO)", 'Lunar Mars'!$A:$A, 0), H$5+1), 0)} -> 3404225.1 | I95: {=IFERROR(INDEX('Lunar Mars'!$D:$AC, MATCH("Capacity Demand (kg-to-LEO)", 'Lunar Mars'!$A:$A, 0), I$5+1), 0)} -> 3482414.5 | J95: {=IFERROR(INDEX('Lunar Mars'!$D:$AC, MATCH("Capacity Demand (kg-to-LEO)", 'Lunar Mars'!$A:$A, 0), J$5+1), 0)} -> 3572723 | K95: {=IFERROR(INDEX('Lunar Mars'!$D:$AC, MATCH("Capacity Demand (kg-to-LEO)", 'Lunar Mars'!$A:$A, 0), K$5+1), 0)} -> 3664111.5 | ... AC95: {=IFERROR(INDEX('Lunar Mars'!$D:$AC, MATCH("Capacity Demand (kg-to-LEO)", 'Lunar Mars'!$A:$A, 0), AC$5+1), 0)} -> 4408977
A96: Capacity available for IRR queue (kg-to-LEO) | D96: =MAX(0, D94 - D95) -> 242.05561 | E96: =MAX(0, E94 - E95) -> 138407.54 | F96: =MAX(0, F94 - F95) -> 232172.87 | G96: =MAX(0, G94 - G95) -> 0 | H96: =MAX(0, H94 - H95) -> 0 | I96: =MAX(0, I94 - I95) -> 0 | J96: =MAX(0, J94 - J95) -> 0 | K96: =MAX(0, K94 - K95) -> 0 | ... AC96: =MAX(0, AC94 - AC95) -> 617703.7
A98: ▸ Customer Launch kg sub-block (external Starship demand)
A99: Customer Launch Blended IRR | D99: {=IFERROR(INDEX('Customer Launch'!$D:$AC, MATCH("Blended IRR", 'Customer Launch'!$A:$A, 0), D$5+1), 0)} -> 2.672961 | E99: {=IFERROR(INDEX('Customer Launch'!$D:$AC, MATCH("Blended IRR", 'Customer Launch'!$A:$A, 0), E$5+1), 0)} -> 2.5531329 | F99: {=IFERROR(INDEX('Customer Launch'!$D:$AC, MATCH("Blended IRR", 'Customer Launch'!$A:$A, 0), F$5+1), 0)} -> 2.3854104 | G99: {=IFERROR(INDEX('Customer Launch'!$D:$AC, MATCH("Blended IRR", 'Customer Launch'!$A:$A, 0), G$5+1), 0)} -> 2.2397201 | H99: {=IFERROR(INDEX('Customer Launch'!$D:$AC, MATCH("Blended IRR", 'Customer Launch'!$A:$A, 0), H$5+1), 0)} -> 2.1144672 | I99: {=IFERROR(INDEX('Customer Launch'!$D:$AC, MATCH("Blended IRR", 'Customer Launch'!$A:$A, 0), I$5+1), 0)} -> 1.8066341 | J99: {=IFERROR(INDEX('Customer Launch'!$D:$AC, MATCH("Blended IRR", 'Customer Launch'!$A:$A, 0), J$5+1), 0)} -> 1.8979413 | K99: {=IFERROR(INDEX('Customer Launch'!$D:$AC, MATCH("Blended IRR", 'Customer Launch'!$A:$A, 0), K$5+1), 0)} -> 1.4068518 | ... AC99: {=IFERROR(INDEX('Customer Launch'!$D:$AC, MATCH("Blended IRR", 'Customer Launch'!$A:$A, 0), AC$5+1), 0)} -> -0.0050735922
A100: Customer Launch kg demand (kg-to-LEO) | D100: {=IFERROR(INDEX('Customer Launch'!$D:$AC, MATCH("Capacity Demand (kg-to-LEO)", 'Customer Launch'!$A:$A, 0), D$5+1), 0)} -> 0 | E100: {=IFERROR(INDEX('Customer Launch'!$D:$AC, MATCH("Capacity Demand (kg-to-LEO)", 'Customer Launch'!$A:$A, 0), E$5+1), 0)} -> 0 | F100: {=IFERROR(INDEX('Customer Launch'!$D:$AC, MATCH("Capacity Demand (kg-to-LEO)", 'Customer Launch'!$A:$A, 0), F$5+1), 0)} -> 238331.65 | G100: {=IFERROR(INDEX('Customer Launch'!$D:$AC, MATCH("Capacity Demand (kg-to-LEO)", 'Customer Launch'!$A:$A, 0), G$5+1), 0)} -> 394502.65 | H100: {=IFERROR(INDEX('Customer Launch'!$D:$AC, MATCH("Capacity Demand (kg-to-LEO)", 'Customer Launch'!$A:$A, 0), H$5+1), 0)} -> 736505.22 | I100: {=IFERROR(INDEX('Customer Launch'!$D:$AC, MATCH("Capacity Demand (kg-to-LEO)", 'Customer Launch'!$A:$A, 0), I$5+1), 0)} -> 1101048.1 | J100: {=IFERROR(INDEX('Customer Launch'!$D:$AC, MATCH("Capacity Demand (kg-to-LEO)", 'Customer Launch'!$A:$A, 0), J$5+1), 0)} -> 1327302.2 | K100: {=IFERROR(INDEX('Customer Launch'!$D:$AC, MATCH("Capacity Demand (kg-to-LEO)", 'Customer Launch'!$A:$A, 0), K$5+1), 0)} -> 2661825.2 | ... AC100: {=IFERROR(INDEX('Customer Launch'!$D:$AC, MATCH("Capacity Demand (kg-to-LEO)", 'Customer Launch'!$A:$A, 0), AC$5+1), 0)} -> 13064557
A101: Customer Launch kg weight | D101: =MAX(D99, 0)^INDEX(Assumptions!$B:$B, MATCH("Sigmoid IRR-blend exponent k", Assumptions!$A:$A, 0)) * IF(D100 > 0, 1, 0) -> 0 | E101: =MAX(E99, 0)^INDEX(Assumptions!$B:$B, MATCH("Sigmoid IRR-blend exponent k", Assumptions!$A:$A, 0)) * IF(E100 > 0, 1, 0) -> 0 | F101: =MAX(F99, 0)^INDEX(Assumptions!$B:$B, MATCH("Sigmoid IRR-blend exponent k", Assumptions!$A:$A, 0)) * IF(F100 > 0, 1, 0) -> 5.6901826 | G101: =MAX(G99, 0)^INDEX(Assumptions!$B:$B, MATCH("Sigmoid IRR-blend exponent k", Assumptions!$A:$A, 0)) * IF(G100 > 0, 1, 0) -> 5.0163459 | H101: =MAX(H99, 0)^INDEX(Assumptions!$B:$B, MATCH("Sigmoid IRR-blend exponent k", Assumptions!$A:$A, 0)) * IF(H100 > 0, 1, 0) -> 4.4709717 | I101: =MAX(I99, 0)^INDEX(Assumptions!$B:$B, MATCH("Sigmoid IRR-blend exponent k", Assumptions!$A:$A, 0)) * IF(I100 > 0, 1, 0) -> 3.2639266 | J101: =MAX(J99, 0)^INDEX(Assumptions!$B:$B, MATCH("Sigmoid IRR-blend exponent k", Assumptions!$A:$A, 0)) * IF(J100 > 0, 1, 0) -> 3.6021813 | K101: =MAX(K99, 0)^INDEX(Assumptions!$B:$B, MATCH("Sigmoid IRR-blend exponent k", Assumptions!$A:$A, 0)) * IF(K100 > 0, 1, 0) -> 1.9792321 | ... AC101: =MAX(AC99, 0)^INDEX(Assumptions!$B:$B, MATCH("Sigmoid IRR-blend exponent k", Assumptions!$A:$A, 0)) * IF(AC100 > 0, 1, 0) -> 0
A102: Customer Launch kg proposed allocation | D102: =MIN(IF(D99 > 0, D100, 0), $D$96 * D101 / IF($D$134 > 0, $D$134, 1)) -> 0 | E102: =MIN(IF(E99 > 0, E100, 0), $D$96 * E101 / IF($D$134 > 0, $D$134, 1)) -> 0 | F102: =MIN(IF(F99 > 0, F100, 0), $D$96 * F101 / IF($D$134 > 0, $D$134, 1)) -> 1377.3406 | G102: =MIN(IF(G99 > 0, G100, 0), $D$96 * G101 / IF($D$134 > 0, $D$134, 1)) -> 1214.2347 | H102: =MIN(IF(H99 > 0, H100, 0), $D$96 * H101 / IF($D$134 > 0, $D$134, 1)) -> 1082.2238 | I102: =MIN(IF(I99 > 0, I100, 0), $D$96 * I101 / IF($D$134 > 0, $D$134, 1)) -> 790.05174 | J102: =MIN(IF(J99 > 0, J100, 0), $D$96 * J101 / IF($D$134 > 0, $D$134, 1)) -> 871.92819 | K102: =MIN(IF(K99 > 0, K100, 0), $D$96 * K101 / IF($D$134 > 0, $D$134, 1)) -> 479.08422 | ... AC102: =MIN(IF(AC99 > 0, AC100, 0), $D$96 * AC101 / IF($D$134 > 0, $D$134, 1)) -> 0
A103: ▸ Starlink V3 BB kg sub-block
A104: Starlink V3 BB Blended IRR | D104: {=IFERROR(INDEX(Starlink!$D:$AC, MATCH("Memo: V3 BB Blended IRR", Starlink!$A:$A, 0), D$5+1), 0)} -> 3.5735863 | E104: {=IFERROR(INDEX(Starlink!$D:$AC, MATCH("Memo: V3 BB Blended IRR", Starlink!$A:$A, 0), E$5+1), 0)} -> 4.7830801 | F104: {=IFERROR(INDEX(Starlink!$D:$AC, MATCH("Memo: V3 BB Blended IRR", Starlink!$A:$A, 0), F$5+1), 0)} -> 6.2508513 | G104: {=IFERROR(INDEX(Starlink!$D:$AC, MATCH("Memo: V3 BB Blended IRR", Starlink!$A:$A, 0), G$5+1), 0)} -> 0.96348162 | H104: {=IFERROR(INDEX(Starlink!$D:$AC, MATCH("Memo: V3 BB Blended IRR", Starlink!$A:$A, 0), H$5+1), 0)} -> 1.4370641 | I104: {=IFERROR(INDEX(Starlink!$D:$AC, MATCH("Memo: V3 BB Blended IRR", Starlink!$A:$A, 0), I$5+1), 0)} -> -1 | J104: {=IFERROR(INDEX(Starlink!$D:$AC, MATCH("Memo: V3 BB Blended IRR", Starlink!$A:$A, 0), J$5+1), 0)} -> -1 | K104: {=IFERROR(INDEX(Starlink!$D:$AC, MATCH("Memo: V3 BB Blended IRR", Starlink!$A:$A, 0), K$5+1), 0)} -> -1 | ... AC104: {=IFERROR(INDEX(Starlink!$D:$AC, MATCH("Memo: V3 BB Blended IRR", Starlink!$A:$A, 0), AC$5+1), 0)} -> -1
A105: Starlink V3 BB kg demand (kg-to-LEO) | D105: {=IF(D$4 < INDEX('Launch Capacity'!$D:$AC, MATCH("V3 Starlink launch trigger year", 'Launch Capacity'!$A:$A, 0), 1), 0, IFERROR(INDEX(Starlink!$D:$AC, MATCH("V3 BB Starship kg demand", Starlink!$A:$A, 0), D$5+1), 0))} -> 0 | E105: {=IF(E$4 < INDEX('Launch Capacity'!$D:$AC, MATCH("V3 Starlink launch trigger year", 'Launch Capacity'!$A:$A, 0), 1), 0, IFERROR(INDEX(Starlink!$D:$AC, MATCH("V3 BB Starship kg demand", Starlink!$A:$A, 0), E$5+1), 0))} -> 0 | F105: {=IF(F$4 < INDEX('Launch Capacity'!$D:$AC, MATCH("V3 Starlink launch trigger year", 'Launch Capacity'!$A:$A, 0), 1), 0, IFERROR(INDEX(Starlink!$D:$AC, MATCH("V3 BB Starship kg demand", Starlink!$A:$A, 0), F$5+1), 0))} -> 0 | G105: {=IF(G$4 < INDEX('Launch Capacity'!$D:$AC, MATCH("V3 Starlink launch trigger year", 'Launch Capacity'!$A:$A, 0), 1), 0, IFERROR(INDEX(Starlink!$D:$AC, MATCH("V3 BB Starship kg demand", Starlink!$A:$A, 0), G$5+1), 0))} -> 0 | H105: {=IF(H$4 < INDEX('Launch Capacity'!$D:$AC, MATCH("V3 Starlink launch trigger year", 'Launch Capacity'!$A:$A, 0), 1), 0, IFERROR(INDEX(Starlink!$D:$AC, MATCH("V3 BB Starship kg demand", Starlink!$A:$A, 0), H$5+1), 0))} -> 0 | I105: {=IF(I$4 < INDEX('Launch Capacity'!$D:$AC, MATCH("V3 Starlink launch trigger year", 'Launch Capacity'!$A:$A, 0), 1), 0, IFERROR(INDEX(Starlink!$D:$AC, MATCH("V3 BB Starship kg demand", Starlink!$A:$A, 0), I$5+1), 0))} -> 0 | J105: {=IF(J$4 < INDEX('Launch Capacity'!$D:$AC, MATCH("V3 Starlink launch trigger year", 'Launch Capacity'!$A:$A, 0), 1), 0, IFERROR(INDEX(Starlink!$D:$AC, MATCH("V3 BB Starship kg demand", Starlink!$A:$A, 0), J$5+1), 0))} -> 0 | K105: {=IF(K$4 < INDEX('Launch Capacity'!$D:$AC, MATCH("V3 Starlink launch trigger year", 'Launch Capacity'!$A:$A, 0), 1), 0, IFERROR(INDEX(Starlink!$D:$AC, MATCH("V3 BB Starship kg demand", Starlink!$A:$A, 0), K$5+1), 0))} -> 0 | ... AC105: {=IF(AC$4 < INDEX('Launch Capacity'!$D:$AC, MATCH("V3 Starlink launch trigger year", 'Launch Capacity'!$A:$A, 0), 1), 0, IFERROR(INDEX(Starlink!$D:$AC, MATCH("V3 BB Starship kg demand", Starlink!$A:$A, 0), AC$5+1), 0))} -> 0
A106: Starlink V3 BB kg weight | D106: =MAX(D104, 0)^INDEX(Assumptions!$B:$B, MATCH("Sigmoid IRR-blend exponent k", Assumptions!$A:$A, 0)) * IF(D105 > 0, 1, 0) -> 0 | E106: =MAX(E104, 0)^INDEX(Assumptions!$B:$B, MATCH("Sigmoid IRR-blend exponent k", Assumptions!$A:$A, 0)) * IF(E105 > 0, 1, 0) -> 0 | F106: =MAX(F104, 0)^INDEX(Assumptions!$B:$B, MATCH("Sigmoid IRR-blend exponent k", Assumptions!$A:$A, 0)) * IF(F105 > 0, 1, 0) -> 0 | G106: =MAX(G104, 0)^INDEX(Assumptions!$B:$B, MATCH("Sigmoid IRR-blend exponent k", Assumptions!$A:$A, 0)) * IF(G105 > 0, 1, 0) -> 0 | H106: =MAX(H104, 0)^INDEX(Assumptions!$B:$B, MATCH("Sigmoid IRR-blend exponent k", Assumptions!$A:$A, 0)) * IF(H105 > 0, 1, 0) -> 0 | I106: =MAX(I104, 0)^INDEX(Assumptions!$B:$B, MATCH("Sigmoid IRR-blend exponent k", Assumptions!$A:$A, 0)) * IF(I105 > 0, 1, 0) -> 0 | J106: =MAX(J104, 0)^INDEX(Assumptions!$B:$B, MATCH("Sigmoid IRR-blend exponent k", Assumptions!$A:$A, 0)) * IF(J105 > 0, 1, 0) -> 0 | K106: =MAX(K104, 0)^INDEX(Assumptions!$B:$B, MATCH("Sigmoid IRR-blend exponent k", Assumptions!$A:$A, 0)) * IF(K105 > 0, 1, 0) -> 0 | ... AC106: =MAX(AC104, 0)^INDEX(Assumptions!$B:$B, MATCH("Sigmoid IRR-blend exponent k", Assumptions!$A:$A, 0)) * IF(AC105 > 0, 1, 0) -> 0
A107: Starlink V3 BB kg proposed allocation | D107: =MIN(IF(D104 > 0, D105, 0), $D$96 * D106 / IF($D$134 > 0, $D$134, 1)) -> 0 | E107: =MIN(IF(E104 > 0, E105, 0), $D$96 * E106 / IF($D$134 > 0, $D$134, 1)) -> 0 | F107: =MIN(IF(F104 > 0, F105, 0), $D$96 * F106 / IF($D$134 > 0, $D$134, 1)) -> 0 | G107: =MIN(IF(G104 > 0, G105, 0), $D$96 * G106 / IF($D$134 > 0, $D$134, 1)) -> 0 | H107: =MIN(IF(H104 > 0, H105, 0), $D$96 * H106 / IF($D$134 > 0, $D$134, 1)) -> 0 | I107: =MIN(IF(I104 > 0, I105, 0), $D$96 * I106 / IF($D$134 > 0, $D$134, 1)) -> 0 | J107: =MIN(IF(J104 > 0, J105, 0), $D$96 * J106 / IF($D$134 > 0, $D$134, 1)) -> 0 | K107: =MIN(IF(K104 > 0, K105, 0), $D$96 * K106 / IF($D$134 > 0, $D$134, 1)) -> 0 | ... AC107: =MIN(IF(AC104 > 0, AC105, 0), $D$96 * AC106 / IF($D$134 > 0, $D$134, 1)) -> 0
A108: ▸ Starlink V3 DTC kg sub-block
A109: Starlink V3 DTC Blended IRR | D109: {=IFERROR(INDEX(Starlink!$D:$AC, MATCH("Memo: V3 DTC Blended IRR", Starlink!$A:$A, 0), D$5+1), 0)} -> 1.3133112 | E109: {=IFERROR(INDEX(Starlink!$D:$AC, MATCH("Memo: V3 DTC Blended IRR", Starlink!$A:$A, 0), E$5+1), 0)} -> 1.7738377 | F109: {=IFERROR(INDEX(Starlink!$D:$AC, MATCH("Memo: V3 DTC Blended IRR", Starlink!$A:$A, 0), F$5+1), 0)} -> 2.3146497 | G109: {=IFERROR(INDEX(Starlink!$D:$AC, MATCH("Memo: V3 DTC Blended IRR", Starlink!$A:$A, 0), G$5+1), 0)} -> 2.6775147 | H109: {=IFERROR(INDEX(Starlink!$D:$AC, MATCH("Memo: V3 DTC Blended IRR", Starlink!$A:$A, 0), H$5+1), 0)} -> 3.0909264 | I109: {=IFERROR(INDEX(Starlink!$D:$AC, MATCH("Memo: V3 DTC Blended IRR", Starlink!$A:$A, 0), I$5+1), 0)} -> 3.4450014 | J109: {=IFERROR(INDEX(Starlink!$D:$AC, MATCH("Memo: V3 DTC Blended IRR", Starlink!$A:$A, 0), J$5+1), 0)} -> 3.8387491 | K109: {=IFERROR(INDEX(Starlink!$D:$AC, MATCH("Memo: V3 DTC Blended IRR", Starlink!$A:$A, 0), K$5+1), 0)} -> 4.276672 | ... AC109: {=IFERROR(INDEX(Starlink!$D:$AC, MATCH("Memo: V3 DTC Blended IRR", Starlink!$A:$A, 0), AC$5+1), 0)} -> 2.7390884
A110: Starlink V3 DTC kg demand (kg-to-LEO) | D110: {=IF(D$4 < INDEX('Launch Capacity'!$D:$AC, MATCH("V3 Starlink launch trigger year", 'Launch Capacity'!$A:$A, 0), 1), 0, IFERROR(INDEX(Starlink!$D:$AC, MATCH("V3 DTC Starship kg demand", Starlink!$A:$A, 0), D$5+1), 0))} -> 0 | E110: {=IF(E$4 < INDEX('Launch Capacity'!$D:$AC, MATCH("V3 Starlink launch trigger year", 'Launch Capacity'!$A:$A, 0), 1), 0, IFERROR(INDEX(Starlink!$D:$AC, MATCH("V3 DTC Starship kg demand", Starlink!$A:$A, 0), E$5+1), 0))} -> 0 | F110: {=IF(F$4 < INDEX('Launch Capacity'!$D:$AC, MATCH("V3 Starlink launch trigger year", 'Launch Capacity'!$A:$A, 0), 1), 0, IFERROR(INDEX(Starlink!$D:$AC, MATCH("V3 DTC Starship kg demand", Starlink!$A:$A, 0), F$5+1), 0))} -> 0 | G110: {=IF(G$4 < INDEX('Launch Capacity'!$D:$AC, MATCH("V3 Starlink launch trigger year", 'Launch Capacity'!$A:$A, 0), 1), 0, IFERROR(INDEX(Starlink!$D:$AC, MATCH("V3 DTC Starship kg demand", Starlink!$A:$A, 0), G$5+1), 0))} -> 0 | H110: {=IF(H$4 < INDEX('Launch Capacity'!$D:$AC, MATCH("V3 Starlink launch trigger year", 'Launch Capacity'!$A:$A, 0), 1), 0, IFERROR(INDEX(Starlink!$D:$AC, MATCH("V3 DTC Starship kg demand", Starlink!$A:$A, 0), H$5+1), 0))} -> 0 | I110: {=IF(I$4 < INDEX('Launch Capacity'!$D:$AC, MATCH("V3 Starlink launch trigger year", 'Launch Capacity'!$A:$A, 0), 1), 0, IFERROR(INDEX(Starlink!$D:$AC, MATCH("V3 DTC Starship kg demand", Starlink!$A:$A, 0), I$5+1), 0))} -> 0 | J110: {=IF(J$4 < INDEX('Launch Capacity'!$D:$AC, MATCH("V3 Starlink launch trigger year", 'Launch Capacity'!$A:$A, 0), 1), 0, IFERROR(INDEX(Starlink!$D:$AC, MATCH("V3 DTC Starship kg demand", Starlink!$A:$A, 0), J$5+1), 0))} -> 0 | K110: {=IF(K$4 < INDEX('Launch Capacity'!$D:$AC, MATCH("V3 Starlink launch trigger year", 'Launch Capacity'!$A:$A, 0), 1), 0, IFERROR(INDEX(Starlink!$D:$AC, MATCH("V3 DTC Starship kg demand", Starlink!$A:$A, 0), K$5+1), 0))} -> 0 | ... AC110: {=IF(AC$4 < INDEX('Launch Capacity'!$D:$AC, MATCH("V3 Starlink launch trigger year", 'Launch Capacity'!$A:$A, 0), 1), 0, IFERROR(INDEX(Starlink!$D:$AC, MATCH("V3 DTC Starship kg demand", Starlink!$A:$A, 0), AC$5+1), 0))} -> 0
A111: Starlink V3 DTC kg weight | D111: =MAX(D109, 0)^INDEX(Assumptions!$B:$B, MATCH("Sigmoid IRR-blend exponent k", Assumptions!$A:$A, 0)) * IF(D110 > 0, 1, 0) -> 0 | E111: =MAX(E109, 0)^INDEX(Assumptions!$B:$B, MATCH("Sigmoid IRR-blend exponent k", Assumptions!$A:$A, 0)) * IF(E110 > 0, 1, 0) -> 0 | F111: =MAX(F109, 0)^INDEX(Assumptions!$B:$B, MATCH("Sigmoid IRR-blend exponent k", Assumptions!$A:$A, 0)) * IF(F110 > 0, 1, 0) -> 0 | G111: =MAX(G109, 0)^INDEX(Assumptions!$B:$B, MATCH("Sigmoid IRR-blend exponent k", Assumptions!$A:$A, 0)) * IF(G110 > 0, 1, 0) -> 0 | H111: =MAX(H109, 0)^INDEX(Assumptions!$B:$B, MATCH("Sigmoid IRR-blend exponent k", Assumptions!$A:$A, 0)) * IF(H110 > 0, 1, 0) -> 0 | I111: =MAX(I109, 0)^INDEX(Assumptions!$B:$B, MATCH("Sigmoid IRR-blend exponent k", Assumptions!$A:$A, 0)) * IF(I110 > 0, 1, 0) -> 0 | J111: =MAX(J109, 0)^INDEX(Assumptions!$B:$B, MATCH("Sigmoid IRR-blend exponent k", Assumptions!$A:$A, 0)) * IF(J110 > 0, 1, 0) -> 0 | K111: =MAX(K109, 0)^INDEX(Assumptions!$B:$B, MATCH("Sigmoid IRR-blend exponent k", Assumptions!$A:$A, 0)) * IF(K110 > 0, 1, 0) -> 0 | ... AC111: =MAX(AC109, 0)^INDEX(Assumptions!$B:$B, MATCH("Sigmoid IRR-blend exponent k", Assumptions!$A:$A, 0)) * IF(AC110 > 0, 1, 0) -> 0
A112: Starlink V3 DTC kg proposed allocation | D112: =MIN(IF(D109 > 0, D110, 0), $D$96 * D111 / IF($D$134 > 0, $D$134, 1)) -> 0 | E112: =MIN(IF(E109 > 0, E110, 0), $D$96 * E111 / IF($D$134 > 0, $D$134, 1)) -> 0 | F112: =MIN(IF(F109 > 0, F110, 0), $D$96 * F111 / IF($D$134 > 0, $D$134, 1)) -> 0 | G112: =MIN(IF(G109 > 0, G110, 0), $D$96 * G111 / IF($D$134 > 0, $D$134, 1)) -> 0 | H112: =MIN(IF(H109 > 0, H110, 0), $D$96 * H111 / IF($D$134 > 0, $D$134, 1)) -> 0 | I112: =MIN(IF(I109 > 0, I110, 0), $D$96 * I111 / IF($D$134 > 0, $D$134, 1)) -> 0 | J112: =MIN(IF(J109 > 0, J110, 0), $D$96 * J111 / IF($D$134 > 0, $D$134, 1)) -> 0 | K112: =MIN(IF(K109 > 0, K110, 0), $D$96 * K111 / IF($D$134 > 0, $D$134, 1)) -> 0 | ... AC112: =MIN(IF(AC109 > 0, AC110, 0), $D$96 * AC111 / IF($D$134 > 0, $D$134, 1)) -> 0
A113: ▸ ODC kg sub-block
A114: ODC Blended IRR | D114: {=IFERROR(INDEX(ODC!$D:$AC, MATCH("Blended IRR", ODC!$A:$A, 0), D$5+1), 0)} -> -0.29679999 | E114: {=IFERROR(INDEX(ODC!$D:$AC, MATCH("Blended IRR", ODC!$A:$A, 0), E$5+1), 0)} -> -0.21105041 | F114: {=IFERROR(INDEX(ODC!$D:$AC, MATCH("Blended IRR", ODC!$A:$A, 0), F$5+1), 0)} -> -0.16557326 | G114: {=IFERROR(INDEX(ODC!$D:$AC, MATCH("Blended IRR", ODC!$A:$A, 0), G$5+1), 0)} -> -0.11544122 | H114: {=IFERROR(INDEX(ODC!$D:$AC, MATCH("Blended IRR", ODC!$A:$A, 0), H$5+1), 0)} -> -0.085999093 | I114: {=IFERROR(INDEX(ODC!$D:$AC, MATCH("Blended IRR", ODC!$A:$A, 0), I$5+1), 0)} -> -0.072553759 | J114: {=IFERROR(INDEX(ODC!$D:$AC, MATCH("Blended IRR", ODC!$A:$A, 0), J$5+1), 0)} -> -0.061917273 | K114: {=IFERROR(INDEX(ODC!$D:$AC, MATCH("Blended IRR", ODC!$A:$A, 0), K$5+1), 0)} -> -0.058045907 | ... AC114: {=IFERROR(INDEX(ODC!$D:$AC, MATCH("Blended IRR", ODC!$A:$A, 0), AC$5+1), 0)} -> -0.14402434
A115: ODC kg demand (kg-to-LEO) | D115: {=IFERROR(INDEX(ODC!$D:$AC, MATCH("Capacity Demand (kg-to-LEO)", ODC!$A:$A, 0), D$5+1), 0)} -> 0 | E115: {=IFERROR(INDEX(ODC!$D:$AC, MATCH("Capacity Demand (kg-to-LEO)", ODC!$A:$A, 0), E$5+1), 0)} -> 0 | F115: {=IFERROR(INDEX(ODC!$D:$AC, MATCH("Capacity Demand (kg-to-LEO)", ODC!$A:$A, 0), F$5+1), 0)} -> 0 | G115: {=IFERROR(INDEX(ODC!$D:$AC, MATCH("Capacity Demand (kg-to-LEO)", ODC!$A:$A, 0), G$5+1), 0)} -> 0 | H115: {=IFERROR(INDEX(ODC!$D:$AC, MATCH("Capacity Demand (kg-to-LEO)", ODC!$A:$A, 0), H$5+1), 0)} -> 0 | I115: {=IFERROR(INDEX(ODC!$D:$AC, MATCH("Capacity Demand (kg-to-LEO)", ODC!$A:$A, 0), I$5+1), 0)} -> 0 | J115: {=IFERROR(INDEX(ODC!$D:$AC, MATCH("Capacity Demand (kg-to-LEO)", ODC!$A:$A, 0), J$5+1), 0)} -> 0 | K115: {=IFERROR(INDEX(ODC!$D:$AC, MATCH("Capacity Demand (kg-to-LEO)", ODC!$A:$A, 0), K$5+1), 0)} -> 0 | ... AC115: {=IFERROR(INDEX(ODC!$D:$AC, MATCH("Capacity Demand (kg-to-LEO)", ODC!$A:$A, 0), AC$5+1), 0)} -> 0
A116: ODC kg weight | D116: =MAX(D114, 0)^INDEX(Assumptions!$B:$B, MATCH("Sigmoid IRR-blend exponent k", Assumptions!$A:$A, 0)) * IF(D115 > 0, 1, 0) -> 0 | E116: =MAX(E114, 0)^INDEX(Assumptions!$B:$B, MATCH("Sigmoid IRR-blend exponent k", Assumptions!$A:$A, 0)) * IF(E115 > 0, 1, 0) -> 0 | F116: =MAX(F114, 0)^INDEX(Assumptions!$B:$B, MATCH("Sigmoid IRR-blend exponent k", Assumptions!$A:$A, 0)) * IF(F115 > 0, 1, 0) -> 0 | G116: =MAX(G114, 0)^INDEX(Assumptions!$B:$B, MATCH("Sigmoid IRR-blend exponent k", Assumptions!$A:$A, 0)) * IF(G115 > 0, 1, 0) -> 0 | H116: =MAX(H114, 0)^INDEX(Assumptions!$B:$B, MATCH("Sigmoid IRR-blend exponent k", Assumptions!$A:$A, 0)) * IF(H115 > 0, 1, 0) -> 0 | I116: =MAX(I114, 0)^INDEX(Assumptions!$B:$B, MATCH("Sigmoid IRR-blend exponent k", Assumptions!$A:$A, 0)) * IF(I115 > 0, 1, 0) -> 0 | J116: =MAX(J114, 0)^INDEX(Assumptions!$B:$B, MATCH("Sigmoid IRR-blend exponent k", Assumptions!$A:$A, 0)) * IF(J115 > 0, 1, 0) -> 0 | K116: =MAX(K114, 0)^INDEX(Assumptions!$B:$B, MATCH("Sigmoid IRR-blend exponent k", Assumptions!$A:$A, 0)) * IF(K115 > 0, 1, 0) -> 0 | ... AC116: =MAX(AC114, 0)^INDEX(Assumptions!$B:$B, MATCH("Sigmoid IRR-blend exponent k", Assumptions!$A:$A, 0)) * IF(AC115 > 0, 1, 0) -> 0
A117: ODC kg proposed allocation | D117: =MIN(IF(D114 > 0, D115, 0), $D$96 * D116 / IF($D$134 > 0, $D$134, 1)) -> 0 | E117: =MIN(IF(E114 > 0, E115, 0), $D$96 * E116 / IF($D$134 > 0, $D$134, 1)) -> 0 | F117: =MIN(IF(F114 > 0, F115, 0), $D$96 * F116 / IF($D$134 > 0, $D$134, 1)) -> 0 | G117: =MIN(IF(G114 > 0, G115, 0), $D$96 * G116 / IF($D$134 > 0, $D$134, 1)) -> 0 | H117: =MIN(IF(H114 > 0, H115, 0), $D$96 * H116 / IF($D$134 > 0, $D$134, 1)) -> 0 | I117: =MIN(IF(I114 > 0, I115, 0), $D$96 * I116 / IF($D$134 > 0, $D$134, 1)) -> 0 | J117: =MIN(IF(J114 > 0, J115, 0), $D$96 * J116 / IF($D$134 > 0, $D$134, 1)) -> 0 | K117: =MIN(IF(K114 > 0, K115, 0), $D$96 * K116 / IF($D$134 > 0, $D$134, 1)) -> 0 | ... AC117: =MIN(IF(AC114 > 0, AC115, 0), $D$96 * AC116 / IF($D$134 > 0, $D$134, 1)) -> 0
A118: ▸ AI Stack kg sub-block (terrestrial — kg demand structurally 0)
A119: AI Stack Blended IRR | D119: {=IFERROR(INDEX('AI Stack'!$D:$AC, MATCH("Blended IRR", 'AI Stack'!$A:$A, 0), D$5+1), 0)} -> 0 | E119: {=IFERROR(INDEX('AI Stack'!$D:$AC, MATCH("Blended IRR", 'AI Stack'!$A:$A, 0), E$5+1), 0)} -> 0 | F119: {=IFERROR(INDEX('AI Stack'!$D:$AC, MATCH("Blended IRR", 'AI Stack'!$A:$A, 0), F$5+1), 0)} -> 0 | G119: {=IFERROR(INDEX('AI Stack'!$D:$AC, MATCH("Blended IRR", 'AI Stack'!$A:$A, 0), G$5+1), 0)} -> 0 | H119: {=IFERROR(INDEX('AI Stack'!$D:$AC, MATCH("Blended IRR", 'AI Stack'!$A:$A, 0), H$5+1), 0)} -> 0 | I119: {=IFERROR(INDEX('AI Stack'!$D:$AC, MATCH("Blended IRR", 'AI Stack'!$A:$A, 0), I$5+1), 0)} -> 0 | J119: {=IFERROR(INDEX('AI Stack'!$D:$AC, MATCH("Blended IRR", 'AI Stack'!$A:$A, 0), J$5+1), 0)} -> 0 | K119: {=IFERROR(INDEX('AI Stack'!$D:$AC, MATCH("Blended IRR", 'AI Stack'!$A:$A, 0), K$5+1), 0)} -> 0 | ... AC119: {=IFERROR(INDEX('AI Stack'!$D:$AC, MATCH("Blended IRR", 'AI Stack'!$A:$A, 0), AC$5+1), 0)} -> 0
A120: AI Stack kg demand (kg-to-LEO) | D120: =0 -> 0 | E120: =0 -> 0 | F120: =0 -> 0 | G120: =0 -> 0 | H120: =0 -> 0 | I120: =0 -> 0 | J120: =0 -> 0 | K120: =0 -> 0 | ... AC120: =0 -> 0
A121: AI Stack kg weight | D121: =MAX(D119, 0)^INDEX(Assumptions!$B:$B, MATCH("Sigmoid IRR-blend exponent k", Assumptions!$A:$A, 0)) * IF(D120 > 0, 1, 0) -> 0 | E121: =MAX(E119, 0)^INDEX(Assumptions!$B:$B, MATCH("Sigmoid IRR-blend exponent k", Assumptions!$A:$A, 0)) * IF(E120 > 0, 1, 0) -> 0 | F121: =MAX(F119, 0)^INDEX(Assumptions!$B:$B, MATCH("Sigmoid IRR-blend exponent k", Assumptions!$A:$A, 0)) * IF(F120 > 0, 1, 0) -> 0 | G121: =MAX(G119, 0)^INDEX(Assumptions!$B:$B, MATCH("Sigmoid IRR-blend exponent k", Assumptions!$A:$A, 0)) * IF(G120 > 0, 1, 0) -> 0 | H121: =MAX(H119, 0)^INDEX(Assumptions!$B:$B, MATCH("Sigmoid IRR-blend exponent k", Assumptions!$A:$A, 0)) * IF(H120 > 0, 1, 0) -> 0 | I121: =MAX(I119, 0)^INDEX(Assumptions!$B:$B, MATCH("Sigmoid IRR-blend exponent k", Assumptions!$A:$A, 0)) * IF(I120 > 0, 1, 0) -> 0 | J121: =MAX(J119, 0)^INDEX(Assumptions!$B:$B, MATCH("Sigmoid IRR-blend exponent k", Assumptions!$A:$A, 0)) * IF(J120 > 0, 1, 0) -> 0 | K121: =MAX(K119, 0)^INDEX(Assumptions!$B:$B, MATCH("Sigmoid IRR-blend exponent k", Assumptions!$A:$A, 0)) * IF(K120 > 0, 1, 0) -> 0 | ... AC121: =MAX(AC119, 0)^INDEX(Assumptions!$B:$B, MATCH("Sigmoid IRR-blend exponent k", Assumptions!$A:$A, 0)) * IF(AC120 > 0, 1, 0) -> 0
...

Sheet Launch Capacity
D4: 2025 | E4: 2026 | F4: 2027 | G4: 2028 | H4: 2029 | I4: 2030 | J4: 2031 | K4: 2032 | L4: 2033 | M4: 2034 | N4: 2035 | O4: 2036 | P4: 2037 | Q4: 2038 | R4: 2039 | S4: 2040 | T4: 2041 | U4: 2042 | V4: 2043 | W4: 2044 | X4: 2045 | Y4: 2046 | Z4: 2047 | AA4: 2048 | AB4: 2049 | AC4: 2050
D5: 0 | E5: 1 | F5: 2 | G5: 3 | H5: 4 | I5: 5 | J5: 6 | K5: 7 | L5: 8 | M5: 9 | N5: 10 | O5: 11 | P5: 12 | Q5: 13 | R5: 14 | S5: 15 | T5: 16 | U5: 17 | V5: 18 | W5: 19 | X5: 20 | Y5: 21 | Z5: 22 | AA5: 23 | AB5: 24 | AC5: 25
A6: STARSHIP — VEHICLE SUPPLY
A7: ▸ Physical + cost parameters (from Assumptions §3)
A8: Super Heavy manufacturing cost ($mm/unit) | D8: =INDEX(Assumptions!$B:$B, MATCH("Super Heavy manufacturing cost ($mm/unit, base year)", Assumptions!$A:$A, 0)) -> 54 | E8: =$D$8 -> 54 | F8: =$D$8 -> 54 | G8: =$D$8 -> 54 | H8: =$D$8 -> 54 | I8: =$D$8 -> 54 | J8: =$D$8 -> 54 | K8: =$D$8 -> 54 | L8: =$D$8 -> 54 | ... AC8: =$D$8 -> 54
A9: Starship 2nd-stage manufacturing cost ($mm/unit) | D9: =INDEX(Assumptions!$B:$B, MATCH("Starship 2nd-stage manufacturing cost ($mm/unit, base)", Assumptions!$A:$A, 0)) -> 36 | E9: =$D$9 -> 36 | F9: =$D$9 -> 36 | G9: =$D$9 -> 36 | H9: =$D$9 -> 36 | I9: =$D$9 -> 36 | J9: =$D$9 -> 36 | K9: =$D$9 -> 36 | L9: =$D$9 -> 36 | ... AC9: =$D$9 -> 36
A11: Payload — booster-only mode (kg-to-LEO) | D11: =INDEX(Assumptions!$B:$B, MATCH("Payload — booster-only mode (kg-to-LEO)", Assumptions!$A:$A, 0)) -> 150000
A12: Payload — fully reusable mode (kg-to-LEO) | D12: =INDEX(Assumptions!$B:$B, MATCH("Payload — fully reusable mode (kg-to-LEO)", Assumptions!$A:$A, 0)) -> 100000
A13: Lifetime reuses per ship (cap) | D13: =INDEX(Assumptions!$B:$B, MATCH("Lifetime reuses per ship (cap)", Assumptions!$A:$A, 0)) -> 30
A14: Manufacturing learning rate (per doubling of cum units) | D14: =INDEX(Assumptions!$B:$B, MATCH("Manufacturing learning rate (per doubling of cum units)", Assumptions!$A:$A, 0)) -> 0.1
A15: Cadence ceiling (flights/booster/year) | D15: =INDEX(Assumptions!$B:$B, MATCH("Cadence ceiling (flights/booster/year)", Assumptions!$A:$A, 0)) -> 60
A16: WL learning rate — turnaround vs cum upmass doubling | D16: =INDEX(Assumptions!$B:$B, MATCH("WL learning rate — turnaround vs cum upmass doubling", Assumptions!$A:$A, 0)) -> 0.145
A17: Anchor year for cum-upmass Wright's Law | D17: =INDEX(Assumptions!$B:$B, MATCH("Anchor year for cum-upmass Wright's Law", Assumptions!$A:$A, 0)) -> 2025
A19: ▸ Variant mix + booster lifetime reuses (year-rows from Assumptions §3)
A20: Variant mix (% fully reusable) | D20: {=INDEX(Assumptions!$D:$AC,MATCH("Variant mix (% fully reusable)",Assumptions!$A:$A,0),D$5+1)} -> 0 | E20: {=INDEX(Assumptions!$D:$AC,MATCH("Variant mix (% fully reusable)",Assumptions!$A:$A,0),E$5+1)} -> 0 | F20: {=INDEX(Assumptions!$D:$AC,MATCH("Variant mix (% fully reusable)",Assumptions!$A:$A,0),F$5+1)} -> 1 | G20: {=INDEX(Assumptions!$D:$AC,MATCH("Variant mix (% fully reusable)",Assumptions!$A:$A,0),G$5+1)} -> 1 | H20: {=INDEX(Assumptions!$D:$AC,MATCH("Variant mix (% fully reusable)",Assumptions!$A:$A,0),H$5+1)} -> 1 | I20: {=INDEX(Assumptions!$D:$AC,MATCH("Variant mix (% fully reusable)",Assumptions!$A:$A,0),I$5+1)} -> 1 | J20: {=INDEX(Assumptions!$D:$AC,MATCH("Variant mix (% fully reusable)",Assumptions!$A:$A,0),J$5+1)} -> 1 | K20: {=INDEX(Assumptions!$D:$AC,MATCH("Variant mix (% fully reusable)",Assumptions!$A:$A,0),K$5+1)} -> 1 | ... AC20: {=INDEX(Assumptions!$D:$AC,MATCH("Variant mix (% fully reusable)",Assumptions!$A:$A,0),AC$5+1)} -> 1
A21: Lifetime reuses per booster (year cap) | D21: {=INDEX(Assumptions!$D:$AC,MATCH("Lifetime reuses per booster (year cap)",Assumptions!$A:$A,0),D$5+1)} -> 5 | E21: {=INDEX(Assumptions!$D:$AC,MATCH("Lifetime reuses per booster (year cap)",Assumptions!$A:$A,0),E$5+1)} -> 8 | F21: {=INDEX(Assumptions!$D:$AC,MATCH("Lifetime reuses per booster (year cap)",Assumptions!$A:$A,0),F$5+1)} -> 12 | G21: {=INDEX(Assumptions!$D:$AC,MATCH("Lifetime reuses per booster (year cap)",Assumptions!$A:$A,0),G$5+1)} -> 18 | H21: {=INDEX(Assumptions!$D:$AC,MATCH("Lifetime reuses per booster (year cap)",Assumptions!$A:$A,0),H$5+1)} -> 25 | I21: {=INDEX(Assumptions!$D:$AC,MATCH("Lifetime reuses per booster (year cap)",Assumptions!$A:$A,0),I$5+1)} -> 30 | J21: {=INDEX(Assumptions!$D:$AC,MATCH("Lifetime reuses per booster (year cap)",Assumptions!$A:$A,0),J$5+1)} -> 35 | K21: {=INDEX(Assumptions!$D:$AC,MATCH("Lifetime reuses per booster (year cap)",Assumptions!$A:$A,0),K$5+1)} -> 42 | ... AC21: {=INDEX(Assumptions!$D:$AC,MATCH("Lifetime reuses per booster (year cap)",Assumptions!$A:$A,0),AC$5+1)} -> 100
A23: Launches per Starship vehicle per year (cadence) | D23: 1 | E23: =MAX(1,MIN($D$15,(1/INDEX(Assumptions!$B:$B,MATCH("Base turnaround time per booster (years/flight)",Assumptions!$A:$A,0)))*IFERROR((D28/$D$12)^(-LOG(1-$D$16,2)),1))) -> 1 | F23: =MAX(1,MIN($D$15,(1/INDEX(Assumptions!$B:$B,MATCH("Base turnaround time per booster (years/flight)",Assumptions!$A:$A,0)))*IFERROR((E28/$D$12)^(-LOG(1-$D$16,2)),1))) -> 1 | G23: =MAX(1,MIN($D$15,(1/INDEX(Assumptions!$B:$B,MATCH("Base turnaround time per booster (years/flight)",Assumptions!$A:$A,0)))*IFERROR((F28/$D$12)^(-LOG(1-$D$16,2)),1))) -> 1.0756595 | H23: =MAX(1,MIN($D$15,(1/INDEX(Assumptions!$B:$B,MATCH("Base turnaround time per booster (years/flight)",Assumptions!$A:$A,0)))*IFERROR((G28/$D$12)^(-LOG(1-$D$16,2)),1))) -> 1.349285 | I23: =MAX(1,MIN($D$15,(1/INDEX(Assumptions!$B:$B,MATCH("Base turnaround time per booster (years/flight)",Assumptions!$A:$A,0)))*IFERROR((H28/$D$12)^(-LOG(1-$D$16,2)),1))) -> 1.5866001 | J23: =MAX(1,MIN($D$15,(1/INDEX(Assumptions!$B:$B,MATCH("Base turnaround time per booster (years/flight)",Assumptions!$A:$A,0)))*IFERROR((I28/$D$12)^(-LOG(1-$D$16,2)),1))) -> 1.8462295 | K23: =MAX(1,MIN($D$15,(1/INDEX(Assumptions!$B:$B,MATCH("Base turnaround time per booster (years/flight)",Assumptions!$A:$A,0)))*IFERROR((J28/$D$12)^(-LOG(1-$D$16,2)),1))) -> 2.0898185 | L23: =MAX(1,MIN($D$15,(1/INDEX(Assumptions!$B:$B,MATCH("Base turnaround time per booster (years/flight)",Assumptions!$A:$A,0)))*IFERROR((K28/$D$12)^(-LOG(1-$D$16,2)),1))) -> 2.2934155 | ... AC23: =MAX(1,MIN($D$15,(1/INDEX(Assumptions!$B:$B,MATCH("Base turnaround time per booster (years/flight)",Assumptions!$A:$A,0)))*IFERROR((AB28/$D$12)^(-LOG(1-$D$16,2)),1))) -> 5.3151933
A24: Booster fleet beginning-of-year (units) | D24: 0 | E24: =D27 -> 0.001613704 | F24: =E27 -> 0.92271691 | G24: =F27 -> 2.3217287 | H24: =G27 -> 3.9222857 | I24: =H27 -> 4.9470428 | J24: =I27 -> 7.2472479 | K24: =J27 -> 8.5549546 | L24: =K27 -> 7.9459869 | ... AC24: =AB27 -> 17.73153
A25: Boosters built per year (units) | D25: {=IFERROR(INDEX(Allocator!$D:$AC, MATCH("Vehicle build claim ($mm)", Allocator!$A:$A, 0), D$5+1) / (D8 + D9), 0)} -> 0 | E25: {=IFERROR(INDEX(Allocator!$D:$AC, MATCH("Vehicle build claim ($mm)", Allocator!$A:$A, 0), E$5+1) / (E8 + E9), 0)} -> 0.93012223 | F25: {=IFERROR(INDEX(Allocator!$D:$AC, MATCH("Vehicle build claim ($mm)", Allocator!$A:$A, 0), F$5+1) / (F8 + F9), 0)} -> 1.4109562 | G25: {=IFERROR(INDEX(Allocator!$D:$AC, MATCH("Vehicle build claim ($mm)", Allocator!$A:$A, 0), G$5+1) / (G8 + G9), 0)} -> 1.4054275 | H25: {=IFERROR(INDEX(Allocator!$D:$AC, MATCH("Vehicle build claim ($mm)", Allocator!$A:$A, 0), H$5+1) / (H8 + H9), 0)} -> 1.6963785 | I25: {=IFERROR(INDEX(Allocator!$D:$AC, MATCH("Vehicle build claim ($mm)", Allocator!$A:$A, 0), I$5+1) / (I8 + I9), 0)} -> 1.0878853 | J25: {=IFERROR(INDEX(Allocator!$D:$AC, MATCH("Vehicle build claim ($mm)", Allocator!$A:$A, 0), J$5+1) / (J8 + J9), 0)} -> 2.0557771 | K25: {=IFERROR(INDEX(Allocator!$D:$AC, MATCH("Vehicle build claim ($mm)", Allocator!$A:$A, 0), K$5+1) / (K8 + K9), 0)} -> 1.6914837 | ... AC25: {=IFERROR(INDEX(Allocator!$D:$AC, MATCH("Vehicle build claim ($mm)", Allocator!$A:$A, 0), AC$5+1) / (AC8 + AC9), 0)} -> 0
A26: Boosters retired per year (units) | D26: 0
A27: Booster fleet end-of-year (units) | D27: =D24+D25-D26 -> 0 | E27: =E24+E25-E26 -> 0.93173594 | F27: =F24+F25-F26 -> 2.3336731 | G27: =G24+G25-G26 -> 3.7271562 | H27: =H24+H25-H26 -> 5.6186642 | I27: =I24+I25-I26 -> 6.0349281 | J27: =J24+J25-J26 -> 9.3030251 | K27: =K24+K25-K26 -> 10.246438 | ... AC27: =AC24+AC25-AC26 -> 17.73153
A28: Cum upmass to date (kg) | D28: 0 | E28: =D28+D33*D29 -> 242.05561 | F28: =E28+E33*E29 -> 138649.59 | G28: =F28+F33*F29 -> 370822.46 | H28: =G28+G33*G29 -> 793956.74 | I28: =H28+H33*H29 -> 1459006 | J28: =I28+I33*I29 -> 2614026.1 | K28: =J28+J33*J29 -> 4192881.9 | L28: =K28+K33*K29 -> 5837081.3 | ... AC28: =AB28+AB33*AB29 -> 1.8347635e+08
A29: Per-launch upmass (kg) | D29: =D20*$D$12+(1-D20)*$D$11 -> 150000 | E29: =E20*$D$12+(1-E20)*$D$11 -> 150000 | F29: =F20*$D$12+(1-F20)*$D$11 -> 100000 | G29: =G20*$D$12+(1-G20)*$D$11 -> 100000 | H29: =H20*$D$12+(1-H20)*$D$11 -> 100000 | I29: =I20*$D$12+(1-I20)*$D$11 -> 100000 | J29: =J20*$D$12+(1-J20)*$D$11 -> 100000 | K29: =K20*$D$12+(1-K20)*$D$11 -> 100000 | ... AC29: =AC20*$D$12+(1-AC20)*$D$11 -> 100000
A30: Cum Starship stacks manufactured (end-of-year, units) | D30: =INDEX(Assumptions!$B:$B, MATCH("Starship cost WL anchor cum units (= cum stacks at end-2024 baseline)", Assumptions!$A:$A, 0)) -> 4 | E30: =D30 + D25 -> 4 | F30: =E30 + E25 -> 4.9301222 | G30: =F30 + F25 -> 6.3410784 | H30: =G30 + G25 -> 7.746506 | I30: =H30 + H25 -> 9.4428845 | J30: =I30 + I25 -> 10.53077 | K30: =J30 + J25 -> 12.586547 | L30: =K30 + K25 -> 14.278031 | ... AC30: =AB30 + AB25 -> 41.971234
A31: Booster-only launches per year (count) | D31: =D27*D23*(1-D20) -> 0 | E31: =E27*E23*(1-E20) -> 0.93173594 | F31: =F27*F23*(1-F20) -> 0 | G31: =G27*G23*(1-G20) -> 0 | H31: =H27*H23*(1-H20) -> 0 | I31: =I27*I23*(1-I20) -> 0 | J31: =J27*J23*(1-J20) -> 0 | K31: =K27*K23*(1-K20) -> 0 | ... AC31: =AC27*AC23*(1-AC20) -> 0
A32: Fully-reusable launches per year (count) | D32: =D27*D23*D20 -> 0 | E32: =E27*E23*E20 -> 0 | F32: =F27*F23*F20 -> 2.3336731 | G32: =G27*G23*G20 -> 4.009151 | H32: =H27*H23*H20 -> 7.5811796 | I32: =I27*I23*I20 -> 9.5750178 | J32: =J27*J23*J20 -> 17.175519 | K32: =K27*K23*K20 -> 21.413196 | ... AC32: =AC27*AC23*AC20 -> 94.246512
A33: Total Starship launches per year | D33: =D31+D32 -> 0 | E33: =E31+E32 -> 0.93173594 | F33: =F31+F32 -> 2.3336731 | G33: =G31+G32 -> 4.009151 | H33: =H31+H32 -> 7.5811796 | I33: =I31+I32 -> 9.5750178 | J33: =J31+J32 -> 17.175519 | K33: =K31+K32 -> 21.413196 | ... AC33: =AC31+AC32 -> 94.246512
A34: Total Annual Capacity (kg-to-LEO) | D34: =D33*D29 -> 0 | E34: =E33*E29 -> 139760.39 | F34: =F33*F29 -> 233367.31 | G34: =G33*G29 -> 400915.1 | H34: =H33*H29 -> 758117.96 | I34: =I33*I29 -> 957501.78 | J34: =J33*J29 -> 1717551.9 | K34: =K33*K29 -> 2141319.6 | ... AC34: =AC33*AC29 -> 9424651.2
A36: ▸ Starship at-cost transfer rate (Architecture §7.1)
A37: Starship manufacturing cost ($mm/stack, this year) | D37: =INDEX(Assumptions!$B:$B, MATCH("Starship manufacturing cost anchor ($mm/stack, 2024 baseline)", Assumptions!$A:$A, 0)) * (D30 / INDEX(Assumptions!$B:$B, MATCH("Starship cost WL anchor cum units (= cum stacks at end-2024 baseline)", Assumptions!$A:$A, 0)))^(LOG(1 - INDEX(Assumptions!$B:$B, MATCH("Starship manufacturing WL learning rate (% reduction per doubling cum stacks)", Assumptions!$A:$A, 0)), 2)) -> 90 | E37: =INDEX(Assumptions!$B:$B, MATCH("Starship manufacturing cost anchor ($mm/stack, 2024 baseline)", Assumptions!$A:$A, 0)) * (E30 / INDEX(Assumptions!$B:$B, MATCH("Starship cost WL anchor cum units (= cum stacks at end-2024 baseline)", Assumptions!$A:$A, 0)))^(LOG(1 - INDEX(Assumptions!$B:$B, MATCH("Starship manufacturing WL learning rate (% reduction per doubling cum stacks)", Assumptions!$A:$A, 0)), 2)) -> 90 | F37: =INDEX(Assumptions!$B:$B, MATCH("Starship manufacturing cost anchor ($mm/stack, 2024 baseline)", Assumptions!$A:$A, 0)) * (F30 / INDEX(Assumptions!$B:$B, MATCH("Starship cost WL anchor cum units (= cum stacks at end-2024 baseline)", Assumptions!$A:$A, 0)))^(LOG(1 - INDEX(Assumptions!$B:$B, MATCH("Starship manufacturing WL learning rate (% reduction per doubling cum stacks)", Assumptions!$A:$A, 0)), 2)) -> 85.694629 | G37: =INDEX(Assumptions!$B:$B, MATCH("Starship manufacturing cost anchor ($mm/stack, 2024 baseline)", Assumptions!$A:$A, 0)) * (G30 / INDEX(Assumptions!$B:$B, MATCH("Starship cost WL anchor cum units (= cum stacks at end-2024 baseline)", Assumptions!$A:$A, 0)))^(LOG(1 - INDEX(Assumptions!$B:$B, MATCH("Starship manufacturing WL learning rate (% reduction per doubling cum stacks)", Assumptions!$A:$A, 0)), 2)) -> 80.783986 | H37: =INDEX(Assumptions!$B:$B, MATCH("Starship manufacturing cost anchor ($mm/stack, 2024 baseline)", Assumptions!$A:$A, 0)) * (H30 / INDEX(Assumptions!$B:$B, MATCH("Starship cost WL anchor cum units (= cum stacks at end-2024 baseline)", Assumptions!$A:$A, 0)))^(LOG(1 - INDEX(Assumptions!$B:$B, MATCH("Starship manufacturing WL learning rate (% reduction per doubling cum stacks)", Assumptions!$A:$A, 0)), 2)) -> 77.079738 | I37: =INDEX(Assumptions!$B:$B, MATCH("Starship manufacturing cost anchor ($mm/stack, 2024 baseline)", Assumptions!$A:$A, 0)) * (I30 / INDEX(Assumptions!$B:$B, MATCH("Starship cost WL anchor cum units (= cum stacks at end-2024 baseline)", Assumptions!$A:$A, 0)))^(LOG(1 - INDEX(Assumptions!$B:$B, MATCH("Starship manufacturing WL learning rate (% reduction per doubling cum stacks)", Assumptions!$A:$A, 0)), 2)) -> 73.582831 | J37: =INDEX(Assumptions!$B:$B, MATCH("Starship manufacturing cost anchor ($mm/stack, 2024 baseline)", Assumptions!$A:$A, 0)) * (J30 / INDEX(Assumptions!$B:$B, MATCH("Starship cost WL anchor cum units (= cum stacks at end-2024 baseline)", Assumptions!$A:$A, 0)))^(LOG(1 - INDEX(Assumptions!$B:$B, MATCH("Starship manufacturing WL learning rate (% reduction per doubling cum stacks)", Assumptions!$A:$A, 0)), 2)) -> 71.725451 | K37: =INDEX(Assumptions!$B:$B, MATCH("Starship manufacturing cost anchor ($mm/stack, 2024 baseline)", Assumptions!$A:$A, 0)) * (K30 / INDEX(Assumptions!$B:$B, MATCH("Starship cost WL anchor cum units (= cum stacks at end-2024 baseline)", Assumptions!$A:$A, 0)))^(LOG(1 - INDEX(Assumptions!$B:$B, MATCH("Starship manufacturing WL learning rate (% reduction per doubling cum stacks)", Assumptions!$A:$A, 0)), 2)) -> 68.788332 | ... AC37: =INDEX(Assumptions!$B:$B, MATCH("Starship manufacturing cost anchor ($mm/stack, 2024 baseline)", Assumptions!$A:$A, 0)) * (AC30 / INDEX(Assumptions!$B:$B, MATCH("Starship cost WL anchor cum units (= cum stacks at end-2024 baseline)", Assumptions!$A:$A, 0)))^(LOG(1 - INDEX(Assumptions!$B:$B, MATCH("Starship manufacturing WL learning rate (% reduction per doubling cum stacks)", Assumptions!$A:$A, 0)), 2)) -> 51.865536
A38: Starship ops + fuel + refurb cost per launch ($mm, this year) | D38: =INDEX(Assumptions!$B:$B, MATCH("Starship ops + fuel + refurb cost anchor ($mm/launch, 2024 baseline)", Assumptions!$A:$A, 0)) * (D30 / INDEX(Assumptions!$B:$B, MATCH("Starship cost WL anchor cum units (= cum stacks at end-2024 baseline)", Assumptions!$A:$A, 0)))^(LOG(1 - INDEX(Assumptions!$B:$B, MATCH("Starship ops + fuel + refurb WL learning rate (% reduction per doubling cum stacks)", Assumptions!$A:$A, 0)), 2)) -> 12 | E38: =INDEX(Assumptions!$B:$B, MATCH("Starship ops + fuel + refurb cost anchor ($mm/launch, 2024 baseline)", Assumptions!$A:$A, 0)) * (E30 / INDEX(Assumptions!$B:$B, MATCH("Starship cost WL anchor cum units (= cum stacks at end-2024 baseline)", Assumptions!$A:$A, 0)))^(LOG(1 - INDEX(Assumptions!$B:$B, MATCH("Starship ops + fuel + refurb WL learning rate (% reduction per doubling cum stacks)", Assumptions!$A:$A, 0)), 2)) -> 12 | F38: =INDEX(Assumptions!$B:$B, MATCH("Starship ops + fuel + refurb cost anchor ($mm/launch, 2024 baseline)", Assumptions!$A:$A, 0)) * (F30 / INDEX(Assumptions!$B:$B, MATCH("Starship cost WL anchor cum units (= cum stacks at end-2024 baseline)", Assumptions!$A:$A, 0)))^(LOG(1 - INDEX(Assumptions!$B:$B, MATCH("Starship ops + fuel + refurb WL learning rate (% reduction per doubling cum stacks)", Assumptions!$A:$A, 0)), 2)) -> 11.624645 | G38: =INDEX(Assumptions!$B:$B, MATCH("Starship ops + fuel + refurb cost anchor ($mm/launch, 2024 baseline)", Assumptions!$A:$A, 0)) * (G30 / INDEX(Assumptions!$B:$B, MATCH("Starship cost WL anchor cum units (= cum stacks at end-2024 baseline)", Assumptions!$A:$A, 0)))^(LOG(1 - INDEX(Assumptions!$B:$B, MATCH("Starship ops + fuel + refurb WL learning rate (% reduction per doubling cum stacks)", Assumptions!$A:$A, 0)), 2)) -> 11.188322 | H38: =INDEX(Assumptions!$B:$B, MATCH("Starship ops + fuel + refurb cost anchor ($mm/launch, 2024 baseline)", Assumptions!$A:$A, 0)) * (H30 / INDEX(Assumptions!$B:$B, MATCH("Starship cost WL anchor cum units (= cum stacks at end-2024 baseline)", Assumptions!$A:$A, 0)))^(LOG(1 - INDEX(Assumptions!$B:$B, MATCH("Starship ops + fuel + refurb WL learning rate (% reduction per doubling cum stacks)", Assumptions!$A:$A, 0)), 2)) -> 10.85299 | I38: =INDEX(Assumptions!$B:$B, MATCH("Starship ops + fuel + refurb cost anchor ($mm/launch, 2024 baseline)", Assumptions!$A:$A, 0)) * (I30 / INDEX(Assumptions!$B:$B, MATCH("Starship cost WL anchor cum units (= cum stacks at end-2024 baseline)", Assumptions!$A:$A, 0)))^(LOG(1 - INDEX(Assumptions!$B:$B, MATCH("Starship ops + fuel + refurb WL learning rate (% reduction per doubling cum stacks)", Assumptions!$A:$A, 0)), 2)) -> 10.531186 | J38: =INDEX(Assumptions!$B:$B, MATCH("Starship ops + fuel + refurb cost anchor ($mm/launch, 2024 baseline)", Assumptions!$A:$A, 0)) * (J30 / INDEX(Assumptions!$B:$B, MATCH("Starship cost WL anchor cum units (= cum stacks at end-2024 baseline)", Assumptions!$A:$A, 0)))^(LOG(1 - INDEX(Assumptions!$B:$B, MATCH("Starship ops + fuel + refurb WL learning rate (% reduction per doubling cum stacks)", Assumptions!$A:$A, 0)), 2)) -> 10.358077 | K38: =INDEX(Assumptions!$B:$B, MATCH("Starship ops + fuel + refurb cost anchor ($mm/launch, 2024 baseline)", Assumptions!$A:$A, 0)) * (K30 / INDEX(Assumptions!$B:$B, MATCH("Starship cost WL anchor cum units (= cum stacks at end-2024 baseline)", Assumptions!$A:$A, 0)))^(LOG(1 - INDEX(Assumptions!$B:$B, MATCH("Starship ops + fuel + refurb WL learning rate (% reduction per doubling cum stacks)", Assumptions!$A:$A, 0)), 2)) -> 10.081079 | ... AC38: =INDEX(Assumptions!$B:$B, MATCH("Starship ops + fuel + refurb cost anchor ($mm/launch, 2024 baseline)", Assumptions!$A:$A, 0)) * (AC30 / INDEX(Assumptions!$B:$B, MATCH("Starship cost WL anchor cum units (= cum stacks at end-2024 baseline)", Assumptions!$A:$A, 0)))^(LOG(1 - INDEX(Assumptions!$B:$B, MATCH("Starship ops + fuel + refurb WL learning rate (% reduction per doubling cum stacks)", Assumptions!$A:$A, 0)), 2)) -> 8.394649
A39: Starship D&A share per launch, fully reusable mode ($mm) | D39: =IFERROR(D37 * (INDEX(Assumptions!$B:$B, MATCH("Starship booster share of manufacturing cost (% of stack mfg)", Assumptions!$A:$A, 0)) / D21 + (1 - INDEX(Assumptions!$B:$B, MATCH("Starship booster share of manufacturing cost (% of stack mfg)", Assumptions!$A:$A, 0))) / $D$13), 0) -> 12 | E39: =IFERROR(E37 * (INDEX(Assumptions!$B:$B, MATCH("Starship booster share of manufacturing cost (% of stack mfg)", Assumptions!$A:$A, 0)) / E21 + (1 - INDEX(Assumptions!$B:$B, MATCH("Starship booster share of manufacturing cost (% of stack mfg)", Assumptions!$A:$A, 0))) / $D$13), 0) -> 7.95 | F39: =IFERROR(F37 * (INDEX(Assumptions!$B:$B, MATCH("Starship booster share of manufacturing cost (% of stack mfg)", Assumptions!$A:$A, 0)) / F21 + (1 - INDEX(Assumptions!$B:$B, MATCH("Starship booster share of manufacturing cost (% of stack mfg)", Assumptions!$A:$A, 0))) / $D$13), 0) -> 5.4273265 | G39: =IFERROR(G37 * (INDEX(Assumptions!$B:$B, MATCH("Starship booster share of manufacturing cost (% of stack mfg)", Assumptions!$A:$A, 0)) / G21 + (1 - INDEX(Assumptions!$B:$B, MATCH("Starship booster share of manufacturing cost (% of stack mfg)", Assumptions!$A:$A, 0))) / $D$13), 0) -> 3.7699193 | H39: =IFERROR(H37 * (INDEX(Assumptions!$B:$B, MATCH("Starship booster share of manufacturing cost (% of stack mfg)", Assumptions!$A:$A, 0)) / H21 + (1 - INDEX(Assumptions!$B:$B, MATCH("Starship booster share of manufacturing cost (% of stack mfg)", Assumptions!$A:$A, 0))) / $D$13), 0) -> 2.8776435 | I39: =IFERROR(I37 * (INDEX(Assumptions!$B:$B, MATCH("Starship booster share of manufacturing cost (% of stack mfg)", Assumptions!$A:$A, 0)) / I21 + (1 - INDEX(Assumptions!$B:$B, MATCH("Starship booster share of manufacturing cost (% of stack mfg)", Assumptions!$A:$A, 0))) / $D$13), 0) -> 2.452761 | J39: =IFERROR(J37 * (INDEX(Assumptions!$B:$B, MATCH("Starship booster share of manufacturing cost (% of stack mfg)", Assumptions!$A:$A, 0)) / J21 + (1 - INDEX(Assumptions!$B:$B, MATCH("Starship booster share of manufacturing cost (% of stack mfg)", Assumptions!$A:$A, 0))) / $D$13), 0) -> 2.1859185 | K39: =IFERROR(K37 * (INDEX(Assumptions!$B:$B, MATCH("Starship booster share of manufacturing cost (% of stack mfg)", Assumptions!$A:$A, 0)) / K21 + (1 - INDEX(Assumptions!$B:$B, MATCH("Starship booster share of manufacturing cost (% of stack mfg)", Assumptions!$A:$A, 0))) / $D$13), 0) -> 1.8998682 | ... AC39: =IFERROR(AC37 * (INDEX(Assumptions!$B:$B, MATCH("Starship booster share of manufacturing cost (% of stack mfg)", Assumptions!$A:$A, 0)) / AC21 + (1 - INDEX(Assumptions!$B:$B, MATCH("Starship booster share of manufacturing cost (% of stack mfg)", Assumptions!$A:$A, 0))) / $D$13), 0) -> 1.0027337
A40: Starship at-cost rate ($mm/launch) | D40: =D38+D39 -> 24 | E40: =E38+E39 -> 19.95 | F40: =F38+F39 -> 17.051972 | G40: =G38+G39 -> 14.958241 | H40: =H38+H39 -> 13.730633 | I40: =I38+I39 -> 12.983947 | J40: =J38+J39 -> 12.543995 | K40: =K38+K39 -> 11.980947 | ... AC40: =AC38+AC39 -> 9.3973827
A41: Memo: Starship at-cost rate, ship-expended mode (Moon/Mars, $mm/launch) | D41: =D38 + IFERROR(D37 * INDEX(Assumptions!$B:$B, MATCH("Starship booster share of manufacturing cost (% of stack mfg)", Assumptions!$A:$A, 0)) / D21, 0) + D37 * (1 - INDEX(Assumptions!$B:$B, MATCH("Starship booster share of manufacturing cost (% of stack mfg)", Assumptions!$A:$A, 0))) -> 58.8 | E41: =E38 + IFERROR(E37 * INDEX(Assumptions!$B:$B, MATCH("Starship booster share of manufacturing cost (% of stack mfg)", Assumptions!$A:$A, 0)) / E21, 0) + E37 * (1 - INDEX(Assumptions!$B:$B, MATCH("Starship booster share of manufacturing cost (% of stack mfg)", Assumptions!$A:$A, 0))) -> 54.75 | F41: =F38 + IFERROR(F37 * INDEX(Assumptions!$B:$B, MATCH("Starship booster share of manufacturing cost (% of stack mfg)", Assumptions!$A:$A, 0)) / F21, 0) + F37 * (1 - INDEX(Assumptions!$B:$B, MATCH("Starship booster share of manufacturing cost (% of stack mfg)", Assumptions!$A:$A, 0))) -> 50.187229 | G41: =G38 + IFERROR(G37 * INDEX(Assumptions!$B:$B, MATCH("Starship booster share of manufacturing cost (% of stack mfg)", Assumptions!$A:$A, 0)) / G21, 0) + G37 * (1 - INDEX(Assumptions!$B:$B, MATCH("Starship booster share of manufacturing cost (% of stack mfg)", Assumptions!$A:$A, 0))) -> 46.194716 | H41: =H38 + IFERROR(H37 * INDEX(Assumptions!$B:$B, MATCH("Starship booster share of manufacturing cost (% of stack mfg)", Assumptions!$A:$A, 0)) / H21, 0) + H37 * (1 - INDEX(Assumptions!$B:$B, MATCH("Starship booster share of manufacturing cost (% of stack mfg)", Assumptions!$A:$A, 0))) -> 43.534798 | I41: =I38 + IFERROR(I37 * INDEX(Assumptions!$B:$B, MATCH("Starship booster share of manufacturing cost (% of stack mfg)", Assumptions!$A:$A, 0)) / I21, 0) + I37 * (1 - INDEX(Assumptions!$B:$B, MATCH("Starship booster share of manufacturing cost (% of stack mfg)", Assumptions!$A:$A, 0))) -> 41.435975 | J41: =J38 + IFERROR(J37 * INDEX(Assumptions!$B:$B, MATCH("Starship booster share of manufacturing cost (% of stack mfg)", Assumptions!$A:$A, 0)) / J21, 0) + J37 * (1 - INDEX(Assumptions!$B:$B, MATCH("Starship booster share of manufacturing cost (% of stack mfg)", Assumptions!$A:$A, 0))) -> 40.277836 | K41: =K38 + IFERROR(K37 * INDEX(Assumptions!$B:$B, MATCH("Starship booster share of manufacturing cost (% of stack mfg)", Assumptions!$A:$A, 0)) / K21, 0) + K37 * (1 - INDEX(Assumptions!$B:$B, MATCH("Starship booster share of manufacturing cost (% of stack mfg)", Assumptions!$A:$A, 0))) -> 38.579102 | ... AC41: =AC38 + IFERROR(AC37 * INDEX(Assumptions!$B:$B, MATCH("Starship booster share of manufacturing cost (% of stack mfg)", Assumptions!$A:$A, 0)) / AC21, 0) + AC37 * (1 - INDEX(Assumptions!$B:$B, MATCH("Starship booster share of manufacturing cost (% of stack mfg)", Assumptions!$A:$A, 0))) -> 29.452056
A42: FALCON 9 — VEHICLE SUPPLY
A43: ▸ Physical + cost parameters (from Assumptions §3)
A44: F9 booster (1st stage) mfg cost ($mm/unit) | D44: =INDEX(Assumptions!$B:$B, MATCH("F9 booster (1st stage) mfg cost ($mm/unit)", Assumptions!$A:$A, 0)) -> 30
A45: F9 2nd stage mfg cost ($mm/unit) | D45: =INDEX(Assumptions!$B:$B, MATCH("F9 2nd stage mfg cost ($mm/unit)", Assumptions!$A:$A, 0)) -> 10
A46: F9 fairing cost net of 75% recovery ($mm/flight) | D46: =INDEX(Assumptions!$B:$B, MATCH("F9 fairing cost net of 75% recovery ($mm/flight)", Assumptions!$A:$A, 0)) -> 1.25
A47: F9 per-launch ops cost ($mm) | D47: =INDEX(Assumptions!$B:$B, MATCH("F9 per-launch ops cost ($mm)", Assumptions!$A:$A, 0)) -> 5
A48: F9 booster refurb % of mfg | D48: =INDEX(Assumptions!$B:$B, MATCH("F9 booster refurb % of mfg", Assumptions!$A:$A, 0)) -> 0.03
A49: F9 payload to LEO (kg) | D49: =INDEX(Assumptions!$B:$B, MATCH("F9 payload to LEO (kg)", Assumptions!$A:$A, 0)) -> 22800
A50: F9 lifetime reuses per booster | D50: =INDEX(Assumptions!$B:$B, MATCH("F9 lifetime reuses per booster", Assumptions!$A:$A, 0)) -> 50
A51: F9 cadence per booster (flights/year, flat) | D51: =INDEX(Assumptions!$B:$B, MATCH("F9 cadence per booster (flights/year, flat)", Assumptions!$A:$A, 0)) -> 12
A52: F9 WL learning rate | D52: =INDEX(Assumptions!$B:$B, MATCH("F9 Wright's Law mfg learning rate", Assumptions!$A:$A, 0)) -> 0.02
A54: ▸ F9 supply mechanic (pre-V3-trigger anchors + post-trigger decay)
A55: F9 base booster build rate (boosters/year, pre-V3-trigger) | D55: =INDEX(Assumptions!$B:$B, MATCH("F9 base booster build rate (boosters/year, pre-V3-trigger)", Assumptions!$A:$A, 0)) -> 8
A56: V3 Starlink launch trigger year | D56: =INDEX(Assumptions!$B:$B, MATCH("V3 Starlink launch trigger year", Assumptions!$A:$A, 0)) -> 2027
A57: F9 build-rate decay window (years) | D57: =INDEX(Assumptions!$B:$B, MATCH("F9 build-rate decay window (years)", Assumptions!$A:$A, 0)) -> 8
A58: F9 starting fleet at 2025 SoY (boosters) | D58: =INDEX(Assumptions!$B:$B, MATCH("F9 starting fleet at 2025 SoY (boosters)", Assumptions!$A:$A, 0)) -> 28
A60: F9 fleet beginning-of-year (boosters) | D60: =$D$58 -> 28 | E60: =D63 -> 39 | F60: =E63 -> 54.29 | G60: =F63 -> 61.887703 | H60: =G63 -> 68.483275 | I60: =H63 -> 74.085546 | J60: =I63 -> 78.686542 | K60: =J63 -> 82.384017 | L60: =K63 -> 84.920211 | ... AC60: =AB63 -> 87.634647
A61: F9 manufactured per year (units) — V3-trigger-aware decay note: D61/E61 historical anchors preserved (Sprint 11 Decision A; full IF-bifurcated form deferred to Sprint 12) | D61: 17 | E61: 17 | F61: =MAX(0,$D$55*(1-(F$4-$D$56)/$D$57)) -> 8 | G61: =MAX(0,$D$55*(1-(G$4-$D$56)/$D$57)) -> 7 | H61: =MAX(0,$D$55*(1-(H$4-$D$56)/$D$57)) -> 6 | I61: =MAX(0,$D$55*(1-(I$4-$D$56)/$D$57)) -> 5 | J61: =MAX(0,$D$55*(1-(J$4-$D$56)/$D$57)) -> 4 | K61: =MAX(0,$D$55*(1-(K$4-$D$56)/$D$57)) -> 3 | L61: =MAX(0,$D$55*(1-(L$4-$D$56)/$D$57)) -> 2 | M61: =MAX(0,$D$55*(1-(M$4-$D$56)/$D$57)) -> 1 | ... AC61: =MAX(0,$D$55*(1-(AC$4-$D$56)/$D$57)) -> 0
A62: F9 retired per year (boosters) | D62: 6 | E62: =MIN(E60+E61, E64 * INDEX(Assumptions!$B:$B, MATCH("F9 retirement rate (% of launches/year)", Assumptions!$A:$A, 0))) -> 1.71 | F62: =MIN(F60+F61, F64 * INDEX(Assumptions!$B:$B, MATCH("F9 retirement rate (% of launches/year)", Assumptions!$A:$A, 0))) -> 0.40151133 | G62: =MIN(G60+G61, G64 * INDEX(Assumptions!$B:$B, MATCH("F9 retirement rate (% of launches/year)", Assumptions!$A:$A, 0))) -> 0.40716146 | H62: =MIN(H60+H61, H64 * INDEX(Assumptions!$B:$B, MATCH("F9 retirement rate (% of launches/year)", Assumptions!$A:$A, 0))) -> 0.39529179 | I62: =MIN(I60+I61, I64 * INDEX(Assumptions!$B:$B, MATCH("F9 retirement rate (% of launches/year)", Assumptions!$A:$A, 0))) -> 0.38228462 | J62: =MIN(J60+J61, J64 * INDEX(Assumptions!$B:$B, MATCH("F9 retirement rate (% of launches/year)", Assumptions!$A:$A, 0))) -> 0.38427868 | K62: =MIN(K60+K61, K64 * INDEX(Assumptions!$B:$B, MATCH("F9 retirement rate (% of launches/year)", Assumptions!$A:$A, 0))) -> 0.27667682 | L62: =MIN(L60+L61, L64 * INDEX(Assumptions!$B:$B, MATCH("F9 retirement rate (% of launches/year)", Assumptions!$A:$A, 0))) -> 0.38951147 | ... AC62: =MIN(AC60+AC61, AC64 * INDEX(Assumptions!$B:$B, MATCH("F9 retirement rate (% of launches/year)", Assumptions!$A:$A, 0))) -> 0
A63: F9 fleet end-of-year (boosters) | D63: =MAX(0,D60+D61-D62) -> 39 | E63: =MAX(0,E60+E61-E62) -> 54.29 | F63: =MAX(0,F60+F61-F62) -> 61.888489 | G63: =MAX(0,G60+G61-G62) -> 68.480541 | H63: =MAX(0,H60+H61-H62) -> 74.087983 | I63: =MAX(0,I60+I61-I62) -> 78.703262 | J63: =MAX(0,J60+J61-J62) -> 82.302264 | K63: =MAX(0,K60+K61-K62) -> 85.10734 | ... AC63: =MAX(0,AC60+AC61-AC62) -> 87.634647
A64: F9 launches per year | D64: 171 | E64: 171 | F64: {=MIN(F60*$D$51, IFERROR(INDEX('Customer Launch'!$D:$AC, MATCH("F9 customer launches per year", 'Customer Launch'!$A:$A, 0), F$5+1), 0) + IFERROR(INDEX(Starlink!$D:$AC, MATCH("F9 V2 BB launches (internal)", Starlink!$A:$A, 0), F$5+1), 0) + IFERROR(INDEX(Starlink!$D:$AC, MATCH("F9 V2 DTC launches (internal)", Starlink!$A:$A, 0), F$5+1), 0))} -> 40.212721 | G64: {=MIN(G60*$D$51, IFERROR(INDEX('Customer Launch'!$D:$AC, MATCH("F9 customer launches per year", 'Customer Launch'!$A:$A, 0), G$5+1), 0) + IFERROR(INDEX(Starlink!$D:$AC, MATCH("F9 V2 BB launches (internal)", Starlink!$A:$A, 0), G$5+1), 0) + IFERROR(INDEX(Starlink!$D:$AC, MATCH("F9 V2 DTC launches (internal)", Starlink!$A:$A, 0), G$5+1), 0))} -> 40.42983 | H64: {=MIN(H60*$D$51, IFERROR(INDEX('Customer Launch'!$D:$AC, MATCH("F9 customer launches per year", 'Customer Launch'!$A:$A, 0), H$5+1), 0) + IFERROR(INDEX(Starlink!$D:$AC, MATCH("F9 V2 BB launches (internal)", Starlink!$A:$A, 0), H$5+1), 0) + IFERROR(INDEX(Starlink!$D:$AC, MATCH("F9 V2 DTC launches (internal)", Starlink!$A:$A, 0), H$5+1), 0))} -> 40.243739 | I64: {=MIN(I60*$D$51, IFERROR(INDEX('Customer Launch'!$D:$AC, MATCH("F9 customer launches per year", 'Customer Launch'!$A:$A, 0), I$5+1), 0) + IFERROR(INDEX(Starlink!$D:$AC, MATCH("F9 V2 BB launches (internal)", Starlink!$A:$A, 0), I$5+1), 0) + IFERROR(INDEX(Starlink!$D:$AC, MATCH("F9 V2 DTC launches (internal)", Starlink!$A:$A, 0), I$5+1), 0))} -> 37.688741 | J64: {=MIN(J60*$D$51, IFERROR(INDEX('Customer Launch'!$D:$AC, MATCH("F9 customer launches per year", 'Customer Launch'!$A:$A, 0), J$5+1), 0) + IFERROR(INDEX(Starlink!$D:$AC, MATCH("F9 V2 BB launches (internal)", Starlink!$A:$A, 0), J$5+1), 0) + IFERROR(INDEX(Starlink!$D:$AC, MATCH("F9 V2 DTC launches (internal)", Starlink!$A:$A, 0), J$5+1), 0))} -> 35.912332 | K64: {=MIN(K60*$D$51, IFERROR(INDEX('Customer Launch'!$D:$AC, MATCH("F9 customer launches per year", 'Customer Launch'!$A:$A, 0), K$5+1), 0) + IFERROR(INDEX(Starlink!$D:$AC, MATCH("F9 V2 BB launches (internal)", Starlink!$A:$A, 0), K$5+1), 0) + IFERROR(INDEX(Starlink!$D:$AC, MATCH("F9 V2 DTC launches (internal)", Starlink!$A:$A, 0), K$5+1), 0))} -> 37.84394 | L64: {=MIN(L60*$D$51, IFERROR(INDEX('Customer Launch'!$D:$AC, MATCH("F9 customer launches per year", 'Customer Launch'!$A:$A, 0), L$5+1), 0) + IFERROR(INDEX(Starlink!$D:$AC, MATCH("F9 V2 BB launches (internal)", Starlink!$A:$A, 0), L$5+1), 0) + IFERROR(INDEX(Starlink!$D:$AC, MATCH("F9 V2 DTC launches (internal)", Starlink!$A:$A, 0), L$5+1), 0))} -> 19.39877 | M64: {=MIN(M60*$D$51, IFERROR(INDEX('Customer Launch'!$D:$AC, MATCH("F9 customer launches per year", 'Customer Launch'!$A:$A, 0), M$5+1), 0) + IFERROR(INDEX(Starlink!$D:$AC, MATCH("F9 V2 BB launches (internal)", Starlink!$A:$A, 0), M$5+1), 0) + IFERROR(INDEX(Starlink!$D:$AC, MATCH("F9 V2 DTC launches (internal)", Starlink!$A:$A, 0), M$5+1), 0))} -> 40.10592 | ... AC64: {=MIN(AC60*$D$51, IFERROR(INDEX('Customer Launch'!$D:$AC, MATCH("F9 customer launches per year", 'Customer Launch'!$A:$A, 0), AC$5+1), 0) + IFERROR(INDEX(Starlink!$D:$AC, MATCH("F9 V2 BB launches (internal)", Starlink!$A:$A, 0), AC$5+1), 0) + IFERROR(INDEX(Starlink!$D:$AC, MATCH("F9 V2 DTC launches (internal)", Starlink!$A:$A, 0), AC$5+1), 0))} -> 80.378766
A65: F9 cadence-utilization per booster (memo, derived) | D65: =IFERROR(D64/D60,0) -> 6.1071429 | E65: =IFERROR(E64/E60,0) -> 4.3846154 | F65: =IFERROR(F64/F60,0) -> 0.74070218 | G65: =IFERROR(G64/G60,0) -> 0.65327727 | H65: =IFERROR(H64/H60,0) -> 0.58764331 | I65: =IFERROR(I64/I60,0) -> 0.50871922 | J65: =IFERROR(J64/J60,0) -> 0.45639738 | K65: =IFERROR(K64/K60,0) -> 0.45936022 | ... AC65: =IFERROR(AC64/AC60,0) -> 0.91720306
A67: ▸ F9 capacity + at-cost transfer rate
A68: F9 Annual Capacity (kg-to-LEO) | D68: =D60*$D$51*$D$49 -> 7660800 | E68: =E60*$D$51*$D$49 -> 10670400 | F68: =F60*$D$51*$D$49 -> 14853744 | G68: =G60*$D$51*$D$49 -> 16932475 | H68: =H60*$D$51*$D$49 -> 18737024 | I68: =I60*$D$51*$D$49 -> 20269805 | J68: =J60*$D$51*$D$49 -> 21528638 | K68: =K60*$D$51*$D$49 -> 22540267 | ... AC68: =AC60*$D$51*$D$49 -> 23976839
A69: F9 variable cost per launch ($mm) | D69: =$D$45+$D$46+$D$47+$D$48*$D$44 -> 17.15 | E69: =$D$45+$D$46+$D$47+$D$48*$D$44 -> 17.15 | F69: =$D$45+$D$46+$D$47+$D$48*$D$44 -> 17.15 | G69: =$D$45+$D$46+$D$47+$D$48*$D$44 -> 17.15 | H69: =$D$45+$D$46+$D$47+$D$48*$D$44 -> 17.15 | I69: =$D$45+$D$46+$D$47+$D$48*$D$44 -> 17.15 | J69: =$D$45+$D$46+$D$47+$D$48*$D$44 -> 17.15 | K69: =$D$45+$D$46+$D$47+$D$48*$D$44 -> 17.15 | ... AC69: =$D$45+$D$46+$D$47+$D$48*$D$44 -> 17.15
A70: F9 booster D&A share per launch ($mm) | D70: =$D$44/$D$50 -> 0.6 | E70: =$D$44/$D$50 -> 0.6 | F70: =$D$44/$D$50 -> 0.6 | G70: =$D$44/$D$50 -> 0.6 | H70: =$D$44/$D$50 -> 0.6 | I70: =$D$44/$D$50 -> 0.6 | J70: =$D$44/$D$50 -> 0.6 | K70: =$D$44/$D$50 -> 0.6 | ... AC70: =$D$44/$D$50 -> 0.6
A71: F9 at-cost rate ($mm/launch) | D71: =$D$69+$D$70 -> 17.75 | E71: =$D$69+$D$70 -> 17.75 | F71: =$D$69+$D$70 -> 17.75 | G71: =$D$69+$D$70 -> 17.75 | H71: =$D$69+$D$70 -> 17.75 | I71: =$D$69+$D$70 -> 17.75 | J71: =$D$69+$D$70 -> 17.75 | K71: =$D$69+$D$70 -> 17.75 | ... AC71: =$D$69+$D$70 -> 17.75
A73: BLENDED COST STACK + CALIBRATION
A74: Total launches per year (all vehicles) | D74: =D64+D33 -> 171 | E74: =E64+E33 -> 171.93174 | F74: =F64+F33 -> 42.546394 | G74: =G64+G33 -> 44.438981 | H74: =H64+H33 -> 47.824918 | I74: =I64+I33 -> 47.263759 | J74: =J64+J33 -> 53.087851 | K74: =K64+K33 -> 59.257136 | ... AC74: =AC64+AC33 -> 174.62528
A75: Total upmass per year (kg) | D75: =D64*$D$49+D34 -> 3898800 | E75: =E64*$D$49+E34 -> 4038560.4 | F75: =F64*$D$49+F34 -> 1150217.4 | G75: =G64*$D$49+G34 -> 1322715.2 | H75: =H64*$D$49+H34 -> 1675675.2 | I75: =I64*$D$49+I34 -> 1816805.1 | J75: =J64*$D$49+J34 -> 2536353.1 | K75: =K64*$D$49+K34 -> 3004161.4 | ... AC75: =AC64*$D$49+AC34 -> 11257287
A76: Total launch CapEx per year ($mm) — variable + amortized D&A | D76: =D64*D71+D33*D40 -> 3035.25 | E76: =E64*E71+E33*E40 -> 3053.8381 | F76: =F64*F71+F33*F40 -> 753.56953 | G76: =G64*G71+G33*G40 -> 777.59932 | H76: =H64*H71+H33*H40 -> 818.42076 | I76: =I64*I71+I33*I40 -> 793.29668 | J76: =J64*J71+J33*J40 -> 852.89352 | K76: =K64*K71+K33*K40 -> 928.28031 | ... AC76: =AC64*AC71+AC33*AC40 -> 2312.3936
A77: Blended $/kg | D77: =IFERROR(D76*1000000/D75,0) -> 778.50877 | E77: =IFERROR(E76*1000000/E75,0) -> 756.16998 | F77: =IFERROR(F76*1000000/F75,0) -> 655.15403 | G77: =IFERROR(G76*1000000/G75,0) -> 587.88114 | H77: =IFERROR(H76*1000000/H75,0) -> 488.41253 | I77: =IFERROR(I76*1000000/I75,0) -> 436.64381 | J77: =IFERROR(J76*1000000/J75,0) -> 336.26766 | K77: =IFERROR(K76*1000000/K75,0) -> 308.99814 | ... AC77: =IFERROR(AC76*1000000/AC75,0) -> 205.41305
A79: Memo: 2025 calibration anchors (read-only diagnostics)
A80: Memo: 2025 calibration status | D80: =IF(AND(ABS(D64-171)<=5,ABS(D63-39)<=5,ABS(D61-17)<=2,D33=0,D77>=400,D77<=800),"PASS","CHECK") -> PASS

Sheet Customer Launch
D4: 2025 | E4: 2026 | F4: 2027 | G4: 2028 | H4: 2029 | I4: 2030 | J4: 2031 | K4: 2032 | L4: 2033 | M4: 2034 | N4: 2035 | O4: 2036 | P4: 2037 | Q4: 2038 | R4: 2039 | S4: 2040 | T4: 2041 | U4: 2042 | V4: 2043 | W4: 2044 | X4: 2045 | Y4: 2046 | Z4: 2047 | AA4: 2048 | AB4: 2049 | AC4: 2050
D5: 0 | E5: 1 | F5: 2 | G5: 3 | H5: 4 | I5: 5 | J5: 6 | K5: 7 | L5: 8 | M5: 9 | N5: 10 | O5: 11 | P5: 12 | Q5: 13 | R5: 14 | S5: 15 | T5: 16 | U5: 17 | V5: 18 | W5: 19 | X5: 20 | Y5: 21 | Z5: 22 | AA5: 23 | AB5: 24 | AC5: 25
A7: INPUTS FROM CENTRAL ALLOCATOR
A8: Capital Allocation ($mm) | C8: Reads Allocator section 5 by label. Sprint 1 returns 0 (placeholder upstream). | D8: =INDEX(Allocator!D:D, MATCH("Customer Launch cash allocation", Allocator!$A:$A, 0)) -> 32.86065 | E8: =INDEX(Allocator!E:E, MATCH("Customer Launch cash allocation", Allocator!$A:$A, 0)) -> 0 | F8: =INDEX(Allocator!F:F, MATCH("Customer Launch cash allocation", Allocator!$A:$A, 0)) -> 0 | G8: =INDEX(Allocator!G:G, MATCH("Customer Launch cash allocation", Allocator!$A:$A, 0)) -> 0 | H8: =INDEX(Allocator!H:H, MATCH("Customer Launch cash allocation", Allocator!$A:$A, 0)) -> 0 | I8: =INDEX(Allocator!I:I, MATCH("Customer Launch cash allocation", Allocator!$A:$A, 0)) -> 0 | J8: =INDEX(Allocator!J:J, MATCH("Customer Launch cash allocation", Allocator!$A:$A, 0)) -> 0 | K8: =INDEX(Allocator!K:K, MATCH("Customer Launch cash allocation", Allocator!$A:$A, 0)) -> 0 | L8: =INDEX(Allocator!L:L, MATCH("Customer Launch cash allocation", Allocator!$A:$A, 0)) -> 0 | M8: =INDEX(Allocator!M:M, MATCH("Customer Launch cash allocation", Allocator!$A:$A, 0)) -> 0 | N8: =INDEX(Allocator!N:N, MATCH("Customer Launch cash allocation", Allocator!$A:$A, 0)) -> 0 | O8: =INDEX(Allocator!O:O, MATCH("Customer Launch cash allocation", Allocator!$A:$A, 0)) -> 0 | P8: =INDEX(Allocator!P:P, MATCH("Customer Launch cash allocation", Allocator!$A:$A, 0)) -> 0 | Q8: =INDEX(Allocator!Q:Q, MATCH("Customer Launch cash allocation", Allocator!$A:$A, 0)) -> 0 | R8: =INDEX(Allocator!R:R, MATCH("Customer Launch cash allocation", Allocator!$A:$A, 0)) -> 0 | S8: =INDEX(Allocator!S:S, MATCH("Customer Launch cash allocation", Allocator!$A:$A, 0)) -> 0 | T8: =INDEX(Allocator!T:T, MATCH("Customer Launch cash allocation", Allocator!$A:$A, 0)) -> 0 | U8: =INDEX(Allocator!U:U, MATCH("Customer Launch cash allocation", Allocator!$A:$A, 0)) -> 0 | V8: =INDEX(Allocator!V:V, MATCH("Customer Launch cash allocation", Allocator!$A:$A, 0)) -> 0 | W8: =INDEX(Allocator!W:W, MATCH("Customer Launch cash allocation", Allocator!$A:$A, 0)) -> 0 | X8: =INDEX(Allocator!X:X, MATCH("Customer Launch cash allocation", Allocator!$A:$A, 0)) -> 0 | Y8: =INDEX(Allocator!Y:Y, MATCH("Customer Launch cash allocation", Allocator!$A:$A, 0)) -> 0 | Z8: =INDEX(Allocator!Z:Z, MATCH("Customer Launch cash allocation", Allocator!$A:$A, 0)) -> 0 | AA8: =INDEX(Allocator!AA:AA, MATCH("Customer Launch cash allocation", Allocator!$A:$A, 0)) -> 0 | AB8: =INDEX(Allocator!AB:AB, MATCH("Customer Launch cash allocation", Allocator!$A:$A, 0)) -> 0 | AC8: =INDEX(Allocator!AC:AC, MATCH("Customer Launch cash allocation", Allocator!$A:$A, 0)) -> 0
A9: Starship Capacity Allocation (kg-to-LEO) | C9: Reads Allocator section 7 by label. Sprint 1 returns 0 (placeholder upstream). | D9: =INDEX(Allocator!D:D, MATCH("Customer Launch kg allocation", Allocator!$A:$A, 0)) -> 0 | E9: =INDEX(Allocator!E:E, MATCH("Customer Launch kg allocation", Allocator!$A:$A, 0)) -> 0 | F9: =INDEX(Allocator!F:F, MATCH("Customer Launch kg allocation", Allocator!$A:$A, 0)) -> 1377.3406 | G9: =INDEX(Allocator!G:G, MATCH("Customer Launch kg allocation", Allocator!$A:$A, 0)) -> 1214.2347 | H9: =INDEX(Allocator!H:H, MATCH("Customer Launch kg allocation", Allocator!$A:$A, 0)) -> 1082.2238 | I9: =INDEX(Allocator!I:I, MATCH("Customer Launch kg allocation", Allocator!$A:$A, 0)) -> 790.05174 | J9: =INDEX(Allocator!J:J, MATCH("Customer Launch kg allocation", Allocator!$A:$A, 0)) -> 871.92819 | K9: =INDEX(Allocator!K:K, MATCH("Customer Launch kg allocation", Allocator!$A:$A, 0)) -> 479.08422 | L9: =INDEX(Allocator!L:L, MATCH("Customer Launch kg allocation", Allocator!$A:$A, 0)) -> 345.28718 | M9: =INDEX(Allocator!M:M, MATCH("Customer Launch kg allocation", Allocator!$A:$A, 0)) -> 563.44485 | N9: =INDEX(Allocator!N:N, MATCH("Customer Launch kg allocation", Allocator!$A:$A, 0)) -> 47.111905 | O9: =INDEX(Allocator!O:O, MATCH("Customer Launch kg allocation", Allocator!$A:$A, 0)) -> 536.07254 | P9: =INDEX(Allocator!P:P, MATCH("Customer Launch kg allocation", Allocator!$A:$A, 0)) -> 13.484802 | Q9: =INDEX(Allocator!Q:Q, MATCH("Customer Launch kg allocation", Allocator!$A:$A, 0)) -> 73.771546 | R9: =INDEX(Allocator!R:R, MATCH("Customer Launch kg allocation", Allocator!$A:$A, 0)) -> 241.49678 | S9: =INDEX(Allocator!S:S, MATCH("Customer Launch kg allocation", Allocator!$A:$A, 0)) -> 5.3430257 | T9: =INDEX(Allocator!T:T, MATCH("Customer Launch kg allocation", Allocator!$A:$A, 0)) -> 310.62054 | U9: =INDEX(Allocator!U:U, MATCH("Customer Launch kg allocation", Allocator!$A:$A, 0)) -> 115.44913 | V9: =INDEX(Allocator!V:V, MATCH("Customer Launch kg allocation", Allocator!$A:$A, 0)) -> 33.236374 | W9: =INDEX(Allocator!W:W, MATCH("Customer Launch kg allocation", Allocator!$A:$A, 0)) -> 255.34294 | X9: =INDEX(Allocator!X:X, MATCH("Customer Launch kg allocation", Allocator!$A:$A, 0)) -> 0.68396606 | Y9: =INDEX(Allocator!Y:Y, MATCH("Customer Launch kg allocation", Allocator!$A:$A, 0)) -> 140.27907 | Z9: =INDEX(Allocator!Z:Z, MATCH("Customer Launch kg allocation", Allocator!$A:$A, 0)) -> 104.56247 | AA9: =INDEX(Allocator!AA:AA, MATCH("Customer Launch kg allocation", Allocator!$A:$A, 0)) -> 7.5750177 | AB9: =INDEX(Allocator!AB:AB, MATCH("Customer Launch kg allocation", Allocator!$A:$A, 0)) -> 18.477118 | AC9: =INDEX(Allocator!AC:AC, MATCH("Customer Launch kg allocation", Allocator!$A:$A, 0)) -> 0
A10: Total Capital Available ($mm) | C10: = Capital Allocation (no separate Cash Sweep row — Layer 3 retired). | D10: =D8 -> 32.86065 | E10: =E8 -> 0 | F10: =F8 -> 0 | G10: =G8 -> 0 | H10: =H8 -> 0 | I10: =I8 -> 0 | J10: =J8 -> 0 | K10: =K8 -> 0 | ... AC10: =AC8 -> 0
A12: CUSTOMER LAUNCH — MODULE BODY
A14: ▸ Demand mechanic (total market + F9 vs Starship split via IRR + capacity)
A15: Total customer launch market (launches/yr) | D15: =INDEX(Assumptions!$B:$B, MATCH("Total customer launch market (launches/yr) — 2025 anchor", Assumptions!$A:$A, 0)) -> 38.58 | E15: =$D$15 * (1 + INDEX(Assumptions!$B:$B, MATCH("Total customer launch market CAGR (% growth/yr)", Assumptions!$A:$A, 0)))^E$5 -> 40.509 | F15: =$D$15 * (1 + INDEX(Assumptions!$B:$B, MATCH("Total customer launch market CAGR (% growth/yr)", Assumptions!$A:$A, 0)))^F$5 -> 42.53445 | G15: =$D$15 * (1 + INDEX(Assumptions!$B:$B, MATCH("Total customer launch market CAGR (% growth/yr)", Assumptions!$A:$A, 0)))^G$5 -> 44.661173 | H15: =$D$15 * (1 + INDEX(Assumptions!$B:$B, MATCH("Total customer launch market CAGR (% growth/yr)", Assumptions!$A:$A, 0)))^H$5 -> 46.894231 | I15: =$D$15 * (1 + INDEX(Assumptions!$B:$B, MATCH("Total customer launch market CAGR (% growth/yr)", Assumptions!$A:$A, 0)))^I$5 -> 49.238943 | J15: =$D$15 * (1 + INDEX(Assumptions!$B:$B, MATCH("Total customer launch market CAGR (% growth/yr)", Assumptions!$A:$A, 0)))^J$5 -> 51.70089 | K15: =$D$15 * (1 + INDEX(Assumptions!$B:$B, MATCH("Total customer launch market CAGR (% growth/yr)", Assumptions!$A:$A, 0)))^K$5 -> 54.285934 | L15: =$D$15 * (1 + INDEX(Assumptions!$B:$B, MATCH("Total customer launch market CAGR (% growth/yr)", Assumptions!$A:$A, 0)))^L$5 -> 57.000231 | ... AC15: =$D$15 * (1 + INDEX(Assumptions!$B:$B, MATCH("Total customer launch market CAGR (% growth/yr)", Assumptions!$A:$A, 0)))^AC$5 -> 130.64557
A16: Starship customer launch margin multiplier (year-row) | D16: 0 | E16: 0 | F16: =INDEX(Assumptions!$B:$B, MATCH("Starship customer launch margin — 2027 anchor (multiplier on at-cost rate)", Assumptions!$A:$A, 0)) -> 4 | G16: =MAX(INDEX(Assumptions!$B:$B, MATCH("Starship customer launch margin — 2050 terminal (multiplier on at-cost rate, floor)", Assumptions!$A:$A, 0)), $F$16 * (1 + INDEX(Assumptions!$B:$B, MATCH("Starship customer launch margin — CAGR (% change/yr from 2027 anchor)", Assumptions!$A:$A, 0)))^(G$5 - 2)) -> 3.833007 | H16: =MAX(INDEX(Assumptions!$B:$B, MATCH("Starship customer launch margin — 2050 terminal (multiplier on at-cost rate, floor)", Assumptions!$A:$A, 0)), $F$16 * (1 + INDEX(Assumptions!$B:$B, MATCH("Starship customer launch margin — CAGR (% change/yr from 2027 anchor)", Assumptions!$A:$A, 0)))^(H$5 - 2)) -> 3.6729857 | I16: =MAX(INDEX(Assumptions!$B:$B, MATCH("Starship customer launch margin — 2050 terminal (multiplier on at-cost rate, floor)", Assumptions!$A:$A, 0)), $F$16 * (1 + INDEX(Assumptions!$B:$B, MATCH("Starship customer launch margin — CAGR (% change/yr from 2027 anchor)", Assumptions!$A:$A, 0)))^(I$5 - 2)) -> 3.5196449 | J16: =MAX(INDEX(Assumptions!$B:$B, MATCH("Starship customer launch margin — 2050 terminal (multiplier on at-cost rate, floor)", Assumptions!$A:$A, 0)), $F$16 * (1 + INDEX(Assumptions!$B:$B, MATCH("Starship customer launch margin — CAGR (% change/yr from 2027 anchor)", Assumptions!$A:$A, 0)))^(J$5 - 2)) -> 3.3727059 | K16: =MAX(INDEX(Assumptions!$B:$B, MATCH("Starship customer launch margin — 2050 terminal (multiplier on at-cost rate, floor)", Assumptions!$A:$A, 0)), $F$16 * (1 + INDEX(Assumptions!$B:$B, MATCH("Starship customer launch margin — CAGR (% change/yr from 2027 anchor)", Assumptions!$A:$A, 0)))^(K$5 - 2)) -> 3.2319013 | L16: =MAX(INDEX(Assumptions!$B:$B, MATCH("Starship customer launch margin — 2050 terminal (multiplier on at-cost rate, floor)", Assumptions!$A:$A, 0)), $F$16 * (1 + INDEX(Assumptions!$B:$B, MATCH("Starship customer launch margin — CAGR (% change/yr from 2027 anchor)", Assumptions!$A:$A, 0)))^(L$5 - 2)) -> 3.0969751 | M16: =MAX(INDEX(Assumptions!$B:$B, MATCH("Starship customer launch margin — 2050 terminal (multiplier on at-cost rate, floor)", Assumptions!$A:$A, 0)), $F$16 * (1 + INDEX(Assumptions!$B:$B, MATCH("Starship customer launch margin — CAGR (% change/yr from 2027 anchor)", Assumptions!$A:$A, 0)))^(M$5 - 2)) -> 2.9676818 | N16: =MAX(INDEX(Assumptions!$B:$B, MATCH("Starship customer launch margin — 2050 terminal (multiplier on at-cost rate, floor)", Assumptions!$A:$A, 0)), $F$16 * (1 + INDEX(Assumptions!$B:$B, MATCH("Starship customer launch margin — CAGR (% change/yr from 2027 anchor)", Assumptions!$A:$A, 0)))^(N$5 - 2)) -> 2.8437863 | ... AC16: =MAX(INDEX(Assumptions!$B:$B, MATCH("Starship customer launch margin — 2050 terminal (multiplier on at-cost rate, floor)", Assumptions!$A:$A, 0)), $F$16 * (1 + INDEX(Assumptions!$B:$B, MATCH("Starship customer launch margin — CAGR (% change/yr from 2027 anchor)", Assumptions!$A:$A, 0)))^(AC$5 - 2)) -> 1.5
A17: F9 customer launch price ($mm/launch) | D17: {=INDEX(Assumptions!$D:$AC, MATCH("F9 customer launch price ($mm/launch) — 2025 anchor", Assumptions!$A:$A, 0), D$5+1)} -> 111 | E17: {=INDEX(Assumptions!$D:$AC, MATCH("F9 customer launch price ($mm/launch) — 2025 anchor", Assumptions!$A:$A, 0), E$5+1)} -> 107.67 | F17: {=INDEX(Assumptions!$D:$AC, MATCH("F9 customer launch price ($mm/launch) — 2025 anchor", Assumptions!$A:$A, 0), F$5+1)} -> 104.44 | G17: {=INDEX(Assumptions!$D:$AC, MATCH("F9 customer launch price ($mm/launch) — 2025 anchor", Assumptions!$A:$A, 0), G$5+1)} -> 101.3 | H17: {=INDEX(Assumptions!$D:$AC, MATCH("F9 customer launch price ($mm/launch) — 2025 anchor", Assumptions!$A:$A, 0), H$5+1)} -> 98.26 | I17: {=INDEX(Assumptions!$D:$AC, MATCH("F9 customer launch price ($mm/launch) — 2025 anchor", Assumptions!$A:$A, 0), I$5+1)} -> 95.31 | J17: {=INDEX(Assumptions!$D:$AC, MATCH("F9 customer launch price ($mm/launch) — 2025 anchor", Assumptions!$A:$A, 0), J$5+1)} -> 92.45 | K17: {=INDEX(Assumptions!$D:$AC, MATCH("F9 customer launch price ($mm/launch) — 2025 anchor", Assumptions!$A:$A, 0), K$5+1)} -> 89.68 | ... AC17: {=INDEX(Assumptions!$D:$AC, MATCH("F9 customer launch price ($mm/launch) — 2025 anchor", Assumptions!$A:$A, 0), AC$5+1)} -> 51.83
A18: Starship customer launch price ($mm/launch) | D18: {=IFERROR(D16 * INDEX('Launch Capacity'!$D:$AC, MATCH("Starship at-cost rate ($mm/launch)", 'Launch Capacity'!$A:$A, 0), D$5+1), 0)} -> 0 | E18: {=IFERROR(E16 * INDEX('Launch Capacity'!$D:$AC, MATCH("Starship at-cost rate ($mm/launch)", 'Launch Capacity'!$A:$A, 0), E$5+1), 0)} -> 0 | F18: {=IFERROR(F16 * INDEX('Launch Capacity'!$D:$AC, MATCH("Starship at-cost rate ($mm/launch)", 'Launch Capacity'!$A:$A, 0), F$5+1), 0)} -> 68.22218 | G18: {=IFERROR(G16 * INDEX('Launch Capacity'!$D:$AC, MATCH("Starship at-cost rate ($mm/launch)", 'Launch Capacity'!$A:$A, 0), G$5+1), 0)} -> 57.359446 | H18: {=IFERROR(H16 * INDEX('Launch Capacity'!$D:$AC, MATCH("Starship at-cost rate ($mm/launch)", 'Launch Capacity'!$A:$A, 0), H$5+1), 0)} -> 50.303582 | I18: {=IFERROR(I16 * INDEX('Launch Capacity'!$D:$AC, MATCH("Starship at-cost rate ($mm/launch)", 'Launch Capacity'!$A:$A, 0), I$5+1), 0)} -> 45.946672 | J18: {=IFERROR(J16 * INDEX('Launch Capacity'!$D:$AC, MATCH("Starship at-cost rate ($mm/launch)", 'Launch Capacity'!$A:$A, 0), J$5+1), 0)} -> 42.049581 | K18: {=IFERROR(K16 * INDEX('Launch Capacity'!$D:$AC, MATCH("Starship at-cost rate ($mm/launch)", 'Launch Capacity'!$A:$A, 0), K$5+1), 0)} -> 38.730425 | ... AC18: {=IFERROR(AC16 * INDEX('Launch Capacity'!$D:$AC, MATCH("Starship at-cost rate ($mm/launch)", 'Launch Capacity'!$A:$A, 0), AC$5+1), 0)} -> 13.94395
A20: Starship Total Annual Capacity (kg-to-LEO) — from Launch Capacity | D20: {=INDEX('Launch Capacity'!$D:$AC, MATCH("Total Annual Capacity (kg-to-LEO)", 'Launch Capacity'!$A:$A, 0), D$5+1)} -> 242.05561 | E20: {=INDEX('Launch Capacity'!$D:$AC, MATCH("Total Annual Capacity (kg-to-LEO)", 'Launch Capacity'!$A:$A, 0), E$5+1)} -> 138407.54 | F20: {=INDEX('Launch Capacity'!$D:$AC, MATCH("Total Annual Capacity (kg-to-LEO)", 'Launch Capacity'!$A:$A, 0), F$5+1)} -> 232172.87 | G20: {=INDEX('Launch Capacity'!$D:$AC, MATCH("Total Annual Capacity (kg-to-LEO)", 'Launch Capacity'!$A:$A, 0), G$5+1)} -> 423134.28 | H20: {=INDEX('Launch Capacity'!$D:$AC, MATCH("Total Annual Capacity (kg-to-LEO)", 'Launch Capacity'!$A:$A, 0), H$5+1)} -> 665049.24 | I20: {=INDEX('Launch Capacity'!$D:$AC, MATCH("Total Annual Capacity (kg-to-LEO)", 'Launch Capacity'!$A:$A, 0), I$5+1)} -> 1155020.2 | J20: {=INDEX('Launch Capacity'!$D:$AC, MATCH("Total Annual Capacity (kg-to-LEO)", 'Launch Capacity'!$A:$A, 0), J$5+1)} -> 1578855.8 | K20: {=INDEX('Launch Capacity'!$D:$AC, MATCH("Total Annual Capacity (kg-to-LEO)", 'Launch Capacity'!$A:$A, 0), K$5+1)} -> 1644199.4 | ... AC20: {=INDEX('Launch Capacity'!$D:$AC, MATCH("Total Annual Capacity (kg-to-LEO)", 'Launch Capacity'!$A:$A, 0), AC$5+1)} -> 5026680.7
A21: Per-launch upmass (kg) — from Launch Capacity | D21: {=INDEX('Launch Capacity'!$D:$AC, MATCH("Per-launch upmass (kg)", 'Launch Capacity'!$A:$A, 0), D$5+1)} -> 150000 | E21: {=INDEX('Launch Capacity'!$D:$AC, MATCH("Per-launch upmass (kg)", 'Launch Capacity'!$A:$A, 0), E$5+1)} -> 150000 | F21: {=INDEX('Launch Capacity'!$D:$AC, MATCH("Per-launch upmass (kg)", 'Launch Capacity'!$A:$A, 0), F$5+1)} -> 100000 | G21: {=INDEX('Launch Capacity'!$D:$AC, MATCH("Per-launch upmass (kg)", 'Launch Capacity'!$A:$A, 0), G$5+1)} -> 100000 | H21: {=INDEX('Launch Capacity'!$D:$AC, MATCH("Per-launch upmass (kg)", 'Launch Capacity'!$A:$A, 0), H$5+1)} -> 100000 | I21: {=INDEX('Launch Capacity'!$D:$AC, MATCH("Per-launch upmass (kg)", 'Launch Capacity'!$A:$A, 0), I$5+1)} -> 100000 | J21: {=INDEX('Launch Capacity'!$D:$AC, MATCH("Per-launch upmass (kg)", 'Launch Capacity'!$A:$A, 0), J$5+1)} -> 100000 | K21: {=INDEX('Launch Capacity'!$D:$AC, MATCH("Per-launch upmass (kg)", 'Launch Capacity'!$A:$A, 0), K$5+1)} -> 100000 | ... AC21: {=INDEX('Launch Capacity'!$D:$AC, MATCH("Per-launch upmass (kg)", 'Launch Capacity'!$A:$A, 0), AC$5+1)} -> 100000
A22: Starship internal kg demand (post-Starlink + ODC + AI Stack) | D22: {=IFERROR(INDEX(Starlink!$D:$AC, MATCH("V3 BB Starship kg demand", Starlink!$A:$A, 0), D$5+1), 0) + IFERROR(INDEX(Starlink!$D:$AC, MATCH("V3 DTC Starship kg demand", Starlink!$A:$A, 0), D$5+1), 0) + IFERROR(INDEX(ODC!$D:$AC, MATCH("ODC Starship kg demand", ODC!$A:$A, 0), D$5+1), 0) + IFERROR(INDEX('AI Stack'!$D:$AC, MATCH("AI Stack Starship kg demand", 'AI Stack'!$A:$A, 0), D$5+1), 0)} -> 0 | E22: {=IFERROR(INDEX(Starlink!$D:$AC, MATCH("V3 BB Starship kg demand", Starlink!$A:$A, 0), E$5+1), 0) + IFERROR(INDEX(Starlink!$D:$AC, MATCH("V3 DTC Starship kg demand", Starlink!$A:$A, 0), E$5+1), 0) + IFERROR(INDEX(ODC!$D:$AC, MATCH("ODC Starship kg demand", ODC!$A:$A, 0), E$5+1), 0) + IFERROR(INDEX('AI Stack'!$D:$AC, MATCH("AI Stack Starship kg demand", 'AI Stack'!$A:$A, 0), E$5+1), 0)} -> 0 | F22: {=IFERROR(INDEX(Starlink!$D:$AC, MATCH("V3 BB Starship kg demand", Starlink!$A:$A, 0), F$5+1), 0) + IFERROR(INDEX(Starlink!$D:$AC, MATCH("V3 DTC Starship kg demand", Starlink!$A:$A, 0), F$5+1), 0) + IFERROR(INDEX(ODC!$D:$AC, MATCH("ODC Starship kg demand", ODC!$A:$A, 0), F$5+1), 0) + IFERROR(INDEX('AI Stack'!$D:$AC, MATCH("AI Stack Starship kg demand", 'AI Stack'!$A:$A, 0), F$5+1), 0)} -> 0 | G22: {=IFERROR(INDEX(Starlink!$D:$AC, MATCH("V3 BB Starship kg demand", Starlink!$A:$A, 0), G$5+1), 0) + IFERROR(INDEX(Starlink!$D:$AC, MATCH("V3 DTC Starship kg demand", Starlink!$A:$A, 0), G$5+1), 0) + IFERROR(INDEX(ODC!$D:$AC, MATCH("ODC Starship kg demand", ODC!$A:$A, 0), G$5+1), 0) + IFERROR(INDEX('AI Stack'!$D:$AC, MATCH("AI Stack Starship kg demand", 'AI Stack'!$A:$A, 0), G$5+1), 0)} -> 0 | H22: {=IFERROR(INDEX(Starlink!$D:$AC, MATCH("V3 BB Starship kg demand", Starlink!$A:$A, 0), H$5+1), 0) + IFERROR(INDEX(Starlink!$D:$AC, MATCH("V3 DTC Starship kg demand", Starlink!$A:$A, 0), H$5+1), 0) + IFERROR(INDEX(ODC!$D:$AC, MATCH("ODC Starship kg demand", ODC!$A:$A, 0), H$5+1), 0) + IFERROR(INDEX('AI Stack'!$D:$AC, MATCH("AI Stack Starship kg demand", 'AI Stack'!$A:$A, 0), H$5+1), 0)} -> 0 | I22: {=IFERROR(INDEX(Starlink!$D:$AC, MATCH("V3 BB Starship kg demand", Starlink!$A:$A, 0), I$5+1), 0) + IFERROR(INDEX(Starlink!$D:$AC, MATCH("V3 DTC Starship kg demand", Starlink!$A:$A, 0), I$5+1), 0) + IFERROR(INDEX(ODC!$D:$AC, MATCH("ODC Starship kg demand", ODC!$A:$A, 0), I$5+1), 0) + IFERROR(INDEX('AI Stack'!$D:$AC, MATCH("AI Stack Starship kg demand", 'AI Stack'!$A:$A, 0), I$5+1), 0)} -> 0 | J22: {=IFERROR(INDEX(Starlink!$D:$AC, MATCH("V3 BB Starship kg demand", Starlink!$A:$A, 0), J$5+1), 0) + IFERROR(INDEX(Starlink!$D:$AC, MATCH("V3 DTC Starship kg demand", Starlink!$A:$A, 0), J$5+1), 0) + IFERROR(INDEX(ODC!$D:$AC, MATCH("ODC Starship kg demand", ODC!$A:$A, 0), J$5+1), 0) + IFERROR(INDEX('AI Stack'!$D:$AC, MATCH("AI Stack Starship kg demand", 'AI Stack'!$A:$A, 0), J$5+1), 0)} -> 0 | K22: {=IFERROR(INDEX(Starlink!$D:$AC, MATCH("V3 BB Starship kg demand", Starlink!$A:$A, 0), K$5+1), 0) + IFERROR(INDEX(Starlink!$D:$AC, MATCH("V3 DTC Starship kg demand", Starlink!$A:$A, 0), K$5+1), 0) + IFERROR(INDEX(ODC!$D:$AC, MATCH("ODC Starship kg demand", ODC!$A:$A, 0), K$5+1), 0) + IFERROR(INDEX('AI Stack'!$D:$AC, MATCH("AI Stack Starship kg demand", 'AI Stack'!$A:$A, 0), K$5+1), 0)} -> 0 | ... AC22: {=IFERROR(INDEX(Starlink!$D:$AC, MATCH("V3 BB Starship kg demand", Starlink!$A:$A, 0), AC$5+1), 0) + IFERROR(INDEX(Starlink!$D:$AC, MATCH("V3 DTC Starship kg demand", Starlink!$A:$A, 0), AC$5+1), 0) + IFERROR(INDEX(ODC!$D:$AC, MATCH("ODC Starship kg demand", ODC!$A:$A, 0), AC$5+1), 0) + IFERROR(INDEX('AI Stack'!$D:$AC, MATCH("AI Stack Starship kg demand", 'AI Stack'!$A:$A, 0), AC$5+1), 0)} -> 0
A23: Starship capacity available for customer launches (kg) | D23: =MAX(0, D20-D22) -> 242.05561 | E23: =MAX(0, E20-E22) -> 138407.54 | F23: =MAX(0, F20-F22) -> 232172.87 | G23: =MAX(0, G20-G22) -> 423134.28 | H23: =MAX(0, H20-H22) -> 665049.24 | I23: =MAX(0, I20-I22) -> 1155020.2 | J23: =MAX(0, J20-J22) -> 1578855.8 | K23: =MAX(0, K20-K22) -> 1644199.4 | ... AC23: =MAX(0, AC20-AC22) -> 5026680.7
A24: Starship customer launches per year | D24: 0 | E24: 0 | F24: =IF(F16>0, MIN($D$15 * (1 + INDEX(Assumptions!$B:$B, MATCH("Total customer launch market CAGR (% growth/yr)", Assumptions!$A:$A, 0)))^F$5, IFERROR(F23/F21, 0)), 0) -> 2.3217287 | G24: =IF(G16>0, MIN($D$15 * (1 + INDEX(Assumptions!$B:$B, MATCH("Total customer launch market CAGR (% growth/yr)", Assumptions!$A:$A, 0)))^G$5, IFERROR(G23/G21, 0)), 0) -> 4.2313428 | H24: =IF(H16>0, MIN($D$15 * (1 + INDEX(Assumptions!$B:$B, MATCH("Total customer launch market CAGR (% growth/yr)", Assumptions!$A:$A, 0)))^H$5, IFERROR(H23/H21, 0)), 0) -> 6.6504924 | I24: =IF(I16>0, MIN($D$15 * (1 + INDEX(Assumptions!$B:$B, MATCH("Total customer launch market CAGR (% growth/yr)", Assumptions!$A:$A, 0)))^I$5, IFERROR(I23/I21, 0)), 0) -> 11.550202 | J24: =IF(J16>0, MIN($D$15 * (1 + INDEX(Assumptions!$B:$B, MATCH("Total customer launch market CAGR (% growth/yr)", Assumptions!$A:$A, 0)))^J$5, IFERROR(J23/J21, 0)), 0) -> 15.788558 | K24: =IF(K16>0, MIN($D$15 * (1 + INDEX(Assumptions!$B:$B, MATCH("Total customer launch market CAGR (% growth/yr)", Assumptions!$A:$A, 0)))^K$5, IFERROR(K23/K21, 0)), 0) -> 16.441994 | L24: =IF(L16>0, MIN($D$15 * (1 + INDEX(Assumptions!$B:$B, MATCH("Total customer launch market CAGR (% growth/yr)", Assumptions!$A:$A, 0)))^L$5, IFERROR(L23/L21, 0)), 0) -> 37.601461 | M24: =IF(M16>0, MIN($D$15 * (1 + INDEX(Assumptions!$B:$B, MATCH("Total customer launch market CAGR (% growth/yr)", Assumptions!$A:$A, 0)))^M$5, IFERROR(M23/M21, 0)), 0) -> 19.744323 | ... AC24: =IF(AC16>0, MIN($D$15 * (1 + INDEX(Assumptions!$B:$B, MATCH("Total customer launch market CAGR (% growth/yr)", Assumptions!$A:$A, 0)))^AC$5, IFERROR(AC23/AC21, 0)), 0) -> 50.266807
A25: F9 customer launches per year | D25: 38.58 | E25: =$D$25 * (1 + INDEX(Assumptions!$B:$B, MATCH("Total customer launch market CAGR (% growth/yr)", Assumptions!$A:$A, 0))) -> 40.509 | F25: =MAX(0, $D$15 * (1 + INDEX(Assumptions!$B:$B, MATCH("Total customer launch market CAGR (% growth/yr)", Assumptions!$A:$A, 0)))^F$5 - F24) -> 40.212721 | G25: =MAX(0, $D$15 * (1 + INDEX(Assumptions!$B:$B, MATCH("Total customer launch market CAGR (% growth/yr)", Assumptions!$A:$A, 0)))^G$5 - G24) -> 40.42983 | H25: =MAX(0, $D$15 * (1 + INDEX(Assumptions!$B:$B, MATCH("Total customer launch market CAGR (% growth/yr)", Assumptions!$A:$A, 0)))^H$5 - H24) -> 40.243739 | I25: =MAX(0, $D$15 * (1 + INDEX(Assumptions!$B:$B, MATCH("Total customer launch market CAGR (% growth/yr)", Assumptions!$A:$A, 0)))^I$5 - I24) -> 37.688741 | J25: =MAX(0, $D$15 * (1 + INDEX(Assumptions!$B:$B, MATCH("Total customer launch market CAGR (% growth/yr)", Assumptions!$A:$A, 0)))^J$5 - J24) -> 35.912332 | K25: =MAX(0, $D$15 * (1 + INDEX(Assumptions!$B:$B, MATCH("Total customer launch market CAGR (% growth/yr)", Assumptions!$A:$A, 0)))^K$5 - K24) -> 37.84394 | L25: =MAX(0, $D$15 * (1 + INDEX(Assumptions!$B:$B, MATCH("Total customer launch market CAGR (% growth/yr)", Assumptions!$A:$A, 0)))^L$5 - L24) -> 19.39877 | M25: =MAX(0, $D$15 * (1 + INDEX(Assumptions!$B:$B, MATCH("Total customer launch market CAGR (% growth/yr)", Assumptions!$A:$A, 0)))^M$5 - M24) -> 40.10592 | ... AC25: =MAX(0, $D$15 * (1 + INDEX(Assumptions!$B:$B, MATCH("Total customer launch market CAGR (% growth/yr)", Assumptions!$A:$A, 0)))^AC$5 - AC24) -> 80.378766
A32: ▸ F9 customer launches — economics
A33: F9 customer revenue ($mm) | D33: =D25*D17 -> 4282.38 | E33: =E25*E17 -> 4361.604 | F33: =F25*F17 -> 4199.8166 | G33: =G25*G17 -> 4095.5417 | H33: =H25*H17 -> 3954.3498 | I33: =I25*I17 -> 3592.1139 | J33: =J25*J17 -> 3320.0951 | K33: =K25*K17 -> 3393.8446 | ... AC33: =AC25*AC17 -> 4166.0315
A34: F9 variable cost per launch ($mm) — read from Launch Capacity | D34: {=INDEX('Launch Capacity'!$D:$AC, MATCH("F9 variable cost per launch ($mm)", 'Launch Capacity'!$A:$A, 0), D$5+1)} -> 17.15 | E34: {=INDEX('Launch Capacity'!$D:$AC, MATCH("F9 variable cost per launch ($mm)", 'Launch Capacity'!$A:$A, 0), E$5+1)} -> 17.15 | F34: {=INDEX('Launch Capacity'!$D:$AC, MATCH("F9 variable cost per launch ($mm)", 'Launch Capacity'!$A:$A, 0), F$5+1)} -> 17.15 | G34: {=INDEX('Launch Capacity'!$D:$AC, MATCH("F9 variable cost per launch ($mm)", 'Launch Capacity'!$A:$A, 0), G$5+1)} -> 17.15 | H34: {=INDEX('Launch Capacity'!$D:$AC, MATCH("F9 variable cost per launch ($mm)", 'Launch Capacity'!$A:$A, 0), H$5+1)} -> 17.15 | I34: {=INDEX('Launch Capacity'!$D:$AC, MATCH("F9 variable cost per launch ($mm)", 'Launch Capacity'!$A:$A, 0), I$5+1)} -> 17.15 | J34: {=INDEX('Launch Capacity'!$D:$AC, MATCH("F9 variable cost per launch ($mm)", 'Launch Capacity'!$A:$A, 0), J$5+1)} -> 17.15 | K34: {=INDEX('Launch Capacity'!$D:$AC, MATCH("F9 variable cost per launch ($mm)", 'Launch Capacity'!$A:$A, 0), K$5+1)} -> 17.15 | ... AC34: {=INDEX('Launch Capacity'!$D:$AC, MATCH("F9 variable cost per launch ($mm)", 'Launch Capacity'!$A:$A, 0), AC$5+1)} -> 17.15
A35: F9 D&A share per launch ($mm) — read from Launch Capacity | D35: {=INDEX('Launch Capacity'!$D:$AC, MATCH("F9 booster D&A share per launch ($mm)", 'Launch Capacity'!$A:$A, 0), D$5+1)} -> 0.6 | E35: {=INDEX('Launch Capacity'!$D:$AC, MATCH("F9 booster D&A share per launch ($mm)", 'Launch Capacity'!$A:$A, 0), E$5+1)} -> 0.6 | F35: {=INDEX('Launch Capacity'!$D:$AC, MATCH("F9 booster D&A share per launch ($mm)", 'Launch Capacity'!$A:$A, 0), F$5+1)} -> 0.6 | G35: {=INDEX('Launch Capacity'!$D:$AC, MATCH("F9 booster D&A share per launch ($mm)", 'Launch Capacity'!$A:$A, 0), G$5+1)} -> 0.6 | H35: {=INDEX('Launch Capacity'!$D:$AC, MATCH("F9 booster D&A share per launch ($mm)", 'Launch Capacity'!$A:$A, 0), H$5+1)} -> 0.6 | I35: {=INDEX('Launch Capacity'!$D:$AC, MATCH("F9 booster D&A share per launch ($mm)", 'Launch Capacity'!$A:$A, 0), I$5+1)} -> 0.6 | J35: {=INDEX('Launch Capacity'!$D:$AC, MATCH("F9 booster D&A share per launch ($mm)", 'Launch Capacity'!$A:$A, 0), J$5+1)} -> 0.6 | K35: {=INDEX('Launch Capacity'!$D:$AC, MATCH("F9 booster D&A share per launch ($mm)", 'Launch Capacity'!$A:$A, 0), K$5+1)} -> 0.6 | ... AC35: {=INDEX('Launch Capacity'!$D:$AC, MATCH("F9 booster D&A share per launch ($mm)", 'Launch Capacity'!$A:$A, 0), AC$5+1)} -> 0.6
A36: F9 at-cost rate ($mm/launch) — read from Launch Capacity | D36: {=INDEX('Launch Capacity'!$D:$AC, MATCH("F9 at-cost rate ($mm/launch)", 'Launch Capacity'!$A:$A, 0), D$5+1)} -> 17.75 | E36: {=INDEX('Launch Capacity'!$D:$AC, MATCH("F9 at-cost rate ($mm/launch)", 'Launch Capacity'!$A:$A, 0), E$5+1)} -> 17.75 | F36: {=INDEX('Launch Capacity'!$D:$AC, MATCH("F9 at-cost rate ($mm/launch)", 'Launch Capacity'!$A:$A, 0), F$5+1)} -> 17.75 | G36: {=INDEX('Launch Capacity'!$D:$AC, MATCH("F9 at-cost rate ($mm/launch)", 'Launch Capacity'!$A:$A, 0), G$5+1)} -> 17.75 | H36: {=INDEX('Launch Capacity'!$D:$AC, MATCH("F9 at-cost rate ($mm/launch)", 'Launch Capacity'!$A:$A, 0), H$5+1)} -> 17.75 | I36: {=INDEX('Launch Capacity'!$D:$AC, MATCH("F9 at-cost rate ($mm/launch)", 'Launch Capacity'!$A:$A, 0), I$5+1)} -> 17.75 | J36: {=INDEX('Launch Capacity'!$D:$AC, MATCH("F9 at-cost rate ($mm/launch)", 'Launch Capacity'!$A:$A, 0), J$5+1)} -> 17.75 | K36: {=INDEX('Launch Capacity'!$D:$AC, MATCH("F9 at-cost rate ($mm/launch)", 'Launch Capacity'!$A:$A, 0), K$5+1)} -> 17.75 | ... AC36: {=INDEX('Launch Capacity'!$D:$AC, MATCH("F9 at-cost rate ($mm/launch)", 'Launch Capacity'!$A:$A, 0), AC$5+1)} -> 17.75
A37: F9 customer launch insurance + other COGS ($mm/launch) | D37: =IFERROR(D33/D25, 0) * (IFERROR(INDEX(Assumptions!$B:$B, MATCH("Launch insurance % of external revenue", Assumptions!$A:$A, 0)), 0.01) + IFERROR(INDEX(Assumptions!$B:$B, MATCH("Launch other COGS % of external revenue", Assumptions!$A:$A, 0)), 0.01)) -> 7.77 | E37: =IFERROR(E33/E25, 0) * (IFERROR(INDEX(Assumptions!$B:$B, MATCH("Launch insurance % of external revenue", Assumptions!$A:$A, 0)), 0.01) + IFERROR(INDEX(Assumptions!$B:$B, MATCH("Launch other COGS % of external revenue", Assumptions!$A:$A, 0)), 0.01)) -> 7.5369 | F37: =IFERROR(F33/F25, 0) * (IFERROR(INDEX(Assumptions!$B:$B, MATCH("Launch insurance % of external revenue", Assumptions!$A:$A, 0)), 0.01) + IFERROR(INDEX(Assumptions!$B:$B, MATCH("Launch other COGS % of external revenue", Assumptions!$A:$A, 0)), 0.01)) -> 7.3108 | G37: =IFERROR(G33/G25, 0) * (IFERROR(INDEX(Assumptions!$B:$B, MATCH("Launch insurance % of external revenue", Assumptions!$A:$A, 0)), 0.01) + IFERROR(INDEX(Assumptions!$B:$B, MATCH("Launch other COGS % of external revenue", Assumptions!$A:$A, 0)), 0.01)) -> 7.091 | H37: =IFERROR(H33/H25, 0) * (IFERROR(INDEX(Assumptions!$B:$B, MATCH("Launch insurance % of external revenue", Assumptions!$A:$A, 0)), 0.01) + IFERROR(INDEX(Assumptions!$B:$B, MATCH("Launch other COGS % of external revenue", Assumptions!$A:$A, 0)), 0.01)) -> 6.8782 | I37: =IFERROR(I33/I25, 0) * (IFERROR(INDEX(Assumptions!$B:$B, MATCH("Launch insurance % of external revenue", Assumptions!$A:$A, 0)), 0.01) + IFERROR(INDEX(Assumptions!$B:$B, MATCH("Launch other COGS % of external revenue", Assumptions!$A:$A, 0)), 0.01)) -> 6.6717 | J37: =IFERROR(J33/J25, 0) * (IFERROR(INDEX(Assumptions!$B:$B, MATCH("Launch insurance % of external revenue", Assumptions!$A:$A, 0)), 0.01) + IFERROR(INDEX(Assumptions!$B:$B, MATCH("Launch other COGS % of external revenue", Assumptions!$A:$A, 0)), 0.01)) -> 6.4715 | K37: =IFERROR(K33/K25, 0) * (IFERROR(INDEX(Assumptions!$B:$B, MATCH("Launch insurance % of external revenue", Assumptions!$A:$A, 0)), 0.01) + IFERROR(INDEX(Assumptions!$B:$B, MATCH("Launch other COGS % of external revenue", Assumptions!$A:$A, 0)), 0.01)) -> 6.2776 | ... AC37: =IFERROR(AC33/AC25, 0) * (IFERROR(INDEX(Assumptions!$B:$B, MATCH("Launch insurance % of external revenue", Assumptions!$A:$A, 0)), 0.01) + IFERROR(INDEX(Assumptions!$B:$B, MATCH("Launch other COGS % of external revenue", Assumptions!$A:$A, 0)), 0.01)) -> 3.6281
A47: ▸ Starship customer launches — economics
A48: Starship customer revenue ($mm) | D48: =D24*D18 -> 0 | E48: =E24*E18 -> 0 | F48: =F24*F18 -> 158.39339 | G48: =G24*G18 -> 242.70748 | H48: =H24*H18 -> 334.54359 | I48: =I24*I18 -> 530.69332 | J48: =J24*J18 -> 663.90224 | K48: =K24*K18 -> 636.80543 | ... AC48: =AC24*AC18 -> 700.91784
A49: Starship ops + fuel + refurb cost per launch ($mm) — read from Launch Capacity | D49: {=INDEX('Launch Capacity'!$D:$AC, MATCH("Starship ops + fuel + refurb cost per launch ($mm, this year)", 'Launch Capacity'!$A:$A, 0), D$5+1)} -> 12 | E49: {=INDEX('Launch Capacity'!$D:$AC, MATCH("Starship ops + fuel + refurb cost per launch ($mm, this year)", 'Launch Capacity'!$A:$A, 0), E$5+1)} -> 11.999264 | F49: {=INDEX('Launch Capacity'!$D:$AC, MATCH("Starship ops + fuel + refurb cost per launch ($mm, this year)", 'Launch Capacity'!$A:$A, 0), F$5+1)} -> 11.626723 | G49: {=INDEX('Launch Capacity'!$D:$AC, MATCH("Starship ops + fuel + refurb cost per launch ($mm, this year)", 'Launch Capacity'!$A:$A, 0), G$5+1)} -> 11.192511 | H49: {=INDEX('Launch Capacity'!$D:$AC, MATCH("Starship ops + fuel + refurb cost per launch ($mm, this year)", 'Launch Capacity'!$A:$A, 0), H$5+1)} -> 10.82809 | I49: {=INDEX('Launch Capacity'!$D:$AC, MATCH("Starship ops + fuel + refurb cost per launch ($mm, this year)", 'Launch Capacity'!$A:$A, 0), I$5+1)} -> 10.582962 | J49: {=INDEX('Launch Capacity'!$D:$AC, MATCH("Starship ops + fuel + refurb cost per launch ($mm, this year)", 'Launch Capacity'!$A:$A, 0), J$5+1)} -> 10.300429 | K49: {=INDEX('Launch Capacity'!$D:$AC, MATCH("Starship ops + fuel + refurb cost per launch ($mm, this year)", 'Launch Capacity'!$A:$A, 0), K$5+1)} -> 10.083281 | ... AC49: {=INDEX('Launch Capacity'!$D:$AC, MATCH("Starship ops + fuel + refurb cost per launch ($mm, this year)", 'Launch Capacity'!$A:$A, 0), AC$5+1)} -> 8.3089746
A50: Starship D&A share per launch ($mm) — read from Launch Capacity | D50: {=INDEX('Launch Capacity'!$D:$AC, MATCH("Starship D&A share per launch, fully reusable mode ($mm)", 'Launch Capacity'!$A:$A, 0), D$5+1)} -> 12 | E50: {=INDEX('Launch Capacity'!$D:$AC, MATCH("Starship D&A share per launch, fully reusable mode ($mm)", 'Launch Capacity'!$A:$A, 0), E$5+1)} -> 7.9492482 | F50: {=INDEX('Launch Capacity'!$D:$AC, MATCH("Starship D&A share per launch, fully reusable mode ($mm)", 'Launch Capacity'!$A:$A, 0), F$5+1)} -> 5.4288225 | G50: {=INDEX('Launch Capacity'!$D:$AC, MATCH("Starship D&A share per launch, fully reusable mode ($mm)", 'Launch Capacity'!$A:$A, 0), G$5+1)} -> 3.7720968 | H50: {=INDEX('Launch Capacity'!$D:$AC, MATCH("Starship D&A share per launch, fully reusable mode ($mm)", 'Launch Capacity'!$A:$A, 0), H$5+1)} -> 2.8674662 | I50: {=INDEX('Launch Capacity'!$D:$AC, MATCH("Starship D&A share per launch, fully reusable mode ($mm)", 'Launch Capacity'!$A:$A, 0), I$5+1)} -> 2.4713865 | J50: {=INDEX('Launch Capacity'!$D:$AC, MATCH("Starship D&A share per launch, fully reusable mode ($mm)", 'Launch Capacity'!$A:$A, 0), J$5+1)} -> 2.1671811 | K50: {=INDEX('Launch Capacity'!$D:$AC, MATCH("Starship D&A share per launch, fully reusable mode ($mm)", 'Launch Capacity'!$A:$A, 0), K$5+1)} -> 1.9005084 | ... AC50: {=INDEX('Launch Capacity'!$D:$AC, MATCH("Starship D&A share per launch, fully reusable mode ($mm)", 'Launch Capacity'!$A:$A, 0), AC$5+1)} -> 0.98699189
A51: Starship at-cost rate ($mm/launch) — read from Launch Capacity | D51: {=INDEX('Launch Capacity'!$D:$AC, MATCH("Starship at-cost rate ($mm/launch)", 'Launch Capacity'!$A:$A, 0), D$5+1)} -> 24 | E51: {=INDEX('Launch Capacity'!$D:$AC, MATCH("Starship at-cost rate ($mm/launch)", 'Launch Capacity'!$A:$A, 0), E$5+1)} -> 19.948513 | F51: {=INDEX('Launch Capacity'!$D:$AC, MATCH("Starship at-cost rate ($mm/launch)", 'Launch Capacity'!$A:$A, 0), F$5+1)} -> 17.055545 | G51: {=INDEX('Launch Capacity'!$D:$AC, MATCH("Starship at-cost rate ($mm/launch)", 'Launch Capacity'!$A:$A, 0), G$5+1)} -> 14.964608 | H51: {=INDEX('Launch Capacity'!$D:$AC, MATCH("Starship at-cost rate ($mm/launch)", 'Launch Capacity'!$A:$A, 0), H$5+1)} -> 13.695556 | I51: {=INDEX('Launch Capacity'!$D:$AC, MATCH("Starship at-cost rate ($mm/launch)", 'Launch Capacity'!$A:$A, 0), I$5+1)} -> 13.054349 | J51: {=INDEX('Launch Capacity'!$D:$AC, MATCH("Starship at-cost rate ($mm/launch)", 'Launch Capacity'!$A:$A, 0), J$5+1)} -> 12.46761 | K51: {=INDEX('Launch Capacity'!$D:$AC, MATCH("Starship at-cost rate ($mm/launch)", 'Launch Capacity'!$A:$A, 0), K$5+1)} -> 11.98379 | ... AC51: {=INDEX('Launch Capacity'!$D:$AC, MATCH("Starship at-cost rate ($mm/launch)", 'Launch Capacity'!$A:$A, 0), AC$5+1)} -> 9.2959665
A52: Starship customer launch insurance + other COGS ($mm/launch) | D52: =IFERROR(D48/D24, 0) * (IFERROR(INDEX(Assumptions!$B:$B, MATCH("Launch insurance % of external revenue", Assumptions!$A:$A, 0)), 0.01) + IFERROR(INDEX(Assumptions!$B:$B, MATCH("Launch other COGS % of external revenue", Assumptions!$A:$A, 0)), 0.01)) -> 0 | E52: =IFERROR(E48/E24, 0) * (IFERROR(INDEX(Assumptions!$B:$B, MATCH("Launch insurance % of external revenue", Assumptions!$A:$A, 0)), 0.01) + IFERROR(INDEX(Assumptions!$B:$B, MATCH("Launch other COGS % of external revenue", Assumptions!$A:$A, 0)), 0.01)) -> 0 | F52: =IFERROR(F48/F24, 0) * (IFERROR(INDEX(Assumptions!$B:$B, MATCH("Launch insurance % of external revenue", Assumptions!$A:$A, 0)), 0.01) + IFERROR(INDEX(Assumptions!$B:$B, MATCH("Launch other COGS % of external revenue", Assumptions!$A:$A, 0)), 0.01)) -> 4.7755526 | G52: =IFERROR(G48/G24, 0) * (IFERROR(INDEX(Assumptions!$B:$B, MATCH("Launch insurance % of external revenue", Assumptions!$A:$A, 0)), 0.01) + IFERROR(INDEX(Assumptions!$B:$B, MATCH("Launch other COGS % of external revenue", Assumptions!$A:$A, 0)), 0.01)) -> 4.0151612 | H52: =IFERROR(H48/H24, 0) * (IFERROR(INDEX(Assumptions!$B:$B, MATCH("Launch insurance % of external revenue", Assumptions!$A:$A, 0)), 0.01) + IFERROR(INDEX(Assumptions!$B:$B, MATCH("Launch other COGS % of external revenue", Assumptions!$A:$A, 0)), 0.01)) -> 3.5212507 | I52: =IFERROR(I48/I24, 0) * (IFERROR(INDEX(Assumptions!$B:$B, MATCH("Launch insurance % of external revenue", Assumptions!$A:$A, 0)), 0.01) + IFERROR(INDEX(Assumptions!$B:$B, MATCH("Launch other COGS % of external revenue", Assumptions!$A:$A, 0)), 0.01)) -> 3.216267 | J52: =IFERROR(J48/J24, 0) * (IFERROR(INDEX(Assumptions!$B:$B, MATCH("Launch insurance % of external revenue", Assumptions!$A:$A, 0)), 0.01) + IFERROR(INDEX(Assumptions!$B:$B, MATCH("Launch other COGS % of external revenue", Assumptions!$A:$A, 0)), 0.01)) -> 2.9434707 | K52: =IFERROR(K48/K24, 0) * (IFERROR(INDEX(Assumptions!$B:$B, MATCH("Launch insurance % of external revenue", Assumptions!$A:$A, 0)), 0.01) + IFERROR(INDEX(Assumptions!$B:$B, MATCH("Launch other COGS % of external revenue", Assumptions!$A:$A, 0)), 0.01)) -> 2.7111298 | ... AC52: =IFERROR(AC48/AC24, 0) * (IFERROR(INDEX(Assumptions!$B:$B, MATCH("Launch insurance % of external revenue", Assumptions!$A:$A, 0)), 0.01) + IFERROR(INDEX(Assumptions!$B:$B, MATCH("Launch other COGS % of external revenue", Assumptions!$A:$A, 0)), 0.01)) -> 0.97607649
A67: ▸ Internal transfer revenue (launch services to Sprint 4/5/6 consumers)
A68: F9 internal launches (BB + DTC) | D68: {=IFERROR(INDEX(Starlink!$D:$AC, MATCH("F9 V2 BB launches (internal)", Starlink!$A:$A, 0), D$5+1), 0) + IFERROR(INDEX(Starlink!$D:$AC, MATCH("F9 V2 DTC launches (internal)", Starlink!$A:$A, 0), D$5+1), 0)} -> 129 | E68: {=IFERROR(INDEX(Starlink!$D:$AC, MATCH("F9 V2 BB launches (internal)", Starlink!$A:$A, 0), E$5+1), 0) + IFERROR(INDEX(Starlink!$D:$AC, MATCH("F9 V2 DTC launches (internal)", Starlink!$A:$A, 0), E$5+1), 0)} -> 0 | F68: {=IFERROR(INDEX(Starlink!$D:$AC, MATCH("F9 V2 BB launches (internal)", Starlink!$A:$A, 0), F$5+1), 0) + IFERROR(INDEX(Starlink!$D:$AC, MATCH("F9 V2 DTC launches (internal)", Starlink!$A:$A, 0), F$5+1), 0)} -> 0 | G68: {=IFERROR(INDEX(Starlink!$D:$AC, MATCH("F9 V2 BB launches (internal)", Starlink!$A:$A, 0), G$5+1), 0) + IFERROR(INDEX(Starlink!$D:$AC, MATCH("F9 V2 DTC launches (internal)", Starlink!$A:$A, 0), G$5+1), 0)} -> 0 | H68: {=IFERROR(INDEX(Starlink!$D:$AC, MATCH("F9 V2 BB launches (internal)", Starlink!$A:$A, 0), H$5+1), 0) + IFERROR(INDEX(Starlink!$D:$AC, MATCH("F9 V2 DTC launches (internal)", Starlink!$A:$A, 0), H$5+1), 0)} -> 0 | I68: {=IFERROR(INDEX(Starlink!$D:$AC, MATCH("F9 V2 BB launches (internal)", Starlink!$A:$A, 0), I$5+1), 0) + IFERROR(INDEX(Starlink!$D:$AC, MATCH("F9 V2 DTC launches (internal)", Starlink!$A:$A, 0), I$5+1), 0)} -> 0 | J68: {=IFERROR(INDEX(Starlink!$D:$AC, MATCH("F9 V2 BB launches (internal)", Starlink!$A:$A, 0), J$5+1), 0) + IFERROR(INDEX(Starlink!$D:$AC, MATCH("F9 V2 DTC launches (internal)", Starlink!$A:$A, 0), J$5+1), 0)} -> 0 | K68: {=IFERROR(INDEX(Starlink!$D:$AC, MATCH("F9 V2 BB launches (internal)", Starlink!$A:$A, 0), K$5+1), 0) + IFERROR(INDEX(Starlink!$D:$AC, MATCH("F9 V2 DTC launches (internal)", Starlink!$A:$A, 0), K$5+1), 0)} -> 0 | ... AC68: {=IFERROR(INDEX(Starlink!$D:$AC, MATCH("F9 V2 BB launches (internal)", Starlink!$A:$A, 0), AC$5+1), 0) + IFERROR(INDEX(Starlink!$D:$AC, MATCH("F9 V2 DTC launches (internal)", Starlink!$A:$A, 0), AC$5+1), 0)} -> 0
A69: Starship internal launches (V3 BB + V3 DTC + ODC + AI Stack) | D69: {=IFERROR(INDEX(Starlink!$D:$AC, MATCH("Starship V3 BB launches (internal)", Starlink!$A:$A, 0), D$5+1), 0) + IFERROR(INDEX(Starlink!$D:$AC, MATCH("Starship V3 DTC launches (internal)", Starlink!$A:$A, 0), D$5+1), 0) + IFERROR(INDEX(ODC!$D:$AC, MATCH("ODC Starship launches (internal)", ODC!$A:$A, 0), D$5+1), 0)} -> 0 | E69: {=IFERROR(INDEX(Starlink!$D:$AC, MATCH("Starship V3 BB launches (internal)", Starlink!$A:$A, 0), E$5+1), 0) + IFERROR(INDEX(Starlink!$D:$AC, MATCH("Starship V3 DTC launches (internal)", Starlink!$A:$A, 0), E$5+1), 0) + IFERROR(INDEX(ODC!$D:$AC, MATCH("ODC Starship launches (internal)", ODC!$A:$A, 0), E$5+1), 0)} -> 0 | F69: {=IFERROR(INDEX(Starlink!$D:$AC, MATCH("Starship V3 BB launches (internal)", Starlink!$A:$A, 0), F$5+1), 0) + IFERROR(INDEX(Starlink!$D:$AC, MATCH("Starship V3 DTC launches (internal)", Starlink!$A:$A, 0), F$5+1), 0) + IFERROR(INDEX(ODC!$D:$AC, MATCH("ODC Starship launches (internal)", ODC!$A:$A, 0), F$5+1), 0)} -> 0 | G69: {=IFERROR(INDEX(Starlink!$D:$AC, MATCH("Starship V3 BB launches (internal)", Starlink!$A:$A, 0), G$5+1), 0) + IFERROR(INDEX(Starlink!$D:$AC, MATCH("Starship V3 DTC launches (internal)", Starlink!$A:$A, 0), G$5+1), 0) + IFERROR(INDEX(ODC!$D:$AC, MATCH("ODC Starship launches (internal)", ODC!$A:$A, 0), G$5+1), 0)} -> 0 | H69: {=IFERROR(INDEX(Starlink!$D:$AC, MATCH("Starship V3 BB launches (internal)", Starlink!$A:$A, 0), H$5+1), 0) + IFERROR(INDEX(Starlink!$D:$AC, MATCH("Starship V3 DTC launches (internal)", Starlink!$A:$A, 0), H$5+1), 0) + IFERROR(INDEX(ODC!$D:$AC, MATCH("ODC Starship launches (internal)", ODC!$A:$A, 0), H$5+1), 0)} -> 0 | I69: {=IFERROR(INDEX(Starlink!$D:$AC, MATCH("Starship V3 BB launches (internal)", Starlink!$A:$A, 0), I$5+1), 0) + IFERROR(INDEX(Starlink!$D:$AC, MATCH("Starship V3 DTC launches (internal)", Starlink!$A:$A, 0), I$5+1), 0) + IFERROR(INDEX(ODC!$D:$AC, MATCH("ODC Starship launches (internal)", ODC!$A:$A, 0), I$5+1), 0)} -> 0 | J69: {=IFERROR(INDEX(Starlink!$D:$AC, MATCH("Starship V3 BB launches (internal)", Starlink!$A:$A, 0), J$5+1), 0) + IFERROR(INDEX(Starlink!$D:$AC, MATCH("Starship V3 DTC launches (internal)", Starlink!$A:$A, 0), J$5+1), 0) + IFERROR(INDEX(ODC!$D:$AC, MATCH("ODC Starship launches (internal)", ODC!$A:$A, 0), J$5+1), 0)} -> 0 | K69: {=IFERROR(INDEX(Starlink!$D:$AC, MATCH("Starship V3 BB launches (internal)", Starlink!$A:$A, 0), K$5+1), 0) + IFERROR(INDEX(Starlink!$D:$AC, MATCH("Starship V3 DTC launches (internal)", Starlink!$A:$A, 0), K$5+1), 0) + IFERROR(INDEX(ODC!$D:$AC, MATCH("ODC Starship launches (internal)", ODC!$A:$A, 0), K$5+1), 0)} -> 0 | ... AC69: {=IFERROR(INDEX(Starlink!$D:$AC, MATCH("Starship V3 BB launches (internal)", Starlink!$A:$A, 0), AC$5+1), 0) + IFERROR(INDEX(Starlink!$D:$AC, MATCH("Starship V3 DTC launches (internal)", Starlink!$A:$A, 0), AC$5+1), 0) + IFERROR(INDEX(ODC!$D:$AC, MATCH("ODC Starship launches (internal)", ODC!$A:$A, 0), AC$5+1), 0)} -> 0
A70: Customer Launch internal transfer revenue ($mm) | D70: {=D68*D36 + D69*INDEX('Launch Capacity'!$D:$AC, MATCH("Starship at-cost rate ($mm/launch)", 'Launch Capacity'!$A:$A, 0), D$5+1)} -> 2289.75 | E70: {=E68*E36 + E69*INDEX('Launch Capacity'!$D:$AC, MATCH("Starship at-cost rate ($mm/launch)", 'Launch Capacity'!$A:$A, 0), E$5+1)} -> 0 | F70: {=F68*F36 + F69*INDEX('Launch Capacity'!$D:$AC, MATCH("Starship at-cost rate ($mm/launch)", 'Launch Capacity'!$A:$A, 0), F$5+1)} -> 0 | G70: {=G68*G36 + G69*INDEX('Launch Capacity'!$D:$AC, MATCH("Starship at-cost rate ($mm/launch)", 'Launch Capacity'!$A:$A, 0), G$5+1)} -> 0 | H70: {=H68*H36 + H69*INDEX('Launch Capacity'!$D:$AC, MATCH("Starship at-cost rate ($mm/launch)", 'Launch Capacity'!$A:$A, 0), H$5+1)} -> 0 | I70: {=I68*I36 + I69*INDEX('Launch Capacity'!$D:$AC, MATCH("Starship at-cost rate ($mm/launch)", 'Launch Capacity'!$A:$A, 0), I$5+1)} -> 0 | J70: {=J68*J36 + J69*INDEX('Launch Capacity'!$D:$AC, MATCH("Starship at-cost rate ($mm/launch)", 'Launch Capacity'!$A:$A, 0), J$5+1)} -> 0 | K70: {=K68*K36 + K69*INDEX('Launch Capacity'!$D:$AC, MATCH("Starship at-cost rate ($mm/launch)", 'Launch Capacity'!$A:$A, 0), K$5+1)} -> 0 | ... AC70: {=AC68*AC36 + AC69*INDEX('Launch Capacity'!$D:$AC, MATCH("Starship at-cost rate ($mm/launch)", 'Launch Capacity'!$A:$A, 0), AC$5+1)} -> 0
A82: ▸ Module P&L (vending-machine: Revenue → COGS → Module EBITDA → CapEx → FCF)
A83: Total Revenue ($mm) | D83: =D33+D48+D70 -> 6572.13 | E83: =E33+E48+E70 -> 4361.604 | F83: =F33+F48+F70 -> 4358.21 | G83: =G33+G48+G70 -> 4338.2492 | H83: =H33+H48+H70 -> 4288.8934 | I83: =I33+I48+I70 -> 4122.8072 | J83: =J33+J48+J70 -> 3983.9973 | K83: =K33+K48+K70 -> 4030.65 | ... AC83: =AC33+AC48+AC70 -> 4866.9493
A84: ▸ COST OF GOODS SOLD ($mm)
A85: F9 variable cost ($mm) | D85: =(D25+D68)*D34 -> 2873.997 | E85: =(E25+E68)*E34 -> 694.72935 | F85: =(F25+F68)*F34 -> 689.64817 | G85: =(G25+G68)*G34 -> 693.37158 | H85: =(H25+H68)*H34 -> 690.18012 | I85: =(I25+I68)*I34 -> 646.36191 | J85: =(J25+J68)*J34 -> 615.8965 | K85: =(K25+K68)*K34 -> 649.02357 | ... AC85: =(AC25+AC68)*AC34 -> 1378.4958
A86: F9 D&A share ($mm) | D86: =(D25+D68)*D35 -> 100.548 | E86: =(E25+E68)*E35 -> 24.3054 | F86: =(F25+F68)*F35 -> 24.127633 | G86: =(G25+G68)*G35 -> 24.257898 | H86: =(H25+H68)*H35 -> 24.146243 | I86: =(I25+I68)*I35 -> 22.613245 | J86: =(J25+J68)*J35 -> 21.547399 | K86: =(K25+K68)*K35 -> 22.706364 | ... AC86: =(AC25+AC68)*AC35 -> 48.22726
A87: Starship variable cost ($mm) | D87: {=(D24+D69)*INDEX('Launch Capacity'!$D:$AC, MATCH("Starship ops + fuel + refurb cost per launch ($mm, this year)", 'Launch Capacity'!$A:$A, 0), D$5+1)} -> 0 | E87: {=(E24+E69)*INDEX('Launch Capacity'!$D:$AC, MATCH("Starship ops + fuel + refurb cost per launch ($mm, this year)", 'Launch Capacity'!$A:$A, 0), E$5+1)} -> 0 | F87: {=(F24+F69)*INDEX('Launch Capacity'!$D:$AC, MATCH("Starship ops + fuel + refurb cost per launch ($mm, this year)", 'Launch Capacity'!$A:$A, 0), F$5+1)} -> 26.994095 | G87: {=(G24+G69)*INDEX('Launch Capacity'!$D:$AC, MATCH("Starship ops + fuel + refurb cost per launch ($mm, this year)", 'Launch Capacity'!$A:$A, 0), G$5+1)} -> 47.35935 | H87: {=(H24+H69)*INDEX('Launch Capacity'!$D:$AC, MATCH("Starship ops + fuel + refurb cost per launch ($mm, this year)", 'Launch Capacity'!$A:$A, 0), H$5+1)} -> 72.012131 | I87: {=(I24+I69)*INDEX('Launch Capacity'!$D:$AC, MATCH("Starship ops + fuel + refurb cost per launch ($mm, this year)", 'Launch Capacity'!$A:$A, 0), I$5+1)} -> 122.23534 | J87: {=(J24+J69)*INDEX('Launch Capacity'!$D:$AC, MATCH("Starship ops + fuel + refurb cost per launch ($mm, this year)", 'Launch Capacity'!$A:$A, 0), J$5+1)} -> 162.62891 | K87: {=(K24+K69)*INDEX('Launch Capacity'!$D:$AC, MATCH("Starship ops + fuel + refurb cost per launch ($mm, this year)", 'Launch Capacity'!$A:$A, 0), K$5+1)} -> 165.78925 | ... AC87: {=(AC24+AC69)*INDEX('Launch Capacity'!$D:$AC, MATCH("Starship ops + fuel + refurb cost per launch ($mm, this year)", 'Launch Capacity'!$A:$A, 0), AC$5+1)} -> 417.66563
A88: Starship D&A share ($mm) | D88: {=(D24+D69)*INDEX('Launch Capacity'!$D:$AC, MATCH("Starship D&A share per launch, fully reusable mode ($mm)", 'Launch Capacity'!$A:$A, 0), D$5+1)} -> 0 | E88: {=(E24+E69)*INDEX('Launch Capacity'!$D:$AC, MATCH("Starship D&A share per launch, fully reusable mode ($mm)", 'Launch Capacity'!$A:$A, 0), E$5+1)} -> 0 | F88: {=(F24+F69)*INDEX('Launch Capacity'!$D:$AC, MATCH("Starship D&A share per launch, fully reusable mode ($mm)", 'Launch Capacity'!$A:$A, 0), F$5+1)} -> 12.604253 | G88: {=(G24+G69)*INDEX('Launch Capacity'!$D:$AC, MATCH("Starship D&A share per launch, fully reusable mode ($mm)", 'Launch Capacity'!$A:$A, 0), G$5+1)} -> 15.961035 | H88: {=(H24+H69)*INDEX('Launch Capacity'!$D:$AC, MATCH("Starship D&A share per launch, fully reusable mode ($mm)", 'Launch Capacity'!$A:$A, 0), H$5+1)} -> 19.070062 | I88: {=(I24+I69)*INDEX('Launch Capacity'!$D:$AC, MATCH("Starship D&A share per launch, fully reusable mode ($mm)", 'Launch Capacity'!$A:$A, 0), I$5+1)} -> 28.545012 | J88: {=(J24+J69)*INDEX('Launch Capacity'!$D:$AC, MATCH("Starship D&A share per launch, fully reusable mode ($mm)", 'Launch Capacity'!$A:$A, 0), J$5+1)} -> 34.216664 | K88: {=(K24+K69)*INDEX('Launch Capacity'!$D:$AC, MATCH("Starship D&A share per launch, fully reusable mode ($mm)", 'Launch Capacity'!$A:$A, 0), K$5+1)} -> 31.248148 | ... AC88: {=(AC24+AC69)*INDEX('Launch Capacity'!$D:$AC, MATCH("Starship D&A share per launch, fully reusable mode ($mm)", 'Launch Capacity'!$A:$A, 0), AC$5+1)} -> 49.612931
A89: Customer Launch ground ops ($mm) | D89: =D83 * IFERROR(INDEX(Assumptions!$B:$B, MATCH("Customer Launch ground ops % of revenue", Assumptions!$A:$A, 0)), 0.01) -> 65.7213 | E89: =E83 * IFERROR(INDEX(Assumptions!$B:$B, MATCH("Customer Launch ground ops % of revenue", Assumptions!$A:$A, 0)), 0.01) -> 43.61604 | F89: =F83 * IFERROR(INDEX(Assumptions!$B:$B, MATCH("Customer Launch ground ops % of revenue", Assumptions!$A:$A, 0)), 0.01) -> 43.5821 | G89: =G83 * IFERROR(INDEX(Assumptions!$B:$B, MATCH("Customer Launch ground ops % of revenue", Assumptions!$A:$A, 0)), 0.01) -> 43.382492 | H89: =H83 * IFERROR(INDEX(Assumptions!$B:$B, MATCH("Customer Launch ground ops % of revenue", Assumptions!$A:$A, 0)), 0.01) -> 42.888934 | I89: =I83 * IFERROR(INDEX(Assumptions!$B:$B, MATCH("Customer Launch ground ops % of revenue", Assumptions!$A:$A, 0)), 0.01) -> 41.228072 | J89: =J83 * IFERROR(INDEX(Assumptions!$B:$B, MATCH("Customer Launch ground ops % of revenue", Assumptions!$A:$A, 0)), 0.01) -> 39.839973 | K89: =K83 * IFERROR(INDEX(Assumptions!$B:$B, MATCH("Customer Launch ground ops % of revenue", Assumptions!$A:$A, 0)), 0.01) -> 40.3065 | ... AC89: =AC83 * IFERROR(INDEX(Assumptions!$B:$B, MATCH("Customer Launch ground ops % of revenue", Assumptions!$A:$A, 0)), 0.01) -> 48.669493
A90: Customer Launch insurance ($mm) | D90: =D83 * IFERROR(INDEX(Assumptions!$B:$B, MATCH("Launch insurance % of external revenue", Assumptions!$A:$A, 0)), 0.01) -> 328.6065 | E90: =E83 * IFERROR(INDEX(Assumptions!$B:$B, MATCH("Launch insurance % of external revenue", Assumptions!$A:$A, 0)), 0.01) -> 218.0802 | F90: =F83 * IFERROR(INDEX(Assumptions!$B:$B, MATCH("Launch insurance % of external revenue", Assumptions!$A:$A, 0)), 0.01) -> 217.9105 | G90: =G83 * IFERROR(INDEX(Assumptions!$B:$B, MATCH("Launch insurance % of external revenue", Assumptions!$A:$A, 0)), 0.01) -> 216.91246 | H90: =H83 * IFERROR(INDEX(Assumptions!$B:$B, MATCH("Launch insurance % of external revenue", Assumptions!$A:$A, 0)), 0.01) -> 214.44467 | I90: =I83 * IFERROR(INDEX(Assumptions!$B:$B, MATCH("Launch insurance % of external revenue", Assumptions!$A:$A, 0)), 0.01) -> 206.14036 | J90: =J83 * IFERROR(INDEX(Assumptions!$B:$B, MATCH("Launch insurance % of external revenue", Assumptions!$A:$A, 0)), 0.01) -> 199.19987 | K90: =K83 * IFERROR(INDEX(Assumptions!$B:$B, MATCH("Launch insurance % of external revenue", Assumptions!$A:$A, 0)), 0.01) -> 201.5325 | ... AC90: =AC83 * IFERROR(INDEX(Assumptions!$B:$B, MATCH("Launch insurance % of external revenue", Assumptions!$A:$A, 0)), 0.01) -> 243.34747
A91: Customer Launch other COGS ($mm) | D91: =D83 * IFERROR(INDEX(Assumptions!$B:$B, MATCH("Launch other COGS % of external revenue", Assumptions!$A:$A, 0)), 0.01) -> 131.4426 | E91: =E83 * IFERROR(INDEX(Assumptions!$B:$B, MATCH("Launch other COGS % of external revenue", Assumptions!$A:$A, 0)), 0.01) -> 87.232081 | F91: =F83 * IFERROR(INDEX(Assumptions!$B:$B, MATCH("Launch other COGS % of external revenue", Assumptions!$A:$A, 0)), 0.01) -> 87.1642 | G91: =G83 * IFERROR(INDEX(Assumptions!$B:$B, MATCH("Launch other COGS % of external revenue", Assumptions!$A:$A, 0)), 0.01) -> 86.764985 | H91: =H83 * IFERROR(INDEX(Assumptions!$B:$B, MATCH("Launch other COGS % of external revenue", Assumptions!$A:$A, 0)), 0.01) -> 85.777867 | I91: =I83 * IFERROR(INDEX(Assumptions!$B:$B, MATCH("Launch other COGS % of external revenue", Assumptions!$A:$A, 0)), 0.01) -> 82.456145 | J91: =J83 * IFERROR(INDEX(Assumptions!$B:$B, MATCH("Launch other COGS % of external revenue", Assumptions!$A:$A, 0)), 0.01) -> 79.679947 | K91: =K83 * IFERROR(INDEX(Assumptions!$B:$B, MATCH("Launch other COGS % of external revenue", Assumptions!$A:$A, 0)), 0.01) -> 80.613 | ... AC91: =AC83 * IFERROR(INDEX(Assumptions!$B:$B, MATCH("Launch other COGS % of external revenue", Assumptions!$A:$A, 0)), 0.01) -> 97.338986
A93: Total COGS ($mm) | D93: =SUM(D85:D92) -> 3500.3154 | E93: =SUM(E85:E92) -> 1067.9631 | F93: =SUM(F85:F92) -> 1102.031 | G93: =SUM(G85:G92) -> 1128.0098 | H93: =SUM(H85:H92) -> 1148.52 | I93: =SUM(I85:I92) -> 1149.5801 | J93: =SUM(J85:J92) -> 1153.0093 | K93: =SUM(K85:K92) -> 1191.2193 | ... AC93: =SUM(AC85:AC92) -> 2283.3576
A94: Gross Profit ($mm) | D94: =D83-D93 -> 3071.8146 | E94: =E83-E93 -> 3293.641 | F94: =F83-F93 -> 3256.1791 | G94: =G83-G93 -> 3210.2394 | H94: =H83-H93 -> 3140.3733 | I94: =I83-I93 -> 2973.2271 | J94: =J83-J93 -> 2830.9881 | K94: =K83-K93 -> 2839.4306 | ... AC94: =AC83-AC93 -> 2583.5917
A95: Module EBITDA ($mm) | D95: =D94 -> 3071.8146 | E95: =E94 -> 3293.641 | F95: =F94 -> 3256.1791 | G95: =G94 -> 3210.2394 | H95: =H94 -> 3140.3733 | I95: =I94 -> 2973.2271 | J95: =J94 -> 2830.9881 | K95: =K94 -> 2839.4306 | ... AC95: =AC94 -> 2583.5917
A96: Module EBITDA Margin % | D96: =IFERROR(D95/D83, 0) -> 0.46740016 | E96: =IFERROR(E95/E83, 0) -> 0.75514442 | F96: =IFERROR(F95/F83, 0) -> 0.74713679 | G96: =IFERROR(G95/G83, 0) -> 0.73998502 | H96: =IFERROR(H95/H83, 0) -> 0.73221064 | I96: =IFERROR(I95/I83, 0) -> 0.72116569 | J96: =IFERROR(J95/J83, 0) -> 0.71058985 | K96: =IFERROR(K95/K83, 0) -> 0.70445974 | ... AC96: =IFERROR(AC95/AC83, 0) -> 0.53084418
A98: ▸ CAPEX + FCF
A99: Module CapEx ($mm) | D99: =D83 * IFERROR(INDEX(Assumptions!$B:$B, MATCH("Customer Launch ground equipment CapEx % of revenue", Assumptions!$A:$A, 0)), 0.005) -> 32.86065 | E99: =E83 * IFERROR(INDEX(Assumptions!$B:$B, MATCH("Customer Launch ground equipment CapEx % of revenue", Assumptions!$A:$A, 0)), 0.005) -> 21.80802 | F99: =F83 * IFERROR(INDEX(Assumptions!$B:$B, MATCH("Customer Launch ground equipment CapEx % of revenue", Assumptions!$A:$A, 0)), 0.005) -> 21.79105 | G99: =G83 * IFERROR(INDEX(Assumptions!$B:$B, MATCH("Customer Launch ground equipment CapEx % of revenue", Assumptions!$A:$A, 0)), 0.005) -> 21.691246 | H99: =H83 * IFERROR(INDEX(Assumptions!$B:$B, MATCH("Customer Launch ground equipment CapEx % of revenue", Assumptions!$A:$A, 0)), 0.005) -> 21.444467 | I99: =I83 * IFERROR(INDEX(Assumptions!$B:$B, MATCH("Customer Launch ground equipment CapEx % of revenue", Assumptions!$A:$A, 0)), 0.005) -> 20.614036 | J99: =J83 * IFERROR(INDEX(Assumptions!$B:$B, MATCH("Customer Launch ground equipment CapEx % of revenue", Assumptions!$A:$A, 0)), 0.005) -> 19.919987 | K99: =K83 * IFERROR(INDEX(Assumptions!$B:$B, MATCH("Customer Launch ground equipment CapEx % of revenue", Assumptions!$A:$A, 0)), 0.005) -> 20.15325 | ... AC99: =AC83 * IFERROR(INDEX(Assumptions!$B:$B, MATCH("Customer Launch ground equipment CapEx % of revenue", Assumptions!$A:$A, 0)), 0.005) -> 24.334747
A100: Module D&A ($mm) — informational (also in COGS rows 86 + 88) | D100: =D86+D88 -> 100.548 | E100: =E86+E88 -> 24.3054 | F100: =F86+F88 -> 36.731886 | G100: =G86+G88 -> 40.218932 | H100: =H86+H88 -> 43.216306 | I100: =I86+I88 -> 51.158257 | J100: =J86+J88 -> 55.764063 | K100: =K86+K88 -> 53.954512 | ... AC100: =AC86+AC88 -> 97.840191
A101: Module FCF ($mm) | D101: =D95+D100-D99 -> 3139.502 | E101: =E95+E100-E99 -> 3296.1383 | F101: =F95+F100-F99 -> 3271.1199 | G101: =G95+G100-G99 -> 3228.7671 | H101: =H95+H100-H99 -> 3162.1452 | I101: =I95+I100-I99 -> 3003.7714 | J101: =J95+J100-J99 -> 2866.8322 | K101: =K95+K100-K99 -> 2873.2319 | ... AC101: =AC95+AC100-AC99 -> 2657.0971
A102: Capital deployed ($mm) | D102: =D99 -> 32.86065 | E102: =E99 -> 21.80802 | F102: =F99 -> 21.79105 | G102: =G99 -> 21.691246 | H102: =H99 -> 21.444467 | I102: =I99 -> 20.614036 | J102: =J99 -> 19.919987 | K102: =K99 -> 20.15325 | ... AC102: =AC99 -> 24.334747
A117: ▸ Per-launch marginal IRR engines (F9 + Starship, external customer only)
A118: F9 lifetime reuses per booster — read from Assumptions | D118: =INDEX(Assumptions!$B:$B, MATCH("F9 lifetime reuses per booster", Assumptions!$A:$A, 0)) -> 50
A119: F9 IRR cashflow stream period count N (clamped at R23 MAX) | D119: =MIN(INDEX(Assumptions!$B:$B, MATCH("MFW-IRR — Customer Launch economic life clamp MAX (years)", Assumptions!$A:$A, 0)), D118) -> 10
A120: Starship lifetime reuses per booster — year-row from Launch Capacity R21 | D120: {=INDEX('Launch Capacity'!$D:$AC, MATCH("Lifetime reuses per booster (year cap)", 'Launch Capacity'!$A:$A, 0), D$5+1)} -> 5 | E120: {=INDEX('Launch Capacity'!$D:$AC, MATCH("Lifetime reuses per booster (year cap)", 'Launch Capacity'!$A:$A, 0), E$5+1)} -> 8 | F120: {=INDEX('Launch Capacity'!$D:$AC, MATCH("Lifetime reuses per booster (year cap)", 'Launch Capacity'!$A:$A, 0), F$5+1)} -> 12 | G120: {=INDEX('Launch Capacity'!$D:$AC, MATCH("Lifetime reuses per booster (year cap)", 'Launch Capacity'!$A:$A, 0), G$5+1)} -> 18 | H120: {=INDEX('Launch Capacity'!$D:$AC, MATCH("Lifetime reuses per booster (year cap)", 'Launch Capacity'!$A:$A, 0), H$5+1)} -> 25 | I120: {=INDEX('Launch Capacity'!$D:$AC, MATCH("Lifetime reuses per booster (year cap)", 'Launch Capacity'!$A:$A, 0), I$5+1)} -> 30 | J120: {=INDEX('Launch Capacity'!$D:$AC, MATCH("Lifetime reuses per booster (year cap)", 'Launch Capacity'!$A:$A, 0), J$5+1)} -> 35 | K120: {=INDEX('Launch Capacity'!$D:$AC, MATCH("Lifetime reuses per booster (year cap)", 'Launch Capacity'!$A:$A, 0), K$5+1)} -> 42 | ... AC120: {=INDEX('Launch Capacity'!$D:$AC, MATCH("Lifetime reuses per booster (year cap)", 'Launch Capacity'!$A:$A, 0), AC$5+1)} -> 100
A121: Starship IRR cashflow stream period count N (clamped at R23 MAX, year-row) | D121: =MIN(INDEX(Assumptions!$B:$B, MATCH("MFW-IRR — Customer Launch economic life clamp MAX (years)", Assumptions!$A:$A, 0)), D120) -> 5 | E121: =MIN(INDEX(Assumptions!$B:$B, MATCH("MFW-IRR — Customer Launch economic life clamp MAX (years)", Assumptions!$A:$A, 0)), E120) -> 8 | F121: =MIN(INDEX(Assumptions!$B:$B, MATCH("MFW-IRR — Customer Launch economic life clamp MAX (years)", Assumptions!$A:$A, 0)), F120) -> 10 | G121: =MIN(INDEX(Assumptions!$B:$B, MATCH("MFW-IRR — Customer Launch economic life clamp MAX (years)", Assumptions!$A:$A, 0)), G120) -> 10 | H121: =MIN(INDEX(Assumptions!$B:$B, MATCH("MFW-IRR — Customer Launch economic life clamp MAX (years)", Assumptions!$A:$A, 0)), H120) -> 10 | I121: =MIN(INDEX(Assumptions!$B:$B, MATCH("MFW-IRR — Customer Launch economic life clamp MAX (years)", Assumptions!$A:$A, 0)), I120) -> 10 | J121: =MIN(INDEX(Assumptions!$B:$B, MATCH("MFW-IRR — Customer Launch economic life clamp MAX (years)", Assumptions!$A:$A, 0)), J120) -> 10 | K121: =MIN(INDEX(Assumptions!$B:$B, MATCH("MFW-IRR — Customer Launch economic life clamp MAX (years)", Assumptions!$A:$A, 0)), K120) -> 10 | ... AC121: =MIN(INDEX(Assumptions!$B:$B, MATCH("MFW-IRR — Customer Launch economic life clamp MAX (years)", Assumptions!$A:$A, 0)), AC120) -> 10
A130: F9 per-launch cost slug ($mm — t=0 capex) | D130: =INDEX(Assumptions!$B:$B, MATCH("F9 booster (1st stage) mfg cost ($mm/unit)", Assumptions!$A:$A, 0)) -> 30
A131: F9 per-launch annual margin ($mm/yr — cadence × per-launch margin) | D131: =D17-D34-D37 -> 86.08 | E131: =E17-E34-E37 -> 82.9831 | F131: =F17-F34-F37 -> 79.9792 | G131: =G17-G34-G37 -> 77.059 | H131: =H17-H34-H37 -> 74.2318 | I131: =I17-I34-I37 -> 71.4883 | J131: =J17-J34-J37 -> 68.8285 | K131: =K17-K34-K37 -> 66.2524 | ... AC131: =AC17-AC34-AC37 -> 31.0519
A132: F9 Spot IRR (per-launch marginal IRR, current year — external customer economics) | D132: {=IFERROR(IRR(IF(_xlfn.SEQUENCE(1, $D$119+1)=1, -$D$130, D131)), -1)} -> 2.8693295 | E132: {=IFERROR(IRR(IF(_xlfn.SEQUENCE(1, $D$119+1)=1, -$D$130, E131)), -1)} -> 2.7660985 | F132: {=IFERROR(IRR(IF(_xlfn.SEQUENCE(1, $D$119+1)=1, -$D$130, F131)), -1)} -> 2.6659673 | G132: {=IFERROR(IRR(IF(_xlfn.SEQUENCE(1, $D$119+1)=1, -$D$130, G131)), -1)} -> 2.5686257 | H132: {=IFERROR(IRR(IF(_xlfn.SEQUENCE(1, $D$119+1)=1, -$D$130, H131)), -1)} -> 2.4743837 | I132: {=IFERROR(IRR(IF(_xlfn.SEQUENCE(1, $D$119+1)=1, -$D$130, I131)), -1)} -> 2.3829312 | J132: {=IFERROR(IRR(IF(_xlfn.SEQUENCE(1, $D$119+1)=1, -$D$130, J131)), -1)} -> 2.2942681 | K132: {=IFERROR(IRR(IF(_xlfn.SEQUENCE(1, $D$119+1)=1, -$D$130, K131)), -1)} -> 2.2083942 | ... AC132: {=IFERROR(IRR(IF(_xlfn.SEQUENCE(1, $D$119+1)=1, -$D$130, AC131)), -1)} -> 1.0342102
A133: F9 Forward IRR (Y+2) — per-launch marginal IRR, year T+2 cashflow | D133: {=IFERROR(IRR(IF(_xlfn.SEQUENCE(1, $D$119+1)=1, -$D$130, F131)), -1)} -> 2.6659673 | E133: {=IFERROR(IRR(IF(_xlfn.SEQUENCE(1, $D$119+1)=1, -$D$130, G131)), -1)} -> 2.5686257 | F133: {=IFERROR(IRR(IF(_xlfn.SEQUENCE(1, $D$119+1)=1, -$D$130, H131)), -1)} -> 2.4743837 | G133: {=IFERROR(IRR(IF(_xlfn.SEQUENCE(1, $D$119+1)=1, -$D$130, I131)), -1)} -> 2.3829312 | H133: {=IFERROR(IRR(IF(_xlfn.SEQUENCE(1, $D$119+1)=1, -$D$130, J131)), -1)} -> 2.2942681 | I133: {=IFERROR(IRR(IF(_xlfn.SEQUENCE(1, $D$119+1)=1, -$D$130, K131)), -1)} -> 2.2083942 | J133: {=IFERROR(IRR(IF(_xlfn.SEQUENCE(1, $D$119+1)=1, -$D$130, L131)), -1)} -> 2.1253094 | K133: {=IFERROR(IRR(IF(_xlfn.SEQUENCE(1, $D$119+1)=1, -$D$130, M131)), -1)} -> 2.0443934 | ... AC133: {=IFERROR(IRR(IF(_xlfn.SEQUENCE(1, $D$119+1)=1, -$D$130, AE131)), -1)} -> -1
A134: F9 per-launch Blended IRR (external customer economics) | D134: =(1 - INDEX(Assumptions!$B:$B, MATCH("Forward IRR weight w (Blended = (1-w)·Spot + w·Forward)", Assumptions!$A:$A, 0))) * D132 + INDEX(Assumptions!$B:$B, MATCH("Forward IRR weight w (Blended = (1-w)·Spot + w·Forward)", Assumptions!$A:$A, 0)) * D133 -> 2.7269759 | E134: =(1 - INDEX(Assumptions!$B:$B, MATCH("Forward IRR weight w (Blended = (1-w)·Spot + w·Forward)", Assumptions!$A:$A, 0))) * E132 + INDEX(Assumptions!$B:$B, MATCH("Forward IRR weight w (Blended = (1-w)·Spot + w·Forward)", Assumptions!$A:$A, 0)) * E133 -> 2.6278675 | F134: =(1 - INDEX(Assumptions!$B:$B, MATCH("Forward IRR weight w (Blended = (1-w)·Spot + w·Forward)", Assumptions!$A:$A, 0))) * F132 + INDEX(Assumptions!$B:$B, MATCH("Forward IRR weight w (Blended = (1-w)·Spot + w·Forward)", Assumptions!$A:$A, 0)) * F133 -> 2.5318588 | G134: =(1 - INDEX(Assumptions!$B:$B, MATCH("Forward IRR weight w (Blended = (1-w)·Spot + w·Forward)", Assumptions!$A:$A, 0))) * G132 + INDEX(Assumptions!$B:$B, MATCH("Forward IRR weight w (Blended = (1-w)·Spot + w·Forward)", Assumptions!$A:$A, 0)) * G133 -> 2.4386395 | H134: =(1 - INDEX(Assumptions!$B:$B, MATCH("Forward IRR weight w (Blended = (1-w)·Spot + w·Forward)", Assumptions!$A:$A, 0))) * H132 + INDEX(Assumptions!$B:$B, MATCH("Forward IRR weight w (Blended = (1-w)·Spot + w·Forward)", Assumptions!$A:$A, 0)) * H133 -> 2.3483028 | I134: =(1 - INDEX(Assumptions!$B:$B, MATCH("Forward IRR weight w (Blended = (1-w)·Spot + w·Forward)", Assumptions!$A:$A, 0))) * I132 + INDEX(Assumptions!$B:$B, MATCH("Forward IRR weight w (Blended = (1-w)·Spot + w·Forward)", Assumptions!$A:$A, 0)) * I133 -> 2.2607553 | J134: =(1 - INDEX(Assumptions!$B:$B, MATCH("Forward IRR weight w (Blended = (1-w)·Spot + w·Forward)", Assumptions!$A:$A, 0))) * J132 + INDEX(Assumptions!$B:$B, MATCH("Forward IRR weight w (Blended = (1-w)·Spot + w·Forward)", Assumptions!$A:$A, 0)) * J133 -> 2.175997 | K134: =(1 - INDEX(Assumptions!$B:$B, MATCH("Forward IRR weight w (Blended = (1-w)·Spot + w·Forward)", Assumptions!$A:$A, 0))) * K132 + INDEX(Assumptions!$B:$B, MATCH("Forward IRR weight w (Blended = (1-w)·Spot + w·Forward)", Assumptions!$A:$A, 0)) * K133 -> 2.0935937 | ... AC134: =(1 - INDEX(Assumptions!$B:$B, MATCH("Forward IRR weight w (Blended = (1-w)·Spot + w·Forward)", Assumptions!$A:$A, 0))) * AC132 + INDEX(Assumptions!$B:$B, MATCH("Forward IRR weight w (Blended = (1-w)·Spot + w·Forward)", Assumptions!$A:$A, 0)) * AC133 -> -0.38973694
A140: Starship per-launch cost slug ($mm — year-row of manufacturing cost from Launch Capacity R37) | D140: {=INDEX('Launch Capacity'!$D:$AC, MATCH("Starship manufacturing cost ($mm/stack, this year)", 'Launch Capacity'!$A:$A, 0), D$5+1)} -> 90 | E140: {=INDEX('Launch Capacity'!$D:$AC, MATCH("Starship manufacturing cost ($mm/stack, this year)", 'Launch Capacity'!$A:$A, 0), E$5+1)} -> 89.991489 | F140: {=INDEX('Launch Capacity'!$D:$AC, MATCH("Starship manufacturing cost ($mm/stack, this year)", 'Launch Capacity'!$A:$A, 0), F$5+1)} -> 85.71825 | G140: {=INDEX('Launch Capacity'!$D:$AC, MATCH("Starship manufacturing cost ($mm/stack, this year)", 'Launch Capacity'!$A:$A, 0), G$5+1)} -> 80.830645 | H140: {=INDEX('Launch Capacity'!$D:$AC, MATCH("Starship manufacturing cost ($mm/stack, this year)", 'Launch Capacity'!$A:$A, 0), H$5+1)} -> 76.807131 | I140: {=INDEX('Launch Capacity'!$D:$AC, MATCH("Starship manufacturing cost ($mm/stack, this year)", 'Launch Capacity'!$A:$A, 0), I$5+1)} -> 74.141596 | J140: {=INDEX('Launch Capacity'!$D:$AC, MATCH("Starship manufacturing cost ($mm/stack, this year)", 'Launch Capacity'!$A:$A, 0), J$5+1)} -> 71.11063 | K140: {=INDEX('Launch Capacity'!$D:$AC, MATCH("Starship manufacturing cost ($mm/stack, this year)", 'Launch Capacity'!$A:$A, 0), K$5+1)} -> 68.811511 | ... AC140: {=INDEX('Launch Capacity'!$D:$AC, MATCH("Starship manufacturing cost ($mm/stack, this year)", 'Launch Capacity'!$A:$A, 0), AC$5+1)} -> 51.051305
